Workbook
Name VAL_DATE: Curve_Interface!$O$5

Sheet Entities
A1: Entities
A2: Type a name and its Bloomberg ticker on any free row. On = 0 removes a name. Overrides beat the BDP pull; blank uses the pull.
A4: Live name | B4: DEMO curve (not market) | C4: only this name is stripped and priced | E4: ticker in use | F4: =IFERROR(IF(ISTEXT(INDEX($C$7:$C$16,MATCH($B$4,$B$7:$B$16,0))),INDEX($C$7:$C$16,MATCH($B$4,$B$7:$B$16,0)),""),"")
A6: On | B6: Entity name | C6: Bloomberg ticker | D6: Ccy | E6: Recovery | F6: 1Y | G6: 2Y | H6: 3Y | I6: 5Y | J6: 7Y | K6: 10Y
A7: 1 | B7: China CITIC Bank Intl | D7: USD
A8: 1 | B8: DEMO curve (not market) | D8: USD
A19: Effective (what the strip uses) | F19: override > BDP pull > manual > 0. This block is what the strip uses.
B20: Entity | E20: Recovery | F20: 1Y | G20: 2Y | H20: 3Y | I20: 5Y | J20: 7Y | K20: 10Y
B21: =IF($B7="","",$B7) | E21: =IF($B7="","",IF($A7=0,"off",IF(ISNUMBER($E7),$E7,CDS_Entities!$F$5))) | F21: =IF($B7="","",IF($A7=0,0,IF(ISNUMBER($F7),$F7,IF(ISNUMBER(CDS_Entities!$AG$5),CDS_Entities!$AG$5,IF(ISNUMBER(CDS_Entities!$H$5),CDS_Entities!$H$5,0))))) | G21: =IF($B7="","",IF($A7=0,0,IF(ISNUMBER($G7),$G7,IF(ISNUMBER(CDS_Entities!$AI$5),CDS_Entities!$AI$5,IF(ISNUMBER(CDS_Entities!$I$5),CDS_Entities!$I$5,0))))) | H21: =IF($B7="","",IF($A7=0,0,IF(ISNUMBER($H7),$H7,IF(ISNUMBER(CDS_Entities!$AK$5),CDS_Entities!$AK$5,IF(ISNUMBER(CDS_Entities!$J$5),CDS_Entities!$J$5,0))))) | I21: =IF($B7="","",IF($A7=0,0,IF(ISNUMBER($I7),$I7,IF(ISNUMBER(CDS_Entities!$AM$5),CDS_Entities!$AM$5,IF(ISNUMBER(CDS_Entities!$K$5),CDS_Entities!$K$5,0))))) | J21: =IF($B7="","",IF($A7=0,0,IF(ISNUMBER($J7),$J7,IF(ISNUMBER(CDS_Entities!$AO$5),CDS_Entities!$AO$5,IF(ISNUMBER(CDS_Entities!$L$5),CDS_Entities!$L$5,0))))) | K21: =IF($B7="","",IF($A7=0,0,IF(ISNUMBER($K7),$K7,IF(ISNUMBER(CDS_Entities!$AQ$5),CDS_Entities!$AQ$5,IF(ISNUMBER(CDS_Entities!$M$5),CDS_Entities!$M$5,0)))))
B22: =IF($B8="","",$B8) | E22: =IF($B8="","",IF($A8=0,"off",IF(ISNUMBER($E8),$E8,CDS_Entities!$F$6))) | F22: =IF($B8="","",IF($A8=0,0,IF(ISNUMBER($F8),$F8,IF(ISNUMBER(CDS_Entities!$AG$6),CDS_Entities!$AG$6,IF(ISNUMBER(CDS_Entities!$H$6),CDS_Entities!$H$6,0))))) | G22: =IF($B8="","",IF($A8=0,0,IF(ISNUMBER($G8),$G8,IF(ISNUMBER(CDS_Entities!$AI$6),CDS_Entities!$AI$6,IF(ISNUMBER(CDS_Entities!$I$6),CDS_Entities!$I$6,0))))) | H22: =IF($B8="","",IF($A8=0,0,IF(ISNUMBER($H8),$H8,IF(ISNUMBER(CDS_Entities!$AK$6),CDS_Entities!$AK$6,IF(ISNUMBER(CDS_Entities!$J$6),CDS_Entities!$J$6,0))))) | I22: =IF($B8="","",IF($A8=0,0,IF(ISNUMBER($I8),$I8,IF(ISNUMBER(CDS_Entities!$AM$6),CDS_Entities!$AM$6,IF(ISNUMBER(CDS_Entities!$K$6),CDS_Entities!$K$6,0))))) | J22: =IF($B8="","",IF($A8=0,0,IF(ISNUMBER($J8),$J8,IF(ISNUMBER(CDS_Entities!$AO$6),CDS_Entities!$AO$6,IF(ISNUMBER(CDS_Entities!$L$6),CDS_Entities!$L$6,0))))) | K22: =IF($B8="","",IF($A8=0,0,IF(ISNUMBER($K8),$K8,IF(ISNUMBER(CDS_Entities!$AQ$6),CDS_Entities!$AQ$6,IF(ISNUMBER(CDS_Entities!$M$6),CDS_Entities!$M$6,0)))))
B23: =IF($B9="","",$B9) | E23: =IF($B9="","",IF($A9=0,"off",IF(ISNUMBER($E9),$E9,CDS_Entities!$F$7))) | F23: =IF($B9="","",IF($A9=0,0,IF(ISNUMBER($F9),$F9,IF(ISNUMBER(CDS_Entities!$AG$7),CDS_Entities!$AG$7,IF(ISNUMBER(CDS_Entities!$H$7),CDS_Entities!$H$7,0))))) | G23: =IF($B9="","",IF($A9=0,0,IF(ISNUMBER($G9),$G9,IF(ISNUMBER(CDS_Entities!$AI$7),CDS_Entities!$AI$7,IF(ISNUMBER(CDS_Entities!$I$7),CDS_Entities!$I$7,0))))) | H23: =IF($B9="","",IF($A9=0,0,IF(ISNUMBER($H9),$H9,IF(ISNUMBER(CDS_Entities!$AK$7),CDS_Entities!$AK$7,IF(ISNUMBER(CDS_Entities!$J$7),CDS_Entities!$J$7,0))))) | I23: =IF($B9="","",IF($A9=0,0,IF(ISNUMBER($I9),$I9,IF(ISNUMBER(CDS_Entities!$AM$7),CDS_Entities!$AM$7,IF(ISNUMBER(CDS_Entities!$K$7),CDS_Entities!$K$7,0))))) | J23: =IF($B9="","",IF($A9=0,0,IF(ISNUMBER($J9),$J9,IF(ISNUMBER(CDS_Entities!$AO$7),CDS_Entities!$AO$7,IF(ISNUMBER(CDS_Entities!$L$7),CDS_Entities!$L$7,0))))) | K23: =IF($B9="","",IF($A9=0,0,IF(ISNUMBER($K9),$K9,IF(ISNUMBER(CDS_Entities!$AQ$7),CDS_Entities!$AQ$7,IF(ISNUMBER(CDS_Entities!$M$7),CDS_Entities!$M$7,0)))))
B24: =IF($B10="","",$B10) | E24: =IF($B10="","",IF($A10=0,"off",IF(ISNUMBER($E10),$E10,CDS_Entities!$F$8))) | F24: =IF($B10="","",IF($A10=0,0,IF(ISNUMBER($F10),$F10,IF(ISNUMBER(CDS_Entities!$AG$8),CDS_Entities!$AG$8,IF(ISNUMBER(CDS_Entities!$H$8),CDS_Entities!$H$8,0))))) | G24: =IF($B10="","",IF($A10=0,0,IF(ISNUMBER($G10),$G10,IF(ISNUMBER(CDS_Entities!$AI$8),CDS_Entities!$AI$8,IF(ISNUMBER(CDS_Entities!$I$8),CDS_Entities!$I$8,0))))) | H24: =IF($B10="","",IF($A10=0,0,IF(ISNUMBER($H10),$H10,IF(ISNUMBER(CDS_Entities!$AK$8),CDS_Entities!$AK$8,IF(ISNUMBER(CDS_Entities!$J$8),CDS_Entities!$J$8,0))))) | I24: =IF($B10="","",IF($A10=0,0,IF(ISNUMBER($I10),$I10,IF(ISNUMBER(CDS_Entities!$AM$8),CDS_Entities!$AM$8,IF(ISNUMBER(CDS_Entities!$K$8),CDS_Entities!$K$8,0))))) | J24: =IF($B10="","",IF($A10=0,0,IF(ISNUMBER($J10),$J10,IF(ISNUMBER(CDS_Entities!$AO$8),CDS_Entities!$AO$8,IF(ISNUMBER(CDS_Entities!$L$8),CDS_Entities!$L$8,0))))) | K24: =IF($B10="","",IF($A10=0,0,IF(ISNUMBER($K10),$K10,IF(ISNUMBER(CDS_Entities!$AQ$8),CDS_Entities!$AQ$8,IF(ISNUMBER(CDS_Entities!$M$8),CDS_Entities!$M$8,0)))))
B25: =IF($B11="","",$B11) | E25: =IF($B11="","",IF($A11=0,"off",IF(ISNUMBER($E11),$E11,CDS_Entities!$F$9))) | F25: =IF($B11="","",IF($A11=0,0,IF(ISNUMBER($F11),$F11,IF(ISNUMBER(CDS_Entities!$AG$9),CDS_Entities!$AG$9,IF(ISNUMBER(CDS_Entities!$H$9),CDS_Entities!$H$9,0))))) | G25: =IF($B11="","",IF($A11=0,0,IF(ISNUMBER($G11),$G11,IF(ISNUMBER(CDS_Entities!$AI$9),CDS_Entities!$AI$9,IF(ISNUMBER(CDS_Entities!$I$9),CDS_Entities!$I$9,0))))) | H25: =IF($B11="","",IF($A11=0,0,IF(ISNUMBER($H11),$H11,IF(ISNUMBER(CDS_Entities!$AK$9),CDS_Entities!$AK$9,IF(ISNUMBER(CDS_Entities!$J$9),CDS_Entities!$J$9,0))))) | I25: =IF($B11="","",IF($A11=0,0,IF(ISNUMBER($I11),$I11,IF(ISNUMBER(CDS_Entities!$AM$9),CDS_Entities!$AM$9,IF(ISNUMBER(CDS_Entities!$K$9),CDS_Entities!$K$9,0))))) | J25: =IF($B11="","",IF($A11=0,0,IF(ISNUMBER($J11),$J11,IF(ISNUMBER(CDS_Entities!$AO$9),CDS_Entities!$AO$9,IF(ISNUMBER(CDS_Entities!$L$9),CDS_Entities!$L$9,0))))) | K25: =IF($B11="","",IF($A11=0,0,IF(ISNUMBER($K11),$K11,IF(ISNUMBER(CDS_Entities!$AQ$9),CDS_Entities!$AQ$9,IF(ISNUMBER(CDS_Entities!$M$9),CDS_Entities!$M$9,0)))))
B26: =IF($B12="","",$B12) | E26: =IF($B12="","",IF($A12=0,"off",IF(ISNUMBER($E12),$E12,CDS_Entities!$F$10))) | F26: =IF($B12="","",IF($A12=0,0,IF(ISNUMBER($F12),$F12,IF(ISNUMBER(CDS_Entities!$AG$10),CDS_Entities!$AG$10,IF(ISNUMBER(CDS_Entities!$H$10),CDS_Entities!$H$10,0))))) | G26: =IF($B12="","",IF($A12=0,0,IF(ISNUMBER($G12),$G12,IF(ISNUMBER(CDS_Entities!$AI$10),CDS_Entities!$AI$10,IF(ISNUMBER(CDS_Entities!$I$10),CDS_Entities!$I$10,0))))) | H26: =IF($B12="","",IF($A12=0,0,IF(ISNUMBER($H12),$H12,IF(ISNUMBER(CDS_Entities!$AK$10),CDS_Entities!$AK$10,IF(ISNUMBER(CDS_Entities!$J$10),CDS_Entities!$J$10,0))))) | I26: =IF($B12="","",IF($A12=0,0,IF(ISNUMBER($I12),$I12,IF(ISNUMBER(CDS_Entities!$AM$10),CDS_Entities!$AM$10,IF(ISNUMBER(CDS_Entities!$K$10),CDS_Entities!$K$10,0))))) | J26: =IF($B12="","",IF($A12=0,0,IF(ISNUMBER($J12),$J12,IF(ISNUMBER(CDS_Entities!$AO$10),CDS_Entities!$AO$10,IF(ISNUMBER(CDS_Entities!$L$10),CDS_Entities!$L$10,0))))) | K26: =IF($B12="","",IF($A12=0,0,IF(ISNUMBER($K12),$K12,IF(ISNUMBER(CDS_Entities!$AQ$10),CDS_Entities!$AQ$10,IF(ISNUMBER(CDS_Entities!$M$10),CDS_Entities!$M$10,0)))))
B27: =IF($B13="","",$B13) | E27: =IF($B13="","",IF($A13=0,"off",IF(ISNUMBER($E13),$E13,CDS_Entities!$F$11))) | F27: =IF($B13="","",IF($A13=0,0,IF(ISNUMBER($F13),$F13,IF(ISNUMBER(CDS_Entities!$AG$11),CDS_Entities!$AG$11,IF(ISNUMBER(CDS_Entities!$H$11),CDS_Entities!$H$11,0))))) | G27: =IF($B13="","",IF($A13=0,0,IF(ISNUMBER($G13),$G13,IF(ISNUMBER(CDS_Entities!$AI$11),CDS_Entities!$AI$11,IF(ISNUMBER(CDS_Entities!$I$11),CDS_Entities!$I$11,0))))) | H27: =IF($B13="","",IF($A13=0,0,IF(ISNUMBER($H13),$H13,IF(ISNUMBER(CDS_Entities!$AK$11),CDS_Entities!$AK$11,IF(ISNUMBER(CDS_Entities!$J$11),CDS_Entities!$J$11,0))))) | I27: =IF($B13="","",IF($A13=0,0,IF(ISNUMBER($I13),$I13,IF(ISNUMBER(CDS_Entities!$AM$11),CDS_Entities!$AM$11,IF(ISNUMBER(CDS_Entities!$K$11),CDS_Entities!$K$11,0))))) | J27: =IF($B13="","",IF($A13=0,0,IF(ISNUMBER($J13),$J13,IF(ISNUMBER(CDS_Entities!$AO$11),CDS_Entities!$AO$11,IF(ISNUMBER(CDS_Entities!$L$11),CDS_Entities!$L$11,0))))) | K27: =IF($B13="","",IF($A13=0,0,IF(ISNUMBER($K13),$K13,IF(ISNUMBER(CDS_Entities!$AQ$11),CDS_Entities!$AQ$11,IF(ISNUMBER(CDS_Entities!$M$11),CDS_Entities!$M$11,0)))))
B28: =IF($B14="","",$B14) | E28: =IF($B14="","",IF($A14=0,"off",IF(ISNUMBER($E14),$E14,CDS_Entities!$F$12))) | F28: =IF($B14="","",IF($A14=0,0,IF(ISNUMBER($F14),$F14,IF(ISNUMBER(CDS_Entities!$AG$12),CDS_Entities!$AG$12,IF(ISNUMBER(CDS_Entities!$H$12),CDS_Entities!$H$12,0))))) | G28: =IF($B14="","",IF($A14=0,0,IF(ISNUMBER($G14),$G14,IF(ISNUMBER(CDS_Entities!$AI$12),CDS_Entities!$AI$12,IF(ISNUMBER(CDS_Entities!$I$12),CDS_Entities!$I$12,0))))) | H28: =IF($B14="","",IF($A14=0,0,IF(ISNUMBER($H14),$H14,IF(ISNUMBER(CDS_Entities!$AK$12),CDS_Entities!$AK$12,IF(ISNUMBER(CDS_Entities!$J$12),CDS_Entities!$J$12,0))))) | I28: =IF($B14="","",IF($A14=0,0,IF(ISNUMBER($I14),$I14,IF(ISNUMBER(CDS_Entities!$AM$12),CDS_Entities!$AM$12,IF(ISNUMBER(CDS_Entities!$K$12),CDS_Entities!$K$12,0))))) | J28: =IF($B14="","",IF($A14=0,0,IF(ISNUMBER($J14),$J14,IF(ISNUMBER(CDS_Entities!$AO$12),CDS_Entities!$AO$12,IF(ISNUMBER(CDS_Entities!$L$12),CDS_Entities!$L$12,0))))) | K28: =IF($B14="","",IF($A14=0,0,IF(ISNUMBER($K14),$K14,IF(ISNUMBER(CDS_Entities!$AQ$12),CDS_Entities!$AQ$12,IF(ISNUMBER(CDS_Entities!$M$12),CDS_Entities!$M$12,0)))))
B29: =IF($B15="","",$B15) | E29: =IF($B15="","",IF($A15=0,"off",IF(ISNUMBER($E15),$E15,CDS_Entities!$F$13))) | F29: =IF($B15="","",IF($A15=0,0,IF(ISNUMBER($F15),$F15,IF(ISNUMBER(CDS_Entities!$AG$13),CDS_Entities!$AG$13,IF(ISNUMBER(CDS_Entities!$H$13),CDS_Entities!$H$13,0))))) | G29: =IF($B15="","",IF($A15=0,0,IF(ISNUMBER($G15),$G15,IF(ISNUMBER(CDS_Entities!$AI$13),CDS_Entities!$AI$13,IF(ISNUMBER(CDS_Entities!$I$13),CDS_Entities!$I$13,0))))) | H29: =IF($B15="","",IF($A15=0,0,IF(ISNUMBER($H15),$H15,IF(ISNUMBER(CDS_Entities!$AK$13),CDS_Entities!$AK$13,IF(ISNUMBER(CDS_Entities!$J$13),CDS_Entities!$J$13,0))))) | I29: =IF($B15="","",IF($A15=0,0,IF(ISNUMBER($I15),$I15,IF(ISNUMBER(CDS_Entities!$AM$13),CDS_Entities!$AM$13,IF(ISNUMBER(CDS_Entities!$K$13),CDS_Entities!$K$13,0))))) | J29: =IF($B15="","",IF($A15=0,0,IF(ISNUMBER($J15),$J15,IF(ISNUMBER(CDS_Entities!$AO$13),CDS_Entities!$AO$13,IF(ISNUMBER(CDS_Entities!$L$13),CDS_Entities!$L$13,0))))) | K29: =IF($B15="","",IF($A15=0,0,IF(ISNUMBER($K15),$K15,IF(ISNUMBER(CDS_Entities!$AQ$13),CDS_Entities!$AQ$13,IF(ISNUMBER(CDS_Entities!$M$13),CDS_Entities!$M$13,0)))))
B30: =IF($B16="","",$B16) | E30: =IF($B16="","",IF($A16=0,"off",IF(ISNUMBER($E16),$E16,CDS_Entities!$F$14))) | F30: =IF($B16="","",IF($A16=0,0,IF(ISNUMBER($F16),$F16,IF(ISNUMBER(CDS_Entities!$AG$14),CDS_Entities!$AG$14,IF(ISNUMBER(CDS_Entities!$H$14),CDS_Entities!$H$14,0))))) | G30: =IF($B16="","",IF($A16=0,0,IF(ISNUMBER($G16),$G16,IF(ISNUMBER(CDS_Entities!$AI$14),CDS_Entities!$AI$14,IF(ISNUMBER(CDS_Entities!$I$14),CDS_Entities!$I$14,0))))) | H30: =IF($B16="","",IF($A16=0,0,IF(ISNUMBER($H16),$H16,IF(ISNUMBER(CDS_Entities!$AK$14),CDS_Entities!$AK$14,IF(ISNUMBER(CDS_Entities!$J$14),CDS_Entities!$J$14,0))))) | I30: =IF($B16="","",IF($A16=0,0,IF(ISNUMBER($I16),$I16,IF(ISNUMBER(CDS_Entities!$AM$14),CDS_Entities!$AM$14,IF(ISNUMBER(CDS_Entities!$K$14),CDS_Entities!$K$14,0))))) | J30: =IF($B16="","",IF($A16=0,0,IF(ISNUMBER($J16),$J16,IF(ISNUMBER(CDS_Entities!$AO$14),CDS_Entities!$AO$14,IF(ISNUMBER(CDS_Entities!$L$14),CDS_Entities!$L$14,0))))) | K30: =IF($B16="","",IF($A16=0,0,IF(ISNUMBER($K16),$K16,IF(ISNUMBER(CDS_Entities!$AQ$14),CDS_Entities!$AQ$14,IF(ISNUMBER(CDS_Entities!$M$14),CDS_Entities!$M$14,0)))))

Sheet Curves
A1: Curves
A2: Discount curve is the pasted snapshot. Hazard and survival come from the strip.
A4: SOFR discount curve
A5: Date | B5: T | C5: DF | D5: Zero %
A6: ='Curve_Interface'!K9 | B6: =('Curve_Interface'!K9-VAL_DATE)/365 | C6: ='Curve_Interface'!L9 | D6: =IF(B6<=0,"",-LN(C6)/B6*100)
A7: ='Curve_Interface'!K10 | B7: =('Curve_Interface'!K10-VAL_DATE)/365 | C7: ='Curve_Interface'!L10 | D7: =IF(B7<=0,"",-LN(C7)/B7*100)
A8: ='Curve_Interface'!K11 | B8: =('Curve_Interface'!K11-VAL_DATE)/365 | C8: ='Curve_Interface'!L11 | D8: =IF(B8<=0,"",-LN(C8)/B8*100)
A9: ='Curve_Interface'!K12 | B9: =('Curve_Interface'!K12-VAL_DATE)/365 | C9: ='Curve_Interface'!L12 | D9: =IF(B9<=0,"",-LN(C9)/B9*100)
A10: ='Curve_Interface'!K13 | B10: =('Curve_Interface'!K13-VAL_DATE)/365 | C10: ='Curve_Interface'!L13 | D10: =IF(B10<=0,"",-LN(C10)/B10*100)
A11: ='Curve_Interface'!K14 | B11: =('Curve_Interface'!K14-VAL_DATE)/365 | C11: ='Curve_Interface'!L14 | D11: =IF(B11<=0,"",-LN(C11)/B11*100)
A12: ='Curve_Interface'!K15 | B12: =('Curve_Interface'!K15-VAL_DATE)/365 | C12: ='Curve_Interface'!L15 | D12: =IF(B12<=0,"",-LN(C12)/B12*100)
A13: ='Curve_Interface'!K16 | B13: =('Curve_Interface'!K16-VAL_DATE)/365 | C13: ='Curve_Interface'!L16 | D13: =IF(B13<=0,"",-LN(C13)/B13*100)
A14: ='Curve_Interface'!K17 | B14: =('Curve_Interface'!K17-VAL_DATE)/365 | C14: ='Curve_Interface'!L17 | D14: =IF(B14<=0,"",-LN(C14)/B14*100)
A15: ='Curve_Interface'!K18 | B15: =('Curve_Interface'!K18-VAL_DATE)/365 | C15: ='Curve_Interface'!L18 | D15: =IF(B15<=0,"",-LN(C15)/B15*100)
A16: ='Curve_Interface'!K19 | B16: =('Curve_Interface'!K19-VAL_DATE)/365 | C16: ='Curve_Interface'!L19 | D16: =IF(B16<=0,"",-LN(C16)/B16*100)
A17: ='Curve_Interface'!K20 | B17: =('Curve_Interface'!K20-VAL_DATE)/365 | C17: ='Curve_Interface'!L20 | D17: =IF(B17<=0,"",-LN(C17)/B17*100)
... A70: ='Curve_Interface'!K73 | B70: =('Curve_Interface'!K73-VAL_DATE)/365 | C70: ='Curve_Interface'!L73 | D70: =IF(B70<=0,"",-LN(C70)/B70*100)
A73: Hazard and survival
A74: Tenor | B74: Hazard % | C74: Survival Q | D74: Default prob 1-Q
A75: =Hazard_Bootstrap!A7 | B75: =Hazard_Bootstrap!D7*100 | C75: =Hazard_Bootstrap!E7 | D75: =Hazard_Bootstrap!F7
A76: =Hazard_Bootstrap!A8 | B76: =Hazard_Bootstrap!D8*100 | C76: =Hazard_Bootstrap!E8 | D76: =Hazard_Bootstrap!F8
A77: =Hazard_Bootstrap!A9 | B77: =Hazard_Bootstrap!D9*100 | C77: =Hazard_Bootstrap!E9 | D77: =Hazard_Bootstrap!F9
A78: =Hazard_Bootstrap!A10 | B78: =Hazard_Bootstrap!D10*100 | C78: =Hazard_Bootstrap!E10 | D78: =Hazard_Bootstrap!F10
A79: =Hazard_Bootstrap!A11 | B79: =Hazard_Bootstrap!D11*100 | C79: =Hazard_Bootstrap!E11 | D79: =Hazard_Bootstrap!F11
A80: =Hazard_Bootstrap!A12 | B80: =Hazard_Bootstrap!D12*100 | C80: =Hazard_Bootstrap!E12 | D80: =Hazard_Bootstrap!F12
A83: Spread term structure
A84: Tenor | B84: Market bp | C84: Model bp | D84: Diff bp | E84: Traded spread
A85: =Hazard_Bootstrap!A7 | B85: =Hazard_Bootstrap!C7 | C85: =Hazard_Bootstrap!I7 | D85: =Hazard_Bootstrap!J7 | E85: =CDS_Pricer!$B$15
A86: =Hazard_Bootstrap!A8 | B86: =Hazard_Bootstrap!C8 | C86: =Hazard_Bootstrap!I8 | D86: =Hazard_Bootstrap!J8 | E86: =CDS_Pricer!$B$15
A87: =Hazard_Bootstrap!A9 | B87: =Hazard_Bootstrap!C9 | C87: =Hazard_Bootstrap!I9 | D87: =Hazard_Bootstrap!J9 | E87: =CDS_Pricer!$B$15
A88: =Hazard_Bootstrap!A10 | B88: =Hazard_Bootstrap!C10 | C88: =Hazard_Bootstrap!I10 | D88: =Hazard_Bootstrap!J10 | E88: =CDS_Pricer!$B$15
A89: =Hazard_Bootstrap!A11 | B89: =Hazard_Bootstrap!C11 | C89: =Hazard_Bootstrap!I11 | D89: =Hazard_Bootstrap!J11 | E89: =CDS_Pricer!$B$15
A90: =Hazard_Bootstrap!A12 | B90: =Hazard_Bootstrap!C12 | C90: =Hazard_Bootstrap!I12 | D90: =Hazard_Bootstrap!J12 | E90: =CDS_Pricer!$B$15

Sheet Model_Notes
A1: Model notes: Bloomberg B-Model (CDSW)
A2: Equation numbers and page cites are the white paper's own. Scans in bloomberg/reference/cds_white_paper/.
A4: Pricing
A5: (3.1) | B5: Market Value = Protection Leg - Premium Leg, both discounted to pricing date T
A6: (3.2) | B6: Upfront = Market Value / D(T_s) + Accrued Interest
A7: (3.3) | B7: S = Protection Leg / (Premium Leg - Accrued Interest * D(T_s)) at C = 1bp
A8: (3.4) | B8: Coupons-in-Survival = A * C * SUM delta(T_i-1, T_i) p_s(T_i) D(T_i)
A9: (3.5) | B9: Accrued-on-Default = A * C * INT_T^TM delta(T_n(t), t) (-dp_s/dt) D(t) dt
A10: (3.6) | B10: Protection Leg = A (1-R) * INT_T^TM (-dp_s/dt) D(t) dt
A12: Conventions that the sheets depend on
A13: p.6 | B13: Accrual dates are IMM (3/20, 6/20, 9/20, 12/20). Payment dates roll to the next business day; the last accrual end date T_M does not roll.
A14: p.6 | B14: Coupon standardised to 100bp / 500bp for most names. ACT/360.
A15: p.6 | B15: Protection starts immediately, so the protection period is T_M - T + 1 days.
A16: p.7 | B16: Accrued interest includes the pricing date.
A17: p.7 | B17: T_s = settlement, typically 3 business days after pricing. The upfront is quoted there, so market value is compounded T to T_s.
A18: p.6 | B18: USD discounting is the SOFR RFR curve: ISDA moved to RFR curves and the B-Model follows.
A19: p.6 | B19: Recovery R is a model parameter, conventionally 40%, not an observable.
A21: Curve stripper (section 4, p.8)
A22: Sequential one-dimensional root-finding, not a joint fit. h_1 is solved on [0, T_M1] to match the first quote;
A23: each later h_i+1 is solved on (T_Mi, T_Mi+1] with all earlier hazards held fixed.
A24: Hazard is piecewise constant. h(t) >= 0 is a hard constraint - default is terminating, so survival cannot rise.
A25: The timeline is discretised finely enough that the forward discount rate and hazard are constant on a segment,
A26: and no segment is longer than a premium accrual period; (3.5) and (3.6) are then analytic on each segment.
A28: Strippability (p.9)
A29: With h_i+1 running 0 to infinity the achievable par spread at the next maturity is a bounded interval, and it
A30: narrows sharply once survival is already low. A quote outside that interval makes the calibration fail.
A31: The paper's reading: usually inconsistent data sources rather than genuine arbitrage. Common with inverted
A32: curves (S_i+1 < S_i, though mildly inverted curves are often still strippable) and distressed non-flat curves.
A33: Approximate lower bound, valid while cumulative default probability is low: S_i+1 >= S_i * T_i / T_i+1
A35: Strippability check on the live quotes
A36: Tenor | B36: T | C36: S (bp) | D36: bound S*T_prev/T | E36: ok?
A37: =Hazard_Bootstrap!A7 | B37: =CDS_Quotes!B7 | C37: =Hazard_Bootstrap!C7 | D37: - | E37: first pillar, unconstrained
A38: =Hazard_Bootstrap!A8 | B38: =CDS_Quotes!B8 | C38: =Hazard_Bootstrap!C8 | D38: =C37*B37/B38 | E38: =IF(C38>=D38,"ok","below bound — may not strip")
A39: =Hazard_Bootstrap!A9 | B39: =CDS_Quotes!B9 | C39: =Hazard_Bootstrap!C9 | D39: =C38*B38/B39 | E39: =IF(C39>=D39,"ok","below bound — may not strip")
A40: =Hazard_Bootstrap!A10 | B40: =CDS_Quotes!B10 | C40: =Hazard_Bootstrap!C10 | D40: =C39*B39/B40 | E40: =IF(C40>=D40,"ok","below bound — may not strip")
A41: =Hazard_Bootstrap!A11 | B41: =CDS_Quotes!B11 | C41: =Hazard_Bootstrap!C11 | D41: =C40*B40/B41 | E41: =IF(C41>=D41,"ok","below bound — may not strip")
A42: =Hazard_Bootstrap!A12 | B42: =CDS_Quotes!B12 | C42: =Hazard_Bootstrap!C12 | D42: =C41*B41/B42 | E42: =IF(C42>=D42,"ok","below bound — may not strip")
A44: A fail is the p.9 condition: a warning about the quotes, not the solver.
A45: Bound is approximate, valid while cumulative default probability is low.
A47: Limits
A48: No external validation of the strip: Bloomberg exports no hazard curve (Help Desk H#1330731572).
A49: Spreads here are demo values. The SOFR curve is real market data; the credit curve is not.

Sheet Root_Methods
A1: Root-finding methods on the hazard strip
A2: All methods solve the same f(h) = (1-R)*Prot(h) - S*(RPV01(h) - AI), B-Model (3.3). Same root; different cost.
A3: Baseline is the scheme, not the algorithm. Section 4 p.8 fixes piecewise-constant hazard solved maturity by maturity, each a 1-D root-find with earlier hazards fixed. It names no method. Hazard_Solver here is bisection.
A4: Needs CDSBrent.bas and CDSRootFinders.bas imported, saved as .xlsm.
A6: Method | B6: Family | C6: Order | D6: Needs | E6: Bracketed | F6: 5Y hazard | G6: its | H6: |f(root)| | I6: vs baseline | J6: Note
A7: BISECTION | B7: bracketing | C7: linear (halves) | D7: no | E7: yes, always | F7: =IFERROR(CDS_Root("BISECTION",Hazard_Solver!$D$136,Hazard_Solver!$F$136,Hazard_Solver!$B$137,Hazard_Solver!$D$137,Hazard_Solver!$F$137,CDS_Parameters!$B$26,Hazard_Solver!$F$139:$U$139,Hazard_Solver!$F$143:$U$143,Hazard_Solver!$F$141:$U$141,Hazard_Solver!$F$142:$U$142),"module not loaded") | G7: =IFERROR(CDS_RootIterations(),"") | H7: =IFERROR(ABS(CDS_Objective(F7,Hazard_Solver!$D$136,Hazard_Solver!$F$136,Hazard_Solver!$B$137,Hazard_Solver!$D$137,Hazard_Solver!$F$137,CDS_Parameters!$B$26,Hazard_Solver!$F$139:$U$139,Hazard_Solver!$F$143:$U$143,Hazard_Solver!$F$141:$U$141,Hazard_Solver!$F$142:$U$142)),"") | I7: =IF(ISNUMBER(F7),F7-Hazard_Solver!$B$175,"") | J7: The safe floor. Cannot fail once bracketed, but pays for it - ~52 steps to machine precision.
A8: FALSE POSITION | B8: bracketing | C8: super-linear | D8: no | E8: yes, always | F8: =IFERROR(CDS_Root("FALSE POSITION",Hazard_Solver!$D$136,Hazard_Solver!$F$136,Hazard_Solver!$B$137,Hazard_Solver!$D$137,Hazard_Solver!$F$137,CDS_Parameters!$B$26,Hazard_Solver!$F$139:$U$139,Hazard_Solver!$F$143:$U$143,Hazard_Solver!$F$141:$U$141,Hazard_Solver!$F$142:$U$142),"module not loaded") | G8: =IFERROR(CDS_RootIterations(),"") | H8: =IFERROR(ABS(CDS_Objective(F8,Hazard_Solver!$D$136,Hazard_Solver!$F$136,Hazard_Solver!$B$137,Hazard_Solver!$D$137,Hazard_Solver!$F$137,CDS_Parameters!$B$26,Hazard_Solver!$F$139:$U$139,Hazard_Solver!$F$143:$U$143,Hazard_Solver!$F$141:$U$141,Hazard_Solver!$F$142:$U$142)),"") | I8: =IF(ISNUMBER(F8),F8-Hazard_Solver!$B$175,"") | J8: Keeps a bracket like bisection but interpolates. Can stall when one end stays fixed.
A9: SECANT | B9: open | C9: ~1.618 | D9: no | E9: no | F9: =IFERROR(CDS_Root("SECANT",Hazard_Solver!$D$136,Hazard_Solver!$F$136,Hazard_Solver!$B$137,Hazard_Solver!$D$137,Hazard_Solver!$F$137,CDS_Parameters!$B$26,Hazard_Solver!$F$139:$U$139,Hazard_Solver!$F$143:$U$143,Hazard_Solver!$F$141:$U$141,Hazard_Solver!$F$142:$U$142),"module not loaded") | G9: =IFERROR(CDS_RootIterations(),"") | H9: =IFERROR(ABS(CDS_Objective(F9,Hazard_Solver!$D$136,Hazard_Solver!$F$136,Hazard_Solver!$B$137,Hazard_Solver!$D$137,Hazard_Solver!$F$137,CDS_Parameters!$B$26,Hazard_Solver!$F$139:$U$139,Hazard_Solver!$F$143:$U$143,Hazard_Solver!$F$141:$U$141,Hazard_Solver!$F$142:$U$142)),"") | I9: =IF(ISNUMBER(F9),F9-Hazard_Solver!$B$175,"") | J9: Newton without a derivative, using the secant of the last two points. No bracket, so it can leave the domain.
A10: NEWTON | B10: open | C10: 2 (quadratic) | D10: f' | E10: no | F10: =IFERROR(CDS_Root("NEWTON",Hazard_Solver!$D$136,Hazard_Solver!$F$136,Hazard_Solver!$B$137,Hazard_Solver!$D$137,Hazard_Solver!$F$137,CDS_Parameters!$B$26,Hazard_Solver!$F$139:$U$139,Hazard_Solver!$F$143:$U$143,Hazard_Solver!$F$141:$U$141,Hazard_Solver!$F$142:$U$142),"module not loaded") | G10: =IFERROR(CDS_RootIterations(),"") | H10: =IFERROR(ABS(CDS_Objective(F10,Hazard_Solver!$D$136,Hazard_Solver!$F$136,Hazard_Solver!$B$137,Hazard_Solver!$D$137,Hazard_Solver!$F$137,CDS_Parameters!$B$26,Hazard_Solver!$F$139:$U$139,Hazard_Solver!$F$143:$U$143,Hazard_Solver!$F$141:$U$141,Hazard_Solver!$F$142:$U$142)),"") | I10: =IF(ISNUMBER(F10),F10-Hazard_Solver!$B$175,"") | J10: Householder d=1. Derivative is analytic here - dQ/dh = -cum*Q - so no bumping.
A11: HALLEY | B11: open | C11: 3 (cubic) | D11: f', f'' | E11: no | F11: =IFERROR(CDS_Root("HALLEY",Hazard_Solver!$D$136,Hazard_Solver!$F$136,Hazard_Solver!$B$137,Hazard_Solver!$D$137,Hazard_Solver!$F$137,CDS_Parameters!$B$26,Hazard_Solver!$F$139:$U$139,Hazard_Solver!$F$143:$U$143,Hazard_Solver!$F$141:$U$141,Hazard_Solver!$F$142:$U$142),"module not loaded") | G11: =IFERROR(CDS_RootIterations(),"") | H11: =IFERROR(ABS(CDS_Objective(F11,Hazard_Solver!$D$136,Hazard_Solver!$F$136,Hazard_Solver!$B$137,Hazard_Solver!$D$137,Hazard_Solver!$F$137,CDS_Parameters!$B$26,Hazard_Solver!$F$139:$U$139,Hazard_Solver!$F$143:$U$143,Hazard_Solver!$F$141:$U$141,Hazard_Solver!$F$142:$U$142)),"") | I11: =IF(ISNUMBER(F11),F11-Hazard_Solver!$B$175,"") | J11: Householder d=2. Second derivative also analytic: d2Q/dh2 = cum^2*Q.
A12: HOUSEHOLDER | B12: open | C12: d+1 | D12: f' ... f^(d) | E12: no | F12: =IFERROR(CDS_Root("HOUSEHOLDER",Hazard_Solver!$D$136,Hazard_Solver!$F$136,Hazard_Solver!$B$137,Hazard_Solver!$D$137,Hazard_Solver!$F$137,CDS_Parameters!$B$26,Hazard_Solver!$F$139:$U$139,Hazard_Solver!$F$143:$U$143,Hazard_Solver!$F$141:$U$141,Hazard_Solver!$F$142:$U$142),"module not loaded") | G12: =IFERROR(CDS_RootIterations(),"") | H12: =IFERROR(ABS(CDS_Objective(F12,Hazard_Solver!$D$136,Hazard_Solver!$F$136,Hazard_Solver!$B$137,Hazard_Solver!$D$137,Hazard_Solver!$F$137,CDS_Parameters!$B$26,Hazard_Solver!$F$139:$U$139,Hazard_Solver!$F$143:$U$143,Hazard_Solver!$F$141:$U$141,Hazard_Solver!$F$142:$U$142)),"") | I12: =IF(ISNUMBER(F12),F12-Hazard_Solver!$B$175,"") | J12: General order d. d=1 reduces to Newton and d=2 to Halley, the M2 identity.
A13: RIDDERS | B13: bracketing hybrid | C13: hybrid | D13: no | E13: yes, always | F13: =IFERROR(CDS_Root("RIDDERS",Hazard_Solver!$D$136,Hazard_Solver!$F$136,Hazard_Solver!$B$137,Hazard_Solver!$D$137,Hazard_Solver!$F$137,CDS_Parameters!$B$26,Hazard_Solver!$F$139:$U$139,Hazard_Solver!$F$143:$U$143,Hazard_Solver!$F$141:$U$141,Hazard_Solver!$F$142:$U$142),"module not loaded") | G13: =IFERROR(CDS_RootIterations(),"") | H13: =IFERROR(ABS(CDS_Objective(F13,Hazard_Solver!$D$136,Hazard_Solver!$F$136,Hazard_Solver!$B$137,Hazard_Solver!$D$137,Hazard_Solver!$F$137,CDS_Parameters!$B$26,Hazard_Solver!$F$139:$U$139,Hazard_Solver!$F$143:$U$143,Hazard_Solver!$F$141:$U$141,Hazard_Solver!$F$142:$U$142)),"") | I13: =IF(ISNUMBER(F13),F13-Hazard_Solver!$B$175,"") | J13: Bisection plus exponential interpolation. Keeps the bracket and converges fast.
A14: BRENT | B14: bracketing hybrid | C14: hybrid | D14: no | E14: yes, always | F14: =IFERROR(CDS_Root("BRENT",Hazard_Solver!$D$136,Hazard_Solver!$F$136,Hazard_Solver!$B$137,Hazard_Solver!$D$137,Hazard_Solver!$F$137,CDS_Parameters!$B$26,Hazard_Solver!$F$139:$U$139,Hazard_Solver!$F$143:$U$143,Hazard_Solver!$F$141:$U$141,Hazard_Solver!$F$142:$U$142),"module not loaded") | G14: =IFERROR(CDS_RootIterations(),"") | H14: =IFERROR(ABS(CDS_Objective(F14,Hazard_Solver!$D$136,Hazard_Solver!$F$136,Hazard_Solver!$B$137,Hazard_Solver!$D$137,Hazard_Solver!$F$137,CDS_Parameters!$B$26,Hazard_Solver!$F$139:$U$139,Hazard_Solver!$F$143:$U$143,Hazard_Solver!$F$141:$U$141,Hazard_Solver!$F$142:$U$142)),"") | I14: =IF(ISNUMBER(F14),F14-Hazard_Solver!$B$175,"") | J14: IQI, falling back to secant, falling back to bisection. Bisection's guarantee at near-secant speed.
A16: Spread of the eight roots (max - min) | F16: =IF(COUNT(F7:F14)=0,"module not loaded",MAX(F7:F14)-MIN(F7:F14)) | G16: they solve the same equation, so this is the real check
A18: Measured on the 5Y objective (quarterly, R=40%, S=95bp), tolerance 1e-15
A19: Method | B19: iters | C19: |root - scipy.brentq| | D19: |f(root)|
A20: bisection | B20: 52 | C20: 5.0e-16 | D20: 1.3e-15
A21: false position | B21: 12 | C21: 2.4e-17 | D21: 6.9e-17
A22: secant | B22: 13 | C22: 3.5e-18 | D22: 1.4e-17
A23: Newton (d=1) | B23: 6 | C23: 6.9e-18 | D23: 1.4e-17
A24: Halley (d=2) | B24: 6 | C24: 3.5e-18 | D24: 1.4e-17
A25: Householder d=3 | B25: 6 | C25: 3.5e-18 | D25: 1.4e-17
A26: Ridders | B26: 5 | C26: 2.1e-17 | D26: 3.5e-17
A27: Brent | B27: 9 | C27: 1.4e-17 | D27: 1.4e-17
A29: Results
A30: All eight agree to ~1e-16. Method is a cost choice here, not an accuracy one.
A31: Bisection: 52 steps. Newton: 6. That is the cost of ignoring the shape of f.
A32: Halley and Householder d=3 do not beat Newton here: 6 iterations each. f is near-linear in h at the root,
A33: so the extra order is spent before tolerance is reached.
A34: Ridders is fastest at 5. But secant, Newton and Halley can all leave the domain on a bad start;
A35: bracketing methods cannot. The strip must never return h < 0 (p.8), so the guarantee outranks the speed.
A36: If nothing converges, suspect the quote. See the p.9 strippability check on Model_Notes.

Sheet Brent_vs_Bisection
A1: Brent (VBA) vs in-cell bisection
A2: Same objective (3.3), same inputs. Only the root-finder differs. Eight methods on Root_Methods.
A3: Import CDSBrent.bas (Alt+F11 > File > Import File), save as .xlsm. Until then col D reads 'module not loaded'.
A5: Tenor | B5: Market bp | C5: Bisection (30 steps) | D5: Brent (VBA) | E5: diff | F5: Brent its | G5: f at bisection | H5: f at Brent | I5: Model bp | J5: Err bp
A6: 1Y | B6: =Hazard_Solver!$B$7 | C6: =Hazard_Solver!$B$46 | D6: =IFERROR(CDS_Hazard(Hazard_Solver!$D$7,Hazard_Solver!$F$7,Hazard_Solver!$B$8,Hazard_Solver!$D$8,Hazard_Solver!$F$8,CDS_Parameters!$B$26,Hazard_Solver!$F$10:$U$10,Hazard_Solver!$F$14:$U$14,Hazard_Solver!$F$12:$U$12,Hazard_Solver!$F$13:$U$13),"module not loaded") | E6: =IF(ISNUMBER(D6),D6-C6,"") | F6: =IFERROR(CDS_LastIterations(),"") | G6: =IFERROR(CDS_Objective(C6,Hazard_Solver!$D$7,Hazard_Solver!$F$7,Hazard_Solver!$B$8,Hazard_Solver!$D$8,Hazard_Solver!$F$8,CDS_Parameters!$B$26,Hazard_Solver!$F$10:$U$10,Hazard_Solver!$F$14:$U$14,Hazard_Solver!$F$12:$U$12,Hazard_Solver!$F$13:$U$13),"") | H6: =IF(ISNUMBER(D6),IFERROR(CDS_Objective(D6,Hazard_Solver!$D$7,Hazard_Solver!$F$7,Hazard_Solver!$B$8,Hazard_Solver!$D$8,Hazard_Solver!$F$8,CDS_Parameters!$B$26,Hazard_Solver!$F$10:$U$10,Hazard_Solver!$F$14:$U$14,Hazard_Solver!$F$12:$U$12,Hazard_Solver!$F$13:$U$13),""),"") | I6: =IF(ISNUMBER(D6),IFERROR(CDS_ModelSpread(D6,Hazard_Solver!$D$7,Hazard_Solver!$F$7,Hazard_Solver!$B$8,Hazard_Solver!$D$8,Hazard_Solver!$F$8,CDS_Parameters!$B$26,Hazard_Solver!$F$10:$U$10,Hazard_Solver!$F$14:$U$14,Hazard_Solver!$F$12:$U$12,Hazard_Solver!$F$13:$U$13),""),"") | J6: =IF(ISNUMBER(I6),I6-B6,"")
A7: 2Y | B7: =Hazard_Solver!$B$50 | C7: =Hazard_Solver!$B$89 | D7: =IFERROR(CDS_Hazard(Hazard_Solver!$D$50,Hazard_Solver!$F$50,Hazard_Solver!$B$51,Hazard_Solver!$D$51,Hazard_Solver!$F$51,CDS_Parameters!$B$26,Hazard_Solver!$F$53:$U$53,Hazard_Solver!$F$57:$U$57,Hazard_Solver!$F$55:$U$55,Hazard_Solver!$F$56:$U$56),"module not loaded") | E7: =IF(ISNUMBER(D7),D7-C7,"") | F7: =IFERROR(CDS_LastIterations(),"") | G7: =IFERROR(CDS_Objective(C7,Hazard_Solver!$D$50,Hazard_Solver!$F$50,Hazard_Solver!$B$51,Hazard_Solver!$D$51,Hazard_Solver!$F$51,CDS_Parameters!$B$26,Hazard_Solver!$F$53:$U$53,Hazard_Solver!$F$57:$U$57,Hazard_Solver!$F$55:$U$55,Hazard_Solver!$F$56:$U$56),"") | H7: =IF(ISNUMBER(D7),IFERROR(CDS_Objective(D7,Hazard_Solver!$D$50,Hazard_Solver!$F$50,Hazard_Solver!$B$51,Hazard_Solver!$D$51,Hazard_Solver!$F$51,CDS_Parameters!$B$26,Hazard_Solver!$F$53:$U$53,Hazard_Solver!$F$57:$U$57,Hazard_Solver!$F$55:$U$55,Hazard_Solver!$F$56:$U$56),""),"") | I7: =IF(ISNUMBER(D7),IFERROR(CDS_ModelSpread(D7,Hazard_Solver!$D$50,Hazard_Solver!$F$50,Hazard_Solver!$B$51,Hazard_Solver!$D$51,Hazard_Solver!$F$51,CDS_Parameters!$B$26,Hazard_Solver!$F$53:$U$53,Hazard_Solver!$F$57:$U$57,Hazard_Solver!$F$55:$U$55,Hazard_Solver!$F$56:$U$56),""),"") | J7: =IF(ISNUMBER(I7),I7-B7,"")
A8: 3Y | B8: =Hazard_Solver!$B$93 | C8: =Hazard_Solver!$B$132 | D8: =IFERROR(CDS_Hazard(Hazard_Solver!$D$93,Hazard_Solver!$F$93,Hazard_Solver!$B$94,Hazard_Solver!$D$94,Hazard_Solver!$F$94,CDS_Parameters!$B$26,Hazard_Solver!$F$96:$U$96,Hazard_Solver!$F$100:$U$100,Hazard_Solver!$F$98:$U$98,Hazard_Solver!$F$99:$U$99),"module not loaded") | E8: =IF(ISNUMBER(D8),D8-C8,"") | F8: =IFERROR(CDS_LastIterations(),"") | G8: =IFERROR(CDS_Objective(C8,Hazard_Solver!$D$93,Hazard_Solver!$F$93,Hazard_Solver!$B$94,Hazard_Solver!$D$94,Hazard_Solver!$F$94,CDS_Parameters!$B$26,Hazard_Solver!$F$96:$U$96,Hazard_Solver!$F$100:$U$100,Hazard_Solver!$F$98:$U$98,Hazard_Solver!$F$99:$U$99),"") | H8: =IF(ISNUMBER(D8),IFERROR(CDS_Objective(D8,Hazard_Solver!$D$93,Hazard_Solver!$F$93,Hazard_Solver!$B$94,Hazard_Solver!$D$94,Hazard_Solver!$F$94,CDS_Parameters!$B$26,Hazard_Solver!$F$96:$U$96,Hazard_Solver!$F$100:$U$100,Hazard_Solver!$F$98:$U$98,Hazard_Solver!$F$99:$U$99),""),"") | I8: =IF(ISNUMBER(D8),IFERROR(CDS_ModelSpread(D8,Hazard_Solver!$D$93,Hazard_Solver!$F$93,Hazard_Solver!$B$94,Hazard_Solver!$D$94,Hazard_Solver!$F$94,CDS_Parameters!$B$26,Hazard_Solver!$F$96:$U$96,Hazard_Solver!$F$100:$U$100,Hazard_Solver!$F$98:$U$98,Hazard_Solver!$F$99:$U$99),""),"") | J8: =IF(ISNUMBER(I8),I8-B8,"")
A9: 5Y | B9: =Hazard_Solver!$B$136 | C9: =Hazard_Solver!$B$175 | D9: =IFERROR(CDS_Hazard(Hazard_Solver!$D$136,Hazard_Solver!$F$136,Hazard_Solver!$B$137,Hazard_Solver!$D$137,Hazard_Solver!$F$137,CDS_Parameters!$B$26,Hazard_Solver!$F$139:$U$139,Hazard_Solver!$F$143:$U$143,Hazard_Solver!$F$141:$U$141,Hazard_Solver!$F$142:$U$142),"module not loaded") | E9: =IF(ISNUMBER(D9),D9-C9,"") | F9: =IFERROR(CDS_LastIterations(),"") | G9: =IFERROR(CDS_Objective(C9,Hazard_Solver!$D$136,Hazard_Solver!$F$136,Hazard_Solver!$B$137,Hazard_Solver!$D$137,Hazard_Solver!$F$137,CDS_Parameters!$B$26,Hazard_Solver!$F$139:$U$139,Hazard_Solver!$F$143:$U$143,Hazard_Solver!$F$141:$U$141,Hazard_Solver!$F$142:$U$142),"") | H9: =IF(ISNUMBER(D9),IFERROR(CDS_Objective(D9,Hazard_Solver!$D$136,Hazard_Solver!$F$136,Hazard_Solver!$B$137,Hazard_Solver!$D$137,Hazard_Solver!$F$137,CDS_Parameters!$B$26,Hazard_Solver!$F$139:$U$139,Hazard_Solver!$F$143:$U$143,Hazard_Solver!$F$141:$U$141,Hazard_Solver!$F$142:$U$142),""),"") | I9: =IF(ISNUMBER(D9),IFERROR(CDS_ModelSpread(D9,Hazard_Solver!$D$136,Hazard_Solver!$F$136,Hazard_Solver!$B$137,Hazard_Solver!$D$137,Hazard_Solver!$F$137,CDS_Parameters!$B$26,Hazard_Solver!$F$139:$U$139,Hazard_Solver!$F$143:$U$143,Hazard_Solver!$F$141:$U$141,Hazard_Solver!$F$142:$U$142),""),"") | J9: =IF(ISNUMBER(I9),I9-B9,"")
A10: 7Y | B10: =Hazard_Solver!$B$179 | C10: =Hazard_Solver!$B$218 | D10: =IFERROR(CDS_Hazard(Hazard_Solver!$D$179,Hazard_Solver!$F$179,Hazard_Solver!$B$180,Hazard_Solver!$D$180,Hazard_Solver!$F$180,CDS_Parameters!$B$26,Hazard_Solver!$F$182:$U$182,Hazard_Solver!$F$186:$U$186,Hazard_Solver!$F$184:$U$184,Hazard_Solver!$F$185:$U$185),"module not loaded") | E10: =IF(ISNUMBER(D10),D10-C10,"") | F10: =IFERROR(CDS_LastIterations(),"") | G10: =IFERROR(CDS_Objective(C10,Hazard_Solver!$D$179,Hazard_Solver!$F$179,Hazard_Solver!$B$180,Hazard_Solver!$D$180,Hazard_Solver!$F$180,CDS_Parameters!$B$26,Hazard_Solver!$F$182:$U$182,Hazard_Solver!$F$186:$U$186,Hazard_Solver!$F$184:$U$184,Hazard_Solver!$F$185:$U$185),"") | H10: =IF(ISNUMBER(D10),IFERROR(CDS_Objective(D10,Hazard_Solver!$D$179,Hazard_Solver!$F$179,Hazard_Solver!$B$180,Hazard_Solver!$D$180,Hazard_Solver!$F$180,CDS_Parameters!$B$26,Hazard_Solver!$F$182:$U$182,Hazard_Solver!$F$186:$U$186,Hazard_Solver!$F$184:$U$184,Hazard_Solver!$F$185:$U$185),""),"") | I10: =IF(ISNUMBER(D10),IFERROR(CDS_ModelSpread(D10,Hazard_Solver!$D$179,Hazard_Solver!$F$179,Hazard_Solver!$B$180,Hazard_Solver!$D$180,Hazard_Solver!$F$180,CDS_Parameters!$B$26,Hazard_Solver!$F$182:$U$182,Hazard_Solver!$F$186:$U$186,Hazard_Solver!$F$184:$U$184,Hazard_Solver!$F$185:$U$185),""),"") | J10: =IF(ISNUMBER(I10),I10-B10,"")
A11: 10Y | B11: =Hazard_Solver!$B$222 | C11: =Hazard_Solver!$B$261 | D11: =IFERROR(CDS_Hazard(Hazard_Solver!$D$222,Hazard_Solver!$F$222,Hazard_Solver!$B$223,Hazard_Solver!$D$223,Hazard_Solver!$F$223,CDS_Parameters!$B$26,Hazard_Solver!$F$225:$U$225,Hazard_Solver!$F$229:$U$229,Hazard_Solver!$F$227:$U$227,Hazard_Solver!$F$228:$U$228),"module not loaded") | E11: =IF(ISNUMBER(D11),D11-C11,"") | F11: =IFERROR(CDS_LastIterations(),"") | G11: =IFERROR(CDS_Objective(C11,Hazard_Solver!$D$222,Hazard_Solver!$F$222,Hazard_Solver!$B$223,Hazard_Solver!$D$223,Hazard_Solver!$F$223,CDS_Parameters!$B$26,Hazard_Solver!$F$225:$U$225,Hazard_Solver!$F$229:$U$229,Hazard_Solver!$F$227:$U$227,Hazard_Solver!$F$228:$U$228),"") | H11: =IF(ISNUMBER(D11),IFERROR(CDS_Objective(D11,Hazard_Solver!$D$222,Hazard_Solver!$F$222,Hazard_Solver!$B$223,Hazard_Solver!$D$223,Hazard_Solver!$F$223,CDS_Parameters!$B$26,Hazard_Solver!$F$225:$U$225,Hazard_Solver!$F$229:$U$229,Hazard_Solver!$F$227:$U$227,Hazard_Solver!$F$228:$U$228),""),"") | I11: =IF(ISNUMBER(D11),IFERROR(CDS_ModelSpread(D11,Hazard_Solver!$D$222,Hazard_Solver!$F$222,Hazard_Solver!$B$223,Hazard_Solver!$D$223,Hazard_Solver!$F$223,CDS_Parameters!$B$26,Hazard_Solver!$F$225:$U$225,Hazard_Solver!$F$229:$U$229,Hazard_Solver!$F$227:$U$227,Hazard_Solver!$F$228:$U$228),""),"") | J11: =IF(ISNUMBER(I11),I11-B11,"")
A13: Max |diff| (hazard) | C13: =IF(COUNT(E6:E11)=0,"module not loaded",MAX(MAX(E6:E11),-MIN(E6:E11)))
A14: Max |Err| Brent (bp) | C14: =IF(COUNT(J6:J11)=0,"",MAX(MAX(J6:J11),-MIN(J6:J11)))
A17: WHAT BRENT ACTUALLY BUYS
B18: In-cell bisection | C18: Brent (VBA) | D18: Better
A19: Iterations | B19: 30, fixed | C19: 8-13, adaptive | D19: Brent
A20: Residual |f| at the root | B20: ~1e-9 | C20: ~1e-17 | D20: Brent, by ~8 orders
A21: Hazard agreement | B21: the two agree to ~1e-9 | D21: immaterial: 1e-9 of hazard is 1e-7 bp of spread
A22: Cells consumed | B22: ~3,600 on Hazard_Solver | C22: 6 function calls | D22: Brent, heavily
A23: Working visible | B23: yes, every halving is a row | C23: no, opaque call | D23: BISECTION
A24: File format | B24: .xlsx | C24: .xlsm + macro trust | D24: BISECTION
A25: Recalc | B25: native | C25: UDF, slower per call, no multithread | D25: bisection
A26: Fails on an unstrippable quote | B26: pins silently at a bracket end | C26: returns #NUM! | D26: Brent
A29: Verdict
A30: Brent wins on the numbers: 8-13 iterations to machine precision vs 30 fixed halvings, residual ~1e-17 vs ~1e-9.
A31: It would return ~3,600 cells and a faster recalc. It costs the visible working and forces .xlsm.
A32: Keeping bisection as the engine and Brent as the cross-check is the useful split: an independent implementation agreeing to 1e-9 is real evidence the strip is right.
A33: Functional gain worth taking: Brent returns #NUM! on an unbracketed quote. Bisection returns a bracket end that looks like an answer. See Model_Notes, p.9.

Sheet Curve_Interface
A1: Curve_Interface
A2: Shared discounting D(0,t). Curve grid in K:L is a dated snapshot from the SOFR bootstrap, pasted as values.
A4: Piecewise-flat instantaneous forward between pillars. Confirmed against S490 as Step Forward (Cont).
N5: Valuation date | O5: 46224
K6: Curve grid - LIVE LINK to the curve workbook | M6: source: [USD_SOFR_Curve_Bloomberg_Pricer.xlsx]Curve_Interface!K8 (anchor) + K10:L74 (65 pillars) | N6: drives every date on the CDS sheets
A7: Valuation: | B7: =VAL_DATE | C7: Spot: | D7: ='[USD_SOFR_Curve_Bloomberg_Pricer.xlsx]Curve_Interface'!$D$7 | E7: 1st CDS date: | F7: =IF(DATE(YEAR(VAL_DATE),CEILING(MONTH(VAL_DATE)/3,1)*3,20)>=VAL_DATE,DATE(YEAR(VAL_DATE),CEILING(MONTH(VAL_DATE)/3,1)*3,20),EDATE(DATE(YEAR(VAL_DATE),CEILING(MONTH(VAL_DATE)/3,1)*3,20),3)) | I7: Interpolation | J7: Step-function forward (flat fwd) | K7: Date | L7: DF
I8: VERIFIED default | J8: Step-function forward reproduces S490 (confirmed on screen: Step Forward (Cont)). Piecewise Linear (Simple) is 48x worse here. Only switch if the screen says so. | K8: ='[USD_SOFR_Curve_Bloomberg_Pricer.xlsx]Curve_Interface'!$K$8 | L8: ='[USD_SOFR_Curve_Bloomberg_Pricer.xlsx]Curve_Interface'!$L$8 | N8: LINK CHECK
A9: Coupon # | B9: Date | C9: Time from val (yrs) | D9: Prev SOFR pillar | E9: Next SOFR pillar | F9: Segment fwd (%) | G9: Interp DF D(0,t) | H9: Interp zero (%) | K9: ='[USD_SOFR_Curve_Bloomberg_Pricer.xlsx]Curve_Interface'!$K$10 | L9: ='[USD_SOFR_Curve_Bloomberg_Pricer.xlsx]Curve_Interface'!$L$10 | N9: pillars linked | O9: =COUNT($L$8:$L$73)
A10: 1 | B10: =EDATE($F$7,3*0) | C10: =(B10-VAL_DATE)/365 | D10: =INDEX($K$8:$K$73,MATCH(B10,$K$8:$K$73,1)) | E10: =INDEX($K$8:$K$73,MATCH(B10,$K$8:$K$73,1)+1) | F10: =-LN(INDEX($L$8:$L$73,MATCH(B10,$K$8:$K$73,1)+1)/INDEX($L$8:$L$73,MATCH(B10,$K$8:$K$73,1)))/((E10-D10)/365)*100 | G10: =IFERROR(IF($J$7="Piecewise Linear (Simple)",IF(((B10-VAL_DATE)/360)<=0,1,1/(1+(IF(MAX((10>0)*(D10-VAL_DATE)/360,0)<=0,IF(((E10-VAL_DATE)/360)<=0,0,(1/INDEX($L$8:$L$73,MATCH(B10,$K$8:$K$73,1)+1)-1)/((E10-VAL_DATE)/360)),IF(MAX((10>0)*(D10-VAL_DATE)/360,0)<=0,0,(1/INDEX($L$8:$L$73,MATCH(B10,$K$8:$K$73,1))-1)/MAX((10>0)*(D10-VAL_DATE)/360,0)))+(IF(((E10-VAL_DATE)/360)<=0,0,(1/INDEX($L$8:$L$73,MATCH(B10,$K$8:$K$73,1)+1)-1)/((E10-VAL_DATE)/360))-IF(MAX((10>0)*(D10-VAL_DATE)/360,0)<=0,IF(((E10-VAL_DATE)/360)<=0,0,(1/INDEX($L$8:$L$73,MATCH(B10,$K$8:$K$73,1)+1)-1)/((E10-VAL_DATE)/360)),IF(MAX((10>0)*(D10-VAL_DATE)/360,0)<=0,0,(1/INDEX($L$8:$L$73,MATCH(B10,$K$8:$K$73,1))-1)/MAX((10>0)*(D10-VAL_DATE)/360,0))))*IF(((E10-VAL_DATE)/360)-MAX((10>0)*(D10-VAL_DATE)/360,0)=0,0,(((B10-VAL_DATE)/360)-MAX((10>0)*(D10-VAL_DATE)/360,0))/(((E10-VAL_DATE)/360)-MAX((10>0)*(D10-VAL_DATE)/360,0))))*((B10-VAL_DATE)/360))),INDEX($L$8:$L$73,MATCH(B10,$K$8:$K$73,1))*EXP(-(F10/100)*(B10-D10)/365)),"") | H10: =-LN(G10)/C10*100 | I10: Method 1: DF=1/(1+r_s*t), r_s linear, ACT/360, flat outside the pillars. | K10: ='[USD_SOFR_Curve_Bloomberg_Pricer.xlsx]Curve_Interface'!$K$11 | L10: ='[USD_SOFR_Curve_Bloomberg_Pricer.xlsx]Curve_Interface'!$L$11 | N10: first date | O10: =IF(COUNT($K$8:$K$73)=0,"",MIN($K$8:$K$73))
A11: 2 | B11: =EDATE($F$7,3*1) | C11: =(B11-VAL_DATE)/365 | D11: =INDEX($K$8:$K$73,MATCH(B11,$K$8:$K$73,1)) | E11: =INDEX($K$8:$K$73,MATCH(B11,$K$8:$K$73,1)+1) | F11: =-LN(INDEX($L$8:$L$73,MATCH(B11,$K$8:$K$73,1)+1)/INDEX($L$8:$L$73,MATCH(B11,$K$8:$K$73,1)))/((E11-D11)/365)*100 | G11: =IFERROR(IF($J$7="Piecewise Linear (Simple)",IF(((B11-VAL_DATE)/360)<=0,1,1/(1+(IF(MAX((11>0)*(D11-VAL_DATE)/360,0)<=0,IF(((E11-VAL_DATE)/360)<=0,0,(1/INDEX($L$8:$L$73,MATCH(B11,$K$8:$K$73,1)+1)-1)/((E11-VAL_DATE)/360)),IF(MAX((11>0)*(D11-VAL_DATE)/360,0)<=0,0,(1/INDEX($L$8:$L$73,MATCH(B11,$K$8:$K$73,1))-1)/MAX((11>0)*(D11-VAL_DATE)/360,0)))+(IF(((E11-VAL_DATE)/360)<=0,0,(1/INDEX($L$8:$L$73,MATCH(B11,$K$8:$K$73,1)+1)-1)/((E11-VAL_DATE)/360))-IF(MAX((11>0)*(D11-VAL_DATE)/360,0)<=0,IF(((E11-VAL_DATE)/360)<=0,0,(1/INDEX($L$8:$L$73,MATCH(B11,$K$8:$K$73,1)+1)-1)/((E11-VAL_DATE)/360)),IF(MAX((11>0)*(D11-VAL_DATE)/360,0)<=0,0,(1/INDEX($L$8:$L$73,MATCH(B11,$K$8:$K$73,1))-1)/MAX((11>0)*(D11-VAL_DATE)/360,0))))*IF(((E11-VAL_DATE)/360)-MAX((11>0)*(D11-VAL_DATE)/360,0)=0,0,(((B11-VAL_DATE)/360)-MAX((11>0)*(D11-VAL_DATE)/360,0))/(((E11-VAL_DATE)/360)-MAX((11>0)*(D11-VAL_DATE)/360,0))))*((B11-VAL_DATE)/360))),INDEX($L$8:$L$73,MATCH(B11,$K$8:$K$73,1))*EXP(-(F11/100)*(B11-D11)/365)),"") | H11: =-LN(G11)/C11*100 | I11: Method 3: flat forward between pillars = log-linear in DF. | K11: ='[USD_SOFR_Curve_Bloomberg_Pricer.xlsx]Curve_Interface'!$K$12 | L11: ='[USD_SOFR_Curve_Bloomberg_Pricer.xlsx]Curve_Interface'!$L$12 | N11: last date | O11: =IF(COUNT($K$8:$K$73)=0,"",MAX($K$8:$K$73))
A12: 3 | B12: =EDATE($F$7,3*2) | C12: =(B12-VAL_DATE)/365 | D12: =INDEX($K$8:$K$73,MATCH(B12,$K$8:$K$73,1)) | E12: =INDEX($K$8:$K$73,MATCH(B12,$K$8:$K$73,1)+1) | F12: =-LN(INDEX($L$8:$L$73,MATCH(B12,$K$8:$K$73,1)+1)/INDEX($L$8:$L$73,MATCH(B12,$K$8:$K$73,1)))/((E12-D12)/365)*100 | G12: =IFERROR(IF($J$7="Piecewise Linear (Simple)",IF(((B12-VAL_DATE)/360)<=0,1,1/(1+(IF(MAX((12>0)*(D12-VAL_DATE)/360,0)<=0,IF(((E12-VAL_DATE)/360)<=0,0,(1/INDEX($L$8:$L$73,MATCH(B12,$K$8:$K$73,1)+1)-1)/((E12-VAL_DATE)/360)),IF(MAX((12>0)*(D12-VAL_DATE)/360,0)<=0,0,(1/INDEX($L$8:$L$73,MATCH(B12,$K$8:$K$73,1))-1)/MAX((12>0)*(D12-VAL_DATE)/360,0)))+(IF(((E12-VAL_DATE)/360)<=0,0,(1/INDEX($L$8:$L$73,MATCH(B12,$K$8:$K$73,1)+1)-1)/((E12-VAL_DATE)/360))-IF(MAX((12>0)*(D12-VAL_DATE)/360,0)<=0,IF(((E12-VAL_DATE)/360)<=0,0,(1/INDEX($L$8:$L$73,MATCH(B12,$K$8:$K$73,1)+1)-1)/((E12-VAL_DATE)/360)),IF(MAX((12>0)*(D12-VAL_DATE)/360,0)<=0,0,(1/INDEX($L$8:$L$73,MATCH(B12,$K$8:$K$73,1))-1)/MAX((12>0)*(D12-VAL_DATE)/360,0))))*IF(((E12-VAL_DATE)/360)-MAX((12>0)*(D12-VAL_DATE)/360,0)=0,0,(((B12-VAL_DATE)/360)-MAX((12>0)*(D12-VAL_DATE)/360,0))/(((E12-VAL_DATE)/360)-MAX((12>0)*(D12-VAL_DATE)/360,0))))*((B12-VAL_DATE)/360))),INDEX($L$8:$L$73,MATCH(B12,$K$8:$K$73,1))*EXP(-(F12/100)*(B12-D12)/365)),"") | H12: =-LN(G12)/C12*100 | I12: Identical at the pillars. They differ off-pillar, which is what CDS_Schedule looks up. ~0.07bp in a 2Y gap. | K12: ='[USD_SOFR_Curve_Bloomberg_Pricer.xlsx]Curve_Interface'!$K$13 | L12: ='[USD_SOFR_Curve_Bloomberg_Pricer.xlsx]Curve_Interface'!$L$13 | N12: anchor DF (want 1) | O12: =IF($L$8="","",$L$8)
A13: 4 | B13: =EDATE($F$7,3*3) | C13: =(B13-VAL_DATE)/365 | D13: =INDEX($K$8:$K$73,MATCH(B13,$K$8:$K$73,1)) | E13: =INDEX($K$8:$K$73,MATCH(B13,$K$8:$K$73,1)+1) | F13: =-LN(INDEX($L$8:$L$73,MATCH(B13,$K$8:$K$73,1)+1)/INDEX($L$8:$L$73,MATCH(B13,$K$8:$K$73,1)))/((E13-D13)/365)*100 | G13: =IFERROR(IF($J$7="Piecewise Linear (Simple)",IF(((B13-VAL_DATE)/360)<=0,1,1/(1+(IF(MAX((13>0)*(D13-VAL_DATE)/360,0)<=0,IF(((E13-VAL_DATE)/360)<=0,0,(1/INDEX($L$8:$L$73,MATCH(B13,$K$8:$K$73,1)+1)-1)/((E13-VAL_DATE)/360)),IF(MAX((13>0)*(D13-VAL_DATE)/360,0)<=0,0,(1/INDEX($L$8:$L$73,MATCH(B13,$K$8:$K$73,1))-1)/MAX((13>0)*(D13-VAL_DATE)/360,0)))+(IF(((E13-VAL_DATE)/360)<=0,0,(1/INDEX($L$8:$L$73,MATCH(B13,$K$8:$K$73,1)+1)-1)/((E13-VAL_DATE)/360))-IF(MAX((13>0)*(D13-VAL_DATE)/360,0)<=0,IF(((E13-VAL_DATE)/360)<=0,0,(1/INDEX($L$8:$L$73,MATCH(B13,$K$8:$K$73,1)+1)-1)/((E13-VAL_DATE)/360)),IF(MAX((13>0)*(D13-VAL_DATE)/360,0)<=0,0,(1/INDEX($L$8:$L$73,MATCH(B13,$K$8:$K$73,1))-1)/MAX((13>0)*(D13-VAL_DATE)/360,0))))*IF(((E13-VAL_DATE)/360)-MAX((13>0)*(D13-VAL_DATE)/360,0)=0,0,(((B13-VAL_DATE)/360)-MAX((13>0)*(D13-VAL_DATE)/360,0))/(((E13-VAL_DATE)/360)-MAX((13>0)*(D13-VAL_DATE)/360,0))))*((B13-VAL_DATE)/360))),INDEX($L$8:$L$73,MATCH(B13,$K$8:$K$73,1))*EXP(-(F13/100)*(B13-D13)/365)),"") | H13: =-LN(G13)/C13*100 | K13: ='[USD_SOFR_Curve_Bloomberg_Pricer.xlsx]Curve_Interface'!$K$14 | L13: ='[USD_SOFR_Curve_Bloomberg_Pricer.xlsx]Curve_Interface'!$L$14 | N13: first tenor date | O13: =IF($K$9="","",$K$9)
A14: 5 | B14: =EDATE($F$7,3*4) | C14: =(B14-VAL_DATE)/365 | D14: =INDEX($K$8:$K$73,MATCH(B14,$K$8:$K$73,1)) | E14: =INDEX($K$8:$K$73,MATCH(B14,$K$8:$K$73,1)+1) | F14: =-LN(INDEX($L$8:$L$73,MATCH(B14,$K$8:$K$73,1)+1)/INDEX($L$8:$L$73,MATCH(B14,$K$8:$K$73,1)))/((E14-D14)/365)*100 | G14: =IFERROR(IF($J$7="Piecewise Linear (Simple)",IF(((B14-VAL_DATE)/360)<=0,1,1/(1+(IF(MAX((14>0)*(D14-VAL_DATE)/360,0)<=0,IF(((E14-VAL_DATE)/360)<=0,0,(1/INDEX($L$8:$L$73,MATCH(B14,$K$8:$K$73,1)+1)-1)/((E14-VAL_DATE)/360)),IF(MAX((14>0)*(D14-VAL_DATE)/360,0)<=0,0,(1/INDEX($L$8:$L$73,MATCH(B14,$K$8:$K$73,1))-1)/MAX((14>0)*(D14-VAL_DATE)/360,0)))+(IF(((E14-VAL_DATE)/360)<=0,0,(1/INDEX($L$8:$L$73,MATCH(B14,$K$8:$K$73,1)+1)-1)/((E14-VAL_DATE)/360))-IF(MAX((14>0)*(D14-VAL_DATE)/360,0)<=0,IF(((E14-VAL_DATE)/360)<=0,0,(1/INDEX($L$8:$L$73,MATCH(B14,$K$8:$K$73,1)+1)-1)/((E14-VAL_DATE)/360)),IF(MAX((14>0)*(D14-VAL_DATE)/360,0)<=0,0,(1/INDEX($L$8:$L$73,MATCH(B14,$K$8:$K$73,1))-1)/MAX((14>0)*(D14-VAL_DATE)/360,0))))*IF(((E14-VAL_DATE)/360)-MAX((14>0)*(D14-VAL_DATE)/360,0)=0,0,(((B14-VAL_DATE)/360)-MAX((14>0)*(D14-VAL_DATE)/360,0))/(((E14-VAL_DATE)/360)-MAX((14>0)*(D14-VAL_DATE)/360,0))))*((B14-VAL_DATE)/360))),INDEX($L$8:$L$73,MATCH(B14,$K$8:$K$73,1))*EXP(-(F14/100)*(B14-D14)/365)),"") | H14: =-LN(G14)/C14*100 | K14: ='[USD_SOFR_Curve_Bloomberg_Pricer.xlsx]Curve_Interface'!$K$15 | L14: ='[USD_SOFR_Curve_Bloomberg_Pricer.xlsx]Curve_Interface'!$L$15 | N14: DF monotone? | O14: =IF(COUNT($L$8:$L$73)<2,"",IF(SUMPRODUCT(--($L$9:$L$73>$L$8:$L$72))=0,"ok","NOT DECREASING"))
A15: 6 | B15: =EDATE($F$7,3*5) | C15: =(B15-VAL_DATE)/365 | D15: =INDEX($K$8:$K$73,MATCH(B15,$K$8:$K$73,1)) | E15: =INDEX($K$8:$K$73,MATCH(B15,$K$8:$K$73,1)+1) | F15: =-LN(INDEX($L$8:$L$73,MATCH(B15,$K$8:$K$73,1)+1)/INDEX($L$8:$L$73,MATCH(B15,$K$8:$K$73,1)))/((E15-D15)/365)*100 | G15: =IFERROR(IF($J$7="Piecewise Linear (Simple)",IF(((B15-VAL_DATE)/360)<=0,1,1/(1+(IF(MAX((15>0)*(D15-VAL_DATE)/360,0)<=0,IF(((E15-VAL_DATE)/360)<=0,0,(1/INDEX($L$8:$L$73,MATCH(B15,$K$8:$K$73,1)+1)-1)/((E15-VAL_DATE)/360)),IF(MAX((15>0)*(D15-VAL_DATE)/360,0)<=0,0,(1/INDEX($L$8:$L$73,MATCH(B15,$K$8:$K$73,1))-1)/MAX((15>0)*(D15-VAL_DATE)/360,0)))+(IF(((E15-VAL_DATE)/360)<=0,0,(1/INDEX($L$8:$L$73,MATCH(B15,$K$8:$K$73,1)+1)-1)/((E15-VAL_DATE)/360))-IF(MAX((15>0)*(D15-VAL_DATE)/360,0)<=0,IF(((E15-VAL_DATE)/360)<=0,0,(1/INDEX($L$8:$L$73,MATCH(B15,$K$8:$K$73,1)+1)-1)/((E15-VAL_DATE)/360)),IF(MAX((15>0)*(D15-VAL_DATE)/360,0)<=0,0,(1/INDEX($L$8:$L$73,MATCH(B15,$K$8:$K$73,1))-1)/MAX((15>0)*(D15-VAL_DATE)/360,0))))*IF(((E15-VAL_DATE)/360)-MAX((15>0)*(D15-VAL_DATE)/360,0)=0,0,(((B15-VAL_DATE)/360)-MAX((15>0)*(D15-VAL_DATE)/360,0))/(((E15-VAL_DATE)/360)-MAX((15>0)*(D15-VAL_DATE)/360,0))))*((B15-VAL_DATE)/360))),INDEX($L$8:$L$73,MATCH(B15,$K$8:$K$73,1))*EXP(-(F15/100)*(B15-D15)/365)),"") | H15: =-LN(G15)/C15*100 | K15: ='[USD_SOFR_Curve_Bloomberg_Pricer.xlsx]Curve_Interface'!$K$16 | L15: ='[USD_SOFR_Curve_Bloomberg_Pricer.xlsx]Curve_Interface'!$L$16 | N15: =IF(O9=0,"LINK NOT RESOLVING - open USD_SOFR_Curve_Bloomberg_Pricer.xlsx",IF(ABS(O12-1)>0.000001,"ROW 8 IS NOT THE ANCHOR - check the offset",IF(O13-VAL_DATE>14,"FIRST TENOR LOOKS WRONG - expected about a week after the curve date",IF(O9<60,"FEWER PILLARS THAN EXPECTED - check the source range","link ok"))))
A16: 7 | B16: =EDATE($F$7,3*6) | C16: =(B16-VAL_DATE)/365 | D16: =INDEX($K$8:$K$73,MATCH(B16,$K$8:$K$73,1)) | E16: =INDEX($K$8:$K$73,MATCH(B16,$K$8:$K$73,1)+1) | F16: =-LN(INDEX($L$8:$L$73,MATCH(B16,$K$8:$K$73,1)+1)/INDEX($L$8:$L$73,MATCH(B16,$K$8:$K$73,1)))/((E16-D16)/365)*100 | G16: =IFERROR(IF($J$7="Piecewise Linear (Simple)",IF(((B16-VAL_DATE)/360)<=0,1,1/(1+(IF(MAX((16>0)*(D16-VAL_DATE)/360,0)<=0,IF(((E16-VAL_DATE)/360)<=0,0,(1/INDEX($L$8:$L$73,MATCH(B16,$K$8:$K$73,1)+1)-1)/((E16-VAL_DATE)/360)),IF(MAX((16>0)*(D16-VAL_DATE)/360,0)<=0,0,(1/INDEX($L$8:$L$73,MATCH(B16,$K$8:$K$73,1))-1)/MAX((16>0)*(D16-VAL_DATE)/360,0)))+(IF(((E16-VAL_DATE)/360)<=0,0,(1/INDEX($L$8:$L$73,MATCH(B16,$K$8:$K$73,1)+1)-1)/((E16-VAL_DATE)/360))-IF(MAX((16>0)*(D16-VAL_DATE)/360,0)<=0,IF(((E16-VAL_DATE)/360)<=0,0,(1/INDEX($L$8:$L$73,MATCH(B16,$K$8:$K$73,1)+1)-1)/((E16-VAL_DATE)/360)),IF(MAX((16>0)*(D16-VAL_DATE)/360,0)<=0,0,(1/INDEX($L$8:$L$73,MATCH(B16,$K$8:$K$73,1))-1)/MAX((16>0)*(D16-VAL_DATE)/360,0))))*IF(((E16-VAL_DATE)/360)-MAX((16>0)*(D16-VAL_DATE)/360,0)=0,0,(((B16-VAL_DATE)/360)-MAX((16>0)*(D16-VAL_DATE)/360,0))/(((E16-VAL_DATE)/360)-MAX((16>0)*(D16-VAL_DATE)/360,0))))*((B16-VAL_DATE)/360))),INDEX($L$8:$L$73,MATCH(B16,$K$8:$K$73,1))*EXP(-(F16/100)*(B16-D16)/365)),"") | H16: =-LN(G16)/C16*100 | K16: ='[USD_SOFR_Curve_Bloomberg_Pricer.xlsx]Curve_Interface'!$K$17 | L16: ='[USD_SOFR_Curve_Bloomberg_Pricer.xlsx]Curve_Interface'!$L$17 | N16: Live only while the curve workbook is OPEN. Closed, Excel serves the last cached values and the BDP pulls in the source do not refresh.
A17: 8 | B17: =EDATE($F$7,3*7) | C17: =(B17-VAL_DATE)/365 | D17: =INDEX($K$8:$K$73,MATCH(B17,$K$8:$K$73,1)) | E17: =INDEX($K$8:$K$73,MATCH(B17,$K$8:$K$73,1)+1) | F17: =-LN(INDEX($L$8:$L$73,MATCH(B17,$K$8:$K$73,1)+1)/INDEX($L$8:$L$73,MATCH(B17,$K$8:$K$73,1)))/((E17-D17)/365)*100 | G17: =IFERROR(IF($J$7="Piecewise Linear (Simple)",IF(((B17-VAL_DATE)/360)<=0,1,1/(1+(IF(MAX((17>0)*(D17-VAL_DATE)/360,0)<=0,IF(((E17-VAL_DATE)/360)<=0,0,(1/INDEX($L$8:$L$73,MATCH(B17,$K$8:$K$73,1)+1)-1)/((E17-VAL_DATE)/360)),IF(MAX((17>0)*(D17-VAL_DATE)/360,0)<=0,0,(1/INDEX($L$8:$L$73,MATCH(B17,$K$8:$K$73,1))-1)/MAX((17>0)*(D17-VAL_DATE)/360,0)))+(IF(((E17-VAL_DATE)/360)<=0,0,(1/INDEX($L$8:$L$73,MATCH(B17,$K$8:$K$73,1)+1)-1)/((E17-VAL_DATE)/360))-IF(MAX((17>0)*(D17-VAL_DATE)/360,0)<=0,IF(((E17-VAL_DATE)/360)<=0,0,(1/INDEX($L$8:$L$73,MATCH(B17,$K$8:$K$73,1)+1)-1)/((E17-VAL_DATE)/360)),IF(MAX((17>0)*(D17-VAL_DATE)/360,0)<=0,0,(1/INDEX($L$8:$L$73,MATCH(B17,$K$8:$K$73,1))-1)/MAX((17>0)*(D17-VAL_DATE)/360,0))))*IF(((E17-VAL_DATE)/360)-MAX((17>0)*(D17-VAL_DATE)/360,0)=0,0,(((B17-VAL_DATE)/360)-MAX((17>0)*(D17-VAL_DATE)/360,0))/(((E17-VAL_DATE)/360)-MAX((17>0)*(D17-VAL_DATE)/360,0))))*((B17-VAL_DATE)/360))),INDEX($L$8:$L$73,MATCH(B17,$K$8:$K$73,1))*EXP(-(F17/100)*(B17-D17)/365)),"") | H17: =-LN(G17)/C17*100 | K17: ='[USD_SOFR_Curve_Bloomberg_Pricer.xlsx]Curve_Interface'!$K$18 | L17: ='[USD_SOFR_Curve_Bloomberg_Pricer.xlsx]Curve_Interface'!$L$18 | N17: Live only while the curve workbook is OPEN. Closed, Excel serves the last cached values and the BDP pulls in the source do not refresh.
A18: 9 | B18: =EDATE($F$7,3*8) | C18: =(B18-VAL_DATE)/365 | D18: =INDEX($K$8:$K$73,MATCH(B18,$K$8:$K$73,1)) | E18: =INDEX($K$8:$K$73,MATCH(B18,$K$8:$K$73,1)+1) | F18: =-LN(INDEX($L$8:$L$73,MATCH(B18,$K$8:$K$73,1)+1)/INDEX($L$8:$L$73,MATCH(B18,$K$8:$K$73,1)))/((E18-D18)/365)*100 | G18: =IFERROR(IF($J$7="Piecewise Linear (Simple)",IF(((B18-VAL_DATE)/360)<=0,1,1/(1+(IF(MAX((18>0)*(D18-VAL_DATE)/360,0)<=0,IF(((E18-VAL_DATE)/360)<=0,0,(1/INDEX($L$8:$L$73,MATCH(B18,$K$8:$K$73,1)+1)-1)/((E18-VAL_DATE)/360)),IF(MAX((18>0)*(D18-VAL_DATE)/360,0)<=0,0,(1/INDEX($L$8:$L$73,MATCH(B18,$K$8:$K$73,1))-1)/MAX((18>0)*(D18-VAL_DATE)/360,0)))+(IF(((E18-VAL_DATE)/360)<=0,0,(1/INDEX($L$8:$L$73,MATCH(B18,$K$8:$K$73,1)+1)-1)/((E18-VAL_DATE)/360))-IF(MAX((18>0)*(D18-VAL_DATE)/360,0)<=0,IF(((E18-VAL_DATE)/360)<=0,0,(1/INDEX($L$8:$L$73,MATCH(B18,$K$8:$K$73,1)+1)-1)/((E18-VAL_DATE)/360)),IF(MAX((18>0)*(D18-VAL_DATE)/360,0)<=0,0,(1/INDEX($L$8:$L$73,MATCH(B18,$K$8:$K$73,1))-1)/MAX((18>0)*(D18-VAL_DATE)/360,0))))*IF(((E18-VAL_DATE)/360)-MAX((18>0)*(D18-VAL_DATE)/360,0)=0,0,(((B18-VAL_DATE)/360)-MAX((18>0)*(D18-VAL_DATE)/360,0))/(((E18-VAL_DATE)/360)-MAX((18>0)*(D18-VAL_DATE)/360,0))))*((B18-VAL_DATE)/360))),INDEX($L$8:$L$73,MATCH(B18,$K$8:$K$73,1))*EXP(-(F18/100)*(B18-D18)/365)),"") | H18: =-LN(G18)/C18*100 | K18: ='[USD_SOFR_Curve_Bloomberg_Pricer.xlsx]Curve_Interface'!$K$19 | L18: ='[USD_SOFR_Curve_Bloomberg_Pricer.xlsx]Curve_Interface'!$L$19 | N18: Data > Edit Links > Change Source if the file moves.
A19: 10 | B19: =EDATE($F$7,3*9) | C19: =(B19-VAL_DATE)/365 | D19: =INDEX($K$8:$K$73,MATCH(B19,$K$8:$K$73,1)) | E19: =INDEX($K$8:$K$73,MATCH(B19,$K$8:$K$73,1)+1) | F19: =-LN(INDEX($L$8:$L$73,MATCH(B19,$K$8:$K$73,1)+1)/INDEX($L$8:$L$73,MATCH(B19,$K$8:$K$73,1)))/((E19-D19)/365)*100 | G19: =IFERROR(IF($J$7="Piecewise Linear (Simple)",IF(((B19-VAL_DATE)/360)<=0,1,1/(1+(IF(MAX((19>0)*(D19-VAL_DATE)/360,0)<=0,IF(((E19-VAL_DATE)/360)<=0,0,(1/INDEX($L$8:$L$73,MATCH(B19,$K$8:$K$73,1)+1)-1)/((E19-VAL_DATE)/360)),IF(MAX((19>0)*(D19-VAL_DATE)/360,0)<=0,0,(1/INDEX($L$8:$L$73,MATCH(B19,$K$8:$K$73,1))-1)/MAX((19>0)*(D19-VAL_DATE)/360,0)))+(IF(((E19-VAL_DATE)/360)<=0,0,(1/INDEX($L$8:$L$73,MATCH(B19,$K$8:$K$73,1)+1)-1)/((E19-VAL_DATE)/360))-IF(MAX((19>0)*(D19-VAL_DATE)/360,0)<=0,IF(((E19-VAL_DATE)/360)<=0,0,(1/INDEX($L$8:$L$73,MATCH(B19,$K$8:$K$73,1)+1)-1)/((E19-VAL_DATE)/360)),IF(MAX((19>0)*(D19-VAL_DATE)/360,0)<=0,0,(1/INDEX($L$8:$L$73,MATCH(B19,$K$8:$K$73,1))-1)/MAX((19>0)*(D19-VAL_DATE)/360,0))))*IF(((E19-VAL_DATE)/360)-MAX((19>0)*(D19-VAL_DATE)/360,0)=0,0,(((B19-VAL_DATE)/360)-MAX((19>0)*(D19-VAL_DATE)/360,0))/(((E19-VAL_DATE)/360)-MAX((19>0)*(D19-VAL_DATE)/360,0))))*((B19-VAL_DATE)/360))),INDEX($L$8:$L$73,MATCH(B19,$K$8:$K$73,1))*EXP(-(F19/100)*(B19-D19)/365)),"") | H19: =-LN(G19)/C19*100 | K19: ='[USD_SOFR_Curve_Bloomberg_Pricer.xlsx]Curve_Interface'!$K$20 | L19: ='[USD_SOFR_Curve_Bloomberg_Pricer.xlsx]Curve_Interface'!$L$20
A20: 11 | B20: =EDATE($F$7,3*10) | C20: =(B20-VAL_DATE)/365 | D20: =INDEX($K$8:$K$73,MATCH(B20,$K$8:$K$73,1)) | E20: =INDEX($K$8:$K$73,MATCH(B20,$K$8:$K$73,1)+1) | F20: =-LN(INDEX($L$8:$L$73,MATCH(B20,$K$8:$K$73,1)+1)/INDEX($L$8:$L$73,MATCH(B20,$K$8:$K$73,1)))/((E20-D20)/365)*100 | G20: =IFERROR(IF($J$7="Piecewise Linear (Simple)",IF(((B20-VAL_DATE)/360)<=0,1,1/(1+(IF(MAX((20>0)*(D20-VAL_DATE)/360,0)<=0,IF(((E20-VAL_DATE)/360)<=0,0,(1/INDEX($L$8:$L$73,MATCH(B20,$K$8:$K$73,1)+1)-1)/((E20-VAL_DATE)/360)),IF(MAX((20>0)*(D20-VAL_DATE)/360,0)<=0,0,(1/INDEX($L$8:$L$73,MATCH(B20,$K$8:$K$73,1))-1)/MAX((20>0)*(D20-VAL_DATE)/360,0)))+(IF(((E20-VAL_DATE)/360)<=0,0,(1/INDEX($L$8:$L$73,MATCH(B20,$K$8:$K$73,1)+1)-1)/((E20-VAL_DATE)/360))-IF(MAX((20>0)*(D20-VAL_DATE)/360,0)<=0,IF(((E20-VAL_DATE)/360)<=0,0,(1/INDEX($L$8:$L$73,MATCH(B20,$K$8:$K$73,1)+1)-1)/((E20-VAL_DATE)/360)),IF(MAX((20>0)*(D20-VAL_DATE)/360,0)<=0,0,(1/INDEX($L$8:$L$73,MATCH(B20,$K$8:$K$73,1))-1)/MAX((20>0)*(D20-VAL_DATE)/360,0))))*IF(((E20-VAL_DATE)/360)-MAX((20>0)*(D20-VAL_DATE)/360,0)=0,0,(((B20-VAL_DATE)/360)-MAX((20>0)*(D20-VAL_DATE)/360,0))/(((E20-VAL_DATE)/360)-MAX((20>0)*(D20-VAL_DATE)/360,0))))*((B20-VAL_DATE)/360))),INDEX($L$8:$L$73,MATCH(B20,$K$8:$K$73,1))*EXP(-(F20/100)*(B20-D20)/365)),"") | H20: =-LN(G20)/C20*100 | K20: ='[USD_SOFR_Curve_Bloomberg_Pricer.xlsx]Curve_Interface'!$K$21 | L20: ='[USD_SOFR_Curve_Bloomberg_Pricer.xlsx]Curve_Interface'!$L$21
A21: 12 | B21: =EDATE($F$7,3*11) | C21: =(B21-VAL_DATE)/365 | D21: =INDEX($K$8:$K$73,MATCH(B21,$K$8:$K$73,1)) | E21: =INDEX($K$8:$K$73,MATCH(B21,$K$8:$K$73,1)+1) | F21: =-LN(INDEX($L$8:$L$73,MATCH(B21,$K$8:$K$73,1)+1)/INDEX($L$8:$L$73,MATCH(B21,$K$8:$K$73,1)))/((E21-D21)/365)*100 | G21: =IFERROR(IF($J$7="Piecewise Linear (Simple)",IF(((B21-VAL_DATE)/360)<=0,1,1/(1+(IF(MAX((21>0)*(D21-VAL_DATE)/360,0)<=0,IF(((E21-VAL_DATE)/360)<=0,0,(1/INDEX($L$8:$L$73,MATCH(B21,$K$8:$K$73,1)+1)-1)/((E21-VAL_DATE)/360)),IF(MAX((21>0)*(D21-VAL_DATE)/360,0)<=0,0,(1/INDEX($L$8:$L$73,MATCH(B21,$K$8:$K$73,1))-1)/MAX((21>0)*(D21-VAL_DATE)/360,0)))+(IF(((E21-VAL_DATE)/360)<=0,0,(1/INDEX($L$8:$L$73,MATCH(B21,$K$8:$K$73,1)+1)-1)/((E21-VAL_DATE)/360))-IF(MAX((21>0)*(D21-VAL_DATE)/360,0)<=0,IF(((E21-VAL_DATE)/360)<=0,0,(1/INDEX($L$8:$L$73,MATCH(B21,$K$8:$K$73,1)+1)-1)/((E21-VAL_DATE)/360)),IF(MAX((21>0)*(D21-VAL_DATE)/360,0)<=0,0,(1/INDEX($L$8:$L$73,MATCH(B21,$K$8:$K$73,1))-1)/MAX((21>0)*(D21-VAL_DATE)/360,0))))*IF(((E21-VAL_DATE)/360)-MAX((21>0)*(D21-VAL_DATE)/360,0)=0,0,(((B21-VAL_DATE)/360)-MAX((21>0)*(D21-VAL_DATE)/360,0))/(((E21-VAL_DATE)/360)-MAX((21>0)*(D21-VAL_DATE)/360,0))))*((B21-VAL_DATE)/360))),INDEX($L$8:$L$73,MATCH(B21,$K$8:$K$73,1))*EXP(-(F21/100)*(B21-D21)/365)),"") | H21: =-LN(G21)/C21*100 | K21: ='[USD_SOFR_Curve_Bloomberg_Pricer.xlsx]Curve_Interface'!$K$22 | L21: ='[USD_SOFR_Curve_Bloomberg_Pricer.xlsx]Curve_Interface'!$L$22
A22: 13 | B22: =EDATE($F$7,3*12) | C22: =(B22-VAL_DATE)/365 | D22: =INDEX($K$8:$K$73,MATCH(B22,$K$8:$K$73,1)) | E22: =INDEX($K$8:$K$73,MATCH(B22,$K$8:$K$73,1)+1) | F22: =-LN(INDEX($L$8:$L$73,MATCH(B22,$K$8:$K$73,1)+1)/INDEX($L$8:$L$73,MATCH(B22,$K$8:$K$73,1)))/((E22-D22)/365)*100 | G22: =IFERROR(IF($J$7="Piecewise Linear (Simple)",IF(((B22-VAL_DATE)/360)<=0,1,1/(1+(IF(MAX((22>0)*(D22-VAL_DATE)/360,0)<=0,IF(((E22-VAL_DATE)/360)<=0,0,(1/INDEX($L$8:$L$73,MATCH(B22,$K$8:$K$73,1)+1)-1)/((E22-VAL_DATE)/360)),IF(MAX((22>0)*(D22-VAL_DATE)/360,0)<=0,0,(1/INDEX($L$8:$L$73,MATCH(B22,$K$8:$K$73,1))-1)/MAX((22>0)*(D22-VAL_DATE)/360,0)))+(IF(((E22-VAL_DATE)/360)<=0,0,(1/INDEX($L$8:$L$73,MATCH(B22,$K$8:$K$73,1)+1)-1)/((E22-VAL_DATE)/360))-IF(MAX((22>0)*(D22-VAL_DATE)/360,0)<=0,IF(((E22-VAL_DATE)/360)<=0,0,(1/INDEX($L$8:$L$73,MATCH(B22,$K$8:$K$73,1)+1)-1)/((E22-VAL_DATE)/360)),IF(MAX((22>0)*(D22-VAL_DATE)/360,0)<=0,0,(1/INDEX($L$8:$L$73,MATCH(B22,$K$8:$K$73,1))-1)/MAX((22>0)*(D22-VAL_DATE)/360,0))))*IF(((E22-VAL_DATE)/360)-MAX((22>0)*(D22-VAL_DATE)/360,0)=0,0,(((B22-VAL_DATE)/360)-MAX((22>0)*(D22-VAL_DATE)/360,0))/(((E22-VAL_DATE)/360)-MAX((22>0)*(D22-VAL_DATE)/360,0))))*((B22-VAL_DATE)/360))),INDEX($L$8:$L$73,MATCH(B22,$K$8:$K$73,1))*EXP(-(F22/100)*(B22-D22)/365)),"") | H22: =-LN(G22)/C22*100 | K22: ='[USD_SOFR_Curve_Bloomberg_Pricer.xlsx]Curve_Interface'!$K$23 | L22: ='[USD_SOFR_Curve_Bloomberg_Pricer.xlsx]Curve_Interface'!$L$23
A23: 14 | B23: =EDATE($F$7,3*13) | C23: =(B23-VAL_DATE)/365 | D23: =INDEX($K$8:$K$73,MATCH(B23,$K$8:$K$73,1)) | E23: =INDEX($K$8:$K$73,MATCH(B23,$K$8:$K$73,1)+1) | F23: =-LN(INDEX($L$8:$L$73,MATCH(B23,$K$8:$K$73,1)+1)/INDEX($L$8:$L$73,MATCH(B23,$K$8:$K$73,1)))/((E23-D23)/365)*100 | G23: =IFERROR(IF($J$7="Piecewise Linear (Simple)",IF(((B23-VAL_DATE)/360)<=0,1,1/(1+(IF(MAX((23>0)*(D23-VAL_DATE)/360,0)<=0,IF(((E23-VAL_DATE)/360)<=0,0,(1/INDEX($L$8:$L$73,MATCH(B23,$K$8:$K$73,1)+1)-1)/((E23-VAL_DATE)/360)),IF(MAX((23>0)*(D23-VAL_DATE)/360,0)<=0,0,(1/INDEX($L$8:$L$73,MATCH(B23,$K$8:$K$73,1))-1)/MAX((23>0)*(D23-VAL_DATE)/360,0)))+(IF(((E23-VAL_DATE)/360)<=0,0,(1/INDEX($L$8:$L$73,MATCH(B23,$K$8:$K$73,1)+1)-1)/((E23-VAL_DATE)/360))-IF(MAX((23>0)*(D23-VAL_DATE)/360,0)<=0,IF(((E23-VAL_DATE)/360)<=0,0,(1/INDEX($L$8:$L$73,MATCH(B23,$K$8:$K$73,1)+1)-1)/((E23-VAL_DATE)/360)),IF(MAX((23>0)*(D23-VAL_DATE)/360,0)<=0,0,(1/INDEX($L$8:$L$73,MATCH(B23,$K$8:$K$73,1))-1)/MAX((23>0)*(D23-VAL_DATE)/360,0))))*IF(((E23-VAL_DATE)/360)-MAX((23>0)*(D23-VAL_DATE)/360,0)=0,0,(((B23-VAL_DATE)/360)-MAX((23>0)*(D23-VAL_DATE)/360,0))/(((E23-VAL_DATE)/360)-MAX((23>0)*(D23-VAL_DATE)/360,0))))*((B23-VAL_DATE)/360))),INDEX($L$8:$L$73,MATCH(B23,$K$8:$K$73,1))*EXP(-(F23/100)*(B23-D23)/365)),"") | H23: =-LN(G23)/C23*100 | K23: ='[USD_SOFR_Curve_Bloomberg_Pricer.xlsx]Curve_Interface'!$K$24 | L23: ='[USD_SOFR_Curve_Bloomberg_Pricer.xlsx]Curve_Interface'!$L$24
A24: 15 | B24: =EDATE($F$7,3*14) | C24: =(B24-VAL_DATE)/365 | D24: =INDEX($K$8:$K$73,MATCH(B24,$K$8:$K$73,1)) | E24: =INDEX($K$8:$K$73,MATCH(B24,$K$8:$K$73,1)+1) | F24: =-LN(INDEX($L$8:$L$73,MATCH(B24,$K$8:$K$73,1)+1)/INDEX($L$8:$L$73,MATCH(B24,$K$8:$K$73,1)))/((E24-D24)/365)*100 | G24: =IFERROR(IF($J$7="Piecewise Linear (Simple)",IF(((B24-VAL_DATE)/360)<=0,1,1/(1+(IF(MAX((24>0)*(D24-VAL_DATE)/360,0)<=0,IF(((E24-VAL_DATE)/360)<=0,0,(1/INDEX($L$8:$L$73,MATCH(B24,$K$8:$K$73,1)+1)-1)/((E24-VAL_DATE)/360)),IF(MAX((24>0)*(D24-VAL_DATE)/360,0)<=0,0,(1/INDEX($L$8:$L$73,MATCH(B24,$K$8:$K$73,1))-1)/MAX((24>0)*(D24-VAL_DATE)/360,0)))+(IF(((E24-VAL_DATE)/360)<=0,0,(1/INDEX($L$8:$L$73,MATCH(B24,$K$8:$K$73,1)+1)-1)/((E24-VAL_DATE)/360))-IF(MAX((24>0)*(D24-VAL_DATE)/360,0)<=0,IF(((E24-VAL_DATE)/360)<=0,0,(1/INDEX($L$8:$L$73,MATCH(B24,$K$8:$K$73,1)+1)-1)/((E24-VAL_DATE)/360)),IF(MAX((24>0)*(D24-VAL_DATE)/360,0)<=0,0,(1/INDEX($L$8:$L$73,MATCH(B24,$K$8:$K$73,1))-1)/MAX((24>0)*(D24-VAL_DATE)/360,0))))*IF(((E24-VAL_DATE)/360)-MAX((24>0)*(D24-VAL_DATE)/360,0)=0,0,(((B24-VAL_DATE)/360)-MAX((24>0)*(D24-VAL_DATE)/360,0))/(((E24-VAL_DATE)/360)-MAX((24>0)*(D24-VAL_DATE)/360,0))))*((B24-VAL_DATE)/360))),INDEX($L$8:$L$73,MATCH(B24,$K$8:$K$73,1))*EXP(-(F24/100)*(B24-D24)/365)),"") | H24: =-LN(G24)/C24*100 | K24: ='[USD_SOFR_Curve_Bloomberg_Pricer.xlsx]Curve_Interface'!$K$25 | L24: ='[USD_SOFR_Curve_Bloomberg_Pricer.xlsx]Curve_Interface'!$L$25
A25: 16 | B25: =EDATE($F$7,3*15) | C25: =(B25-VAL_DATE)/365 | D25: =INDEX($K$8:$K$73,MATCH(B25,$K$8:$K$73,1)) | E25: =INDEX($K$8:$K$73,MATCH(B25,$K$8:$K$73,1)+1) | F25: =-LN(INDEX($L$8:$L$73,MATCH(B25,$K$8:$K$73,1)+1)/INDEX($L$8:$L$73,MATCH(B25,$K$8:$K$73,1)))/((E25-D25)/365)*100 | G25: =IFERROR(IF($J$7="Piecewise Linear (Simple)",IF(((B25-VAL_DATE)/360)<=0,1,1/(1+(IF(MAX((25>0)*(D25-VAL_DATE)/360,0)<=0,IF(((E25-VAL_DATE)/360)<=0,0,(1/INDEX($L$8:$L$73,MATCH(B25,$K$8:$K$73,1)+1)-1)/((E25-VAL_DATE)/360)),IF(MAX((25>0)*(D25-VAL_DATE)/360,0)<=0,0,(1/INDEX($L$8:$L$73,MATCH(B25,$K$8:$K$73,1))-1)/MAX((25>0)*(D25-VAL_DATE)/360,0)))+(IF(((E25-VAL_DATE)/360)<=0,0,(1/INDEX($L$8:$L$73,MATCH(B25,$K$8:$K$73,1)+1)-1)/((E25-VAL_DATE)/360))-IF(MAX((25>0)*(D25-VAL_DATE)/360,0)<=0,IF(((E25-VAL_DATE)/360)<=0,0,(1/INDEX($L$8:$L$73,MATCH(B25,$K$8:$K$73,1)+1)-1)/((E25-VAL_DATE)/360)),IF(MAX((25>0)*(D25-VAL_DATE)/360,0)<=0,0,(1/INDEX($L$8:$L$73,MATCH(B25,$K$8:$K$73,1))-1)/MAX((25>0)*(D25-VAL_DATE)/360,0))))*IF(((E25-VAL_DATE)/360)-MAX((25>0)*(D25-VAL_DATE)/360,0)=0,0,(((B25-VAL_DATE)/360)-MAX((25>0)*(D25-VAL_DATE)/360,0))/(((E25-VAL_DATE)/360)-MAX((25>0)*(D25-VAL_DATE)/360,0))))*((B25-VAL_DATE)/360))),INDEX($L$8:$L$73,MATCH(B25,$K$8:$K$73,1))*EXP(-(F25/100)*(B25-D25)/365)),"") | H25: =-LN(G25)/C25*100 | K25: ='[USD_SOFR_Curve_Bloomberg_Pricer.xlsx]Curve_Interface'!$K$26 | L25: ='[USD_SOFR_Curve_Bloomberg_Pricer.xlsx]Curve_Interface'!$L$26
A26: 17 | B26: =EDATE($F$7,3*16) | C26: =(B26-VAL_DATE)/365 | D26: =INDEX($K$8:$K$73,MATCH(B26,$K$8:$K$73,1)) | E26: =INDEX($K$8:$K$73,MATCH(B26,$K$8:$K$73,1)+1) | F26: =-LN(INDEX($L$8:$L$73,MATCH(B26,$K$8:$K$73,1)+1)/INDEX($L$8:$L$73,MATCH(B26,$K$8:$K$73,1)))/((E26-D26)/365)*100 | G26: =IFERROR(IF($J$7="Piecewise Linear (Simple)",IF(((B26-VAL_DATE)/360)<=0,1,1/(1+(IF(MAX((26>0)*(D26-VAL_DATE)/360,0)<=0,IF(((E26-VAL_DATE)/360)<=0,0,(1/INDEX($L$8:$L$73,MATCH(B26,$K$8:$K$73,1)+1)-1)/((E26-VAL_DATE)/360)),IF(MAX((26>0)*(D26-VAL_DATE)/360,0)<=0,0,(1/INDEX($L$8:$L$73,MATCH(B26,$K$8:$K$73,1))-1)/MAX((26>0)*(D26-VAL_DATE)/360,0)))+(IF(((E26-VAL_DATE)/360)<=0,0,(1/INDEX($L$8:$L$73,MATCH(B26,$K$8:$K$73,1)+1)-1)/((E26-VAL_DATE)/360))-IF(MAX((26>0)*(D26-VAL_DATE)/360,0)<=0,IF(((E26-VAL_DATE)/360)<=0,0,(1/INDEX($L$8:$L$73,MATCH(B26,$K$8:$K$73,1)+1)-1)/((E26-VAL_DATE)/360)),IF(MAX((26>0)*(D26-VAL_DATE)/360,0)<=0,0,(1/INDEX($L$8:$L$73,MATCH(B26,$K$8:$K$73,1))-1)/MAX((26>0)*(D26-VAL_DATE)/360,0))))*IF(((E26-VAL_DATE)/360)-MAX((26>0)*(D26-VAL_DATE)/360,0)=0,0,(((B26-VAL_DATE)/360)-MAX((26>0)*(D26-VAL_DATE)/360,0))/(((E26-VAL_DATE)/360)-MAX((26>0)*(D26-VAL_DATE)/360,0))))*((B26-VAL_DATE)/360))),INDEX($L$8:$L$73,MATCH(B26,$K$8:$K$73,1))*EXP(-(F26/100)*(B26-D26)/365)),"") | H26: =-LN(G26)/C26*100 | K26: ='[USD_SOFR_Curve_Bloomberg_Pricer.xlsx]Curve_Interface'!$K$27 | L26: ='[USD_SOFR_Curve_Bloomberg_Pricer.xlsx]Curve_Interface'!$L$27
A27: 18 | B27: =EDATE($F$7,3*17) | C27: =(B27-VAL_DATE)/365 | D27: =INDEX($K$8:$K$73,MATCH(B27,$K$8:$K$73,1)) | E27: =INDEX($K$8:$K$73,MATCH(B27,$K$8:$K$73,1)+1) | F27: =-LN(INDEX($L$8:$L$73,MATCH(B27,$K$8:$K$73,1)+1)/INDEX($L$8:$L$73,MATCH(B27,$K$8:$K$73,1)))/((E27-D27)/365)*100 | G27: =IFERROR(IF($J$7="Piecewise Linear (Simple)",IF(((B27-VAL_DATE)/360)<=0,1,1/(1+(IF(MAX((27>0)*(D27-VAL_DATE)/360,0)<=0,IF(((E27-VAL_DATE)/360)<=0,0,(1/INDEX($L$8:$L$73,MATCH(B27,$K$8:$K$73,1)+1)-1)/((E27-VAL_DATE)/360)),IF(MAX((27>0)*(D27-VAL_DATE)/360,0)<=0,0,(1/INDEX($L$8:$L$73,MATCH(B27,$K$8:$K$73,1))-1)/MAX((27>0)*(D27-VAL_DATE)/360,0)))+(IF(((E27-VAL_DATE)/360)<=0,0,(1/INDEX($L$8:$L$73,MATCH(B27,$K$8:$K$73,1)+1)-1)/((E27-VAL_DATE)/360))-IF(MAX((27>0)*(D27-VAL_DATE)/360,0)<=0,IF(((E27-VAL_DATE)/360)<=0,0,(1/INDEX($L$8:$L$73,MATCH(B27,$K$8:$K$73,1)+1)-1)/((E27-VAL_DATE)/360)),IF(MAX((27>0)*(D27-VAL_DATE)/360,0)<=0,0,(1/INDEX($L$8:$L$73,MATCH(B27,$K$8:$K$73,1))-1)/MAX((27>0)*(D27-VAL_DATE)/360,0))))*IF(((E27-VAL_DATE)/360)-MAX((27>0)*(D27-VAL_DATE)/360,0)=0,0,(((B27-VAL_DATE)/360)-MAX((27>0)*(D27-VAL_DATE)/360,0))/(((E27-VAL_DATE)/360)-MAX((27>0)*(D27-VAL_DATE)/360,0))))*((B27-VAL_DATE)/360))),INDEX($L$8:$L$73,MATCH(B27,$K$8:$K$73,1))*EXP(-(F27/100)*(B27-D27)/365)),"") | H27: =-LN(G27)/C27*100 | K27: ='[USD_SOFR_Curve_Bloomberg_Pricer.xlsx]Curve_Interface'!$K$28 | L27: ='[USD_SOFR_Curve_Bloomberg_Pricer.xlsx]Curve_Interface'!$L$28
A28: 19 | B28: =EDATE($F$7,3*18) | C28: =(B28-VAL_DATE)/365 | D28: =INDEX($K$8:$K$73,MATCH(B28,$K$8:$K$73,1)) | E28: =INDEX($K$8:$K$73,MATCH(B28,$K$8:$K$73,1)+1) | F28: =-LN(INDEX($L$8:$L$73,MATCH(B28,$K$8:$K$73,1)+1)/INDEX($L$8:$L$73,MATCH(B28,$K$8:$K$73,1)))/((E28-D28)/365)*100 | G28: =IFERROR(IF($J$7="Piecewise Linear (Simple)",IF(((B28-VAL_DATE)/360)<=0,1,1/(1+(IF(MAX((28>0)*(D28-VAL_DATE)/360,0)<=0,IF(((E28-VAL_DATE)/360)<=0,0,(1/INDEX($L$8:$L$73,MATCH(B28,$K$8:$K$73,1)+1)-1)/((E28-VAL_DATE)/360)),IF(MAX((28>0)*(D28-VAL_DATE)/360,0)<=0,0,(1/INDEX($L$8:$L$73,MATCH(B28,$K$8:$K$73,1))-1)/MAX((28>0)*(D28-VAL_DATE)/360,0)))+(IF(((E28-VAL_DATE)/360)<=0,0,(1/INDEX($L$8:$L$73,MATCH(B28,$K$8:$K$73,1)+1)-1)/((E28-VAL_DATE)/360))-IF(MAX((28>0)*(D28-VAL_DATE)/360,0)<=0,IF(((E28-VAL_DATE)/360)<=0,0,(1/INDEX($L$8:$L$73,MATCH(B28,$K$8:$K$73,1)+1)-1)/((E28-VAL_DATE)/360)),IF(MAX((28>0)*(D28-VAL_DATE)/360,0)<=0,0,(1/INDEX($L$8:$L$73,MATCH(B28,$K$8:$K$73,1))-1)/MAX((28>0)*(D28-VAL_DATE)/360,0))))*IF(((E28-VAL_DATE)/360)-MAX((28>0)*(D28-VAL_DATE)/360,0)=0,0,(((B28-VAL_DATE)/360)-MAX((28>0)*(D28-VAL_DATE)/360,0))/(((E28-VAL_DATE)/360)-MAX((28>0)*(D28-VAL_DATE)/360,0))))*((B28-VAL_DATE)/360))),INDEX($L$8:$L$73,MATCH(B28,$K$8:$K$73,1))*EXP(-(F28/100)*(B28-D28)/365)),"") | H28: =-LN(G28)/C28*100 | K28: ='[USD_SOFR_Curve_Bloomberg_Pricer.xlsx]Curve_Interface'!$K$29 | L28: ='[USD_SOFR_Curve_Bloomberg_Pricer.xlsx]Curve_Interface'!$L$29
A29: 20 | B29: =EDATE($F$7,3*19) | C29: =(B29-VAL_DATE)/365 | D29: =INDEX($K$8:$K$73,MATCH(B29,$K$8:$K$73,1)) | E29: =INDEX($K$8:$K$73,MATCH(B29,$K$8:$K$73,1)+1) | F29: =-LN(INDEX($L$8:$L$73,MATCH(B29,$K$8:$K$73,1)+1)/INDEX($L$8:$L$73,MATCH(B29,$K$8:$K$73,1)))/((E29-D29)/365)*100 | G29: =IFERROR(IF($J$7="Piecewise Linear (Simple)",IF(((B29-VAL_DATE)/360)<=0,1,1/(1+(IF(MAX((29>0)*(D29-VAL_DATE)/360,0)<=0,IF(((E29-VAL_DATE)/360)<=0,0,(1/INDEX($L$8:$L$73,MATCH(B29,$K$8:$K$73,1)+1)-1)/((E29-VAL_DATE)/360)),IF(MAX((29>0)*(D29-VAL_DATE)/360,0)<=0,0,(1/INDEX($L$8:$L$73,MATCH(B29,$K$8:$K$73,1))-1)/MAX((29>0)*(D29-VAL_DATE)/360,0)))+(IF(((E29-VAL_DATE)/360)<=0,0,(1/INDEX($L$8:$L$73,MATCH(B29,$K$8:$K$73,1)+1)-1)/((E29-VAL_DATE)/360))-IF(MAX((29>0)*(D29-VAL_DATE)/360,0)<=0,IF(((E29-VAL_DATE)/360)<=0,0,(1/INDEX($L$8:$L$73,MATCH(B29,$K$8:$K$73,1)+1)-1)/((E29-VAL_DATE)/360)),IF(MAX((29>0)*(D29-VAL_DATE)/360,0)<=0,0,(1/INDEX($L$8:$L$73,MATCH(B29,$K$8:$K$73,1))-1)/MAX((29>0)*(D29-VAL_DATE)/360,0))))*IF(((E29-VAL_DATE)/360)-MAX((29>0)*(D29-VAL_DATE)/360,0)=0,0,(((B29-VAL_DATE)/360)-MAX((29>0)*(D29-VAL_DATE)/360,0))/(((E29-VAL_DATE)/360)-MAX((29>0)*(D29-VAL_DATE)/360,0))))*((B29-VAL_DATE)/360))),INDEX($L$8:$L$73,MATCH(B29,$K$8:$K$73,1))*EXP(-(F29/100)*(B29-D29)/365)),"") | H29: =-LN(G29)/C29*100 | K29: ='[USD_SOFR_Curve_Bloomberg_Pricer.xlsx]Curve_Interface'!$K$30 | L29: ='[USD_SOFR_Curve_Bloomberg_Pricer.xlsx]Curve_Interface'!$L$30
A30: 21 | B30: =EDATE($F$7,3*20) | C30: =(B30-VAL_DATE)/365 | D30: =INDEX($K$8:$K$73,MATCH(B30,$K$8:$K$73,1)) | E30: =INDEX($K$8:$K$73,MATCH(B30,$K$8:$K$73,1)+1) | F30: =-LN(INDEX($L$8:$L$73,MATCH(B30,$K$8:$K$73,1)+1)/INDEX($L$8:$L$73,MATCH(B30,$K$8:$K$73,1)))/((E30-D30)/365)*100 | G30: =IFERROR(IF($J$7="Piecewise Linear (Simple)",IF(((B30-VAL_DATE)/360)<=0,1,1/(1+(IF(MAX((30>0)*(D30-VAL_DATE)/360,0)<=0,IF(((E30-VAL_DATE)/360)<=0,0,(1/INDEX($L$8:$L$73,MATCH(B30,$K$8:$K$73,1)+1)-1)/((E30-VAL_DATE)/360)),IF(MAX((30>0)*(D30-VAL_DATE)/360,0)<=0,0,(1/INDEX($L$8:$L$73,MATCH(B30,$K$8:$K$73,1))-1)/MAX((30>0)*(D30-VAL_DATE)/360,0)))+(IF(((E30-VAL_DATE)/360)<=0,0,(1/INDEX($L$8:$L$73,MATCH(B30,$K$8:$K$73,1)+1)-1)/((E30-VAL_DATE)/360))-IF(MAX((30>0)*(D30-VAL_DATE)/360,0)<=0,IF(((E30-VAL_DATE)/360)<=0,0,(1/INDEX($L$8:$L$73,MATCH(B30,$K$8:$K$73,1)+1)-1)/((E30-VAL_DATE)/360)),IF(MAX((30>0)*(D30-VAL_DATE)/360,0)<=0,0,(1/INDEX($L$8:$L$73,MATCH(B30,$K$8:$K$73,1))-1)/MAX((30>0)*(D30-VAL_DATE)/360,0))))*IF(((E30-VAL_DATE)/360)-MAX((30>0)*(D30-VAL_DATE)/360,0)=0,0,(((B30-VAL_DATE)/360)-MAX((30>0)*(D30-VAL_DATE)/360,0))/(((E30-VAL_DATE)/360)-MAX((30>0)*(D30-VAL_DATE)/360,0))))*((B30-VAL_DATE)/360))),INDEX($L$8:$L$73,MATCH(B30,$K$8:$K$73,1))*EXP(-(F30/100)*(B30-D30)/365)),"") | H30: =-LN(G30)/C30*100 | K30: ='[USD_SOFR_Curve_Bloomberg_Pricer.xlsx]Curve_Interface'!$K$31 | L30: ='[USD_SOFR_Curve_Bloomberg_Pricer.xlsx]Curve_Interface'!$L$31
A31: 22 | B31: =EDATE($F$7,3*21) | C31: =(B31-VAL_DATE)/365 | D31: =INDEX($K$8:$K$73,MATCH(B31,$K$8:$K$73,1)) | E31: =INDEX($K$8:$K$73,MATCH(B31,$K$8:$K$73,1)+1) | F31: =-LN(INDEX($L$8:$L$73,MATCH(B31,$K$8:$K$73,1)+1)/INDEX($L$8:$L$73,MATCH(B31,$K$8:$K$73,1)))/((E31-D31)/365)*100 | G31: =IFERROR(IF($J$7="Piecewise Linear (Simple)",IF(((B31-VAL_DATE)/360)<=0,1,1/(1+(IF(MAX((31>0)*(D31-VAL_DATE)/360,0)<=0,IF(((E31-VAL_DATE)/360)<=0,0,(1/INDEX($L$8:$L$73,MATCH(B31,$K$8:$K$73,1)+1)-1)/((E31-VAL_DATE)/360)),IF(MAX((31>0)*(D31-VAL_DATE)/360,0)<=0,0,(1/INDEX($L$8:$L$73,MATCH(B31,$K$8:$K$73,1))-1)/MAX((31>0)*(D31-VAL_DATE)/360,0)))+(IF(((E31-VAL_DATE)/360)<=0,0,(1/INDEX($L$8:$L$73,MATCH(B31,$K$8:$K$73,1)+1)-1)/((E31-VAL_DATE)/360))-IF(MAX((31>0)*(D31-VAL_DATE)/360,0)<=0,IF(((E31-VAL_DATE)/360)<=0,0,(1/INDEX($L$8:$L$73,MATCH(B31,$K$8:$K$73,1)+1)-1)/((E31-VAL_DATE)/360)),IF(MAX((31>0)*(D31-VAL_DATE)/360,0)<=0,0,(1/INDEX($L$8:$L$73,MATCH(B31,$K$8:$K$73,1))-1)/MAX((31>0)*(D31-VAL_DATE)/360,0))))*IF(((E31-VAL_DATE)/360)-MAX((31>0)*(D31-VAL_DATE)/360,0)=0,0,(((B31-VAL_DATE)/360)-MAX((31>0)*(D31-VAL_DATE)/360,0))/(((E31-VAL_DATE)/360)-MAX((31>0)*(D31-VAL_DATE)/360,0))))*((B31-VAL_DATE)/360))),INDEX($L$8:$L$73,MATCH(B31,$K$8:$K$73,1))*EXP(-(F31/100)*(B31-D31)/365)),"") | H31: =-LN(G31)/C31*100 | K31: ='[USD_SOFR_Curve_Bloomberg_Pricer.xlsx]Curve_Interface'!$K$32 | L31: ='[USD_SOFR_Curve_Bloomberg_Pricer.xlsx]Curve_Interface'!$L$32
A32: 23 | B32: =EDATE($F$7,3*22) | C32: =(B32-VAL_DATE)/365 | D32: =INDEX($K$8:$K$73,MATCH(B32,$K$8:$K$73,1)) | E32: =INDEX($K$8:$K$73,MATCH(B32,$K$8:$K$73,1)+1) | F32: =-LN(INDEX($L$8:$L$73,MATCH(B32,$K$8:$K$73,1)+1)/INDEX($L$8:$L$73,MATCH(B32,$K$8:$K$73,1)))/((E32-D32)/365)*100 | G32: =IFERROR(IF($J$7="Piecewise Linear (Simple)",IF(((B32-VAL_DATE)/360)<=0,1,1/(1+(IF(MAX((32>0)*(D32-VAL_DATE)/360,0)<=0,IF(((E32-VAL_DATE)/360)<=0,0,(1/INDEX($L$8:$L$73,MATCH(B32,$K$8:$K$73,1)+1)-1)/((E32-VAL_DATE)/360)),IF(MAX((32>0)*(D32-VAL_DATE)/360,0)<=0,0,(1/INDEX($L$8:$L$73,MATCH(B32,$K$8:$K$73,1))-1)/MAX((32>0)*(D32-VAL_DATE)/360,0)))+(IF(((E32-VAL_DATE)/360)<=0,0,(1/INDEX($L$8:$L$73,MATCH(B32,$K$8:$K$73,1)+1)-1)/((E32-VAL_DATE)/360))-IF(MAX((32>0)*(D32-VAL_DATE)/360,0)<=0,IF(((E32-VAL_DATE)/360)<=0,0,(1/INDEX($L$8:$L$73,MATCH(B32,$K$8:$K$73,1)+1)-1)/((E32-VAL_DATE)/360)),IF(MAX((32>0)*(D32-VAL_DATE)/360,0)<=0,0,(1/INDEX($L$8:$L$73,MATCH(B32,$K$8:$K$73,1))-1)/MAX((32>0)*(D32-VAL_DATE)/360,0))))*IF(((E32-VAL_DATE)/360)-MAX((32>0)*(D32-VAL_DATE)/360,0)=0,0,(((B32-VAL_DATE)/360)-MAX((32>0)*(D32-VAL_DATE)/360,0))/(((E32-VAL_DATE)/360)-MAX((32>0)*(D32-VAL_DATE)/360,0))))*((B32-VAL_DATE)/360))),INDEX($L$8:$L$73,MATCH(B32,$K$8:$K$73,1))*EXP(-(F32/100)*(B32-D32)/365)),"") | H32: =-LN(G32)/C32*100 | K32: ='[USD_SOFR_Curve_Bloomberg_Pricer.xlsx]Curve_Interface'!$K$33 | L32: ='[USD_SOFR_Curve_Bloomberg_Pricer.xlsx]Curve_Interface'!$L$33
A33: 24 | B33: =EDATE($F$7,3*23) | C33: =(B33-VAL_DATE)/365 | D33: =INDEX($K$8:$K$73,MATCH(B33,$K$8:$K$73,1)) | E33: =INDEX($K$8:$K$73,MATCH(B33,$K$8:$K$73,1)+1) | F33: =-LN(INDEX($L$8:$L$73,MATCH(B33,$K$8:$K$73,1)+1)/INDEX($L$8:$L$73,MATCH(B33,$K$8:$K$73,1)))/((E33-D33)/365)*100 | G33: =IFERROR(IF($J$7="Piecewise Linear (Simple)",IF(((B33-VAL_DATE)/360)<=0,1,1/(1+(IF(MAX((33>0)*(D33-VAL_DATE)/360,0)<=0,IF(((E33-VAL_DATE)/360)<=0,0,(1/INDEX($L$8:$L$73,MATCH(B33,$K$8:$K$73,1)+1)-1)/((E33-VAL_DATE)/360)),IF(MAX((33>0)*(D33-VAL_DATE)/360,0)<=0,0,(1/INDEX($L$8:$L$73,MATCH(B33,$K$8:$K$73,1))-1)/MAX((33>0)*(D33-VAL_DATE)/360,0)))+(IF(((E33-VAL_DATE)/360)<=0,0,(1/INDEX($L$8:$L$73,MATCH(B33,$K$8:$K$73,1)+1)-1)/((E33-VAL_DATE)/360))-IF(MAX((33>0)*(D33-VAL_DATE)/360,0)<=0,IF(((E33-VAL_DATE)/360)<=0,0,(1/INDEX($L$8:$L$73,MATCH(B33,$K$8:$K$73,1)+1)-1)/((E33-VAL_DATE)/360)),IF(MAX((33>0)*(D33-VAL_DATE)/360,0)<=0,0,(1/INDEX($L$8:$L$73,MATCH(B33,$K$8:$K$73,1))-1)/MAX((33>0)*(D33-VAL_DATE)/360,0))))*IF(((E33-VAL_DATE)/360)-MAX((33>0)*(D33-VAL_DATE)/360,0)=0,0,(((B33-VAL_DATE)/360)-MAX((33>0)*(D33-VAL_DATE)/360,0))/(((E33-VAL_DATE)/360)-MAX((33>0)*(D33-VAL_DATE)/360,0))))*((B33-VAL_DATE)/360))),INDEX($L$8:$L$73,MATCH(B33,$K$8:$K$73,1))*EXP(-(F33/100)*(B33-D33)/365)),"") | H33: =-LN(G33)/C33*100 | K33: ='[USD_SOFR_Curve_Bloomberg_Pricer.xlsx]Curve_Interface'!$K$34 | L33: ='[USD_SOFR_Curve_Bloomberg_Pricer.xlsx]Curve_Interface'!$L$34
A34: 25 | B34: =EDATE($F$7,3*24) | C34: =(B34-VAL_DATE)/365 | D34: =INDEX($K$8:$K$73,MATCH(B34,$K$8:$K$73,1)) | E34: =INDEX($K$8:$K$73,MATCH(B34,$K$8:$K$73,1)+1) | F34: =-LN(INDEX($L$8:$L$73,MATCH(B34,$K$8:$K$73,1)+1)/INDEX($L$8:$L$73,MATCH(B34,$K$8:$K$73,1)))/((E34-D34)/365)*100 | G34: =IFERROR(IF($J$7="Piecewise Linear (Simple)",IF(((B34-VAL_DATE)/360)<=0,1,1/(1+(IF(MAX((34>0)*(D34-VAL_DATE)/360,0)<=0,IF(((E34-VAL_DATE)/360)<=0,0,(1/INDEX($L$8:$L$73,MATCH(B34,$K$8:$K$73,1)+1)-1)/((E34-VAL_DATE)/360)),IF(MAX((34>0)*(D34-VAL_DATE)/360,0)<=0,0,(1/INDEX($L$8:$L$73,MATCH(B34,$K$8:$K$73,1))-1)/MAX((34>0)*(D34-VAL_DATE)/360,0)))+(IF(((E34-VAL_DATE)/360)<=0,0,(1/INDEX($L$8:$L$73,MATCH(B34,$K$8:$K$73,1)+1)-1)/((E34-VAL_DATE)/360))-IF(MAX((34>0)*(D34-VAL_DATE)/360,0)<=0,IF(((E34-VAL_DATE)/360)<=0,0,(1/INDEX($L$8:$L$73,MATCH(B34,$K$8:$K$73,1)+1)-1)/((E34-VAL_DATE)/360)),IF(MAX((34>0)*(D34-VAL_DATE)/360,0)<=0,0,(1/INDEX($L$8:$L$73,MATCH(B34,$K$8:$K$73,1))-1)/MAX((34>0)*(D34-VAL_DATE)/360,0))))*IF(((E34-VAL_DATE)/360)-MAX((34>0)*(D34-VAL_DATE)/360,0)=0,0,(((B34-VAL_DATE)/360)-MAX((34>0)*(D34-VAL_DATE)/360,0))/(((E34-VAL_DATE)/360)-MAX((34>0)*(D34-VAL_DATE)/360,0))))*((B34-VAL_DATE)/360))),INDEX($L$8:$L$73,MATCH(B34,$K$8:$K$73,1))*EXP(-(F34/100)*(B34-D34)/365)),"") | H34: =-LN(G34)/C34*100 | K34: ='[USD_SOFR_Curve_Bloomberg_Pricer.xlsx]Curve_Interface'!$K$35 | L34: ='[USD_SOFR_Curve_Bloomberg_Pricer.xlsx]Curve_Interface'!$L$35
A35: 26 | B35: =EDATE($F$7,3*25) | C35: =(B35-VAL_DATE)/365 | D35: =INDEX($K$8:$K$73,MATCH(B35,$K$8:$K$73,1)) | E35: =INDEX($K$8:$K$73,MATCH(B35,$K$8:$K$73,1)+1) | F35: =-LN(INDEX($L$8:$L$73,MATCH(B35,$K$8:$K$73,1)+1)/INDEX($L$8:$L$73,MATCH(B35,$K$8:$K$73,1)))/((E35-D35)/365)*100 | G35: =IFERROR(IF($J$7="Piecewise Linear (Simple)",IF(((B35-VAL_DATE)/360)<=0,1,1/(1+(IF(MAX((35>0)*(D35-VAL_DATE)/360,0)<=0,IF(((E35-VAL_DATE)/360)<=0,0,(1/INDEX($L$8:$L$73,MATCH(B35,$K$8:$K$73,1)+1)-1)/((E35-VAL_DATE)/360)),IF(MAX((35>0)*(D35-VAL_DATE)/360,0)<=0,0,(1/INDEX($L$8:$L$73,MATCH(B35,$K$8:$K$73,1))-1)/MAX((35>0)*(D35-VAL_DATE)/360,0)))+(IF(((E35-VAL_DATE)/360)<=0,0,(1/INDEX($L$8:$L$73,MATCH(B35,$K$8:$K$73,1)+1)-1)/((E35-VAL_DATE)/360))-IF(MAX((35>0)*(D35-VAL_DATE)/360,0)<=0,IF(((E35-VAL_DATE)/360)<=0,0,(1/INDEX($L$8:$L$73,MATCH(B35,$K$8:$K$73,1)+1)-1)/((E35-VAL_DATE)/360)),IF(MAX((35>0)*(D35-VAL_DATE)/360,0)<=0,0,(1/INDEX($L$8:$L$73,MATCH(B35,$K$8:$K$73,1))-1)/MAX((35>0)*(D35-VAL_DATE)/360,0))))*IF(((E35-VAL_DATE)/360)-MAX((35>0)*(D35-VAL_DATE)/360,0)=0,0,(((B35-VAL_DATE)/360)-MAX((35>0)*(D35-VAL_DATE)/360,0))/(((E35-VAL_DATE)/360)-MAX((35>0)*(D35-VAL_DATE)/360,0))))*((B35-VAL_DATE)/360))),INDEX($L$8:$L$73,MATCH(B35,$K$8:$K$73,1))*EXP(-(F35/100)*(B35-D35)/365)),"") | H35: =-LN(G35)/C35*100 | K35: ='[USD_SOFR_Curve_Bloomberg_Pricer.xlsx]Curve_Interface'!$K$36 | L35: ='[USD_SOFR_Curve_Bloomberg_Pricer.xlsx]Curve_Interface'!$L$36
A36: 27 | B36: =EDATE($F$7,3*26) | C36: =(B36-VAL_DATE)/365 | D36: =INDEX($K$8:$K$73,MATCH(B36,$K$8:$K$73,1)) | E36: =INDEX($K$8:$K$73,MATCH(B36,$K$8:$K$73,1)+1) | F36: =-LN(INDEX($L$8:$L$73,MATCH(B36,$K$8:$K$73,1)+1)/INDEX($L$8:$L$73,MATCH(B36,$K$8:$K$73,1)))/((E36-D36)/365)*100 | G36: =IFERROR(IF($J$7="Piecewise Linear (Simple)",IF(((B36-VAL_DATE)/360)<=0,1,1/(1+(IF(MAX((36>0)*(D36-VAL_DATE)/360,0)<=0,IF(((E36-VAL_DATE)/360)<=0,0,(1/INDEX($L$8:$L$73,MATCH(B36,$K$8:$K$73,1)+1)-1)/((E36-VAL_DATE)/360)),IF(MAX((36>0)*(D36-VAL_DATE)/360,0)<=0,0,(1/INDEX($L$8:$L$73,MATCH(B36,$K$8:$K$73,1))-1)/MAX((36>0)*(D36-VAL_DATE)/360,0)))+(IF(((E36-VAL_DATE)/360)<=0,0,(1/INDEX($L$8:$L$73,MATCH(B36,$K$8:$K$73,1)+1)-1)/((E36-VAL_DATE)/360))-IF(MAX((36>0)*(D36-VAL_DATE)/360,0)<=0,IF(((E36-VAL_DATE)/360)<=0,0,(1/INDEX($L$8:$L$73,MATCH(B36,$K$8:$K$73,1)+1)-1)/((E36-VAL_DATE)/360)),IF(MAX((36>0)*(D36-VAL_DATE)/360,0)<=0,0,(1/INDEX($L$8:$L$73,MATCH(B36,$K$8:$K$73,1))-1)/MAX((36>0)*(D36-VAL_DATE)/360,0))))*IF(((E36-VAL_DATE)/360)-MAX((36>0)*(D36-VAL_DATE)/360,0)=0,0,(((B36-VAL_DATE)/360)-MAX((36>0)*(D36-VAL_DATE)/360,0))/(((E36-VAL_DATE)/360)-MAX((36>0)*(D36-VAL_DATE)/360,0))))*((B36-VAL_DATE)/360))),INDEX($L$8:$L$73,MATCH(B36,$K$8:$K$73,1))*EXP(-(F36/100)*(B36-D36)/365)),"") | H36: =-LN(G36)/C36*100 | K36: ='[USD_SOFR_Curve_Bloomberg_Pricer.xlsx]Curve_Interface'!$K$37 | L36: ='[USD_SOFR_Curve_Bloomberg_Pricer.xlsx]Curve_Interface'!$L$37
A37: 28 | B37: =EDATE($F$7,3*27) | C37: =(B37-VAL_DATE)/365 | D37: =INDEX($K$8:$K$73,MATCH(B37,$K$8:$K$73,1)) | E37: =INDEX($K$8:$K$73,MATCH(B37,$K$8:$K$73,1)+1) | F37: =-LN(INDEX($L$8:$L$73,MATCH(B37,$K$8:$K$73,1)+1)/INDEX($L$8:$L$73,MATCH(B37,$K$8:$K$73,1)))/((E37-D37)/365)*100 | G37: =IFERROR(IF($J$7="Piecewise Linear (Simple)",IF(((B37-VAL_DATE)/360)<=0,1,1/(1+(IF(MAX((37>0)*(D37-VAL_DATE)/360,0)<=0,IF(((E37-VAL_DATE)/360)<=0,0,(1/INDEX($L$8:$L$73,MATCH(B37,$K$8:$K$73,1)+1)-1)/((E37-VAL_DATE)/360)),IF(MAX((37>0)*(D37-VAL_DATE)/360,0)<=0,0,(1/INDEX($L$8:$L$73,MATCH(B37,$K$8:$K$73,1))-1)/MAX((37>0)*(D37-VAL_DATE)/360,0)))+(IF(((E37-VAL_DATE)/360)<=0,0,(1/INDEX($L$8:$L$73,MATCH(B37,$K$8:$K$73,1)+1)-1)/((E37-VAL_DATE)/360))-IF(MAX((37>0)*(D37-VAL_DATE)/360,0)<=0,IF(((E37-VAL_DATE)/360)<=0,0,(1/INDEX($L$8:$L$73,MATCH(B37,$K$8:$K$73,1)+1)-1)/((E37-VAL_DATE)/360)),IF(MAX((37>0)*(D37-VAL_DATE)/360,0)<=0,0,(1/INDEX($L$8:$L$73,MATCH(B37,$K$8:$K$73,1))-1)/MAX((37>0)*(D37-VAL_DATE)/360,0))))*IF(((E37-VAL_DATE)/360)-MAX((37>0)*(D37-VAL_DATE)/360,0)=0,0,(((B37-VAL_DATE)/360)-MAX((37>0)*(D37-VAL_DATE)/360,0))/(((E37-VAL_DATE)/360)-MAX((37>0)*(D37-VAL_DATE)/360,0))))*((B37-VAL_DATE)/360))),INDEX($L$8:$L$73,MATCH(B37,$K$8:$K$73,1))*EXP(-(F37/100)*(B37-D37)/365)),"") | H37: =-LN(G37)/C37*100 | K37: ='[USD_SOFR_Curve_Bloomberg_Pricer.xlsx]Curve_Interface'!$K$38 | L37: ='[USD_SOFR_Curve_Bloomberg_Pricer.xlsx]Curve_Interface'!$L$38
A38: 29 | B38: =EDATE($F$7,3*28) | C38: =(B38-VAL_DATE)/365 | D38: =INDEX($K$8:$K$73,MATCH(B38,$K$8:$K$73,1)) | E38: =INDEX($K$8:$K$73,MATCH(B38,$K$8:$K$73,1)+1) | F38: =-LN(INDEX($L$8:$L$73,MATCH(B38,$K$8:$K$73,1)+1)/INDEX($L$8:$L$73,MATCH(B38,$K$8:$K$73,1)))/((E38-D38)/365)*100 | G38: =IFERROR(IF($J$7="Piecewise Linear (Simple)",IF(((B38-VAL_DATE)/360)<=0,1,1/(1+(IF(MAX((38>0)*(D38-VAL_DATE)/360,0)<=0,IF(((E38-VAL_DATE)/360)<=0,0,(1/INDEX($L$8:$L$73,MATCH(B38,$K$8:$K$73,1)+1)-1)/((E38-VAL_DATE)/360)),IF(MAX((38>0)*(D38-VAL_DATE)/360,0)<=0,0,(1/INDEX($L$8:$L$73,MATCH(B38,$K$8:$K$73,1))-1)/MAX((38>0)*(D38-VAL_DATE)/360,0)))+(IF(((E38-VAL_DATE)/360)<=0,0,(1/INDEX($L$8:$L$73,MATCH(B38,$K$8:$K$73,1)+1)-1)/((E38-VAL_DATE)/360))-IF(MAX((38>0)*(D38-VAL_DATE)/360,0)<=0,IF(((E38-VAL_DATE)/360)<=0,0,(1/INDEX($L$8:$L$73,MATCH(B38,$K$8:$K$73,1)+1)-1)/((E38-VAL_DATE)/360)),IF(MAX((38>0)*(D38-VAL_DATE)/360,0)<=0,0,(1/INDEX($L$8:$L$73,MATCH(B38,$K$8:$K$73,1))-1)/MAX((38>0)*(D38-VAL_DATE)/360,0))))*IF(((E38-VAL_DATE)/360)-MAX((38>0)*(D38-VAL_DATE)/360,0)=0,0,(((B38-VAL_DATE)/360)-MAX((38>0)*(D38-VAL_DATE)/360,0))/(((E38-VAL_DATE)/360)-MAX((38>0)*(D38-VAL_DATE)/360,0))))*((B38-VAL_DATE)/360))),INDEX($L$8:$L$73,MATCH(B38,$K$8:$K$73,1))*EXP(-(F38/100)*(B38-D38)/365)),"") | H38: =-LN(G38)/C38*100 | K38: ='[USD_SOFR_Curve_Bloomberg_Pricer.xlsx]Curve_Interface'!$K$39 | L38: ='[USD_SOFR_Curve_Bloomberg_Pricer.xlsx]Curve_Interface'!$L$39
A39: 30 | B39: =EDATE($F$7,3*29) | C39: =(B39-VAL_DATE)/365 | D39: =INDEX($K$8:$K$73,MATCH(B39,$K$8:$K$73,1)) | E39: =INDEX($K$8:$K$73,MATCH(B39,$K$8:$K$73,1)+1) | F39: =-LN(INDEX($L$8:$L$73,MATCH(B39,$K$8:$K$73,1)+1)/INDEX($L$8:$L$73,MATCH(B39,$K$8:$K$73,1)))/((E39-D39)/365)*100 | G39: =IFERROR(IF($J$7="Piecewise Linear (Simple)",IF(((B39-VAL_DATE)/360)<=0,1,1/(1+(IF(MAX((39>0)*(D39-VAL_DATE)/360,0)<=0,IF(((E39-VAL_DATE)/360)<=0,0,(1/INDEX($L$8:$L$73,MATCH(B39,$K$8:$K$73,1)+1)-1)/((E39-VAL_DATE)/360)),IF(MAX((39>0)*(D39-VAL_DATE)/360,0)<=0,0,(1/INDEX($L$8:$L$73,MATCH(B39,$K$8:$K$73,1))-1)/MAX((39>0)*(D39-VAL_DATE)/360,0)))+(IF(((E39-VAL_DATE)/360)<=0,0,(1/INDEX($L$8:$L$73,MATCH(B39,$K$8:$K$73,1)+1)-1)/((E39-VAL_DATE)/360))-IF(MAX((39>0)*(D39-VAL_DATE)/360,0)<=0,IF(((E39-VAL_DATE)/360)<=0,0,(1/INDEX($L$8:$L$73,MATCH(B39,$K$8:$K$73,1)+1)-1)/((E39-VAL_DATE)/360)),IF(MAX((39>0)*(D39-VAL_DATE)/360,0)<=0,0,(1/INDEX($L$8:$L$73,MATCH(B39,$K$8:$K$73,1))-1)/MAX((39>0)*(D39-VAL_DATE)/360,0))))*IF(((E39-VAL_DATE)/360)-MAX((39>0)*(D39-VAL_DATE)/360,0)=0,0,(((B39-VAL_DATE)/360)-MAX((39>0)*(D39-VAL_DATE)/360,0))/(((E39-VAL_DATE)/360)-MAX((39>0)*(D39-VAL_DATE)/360,0))))*((B39-VAL_DATE)/360))),INDEX($L$8:$L$73,MATCH(B39,$K$8:$K$73,1))*EXP(-(F39/100)*(B39-D39)/365)),"") | H39: =-LN(G39)/C39*100 | K39: ='[USD_SOFR_Curve_Bloomberg_Pricer.xlsx]Curve_Interface'!$K$40 | L39: ='[USD_SOFR_Curve_Bloomberg_Pricer.xlsx]Curve_Interface'!$L$40
A40: 31 | B40: =EDATE($F$7,3*30) | C40: =(B40-VAL_DATE)/365 | D40: =INDEX($K$8:$K$73,MATCH(B40,$K$8:$K$73,1)) | E40: =INDEX($K$8:$K$73,MATCH(B40,$K$8:$K$73,1)+1) | F40: =-LN(INDEX($L$8:$L$73,MATCH(B40,$K$8:$K$73,1)+1)/INDEX($L$8:$L$73,MATCH(B40,$K$8:$K$73,1)))/((E40-D40)/365)*100 | G40: =IFERROR(IF($J$7="Piecewise Linear (Simple)",IF(((B40-VAL_DATE)/360)<=0,1,1/(1+(IF(MAX((40>0)*(D40-VAL_DATE)/360,0)<=0,IF(((E40-VAL_DATE)/360)<=0,0,(1/INDEX($L$8:$L$73,MATCH(B40,$K$8:$K$73,1)+1)-1)/((E40-VAL_DATE)/360)),IF(MAX((40>0)*(D40-VAL_DATE)/360,0)<=0,0,(1/INDEX($L$8:$L$73,MATCH(B40,$K$8:$K$73,1))-1)/MAX((40>0)*(D40-VAL_DATE)/360,0)))+(IF(((E40-VAL_DATE)/360)<=0,0,(1/INDEX($L$8:$L$73,MATCH(B40,$K$8:$K$73,1)+1)-1)/((E40-VAL_DATE)/360))-IF(MAX((40>0)*(D40-VAL_DATE)/360,0)<=0,IF(((E40-VAL_DATE)/360)<=0,0,(1/INDEX($L$8:$L$73,MATCH(B40,$K$8:$K$73,1)+1)-1)/((E40-VAL_DATE)/360)),IF(MAX((40>0)*(D40-VAL_DATE)/360,0)<=0,0,(1/INDEX($L$8:$L$73,MATCH(B40,$K$8:$K$73,1))-1)/MAX((40>0)*(D40-VAL_DATE)/360,0))))*IF(((E40-VAL_DATE)/360)-MAX((40>0)*(D40-VAL_DATE)/360,0)=0,0,(((B40-VAL_DATE)/360)-MAX((40>0)*(D40-VAL_DATE)/360,0))/(((E40-VAL_DATE)/360)-MAX((40>0)*(D40-VAL_DATE)/360,0))))*((B40-VAL_DATE)/360))),INDEX($L$8:$L$73,MATCH(B40,$K$8:$K$73,1))*EXP(-(F40/100)*(B40-D40)/365)),"") | H40: =-LN(G40)/C40*100 | K40: ='[USD_SOFR_Curve_Bloomberg_Pricer.xlsx]Curve_Interface'!$K$41 | L40: ='[USD_SOFR_Curve_Bloomberg_Pricer.xlsx]Curve_Interface'!$L$41
A41: 32 | B41: =EDATE($F$7,3*31) | C41: =(B41-VAL_DATE)/365 | D41: =INDEX($K$8:$K$73,MATCH(B41,$K$8:$K$73,1)) | E41: =INDEX($K$8:$K$73,MATCH(B41,$K$8:$K$73,1)+1) | F41: =-LN(INDEX($L$8:$L$73,MATCH(B41,$K$8:$K$73,1)+1)/INDEX($L$8:$L$73,MATCH(B41,$K$8:$K$73,1)))/((E41-D41)/365)*100 | G41: =IFERROR(IF($J$7="Piecewise Linear (Simple)",IF(((B41-VAL_DATE)/360)<=0,1,1/(1+(IF(MAX((41>0)*(D41-VAL_DATE)/360,0)<=0,IF(((E41-VAL_DATE)/360)<=0,0,(1/INDEX($L$8:$L$73,MATCH(B41,$K$8:$K$73,1)+1)-1)/((E41-VAL_DATE)/360)),IF(MAX((41>0)*(D41-VAL_DATE)/360,0)<=0,0,(1/INDEX($L$8:$L$73,MATCH(B41,$K$8:$K$73,1))-1)/MAX((41>0)*(D41-VAL_DATE)/360,0)))+(IF(((E41-VAL_DATE)/360)<=0,0,(1/INDEX($L$8:$L$73,MATCH(B41,$K$8:$K$73,1)+1)-1)/((E41-VAL_DATE)/360))-IF(MAX((41>0)*(D41-VAL_DATE)/360,0)<=0,IF(((E41-VAL_DATE)/360)<=0,0,(1/INDEX($L$8:$L$73,MATCH(B41,$K$8:$K$73,1)+1)-1)/((E41-VAL_DATE)/360)),IF(MAX((41>0)*(D41-VAL_DATE)/360,0)<=0,0,(1/INDEX($L$8:$L$73,MATCH(B41,$K$8:$K$73,1))-1)/MAX((41>0)*(D41-VAL_DATE)/360,0))))*IF(((E41-VAL_DATE)/360)-MAX((41>0)*(D41-VAL_DATE)/360,0)=0,0,(((B41-VAL_DATE)/360)-MAX((41>0)*(D41-VAL_DATE)/360,0))/(((E41-VAL_DATE)/360)-MAX((41>0)*(D41-VAL_DATE)/360,0))))*((B41-VAL_DATE)/360))),INDEX($L$8:$L$73,MATCH(B41,$K$8:$K$73,1))*EXP(-(F41/100)*(B41-D41)/365)),"") | H41: =-LN(G41)/C41*100 | K41: ='[USD_SOFR_Curve_Bloomberg_Pricer.xlsx]Curve_Interface'!$K$42 | L41: ='[USD_SOFR_Curve_Bloomberg_Pricer.xlsx]Curve_Interface'!$L$42
A42: 33 | B42: =EDATE($F$7,3*32) | C42: =(B42-VAL_DATE)/365 | D42: =INDEX($K$8:$K$73,MATCH(B42,$K$8:$K$73,1)) | E42: =INDEX($K$8:$K$73,MATCH(B42,$K$8:$K$73,1)+1) | F42: =-LN(INDEX($L$8:$L$73,MATCH(B42,$K$8:$K$73,1)+1)/INDEX($L$8:$L$73,MATCH(B42,$K$8:$K$73,1)))/((E42-D42)/365)*100 | G42: =IFERROR(IF($J$7="Piecewise Linear (Simple)",IF(((B42-VAL_DATE)/360)<=0,1,1/(1+(IF(MAX((42>0)*(D42-VAL_DATE)/360,0)<=0,IF(((E42-VAL_DATE)/360)<=0,0,(1/INDEX($L$8:$L$73,MATCH(B42,$K$8:$K$73,1)+1)-1)/((E42-VAL_DATE)/360)),IF(MAX((42>0)*(D42-VAL_DATE)/360,0)<=0,0,(1/INDEX($L$8:$L$73,MATCH(B42,$K$8:$K$73,1))-1)/MAX((42>0)*(D42-VAL_DATE)/360,0)))+(IF(((E42-VAL_DATE)/360)<=0,0,(1/INDEX($L$8:$L$73,MATCH(B42,$K$8:$K$73,1)+1)-1)/((E42-VAL_DATE)/360))-IF(MAX((42>0)*(D42-VAL_DATE)/360,0)<=0,IF(((E42-VAL_DATE)/360)<=0,0,(1/INDEX($L$8:$L$73,MATCH(B42,$K$8:$K$73,1)+1)-1)/((E42-VAL_DATE)/360)),IF(MAX((42>0)*(D42-VAL_DATE)/360,0)<=0,0,(1/INDEX($L$8:$L$73,MATCH(B42,$K$8:$K$73,1))-1)/MAX((42>0)*(D42-VAL_DATE)/360,0))))*IF(((E42-VAL_DATE)/360)-MAX((42>0)*(D42-VAL_DATE)/360,0)=0,0,(((B42-VAL_DATE)/360)-MAX((42>0)*(D42-VAL_DATE)/360,0))/(((E42-VAL_DATE)/360)-MAX((42>0)*(D42-VAL_DATE)/360,0))))*((B42-VAL_DATE)/360))),INDEX($L$8:$L$73,MATCH(B42,$K$8:$K$73,1))*EXP(-(F42/100)*(B42-D42)/365)),"") | H42: =-LN(G42)/C42*100 | K42: ='[USD_SOFR_Curve_Bloomberg_Pricer.xlsx]Curve_Interface'!$K$43 | L42: ='[USD_SOFR_Curve_Bloomberg_Pricer.xlsx]Curve_Interface'!$L$43
A43: 34 | B43: =EDATE($F$7,3*33) | C43: =(B43-VAL_DATE)/365 | D43: =INDEX($K$8:$K$73,MATCH(B43,$K$8:$K$73,1)) | E43: =INDEX($K$8:$K$73,MATCH(B43,$K$8:$K$73,1)+1) | F43: =-LN(INDEX($L$8:$L$73,MATCH(B43,$K$8:$K$73,1)+1)/INDEX($L$8:$L$73,MATCH(B43,$K$8:$K$73,1)))/((E43-D43)/365)*100 | G43: =IFERROR(IF($J$7="Piecewise Linear (Simple)",IF(((B43-VAL_DATE)/360)<=0,1,1/(1+(IF(MAX((43>0)*(D43-VAL_DATE)/360,0)<=0,IF(((E43-VAL_DATE)/360)<=0,0,(1/INDEX($L$8:$L$73,MATCH(B43,$K$8:$K$73,1)+1)-1)/((E43-VAL_DATE)/360)),IF(MAX((43>0)*(D43-VAL_DATE)/360,0)<=0,0,(1/INDEX($L$8:$L$73,MATCH(B43,$K$8:$K$73,1))-1)/MAX((43>0)*(D43-VAL_DATE)/360,0)))+(IF(((E43-VAL_DATE)/360)<=0,0,(1/INDEX($L$8:$L$73,MATCH(B43,$K$8:$K$73,1)+1)-1)/((E43-VAL_DATE)/360))-IF(MAX((43>0)*(D43-VAL_DATE)/360,0)<=0,IF(((E43-VAL_DATE)/360)<=0,0,(1/INDEX($L$8:$L$73,MATCH(B43,$K$8:$K$73,1)+1)-1)/((E43-VAL_DATE)/360)),IF(MAX((43>0)*(D43-VAL_DATE)/360,0)<=0,0,(1/INDEX($L$8:$L$73,MATCH(B43,$K$8:$K$73,1))-1)/MAX((43>0)*(D43-VAL_DATE)/360,0))))*IF(((E43-VAL_DATE)/360)-MAX((43>0)*(D43-VAL_DATE)/360,0)=0,0,(((B43-VAL_DATE)/360)-MAX((43>0)*(D43-VAL_DATE)/360,0))/(((E43-VAL_DATE)/360)-MAX((43>0)*(D43-VAL_DATE)/360,0))))*((B43-VAL_DATE)/360))),INDEX($L$8:$L$73,MATCH(B43,$K$8:$K$73,1))*EXP(-(F43/100)*(B43-D43)/365)),"") | H43: =-LN(G43)/C43*100 | K43: ='[USD_SOFR_Curve_Bloomberg_Pricer.xlsx]Curve_Interface'!$K$44 | L43: ='[USD_SOFR_Curve_Bloomberg_Pricer.xlsx]Curve_Interface'!$L$44
A44: 35 | B44: =EDATE($F$7,3*34) | C44: =(B44-VAL_DATE)/365 | D44: =INDEX($K$8:$K$73,MATCH(B44,$K$8:$K$73,1)) | E44: =INDEX($K$8:$K$73,MATCH(B44,$K$8:$K$73,1)+1) | F44: =-LN(INDEX($L$8:$L$73,MATCH(B44,$K$8:$K$73,1)+1)/INDEX($L$8:$L$73,MATCH(B44,$K$8:$K$73,1)))/((E44-D44)/365)*100 | G44: =IFERROR(IF($J$7="Piecewise Linear (Simple)",IF(((B44-VAL_DATE)/360)<=0,1,1/(1+(IF(MAX((44>0)*(D44-VAL_DATE)/360,0)<=0,IF(((E44-VAL_DATE)/360)<=0,0,(1/INDEX($L$8:$L$73,MATCH(B44,$K$8:$K$73,1)+1)-1)/((E44-VAL_DATE)/360)),IF(MAX((44>0)*(D44-VAL_DATE)/360,0)<=0,0,(1/INDEX($L$8:$L$73,MATCH(B44,$K$8:$K$73,1))-1)/MAX((44>0)*(D44-VAL_DATE)/360,0)))+(IF(((E44-VAL_DATE)/360)<=0,0,(1/INDEX($L$8:$L$73,MATCH(B44,$K$8:$K$73,1)+1)-1)/((E44-VAL_DATE)/360))-IF(MAX((44>0)*(D44-VAL_DATE)/360,0)<=0,IF(((E44-VAL_DATE)/360)<=0,0,(1/INDEX($L$8:$L$73,MATCH(B44,$K$8:$K$73,1)+1)-1)/((E44-VAL_DATE)/360)),IF(MAX((44>0)*(D44-VAL_DATE)/360,0)<=0,0,(1/INDEX($L$8:$L$73,MATCH(B44,$K$8:$K$73,1))-1)/MAX((44>0)*(D44-VAL_DATE)/360,0))))*IF(((E44-VAL_DATE)/360)-MAX((44>0)*(D44-VAL_DATE)/360,0)=0,0,(((B44-VAL_DATE)/360)-MAX((44>0)*(D44-VAL_DATE)/360,0))/(((E44-VAL_DATE)/360)-MAX((44>0)*(D44-VAL_DATE)/360,0))))*((B44-VAL_DATE)/360))),INDEX($L$8:$L$73,MATCH(B44,$K$8:$K$73,1))*EXP(-(F44/100)*(B44-D44)/365)),"") | H44: =-LN(G44)/C44*100 | K44: ='[USD_SOFR_Curve_Bloomberg_Pricer.xlsx]Curve_Interface'!$K$45 | L44: ='[USD_SOFR_Curve_Bloomberg_Pricer.xlsx]Curve_Interface'!$L$45
A45: 36 | B45: =EDATE($F$7,3*35) | C45: =(B45-VAL_DATE)/365 | D45: =INDEX($K$8:$K$73,MATCH(B45,$K$8:$K$73,1)) | E45: =INDEX($K$8:$K$73,MATCH(B45,$K$8:$K$73,1)+1) | F45: =-LN(INDEX($L$8:$L$73,MATCH(B45,$K$8:$K$73,1)+1)/INDEX($L$8:$L$73,MATCH(B45,$K$8:$K$73,1)))/((E45-D45)/365)*100 | G45: =IFERROR(IF($J$7="Piecewise Linear (Simple)",IF(((B45-VAL_DATE)/360)<=0,1,1/(1+(IF(MAX((45>0)*(D45-VAL_DATE)/360,0)<=0,IF(((E45-VAL_DATE)/360)<=0,0,(1/INDEX($L$8:$L$73,MATCH(B45,$K$8:$K$73,1)+1)-1)/((E45-VAL_DATE)/360)),IF(MAX((45>0)*(D45-VAL_DATE)/360,0)<=0,0,(1/INDEX($L$8:$L$73,MATCH(B45,$K$8:$K$73,1))-1)/MAX((45>0)*(D45-VAL_DATE)/360,0)))+(IF(((E45-VAL_DATE)/360)<=0,0,(1/INDEX($L$8:$L$73,MATCH(B45,$K$8:$K$73,1)+1)-1)/((E45-VAL_DATE)/360))-IF(MAX((45>0)*(D45-VAL_DATE)/360,0)<=0,IF(((E45-VAL_DATE)/360)<=0,0,(1/INDEX($L$8:$L$73,MATCH(B45,$K$8:$K$73,1)+1)-1)/((E45-VAL_DATE)/360)),IF(MAX((45>0)*(D45-VAL_DATE)/360,0)<=0,0,(1/INDEX($L$8:$L$73,MATCH(B45,$K$8:$K$73,1))-1)/MAX((45>0)*(D45-VAL_DATE)/360,0))))*IF(((E45-VAL_DATE)/360)-MAX((45>0)*(D45-VAL_DATE)/360,0)=0,0,(((B45-VAL_DATE)/360)-MAX((45>0)*(D45-VAL_DATE)/360,0))/(((E45-VAL_DATE)/360)-MAX((45>0)*(D45-VAL_DATE)/360,0))))*((B45-VAL_DATE)/360))),INDEX($L$8:$L$73,MATCH(B45,$K$8:$K$73,1))*EXP(-(F45/100)*(B45-D45)/365)),"") | H45: =-LN(G45)/C45*100 | K45: ='[USD_SOFR_Curve_Bloomberg_Pricer.xlsx]Curve_Interface'!$K$46 | L45: ='[USD_SOFR_Curve_Bloomberg_Pricer.xlsx]Curve_Interface'!$L$46
A46: 37 | B46: =EDATE($F$7,3*36) | C46: =(B46-VAL_DATE)/365 | D46: =INDEX($K$8:$K$73,MATCH(B46,$K$8:$K$73,1)) | E46: =INDEX($K$8:$K$73,MATCH(B46,$K$8:$K$73,1)+1) | F46: =-LN(INDEX($L$8:$L$73,MATCH(B46,$K$8:$K$73,1)+1)/INDEX($L$8:$L$73,MATCH(B46,$K$8:$K$73,1)))/((E46-D46)/365)*100 | G46: =IFERROR(IF($J$7="Piecewise Linear (Simple)",IF(((B46-VAL_DATE)/360)<=0,1,1/(1+(IF(MAX((46>0)*(D46-VAL_DATE)/360,0)<=0,IF(((E46-VAL_DATE)/360)<=0,0,(1/INDEX($L$8:$L$73,MATCH(B46,$K$8:$K$73,1)+1)-1)/((E46-VAL_DATE)/360)),IF(MAX((46>0)*(D46-VAL_DATE)/360,0)<=0,0,(1/INDEX($L$8:$L$73,MATCH(B46,$K$8:$K$73,1))-1)/MAX((46>0)*(D46-VAL_DATE)/360,0)))+(IF(((E46-VAL_DATE)/360)<=0,0,(1/INDEX($L$8:$L$73,MATCH(B46,$K$8:$K$73,1)+1)-1)/((E46-VAL_DATE)/360))-IF(MAX((46>0)*(D46-VAL_DATE)/360,0)<=0,IF(((E46-VAL_DATE)/360)<=0,0,(1/INDEX($L$8:$L$73,MATCH(B46,$K$8:$K$73,1)+1)-1)/((E46-VAL_DATE)/360)),IF(MAX((46>0)*(D46-VAL_DATE)/360,0)<=0,0,(1/INDEX($L$8:$L$73,MATCH(B46,$K$8:$K$73,1))-1)/MAX((46>0)*(D46-VAL_DATE)/360,0))))*IF(((E46-VAL_DATE)/360)-MAX((46>0)*(D46-VAL_DATE)/360,0)=0,0,(((B46-VAL_DATE)/360)-MAX((46>0)*(D46-VAL_DATE)/360,0))/(((E46-VAL_DATE)/360)-MAX((46>0)*(D46-VAL_DATE)/360,0))))*((B46-VAL_DATE)/360))),INDEX($L$8:$L$73,MATCH(B46,$K$8:$K$73,1))*EXP(-(F46/100)*(B46-D46)/365)),"") | H46: =-LN(G46)/C46*100 | K46: ='[USD_SOFR_Curve_Bloomberg_Pricer.xlsx]Curve_Interface'!$K$47 | L46: ='[USD_SOFR_Curve_Bloomberg_Pricer.xlsx]Curve_Interface'!$L$47
A47: 38 | B47: =EDATE($F$7,3*37) | C47: =(B47-VAL_DATE)/365 | D47: =INDEX($K$8:$K$73,MATCH(B47,$K$8:$K$73,1)) | E47: =INDEX($K$8:$K$73,MATCH(B47,$K$8:$K$73,1)+1) | F47: =-LN(INDEX($L$8:$L$73,MATCH(B47,$K$8:$K$73,1)+1)/INDEX($L$8:$L$73,MATCH(B47,$K$8:$K$73,1)))/((E47-D47)/365)*100 | G47: =IFERROR(IF($J$7="Piecewise Linear (Simple)",IF(((B47-VAL_DATE)/360)<=0,1,1/(1+(IF(MAX((47>0)*(D47-VAL_DATE)/360,0)<=0,IF(((E47-VAL_DATE)/360)<=0,0,(1/INDEX($L$8:$L$73,MATCH(B47,$K$8:$K$73,1)+1)-1)/((E47-VAL_DATE)/360)),IF(MAX((47>0)*(D47-VAL_DATE)/360,0)<=0,0,(1/INDEX($L$8:$L$73,MATCH(B47,$K$8:$K$73,1))-1)/MAX((47>0)*(D47-VAL_DATE)/360,0)))+(IF(((E47-VAL_DATE)/360)<=0,0,(1/INDEX($L$8:$L$73,MATCH(B47,$K$8:$K$73,1)+1)-1)/((E47-VAL_DATE)/360))-IF(MAX((47>0)*(D47-VAL_DATE)/360,0)<=0,IF(((E47-VAL_DATE)/360)<=0,0,(1/INDEX($L$8:$L$73,MATCH(B47,$K$8:$K$73,1)+1)-1)/((E47-VAL_DATE)/360)),IF(MAX((47>0)*(D47-VAL_DATE)/360,0)<=0,0,(1/INDEX($L$8:$L$73,MATCH(B47,$K$8:$K$73,1))-1)/MAX((47>0)*(D47-VAL_DATE)/360,0))))*IF(((E47-VAL_DATE)/360)-MAX((47>0)*(D47-VAL_DATE)/360,0)=0,0,(((B47-VAL_DATE)/360)-MAX((47>0)*(D47-VAL_DATE)/360,0))/(((E47-VAL_DATE)/360)-MAX((47>0)*(D47-VAL_DATE)/360,0))))*((B47-VAL_DATE)/360))),INDEX($L$8:$L$73,MATCH(B47,$K$8:$K$73,1))*EXP(-(F47/100)*(B47-D47)/365)),"") | H47: =-LN(G47)/C47*100 | K47: ='[USD_SOFR_Curve_Bloomberg_Pricer.xlsx]Curve_Interface'!$K$48 | L47: ='[USD_SOFR_Curve_Bloomberg_Pricer.xlsx]Curve_Interface'!$L$48
A48: 39 | B48: =EDATE($F$7,3*38) | C48: =(B48-VAL_DATE)/365 | D48: =INDEX($K$8:$K$73,MATCH(B48,$K$8:$K$73,1)) | E48: =INDEX($K$8:$K$73,MATCH(B48,$K$8:$K$73,1)+1) | F48: =-LN(INDEX($L$8:$L$73,MATCH(B48,$K$8:$K$73,1)+1)/INDEX($L$8:$L$73,MATCH(B48,$K$8:$K$73,1)))/((E48-D48)/365)*100 | G48: =IFERROR(IF($J$7="Piecewise Linear (Simple)",IF(((B48-VAL_DATE)/360)<=0,1,1/(1+(IF(MAX((48>0)*(D48-VAL_DATE)/360,0)<=0,IF(((E48-VAL_DATE)/360)<=0,0,(1/INDEX($L$8:$L$73,MATCH(B48,$K$8:$K$73,1)+1)-1)/((E48-VAL_DATE)/360)),IF(MAX((48>0)*(D48-VAL_DATE)/360,0)<=0,0,(1/INDEX($L$8:$L$73,MATCH(B48,$K$8:$K$73,1))-1)/MAX((48>0)*(D48-VAL_DATE)/360,0)))+(IF(((E48-VAL_DATE)/360)<=0,0,(1/INDEX($L$8:$L$73,MATCH(B48,$K$8:$K$73,1)+1)-1)/((E48-VAL_DATE)/360))-IF(MAX((48>0)*(D48-VAL_DATE)/360,0)<=0,IF(((E48-VAL_DATE)/360)<=0,0,(1/INDEX($L$8:$L$73,MATCH(B48,$K$8:$K$73,1)+1)-1)/((E48-VAL_DATE)/360)),IF(MAX((48>0)*(D48-VAL_DATE)/360,0)<=0,0,(1/INDEX($L$8:$L$73,MATCH(B48,$K$8:$K$73,1))-1)/MAX((48>0)*(D48-VAL_DATE)/360,0))))*IF(((E48-VAL_DATE)/360)-MAX((48>0)*(D48-VAL_DATE)/360,0)=0,0,(((B48-VAL_DATE)/360)-MAX((48>0)*(D48-VAL_DATE)/360,0))/(((E48-VAL_DATE)/360)-MAX((48>0)*(D48-VAL_DATE)/360,0))))*((B48-VAL_DATE)/360))),INDEX($L$8:$L$73,MATCH(B48,$K$8:$K$73,1))*EXP(-(F48/100)*(B48-D48)/365)),"") | H48: =-LN(G48)/C48*100 | K48: ='[USD_SOFR_Curve_Bloomberg_Pricer.xlsx]Curve_Interface'!$K$49 | L48: ='[USD_SOFR_Curve_Bloomberg_Pricer.xlsx]Curve_Interface'!$L$49
A49: 40 | B49: =EDATE($F$7,3*39) | C49: =(B49-VAL_DATE)/365 | D49: =INDEX($K$8:$K$73,MATCH(B49,$K$8:$K$73,1)) | E49: =INDEX($K$8:$K$73,MATCH(B49,$K$8:$K$73,1)+1) | F49: =-LN(INDEX($L$8:$L$73,MATCH(B49,$K$8:$K$73,1)+1)/INDEX($L$8:$L$73,MATCH(B49,$K$8:$K$73,1)))/((E49-D49)/365)*100 | G49: =IFERROR(IF($J$7="Piecewise Linear (Simple)",IF(((B49-VAL_DATE)/360)<=0,1,1/(1+(IF(MAX((49>0)*(D49-VAL_DATE)/360,0)<=0,IF(((E49-VAL_DATE)/360)<=0,0,(1/INDEX($L$8:$L$73,MATCH(B49,$K$8:$K$73,1)+1)-1)/((E49-VAL_DATE)/360)),IF(MAX((49>0)*(D49-VAL_DATE)/360,0)<=0,0,(1/INDEX($L$8:$L$73,MATCH(B49,$K$8:$K$73,1))-1)/MAX((49>0)*(D49-VAL_DATE)/360,0)))+(IF(((E49-VAL_DATE)/360)<=0,0,(1/INDEX($L$8:$L$73,MATCH(B49,$K$8:$K$73,1)+1)-1)/((E49-VAL_DATE)/360))-IF(MAX((49>0)*(D49-VAL_DATE)/360,0)<=0,IF(((E49-VAL_DATE)/360)<=0,0,(1/INDEX($L$8:$L$73,MATCH(B49,$K$8:$K$73,1)+1)-1)/((E49-VAL_DATE)/360)),IF(MAX((49>0)*(D49-VAL_DATE)/360,0)<=0,0,(1/INDEX($L$8:$L$73,MATCH(B49,$K$8:$K$73,1))-1)/MAX((49>0)*(D49-VAL_DATE)/360,0))))*IF(((E49-VAL_DATE)/360)-MAX((49>0)*(D49-VAL_DATE)/360,0)=0,0,(((B49-VAL_DATE)/360)-MAX((49>0)*(D49-VAL_DATE)/360,0))/(((E49-VAL_DATE)/360)-MAX((49>0)*(D49-VAL_DATE)/360,0))))*((B49-VAL_DATE)/360))),INDEX($L$8:$L$73,MATCH(B49,$K$8:$K$73,1))*EXP(-(F49/100)*(B49-D49)/365)),"") | H49: =-LN(G49)/C49*100 | K49: ='[USD_SOFR_Curve_Bloomberg_Pricer.xlsx]Curve_Interface'!$K$50 | L49: ='[USD_SOFR_Curve_Bloomberg_Pricer.xlsx]Curve_Interface'!$L$50
K50: ='[USD_SOFR_Curve_Bloomberg_Pricer.xlsx]Curve_Interface'!$K$51 | L50: ='[USD_SOFR_Curve_Bloomberg_Pricer.xlsx]Curve_Interface'!$L$51
K51: ='[USD_SOFR_Curve_Bloomberg_Pricer.xlsx]Curve_Interface'!$K$52 | L51: ='[USD_SOFR_Curve_Bloomberg_Pricer.xlsx]Curve_Interface'!$L$52
K52: ='[USD_SOFR_Curve_Bloomberg_Pricer.xlsx]Curve_Interface'!$K$53 | L52: ='[USD_SOFR_Curve_Bloomberg_Pricer.xlsx]Curve_Interface'!$L$53
K53: ='[USD_SOFR_Curve_Bloomberg_Pricer.xlsx]Curve_Interface'!$K$54 | L53: ='[USD_SOFR_Curve_Bloomberg_Pricer.xlsx]Curve_Interface'!$L$54
K54: ='[USD_SOFR_Curve_Bloomberg_Pricer.xlsx]Curve_Interface'!$K$55 | L54: ='[USD_SOFR_Curve_Bloomberg_Pricer.xlsx]Curve_Interface'!$L$55
K55: ='[USD_SOFR_Curve_Bloomberg_Pricer.xlsx]Curve_Interface'!$K$56 | L55: ='[USD_SOFR_Curve_Bloomberg_Pricer.xlsx]Curve_Interface'!$L$56
K56: ='[USD_SOFR_Curve_Bloomberg_Pricer.xlsx]Curve_Interface'!$K$57 | L56: ='[USD_SOFR_Curve_Bloomberg_Pricer.xlsx]Curve_Interface'!$L$57
K57: ='[USD_SOFR_Curve_Bloomberg_Pricer.xlsx]Curve_Interface'!$K$58 | L57: ='[USD_SOFR_Curve_Bloomberg_Pricer.xlsx]Curve_Interface'!$L$58
K58: ='[USD_SOFR_Curve_Bloomberg_Pricer.xlsx]Curve_Interface'!$K$59 | L58: ='[USD_SOFR_Curve_Bloomberg_Pricer.xlsx]Curve_Interface'!$L$59
K59: ='[USD_SOFR_Curve_Bloomberg_Pricer.xlsx]Curve_Interface'!$K$60 | L59: ='[USD_SOFR_Curve_Bloomberg_Pricer.xlsx]Curve_Interface'!$L$60
K60: ='[USD_SOFR_Curve_Bloomberg_Pricer.xlsx]Curve_Interface'!$K$61 | L60: ='[USD_SOFR_Curve_Bloomberg_Pricer.xlsx]Curve_Interface'!$L$61
K61: ='[USD_SOFR_Curve_Bloomberg_Pricer.xlsx]Curve_Interface'!$K$62 | L61: ='[USD_SOFR_Curve_Bloomberg_Pricer.xlsx]Curve_Interface'!$L$62
K62: ='[USD_SOFR_Curve_Bloomberg_Pricer.xlsx]Curve_Interface'!$K$63 | L62: ='[USD_SOFR_Curve_Bloomberg_Pricer.xlsx]Curve_Interface'!$L$63
K63: ='[USD_SOFR_Curve_Bloomberg_Pricer.xlsx]Curve_Interface'!$K$64 | L63: ='[USD_SOFR_Curve_Bloomberg_Pricer.xlsx]Curve_Interface'!$L$64
K64: ='[USD_SOFR_Curve_Bloomberg_Pricer.xlsx]Curve_Interface'!$K$65 | L64: ='[USD_SOFR_Curve_Bloomberg_Pricer.xlsx]Curve_Interface'!$L$65
K65: ='[USD_SOFR_Curve_Bloomberg_Pricer.xlsx]Curve_Interface'!$K$66 | L65: ='[USD_SOFR_Curve_Bloomberg_Pricer.xlsx]Curve_Interface'!$L$66
K66: ='[USD_SOFR_Curve_Bloomberg_Pricer.xlsx]Curve_Interface'!$K$67 | L66: ='[USD_SOFR_Curve_Bloomberg_Pricer.xlsx]Curve_Interface'!$L$67
K67: ='[USD_SOFR_Curve_Bloomberg_Pricer.xlsx]Curve_Interface'!$K$68 | L67: ='[USD_SOFR_Curve_Bloomberg_Pricer.xlsx]Curve_Interface'!$L$68
K68: ='[USD_SOFR_Curve_Bloomberg_Pricer.xlsx]Curve_Interface'!$K$69 | L68: ='[USD_SOFR_Curve_Bloomberg_Pricer.xlsx]Curve_Interface'!$L$69
K69: ='[USD_SOFR_Curve_Bloomberg_Pricer.xlsx]Curve_Interface'!$K$70 | L69: ='[USD_SOFR_Curve_Bloomberg_Pricer.xlsx]Curve_Interface'!$L$70
K70: ='[USD_SOFR_Curve_Bloomberg_Pricer.xlsx]Curve_Interface'!$K$71 | L70: ='[USD_SOFR_Curve_Bloomberg_Pricer.xlsx]Curve_Interface'!$L$71
K71: ='[USD_SOFR_Curve_Bloomberg_Pricer.xlsx]Curve_Interface'!$K$72 | L71: ='[USD_SOFR_Curve_Bloomberg_Pricer.xlsx]Curve_Interface'!$L$72
K72: ='[USD_SOFR_Curve_Bloomberg_Pricer.xlsx]Curve_Interface'!$K$73 | L72: ='[USD_SOFR_Curve_Bloomberg_Pricer.xlsx]Curve_Interface'!$L$73
K73: ='[USD_SOFR_Curve_Bloomberg_Pricer.xlsx]Curve_Interface'!$K$74 | L73: ='[USD_SOFR_Curve_Bloomberg_Pricer.xlsx]Curve_Interface'!$L$74

Sheet CDS_Entities
A1: CDS_Entities: names pulled from Bloomberg
A2: One row per name. Blue/yellow cells are typed in from the terminal. CDS_Parameters!B27 selects which row prices. | AE2: Type a ticker in col B and the row populates. Cols H:M show what is in use: the live pull when it resolves. To hard-code instead, overwrite H:M directly. | AR2: Guaranteed numeric. CDS_Quotes reads THIS, never H:M directly - an empty string here propagates into the hazard chain and takes out the module.
A3: Spreads H:M are T3 (term structure). O:AC are T4 (the CDSW screen for that name) and are the acceptance test: see TEST_CASES.md. | H3: TERM STRUCTURE (T3) | O3: CDSW SCREEN CAPTURE (T4) | AE3: DYNAMIC PULL: Help Desk H#1330731572 | AR3: in use = Entities effective block (override > BDP > manual)
A4: Entity name | B4: Ticker (BDP) | C4: Ccy | D4: Seniority | E4: Clause | F4: Recovery | G4: Captured | H4: 1Y bp (manual) | I4: 2Y bp (manual) | J4: 3Y bp (manual) | K4: 5Y bp (manual) | L4: 7Y bp (manual) | M4: 10Y bp (manual) | O4: Notional | P4: Coupon bp | Q4: Maturity | R4: Traded sprd bp | S4: Pts upfront | T4: Price | U4: Principal | V4: Accr days | W4: Accrued | X4: Cash amount | Y4: Spread DV01 | Z4: IR DV01 | AA4: Rec risk 1% | AB4: Def exposure | AC4: Prob 5Y | AE4: Step 1 ticker | AF4: 1Y ticker | AG4: 1Y bp live | AH4: 2Y ticker | AI4: 2Y bp live | AJ4: 3Y ticker | AK4: 3Y bp live | AL4: 5Y ticker | AM4: 5Y bp live | AN4: 7Y ticker | AO4: 7Y bp live | AP4: 10Y ticker | AQ4: 10Y bp live | AR4: 1Y used | AS4: 2Y used | AT4: 3Y used | AU4: 5Y used | AV4: 7Y used | AW4: 10Y used
A5: =IF(Entities!$B7="","",Entities!$B7) | B5: =IF(Entities!$C7="","",Entities!$C7) | C5: =IF(Entities!$D7="","",Entities!$D7) | D5: Senior | E5: CR14 | F5: 0.4 | G5: 46224 | K5: 55.1514 | O5: 10000000 | P5: 100 | Q5: 48019 | R5: 55.1514 | S5: -1.9759627 | T5: 101.97596 | U5: -197597 | V5: 30 | W5: -8333 | X5: -205930 | Y5: 4482.41 | Z5: 47.71 | AA5: 72 | AB5: 6197596 | AC5: 0.0446 | AF5: =IFERROR(BDP($B5,"CDS_SPREAD_TICKER_1Y"),"") | AG5: =IFERROR(BDP(AF5&" BEST Curncy","PX_LAST")+0,"") | AH5: =IFERROR(BDP($B5,"CDS_SPREAD_TICKER_2Y"),"") | AI5: =IFERROR(BDP(AH5&" BEST Curncy","PX_LAST")+0,"") | AJ5: =IFERROR(BDP($B5,"CDS_SPREAD_TICKER_3Y"),"") | AK5: =IFERROR(BDP(AJ5&" BEST Curncy","PX_LAST")+0,"") | AL5: =IFERROR(BDP($B5,"CDS_SPREAD_TICKER_5Y"),"") | AM5: =IFERROR(BDP(AL5&" BEST Curncy","PX_LAST")+0,"") | AN5: =IFERROR(BDP($B5,"CDS_SPREAD_TICKER_7Y"),"") | AO5: =IFERROR(BDP(AN5&" BEST Curncy","PX_LAST")+0,"") | AP5: =IFERROR(BDP($B5,"CDS_SPREAD_TICKER_10Y"),"") | AQ5: =IFERROR(BDP(AP5&" BEST Curncy","PX_LAST")+0,"") | AR5: =IF(Entities!$F21="",0,Entities!$F21) | AS5: =IF(Entities!$G21="",0,Entities!$G21) | AT5: =IF(Entities!$H21="",0,Entities!$H21) | AU5: =IF(Entities!$I21="",0,Entities!$I21) | AV5: =IF(Entities!$J21="",0,Entities!$J21) | AW5: =IF(Entities!$K21="",0,Entities!$K21)
A6: =IF(Entities!$B8="","",Entities!$B8) | B6: =IF(Entities!$C8="","",Entities!$C8) | C6: =IF(Entities!$D8="","",Entities!$D8) | D6: Senior | E6: CR14 | F6: 0.4 | H6: 40 | I6: 55 | J6: 70 | K6: 95 | L6: 115 | M6: 135 | AF6: =IFERROR(BDP($B6,"CDS_SPREAD_TICKER_1Y"),"") | AG6: =IFERROR(BDP(AF6&" BEST Curncy","PX_LAST")+0,"") | AH6: =IFERROR(BDP($B6,"CDS_SPREAD_TICKER_2Y"),"") | AI6: =IFERROR(BDP(AH6&" BEST Curncy","PX_LAST")+0,"") | AJ6: =IFERROR(BDP($B6,"CDS_SPREAD_TICKER_3Y"),"") | AK6: =IFERROR(BDP(AJ6&" BEST Curncy","PX_LAST")+0,"") | AL6: =IFERROR(BDP($B6,"CDS_SPREAD_TICKER_5Y"),"") | AM6: =IFERROR(BDP(AL6&" BEST Curncy","PX_LAST")+0,"") | AN6: =IFERROR(BDP($B6,"CDS_SPREAD_TICKER_7Y"),"") | AO6: =IFERROR(BDP(AN6&" BEST Curncy","PX_LAST")+0,"") | AP6: =IFERROR(BDP($B6,"CDS_SPREAD_TICKER_10Y"),"") | AQ6: =IFERROR(BDP(AP6&" BEST Curncy","PX_LAST")+0,"") | AR6: =IF(Entities!$F22="",0,Entities!$F22) | AS6: =IF(Entities!$G22="",0,Entities!$G22) | AT6: =IF(Entities!$H22="",0,Entities!$H22) | AU6: =IF(Entities!$I22="",0,Entities!$I22) | AV6: =IF(Entities!$J22="",0,Entities!$J22) | AW6: =IF(Entities!$K22="",0,Entities!$K22)
A7: =IF(Entities!$B9="","",Entities!$B9) | B7: =IF(Entities!$C9="","",Entities!$C9) | C7: =IF(Entities!$D9="","",Entities!$D9) | F7: 0.4 | AF7: =IFERROR(BDP($B7,"CDS_SPREAD_TICKER_1Y"),"") | AG7: =IFERROR(BDP(AF7&" BEST Curncy","PX_LAST")+0,"") | AH7: =IFERROR(BDP($B7,"CDS_SPREAD_TICKER_2Y"),"") | AI7: =IFERROR(BDP(AH7&" BEST Curncy","PX_LAST")+0,"") | AJ7: =IFERROR(BDP($B7,"CDS_SPREAD_TICKER_3Y"),"") | AK7: =IFERROR(BDP(AJ7&" BEST Curncy","PX_LAST")+0,"") | AL7: =IFERROR(BDP($B7,"CDS_SPREAD_TICKER_5Y"),"") | AM7: =IFERROR(BDP(AL7&" BEST Curncy","PX_LAST")+0,"") | AN7: =IFERROR(BDP($B7,"CDS_SPREAD_TICKER_7Y"),"") | AO7: =IFERROR(BDP(AN7&" BEST Curncy","PX_LAST")+0,"") | AP7: =IFERROR(BDP($B7,"CDS_SPREAD_TICKER_10Y"),"") | AQ7: =IFERROR(BDP(AP7&" BEST Curncy","PX_LAST")+0,"") | AR7: =IF(Entities!$F23="",0,Entities!$F23) | AS7: =IF(Entities!$G23="",0,Entities!$G23) | AT7: =IF(Entities!$H23="",0,Entities!$H23) | AU7: =IF(Entities!$I23="",0,Entities!$I23) | AV7: =IF(Entities!$J23="",0,Entities!$J23) | AW7: =IF(Entities!$K23="",0,Entities!$K23)
A8: =IF(Entities!$B10="","",Entities!$B10) | B8: =IF(Entities!$C10="","",Entities!$C10) | C8: =IF(Entities!$D10="","",Entities!$D10) | F8: 0.4 | AF8: =IFERROR(BDP($B8,"CDS_SPREAD_TICKER_1Y"),"") | AG8: =IFERROR(BDP(AF8&" BEST Curncy","PX_LAST")+0,"") | AH8: =IFERROR(BDP($B8,"CDS_SPREAD_TICKER_2Y"),"") | AI8: =IFERROR(BDP(AH8&" BEST Curncy","PX_LAST")+0,"") | AJ8: =IFERROR(BDP($B8,"CDS_SPREAD_TICKER_3Y"),"") | AK8: =IFERROR(BDP(AJ8&" BEST Curncy","PX_LAST")+0,"") | AL8: =IFERROR(BDP($B8,"CDS_SPREAD_TICKER_5Y"),"") | AM8: =IFERROR(BDP(AL8&" BEST Curncy","PX_LAST")+0,"") | AN8: =IFERROR(BDP($B8,"CDS_SPREAD_TICKER_7Y"),"") | AO8: =IFERROR(BDP(AN8&" BEST Curncy","PX_LAST")+0,"") | AP8: =IFERROR(BDP($B8,"CDS_SPREAD_TICKER_10Y"),"") | AQ8: =IFERROR(BDP(AP8&" BEST Curncy","PX_LAST")+0,"") | AR8: =IF(Entities!$F24="",0,Entities!$F24) | AS8: =IF(Entities!$G24="",0,Entities!$G24) | AT8: =IF(Entities!$H24="",0,Entities!$H24) | AU8: =IF(Entities!$I24="",0,Entities!$I24) | AV8: =IF(Entities!$J24="",0,Entities!$J24) | AW8: =IF(Entities!$K24="",0,Entities!$K24)
A9: =IF(Entities!$B11="","",Entities!$B11) | B9: =IF(Entities!$C11="","",Entities!$C11) | C9: =IF(Entities!$D11="","",Entities!$D11) | F9: 0.4 | AF9: =IFERROR(BDP($B9,"CDS_SPREAD_TICKER_1Y"),"") | AG9: =IFERROR(BDP(AF9&" BEST Curncy","PX_LAST")+0,"") | AH9: =IFERROR(BDP($B9,"CDS_SPREAD_TICKER_2Y"),"") | AI9: =IFERROR(BDP(AH9&" BEST Curncy","PX_LAST")+0,"") | AJ9: =IFERROR(BDP($B9,"CDS_SPREAD_TICKER_3Y"),"") | AK9: =IFERROR(BDP(AJ9&" BEST Curncy","PX_LAST")+0,"") | AL9: =IFERROR(BDP($B9,"CDS_SPREAD_TICKER_5Y"),"") | AM9: =IFERROR(BDP(AL9&" BEST Curncy","PX_LAST")+0,"") | AN9: =IFERROR(BDP($B9,"CDS_SPREAD_TICKER_7Y"),"") | AO9: =IFERROR(BDP(AN9&" BEST Curncy","PX_LAST")+0,"") | AP9: =IFERROR(BDP($B9,"CDS_SPREAD_TICKER_10Y"),"") | AQ9: =IFERROR(BDP(AP9&" BEST Curncy","PX_LAST")+0,"") | AR9: =IF(Entities!$F25="",0,Entities!$F25) | AS9: =IF(Entities!$G25="",0,Entities!$G25) | AT9: =IF(Entities!$H25="",0,Entities!$H25) | AU9: =IF(Entities!$I25="",0,Entities!$I25) | AV9: =IF(Entities!$J25="",0,Entities!$J25) | AW9: =IF(Entities!$K25="",0,Entities!$K25)
A10: =IF(Entities!$B12="","",Entities!$B12) | B10: =IF(Entities!$C12="","",Entities!$C12) | C10: =IF(Entities!$D12="","",Entities!$D12) | F10: 0.4 | AF10: =IFERROR(BDP($B10,"CDS_SPREAD_TICKER_1Y"),"") | AG10: =IFERROR(BDP(AF10&" BEST Curncy","PX_LAST")+0,"") | AH10: =IFERROR(BDP($B10,"CDS_SPREAD_TICKER_2Y"),"") | AI10: =IFERROR(BDP(AH10&" BEST Curncy","PX_LAST")+0,"") | AJ10: =IFERROR(BDP($B10,"CDS_SPREAD_TICKER_3Y"),"") | AK10: =IFERROR(BDP(AJ10&" BEST Curncy","PX_LAST")+0,"") | AL10: =IFERROR(BDP($B10,"CDS_SPREAD_TICKER_5Y"),"") | AM10: =IFERROR(BDP(AL10&" BEST Curncy","PX_LAST")+0,"") | AN10: =IFERROR(BDP($B10,"CDS_SPREAD_TICKER_7Y"),"") | AO10: =IFERROR(BDP(AN10&" BEST Curncy","PX_LAST")+0,"") | AP10: =IFERROR(BDP($B10,"CDS_SPREAD_TICKER_10Y"),"") | AQ10: =IFERROR(BDP(AP10&" BEST Curncy","PX_LAST")+0,"") | AR10: =IF(Entities!$F26="",0,Entities!$F26) | AS10: =IF(Entities!$G26="",0,Entities!$G26) | AT10: =IF(Entities!$H26="",0,Entities!$H26) | AU10: =IF(Entities!$I26="",0,Entities!$I26) | AV10: =IF(Entities!$J26="",0,Entities!$J26) | AW10: =IF(Entities!$K26="",0,Entities!$K26)
A11: =IF(Entities!$B13="","",Entities!$B13) | B11: =IF(Entities!$C13="","",Entities!$C13) | C11: =IF(Entities!$D13="","",Entities!$D13) | F11: 0.4 | AF11: =IFERROR(BDP($B11,"CDS_SPREAD_TICKER_1Y"),"") | AG11: =IFERROR(BDP(AF11&" BEST Curncy","PX_LAST")+0,"") | AH11: =IFERROR(BDP($B11,"CDS_SPREAD_TICKER_2Y"),"") | AI11: =IFERROR(BDP(AH11&" BEST Curncy","PX_LAST")+0,"") | AJ11: =IFERROR(BDP($B11,"CDS_SPREAD_TICKER_3Y"),"") | AK11: =IFERROR(BDP(AJ11&" BEST Curncy","PX_LAST")+0,"") | AL11: =IFERROR(BDP($B11,"CDS_SPREAD_TICKER_5Y"),"") | AM11: =IFERROR(BDP(AL11&" BEST Curncy","PX_LAST")+0,"") | AN11: =IFERROR(BDP($B11,"CDS_SPREAD_TICKER_7Y"),"") | AO11: =IFERROR(BDP(AN11&" BEST Curncy","PX_LAST")+0,"") | AP11: =IFERROR(BDP($B11,"CDS_SPREAD_TICKER_10Y"),"") | AQ11: =IFERROR(BDP(AP11&" BEST Curncy","PX_LAST")+0,"") | AR11: =IF(Entities!$F27="",0,Entities!$F27) | AS11: =IF(Entities!$G27="",0,Entities!$G27) | AT11: =IF(Entities!$H27="",0,Entities!$H27) | AU11: =IF(Entities!$I27="",0,Entities!$I27) | AV11: =IF(Entities!$J27="",0,Entities!$J27) | AW11: =IF(Entities!$K27="",0,Entities!$K27)
A12: =IF(Entities!$B14="","",Entities!$B14) | B12: =IF(Entities!$C14="","",Entities!$C14) | C12: =IF(Entities!$D14="","",Entities!$D14) | F12: 0.4 | AF12: =IFERROR(BDP($B12,"CDS_SPREAD_TICKER_1Y"),"") | AG12: =IFERROR(BDP(AF12&" BEST Curncy","PX_LAST")+0,"") | AH12: =IFERROR(BDP($B12,"CDS_SPREAD_TICKER_2Y"),"") | AI12: =IFERROR(BDP(AH12&" BEST Curncy","PX_LAST")+0,"") | AJ12: =IFERROR(BDP($B12,"CDS_SPREAD_TICKER_3Y"),"") | AK12: =IFERROR(BDP(AJ12&" BEST Curncy","PX_LAST")+0,"") | AL12: =IFERROR(BDP($B12,"CDS_SPREAD_TICKER_5Y"),"") | AM12: =IFERROR(BDP(AL12&" BEST Curncy","PX_LAST")+0,"") | AN12: =IFERROR(BDP($B12,"CDS_SPREAD_TICKER_7Y"),"") | AO12: =IFERROR(BDP(AN12&" BEST Curncy","PX_LAST")+0,"") | AP12: =IFERROR(BDP($B12,"CDS_SPREAD_TICKER_10Y"),"") | AQ12: =IFERROR(BDP(AP12&" BEST Curncy","PX_LAST")+0,"") | AR12: =IF(Entities!$F28="",0,Entities!$F28) | AS12: =IF(Entities!$G28="",0,Entities!$G28) | AT12: =IF(Entities!$H28="",0,Entities!$H28) | AU12: =IF(Entities!$I28="",0,Entities!$I28) | AV12: =IF(Entities!$J28="",0,Entities!$J28) | AW12: =IF(Entities!$K28="",0,Entities!$K28)
A13: =IF(Entities!$B15="","",Entities!$B15) | B13: =IF(Entities!$C15="","",Entities!$C15) | C13: =IF(Entities!$D15="","",Entities!$D15) | F13: 0.4 | AF13: =IFERROR(BDP($B13,"CDS_SPREAD_TICKER_1Y"),"") | AG13: =IFERROR(BDP(AF13&" BEST Curncy","PX_LAST")+0,"") | AH13: =IFERROR(BDP($B13,"CDS_SPREAD_TICKER_2Y"),"") | AI13: =IFERROR(BDP(AH13&" BEST Curncy","PX_LAST")+0,"") | AJ13: =IFERROR(BDP($B13,"CDS_SPREAD_TICKER_3Y"),"") | AK13: =IFERROR(BDP(AJ13&" BEST Curncy","PX_LAST")+0,"") | AL13: =IFERROR(BDP($B13,"CDS_SPREAD_TICKER_5Y"),"") | AM13: =IFERROR(BDP(AL13&" BEST Curncy","PX_LAST")+0,"") | AN13: =IFERROR(BDP($B13,"CDS_SPREAD_TICKER_7Y"),"") | AO13: =IFERROR(BDP(AN13&" BEST Curncy","PX_LAST")+0,"") | AP13: =IFERROR(BDP($B13,"CDS_SPREAD_TICKER_10Y"),"") | AQ13: =IFERROR(BDP(AP13&" BEST Curncy","PX_LAST")+0,"") | AR13: =IF(Entities!$F29="",0,Entities!$F29) | AS13: =IF(Entities!$G29="",0,Entities!$G29) | AT13: =IF(Entities!$H29="",0,Entities!$H29) | AU13: =IF(Entities!$I29="",0,Entities!$I29) | AV13: =IF(Entities!$J29="",0,Entities!$J29) | AW13: =IF(Entities!$K29="",0,Entities!$K29)
A14: =IF(Entities!$B16="","",Entities!$B16) | B14: =IF(Entities!$C16="","",Entities!$C16) | C14: =IF(Entities!$D16="","",Entities!$D16) | F14: 0.4 | AF14: =IFERROR(BDP($B14,"CDS_SPREAD_TICKER_1Y"),"") | AG14: =IFERROR(BDP(AF14&" BEST Curncy","PX_LAST")+0,"") | AH14: =IFERROR(BDP($B14,"CDS_SPREAD_TICKER_2Y"),"") | AI14: =IFERROR(BDP(AH14&" BEST Curncy","PX_LAST")+0,"") | AJ14: =IFERROR(BDP($B14,"CDS_SPREAD_TICKER_3Y"),"") | AK14: =IFERROR(BDP(AJ14&" BEST Curncy","PX_LAST")+0,"") | AL14: =IFERROR(BDP($B14,"CDS_SPREAD_TICKER_5Y"),"") | AM14: =IFERROR(BDP(AL14&" BEST Curncy","PX_LAST")+0,"") | AN14: =IFERROR(BDP($B14,"CDS_SPREAD_TICKER_7Y"),"") | AO14: =IFERROR(BDP(AN14&" BEST Curncy","PX_LAST")+0,"") | AP14: =IFERROR(BDP($B14,"CDS_SPREAD_TICKER_10Y"),"") | AQ14: =IFERROR(BDP(AP14&" BEST Curncy","PX_LAST")+0,"") | AR14: =IF(Entities!$F30="",0,Entities!$F30) | AS14: =IF(Entities!$G30="",0,Entities!$G30) | AT14: =IF(Entities!$H30="",0,Entities!$H30) | AU14: =IF(Entities!$I30="",0,Entities!$I30) | AV14: =IF(Entities!$J30="",0,Entities!$J30) | AW14: =IF(Entities!$K30="",0,Entities!$K30)
A16: Row 5 is the reference screen already on file. Only its 5Y spread is known: the rest of its term structure was never captured, which is exactly what T3 is for. Its CDSW outputs ARE known and are the target to hit.
A17: Row 5 is the pending real case: only its 5Y spread is known, so its strip fails - a 0/0/0/55/0/0 term structure is not strippable, which is the D8 condition. That is correct behaviour, not a fault. Row 6 is a DEMO curve so the module has something sane to run on until the real term structure arrives.

Sheet CDS_Parameters
A1: CDS_Parameters
A2: Credit-default-swap assumptions (recovery is an INPUT, not bootstrapped)
A4: Valuation date | B4: =VAL_DATE | C4: Linked to the Parameters/Instructions tab.
A5: 1st CDS date (roll) | B5: ='Curve_Interface'!$F$7 | C5: Next 20 Mar/Jun/Sep/Dec.
A6: Currency | B6: USD
A7: Reference entity | B7: EXAMPLE CORP | C7: Type your reference entity.
A8: Recovery rate R | B8: 0.4 | C8: Assumed. Changing R re-fits every hazard.
A9: Notional | B9: 10000000
A10: Standard coupon (bp) | B10: 100 | C10: Fixed running coupon (IG=100, HY=500).
A11: Premium frequency | B11: Quarterly
A12: Premium day count | B12: ACT/360
A13: Hazard interpolation | B13: Piecewise-constant
A14: Discount curve | B14: SOFR OIS (Curve_Interface)
A15: Protection direction | B15: Buy protection | C15: "Buy protection" or "Sell protection".
A16: Accrual-on-default | B16: Included (midpoint approx.)
A17: Hazard mode | B17: Bootstrap from CDS curve | C17: Bootstrap fits the term structure to CDS_Quotes; Flat overrides every tenor with B18.
A18: Flat hazard rate | B18: 0.015 | C18: Continuously-compounded intensity. Credit-triangle guide: S/(1-R).
A19: Reference entity ticker | B19: =IF(Entities!$F$4="","",Entities!$F$4) | C19: from Entities!F4 - the selected name's ticker
A20: SETTLEMENT / ACCRUAL (white paper p.6-7)
A21: Settlement date T_s | B21: =CDS_Parameters!$B$4+3+IF(WEEKDAY(CDS_Parameters!$B$4,2)>=3,2,0) | C21: T + 3 business days (p.6). 07/21/26 -> 07/24/26, matching the screen.
A22: D(T_s) | B22: =IFERROR(INDEX('Curve_Interface'!$L$8:$L$73,MATCH($B$21,'Curve_Interface'!$K$8:$K$73,1))*(INDEX('Curve_Interface'!$L$8:$L$73,MATCH($B$21,'Curve_Interface'!$K$8:$K$73,1)+1)/INDEX('Curve_Interface'!$L$8:$L$73,MATCH($B$21,'Curve_Interface'!$K$8:$K$73,1)))^(($B$21-INDEX('Curve_Interface'!$K$8:$K$73,MATCH($B$21,'Curve_Interface'!$K$8:$K$73,1)))/(INDEX('Curve_Interface'!$K$8:$K$73,MATCH($B$21,'Curve_Interface'!$K$8:$K$73,1)+1)-INDEX('Curve_Interface'!$K$8:$K$73,MATCH($B$21,'Curve_Interface'!$K$8:$K$73,1)))),INDEX('Curve_Interface'!$L$8:$L$73,MATCH($B$21,'Curve_Interface'!$K$8:$K$73,1))) | C22: Discount factor at settlement, off Curve_Interface. The DF component.
A23: Accrual start T_0 | B23: =IF(MONTH((EDATE($B$5,-3)+IF(WEEKDAY(EDATE($B$5,-3),2)=6,2,IF(WEEKDAY(EDATE($B$5,-3),2)=7,1,0))))<>MONTH(EDATE($B$5,-3)),(EDATE($B$5,-3)-IF(WEEKDAY(EDATE($B$5,-3),2)=6,1,IF(WEEKDAY(EDATE($B$5,-3),2)=7,2,0))),(EDATE($B$5,-3)+IF(WEEKDAY(EDATE($B$5,-3),2)=6,2,IF(WEEKDAY(EDATE($B$5,-3),2)=7,1,0)))) | C23: Previous IMM roll, business-day adjusted.
A24: Accrued days | B24: =MAX(0,CDS_Parameters!$B$4-$B$23+1) | C24: Includes the pricing date (p.7): one more than the daycount difference.
A25: Accrual fraction D0 (ACT/360) | B25: =$B$24/360
A26: PV01 netting term D0 * D(T_s) | B26: =$B$25*$B$22 | C26: Subtracted from the premium leg in (3.3). ~0.083 against RPV01 ~4.4, so it moves the stripped hazards by roughly 2%.
A27: Active entity | B27: =Entities!$B$4 | C27: Picks a row on CDS_Entities. Spreads, recovery and the CDSW targets all follow.
A28: row on CDS_Entities | B28: =IFERROR(MATCH($B$27,CDS_Entities!$A$5:$A$14,0),0)
A29: Recovery from that row | B29: =IFERROR(INDEX(CDS_Entities!$F$5:$F$14,$B$28),"") | C29: Type it into B8 to use it; left manual so a mis-selection cannot silently reprice the book.

Sheet CDS_Quotes
A1: CDS_Quotes
A2: Step 1 (col D) resolves each tenor's CDS ticker from CDS_Parameters!B19; step 2 (col F) quotes it. Col E used only when BDP fails.
K3: BLOOMBERG HELP DESK H#1330731572
A4: Enter each tenor's CDS ticker, or let col D resolve it. Two-step pull per Help Desk H#1330731572, documented in K. | K4: The documented two-step pull, implemented verbatim:
K5: step 1 col D = BDP( <entity>, "CDS_SPREAD_TICKER_nY" ) -> ticker
A6: Tenor | B6: Tenor (yrs) | C6: Maturity | D6: CDS ticker (step 1, live) | E6: Manual spread (bp) | F6: Market spread (bp) | G6: Approx hazard s/(1-R) | H6: Quote source in use | K6: step 2 col F = BDP( <ticker> & " BEST Curncy", "PX_LAST" )
A7: 1Y | B7: 1 | C7: =EDATE('Curve_Interface'!$F$7,3*(4-1)) | D7: =IFERROR(BDP(CDS_Parameters!$B$19,"CDS_SPREAD_TICKER_1Y"),"") | E7: =IFERROR(INDEX(CDS_Entities!$AR$5:$AR$14,CDS_Parameters!$B$28),0) | F7: =IFERROR(BDP(D7&" BEST Curncy","PX_LAST")+0,IFERROR(BDP(D7&" BEST Curncy","PX_MID")+0,E7)) | G7: =(F7/10000)/(1-CDS_Parameters!$B$8) | H7: =IF(ISNUMBER(IFERROR(BDP(D7&" BEST Curncy","PX_LAST")+0,"")),"BDP live","MANUAL (demo)")
A8: 2Y | B8: 2 | C8: =EDATE('Curve_Interface'!$F$7,3*(8-1)) | D8: =IFERROR(BDP(CDS_Parameters!$B$19,"CDS_SPREAD_TICKER_2Y"),"") | E8: =IFERROR(INDEX(CDS_Entities!$AS$5:$AS$14,CDS_Parameters!$B$28),0) | F8: =IFERROR(BDP(D8&" BEST Curncy","PX_LAST")+0,IFERROR(BDP(D8&" BEST Curncy","PX_MID")+0,E8)) | G8: =(F8/10000)/(1-CDS_Parameters!$B$8) | H8: =IF(ISNUMBER(IFERROR(BDP(D8&" BEST Curncy","PX_LAST")+0,"")),"BDP live","MANUAL (demo)") | I8: tenor not in the Help Desk list (1Y/3Y/5Y/7Y/10Y) - CDS_SPREAD_TICKER_2Y may not be a valid field | K8: Their tenors are 1Y 3Y 5Y 7Y 10Y. The 2Y row is ours -
A9: 3Y | B9: 3 | C9: =EDATE('Curve_Interface'!$F$7,3*(12-1)) | D9: =IFERROR(BDP(CDS_Parameters!$B$19,"CDS_SPREAD_TICKER_3Y"),"") | E9: =IFERROR(INDEX(CDS_Entities!$AT$5:$AT$14,CDS_Parameters!$B$28),0) | F9: =IFERROR(BDP(D9&" BEST Curncy","PX_LAST")+0,IFERROR(BDP(D9&" BEST Curncy","PX_MID")+0,E9)) | G9: =(F9/10000)/(1-CDS_Parameters!$B$8) | H9: =IF(ISNUMBER(IFERROR(BDP(D9&" BEST Curncy","PX_LAST")+0,"")),"BDP live","MANUAL (demo)") | K9: CDS_SPREAD_TICKER_2Y may not be a valid field; that row is flagged.
A10: 5Y | B10: 5 | C10: =EDATE('Curve_Interface'!$F$7,3*(20-1)) | D10: =IFERROR(BDP(CDS_Parameters!$B$19,"CDS_SPREAD_TICKER_5Y"),"") | E10: =IFERROR(INDEX(CDS_Entities!$AU$5:$AU$14,CDS_Parameters!$B$28),0) | F10: =IFERROR(BDP(D10&" BEST Curncy","PX_LAST")+0,IFERROR(BDP(D10&" BEST Curncy","PX_MID")+0,E10)) | G10: =(F10/10000)/(1-CDS_Parameters!$B$8) | H10: =IF(ISNUMBER(IFERROR(BDP(D10&" BEST Curncy","PX_LAST")+0,"")),"BDP live","MANUAL (demo)")
A11: 7Y | B11: 7 | C11: =EDATE('Curve_Interface'!$F$7,3*(28-1)) | D11: =IFERROR(BDP(CDS_Parameters!$B$19,"CDS_SPREAD_TICKER_7Y"),"") | E11: =IFERROR(INDEX(CDS_Entities!$AV$5:$AV$14,CDS_Parameters!$B$28),0) | F11: =IFERROR(BDP(D11&" BEST Curncy","PX_LAST")+0,IFERROR(BDP(D11&" BEST Curncy","PX_MID")+0,E11)) | G11: =(F11/10000)/(1-CDS_Parameters!$B$8) | H11: =IF(ISNUMBER(IFERROR(BDP(D11&" BEST Curncy","PX_LAST")+0,"")),"BDP live","MANUAL (demo)") | K11: step 3 they suggest Hazard = S/(1-R), shown in col G.
A12: 10Y | B12: 10 | C12: =EDATE('Curve_Interface'!$F$7,3*(40-1)) | D12: =IFERROR(BDP(CDS_Parameters!$B$19,"CDS_SPREAD_TICKER_10Y"),"") | E12: =IFERROR(INDEX(CDS_Entities!$AW$5:$AW$14,CDS_Parameters!$B$28),0) | F12: =IFERROR(BDP(D12&" BEST Curncy","PX_LAST")+0,IFERROR(BDP(D12&" BEST Curncy","PX_MID")+0,E12)) | G12: =(F12/10000)/(1-CDS_Parameters!$B$8) | H12: =IF(ISNUMBER(IFERROR(BDP(D12&" BEST Curncy","PX_LAST")+0,"")),"BDP live","MANUAL (demo)") | K12: Exact only for a flat curve. We bootstrap instead, which their
K13: own note says to do:
A14: Manual spreads in col E are DEMO values, not market. Col H shows which source each tenor is using. Replace col E or connect a terminal before using any CDS output. | K14: "Bloomberg does not provide a direct zero-coupon CDS spread
K15: output by maturity as an exportable field... you would
A16: Help Desk H#1330731572. Step 1 BDP(ticker,"CDS_SPREAD_TICKER_nY"); step 2 BDP(returned&" BEST Curncy","PX_LAST"). Tenors 1Y/3Y/5Y/7Y/10Y. | K16: bootstrap the hazard-rate curve using the par spreads and an
A17: No Bloomberg export exists for zero-coupon CDS spreads or bootstrapped hazard rates (Help Desk). The credit curve has no external ground truth, unlike the SOFR curve. | K17: assumed recovery rate."
A18: Bloomberg suggest the credit triangle, hazard = S/(1-R). Exact only for a flat curve. Hazard_Solver bootstraps properly; CDS_Validation 13-18 compares the two.
A19: Col E reads CDS_Entities in-use (AR:AW) for the active row: live pull when it resolves, else the manual spread, else 0. Always numeric.

Sheet Hazard_Bootstrap
A1: Hazard_Bootstrap
A2: Piecewise-constant hazard. Col D solved live by Hazard_Solver, no Goal Seek. CDS_Parameters!B17 switches to a flat hazard.
A4: Maturity by maturity: hold earlier hazards fixed, solve the current segment so model spread = market. Col J (repricing error) stays ~0 as inputs move.
A6: Tenor | B6: Maturity | C6: Market spread (bp) | D6: Hazard lambda (solve) | E6: Cum. survival Q(T) | F6: Cum. default 1-Q | G6: RPV01 (risky annuity) | H6: Protection PV factor | I6: Model spread (bp) | J6: Repricing error (bp) | L6: Solver resid
A7: 1Y | B7: =CDS_Quotes!C7 | C7: =CDS_Quotes!F7 | D7: =IF(CDS_Parameters!$B$17="Flat hazard rate",CDS_Parameters!$B$18,Hazard_Solver!$B$46) | E7: =INDEX(CDS_Schedule!$K$7:$K$46,MATCH(B7,CDS_Schedule!$C$7:$C$46,1)) | F7: =1-E7 | G7: =SUMIF(CDS_Schedule!$C$7:$C$46,"<="&B7,CDS_Schedule!$M$7:$M$46)+SUMIF(CDS_Schedule!$C$7:$C$46,"<="&B7,CDS_Schedule!$N$7:$N$46) | H7: =SUMIF(CDS_Schedule!$C$7:$C$46,"<="&B7,CDS_Schedule!$O$7:$O$46) | I7: =(1-CDS_Parameters!$B$8)*H7/(G7-CDS_Parameters!$B$26)*10000 | J7: =I7-C7 | L7: =Hazard_Solver!$D$46
A8: 2Y | B8: =CDS_Quotes!C8 | C8: =CDS_Quotes!F8 | D8: =IF(CDS_Parameters!$B$17="Flat hazard rate",CDS_Parameters!$B$18,Hazard_Solver!$B$89) | E8: =INDEX(CDS_Schedule!$K$7:$K$46,MATCH(B8,CDS_Schedule!$C$7:$C$46,1)) | F8: =1-E8 | G8: =SUMIF(CDS_Schedule!$C$7:$C$46,"<="&B8,CDS_Schedule!$M$7:$M$46)+SUMIF(CDS_Schedule!$C$7:$C$46,"<="&B8,CDS_Schedule!$N$7:$N$46) | H8: =SUMIF(CDS_Schedule!$C$7:$C$46,"<="&B8,CDS_Schedule!$O$7:$O$46) | I8: =(1-CDS_Parameters!$B$8)*H8/(G8-CDS_Parameters!$B$26)*10000 | J8: =I8-C8 | L8: =Hazard_Solver!$D$89
A9: 3Y | B9: =CDS_Quotes!C9 | C9: =CDS_Quotes!F9 | D9: =IF(CDS_Parameters!$B$17="Flat hazard rate",CDS_Parameters!$B$18,Hazard_Solver!$B$132) | E9: =INDEX(CDS_Schedule!$K$7:$K$46,MATCH(B9,CDS_Schedule!$C$7:$C$46,1)) | F9: =1-E9 | G9: =SUMIF(CDS_Schedule!$C$7:$C$46,"<="&B9,CDS_Schedule!$M$7:$M$46)+SUMIF(CDS_Schedule!$C$7:$C$46,"<="&B9,CDS_Schedule!$N$7:$N$46) | H9: =SUMIF(CDS_Schedule!$C$7:$C$46,"<="&B9,CDS_Schedule!$O$7:$O$46) | I9: =(1-CDS_Parameters!$B$8)*H9/(G9-CDS_Parameters!$B$26)*10000 | J9: =I9-C9 | L9: =Hazard_Solver!$D$132
A10: 5Y | B10: =CDS_Quotes!C10 | C10: =CDS_Quotes!F10 | D10: =IF(CDS_Parameters!$B$17="Flat hazard rate",CDS_Parameters!$B$18,Hazard_Solver!$B$175) | E10: =INDEX(CDS_Schedule!$K$7:$K$46,MATCH(B10,CDS_Schedule!$C$7:$C$46,1)) | F10: =1-E10 | G10: =SUMIF(CDS_Schedule!$C$7:$C$46,"<="&B10,CDS_Schedule!$M$7:$M$46)+SUMIF(CDS_Schedule!$C$7:$C$46,"<="&B10,CDS_Schedule!$N$7:$N$46) | H10: =SUMIF(CDS_Schedule!$C$7:$C$46,"<="&B10,CDS_Schedule!$O$7:$O$46) | I10: =(1-CDS_Parameters!$B$8)*H10/(G10-CDS_Parameters!$B$26)*10000 | J10: =I10-C10 | L10: =Hazard_Solver!$D$175
A11: 7Y | B11: =CDS_Quotes!C11 | C11: =CDS_Quotes!F11 | D11: =IF(CDS_Parameters!$B$17="Flat hazard rate",CDS_Parameters!$B$18,Hazard_Solver!$B$218) | E11: =INDEX(CDS_Schedule!$K$7:$K$46,MATCH(B11,CDS_Schedule!$C$7:$C$46,1)) | F11: =1-E11 | G11: =SUMIF(CDS_Schedule!$C$7:$C$46,"<="&B11,CDS_Schedule!$M$7:$M$46)+SUMIF(CDS_Schedule!$C$7:$C$46,"<="&B11,CDS_Schedule!$N$7:$N$46) | H11: =SUMIF(CDS_Schedule!$C$7:$C$46,"<="&B11,CDS_Schedule!$O$7:$O$46) | I11: =(1-CDS_Parameters!$B$8)*H11/(G11-CDS_Parameters!$B$26)*10000 | J11: =I11-C11 | L11: =Hazard_Solver!$D$218
A12: 10Y | B12: =CDS_Quotes!C12 | C12: =CDS_Quotes!F12 | D12: =IF(CDS_Parameters!$B$17="Flat hazard rate",CDS_Parameters!$B$18,Hazard_Solver!$B$261) | E12: =INDEX(CDS_Schedule!$K$7:$K$46,MATCH(B12,CDS_Schedule!$C$7:$C$46,1)) | F12: =1-E12 | G12: =SUMIF(CDS_Schedule!$C$7:$C$46,"<="&B12,CDS_Schedule!$M$7:$M$46)+SUMIF(CDS_Schedule!$C$7:$C$46,"<="&B12,CDS_Schedule!$N$7:$N$46) | H12: =SUMIF(CDS_Schedule!$C$7:$C$46,"<="&B12,CDS_Schedule!$O$7:$O$46) | I12: =(1-CDS_Parameters!$B$8)*H12/(G12-CDS_Parameters!$B$26)*10000 | J12: =I12-C12 | L12: =Hazard_Solver!$D$261

Sheet Hazard_Solver
A1: Hazard_Solver
A2: Solves each piecewise-constant hazard by bisection in cells. Replaces Goal Seek; refits live as spreads, recovery or the SOFR curve move.
A3: Reads only the hazard-independent columns of CDS_Schedule (D alpha, E dt, G DF_end, H DF_mid), so no circular reference. | V3: WHAT THIS SHEET SOLVES
A4: Bracket [0, 3], 30 bisection steps -> resolution ~3e-9. | V4: For each tenor k, find h_k so the model par spread equals the quote.
A5: Objective is (3.3): protection leg minus S x PV01, where PV01 is the premium leg NET of accrued interest x D(T_s) (CDS_Parameters!$B$26).
A6: TENOR 1Y: periods 1-4 - solve lambda1 | V6: (3.3) S = Protection / ( Premium - AccruedInterest*D(T_s) ) at C=1bp
A7: market S (bp) | B7: =Hazard_Bootstrap!$C$7 | C7: S (dec) | D7: =B7/10000 | E7: recovery R | F7: =CDS_Parameters!$B$8
A8: Q(start) | B8: =1 | C8: ProtFixed | D8: =0 | E8: RPV01Fixed | F8: =0 | V8: as a root:
A9: period | F9: 1 | G9: 2 | H9: 3 | I9: 4 | V9: f(h) = (1-R)*ProtCum(h) - S*( RPV01Cum(h) - D0*D(T_s) )
A10: alpha 360 | F10: =CDS_Schedule!$D$7 | G10: =CDS_Schedule!$D$8 | H10: =CDS_Schedule!$D$9 | I10: =CDS_Schedule!$D$10 | J10: 0 | K10: 0 | L10: 0 | M10: 0 | N10: 0 | O10: 0 | P10: 0 | Q10: 0 | V10: ProtCum = ProtFixed + SUM Z(mid)*dPD over this segment
A11: dt 365 | F11: =CDS_Schedule!$E$7 | G11: =CDS_Schedule!$E$8 | H11: =CDS_Schedule!$E$9 | I11: =CDS_Schedule!$E$10 | J11: 0 | K11: 0 | L11: 0 | M11: 0 | N11: 0 | O11: 0 | P11: 0 | Q11: 0 | V11: RPV01Cum = RPV01Fixed + SUM alpha*Z(end)*Q
A12: DF(end) | F12: =CDS_Schedule!$G$7 | G12: =CDS_Schedule!$G$8 | H12: =CDS_Schedule!$G$9 | I12: =CDS_Schedule!$G$10 | J12: 0 | K12: 0 | L12: 0 | M12: 0 | N12: 0 | O12: 0 | P12: 0 | Q12: 0 | V12: + (1/2) SUM alpha*Z(mid)*dPD
A13: DF(mid) | F13: =CDS_Schedule!$H$7 | G13: =CDS_Schedule!$H$8 | H13: =CDS_Schedule!$H$9 | I13: =CDS_Schedule!$H$10 | J13: 0 | K13: 0 | L13: 0 | M13: 0 | N13: 0 | O13: 0 | P13: 0 | Q13: 0
A14: cum dt in seg | F14: =0+F11 | G14: =F14+G11 | H14: =G14+H11 | I14: =H14+I11 | J14: =I14+J11 | K14: =J14+K11 | L14: =K14+L11 | M14: =L14+M11 | N14: =M14+N11 | ... Q14: =P14+Q11 | V14: ProtFixed / RPV01Fixed carry in from the shorter tenors, already solved.
A15: bisection | B15: lo | C15: hi | D15: lambda trial | E15: Q(start) | R15: ProtSeg | S15: RPV01Seg | T15: f(lambda) | V15: That carry IS the bootstrap: only h_k is unknown on each block.
B16: 0 | C16: 3 | D16: =(B16+C16)/2 | E16: =$B$8 | F16: =$B$8*EXP(-$D16*F$14) | G16: =$B$8*EXP(-$D16*G$14) | H16: =$B$8*EXP(-$D16*H$14) | I16: =$B$8*EXP(-$D16*I$14) | J16: =I16 | K16: =J16 | L16: =K16 | M16: =L16 | N16: =M16 | O16: =N16 | P16: =O16 | Q16: =P16 | R16: =SUMPRODUCT($F$13:$Q$13,$E16:$P16-$F16:$Q16) | S16: =SUMPRODUCT($F$10:$Q$10,$F$12:$Q$12,$F16:$Q16)+0.5*SUMPRODUCT($F$10:$Q$10,$F$13:$Q$13,$E16:$P16-$F16:$Q16) | T16: =(1-$F$7)*($D$8+R16)-$D$7*(($F$8+S16)-CDS_Parameters!$B$26)
B17: =IF(T16<0,D16,B16) | C17: =IF(T16<0,C16,D16) | D17: =(B17+C17)/2 | E17: =$B$8 | F17: =$B$8*EXP(-$D17*F$14) | G17: =$B$8*EXP(-$D17*G$14) | H17: =$B$8*EXP(-$D17*H$14) | I17: =$B$8*EXP(-$D17*I$14) | J17: =I17 | K17: =J17 | L17: =K17 | M17: =L17 | N17: =M17 | O17: =N17 | P17: =O17 | Q17: =P17 | R17: =SUMPRODUCT($F$13:$Q$13,$E17:$P17-$F17:$Q17) | S17: =SUMPRODUCT($F$10:$Q$10,$F$12:$Q$12,$F17:$Q17)+0.5*SUMPRODUCT($F$10:$Q$10,$F$13:$Q$13,$E17:$P17-$F17:$Q17) | T17: =(1-$F$7)*($D$8+R17)-$D$7*(($F$8+S17)-CDS_Parameters!$B$26) | V17: survival Q(t) = Q(t_k-1) * exp(-h_k*(t - t_k-1)) B-Model p.5
B18: =IF(T17<0,D17,B17) | C18: =IF(T17<0,C17,D17) | D18: =(B18+C18)/2 | E18: =$B$8 | F18: =$B$8*EXP(-$D18*F$14) | G18: =$B$8*EXP(-$D18*G$14) | H18: =$B$8*EXP(-$D18*H$14) | I18: =$B$8*EXP(-$D18*I$14) | J18: =I18 | K18: =J18 | L18: =K18 | M18: =L18 | N18: =M18 | O18: =N18 | P18: =O18 | Q18: =P18 | R18: =SUMPRODUCT($F$13:$Q$13,$E18:$P18-$F18:$Q18) | S18: =SUMPRODUCT($F$10:$Q$10,$F$12:$Q$12,$F18:$Q18)+0.5*SUMPRODUCT($F$10:$Q$10,$F$13:$Q$13,$E18:$P18-$F18:$Q18) | T18: =(1-$F$7)*($D$8+R18)-$D$7*(($F$8+S18)-CDS_Parameters!$B$26) | V18: method 1-D root search per maturity, earlier hazards held
B19: =IF(T18<0,D18,B18) | C19: =IF(T18<0,C18,D18) | D19: =(B19+C19)/2 | E19: =$B$8 | F19: =$B$8*EXP(-$D19*F$14) | G19: =$B$8*EXP(-$D19*G$14) | H19: =$B$8*EXP(-$D19*H$14) | I19: =$B$8*EXP(-$D19*I$14) | J19: =I19 | K19: =J19 | L19: =K19 | M19: =L19 | N19: =M19 | O19: =N19 | P19: =O19 | Q19: =P19 | R19: =SUMPRODUCT($F$13:$Q$13,$E19:$P19-$F19:$Q19) | S19: =SUMPRODUCT($F$10:$Q$10,$F$12:$Q$12,$F19:$Q19)+0.5*SUMPRODUCT($F$10:$Q$10,$F$13:$Q$13,$E19:$P19-$F19:$Q19) | T19: =(1-$F$7)*($D$8+R19)-$D$7*(($F$8+S19)-CDS_Parameters!$B$26) | V19: B-Model S4 p.8 ; O-T S9, footnote 8 names bisection
B20: =IF(T19<0,D19,B19) | C20: =IF(T19<0,C19,D19) | D20: =(B20+C20)/2 | E20: =$B$8 | F20: =$B$8*EXP(-$D20*F$14) | G20: =$B$8*EXP(-$D20*G$14) | H20: =$B$8*EXP(-$D20*H$14) | I20: =$B$8*EXP(-$D20*I$14) | J20: =I20 | K20: =J20 | L20: =K20 | M20: =L20 | N20: =M20 | O20: =N20 | P20: =O20 | Q20: =P20 | R20: =SUMPRODUCT($F$13:$Q$13,$E20:$P20-$F20:$Q20) | S20: =SUMPRODUCT($F$10:$Q$10,$F$12:$Q$12,$F20:$Q20)+0.5*SUMPRODUCT($F$10:$Q$10,$F$13:$Q$13,$E20:$P20-$F20:$Q20) | T20: =(1-$F$7)*($D$8+R20)-$D$7*(($F$8+S20)-CDS_Parameters!$B$26) | V20: bracket [0,3], 30 halvings -> ~3e-9. h >= 0 is hard (p.8)
B21: =IF(T20<0,D20,B20) | C21: =IF(T20<0,C20,D20) | D21: =(B21+C21)/2 | E21: =$B$8 | F21: =$B$8*EXP(-$D21*F$14) | G21: =$B$8*EXP(-$D21*G$14) | H21: =$B$8*EXP(-$D21*H$14) | I21: =$B$8*EXP(-$D21*I$14) | J21: =I21 | K21: =J21 | L21: =K21 | M21: =L21 | N21: =M21 | O21: =N21 | P21: =O21 | Q21: =P21 | R21: =SUMPRODUCT($F$13:$Q$13,$E21:$P21-$F21:$Q21) | S21: =SUMPRODUCT($F$10:$Q$10,$F$12:$Q$12,$F21:$Q21)+0.5*SUMPRODUCT($F$10:$Q$10,$F$13:$Q$13,$E21:$P21-$F21:$Q21) | T21: =(1-$F$7)*($D$8+R21)-$D$7*(($F$8+S21)-CDS_Parameters!$B$26)
B22: =IF(T21<0,D21,B21) | C22: =IF(T21<0,C21,D21) | D22: =(B22+C22)/2 | E22: =$B$8 | F22: =$B$8*EXP(-$D22*F$14) | G22: =$B$8*EXP(-$D22*G$14) | H22: =$B$8*EXP(-$D22*H$14) | I22: =$B$8*EXP(-$D22*I$14) | J22: =I22 | K22: =J22 | L22: =K22 | M22: =L22 | N22: =M22 | O22: =N22 | P22: =O22 | Q22: =P22 | R22: =SUMPRODUCT($F$13:$Q$13,$E22:$P22-$F22:$Q22) | S22: =SUMPRODUCT($F$10:$Q$10,$F$12:$Q$12,$F22:$Q22)+0.5*SUMPRODUCT($F$10:$Q$10,$F$13:$Q$13,$E22:$P22-$F22:$Q22) | T22: =(1-$F$7)*($D$8+R22)-$D$7*(($F$8+S22)-CDS_Parameters!$B$26)
B23: =IF(T22<0,D22,B22) | C23: =IF(T22<0,C22,D22) | D23: =(B23+C23)/2 | E23: =$B$8 | F23: =$B$8*EXP(-$D23*F$14) | G23: =$B$8*EXP(-$D23*G$14) | H23: =$B$8*EXP(-$D23*H$14) | I23: =$B$8*EXP(-$D23*I$14) | J23: =I23 | K23: =J23 | L23: =K23 | M23: =L23 | N23: =M23 | O23: =N23 | P23: =O23 | Q23: =P23 | R23: =SUMPRODUCT($F$13:$Q$13,$E23:$P23-$F23:$Q23) | S23: =SUMPRODUCT($F$10:$Q$10,$F$12:$Q$12,$F23:$Q23)+0.5*SUMPRODUCT($F$10:$Q$10,$F$13:$Q$13,$E23:$P23-$F23:$Q23) | T23: =(1-$F$7)*($D$8+R23)-$D$7*(($F$8+S23)-CDS_Parameters!$B$26)
B24: =IF(T23<0,D23,B23) | C24: =IF(T23<0,C23,D23) | D24: =(B24+C24)/2 | E24: =$B$8 | F24: =$B$8*EXP(-$D24*F$14) | G24: =$B$8*EXP(-$D24*G$14) | H24: =$B$8*EXP(-$D24*H$14) | I24: =$B$8*EXP(-$D24*I$14) | J24: =I24 | K24: =J24 | L24: =K24 | M24: =L24 | N24: =M24 | O24: =N24 | P24: =O24 | Q24: =P24 | R24: =SUMPRODUCT($F$13:$Q$13,$E24:$P24-$F24:$Q24) | S24: =SUMPRODUCT($F$10:$Q$10,$F$12:$Q$12,$F24:$Q24)+0.5*SUMPRODUCT($F$10:$Q$10,$F$13:$Q$13,$E24:$P24-$F24:$Q24) | T24: =(1-$F$7)*($D$8+R24)-$D$7*(($F$8+S24)-CDS_Parameters!$B$26)
B25: =IF(T24<0,D24,B24) | C25: =IF(T24<0,C24,D24) | D25: =(B25+C25)/2 | E25: =$B$8 | F25: =$B$8*EXP(-$D25*F$14) | G25: =$B$8*EXP(-$D25*G$14) | H25: =$B$8*EXP(-$D25*H$14) | I25: =$B$8*EXP(-$D25*I$14) | J25: =I25 | K25: =J25 | L25: =K25 | M25: =L25 | N25: =M25 | O25: =N25 | P25: =O25 | Q25: =P25 | R25: =SUMPRODUCT($F$13:$Q$13,$E25:$P25-$F25:$Q25) | S25: =SUMPRODUCT($F$10:$Q$10,$F$12:$Q$12,$F25:$Q25)+0.5*SUMPRODUCT($F$10:$Q$10,$F$13:$Q$13,$E25:$P25-$F25:$Q25) | T25: =(1-$F$7)*($D$8+R25)-$D$7*(($F$8+S25)-CDS_Parameters!$B$26)
B26: =IF(T25<0,D25,B25) | C26: =IF(T25<0,C25,D25) | D26: =(B26+C26)/2 | E26: =$B$8 | F26: =$B$8*EXP(-$D26*F$14) | G26: =$B$8*EXP(-$D26*G$14) | H26: =$B$8*EXP(-$D26*H$14) | I26: =$B$8*EXP(-$D26*I$14) | J26: =I26 | K26: =J26 | L26: =K26 | M26: =L26 | N26: =M26 | O26: =N26 | P26: =O26 | Q26: =P26 | R26: =SUMPRODUCT($F$13:$Q$13,$E26:$P26-$F26:$Q26) | S26: =SUMPRODUCT($F$10:$Q$10,$F$12:$Q$12,$F26:$Q26)+0.5*SUMPRODUCT($F$10:$Q$10,$F$13:$Q$13,$E26:$P26-$F26:$Q26) | T26: =(1-$F$7)*($D$8+R26)-$D$7*(($F$8+S26)-CDS_Parameters!$B$26)
B27: =IF(T26<0,D26,B26) | C27: =IF(T26<0,C26,D26) | D27: =(B27+C27)/2 | E27: =$B$8 | F27: =$B$8*EXP(-$D27*F$14) | G27: =$B$8*EXP(-$D27*G$14) | H27: =$B$8*EXP(-$D27*H$14) | I27: =$B$8*EXP(-$D27*I$14) | J27: =I27 | K27: =J27 | L27: =K27 | M27: =L27 | N27: =M27 | O27: =N27 | P27: =O27 | Q27: =P27 | R27: =SUMPRODUCT($F$13:$Q$13,$E27:$P27-$F27:$Q27) | S27: =SUMPRODUCT($F$10:$Q$10,$F$12:$Q$12,$F27:$Q27)+0.5*SUMPRODUCT($F$10:$Q$10,$F$13:$Q$13,$E27:$P27-$F27:$Q27) | T27: =(1-$F$7)*($D$8+R27)-$D$7*(($F$8+S27)-CDS_Parameters!$B$26)
B28: =IF(T27<0,D27,B27) | C28: =IF(T27<0,C27,D27) | D28: =(B28+C28)/2 | E28: =$B$8 | F28: =$B$8*EXP(-$D28*F$14) | G28: =$B$8*EXP(-$D28*G$14) | H28: =$B$8*EXP(-$D28*H$14) | I28: =$B$8*EXP(-$D28*I$14) | J28: =I28 | K28: =J28 | L28: =K28 | M28: =L28 | N28: =M28 | O28: =N28 | P28: =O28 | Q28: =P28 | R28: =SUMPRODUCT($F$13:$Q$13,$E28:$P28-$F28:$Q28) | S28: =SUMPRODUCT($F$10:$Q$10,$F$12:$Q$12,$F28:$Q28)+0.5*SUMPRODUCT($F$10:$Q$10,$F$13:$Q$13,$E28:$P28-$F28:$Q28) | T28: =(1-$F$7)*($D$8+R28)-$D$7*(($F$8+S28)-CDS_Parameters!$B$26)
B29: =IF(T28<0,D28,B28) | C29: =IF(T28<0,C28,D28) | D29: =(B29+C29)/2 | E29: =$B$8 | F29: =$B$8*EXP(-$D29*F$14) | G29: =$B$8*EXP(-$D29*G$14) | H29: =$B$8*EXP(-$D29*H$14) | I29: =$B$8*EXP(-$D29*I$14) | J29: =I29 | K29: =J29 | L29: =K29 | M29: =L29 | N29: =M29 | O29: =N29 | P29: =O29 | Q29: =P29 | R29: =SUMPRODUCT($F$13:$Q$13,$E29:$P29-$F29:$Q29) | S29: =SUMPRODUCT($F$10:$Q$10,$F$12:$Q$12,$F29:$Q29)+0.5*SUMPRODUCT($F$10:$Q$10,$F$13:$Q$13,$E29:$P29-$F29:$Q29) | T29: =(1-$F$7)*($D$8+R29)-$D$7*(($F$8+S29)-CDS_Parameters!$B$26)
B30: =IF(T29<0,D29,B29) | C30: =IF(T29<0,C29,D29) | D30: =(B30+C30)/2 | E30: =$B$8 | F30: =$B$8*EXP(-$D30*F$14) | G30: =$B$8*EXP(-$D30*G$14) | H30: =$B$8*EXP(-$D30*H$14) | I30: =$B$8*EXP(-$D30*I$14) | J30: =I30 | K30: =J30 | L30: =K30 | M30: =L30 | N30: =M30 | O30: =N30 | P30: =O30 | Q30: =P30 | R30: =SUMPRODUCT($F$13:$Q$13,$E30:$P30-$F30:$Q30) | S30: =SUMPRODUCT($F$10:$Q$10,$F$12:$Q$12,$F30:$Q30)+0.5*SUMPRODUCT($F$10:$Q$10,$F$13:$Q$13,$E30:$P30-$F30:$Q30) | T30: =(1-$F$7)*($D$8+R30)-$D$7*(($F$8+S30)-CDS_Parameters!$B$26)
B31: =IF(T30<0,D30,B30) | C31: =IF(T30<0,C30,D30) | D31: =(B31+C31)/2 | E31: =$B$8 | F31: =$B$8*EXP(-$D31*F$14) | G31: =$B$8*EXP(-$D31*G$14) | H31: =$B$8*EXP(-$D31*H$14) | I31: =$B$8*EXP(-$D31*I$14) | J31: =I31 | K31: =J31 | L31: =K31 | M31: =L31 | N31: =M31 | O31: =N31 | P31: =O31 | Q31: =P31 | R31: =SUMPRODUCT($F$13:$Q$13,$E31:$P31-$F31:$Q31) | S31: =SUMPRODUCT($F$10:$Q$10,$F$12:$Q$12,$F31:$Q31)+0.5*SUMPRODUCT($F$10:$Q$10,$F$13:$Q$13,$E31:$P31-$F31:$Q31) | T31: =(1-$F$7)*($D$8+R31)-$D$7*(($F$8+S31)-CDS_Parameters!$B$26)
B32: =IF(T31<0,D31,B31) | C32: =IF(T31<0,C31,D31) | D32: =(B32+C32)/2 | E32: =$B$8 | F32: =$B$8*EXP(-$D32*F$14) | G32: =$B$8*EXP(-$D32*G$14) | H32: =$B$8*EXP(-$D32*H$14) | I32: =$B$8*EXP(-$D32*I$14) | J32: =I32 | K32: =J32 | L32: =K32 | M32: =L32 | N32: =M32 | O32: =N32 | P32: =O32 | Q32: =P32 | R32: =SUMPRODUCT($F$13:$Q$13,$E32:$P32-$F32:$Q32) | S32: =SUMPRODUCT($F$10:$Q$10,$F$12:$Q$12,$F32:$Q32)+0.5*SUMPRODUCT($F$10:$Q$10,$F$13:$Q$13,$E32:$P32-$F32:$Q32) | T32: =(1-$F$7)*($D$8+R32)-$D$7*(($F$8+S32)-CDS_Parameters!$B$26)
... B45: =IF(T44<0,D44,B44) | C45: =IF(T44<0,C44,D44) | D45: =(B45+C45)/2 | E45: =$B$8 | F45: =$B$8*EXP(-$D45*F$14) | G45: =$B$8*EXP(-$D45*G$14) | H45: =$B$8*EXP(-$D45*H$14) | I45: =$B$8*EXP(-$D45*I$14) | J45: =I45 | K45: =J45 | L45: =K45 | M45: =L45 | N45: =M45 | O45: =N45 | P45: =O45 | Q45: =P45 | R45: =SUMPRODUCT($F$13:$Q$13,$E45:$P45-$F45:$Q45) | S45: =SUMPRODUCT($F$10:$Q$10,$F$12:$Q$12,$F45:$Q45)+0.5*SUMPRODUCT($F$10:$Q$10,$F$13:$Q$13,$E45:$P45-$F45:$Q45) | T45: =(1-$F$7)*($D$8+R45)-$D$7*(($F$8+S45)-CDS_Parameters!$B$26)
A46: lambda1 SOLVED | B46: =D45 | C46: resid | D46: =T45 | E46: Q(T_k) | F46: =Q45 | G46: ProtCum | H46: =$D$8+R45 | I46: RPV01Cum | J46: =$F$8+S45 | K46: model S (bp) | L46: =IFERROR((1-$F$7)*H46/J46*10000,0)
A49: TENOR 2Y: periods 5-8 - solve lambda2
A50: market S (bp) | B50: =Hazard_Bootstrap!$C$8 | C50: S (dec) | D50: =B50/10000 | E50: recovery R | F50: =CDS_Parameters!$B$8
A51: Q(start) | B51: =$F$46 | C51: ProtFixed | D51: =$H$46 | E51: RPV01Fixed | F51: =$J$46
A52: period | F52: 5 | G52: 6 | H52: 7 | I52: 8
A53: alpha 360 | F53: =CDS_Schedule!$D$11 | G53: =CDS_Schedule!$D$12 | H53: =CDS_Schedule!$D$13 | I53: =CDS_Schedule!$D$14 | J53: 0 | K53: 0 | L53: 0 | M53: 0 | N53: 0 | O53: 0 | P53: 0 | Q53: 0
A54: dt 365 | F54: =CDS_Schedule!$E$11 | G54: =CDS_Schedule!$E$12 | H54: =CDS_Schedule!$E$13 | I54: =CDS_Schedule!$E$14 | J54: 0 | K54: 0 | L54: 0 | M54: 0 | N54: 0 | O54: 0 | P54: 0 | Q54: 0
A55: DF(end) | F55: =CDS_Schedule!$G$11 | G55: =CDS_Schedule!$G$12 | H55: =CDS_Schedule!$G$13 | I55: =CDS_Schedule!$G$14 | J55: 0 | K55: 0 | L55: 0 | M55: 0 | N55: 0 | O55: 0 | P55: 0 | Q55: 0
A56: DF(mid) | F56: =CDS_Schedule!$H$11 | G56: =CDS_Schedule!$H$12 | H56: =CDS_Schedule!$H$13 | I56: =CDS_Schedule!$H$14 | J56: 0 | K56: 0 | L56: 0 | M56: 0 | N56: 0 | O56: 0 | P56: 0 | Q56: 0
A57: cum dt in seg | F57: =0+F54 | G57: =F57+G54 | H57: =G57+H54 | I57: =H57+I54 | J57: =I57+J54 | K57: =J57+K54 | L57: =K57+L54 | M57: =L57+M54 | N57: =M57+N54 | ... Q57: =P57+Q54
A58: bisection | B58: lo | C58: hi | D58: lambda trial | E58: Q(start) | R58: ProtSeg | S58: RPV01Seg | T58: f(lambda)
B59: 0 | C59: 3 | D59: =(B59+C59)/2 | E59: =$B$51 | F59: =$B$51*EXP(-$D59*F$57) | G59: =$B$51*EXP(-$D59*G$57) | H59: =$B$51*EXP(-$D59*H$57) | I59: =$B$51*EXP(-$D59*I$57) | J59: =I59 | K59: =J59 | L59: =K59 | M59: =L59 | N59: =M59 | O59: =N59 | P59: =O59 | Q59: =P59 | R59: =SUMPRODUCT($F$56:$Q$56,$E59:$P59-$F59:$Q59) | S59: =SUMPRODUCT($F$53:$Q$53,$F$55:$Q$55,$F59:$Q59)+0.5*SUMPRODUCT($F$53:$Q$53,$F$56:$Q$56,$E59:$P59-$F59:$Q59) | T59: =(1-$F$50)*($D$51+R59)-$D$50*(($F$51+S59)-CDS_Parameters!$B$26)
B60: =IF(T59<0,D59,B59) | C60: =IF(T59<0,C59,D59) | D60: =(B60+C60)/2 | E60: =$B$51 | F60: =$B$51*EXP(-$D60*F$57) | G60: =$B$51*EXP(-$D60*G$57) | H60: =$B$51*EXP(-$D60*H$57) | I60: =$B$51*EXP(-$D60*I$57) | J60: =I60 | K60: =J60 | L60: =K60 | M60: =L60 | N60: =M60 | O60: =N60 | P60: =O60 | Q60: =P60 | R60: =SUMPRODUCT($F$56:$Q$56,$E60:$P60-$F60:$Q60) | S60: =SUMPRODUCT($F$53:$Q$53,$F$55:$Q$55,$F60:$Q60)+0.5*SUMPRODUCT($F$53:$Q$53,$F$56:$Q$56,$E60:$P60-$F60:$Q60) | T60: =(1-$F$50)*($D$51+R60)-$D$50*(($F$51+S60)-CDS_Parameters!$B$26)
B61: =IF(T60<0,D60,B60) | C61: =IF(T60<0,C60,D60) | D61: =(B61+C61)/2 | E61: =$B$51 | F61: =$B$51*EXP(-$D61*F$57) | G61: =$B$51*EXP(-$D61*G$57) | H61: =$B$51*EXP(-$D61*H$57) | I61: =$B$51*EXP(-$D61*I$57) | J61: =I61 | K61: =J61 | L61: =K61 | M61: =L61 | N61: =M61 | O61: =N61 | P61: =O61 | Q61: =P61 | R61: =SUMPRODUCT($F$56:$Q$56,$E61:$P61-$F61:$Q61) | S61: =SUMPRODUCT($F$53:$Q$53,$F$55:$Q$55,$F61:$Q61)+0.5*SUMPRODUCT($F$53:$Q$53,$F$56:$Q$56,$E61:$P61-$F61:$Q61) | T61: =(1-$F$50)*($D$51+R61)-$D$50*(($F$51+S61)-CDS_Parameters!$B$26)
B62: =IF(T61<0,D61,B61) | C62: =IF(T61<0,C61,D61) | D62: =(B62+C62)/2 | E62: =$B$51 | F62: =$B$51*EXP(-$D62*F$57) | G62: =$B$51*EXP(-$D62*G$57) | H62: =$B$51*EXP(-$D62*H$57) | I62: =$B$51*EXP(-$D62*I$57) | J62: =I62 | K62: =J62 | L62: =K62 | M62: =L62 | N62: =M62 | O62: =N62 | P62: =O62 | Q62: =P62 | R62: =SUMPRODUCT($F$56:$Q$56,$E62:$P62-$F62:$Q62) | S62: =SUMPRODUCT($F$53:$Q$53,$F$55:$Q$55,$F62:$Q62)+0.5*SUMPRODUCT($F$53:$Q$53,$F$56:$Q$56,$E62:$P62-$F62:$Q62) | T62: =(1-$F$50)*($D$51+R62)-$D$50*(($F$51+S62)-CDS_Parameters!$B$26)
B63: =IF(T62<0,D62,B62) | C63: =IF(T62<0,C62,D62) | D63: =(B63+C63)/2 | E63: =$B$51 | F63: =$B$51*EXP(-$D63*F$57) | G63: =$B$51*EXP(-$D63*G$57) | H63: =$B$51*EXP(-$D63*H$57) | I63: =$B$51*EXP(-$D63*I$57) | J63: =I63 | K63: =J63 | L63: =K63 | M63: =L63 | N63: =M63 | O63: =N63 | P63: =O63 | Q63: =P63 | R63: =SUMPRODUCT($F$56:$Q$56,$E63:$P63-$F63:$Q63) | S63: =SUMPRODUCT($F$53:$Q$53,$F$55:$Q$55,$F63:$Q63)+0.5*SUMPRODUCT($F$53:$Q$53,$F$56:$Q$56,$E63:$P63-$F63:$Q63) | T63: =(1-$F$50)*($D$51+R63)-$D$50*(($F$51+S63)-CDS_Parameters!$B$26)
B64: =IF(T63<0,D63,B63) | C64: =IF(T63<0,C63,D63) | D64: =(B64+C64)/2 | E64: =$B$51 | F64: =$B$51*EXP(-$D64*F$57) | G64: =$B$51*EXP(-$D64*G$57) | H64: =$B$51*EXP(-$D64*H$57) | I64: =$B$51*EXP(-$D64*I$57) | J64: =I64 | K64: =J64 | L64: =K64 | M64: =L64 | N64: =M64 | O64: =N64 | P64: =O64 | Q64: =P64 | R64: =SUMPRODUCT($F$56:$Q$56,$E64:$P64-$F64:$Q64) | S64: =SUMPRODUCT($F$53:$Q$53,$F$55:$Q$55,$F64:$Q64)+0.5*SUMPRODUCT($F$53:$Q$53,$F$56:$Q$56,$E64:$P64-$F64:$Q64) | T64: =(1-$F$50)*($D$51+R64)-$D$50*(($F$51+S64)-CDS_Parameters!$B$26)
B65: =IF(T64<0,D64,B64) | C65: =IF(T64<0,C64,D64) | D65: =(B65+C65)/2 | E65: =$B$51 | F65: =$B$51*EXP(-$D65*F$57) | G65: =$B$51*EXP(-$D65*G$57) | H65: =$B$51*EXP(-$D65*H$57) | I65: =$B$51*EXP(-$D65*I$57) | J65: =I65 | K65: =J65 | L65: =K65 | M65: =L65 | N65: =M65 | O65: =N65 | P65: =O65 | Q65: =P65 | R65: =SUMPRODUCT($F$56:$Q$56,$E65:$P65-$F65:$Q65) | S65: =SUMPRODUCT($F$53:$Q$53,$F$55:$Q$55,$F65:$Q65)+0.5*SUMPRODUCT($F$53:$Q$53,$F$56:$Q$56,$E65:$P65-$F65:$Q65) | T65: =(1-$F$50)*($D$51+R65)-$D$50*(($F$51+S65)-CDS_Parameters!$B$26)
B66: =IF(T65<0,D65,B65) | C66: =IF(T65<0,C65,D65) | D66: =(B66+C66)/2 | E66: =$B$51 | F66: =$B$51*EXP(-$D66*F$57) | G66: =$B$51*EXP(-$D66*G$57) | H66: =$B$51*EXP(-$D66*H$57) | I66: =$B$51*EXP(-$D66*I$57) | J66: =I66 | K66: =J66 | L66: =K66 | M66: =L66 | N66: =M66 | O66: =N66 | P66: =O66 | Q66: =P66 | R66: =SUMPRODUCT($F$56:$Q$56,$E66:$P66-$F66:$Q66) | S66: =SUMPRODUCT($F$53:$Q$53,$F$55:$Q$55,$F66:$Q66)+0.5*SUMPRODUCT($F$53:$Q$53,$F$56:$Q$56,$E66:$P66-$F66:$Q66) | T66: =(1-$F$50)*($D$51+R66)-$D$50*(($F$51+S66)-CDS_Parameters!$B$26)
B67: =IF(T66<0,D66,B66) | C67: =IF(T66<0,C66,D66) | D67: =(B67+C67)/2 | E67: =$B$51 | F67: =$B$51*EXP(-$D67*F$57) | G67: =$B$51*EXP(-$D67*G$57) | H67: =$B$51*EXP(-$D67*H$57) | I67: =$B$51*EXP(-$D67*I$57) | J67: =I67 | K67: =J67 | L67: =K67 | M67: =L67 | N67: =M67 | O67: =N67 | P67: =O67 | Q67: =P67 | R67: =SUMPRODUCT($F$56:$Q$56,$E67:$P67-$F67:$Q67) | S67: =SUMPRODUCT($F$53:$Q$53,$F$55:$Q$55,$F67:$Q67)+0.5*SUMPRODUCT($F$53:$Q$53,$F$56:$Q$56,$E67:$P67-$F67:$Q67) | T67: =(1-$F$50)*($D$51+R67)-$D$50*(($F$51+S67)-CDS_Parameters!$B$26)
B68: =IF(T67<0,D67,B67) | C68: =IF(T67<0,C67,D67) | D68: =(B68+C68)/2 | E68: =$B$51 | F68: =$B$51*EXP(-$D68*F$57) | G68: =$B$51*EXP(-$D68*G$57) | H68: =$B$51*EXP(-$D68*H$57) | I68: =$B$51*EXP(-$D68*I$57) | J68: =I68 | K68: =J68 | L68: =K68 | M68: =L68 | N68: =M68 | O68: =N68 | P68: =O68 | Q68: =P68 | R68: =SUMPRODUCT($F$56:$Q$56,$E68:$P68-$F68:$Q68) | S68: =SUMPRODUCT($F$53:$Q$53,$F$55:$Q$55,$F68:$Q68)+0.5*SUMPRODUCT($F$53:$Q$53,$F$56:$Q$56,$E68:$P68-$F68:$Q68) | T68: =(1-$F$50)*($D$51+R68)-$D$50*(($F$51+S68)-CDS_Parameters!$B$26)
B69: =IF(T68<0,D68,B68) | C69: =IF(T68<0,C68,D68) | D69: =(B69+C69)/2 | E69: =$B$51 | F69: =$B$51*EXP(-$D69*F$57) | G69: =$B$51*EXP(-$D69*G$57) | H69: =$B$51*EXP(-$D69*H$57) | I69: =$B$51*EXP(-$D69*I$57) | J69: =I69 | K69: =J69 | L69: =K69 | M69: =L69 | N69: =M69 | O69: =N69 | P69: =O69 | Q69: =P69 | R69: =SUMPRODUCT($F$56:$Q$56,$E69:$P69-$F69:$Q69) | S69: =SUMPRODUCT($F$53:$Q$53,$F$55:$Q$55,$F69:$Q69)+0.5*SUMPRODUCT($F$53:$Q$53,$F$56:$Q$56,$E69:$P69-$F69:$Q69) | T69: =(1-$F$50)*($D$51+R69)-$D$50*(($F$51+S69)-CDS_Parameters!$B$26)
B70: =IF(T69<0,D69,B69) | C70: =IF(T69<0,C69,D69) | D70: =(B70+C70)/2 | E70: =$B$51 | F70: =$B$51*EXP(-$D70*F$57) | G70: =$B$51*EXP(-$D70*G$57) | H70: =$B$51*EXP(-$D70*H$57) | I70: =$B$51*EXP(-$D70*I$57) | J70: =I70 | K70: =J70 | L70: =K70 | M70: =L70 | N70: =M70 | O70: =N70 | P70: =O70 | Q70: =P70 | R70: =SUMPRODUCT($F$56:$Q$56,$E70:$P70-$F70:$Q70) | S70: =SUMPRODUCT($F$53:$Q$53,$F$55:$Q$55,$F70:$Q70)+0.5*SUMPRODUCT($F$53:$Q$53,$F$56:$Q$56,$E70:$P70-$F70:$Q70) | T70: =(1-$F$50)*($D$51+R70)-$D$50*(($F$51+S70)-CDS_Parameters!$B$26)
B71: =IF(T70<0,D70,B70) | C71: =IF(T70<0,C70,D70) | D71: =(B71+C71)/2 | E71: =$B$51 | F71: =$B$51*EXP(-$D71*F$57) | G71: =$B$51*EXP(-$D71*G$57) | H71: =$B$51*EXP(-$D71*H$57) | I71: =$B$51*EXP(-$D71*I$57) | J71: =I71 | K71: =J71 | L71: =K71 | M71: =L71 | N71: =M71 | O71: =N71 | P71: =O71 | Q71: =P71 | R71: =SUMPRODUCT($F$56:$Q$56,$E71:$P71-$F71:$Q71) | S71: =SUMPRODUCT($F$53:$Q$53,$F$55:$Q$55,$F71:$Q71)+0.5*SUMPRODUCT($F$53:$Q$53,$F$56:$Q$56,$E71:$P71-$F71:$Q71) | T71: =(1-$F$50)*($D$51+R71)-$D$50*(($F$51+S71)-CDS_Parameters!$B$26)
... B88: =IF(T87<0,D87,B87) | C88: =IF(T87<0,C87,D87) | D88: =(B88+C88)/2 | E88: =$B$51 | F88: =$B$51*EXP(-$D88*F$57) | G88: =$B$51*EXP(-$D88*G$57) | H88: =$B$51*EXP(-$D88*H$57) | I88: =$B$51*EXP(-$D88*I$57) | J88: =I88 | K88: =J88 | L88: =K88 | M88: =L88 | N88: =M88 | O88: =N88 | P88: =O88 | Q88: =P88 | R88: =SUMPRODUCT($F$56:$Q$56,$E88:$P88-$F88:$Q88) | S88: =SUMPRODUCT($F$53:$Q$53,$F$55:$Q$55,$F88:$Q88)+0.5*SUMPRODUCT($F$53:$Q$53,$F$56:$Q$56,$E88:$P88-$F88:$Q88) | T88: =(1-$F$50)*($D$51+R88)-$D$50*(($F$51+S88)-CDS_Parameters!$B$26)
A89: lambda2 SOLVED | B89: =D88 | C89: resid | D89: =T88 | E89: Q(T_k) | F89: =Q88 | G89: ProtCum | H89: =$D$51+R88 | I89: RPV01Cum | J89: =$F$51+S88 | K89: model S (bp) | L89: =IFERROR((1-$F$50)*H89/J89*10000,0)
A92: TENOR 3Y: periods 9-12 - solve lambda3
A93: market S (bp) | B93: =Hazard_Bootstrap!$C$9 | C93: S (dec) | D93: =B93/10000 | E93: recovery R | F93: =CDS_Parameters!$B$8
A94: Q(start) | B94: =$F$89 | C94: ProtFixed | D94: =$H$89 | E94: RPV01Fixed | F94: =$J$89
A95: period | F95: 9 | G95: 10 | H95: 11 | I95: 12
A96: alpha 360 | F96: =CDS_Schedule!$D$15 | G96: =CDS_Schedule!$D$16 | H96: =CDS_Schedule!$D$17 | I96: =CDS_Schedule!$D$18 | J96: 0 | K96: 0 | L96: 0 | M96: 0 | N96: 0 | O96: 0 | P96: 0 | Q96: 0
A97: dt 365 | F97: =CDS_Schedule!$E$15 | G97: =CDS_Schedule!$E$16 | H97: =CDS_Schedule!$E$17 | I97: =CDS_Schedule!$E$18 | J97: 0 | K97: 0 | L97: 0 | M97: 0 | N97: 0 | O97: 0 | P97: 0 | Q97: 0
A98: DF(end) | F98: =CDS_Schedule!$G$15 | G98: =CDS_Schedule!$G$16 | H98: =CDS_Schedule!$G$17 | I98: =CDS_Schedule!$G$18 | J98: 0 | K98: 0 | L98: 0 | M98: 0 | N98: 0 | O98: 0 | P98: 0 | Q98: 0
A99: DF(mid) | F99: =CDS_Schedule!$H$15 | G99: =CDS_Schedule!$H$16 | H99: =CDS_Schedule!$H$17 | I99: =CDS_Schedule!$H$18 | J99: 0 | K99: 0 | L99: 0 | M99: 0 | N99: 0 | O99: 0 | P99: 0 | Q99: 0
A100: cum dt in seg | F100: =0+F97 | G100: =F100+G97 | H100: =G100+H97 | I100: =H100+I97 | J100: =I100+J97 | K100: =J100+K97 | L100: =K100+L97 | M100: =L100+M97 | N100: =M100+N97 | ... Q100: =P100+Q97
A101: bisection | B101: lo | C101: hi | D101: lambda trial | E101: Q(start) | R101: ProtSeg | S101: RPV01Seg | T101: f(lambda)
B102: 0 | C102: 3 | D102: =(B102+C102)/2 | E102: =$B$94 | F102: =$B$94*EXP(-$D102*F$100) | G102: =$B$94*EXP(-$D102*G$100) | H102: =$B$94*EXP(-$D102*H$100) | I102: =$B$94*EXP(-$D102*I$100) | J102: =I102 | K102: =J102 | L102: =K102 | M102: =L102 | N102: =M102 | O102: =N102 | P102: =O102 | Q102: =P102 | R102: =SUMPRODUCT($F$99:$Q$99,$E102:$P102-$F102:$Q102) | S102: =SUMPRODUCT($F$96:$Q$96,$F$98:$Q$98,$F102:$Q102)+0.5*SUMPRODUCT($F$96:$Q$96,$F$99:$Q$99,$E102:$P102-$F102:$Q102) | T102: =(1-$F$93)*($D$94+R102)-$D$93*(($F$94+S102)-CDS_Parameters!$B$26)
B103: =IF(T102<0,D102,B102) | C103: =IF(T102<0,C102,D102) | D103: =(B103+C103)/2 | E103: =$B$94 | F103: =$B$94*EXP(-$D103*F$100) | G103: =$B$94*EXP(-$D103*G$100) | H103: =$B$94*EXP(-$D103*H$100) | I103: =$B$94*EXP(-$D103*I$100) | J103: =I103 | K103: =J103 | L103: =K103 | M103: =L103 | N103: =M103 | O103: =N103 | P103: =O103 | Q103: =P103 | R103: =SUMPRODUCT($F$99:$Q$99,$E103:$P103-$F103:$Q103) | S103: =SUMPRODUCT($F$96:$Q$96,$F$98:$Q$98,$F103:$Q103)+0.5*SUMPRODUCT($F$96:$Q$96,$F$99:$Q$99,$E103:$P103-$F103:$Q103) | T103: =(1-$F$93)*($D$94+R103)-$D$93*(($F$94+S103)-CDS_Parameters!$B$26)
B104: =IF(T103<0,D103,B103) | C104: =IF(T103<0,C103,D103) | D104: =(B104+C104)/2 | E104: =$B$94 | F104: =$B$94*EXP(-$D104*F$100) | G104: =$B$94*EXP(-$D104*G$100) | H104: =$B$94*EXP(-$D104*H$100) | I104: =$B$94*EXP(-$D104*I$100) | J104: =I104 | K104: =J104 | L104: =K104 | M104: =L104 | N104: =M104 | O104: =N104 | P104: =O104 | Q104: =P104 | R104: =SUMPRODUCT($F$99:$Q$99,$E104:$P104-$F104:$Q104) | S104: =SUMPRODUCT($F$96:$Q$96,$F$98:$Q$98,$F104:$Q104)+0.5*SUMPRODUCT($F$96:$Q$96,$F$99:$Q$99,$E104:$P104-$F104:$Q104) | T104: =(1-$F$93)*($D$94+R104)-$D$93*(($F$94+S104)-CDS_Parameters!$B$26)
B105: =IF(T104<0,D104,B104) | C105: =IF(T104<0,C104,D104) | D105: =(B105+C105)/2 | E105: =$B$94 | F105: =$B$94*EXP(-$D105*F$100) | G105: =$B$94*EXP(-$D105*G$100) | H105: =$B$94*EXP(-$D105*H$100) | I105: =$B$94*EXP(-$D105*I$100) | J105: =I105 | K105: =J105 | L105: =K105 | M105: =L105 | N105: =M105 | O105: =N105 | P105: =O105 | Q105: =P105 | R105: =SUMPRODUCT($F$99:$Q$99,$E105:$P105-$F105:$Q105) | S105: =SUMPRODUCT($F$96:$Q$96,$F$98:$Q$98,$F105:$Q105)+0.5*SUMPRODUCT($F$96:$Q$96,$F$99:$Q$99,$E105:$P105-$F105:$Q105) | T105: =(1-$F$93)*($D$94+R105)-$D$93*(($F$94+S105)-CDS_Parameters!$B$26)
B106: =IF(T105<0,D105,B105) | C106: =IF(T105<0,C105,D105) | D106: =(B106+C106)/2 | E106: =$B$94 | F106: =$B$94*EXP(-$D106*F$100) | G106: =$B$94*EXP(-$D106*G$100) | H106: =$B$94*EXP(-$D106*H$100) | I106: =$B$94*EXP(-$D106*I$100) | J106: =I106 | K106: =J106 | L106: =K106 | M106: =L106 | N106: =M106 | O106: =N106 | P106: =O106 | Q106: =P106 | R106: =SUMPRODUCT($F$99:$Q$99,$E106:$P106-$F106:$Q106) | S106: =SUMPRODUCT($F$96:$Q$96,$F$98:$Q$98,$F106:$Q106)+0.5*SUMPRODUCT($F$96:$Q$96,$F$99:$Q$99,$E106:$P106-$F106:$Q106) | T106: =(1-$F$93)*($D$94+R106)-$D$93*(($F$94+S106)-CDS_Parameters!$B$26)
B107: =IF(T106<0,D106,B106) | C107: =IF(T106<0,C106,D106) | D107: =(B107+C107)/2 | E107: =$B$94 | F107: =$B$94*EXP(-$D107*F$100) | G107: =$B$94*EXP(-$D107*G$100) | H107: =$B$94*EXP(-$D107*H$100) | I107: =$B$94*EXP(-$D107*I$100) | J107: =I107 | K107: =J107 | L107: =K107 | M107: =L107 | N107: =M107 | O107: =N107 | P107: =O107 | Q107: =P107 | R107: =SUMPRODUCT($F$99:$Q$99,$E107:$P107-$F107:$Q107) | S107: =SUMPRODUCT($F$96:$Q$96,$F$98:$Q$98,$F107:$Q107)+0.5*SUMPRODUCT($F$96:$Q$96,$F$99:$Q$99,$E107:$P107-$F107:$Q107) | T107: =(1-$F$93)*($D$94+R107)-$D$93*(($F$94+S107)-CDS_Parameters!$B$26)
B108: =IF(T107<0,D107,B107) | C108: =IF(T107<0,C107,D107) | D108: =(B108+C108)/2 | E108: =$B$94 | F108: =$B$94*EXP(-$D108*F$100) | G108: =$B$94*EXP(-$D108*G$100) | H108: =$B$94*EXP(-$D108*H$100) | I108: =$B$94*EXP(-$D108*I$100) | J108: =I108 | K108: =J108 | L108: =K108 | M108: =L108 | N108: =M108 | O108: =N108 | P108: =O108 | Q108: =P108 | R108: =SUMPRODUCT($F$99:$Q$99,$E108:$P108-$F108:$Q108) | S108: =SUMPRODUCT($F$96:$Q$96,$F$98:$Q$98,$F108:$Q108)+0.5*SUMPRODUCT($F$96:$Q$96,$F$99:$Q$99,$E108:$P108-$F108:$Q108) | T108: =(1-$F$93)*($D$94+R108)-$D$93*(($F$94+S108)-CDS_Parameters!$B$26)
B109: =IF(T108<0,D108,B108) | C109: =IF(T108<0,C108,D108) | D109: =(B109+C109)/2 | E109: =$B$94 | F109: =$B$94*EXP(-$D109*F$100) | G109: =$B$94*EXP(-$D109*G$100) | H109: =$B$94*EXP(-$D109*H$100) | I109: =$B$94*EXP(-$D109*I$100) | J109: =I109 | K109: =J109 | L109: =K109 | M109: =L109 | N109: =M109 | O109: =N109 | P109: =O109 | Q109: =P109 | R109: =SUMPRODUCT($F$99:$Q$99,$E109:$P109-$F109:$Q109) | S109: =SUMPRODUCT($F$96:$Q$96,$F$98:$Q$98,$F109:$Q109)+0.5*SUMPRODUCT($F$96:$Q$96,$F$99:$Q$99,$E109:$P109-$F109:$Q109) | T109: =(1-$F$93)*($D$94+R109)-$D$93*(($F$94+S109)-CDS_Parameters!$B$26)
B110: =IF(T109<0,D109,B109) | C110: =IF(T109<0,C109,D109) | D110: =(B110+C110)/2 | E110: =$B$94 | F110: =$B$94*EXP(-$D110*F$100) | G110: =$B$94*EXP(-$D110*G$100) | H110: =$B$94*EXP(-$D110*H$100) | I110: =$B$94*EXP(-$D110*I$100) | J110: =I110 | K110: =J110 | L110: =K110 | M110: =L110 | N110: =M110 | O110: =N110 | P110: =O110 | Q110: =P110 | R110: =SUMPRODUCT($F$99:$Q$99,$E110:$P110-$F110:$Q110) | S110: =SUMPRODUCT($F$96:$Q$96,$F$98:$Q$98,$F110:$Q110)+0.5*SUMPRODUCT($F$96:$Q$96,$F$99:$Q$99,$E110:$P110-$F110:$Q110) | T110: =(1-$F$93)*($D$94+R110)-$D$93*(($F$94+S110)-CDS_Parameters!$B$26)
B111: =IF(T110<0,D110,B110) | C111: =IF(T110<0,C110,D110) | D111: =(B111+C111)/2 | E111: =$B$94 | F111: =$B$94*EXP(-$D111*F$100) | G111: =$B$94*EXP(-$D111*G$100) | H111: =$B$94*EXP(-$D111*H$100) | I111: =$B$94*EXP(-$D111*I$100) | J111: =I111 | K111: =J111 | L111: =K111 | M111: =L111 | N111: =M111 | O111: =N111 | P111: =O111 | Q111: =P111 | R111: =SUMPRODUCT($F$99:$Q$99,$E111:$P111-$F111:$Q111) | S111: =SUMPRODUCT($F$96:$Q$96,$F$98:$Q$98,$F111:$Q111)+0.5*SUMPRODUCT($F$96:$Q$96,$F$99:$Q$99,$E111:$P111-$F111:$Q111) | T111: =(1-$F$93)*($D$94+R111)-$D$93*(($F$94+S111)-CDS_Parameters!$B$26)
B112: =IF(T111<0,D111,B111) | C112: =IF(T111<0,C111,D111) | D112: =(B112+C112)/2 | E112: =$B$94 | F112: =$B$94*EXP(-$D112*F$100) | G112: =$B$94*EXP(-$D112*G$100) | H112: =$B$94*EXP(-$D112*H$100) | I112: =$B$94*EXP(-$D112*I$100) | J112: =I112 | K112: =J112 | L112: =K112 | M112: =L112 | N112: =M112 | O112: =N112 | P112: =O112 | Q112: =P112 | R112: =SUMPRODUCT($F$99:$Q$99,$E112:$P112-$F112:$Q112) | S112: =SUMPRODUCT($F$96:$Q$96,$F$98:$Q$98,$F112:$Q112)+0.5*SUMPRODUCT($F$96:$Q$96,$F$99:$Q$99,$E112:$P112-$F112:$Q112) | T112: =(1-$F$93)*($D$94+R112)-$D$93*(($F$94+S112)-CDS_Parameters!$B$26)
B113: =IF(T112<0,D112,B112) | C113: =IF(T112<0,C112,D112) | D113: =(B113+C113)/2 | E113: =$B$94 | F113: =$B$94*EXP(-$D113*F$100) | G113: =$B$94*EXP(-$D113*G$100) | H113: =$B$94*EXP(-$D113*H$100) | I113: =$B$94*EXP(-$D113*I$100) | J113: =I113 | K113: =J113 | L113: =K113 | M113: =L113 | N113: =M113 | O113: =N113 | P113: =O113 | Q113: =P113 | R113: =SUMPRODUCT($F$99:$Q$99,$E113:$P113-$F113:$Q113) | S113: =SUMPRODUCT($F$96:$Q$96,$F$98:$Q$98,$F113:$Q113)+0.5*SUMPRODUCT($F$96:$Q$96,$F$99:$Q$99,$E113:$P113-$F113:$Q113) | T113: =(1-$F$93)*($D$94+R113)-$D$93*(($F$94+S113)-CDS_Parameters!$B$26)
B114: =IF(T113<0,D113,B113) | C114: =IF(T113<0,C113,D113) | D114: =(B114+C114)/2 | E114: =$B$94 | F114: =$B$94*EXP(-$D114*F$100) | G114: =$B$94*EXP(-$D114*G$100) | H114: =$B$94*EXP(-$D114*H$100) | I114: =$B$94*EXP(-$D114*I$100) | J114: =I114 | K114: =J114 | L114: =K114 | M114: =L114 | N114: =M114 | O114: =N114 | P114: =O114 | Q114: =P114 | R114: =SUMPRODUCT($F$99:$Q$99,$E114:$P114-$F114:$Q114) | S114: =SUMPRODUCT($F$96:$Q$96,$F$98:$Q$98,$F114:$Q114)+0.5*SUMPRODUCT($F$96:$Q$96,$F$99:$Q$99,$E114:$P114-$F114:$Q114) | T114: =(1-$F$93)*($D$94+R114)-$D$93*(($F$94+S114)-CDS_Parameters!$B$26)
... B131: =IF(T130<0,D130,B130) | C131: =IF(T130<0,C130,D130) | D131: =(B131+C131)/2 | E131: =$B$94 | F131: =$B$94*EXP(-$D131*F$100) | G131: =$B$94*EXP(-$D131*G$100) | H131: =$B$94*EXP(-$D131*H$100) | I131: =$B$94*EXP(-$D131*I$100) | J131: =I131 | K131: =J131 | L131: =K131 | M131: =L131 | N131: =M131 | O131: =N131 | P131: =O131 | Q131: =P131 | R131: =SUMPRODUCT($F$99:$Q$99,$E131:$P131-$F131:$Q131) | S131: =SUMPRODUCT($F$96:$Q$96,$F$98:$Q$98,$F131:$Q131)+0.5*SUMPRODUCT($F$96:$Q$96,$F$99:$Q$99,$E131:$P131-$F131:$Q131) | T131: =(1-$F$93)*($D$94+R131)-$D$93*(($F$94+S131)-CDS_Parameters!$B$26)
A132: lambda3 SOLVED | B132: =D131 | C132: resid | D132: =T131 | E132: Q(T_k) | F132: =Q131 | G132: ProtCum | H132: =$D$94+R131 | I132: RPV01Cum | J132: =$F$94+S131 | K132: model S (bp) | L132: =IFERROR((1-$F$93)*H132/J132*10000,0)
A135: TENOR 5Y: periods 13-20 - solve lambda4
A136: market S (bp) | B136: =Hazard_Bootstrap!$C$10 | C136: S (dec) | D136: =B136/10000 | E136: recovery R | F136: =CDS_Parameters!$B$8
A137: Q(start) | B137: =$F$132 | C137: ProtFixed | D137: =$H$132 | E137: RPV01Fixed | F137: =$J$132
A138: period | F138: 13 | G138: 14 | H138: 15 | I138: 16 | J138: 17 | K138: 18 | L138: 19 | M138: 20
A139: alpha 360 | F139: =CDS_Schedule!$D$19 | G139: =CDS_Schedule!$D$20 | H139: =CDS_Schedule!$D$21 | I139: =CDS_Schedule!$D$22 | J139: =CDS_Schedule!$D$23 | K139: =CDS_Schedule!$D$24 | L139: =CDS_Schedule!$D$25 | M139: =CDS_Schedule!$D$26 | N139: 0 | O139: 0 | P139: 0 | Q139: 0
A140: dt 365 | F140: =CDS_Schedule!$E$19 | G140: =CDS_Schedule!$E$20 | H140: =CDS_Schedule!$E$21 | I140: =CDS_Schedule!$E$22 | J140: =CDS_Schedule!$E$23 | K140: =CDS_Schedule!$E$24 | L140: =CDS_Schedule!$E$25 | M140: =CDS_Schedule!$E$26 | N140: 0 | O140: 0 | P140: 0 | Q140: 0
A141: DF(end) | F141: =CDS_Schedule!$G$19 | G141: =CDS_Schedule!$G$20 | H141: =CDS_Schedule!$G$21 | I141: =CDS_Schedule!$G$22 | J141: =CDS_Schedule!$G$23 | K141: =CDS_Schedule!$G$24 | L141: =CDS_Schedule!$G$25 | M141: =CDS_Schedule!$G$26 | N141: 0 | O141: 0 | P141: 0 | Q141: 0
A142: DF(mid) | F142: =CDS_Schedule!$H$19 | G142: =CDS_Schedule!$H$20 | H142: =CDS_Schedule!$H$21 | I142: =CDS_Schedule!$H$22 | J142: =CDS_Schedule!$H$23 | K142: =CDS_Schedule!$H$24 | L142: =CDS_Schedule!$H$25 | M142: =CDS_Schedule!$H$26 | N142: 0 | O142: 0 | P142: 0 | Q142: 0
A143: cum dt in seg | F143: =0+F140 | G143: =F143+G140 | H143: =G143+H140 | I143: =H143+I140 | J143: =I143+J140 | K143: =J143+K140 | L143: =K143+L140 | M143: =L143+M140 | N143: =M143+N140 | ... Q143: =P143+Q140
A144: bisection | B144: lo | C144: hi | D144: lambda trial | E144: Q(start) | R144: ProtSeg | S144: RPV01Seg | T144: f(lambda)
B145: 0 | C145: 3 | D145: =(B145+C145)/2 | E145: =$B$137 | F145: =$B$137*EXP(-$D145*F$143) | G145: =$B$137*EXP(-$D145*G$143) | H145: =$B$137*EXP(-$D145*H$143) | I145: =$B$137*EXP(-$D145*I$143) | J145: =$B$137*EXP(-$D145*J$143) | K145: =$B$137*EXP(-$D145*K$143) | L145: =$B$137*EXP(-$D145*L$143) | M145: =$B$137*EXP(-$D145*M$143) | N145: =M145 | O145: =N145 | P145: =O145 | Q145: =P145 | R145: =SUMPRODUCT($F$142:$Q$142,$E145:$P145-$F145:$Q145) | S145: =SUMPRODUCT($F$139:$Q$139,$F$141:$Q$141,$F145:$Q145)+0.5*SUMPRODUCT($F$139:$Q$139,$F$142:$Q$142,$E145:$P145-$F145:$Q145) | T145: =(1-$F$136)*($D$137+R145)-$D$136*(($F$137+S145)-CDS_Parameters!$B$26)
B146: =IF(T145<0,D145,B145) | C146: =IF(T145<0,C145,D145) | D146: =(B146+C146)/2 | E146: =$B$137 | F146: =$B$137*EXP(-$D146*F$143) | G146: =$B$137*EXP(-$D146*G$143) | H146: =$B$137*EXP(-$D146*H$143) | I146: =$B$137*EXP(-$D146*I$143) | J146: =$B$137*EXP(-$D146*J$143) | K146: =$B$137*EXP(-$D146*K$143) | L146: =$B$137*EXP(-$D146*L$143) | M146: =$B$137*EXP(-$D146*M$143) | N146: =M146 | O146: =N146 | P146: =O146 | Q146: =P146 | R146: =SUMPRODUCT($F$142:$Q$142,$E146:$P146-$F146:$Q146) | S146: =SUMPRODUCT($F$139:$Q$139,$F$141:$Q$141,$F146:$Q146)+0.5*SUMPRODUCT($F$139:$Q$139,$F$142:$Q$142,$E146:$P146-$F146:$Q146) | T146: =(1-$F$136)*($D$137+R146)-$D$136*(($F$137+S146)-CDS_Parameters!$B$26)
B147: =IF(T146<0,D146,B146) | C147: =IF(T146<0,C146,D146) | D147: =(B147+C147)/2 | E147: =$B$137 | F147: =$B$137*EXP(-$D147*F$143) | G147: =$B$137*EXP(-$D147*G$143) | H147: =$B$137*EXP(-$D147*H$143) | I147: =$B$137*EXP(-$D147*I$143) | J147: =$B$137*EXP(-$D147*J$143) | K147: =$B$137*EXP(-$D147*K$143) | L147: =$B$137*EXP(-$D147*L$143) | M147: =$B$137*EXP(-$D147*M$143) | N147: =M147 | O147: =N147 | P147: =O147 | Q147: =P147 | R147: =SUMPRODUCT($F$142:$Q$142,$E147:$P147-$F147:$Q147) | S147: =SUMPRODUCT($F$139:$Q$139,$F$141:$Q$141,$F147:$Q147)+0.5*SUMPRODUCT($F$139:$Q$139,$F$142:$Q$142,$E147:$P147-$F147:$Q147) | T147: =(1-$F$136)*($D$137+R147)-$D$136*(($F$137+S147)-CDS_Parameters!$B$26)
B148: =IF(T147<0,D147,B147) | C148: =IF(T147<0,C147,D147) | D148: =(B148+C148)/2 | E148: =$B$137 | F148: =$B$137*EXP(-$D148*F$143) | G148: =$B$137*EXP(-$D148*G$143) | H148: =$B$137*EXP(-$D148*H$143) | I148: =$B$137*EXP(-$D148*I$143) | J148: =$B$137*EXP(-$D148*J$143) | K148: =$B$137*EXP(-$D148*K$143) | L148: =$B$137*EXP(-$D148*L$143) | M148: =$B$137*EXP(-$D148*M$143) | N148: =M148 | O148: =N148 | P148: =O148 | Q148: =P148 | R148: =SUMPRODUCT($F$142:$Q$142,$E148:$P148-$F148:$Q148) | S148: =SUMPRODUCT($F$139:$Q$139,$F$141:$Q$141,$F148:$Q148)+0.5*SUMPRODUCT($F$139:$Q$139,$F$142:$Q$142,$E148:$P148-$F148:$Q148) | T148: =(1-$F$136)*($D$137+R148)-$D$136*(($F$137+S148)-CDS_Parameters!$B$26)
B149: =IF(T148<0,D148,B148) | C149: =IF(T148<0,C148,D148) | D149: =(B149+C149)/2 | E149: =$B$137 | F149: =$B$137*EXP(-$D149*F$143) | G149: =$B$137*EXP(-$D149*G$143) | H149: =$B$137*EXP(-$D149*H$143) | I149: =$B$137*EXP(-$D149*I$143) | J149: =$B$137*EXP(-$D149*J$143) | K149: =$B$137*EXP(-$D149*K$143) | L149: =$B$137*EXP(-$D149*L$143) | M149: =$B$137*EXP(-$D149*M$143) | N149: =M149 | O149: =N149 | P149: =O149 | Q149: =P149 | R149: =SUMPRODUCT($F$142:$Q$142,$E149:$P149-$F149:$Q149) | S149: =SUMPRODUCT($F$139:$Q$139,$F$141:$Q$141,$F149:$Q149)+0.5*SUMPRODUCT($F$139:$Q$139,$F$142:$Q$142,$E149:$P149-$F149:$Q149) | T149: =(1-$F$136)*($D$137+R149)-$D$136*(($F$137+S149)-CDS_Parameters!$B$26)
B150: =IF(T149<0,D149,B149) | C150: =IF(T149<0,C149,D149) | D150: =(B150+C150)/2 | E150: =$B$137 | F150: =$B$137*EXP(-$D150*F$143) | G150: =$B$137*EXP(-$D150*G$143) | H150: =$B$137*EXP(-$D150*H$143) | I150: =$B$137*EXP(-$D150*I$143) | J150: =$B$137*EXP(-$D150*J$143) | K150: =$B$137*EXP(-$D150*K$143) | L150: =$B$137*EXP(-$D150*L$143) | M150: =$B$137*EXP(-$D150*M$143) | N150: =M150 | O150: =N150 | P150: =O150 | Q150: =P150 | R150: =SUMPRODUCT($F$142:$Q$142,$E150:$P150-$F150:$Q150) | S150: =SUMPRODUCT($F$139:$Q$139,$F$141:$Q$141,$F150:$Q150)+0.5*SUMPRODUCT($F$139:$Q$139,$F$142:$Q$142,$E150:$P150-$F150:$Q150) | T150: =(1-$F$136)*($D$137+R150)-$D$136*(($F$137+S150)-CDS_Parameters!$B$26)
...

Sheet CDS_Schedule
A1: CDS_Schedule
A2: Quarterly premium & default schedule to 10Y. DF from the shared SOFR curve; survival from the hazard curve.
Q3: WHAT EACH COLUMN COMPUTES
A4: One row per quarterly coupon period. DF(end) and DF(mid) interpolate the SOFR curve; hazard is the piecewise-constant lambda for the segment, by pay date. Q(end) = Q(prev)*exp(-hazard*dt). See Model_Notes. | Q4: Z(.) is the bootstrapped SOFR curve via Curve_Interface (B-Model p.6).
P5: DF(end)/DF(mid) honour the interpolation selector at Curve_Interface!J7. Default is step-function forward, which is the method verified against the S490 screen.
A6: Period | B6: Accrual start | C6: Pay date | D6: alpha ACT/360 | E6: dt ACT/365 | F6: T (yrs) | G6: DF(end) | H6: DF(mid) | I6: hazard | J6: Q(prev) | K6: Q(end) | L6: delta PD | M6: Premium factor | N6: Accrual factor | O6: Protection factor | Q6: col I hazard h_i, piecewise-constant, picked by pay date
A7: 1 | B7: =VAL_DATE | C7: =EDATE('Curve_Interface'!$F$7,3*0) | D7: =(C7-B7)/360 | E7: =(C7-B7)/365 | F7: =(C7-VAL_DATE)/365 | G7: =IFERROR(IF(Curve_Interface!$J$7="Piecewise Linear (Simple)",IF(((C7-VAL_DATE)/360)<=0,1,1/(1+(IF(((INDEX('Curve_Interface'!$K$8:$K$73,MATCH(C7,'Curve_Interface'!$K$8:$K$73,1))-VAL_DATE)/360)<=0,IF(((INDEX('Curve_Interface'!$K$8:$K$73,MATCH(C7,'Curve_Interface'!$K$8:$K$73,1)+1)-VAL_DATE)/360)<=0,0,(1/INDEX('Curve_Interface'!$L$8:$L$73,MATCH(C7,'Curve_Interface'!$K$8:$K$73,1)+1)-1)/((INDEX('Curve_Interface'!$K$8:$K$73,MATCH(C7,'Curve_Interface'!$K$8:$K$73,1)+1)-VAL_DATE)/360)),(1/INDEX('Curve_Interface'!$L$8:$L$73,MATCH(C7,'Curve_Interface'!$K$8:$K$73,1))-1)/((INDEX('Curve_Interface'!$K$8:$K$73,MATCH(C7,'Curve_Interface'!$K$8:$K$73,1))-VAL_DATE)/360))+(IF(((INDEX('Curve_Interface'!$K$8:$K$73,MATCH(C7,'Curve_Interface'!$K$8:$K$73,1)+1)-VAL_DATE)/360)<=0,0,(1/INDEX('Curve_Interface'!$L$8:$L$73,MATCH(C7,'Curve_Interface'!$K$8:$K$73,1)+1)-1)/((INDEX('Curve_Interface'!$K$8:$K$73,MATCH(C7,'Curve_Interface'!$K$8:$K$73,1)+1)-VAL_DATE)/360))-IF(((INDEX('Curve_Interface'!$K$8:$K$73,MATCH(C7,'Curve_Interface'!$K$8:$K$73,1))-VAL_DATE)/360)<=0,IF(((INDEX('Curve_Interface'!$K$8:$K$73,MATCH(C7,'Curve_Interface'!$K$8:$K$73,1)+1)-VAL_DATE)/360)<=0,0,(1/INDEX('Curve_Interface'!$L$8:$L$73,MATCH(C7,'Curve_Interface'!$K$8:$K$73,1)+1)-1)/((INDEX('Curve_Interface'!$K$8:$K$73,MATCH(C7,'Curve_Interface'!$K$8:$K$73,1)+1)-VAL_DATE)/360)),(1/INDEX('Curve_Interface'!$L$8:$L$73,MATCH(C7,'Curve_Interface'!$K$8:$K$73,1))-1)/((INDEX('Curve_Interface'!$K$8:$K$73,MATCH(C7,'Curve_Interface'!$K$8:$K$73,1))-VAL_DATE)/360)))*IF(((INDEX('Curve_Interface'!$K$8:$K$73,MATCH(C7,'Curve_Interface'!$K$8:$K$73,1)+1)-VAL_DATE)/360)-((INDEX('Curve_Interface'!$K$8:$K$73,MATCH(C7,'Curve_Interface'!$K$8:$K$73,1))-VAL_DATE)/360)=0,0,(((C7-VAL_DATE)/360)-((INDEX('Curve_Interface'!$K$8:$K$73,MATCH(C7,'Curve_Interface'!$K$8:$K$73,1))-VAL_DATE)/360))/(((INDEX('Curve_Interface'!$K$8:$K$73,MATCH(C7,'Curve_Interface'!$K$8:$K$73,1)+1)-VAL_DATE)/360)-((INDEX('Curve_Interface'!$K$8:$K$73,MATCH(C7,'Curve_Interface'!$K$8:$K$73,1))-VAL_DATE)/360))))*((C7-VAL_DATE)/360))),INDEX('Curve_Interface'!$L$8:$L$73,MATCH(C7,'Curve_Interface'!$K$8:$K$73,1))*(INDEX('Curve_Interface'!$L$8:$L$73,MATCH(C7,'Curve_Interface'!$K$8:$K$73,1)+1)/INDEX('Curve_Interface'!$L$8:$L$73,MATCH(C7,'Curve_Interface'!$K$8:$K$73,1)))^((C7-INDEX('Curve_Interface'!$K$8:$K$73,MATCH(C7,'Curve_Interface'!$K$8:$K$73,1)))/(INDEX('Curve_Interface'!$K$8:$K$73,MATCH(C7,'Curve_Interface'!$K$8:$K$73,1)+1)-INDEX('Curve_Interface'!$K$8:$K$73,MATCH(C7,'Curve_Interface'!$K$8:$K$73,1))))),INDEX('Curve_Interface'!$L$8:$L$73,MATCH(C7,'Curve_Interface'!$K$8:$K$73,1))) | H7: =IFERROR(IF(Curve_Interface!$J$7="Piecewise Linear (Simple)",IF((((B7+C7)/2-VAL_DATE)/360)<=0,1,1/(1+(IF(((INDEX('Curve_Interface'!$K$8:$K$73,MATCH((B7+C7)/2,'Curve_Interface'!$K$8:$K$73,1))-VAL_DATE)/360)<=0,IF(((INDEX('Curve_Interface'!$K$8:$K$73,MATCH((B7+C7)/2,'Curve_Interface'!$K$8:$K$73,1)+1)-VAL_DATE)/360)<=0,0,(1/INDEX('Curve_Interface'!$L$8:$L$73,MATCH((B7+C7)/2,'Curve_Interface'!$K$8:$K$73,1)+1)-1)/((INDEX('Curve_Interface'!$K$8:$K$73,MATCH((B7+C7)/2,'Curve_Interface'!$K$8:$K$73,1)+1)-VAL_DATE)/360)),(1/INDEX('Curve_Interface'!$L$8:$L$73,MATCH((B7+C7)/2,'Curve_Interface'!$K$8:$K$73,1))-1)/((INDEX('Curve_Interface'!$K$8:$K$73,MATCH((B7+C7)/2,'Curve_Interface'!$K$8:$K$73,1))-VAL_DATE)/360))+(IF(((INDEX('Curve_Interface'!$K$8:$K$73,MATCH((B7+C7)/2,'Curve_Interface'!$K$8:$K$73,1)+1)-VAL_DATE)/360)<=0,0,(1/INDEX('Curve_Interface'!$L$8:$L$73,MATCH((B7+C7)/2,'Curve_Interface'!$K$8:$K$73,1)+1)-1)/((INDEX('Curve_Interface'!$K$8:$K$73,MATCH((B7+C7)/2,'Curve_Interface'!$K$8:$K$73,1)+1)-VAL_DATE)/360))-IF(((INDEX('Curve_Interface'!$K$8:$K$73,MATCH((B7+C7)/2,'Curve_Interface'!$K$8:$K$73,1))-VAL_DATE)/360)<=0,IF(((INDEX('Curve_Interface'!$K$8:$K$73,MATCH((B7+C7)/2,'Curve_Interface'!$K$8:$K$73,1)+1)-VAL_DATE)/360)<=0,0,(1/INDEX('Curve_Interface'!$L$8:$L$73,MATCH((B7+C7)/2,'Curve_Interface'!$K$8:$K$73,1)+1)-1)/((INDEX('Curve_Interface'!$K$8:$K$73,MATCH((B7+C7)/2,'Curve_Interface'!$K$8:$K$73,1)+1)-VAL_DATE)/360)),(1/INDEX('Curve_Interface'!$L$8:$L$73,MATCH((B7+C7)/2,'Curve_Interface'!$K$8:$K$73,1))-1)/((INDEX('Curve_Interface'!$K$8:$K$73,MATCH((B7+C7)/2,'Curve_Interface'!$K$8:$K$73,1))-VAL_DATE)/360)))*IF(((INDEX('Curve_Interface'!$K$8:$K$73,MATCH((B7+C7)/2,'Curve_Interface'!$K$8:$K$73,1)+1)-VAL_DATE)/360)-((INDEX('Curve_Interface'!$K$8:$K$73,MATCH((B7+C7)/2,'Curve_Interface'!$K$8:$K$73,1))-VAL_DATE)/360)=0,0,((((B7+C7)/2-VAL_DATE)/360)-((INDEX('Curve_Interface'!$K$8:$K$73,MATCH((B7+C7)/2,'Curve_Interface'!$K$8:$K$73,1))-VAL_DATE)/360))/(((INDEX('Curve_Interface'!$K$8:$K$73,MATCH((B7+C7)/2,'Curve_Interface'!$K$8:$K$73,1)+1)-VAL_DATE)/360)-((INDEX('Curve_Interface'!$K$8:$K$73,MATCH((B7+C7)/2,'Curve_Interface'!$K$8:$K$73,1))-VAL_DATE)/360))))*(((B7+C7)/2-VAL_DATE)/360))),INDEX('Curve_Interface'!$L$8:$L$73,MATCH((B7+C7)/2,'Curve_Interface'!$K$8:$K$73,1))*(INDEX('Curve_Interface'!$L$8:$L$73,MATCH((B7+C7)/2,'Curve_Interface'!$K$8:$K$73,1)+1)/INDEX('Curve_Interface'!$L$8:$L$73,MATCH((B7+C7)/2,'Curve_Interface'!$K$8:$K$73,1)))^(((B7+C7)/2-INDEX('Curve_Interface'!$K$8:$K$73,MATCH((B7+C7)/2,'Curve_Interface'!$K$8:$K$73,1)))/(INDEX('Curve_Interface'!$K$8:$K$73,MATCH((B7+C7)/2,'Curve_Interface'!$K$8:$K$73,1)+1)-INDEX('Curve_Interface'!$K$8:$K$73,MATCH((B7+C7)/2,'Curve_Interface'!$K$8:$K$73,1))))),INDEX('Curve_Interface'!$L$8:$L$73,MATCH((B7+C7)/2,'Curve_Interface'!$K$8:$K$73,1))) | I7: =INDEX(Hazard_Bootstrap!$D$7:$D$12,MIN(COUNTIF(Hazard_Bootstrap!$B$7:$B$12,"<"&C7)+1,6)) | J7: =1 | K7: =J7*EXP(-I7*E7) | L7: =J7-K7 | M7: =D7*G7*K7 | N7: =(D7/2)*H7*L7 | O7: =H7*L7 | Q7: col K Q(t_i) = Q(t_i-1) * exp(-h_i * dt_i) B-Model p.5
A8: 2 | B8: =C7 | C8: =EDATE('Curve_Interface'!$F$7,3*1) | D8: =(C8-B8)/360 | E8: =(C8-B8)/365 | F8: =(C8-VAL_DATE)/365 | G8: =IFERROR(IF(Curve_Interface!$J$7="Piecewise Linear (Simple)",IF(((C8-VAL_DATE)/360)<=0,1,1/(1+(IF(((INDEX('Curve_Interface'!$K$8:$K$73,MATCH(C8,'Curve_Interface'!$K$8:$K$73,1))-VAL_DATE)/360)<=0,IF(((INDEX('Curve_Interface'!$K$8:$K$73,MATCH(C8,'Curve_Interface'!$K$8:$K$73,1)+1)-VAL_DATE)/360)<=0,0,(1/INDEX('Curve_Interface'!$L$8:$L$73,MATCH(C8,'Curve_Interface'!$K$8:$K$73,1)+1)-1)/((INDEX('Curve_Interface'!$K$8:$K$73,MATCH(C8,'Curve_Interface'!$K$8:$K$73,1)+1)-VAL_DATE)/360)),(1/INDEX('Curve_Interface'!$L$8:$L$73,MATCH(C8,'Curve_Interface'!$K$8:$K$73,1))-1)/((INDEX('Curve_Interface'!$K$8:$K$73,MATCH(C8,'Curve_Interface'!$K$8:$K$73,1))-VAL_DATE)/360))+(IF(((INDEX('Curve_Interface'!$K$8:$K$73,MATCH(C8,'Curve_Interface'!$K$8:$K$73,1)+1)-VAL_DATE)/360)<=0,0,(1/INDEX('Curve_Interface'!$L$8:$L$73,MATCH(C8,'Curve_Interface'!$K$8:$K$73,1)+1)-1)/((INDEX('Curve_Interface'!$K$8:$K$73,MATCH(C8,'Curve_Interface'!$K$8:$K$73,1)+1)-VAL_DATE)/360))-IF(((INDEX('Curve_Interface'!$K$8:$K$73,MATCH(C8,'Curve_Interface'!$K$8:$K$73,1))-VAL_DATE)/360)<=0,IF(((INDEX('Curve_Interface'!$K$8:$K$73,MATCH(C8,'Curve_Interface'!$K$8:$K$73,1)+1)-VAL_DATE)/360)<=0,0,(1/INDEX('Curve_Interface'!$L$8:$L$73,MATCH(C8,'Curve_Interface'!$K$8:$K$73,1)+1)-1)/((INDEX('Curve_Interface'!$K$8:$K$73,MATCH(C8,'Curve_Interface'!$K$8:$K$73,1)+1)-VAL_DATE)/360)),(1/INDEX('Curve_Interface'!$L$8:$L$73,MATCH(C8,'Curve_Interface'!$K$8:$K$73,1))-1)/((INDEX('Curve_Interface'!$K$8:$K$73,MATCH(C8,'Curve_Interface'!$K$8:$K$73,1))-VAL_DATE)/360)))*IF(((INDEX('Curve_Interface'!$K$8:$K$73,MATCH(C8,'Curve_Interface'!$K$8:$K$73,1)+1)-VAL_DATE)/360)-((INDEX('Curve_Interface'!$K$8:$K$73,MATCH(C8,'Curve_Interface'!$K$8:$K$73,1))-VAL_DATE)/360)=0,0,(((C8-VAL_DATE)/360)-((INDEX('Curve_Interface'!$K$8:$K$73,MATCH(C8,'Curve_Interface'!$K$8:$K$73,1))-VAL_DATE)/360))/(((INDEX('Curve_Interface'!$K$8:$K$73,MATCH(C8,'Curve_Interface'!$K$8:$K$73,1)+1)-VAL_DATE)/360)-((INDEX('Curve_Interface'!$K$8:$K$73,MATCH(C8,'Curve_Interface'!$K$8:$K$73,1))-VAL_DATE)/360))))*((C8-VAL_DATE)/360))),INDEX('Curve_Interface'!$L$8:$L$73,MATCH(C8,'Curve_Interface'!$K$8:$K$73,1))*(INDEX('Curve_Interface'!$L$8:$L$73,MATCH(C8,'Curve_Interface'!$K$8:$K$73,1)+1)/INDEX('Curve_Interface'!$L$8:$L$73,MATCH(C8,'Curve_Interface'!$K$8:$K$73,1)))^((C8-INDEX('Curve_Interface'!$K$8:$K$73,MATCH(C8,'Curve_Interface'!$K$8:$K$73,1)))/(INDEX('Curve_Interface'!$K$8:$K$73,MATCH(C8,'Curve_Interface'!$K$8:$K$73,1)+1)-INDEX('Curve_Interface'!$K$8:$K$73,MATCH(C8,'Curve_Interface'!$K$8:$K$73,1))))),INDEX('Curve_Interface'!$L$8:$L$73,MATCH(C8,'Curve_Interface'!$K$8:$K$73,1))) | H8: =IFERROR(IF(Curve_Interface!$J$7="Piecewise Linear (Simple)",IF((((B8+C8)/2-VAL_DATE)/360)<=0,1,1/(1+(IF(((INDEX('Curve_Interface'!$K$8:$K$73,MATCH((B8+C8)/2,'Curve_Interface'!$K$8:$K$73,1))-VAL_DATE)/360)<=0,IF(((INDEX('Curve_Interface'!$K$8:$K$73,MATCH((B8+C8)/2,'Curve_Interface'!$K$8:$K$73,1)+1)-VAL_DATE)/360)<=0,0,(1/INDEX('Curve_Interface'!$L$8:$L$73,MATCH((B8+C8)/2,'Curve_Interface'!$K$8:$K$73,1)+1)-1)/((INDEX('Curve_Interface'!$K$8:$K$73,MATCH((B8+C8)/2,'Curve_Interface'!$K$8:$K$73,1)+1)-VAL_DATE)/360)),(1/INDEX('Curve_Interface'!$L$8:$L$73,MATCH((B8+C8)/2,'Curve_Interface'!$K$8:$K$73,1))-1)/((INDEX('Curve_Interface'!$K$8:$K$73,MATCH((B8+C8)/2,'Curve_Interface'!$K$8:$K$73,1))-VAL_DATE)/360))+(IF(((INDEX('Curve_Interface'!$K$8:$K$73,MATCH((B8+C8)/2,'Curve_Interface'!$K$8:$K$73,1)+1)-VAL_DATE)/360)<=0,0,(1/INDEX('Curve_Interface'!$L$8:$L$73,MATCH((B8+C8)/2,'Curve_Interface'!$K$8:$K$73,1)+1)-1)/((INDEX('Curve_Interface'!$K$8:$K$73,MATCH((B8+C8)/2,'Curve_Interface'!$K$8:$K$73,1)+1)-VAL_DATE)/360))-IF(((INDEX('Curve_Interface'!$K$8:$K$73,MATCH((B8+C8)/2,'Curve_Interface'!$K$8:$K$73,1))-VAL_DATE)/360)<=0,IF(((INDEX('Curve_Interface'!$K$8:$K$73,MATCH((B8+C8)/2,'Curve_Interface'!$K$8:$K$73,1)+1)-VAL_DATE)/360)<=0,0,(1/INDEX('Curve_Interface'!$L$8:$L$73,MATCH((B8+C8)/2,'Curve_Interface'!$K$8:$K$73,1)+1)-1)/((INDEX('Curve_Interface'!$K$8:$K$73,MATCH((B8+C8)/2,'Curve_Interface'!$K$8:$K$73,1)+1)-VAL_DATE)/360)),(1/INDEX('Curve_Interface'!$L$8:$L$73,MATCH((B8+C8)/2,'Curve_Interface'!$K$8:$K$73,1))-1)/((INDEX('Curve_Interface'!$K$8:$K$73,MATCH((B8+C8)/2,'Curve_Interface'!$K$8:$K$73,1))-VAL_DATE)/360)))*IF(((INDEX('Curve_Interface'!$K$8:$K$73,MATCH((B8+C8)/2,'Curve_Interface'!$K$8:$K$73,1)+1)-VAL_DATE)/360)-((INDEX('Curve_Interface'!$K$8:$K$73,MATCH((B8+C8)/2,'Curve_Interface'!$K$8:$K$73,1))-VAL_DATE)/360)=0,0,((((B8+C8)/2-VAL_DATE)/360)-((INDEX('Curve_Interface'!$K$8:$K$73,MATCH((B8+C8)/2,'Curve_Interface'!$K$8:$K$73,1))-VAL_DATE)/360))/(((INDEX('Curve_Interface'!$K$8:$K$73,MATCH((B8+C8)/2,'Curve_Interface'!$K$8:$K$73,1)+1)-VAL_DATE)/360)-((INDEX('Curve_Interface'!$K$8:$K$73,MATCH((B8+C8)/2,'Curve_Interface'!$K$8:$K$73,1))-VAL_DATE)/360))))*(((B8+C8)/2-VAL_DATE)/360))),INDEX('Curve_Interface'!$L$8:$L$73,MATCH((B8+C8)/2,'Curve_Interface'!$K$8:$K$73,1))*(INDEX('Curve_Interface'!$L$8:$L$73,MATCH((B8+C8)/2,'Curve_Interface'!$K$8:$K$73,1)+1)/INDEX('Curve_Interface'!$L$8:$L$73,MATCH((B8+C8)/2,'Curve_Interface'!$K$8:$K$73,1)))^(((B8+C8)/2-INDEX('Curve_Interface'!$K$8:$K$73,MATCH((B8+C8)/2,'Curve_Interface'!$K$8:$K$73,1)))/(INDEX('Curve_Interface'!$K$8:$K$73,MATCH((B8+C8)/2,'Curve_Interface'!$K$8:$K$73,1)+1)-INDEX('Curve_Interface'!$K$8:$K$73,MATCH((B8+C8)/2,'Curve_Interface'!$K$8:$K$73,1))))),INDEX('Curve_Interface'!$L$8:$L$73,MATCH((B8+C8)/2,'Curve_Interface'!$K$8:$K$73,1))) | I8: =INDEX(Hazard_Bootstrap!$D$7:$D$12,MIN(COUNTIF(Hazard_Bootstrap!$B$7:$B$12,"<"&C8)+1,6)) | J8: =K7 | K8: =J8*EXP(-I8*E8) | L8: =J8-K8 | M8: =D8*G8*K8 | N8: =(D8/2)*H8*L8 | O8: =H8*L8 | Q8: col L dPD = Q(t_i-1) - Q(t_i)
A9: 3 | B9: =C8 | C9: =EDATE('Curve_Interface'!$F$7,3*2) | D9: =(C9-B9)/360 | E9: =(C9-B9)/365 | F9: =(C9-VAL_DATE)/365 | G9: =IFERROR(IF(Curve_Interface!$J$7="Piecewise Linear (Simple)",IF(((C9-VAL_DATE)/360)<=0,1,1/(1+(IF(((INDEX('Curve_Interface'!$K$8:$K$73,MATCH(C9,'Curve_Interface'!$K$8:$K$73,1))-VAL_DATE)/360)<=0,IF(((INDEX('Curve_Interface'!$K$8:$K$73,MATCH(C9,'Curve_Interface'!$K$8:$K$73,1)+1)-VAL_DATE)/360)<=0,0,(1/INDEX('Curve_Interface'!$L$8:$L$73,MATCH(C9,'Curve_Interface'!$K$8:$K$73,1)+1)-1)/((INDEX('Curve_Interface'!$K$8:$K$73,MATCH(C9,'Curve_Interface'!$K$8:$K$73,1)+1)-VAL_DATE)/360)),(1/INDEX('Curve_Interface'!$L$8:$L$73,MATCH(C9,'Curve_Interface'!$K$8:$K$73,1))-1)/((INDEX('Curve_Interface'!$K$8:$K$73,MATCH(C9,'Curve_Interface'!$K$8:$K$73,1))-VAL_DATE)/360))+(IF(((INDEX('Curve_Interface'!$K$8:$K$73,MATCH(C9,'Curve_Interface'!$K$8:$K$73,1)+1)-VAL_DATE)/360)<=0,0,(1/INDEX('Curve_Interface'!$L$8:$L$73,MATCH(C9,'Curve_Interface'!$K$8:$K$73,1)+1)-1)/((INDEX('Curve_Interface'!$K$8:$K$73,MATCH(C9,'Curve_Interface'!$K$8:$K$73,1)+1)-VAL_DATE)/360))-IF(((INDEX('Curve_Interface'!$K$8:$K$73,MATCH(C9,'Curve_Interface'!$K$8:$K$73,1))-VAL_DATE)/360)<=0,IF(((INDEX('Curve_Interface'!$K$8:$K$73,MATCH(C9,'Curve_Interface'!$K$8:$K$73,1)+1)-VAL_DATE)/360)<=0,0,(1/INDEX('Curve_Interface'!$L$8:$L$73,MATCH(C9,'Curve_Interface'!$K$8:$K$73,1)+1)-1)/((INDEX('Curve_Interface'!$K$8:$K$73,MATCH(C9,'Curve_Interface'!$K$8:$K$73,1)+1)-VAL_DATE)/360)),(1/INDEX('Curve_Interface'!$L$8:$L$73,MATCH(C9,'Curve_Interface'!$K$8:$K$73,1))-1)/((INDEX('Curve_Interface'!$K$8:$K$73,MATCH(C9,'Curve_Interface'!$K$8:$K$73,1))-VAL_DATE)/360)))*IF(((INDEX('Curve_Interface'!$K$8:$K$73,MATCH(C9,'Curve_Interface'!$K$8:$K$73,1)+1)-VAL_DATE)/360)-((INDEX('Curve_Interface'!$K$8:$K$73,MATCH(C9,'Curve_Interface'!$K$8:$K$73,1))-VAL_DATE)/360)=0,0,(((C9-VAL_DATE)/360)-((INDEX('Curve_Interface'!$K$8:$K$73,MATCH(C9,'Curve_Interface'!$K$8:$K$73,1))-VAL_DATE)/360))/(((INDEX('Curve_Interface'!$K$8:$K$73,MATCH(C9,'Curve_Interface'!$K$8:$K$73,1)+1)-VAL_DATE)/360)-((INDEX('Curve_Interface'!$K$8:$K$73,MATCH(C9,'Curve_Interface'!$K$8:$K$73,1))-VAL_DATE)/360))))*((C9-VAL_DATE)/360))),INDEX('Curve_Interface'!$L$8:$L$73,MATCH(C9,'Curve_Interface'!$K$8:$K$73,1))*(INDEX('Curve_Interface'!$L$8:$L$73,MATCH(C9,'Curve_Interface'!$K$8:$K$73,1)+1)/INDEX('Curve_Interface'!$L$8:$L$73,MATCH(C9,'Curve_Interface'!$K$8:$K$73,1)))^((C9-INDEX('Curve_Interface'!$K$8:$K$73,MATCH(C9,'Curve_Interface'!$K$8:$K$73,1)))/(INDEX('Curve_Interface'!$K$8:$K$73,MATCH(C9,'Curve_Interface'!$K$8:$K$73,1)+1)-INDEX('Curve_Interface'!$K$8:$K$73,MATCH(C9,'Curve_Interface'!$K$8:$K$73,1))))),INDEX('Curve_Interface'!$L$8:$L$73,MATCH(C9,'Curve_Interface'!$K$8:$K$73,1))) | H9: =IFERROR(IF(Curve_Interface!$J$7="Piecewise Linear (Simple)",IF((((B9+C9)/2-VAL_DATE)/360)<=0,1,1/(1+(IF(((INDEX('Curve_Interface'!$K$8:$K$73,MATCH((B9+C9)/2,'Curve_Interface'!$K$8:$K$73,1))-VAL_DATE)/360)<=0,IF(((INDEX('Curve_Interface'!$K$8:$K$73,MATCH((B9+C9)/2,'Curve_Interface'!$K$8:$K$73,1)+1)-VAL_DATE)/360)<=0,0,(1/INDEX('Curve_Interface'!$L$8:$L$73,MATCH((B9+C9)/2,'Curve_Interface'!$K$8:$K$73,1)+1)-1)/((INDEX('Curve_Interface'!$K$8:$K$73,MATCH((B9+C9)/2,'Curve_Interface'!$K$8:$K$73,1)+1)-VAL_DATE)/360)),(1/INDEX('Curve_Interface'!$L$8:$L$73,MATCH((B9+C9)/2,'Curve_Interface'!$K$8:$K$73,1))-1)/((INDEX('Curve_Interface'!$K$8:$K$73,MATCH((B9+C9)/2,'Curve_Interface'!$K$8:$K$73,1))-VAL_DATE)/360))+(IF(((INDEX('Curve_Interface'!$K$8:$K$73,MATCH((B9+C9)/2,'Curve_Interface'!$K$8:$K$73,1)+1)-VAL_DATE)/360)<=0,0,(1/INDEX('Curve_Interface'!$L$8:$L$73,MATCH((B9+C9)/2,'Curve_Interface'!$K$8:$K$73,1)+1)-1)/((INDEX('Curve_Interface'!$K$8:$K$73,MATCH((B9+C9)/2,'Curve_Interface'!$K$8:$K$73,1)+1)-VAL_DATE)/360))-IF(((INDEX('Curve_Interface'!$K$8:$K$73,MATCH((B9+C9)/2,'Curve_Interface'!$K$8:$K$73,1))-VAL_DATE)/360)<=0,IF(((INDEX('Curve_Interface'!$K$8:$K$73,MATCH((B9+C9)/2,'Curve_Interface'!$K$8:$K$73,1)+1)-VAL_DATE)/360)<=0,0,(1/INDEX('Curve_Interface'!$L$8:$L$73,MATCH((B9+C9)/2,'Curve_Interface'!$K$8:$K$73,1)+1)-1)/((INDEX('Curve_Interface'!$K$8:$K$73,MATCH((B9+C9)/2,'Curve_Interface'!$K$8:$K$73,1)+1)-VAL_DATE)/360)),(1/INDEX('Curve_Interface'!$L$8:$L$73,MATCH((B9+C9)/2,'Curve_Interface'!$K$8:$K$73,1))-1)/((INDEX('Curve_Interface'!$K$8:$K$73,MATCH((B9+C9)/2,'Curve_Interface'!$K$8:$K$73,1))-VAL_DATE)/360)))*IF(((INDEX('Curve_Interface'!$K$8:$K$73,MATCH((B9+C9)/2,'Curve_Interface'!$K$8:$K$73,1)+1)-VAL_DATE)/360)-((INDEX('Curve_Interface'!$K$8:$K$73,MATCH((B9+C9)/2,'Curve_Interface'!$K$8:$K$73,1))-VAL_DATE)/360)=0,0,((((B9+C9)/2-VAL_DATE)/360)-((INDEX('Curve_Interface'!$K$8:$K$73,MATCH((B9+C9)/2,'Curve_Interface'!$K$8:$K$73,1))-VAL_DATE)/360))/(((INDEX('Curve_Interface'!$K$8:$K$73,MATCH((B9+C9)/2,'Curve_Interface'!$K$8:$K$73,1)+1)-VAL_DATE)/360)-((INDEX('Curve_Interface'!$K$8:$K$73,MATCH((B9+C9)/2,'Curve_Interface'!$K$8:$K$73,1))-VAL_DATE)/360))))*(((B9+C9)/2-VAL_DATE)/360))),INDEX('Curve_Interface'!$L$8:$L$73,MATCH((B9+C9)/2,'Curve_Interface'!$K$8:$K$73,1))*(INDEX('Curve_Interface'!$L$8:$L$73,MATCH((B9+C9)/2,'Curve_Interface'!$K$8:$K$73,1)+1)/INDEX('Curve_Interface'!$L$8:$L$73,MATCH((B9+C9)/2,'Curve_Interface'!$K$8:$K$73,1)))^(((B9+C9)/2-INDEX('Curve_Interface'!$K$8:$K$73,MATCH((B9+C9)/2,'Curve_Interface'!$K$8:$K$73,1)))/(INDEX('Curve_Interface'!$K$8:$K$73,MATCH((B9+C9)/2,'Curve_Interface'!$K$8:$K$73,1)+1)-INDEX('Curve_Interface'!$K$8:$K$73,MATCH((B9+C9)/2,'Curve_Interface'!$K$8:$K$73,1))))),INDEX('Curve_Interface'!$L$8:$L$73,MATCH((B9+C9)/2,'Curve_Interface'!$K$8:$K$73,1))) | I9: =INDEX(Hazard_Bootstrap!$D$7:$D$12,MIN(COUNTIF(Hazard_Bootstrap!$B$7:$B$12,"<"&C9)+1,6)) | J9: =K8 | K9: =J9*EXP(-I9*E9) | L9: =J9-K9 | M9: =D9*G9*K9 | N9: =(D9/2)*H9*L9 | O9: =H9*L9
A10: 4 | B10: =C9 | C10: =EDATE('Curve_Interface'!$F$7,3*3) | D10: =(C10-B10)/360 | E10: =(C10-B10)/365 | F10: =(C10-VAL_DATE)/365 | G10: =IFERROR(IF(Curve_Interface!$J$7="Piecewise Linear (Simple)",IF(((C10-VAL_DATE)/360)<=0,1,1/(1+(IF(((INDEX('Curve_Interface'!$K$8:$K$73,MATCH(C10,'Curve_Interface'!$K$8:$K$73,1))-VAL_DATE)/360)<=0,IF(((INDEX('Curve_Interface'!$K$8:$K$73,MATCH(C10,'Curve_Interface'!$K$8:$K$73,1)+1)-VAL_DATE)/360)<=0,0,(1/INDEX('Curve_Interface'!$L$8:$L$73,MATCH(C10,'Curve_Interface'!$K$8:$K$73,1)+1)-1)/((INDEX('Curve_Interface'!$K$8:$K$73,MATCH(C10,'Curve_Interface'!$K$8:$K$73,1)+1)-VAL_DATE)/360)),(1/INDEX('Curve_Interface'!$L$8:$L$73,MATCH(C10,'Curve_Interface'!$K$8:$K$73,1))-1)/((INDEX('Curve_Interface'!$K$8:$K$73,MATCH(C10,'Curve_Interface'!$K$8:$K$73,1))-VAL_DATE)/360))+(IF(((INDEX('Curve_Interface'!$K$8:$K$73,MATCH(C10,'Curve_Interface'!$K$8:$K$73,1)+1)-VAL_DATE)/360)<=0,0,(1/INDEX('Curve_Interface'!$L$8:$L$73,MATCH(C10,'Curve_Interface'!$K$8:$K$73,1)+1)-1)/((INDEX('Curve_Interface'!$K$8:$K$73,MATCH(C10,'Curve_Interface'!$K$8:$K$73,1)+1)-VAL_DATE)/360))-IF(((INDEX('Curve_Interface'!$K$8:$K$73,MATCH(C10,'Curve_Interface'!$K$8:$K$73,1))-VAL_DATE)/360)<=0,IF(((INDEX('Curve_Interface'!$K$8:$K$73,MATCH(C10,'Curve_Interface'!$K$8:$K$73,1)+1)-VAL_DATE)/360)<=0,0,(1/INDEX('Curve_Interface'!$L$8:$L$73,MATCH(C10,'Curve_Interface'!$K$8:$K$73,1)+1)-1)/((INDEX('Curve_Interface'!$K$8:$K$73,MATCH(C10,'Curve_Interface'!$K$8:$K$73,1)+1)-VAL_DATE)/360)),(1/INDEX('Curve_Interface'!$L$8:$L$73,MATCH(C10,'Curve_Interface'!$K$8:$K$73,1))-1)/((INDEX('Curve_Interface'!$K$8:$K$73,MATCH(C10,'Curve_Interface'!$K$8:$K$73,1))-VAL_DATE)/360)))*IF(((INDEX('Curve_Interface'!$K$8:$K$73,MATCH(C10,'Curve_Interface'!$K$8:$K$73,1)+1)-VAL_DATE)/360)-((INDEX('Curve_Interface'!$K$8:$K$73,MATCH(C10,'Curve_Interface'!$K$8:$K$73,1))-VAL_DATE)/360)=0,0,(((C10-VAL_DATE)/360)-((INDEX('Curve_Interface'!$K$8:$K$73,MATCH(C10,'Curve_Interface'!$K$8:$K$73,1))-VAL_DATE)/360))/(((INDEX('Curve_Interface'!$K$8:$K$73,MATCH(C10,'Curve_Interface'!$K$8:$K$73,1)+1)-VAL_DATE)/360)-((INDEX('Curve_Interface'!$K$8:$K$73,MATCH(C10,'Curve_Interface'!$K$8:$K$73,1))-VAL_DATE)/360))))*((C10-VAL_DATE)/360))),INDEX('Curve_Interface'!$L$8:$L$73,MATCH(C10,'Curve_Interface'!$K$8:$K$73,1))*(INDEX('Curve_Interface'!$L$8:$L$73,MATCH(C10,'Curve_Interface'!$K$8:$K$73,1)+1)/INDEX('Curve_Interface'!$L$8:$L$73,MATCH(C10,'Curve_Interface'!$K$8:$K$73,1)))^((C10-INDEX('Curve_Interface'!$K$8:$K$73,MATCH(C10,'Curve_Interface'!$K$8:$K$73,1)))/(INDEX('Curve_Interface'!$K$8:$K$73,MATCH(C10,'Curve_Interface'!$K$8:$K$73,1)+1)-INDEX('Curve_Interface'!$K$8:$K$73,MATCH(C10,'Curve_Interface'!$K$8:$K$73,1))))),INDEX('Curve_Interface'!$L$8:$L$73,MATCH(C10,'Curve_Interface'!$K$8:$K$73,1))) | H10: =IFERROR(IF(Curve_Interface!$J$7="Piecewise Linear (Simple)",IF((((B10+C10)/2-VAL_DATE)/360)<=0,1,1/(1+(IF(((INDEX('Curve_Interface'!$K$8:$K$73,MATCH((B10+C10)/2,'Curve_Interface'!$K$8:$K$73,1))-VAL_DATE)/360)<=0,IF(((INDEX('Curve_Interface'!$K$8:$K$73,MATCH((B10+C10)/2,'Curve_Interface'!$K$8:$K$73,1)+1)-VAL_DATE)/360)<=0,0,(1/INDEX('Curve_Interface'!$L$8:$L$73,MATCH((B10+C10)/2,'Curve_Interface'!$K$8:$K$73,1)+1)-1)/((INDEX('Curve_Interface'!$K$8:$K$73,MATCH((B10+C10)/2,'Curve_Interface'!$K$8:$K$73,1)+1)-VAL_DATE)/360)),(1/INDEX('Curve_Interface'!$L$8:$L$73,MATCH((B10+C10)/2,'Curve_Interface'!$K$8:$K$73,1))-1)/((INDEX('Curve_Interface'!$K$8:$K$73,MATCH((B10+C10)/2,'Curve_Interface'!$K$8:$K$73,1))-VAL_DATE)/360))+(IF(((INDEX('Curve_Interface'!$K$8:$K$73,MATCH((B10+C10)/2,'Curve_Interface'!$K$8:$K$73,1)+1)-VAL_DATE)/360)<=0,0,(1/INDEX('Curve_Interface'!$L$8:$L$73,MATCH((B10+C10)/2,'Curve_Interface'!$K$8:$K$73,1)+1)-1)/((INDEX('Curve_Interface'!$K$8:$K$73,MATCH((B10+C10)/2,'Curve_Interface'!$K$8:$K$73,1)+1)-VAL_DATE)/360))-IF(((INDEX('Curve_Interface'!$K$8:$K$73,MATCH((B10+C10)/2,'Curve_Interface'!$K$8:$K$73,1))-VAL_DATE)/360)<=0,IF(((INDEX('Curve_Interface'!$K$8:$K$73,MATCH((B10+C10)/2,'Curve_Interface'!$K$8:$K$73,1)+1)-VAL_DATE)/360)<=0,0,(1/INDEX('Curve_Interface'!$L$8:$L$73,MATCH((B10+C10)/2,'Curve_Interface'!$K$8:$K$73,1)+1)-1)/((INDEX('Curve_Interface'!$K$8:$K$73,MATCH((B10+C10)/2,'Curve_Interface'!$K$8:$K$73,1)+1)-VAL_DATE)/360)),(1/INDEX('Curve_Interface'!$L$8:$L$73,MATCH((B10+C10)/2,'Curve_Interface'!$K$8:$K$73,1))-1)/((INDEX('Curve_Interface'!$K$8:$K$73,MATCH((B10+C10)/2,'Curve_Interface'!$K$8:$K$73,1))-VAL_DATE)/360)))*IF(((INDEX('Curve_Interface'!$K$8:$K$73,MATCH((B10+C10)/2,'Curve_Interface'!$K$8:$K$73,1)+1)-VAL_DATE)/360)-((INDEX('Curve_Interface'!$K$8:$K$73,MATCH((B10+C10)/2,'Curve_Interface'!$K$8:$K$73,1))-VAL_DATE)/360)=0,0,((((B10+C10)/2-VAL_DATE)/360)-((INDEX('Curve_Interface'!$K$8:$K$73,MATCH((B10+C10)/2,'Curve_Interface'!$K$8:$K$73,1))-VAL_DATE)/360))/(((INDEX('Curve_Interface'!$K$8:$K$73,MATCH((B10+C10)/2,'Curve_Interface'!$K$8:$K$73,1)+1)-VAL_DATE)/360)-((INDEX('Curve_Interface'!$K$8:$K$73,MATCH((B10+C10)/2,'Curve_Interface'!$K$8:$K$73,1))-VAL_DATE)/360))))*(((B10+C10)/2-VAL_DATE)/360))),INDEX('Curve_Interface'!$L$8:$L$73,MATCH((B10+C10)/2,'Curve_Interface'!$K$8:$K$73,1))*(INDEX('Curve_Interface'!$L$8:$L$73,MATCH((B10+C10)/2,'Curve_Interface'!$K$8:$K$73,1)+1)/INDEX('Curve_Interface'!$L$8:$L$73,MATCH((B10+C10)/2,'Curve_Interface'!$K$8:$K$73,1)))^(((B10+C10)/2-INDEX('Curve_Interface'!$K$8:$K$73,MATCH((B10+C10)/2,'Curve_Interface'!$K$8:$K$73,1)))/(INDEX('Curve_Interface'!$K$8:$K$73,MATCH((B10+C10)/2,'Curve_Interface'!$K$8:$K$73,1)+1)-INDEX('Curve_Interface'!$K$8:$K$73,MATCH((B10+C10)/2,'Curve_Interface'!$K$8:$K$73,1))))),INDEX('Curve_Interface'!$L$8:$L$73,MATCH((B10+C10)/2,'Curve_Interface'!$K$8:$K$73,1))) | I10: =INDEX(Hazard_Bootstrap!$D$7:$D$12,MIN(COUNTIF(Hazard_Bootstrap!$B$7:$B$12,"<"&C10)+1,6)) | J10: =K9 | K10: =J10*EXP(-I10*E10) | L10: =J10-K10 | M10: =D10*G10*K10 | N10: =(D10/2)*H10*L10 | O10: =H10*L10 | Q10: col M premium factor (3.4) / O-T (5) 1st term
A11: 5 | B11: =C10 | C11: =EDATE('Curve_Interface'!$F$7,3*4) | D11: =(C11-B11)/360 | E11: =(C11-B11)/365 | F11: =(C11-VAL_DATE)/365 | G11: =IFERROR(IF(Curve_Interface!$J$7="Piecewise Linear (Simple)",IF(((C11-VAL_DATE)/360)<=0,1,1/(1+(IF(((INDEX('Curve_Interface'!$K$8:$K$73,MATCH(C11,'Curve_Interface'!$K$8:$K$73,1))-VAL_DATE)/360)<=0,IF(((INDEX('Curve_Interface'!$K$8:$K$73,MATCH(C11,'Curve_Interface'!$K$8:$K$73,1)+1)-VAL_DATE)/360)<=0,0,(1/INDEX('Curve_Interface'!$L$8:$L$73,MATCH(C11,'Curve_Interface'!$K$8:$K$73,1)+1)-1)/((INDEX('Curve_Interface'!$K$8:$K$73,MATCH(C11,'Curve_Interface'!$K$8:$K$73,1)+1)-VAL_DATE)/360)),(1/INDEX('Curve_Interface'!$L$8:$L$73,MATCH(C11,'Curve_Interface'!$K$8:$K$73,1))-1)/((INDEX('Curve_Interface'!$K$8:$K$73,MATCH(C11,'Curve_Interface'!$K$8:$K$73,1))-VAL_DATE)/360))+(IF(((INDEX('Curve_Interface'!$K$8:$K$73,MATCH(C11,'Curve_Interface'!$K$8:$K$73,1)+1)-VAL_DATE)/360)<=0,0,(1/INDEX('Curve_Interface'!$L$8:$L$73,MATCH(C11,'Curve_Interface'!$K$8:$K$73,1)+1)-1)/((INDEX('Curve_Interface'!$K$8:$K$73,MATCH(C11,'Curve_Interface'!$K$8:$K$73,1)+1)-VAL_DATE)/360))-IF(((INDEX('Curve_Interface'!$K$8:$K$73,MATCH(C11,'Curve_Interface'!$K$8:$K$73,1))-VAL_DATE)/360)<=0,IF(((INDEX('Curve_Interface'!$K$8:$K$73,MATCH(C11,'Curve_Interface'!$K$8:$K$73,1)+1)-VAL_DATE)/360)<=0,0,(1/INDEX('Curve_Interface'!$L$8:$L$73,MATCH(C11,'Curve_Interface'!$K$8:$K$73,1)+1)-1)/((INDEX('Curve_Interface'!$K$8:$K$73,MATCH(C11,'Curve_Interface'!$K$8:$K$73,1)+1)-VAL_DATE)/360)),(1/INDEX('Curve_Interface'!$L$8:$L$73,MATCH(C11,'Curve_Interface'!$K$8:$K$73,1))-1)/((INDEX('Curve_Interface'!$K$8:$K$73,MATCH(C11,'Curve_Interface'!$K$8:$K$73,1))-VAL_DATE)/360)))*IF(((INDEX('Curve_Interface'!$K$8:$K$73,MATCH(C11,'Curve_Interface'!$K$8:$K$73,1)+1)-VAL_DATE)/360)-((INDEX('Curve_Interface'!$K$8:$K$73,MATCH(C11,'Curve_Interface'!$K$8:$K$73,1))-VAL_DATE)/360)=0,0,(((C11-VAL_DATE)/360)-((INDEX('Curve_Interface'!$K$8:$K$73,MATCH(C11,'Curve_Interface'!$K$8:$K$73,1))-VAL_DATE)/360))/(((INDEX('Curve_Interface'!$K$8:$K$73,MATCH(C11,'Curve_Interface'!$K$8:$K$73,1)+1)-VAL_DATE)/360)-((INDEX('Curve_Interface'!$K$8:$K$73,MATCH(C11,'Curve_Interface'!$K$8:$K$73,1))-VAL_DATE)/360))))*((C11-VAL_DATE)/360))),INDEX('Curve_Interface'!$L$8:$L$73,MATCH(C11,'Curve_Interface'!$K$8:$K$73,1))*(INDEX('Curve_Interface'!$L$8:$L$73,MATCH(C11,'Curve_Interface'!$K$8:$K$73,1)+1)/INDEX('Curve_Interface'!$L$8:$L$73,MATCH(C11,'Curve_Interface'!$K$8:$K$73,1)))^((C11-INDEX('Curve_Interface'!$K$8:$K$73,MATCH(C11,'Curve_Interface'!$K$8:$K$73,1)))/(INDEX('Curve_Interface'!$K$8:$K$73,MATCH(C11,'Curve_Interface'!$K$8:$K$73,1)+1)-INDEX('Curve_Interface'!$K$8:$K$73,MATCH(C11,'Curve_Interface'!$K$8:$K$73,1))))),INDEX('Curve_Interface'!$L$8:$L$73,MATCH(C11,'Curve_Interface'!$K$8:$K$73,1))) | H11: =IFERROR(IF(Curve_Interface!$J$7="Piecewise Linear (Simple)",IF((((B11+C11)/2-VAL_DATE)/360)<=0,1,1/(1+(IF(((INDEX('Curve_Interface'!$K$8:$K$73,MATCH((B11+C11)/2,'Curve_Interface'!$K$8:$K$73,1))-VAL_DATE)/360)<=0,IF(((INDEX('Curve_Interface'!$K$8:$K$73,MATCH((B11+C11)/2,'Curve_Interface'!$K$8:$K$73,1)+1)-VAL_DATE)/360)<=0,0,(1/INDEX('Curve_Interface'!$L$8:$L$73,MATCH((B11+C11)/2,'Curve_Interface'!$K$8:$K$73,1)+1)-1)/((INDEX('Curve_Interface'!$K$8:$K$73,MATCH((B11+C11)/2,'Curve_Interface'!$K$8:$K$73,1)+1)-VAL_DATE)/360)),(1/INDEX('Curve_Interface'!$L$8:$L$73,MATCH((B11+C11)/2,'Curve_Interface'!$K$8:$K$73,1))-1)/((INDEX('Curve_Interface'!$K$8:$K$73,MATCH((B11+C11)/2,'Curve_Interface'!$K$8:$K$73,1))-VAL_DATE)/360))+(IF(((INDEX('Curve_Interface'!$K$8:$K$73,MATCH((B11+C11)/2,'Curve_Interface'!$K$8:$K$73,1)+1)-VAL_DATE)/360)<=0,0,(1/INDEX('Curve_Interface'!$L$8:$L$73,MATCH((B11+C11)/2,'Curve_Interface'!$K$8:$K$73,1)+1)-1)/((INDEX('Curve_Interface'!$K$8:$K$73,MATCH((B11+C11)/2,'Curve_Interface'!$K$8:$K$73,1)+1)-VAL_DATE)/360))-IF(((INDEX('Curve_Interface'!$K$8:$K$73,MATCH((B11+C11)/2,'Curve_Interface'!$K$8:$K$73,1))-VAL_DATE)/360)<=0,IF(((INDEX('Curve_Interface'!$K$8:$K$73,MATCH((B11+C11)/2,'Curve_Interface'!$K$8:$K$73,1)+1)-VAL_DATE)/360)<=0,0,(1/INDEX('Curve_Interface'!$L$8:$L$73,MATCH((B11+C11)/2,'Curve_Interface'!$K$8:$K$73,1)+1)-1)/((INDEX('Curve_Interface'!$K$8:$K$73,MATCH((B11+C11)/2,'Curve_Interface'!$K$8:$K$73,1)+1)-VAL_DATE)/360)),(1/INDEX('Curve_Interface'!$L$8:$L$73,MATCH((B11+C11)/2,'Curve_Interface'!$K$8:$K$73,1))-1)/((INDEX('Curve_Interface'!$K$8:$K$73,MATCH((B11+C11)/2,'Curve_Interface'!$K$8:$K$73,1))-VAL_DATE)/360)))*IF(((INDEX('Curve_Interface'!$K$8:$K$73,MATCH((B11+C11)/2,'Curve_Interface'!$K$8:$K$73,1)+1)-VAL_DATE)/360)-((INDEX('Curve_Interface'!$K$8:$K$73,MATCH((B11+C11)/2,'Curve_Interface'!$K$8:$K$73,1))-VAL_DATE)/360)=0,0,((((B11+C11)/2-VAL_DATE)/360)-((INDEX('Curve_Interface'!$K$8:$K$73,MATCH((B11+C11)/2,'Curve_Interface'!$K$8:$K$73,1))-VAL_DATE)/360))/(((INDEX('Curve_Interface'!$K$8:$K$73,MATCH((B11+C11)/2,'Curve_Interface'!$K$8:$K$73,1)+1)-VAL_DATE)/360)-((INDEX('Curve_Interface'!$K$8:$K$73,MATCH((B11+C11)/2,'Curve_Interface'!$K$8:$K$73,1))-VAL_DATE)/360))))*(((B11+C11)/2-VAL_DATE)/360))),INDEX('Curve_Interface'!$L$8:$L$73,MATCH((B11+C11)/2,'Curve_Interface'!$K$8:$K$73,1))*(INDEX('Curve_Interface'!$L$8:$L$73,MATCH((B11+C11)/2,'Curve_Interface'!$K$8:$K$73,1)+1)/INDEX('Curve_Interface'!$L$8:$L$73,MATCH((B11+C11)/2,'Curve_Interface'!$K$8:$K$73,1)))^(((B11+C11)/2-INDEX('Curve_Interface'!$K$8:$K$73,MATCH((B11+C11)/2,'Curve_Interface'!$K$8:$K$73,1)))/(INDEX('Curve_Interface'!$K$8:$K$73,MATCH((B11+C11)/2,'Curve_Interface'!$K$8:$K$73,1)+1)-INDEX('Curve_Interface'!$K$8:$K$73,MATCH((B11+C11)/2,'Curve_Interface'!$K$8:$K$73,1))))),INDEX('Curve_Interface'!$L$8:$L$73,MATCH((B11+C11)/2,'Curve_Interface'!$K$8:$K$73,1))) | I11: =INDEX(Hazard_Bootstrap!$D$7:$D$12,MIN(COUNTIF(Hazard_Bootstrap!$B$7:$B$12,"<"&C11)+1,6)) | J11: =K10 | K11: =J11*EXP(-I11*E11) | L11: =J11-K11 | M11: =D11*G11*K11 | N11: =(D11/2)*H11*L11 | O11: =H11*L11 | Q11: alpha_i * Z(t_i) * Q(t_i)
