Workbook
Name VAL_DATE: Instructions!$B$9
Name HIST_START: Instructions!$B$10
Name HIST_END: Instructions!$B$11
Name PX_SRC: Instructions!$B$12
Name SOFR_TKR: Instructions!$B$13
Name S490_TKR: Instructions!$B$14

Sheet Instructions
A1: USD SOFR Curve — Bloomberg Data Template
A2: Modern replication of the Lehman (2002) USD single-curve build: fixing + SR3/SR1 futures + SOFR OIS
A4: This workbook is a live Bloomberg template. Open it in Excel on a machine with the Bloomberg Add-in (BLPAPI) connected; the BDP / BDH / BDS formulas then populate automatically. Off-terminal (or in any non-Bloomberg viewer) the Bloomberg cells show #NAME? or blanks — that is expected, not a defect. Set the parameters below first; every date-driven pull references them.
A7: PARAMETERS (edit the yellow cells)
A8: Parameter | B8: Value | C8: Named ref | D8: Notes
A9: Valuation date | B9: =TODAY() | C9: VAL_DATE | D9: Curve reference / spot date. Live pulls (BDP) are as-of now; set this to your snapshot date.
A10: Historical start | B10: 01/01/2018 | C10: HIST_START | D10: Start of BDH history windows.
A11: Historical end | B11: 07/20/2026 | C11: HIST_END | D11: End of BDH history windows.
A12: Price source | B12: BGN | C12: PX_SRC | D12: Bloomberg pricing source suffix used across every OIS ticker (BGN = Bloomberg Generic). Keep one source across all maturities.
A13: Overnight SOFR ticker | B13: SOFRRATE Index | C13: SOFR_TKR | D13: Published overnight SOFR fixing (NY Fed).
A14: Bloomberg SOFR curve | B14: YCSW0490 Index | C14: S490_TKR | D14: Bloomberg curve S490 (USD SOFR) — validation benchmark only.
A16: LEHMAN 2002 → MODERN USD CURVE MAPPING
A17: Lehman 2002 instrument | C17: Modern equivalent | E17: Bloomberg source
A18: LIBOR deposits | C18: SOFR fixing / short OIS | E18: SOFRRATE Index; USOSFR1Z..USOSFRF
A19: Eurodollar futures | C19: 3M SOFR futures (SR3) | E19: SFRA Comdty (CT chain)
A20: (1M money market) | C20: 1M SOFR futures (SR1) | E20: SERA Comdty (CT chain)
A21: LIBOR swaps | C21: SOFR OIS swaps | E21: USOSFR2..USOSFR50 BGN Curncy
A22: Dealer curve | C22: Bloomberg S490 (validation) | E22: YCSW0490 Index
A24: BOOTSTRAP METHODOLOGY — one discount curve, three liquid segments
A25: Short end (o/n – ~1Y) | B25: SOFR fixing + short OIS (1W,1M,3M,6M) anchor P(0,T) at the front — the modern LIBOR-deposit segment.
A26: Mid (~3M – ~5Y) | B26: SR3 3M-SOFR futures; implied rate = 100 − price, each covering one 3M IMM reference quarter — the modern Eurodollar-futures segment.
A27: Long end (~2Y – 50Y) | B27: SOFR OIS par swaps (mid = (bid+ask)/2) where deep liquidity lives — the modern LIBOR-swap segment.
A28: Bootstrap order | B28: Left → right: each instrument solves for the next discount-factor pillar given everything already solved to its left (sequential 1-D root find).
A30: Three differences vs. Lehman 2002 (where 'modern' is not a literal copy):
A31: • Single-curve: the SOFR curve both projects forwards AND discounts. Lehman 2002 was also single-curve (LIBOR did both), so a SOFR OIS build is CLOSER to the paper than a modern LIBOR build would be.
A32: • Compounding: SOFR is an overnight rate compounded daily in arrears over each period; LIBOR was a term rate set once. The OIS/futures legs carry a daily-compounding calc LIBOR did not need.
A33: • Futures convexity: SR3 (like Eurodollar) futures need a small convexity adjustment before the implied rate enters the curve. A first pass can omit it and report the bias against the S490 benchmark.
A35: TABS IN THIS WORKBOOK
A36: Charts | B36: Curve visuals — zero curve, discount factors, and V1-vs-V2 forward comparison.
A37: 1. SOFR_Fixings | B37: Overnight SOFR fixing — current (BDP) + daily history (BDH).
A38: 2. SOFR_Futures | B38: SR3 (3M) and SR1 (1M) SOFR futures chains + fields + implied rate = 100 − price.
A39: 3. SOFR_OIS_Quotes | B39: Full USOSFR OIS strip (1W–50Y): bid / ask / last + mid. Bootstrap-set flagged.
A40: 4. Bootstrap | B40: Live single-curve OIS bootstrap → discount factors, zero & forward rates, S490 Δz check.
A41: Curve_Interface | B41: Shared D(0,t): interpolates the SOFR curve to ANY date (quarterly CDS dates demo). Used by Swap_Pricer + CDS.
A42: CDS_Parameters | B42: Credit assumptions: recovery, notional, coupon, direction (recovery is an INPUT).
A43: CDS_Quotes | B43: Single-name CDS par spreads (BDP ticker, or manual demo). One entity, one seniority.
A44: CDS_Schedule | B44: Quarterly premium/default schedule to 10Y; DF from the SOFR curve, survival from hazards.
A45: Hazard_Bootstrap | B45: Piecewise-constant hazard curve; s/(1-R) default, Goal-Seek the error to 0 for exact fit.
A46: CDS_Pricer | B46: Prices a CDS off both curves: protection − premium, par spread, upfront, CS01.
A47: CDS_Validation | B47: Survival/hazard sanity checks + the s ≈ (1-R)·lambda approximation.
... A50: 7. Fwd_Interp | B50: Zhou 2002 forward interpolation: V1 piecewise-flat vs V2 piecewise-quadratic forwards.
A52: DO NOT substitute these (wrong instruments):
A53: • TSFR1M/3M/6M/12M Index — Term SOFR benchmarks, NOT overnight-SOFR OIS calibration instruments.
A54: • USISSO02/05/10/30 Index — ICE Swap Rate fixings, NOT the live OIS quote strip needed to bootstrap.
A55: • Use PX midpoint (bid+ask)/2 for construction; use PX_LAST only where bid/ask are unavailable.
A57: Licensing: Bloomberg data is licensed and entitlement-dependent — do NOT redistribute pulled values or commit them to a public repository. This template ships formulas only, no data. Some static convention fields may return N/A under your entitlement; use FLDS <GO> on the security to find the enabled mnemonic.

Sheet Charts
A1: Curve visuals
A2: Charts read live from the Bootstrap and Fwd_Interp tabs — they populate once Bloomberg fills the data. Bootstrap columns: T (C), Discount factor (H), Zero (J); Fwd_Interp: T (B), flat fwd V1 (F), quadratic V2 (K).

Sheet SOFR_Fixings
A1: SOFR_Fixings
A2: Overnight SOFR fixing (SOFRRATE Index) — the curve's shortest anchor point
A4: CURRENT FIXING
A5: Ticker | B5: Field | C5: Value (%) | D5: As of
A6: =SOFR_TKR | B6: PX_LAST | C6: =IFERROR(BDP(SOFR_TKR,"PX_LAST"),"ERROR PLZ FIX") | D6: =IFERROR(BDP(SOFR_TKR,"LAST_UPDATE_DT"),"ERROR PLZ FIX")
A9: DAILY HISTORY
A10: The BDH array below spills down two columns (Date, PX_LAST) from the anchor cell A12. It uses the HIST_START / HIST_END parameters on the Instructions tab.
A11: Date | B11: SOFR PX_LAST (%)
A12: =IFERROR(BDH(SOFR_TKR,"PX_LAST",TEXT(HIST_START,"mm/dd/yyyy"),TEXT(HIST_END,"mm/dd/yyyy")),"ERROR PLZ FIX")

Sheet SOFR_Futures
A1: SOFR_Futures
A2: SR3 (3M) and SR1 (1M) SOFR futures — modern replacement for the Eurodollar-futures strip
A4: SR3 — THREE-MONTH SOFR FUTURES (SFRA Comdty · CME SR3) — first 20 quarterly contracts
A5: Column A cell below holds =BDS("SFRA Comdty","FUT_CHAIN") and SPILLS the active contract tickers down. Field columns reference each row's contract in column A. Adjust the row count to the liquid strip (check VOLUME / OPEN_INT).
A6: Contract (from CT chain) | B6: SECURITY_DES | C6: PX_LAST | D6: PX_BID | E6: PX_ASK | F6: Implied rate % (100−Last) | G6: FUT_MONTH_YR | H6: Ref. start (FUT_DLV_DT_FIRST) | I6: LAST_TRADEABLE_DT | J6: VOLUME | K6: OPEN_INT
A7: =BDS("SFRA Comdty","FUT_CHAIN") | B7: =IFERROR(BDP($A7,"SECURITY_DES"),"ERROR PLZ FIX") | C7: =IFERROR(BDP($A7,"PX_LAST"),"ERROR PLZ FIX") | D7: =IFERROR(BDP($A7,"PX_BID"),"ERROR PLZ FIX") | E7: =IFERROR(BDP($A7,"PX_ASK"),"ERROR PLZ FIX") | F7: =IFERROR(100-C7,"ERROR PLZ FIX") | G7: =IFERROR(BDP($A7,"FUT_MONTH_YR"),"ERROR PLZ FIX") | H7: =IFERROR(BDP($A7,"FUT_DLV_DT_FIRST"),"ERROR PLZ FIX") | I7: =IFERROR(BDP($A7,"LAST_TRADEABLE_DT"),"ERROR PLZ FIX") | J7: =IFERROR(BDP($A7,"VOLUME"),"ERROR PLZ FIX") | K7: =IFERROR(BDP($A7,"OPEN_INT"),"ERROR PLZ FIX")
B8: =IFERROR(BDP($A8,"SECURITY_DES"),"ERROR PLZ FIX") | C8: =IFERROR(BDP($A8,"PX_LAST"),"ERROR PLZ FIX") | D8: =IFERROR(BDP($A8,"PX_BID"),"ERROR PLZ FIX") | E8: =IFERROR(BDP($A8,"PX_ASK"),"ERROR PLZ FIX") | F8: =IFERROR(100-C8,"ERROR PLZ FIX") | G8: =IFERROR(BDP($A8,"FUT_MONTH_YR"),"ERROR PLZ FIX") | H8: =IFERROR(BDP($A8,"FUT_DLV_DT_FIRST"),"ERROR PLZ FIX") | I8: =IFERROR(BDP($A8,"LAST_TRADEABLE_DT"),"ERROR PLZ FIX") | J8: =IFERROR(BDP($A8,"VOLUME"),"ERROR PLZ FIX") | K8: =IFERROR(BDP($A8,"OPEN_INT"),"ERROR PLZ FIX")
B9: =IFERROR(BDP($A9,"SECURITY_DES"),"ERROR PLZ FIX") | C9: =IFERROR(BDP($A9,"PX_LAST"),"ERROR PLZ FIX") | D9: =IFERROR(BDP($A9,"PX_BID"),"ERROR PLZ FIX") | E9: =IFERROR(BDP($A9,"PX_ASK"),"ERROR PLZ FIX") | F9: =IFERROR(100-C9,"ERROR PLZ FIX") | G9: =IFERROR(BDP($A9,"FUT_MONTH_YR"),"ERROR PLZ FIX") | H9: =IFERROR(BDP($A9,"FUT_DLV_DT_FIRST"),"ERROR PLZ FIX") | I9: =IFERROR(BDP($A9,"LAST_TRADEABLE_DT"),"ERROR PLZ FIX") | J9: =IFERROR(BDP($A9,"VOLUME"),"ERROR PLZ FIX") | K9: =IFERROR(BDP($A9,"OPEN_INT"),"ERROR PLZ FIX")
B10: =IFERROR(BDP($A10,"SECURITY_DES"),"ERROR PLZ FIX") | C10: =IFERROR(BDP($A10,"PX_LAST"),"ERROR PLZ FIX") | D10: =IFERROR(BDP($A10,"PX_BID"),"ERROR PLZ FIX") | E10: =IFERROR(BDP($A10,"PX_ASK"),"ERROR PLZ FIX") | F10: =IFERROR(100-C10,"ERROR PLZ FIX") | G10: =IFERROR(BDP($A10,"FUT_MONTH_YR"),"ERROR PLZ FIX") | H10: =IFERROR(BDP($A10,"FUT_DLV_DT_FIRST"),"ERROR PLZ FIX") | I10: =IFERROR(BDP($A10,"LAST_TRADEABLE_DT"),"ERROR PLZ FIX") | J10: =IFERROR(BDP($A10,"VOLUME"),"ERROR PLZ FIX") | K10: =IFERROR(BDP($A10,"OPEN_INT"),"ERROR PLZ FIX")
B11: =IFERROR(BDP($A11,"SECURITY_DES"),"ERROR PLZ FIX") | C11: =IFERROR(BDP($A11,"PX_LAST"),"ERROR PLZ FIX") | D11: =IFERROR(BDP($A11,"PX_BID"),"ERROR PLZ FIX") | E11: =IFERROR(BDP($A11,"PX_ASK"),"ERROR PLZ FIX") | F11: =IFERROR(100-C11,"ERROR PLZ FIX") | G11: =IFERROR(BDP($A11,"FUT_MONTH_YR"),"ERROR PLZ FIX") | H11: =IFERROR(BDP($A11,"FUT_DLV_DT_FIRST"),"ERROR PLZ FIX") | I11: =IFERROR(BDP($A11,"LAST_TRADEABLE_DT"),"ERROR PLZ FIX") | J11: =IFERROR(BDP($A11,"VOLUME"),"ERROR PLZ FIX") | K11: =IFERROR(BDP($A11,"OPEN_INT"),"ERROR PLZ FIX")
B12: =IFERROR(BDP($A12,"SECURITY_DES"),"ERROR PLZ FIX") | C12: =IFERROR(BDP($A12,"PX_LAST"),"ERROR PLZ FIX") | D12: =IFERROR(BDP($A12,"PX_BID"),"ERROR PLZ FIX") | E12: =IFERROR(BDP($A12,"PX_ASK"),"ERROR PLZ FIX") | F12: =IFERROR(100-C12,"ERROR PLZ FIX") | G12: =IFERROR(BDP($A12,"FUT_MONTH_YR"),"ERROR PLZ FIX") | H12: =IFERROR(BDP($A12,"FUT_DLV_DT_FIRST"),"ERROR PLZ FIX") | I12: =IFERROR(BDP($A12,"LAST_TRADEABLE_DT"),"ERROR PLZ FIX") | J12: =IFERROR(BDP($A12,"VOLUME"),"ERROR PLZ FIX") | K12: =IFERROR(BDP($A12,"OPEN_INT"),"ERROR PLZ FIX")
B13: =IFERROR(BDP($A13,"SECURITY_DES"),"ERROR PLZ FIX") | C13: =IFERROR(BDP($A13,"PX_LAST"),"ERROR PLZ FIX") | D13: =IFERROR(BDP($A13,"PX_BID"),"ERROR PLZ FIX") | E13: =IFERROR(BDP($A13,"PX_ASK"),"ERROR PLZ FIX") | F13: =IFERROR(100-C13,"ERROR PLZ FIX") | G13: =IFERROR(BDP($A13,"FUT_MONTH_YR"),"ERROR PLZ FIX") | H13: =IFERROR(BDP($A13,"FUT_DLV_DT_FIRST"),"ERROR PLZ FIX") | I13: =IFERROR(BDP($A13,"LAST_TRADEABLE_DT"),"ERROR PLZ FIX") | J13: =IFERROR(BDP($A13,"VOLUME"),"ERROR PLZ FIX") | K13: =IFERROR(BDP($A13,"OPEN_INT"),"ERROR PLZ FIX")
B14: =IFERROR(BDP($A14,"SECURITY_DES"),"ERROR PLZ FIX") | C14: =IFERROR(BDP($A14,"PX_LAST"),"ERROR PLZ FIX") | D14: =IFERROR(BDP($A14,"PX_BID"),"ERROR PLZ FIX") | E14: =IFERROR(BDP($A14,"PX_ASK"),"ERROR PLZ FIX") | F14: =IFERROR(100-C14,"ERROR PLZ FIX") | G14: =IFERROR(BDP($A14,"FUT_MONTH_YR"),"ERROR PLZ FIX") | H14: =IFERROR(BDP($A14,"FUT_DLV_DT_FIRST"),"ERROR PLZ FIX") | I14: =IFERROR(BDP($A14,"LAST_TRADEABLE_DT"),"ERROR PLZ FIX") | J14: =IFERROR(BDP($A14,"VOLUME"),"ERROR PLZ FIX") | K14: =IFERROR(BDP($A14,"OPEN_INT"),"ERROR PLZ FIX")
B15: =IFERROR(BDP($A15,"SECURITY_DES"),"ERROR PLZ FIX") | C15: =IFERROR(BDP($A15,"PX_LAST"),"ERROR PLZ FIX") | D15: =IFERROR(BDP($A15,"PX_BID"),"ERROR PLZ FIX") | E15: =IFERROR(BDP($A15,"PX_ASK"),"ERROR PLZ FIX") | F15: =IFERROR(100-C15,"ERROR PLZ FIX") | G15: =IFERROR(BDP($A15,"FUT_MONTH_YR"),"ERROR PLZ FIX") | H15: =IFERROR(BDP($A15,"FUT_DLV_DT_FIRST"),"ERROR PLZ FIX") | I15: =IFERROR(BDP($A15,"LAST_TRADEABLE_DT"),"ERROR PLZ FIX") | J15: =IFERROR(BDP($A15,"VOLUME"),"ERROR PLZ FIX") | K15: =IFERROR(BDP($A15,"OPEN_INT"),"ERROR PLZ FIX")
B16: =IFERROR(BDP($A16,"SECURITY_DES"),"ERROR PLZ FIX") | C16: =IFERROR(BDP($A16,"PX_LAST"),"ERROR PLZ FIX") | D16: =IFERROR(BDP($A16,"PX_BID"),"ERROR PLZ FIX") | E16: =IFERROR(BDP($A16,"PX_ASK"),"ERROR PLZ FIX") | F16: =IFERROR(100-C16,"ERROR PLZ FIX") | G16: =IFERROR(BDP($A16,"FUT_MONTH_YR"),"ERROR PLZ FIX") | H16: =IFERROR(BDP($A16,"FUT_DLV_DT_FIRST"),"ERROR PLZ FIX") | I16: =IFERROR(BDP($A16,"LAST_TRADEABLE_DT"),"ERROR PLZ FIX") | J16: =IFERROR(BDP($A16,"VOLUME"),"ERROR PLZ FIX") | K16: =IFERROR(BDP($A16,"OPEN_INT"),"ERROR PLZ FIX")
B17: =IFERROR(BDP($A17,"SECURITY_DES"),"ERROR PLZ FIX") | C17: =IFERROR(BDP($A17,"PX_LAST"),"ERROR PLZ FIX") | D17: =IFERROR(BDP($A17,"PX_BID"),"ERROR PLZ FIX") | E17: =IFERROR(BDP($A17,"PX_ASK"),"ERROR PLZ FIX") | F17: =IFERROR(100-C17,"ERROR PLZ FIX") | G17: =IFERROR(BDP($A17,"FUT_MONTH_YR"),"ERROR PLZ FIX") | H17: =IFERROR(BDP($A17,"FUT_DLV_DT_FIRST"),"ERROR PLZ FIX") | I17: =IFERROR(BDP($A17,"LAST_TRADEABLE_DT"),"ERROR PLZ FIX") | J17: =IFERROR(BDP($A17,"VOLUME"),"ERROR PLZ FIX") | K17: =IFERROR(BDP($A17,"OPEN_INT"),"ERROR PLZ FIX")
B18: =IFERROR(BDP($A18,"SECURITY_DES"),"ERROR PLZ FIX") | C18: =IFERROR(BDP($A18,"PX_LAST"),"ERROR PLZ FIX") | D18: =IFERROR(BDP($A18,"PX_BID"),"ERROR PLZ FIX") | E18: =IFERROR(BDP($A18,"PX_ASK"),"ERROR PLZ FIX") | F18: =IFERROR(100-C18,"ERROR PLZ FIX") | G18: =IFERROR(BDP($A18,"FUT_MONTH_YR"),"ERROR PLZ FIX") | H18: =IFERROR(BDP($A18,"FUT_DLV_DT_FIRST"),"ERROR PLZ FIX") | I18: =IFERROR(BDP($A18,"LAST_TRADEABLE_DT"),"ERROR PLZ FIX") | J18: =IFERROR(BDP($A18,"VOLUME"),"ERROR PLZ FIX") | K18: =IFERROR(BDP($A18,"OPEN_INT"),"ERROR PLZ FIX")
B19: =IFERROR(BDP($A19,"SECURITY_DES"),"ERROR PLZ FIX") | C19: =IFERROR(BDP($A19,"PX_LAST"),"ERROR PLZ FIX") | D19: =IFERROR(BDP($A19,"PX_BID"),"ERROR PLZ FIX") | E19: =IFERROR(BDP($A19,"PX_ASK"),"ERROR PLZ FIX") | F19: =IFERROR(100-C19,"ERROR PLZ FIX") | G19: =IFERROR(BDP($A19,"FUT_MONTH_YR"),"ERROR PLZ FIX") | H19: =IFERROR(BDP($A19,"FUT_DLV_DT_FIRST"),"ERROR PLZ FIX") | I19: =IFERROR(BDP($A19,"LAST_TRADEABLE_DT"),"ERROR PLZ FIX") | J19: =IFERROR(BDP($A19,"VOLUME"),"ERROR PLZ FIX") | K19: =IFERROR(BDP($A19,"OPEN_INT"),"ERROR PLZ FIX")
... B26: =IFERROR(BDP($A26,"SECURITY_DES"),"ERROR PLZ FIX") | C26: =IFERROR(BDP($A26,"PX_LAST"),"ERROR PLZ FIX") | D26: =IFERROR(BDP($A26,"PX_BID"),"ERROR PLZ FIX") | E26: =IFERROR(BDP($A26,"PX_ASK"),"ERROR PLZ FIX") | F26: =IFERROR(100-C26,"ERROR PLZ FIX") | G26: =IFERROR(BDP($A26,"FUT_MONTH_YR"),"ERROR PLZ FIX") | H26: =IFERROR(BDP($A26,"FUT_DLV_DT_FIRST"),"ERROR PLZ FIX") | I26: =IFERROR(BDP($A26,"LAST_TRADEABLE_DT"),"ERROR PLZ FIX") | J26: =IFERROR(BDP($A26,"VOLUME"),"ERROR PLZ FIX") | K26: =IFERROR(BDP($A26,"OPEN_INT"),"ERROR PLZ FIX")
A29: SR1 — ONE-MONTH SOFR FUTURES (SERA Comdty · CME SR1) — first 13 monthly contracts
A30: Column A cell below holds =BDS("SERA Comdty","FUT_CHAIN") and SPILLS the active contract tickers down. Field columns reference each row's contract in column A. Adjust the row count to the liquid strip (check VOLUME / OPEN_INT).
A31: Contract (from CT chain) | B31: SECURITY_DES | C31: PX_LAST | D31: PX_BID | E31: PX_ASK | F31: Implied rate % (100−Last) | G31: FUT_MONTH_YR | H31: Ref. start (FUT_DLV_DT_FIRST) | I31: LAST_TRADEABLE_DT | J31: VOLUME | K31: OPEN_INT
A32: =BDS("SERA Comdty","FUT_CHAIN") | B32: =IFERROR(BDP($A32,"SECURITY_DES"),"ERROR PLZ FIX") | C32: =IFERROR(BDP($A32,"PX_LAST"),"ERROR PLZ FIX") | D32: =IFERROR(BDP($A32,"PX_BID"),"ERROR PLZ FIX") | E32: =IFERROR(BDP($A32,"PX_ASK"),"ERROR PLZ FIX") | F32: =IFERROR(100-C32,"ERROR PLZ FIX") | G32: =IFERROR(BDP($A32,"FUT_MONTH_YR"),"ERROR PLZ FIX") | H32: =IFERROR(BDP($A32,"FUT_DLV_DT_FIRST"),"ERROR PLZ FIX") | I32: =IFERROR(BDP($A32,"LAST_TRADEABLE_DT"),"ERROR PLZ FIX") | J32: =IFERROR(BDP($A32,"VOLUME"),"ERROR PLZ FIX") | K32: =IFERROR(BDP($A32,"OPEN_INT"),"ERROR PLZ FIX")
B33: =IFERROR(BDP($A33,"SECURITY_DES"),"ERROR PLZ FIX") | C33: =IFERROR(BDP($A33,"PX_LAST"),"ERROR PLZ FIX") | D33: =IFERROR(BDP($A33,"PX_BID"),"ERROR PLZ FIX") | E33: =IFERROR(BDP($A33,"PX_ASK"),"ERROR PLZ FIX") | F33: =IFERROR(100-C33,"ERROR PLZ FIX") | G33: =IFERROR(BDP($A33,"FUT_MONTH_YR"),"ERROR PLZ FIX") | H33: =IFERROR(BDP($A33,"FUT_DLV_DT_FIRST"),"ERROR PLZ FIX") | I33: =IFERROR(BDP($A33,"LAST_TRADEABLE_DT"),"ERROR PLZ FIX") | J33: =IFERROR(BDP($A33,"VOLUME"),"ERROR PLZ FIX") | K33: =IFERROR(BDP($A33,"OPEN_INT"),"ERROR PLZ FIX")
B34: =IFERROR(BDP($A34,"SECURITY_DES"),"ERROR PLZ FIX") | C34: =IFERROR(BDP($A34,"PX_LAST"),"ERROR PLZ FIX") | D34: =IFERROR(BDP($A34,"PX_BID"),"ERROR PLZ FIX") | E34: =IFERROR(BDP($A34,"PX_ASK"),"ERROR PLZ FIX") | F34: =IFERROR(100-C34,"ERROR PLZ FIX") | G34: =IFERROR(BDP($A34,"FUT_MONTH_YR"),"ERROR PLZ FIX") | H34: =IFERROR(BDP($A34,"FUT_DLV_DT_FIRST"),"ERROR PLZ FIX") | I34: =IFERROR(BDP($A34,"LAST_TRADEABLE_DT"),"ERROR PLZ FIX") | J34: =IFERROR(BDP($A34,"VOLUME"),"ERROR PLZ FIX") | K34: =IFERROR(BDP($A34,"OPEN_INT"),"ERROR PLZ FIX")
B35: =IFERROR(BDP($A35,"SECURITY_DES"),"ERROR PLZ FIX") | C35: =IFERROR(BDP($A35,"PX_LAST"),"ERROR PLZ FIX") | D35: =IFERROR(BDP($A35,"PX_BID"),"ERROR PLZ FIX") | E35: =IFERROR(BDP($A35,"PX_ASK"),"ERROR PLZ FIX") | F35: =IFERROR(100-C35,"ERROR PLZ FIX") | G35: =IFERROR(BDP($A35,"FUT_MONTH_YR"),"ERROR PLZ FIX") | H35: =IFERROR(BDP($A35,"FUT_DLV_DT_FIRST"),"ERROR PLZ FIX") | I35: =IFERROR(BDP($A35,"LAST_TRADEABLE_DT"),"ERROR PLZ FIX") | J35: =IFERROR(BDP($A35,"VOLUME"),"ERROR PLZ FIX") | K35: =IFERROR(BDP($A35,"OPEN_INT"),"ERROR PLZ FIX")
B36: =IFERROR(BDP($A36,"SECURITY_DES"),"ERROR PLZ FIX") | C36: =IFERROR(BDP($A36,"PX_LAST"),"ERROR PLZ FIX") | D36: =IFERROR(BDP($A36,"PX_BID"),"ERROR PLZ FIX") | E36: =IFERROR(BDP($A36,"PX_ASK"),"ERROR PLZ FIX") | F36: =IFERROR(100-C36,"ERROR PLZ FIX") | G36: =IFERROR(BDP($A36,"FUT_MONTH_YR"),"ERROR PLZ FIX") | H36: =IFERROR(BDP($A36,"FUT_DLV_DT_FIRST"),"ERROR PLZ FIX") | I36: =IFERROR(BDP($A36,"LAST_TRADEABLE_DT"),"ERROR PLZ FIX") | J36: =IFERROR(BDP($A36,"VOLUME"),"ERROR PLZ FIX") | K36: =IFERROR(BDP($A36,"OPEN_INT"),"ERROR PLZ FIX")
B37: =IFERROR(BDP($A37,"SECURITY_DES"),"ERROR PLZ FIX") | C37: =IFERROR(BDP($A37,"PX_LAST"),"ERROR PLZ FIX") | D37: =IFERROR(BDP($A37,"PX_BID"),"ERROR PLZ FIX") | E37: =IFERROR(BDP($A37,"PX_ASK"),"ERROR PLZ FIX") | F37: =IFERROR(100-C37,"ERROR PLZ FIX") | G37: =IFERROR(BDP($A37,"FUT_MONTH_YR"),"ERROR PLZ FIX") | H37: =IFERROR(BDP($A37,"FUT_DLV_DT_FIRST"),"ERROR PLZ FIX") | I37: =IFERROR(BDP($A37,"LAST_TRADEABLE_DT"),"ERROR PLZ FIX") | J37: =IFERROR(BDP($A37,"VOLUME"),"ERROR PLZ FIX") | K37: =IFERROR(BDP($A37,"OPEN_INT"),"ERROR PLZ FIX")
B38: =IFERROR(BDP($A38,"SECURITY_DES"),"ERROR PLZ FIX") | C38: =IFERROR(BDP($A38,"PX_LAST"),"ERROR PLZ FIX") | D38: =IFERROR(BDP($A38,"PX_BID"),"ERROR PLZ FIX") | E38: =IFERROR(BDP($A38,"PX_ASK"),"ERROR PLZ FIX") | F38: =IFERROR(100-C38,"ERROR PLZ FIX") | G38: =IFERROR(BDP($A38,"FUT_MONTH_YR"),"ERROR PLZ FIX") | H38: =IFERROR(BDP($A38,"FUT_DLV_DT_FIRST"),"ERROR PLZ FIX") | I38: =IFERROR(BDP($A38,"LAST_TRADEABLE_DT"),"ERROR PLZ FIX") | J38: =IFERROR(BDP($A38,"VOLUME"),"ERROR PLZ FIX") | K38: =IFERROR(BDP($A38,"OPEN_INT"),"ERROR PLZ FIX")
B39: =IFERROR(BDP($A39,"SECURITY_DES"),"ERROR PLZ FIX") | C39: =IFERROR(BDP($A39,"PX_LAST"),"ERROR PLZ FIX") | D39: =IFERROR(BDP($A39,"PX_BID"),"ERROR PLZ FIX") | E39: =IFERROR(BDP($A39,"PX_ASK"),"ERROR PLZ FIX") | F39: =IFERROR(100-C39,"ERROR PLZ FIX") | G39: =IFERROR(BDP($A39,"FUT_MONTH_YR"),"ERROR PLZ FIX") | H39: =IFERROR(BDP($A39,"FUT_DLV_DT_FIRST"),"ERROR PLZ FIX") | I39: =IFERROR(BDP($A39,"LAST_TRADEABLE_DT"),"ERROR PLZ FIX") | J39: =IFERROR(BDP($A39,"VOLUME"),"ERROR PLZ FIX") | K39: =IFERROR(BDP($A39,"OPEN_INT"),"ERROR PLZ FIX")
B40: =IFERROR(BDP($A40,"SECURITY_DES"),"ERROR PLZ FIX") | C40: =IFERROR(BDP($A40,"PX_LAST"),"ERROR PLZ FIX") | D40: =IFERROR(BDP($A40,"PX_BID"),"ERROR PLZ FIX") | E40: =IFERROR(BDP($A40,"PX_ASK"),"ERROR PLZ FIX") | F40: =IFERROR(100-C40,"ERROR PLZ FIX") | G40: =IFERROR(BDP($A40,"FUT_MONTH_YR"),"ERROR PLZ FIX") | H40: =IFERROR(BDP($A40,"FUT_DLV_DT_FIRST"),"ERROR PLZ FIX") | I40: =IFERROR(BDP($A40,"LAST_TRADEABLE_DT"),"ERROR PLZ FIX") | J40: =IFERROR(BDP($A40,"VOLUME"),"ERROR PLZ FIX") | K40: =IFERROR(BDP($A40,"OPEN_INT"),"ERROR PLZ FIX")
B41: =IFERROR(BDP($A41,"SECURITY_DES"),"ERROR PLZ FIX") | C41: =IFERROR(BDP($A41,"PX_LAST"),"ERROR PLZ FIX") | D41: =IFERROR(BDP($A41,"PX_BID"),"ERROR PLZ FIX") | E41: =IFERROR(BDP($A41,"PX_ASK"),"ERROR PLZ FIX") | F41: =IFERROR(100-C41,"ERROR PLZ FIX") | G41: =IFERROR(BDP($A41,"FUT_MONTH_YR"),"ERROR PLZ FIX") | H41: =IFERROR(BDP($A41,"FUT_DLV_DT_FIRST"),"ERROR PLZ FIX") | I41: =IFERROR(BDP($A41,"LAST_TRADEABLE_DT"),"ERROR PLZ FIX") | J41: =IFERROR(BDP($A41,"VOLUME"),"ERROR PLZ FIX") | K41: =IFERROR(BDP($A41,"OPEN_INT"),"ERROR PLZ FIX")
B42: =IFERROR(BDP($A42,"SECURITY_DES"),"ERROR PLZ FIX") | C42: =IFERROR(BDP($A42,"PX_LAST"),"ERROR PLZ FIX") | D42: =IFERROR(BDP($A42,"PX_BID"),"ERROR PLZ FIX") | E42: =IFERROR(BDP($A42,"PX_ASK"),"ERROR PLZ FIX") | F42: =IFERROR(100-C42,"ERROR PLZ FIX") | G42: =IFERROR(BDP($A42,"FUT_MONTH_YR"),"ERROR PLZ FIX") | H42: =IFERROR(BDP($A42,"FUT_DLV_DT_FIRST"),"ERROR PLZ FIX") | I42: =IFERROR(BDP($A42,"LAST_TRADEABLE_DT"),"ERROR PLZ FIX") | J42: =IFERROR(BDP($A42,"VOLUME"),"ERROR PLZ FIX") | K42: =IFERROR(BDP($A42,"OPEN_INT"),"ERROR PLZ FIX")
B43: =IFERROR(BDP($A43,"SECURITY_DES"),"ERROR PLZ FIX") | C43: =IFERROR(BDP($A43,"PX_LAST"),"ERROR PLZ FIX") | D43: =IFERROR(BDP($A43,"PX_BID"),"ERROR PLZ FIX") | E43: =IFERROR(BDP($A43,"PX_ASK"),"ERROR PLZ FIX") | F43: =IFERROR(100-C43,"ERROR PLZ FIX") | G43: =IFERROR(BDP($A43,"FUT_MONTH_YR"),"ERROR PLZ FIX") | H43: =IFERROR(BDP($A43,"FUT_DLV_DT_FIRST"),"ERROR PLZ FIX") | I43: =IFERROR(BDP($A43,"LAST_TRADEABLE_DT"),"ERROR PLZ FIX") | J43: =IFERROR(BDP($A43,"VOLUME"),"ERROR PLZ FIX") | K43: =IFERROR(BDP($A43,"OPEN_INT"),"ERROR PLZ FIX")
B44: =IFERROR(BDP($A44,"SECURITY_DES"),"ERROR PLZ FIX") | C44: =IFERROR(BDP($A44,"PX_LAST"),"ERROR PLZ FIX") | D44: =IFERROR(BDP($A44,"PX_BID"),"ERROR PLZ FIX") | E44: =IFERROR(BDP($A44,"PX_ASK"),"ERROR PLZ FIX") | F44: =IFERROR(100-C44,"ERROR PLZ FIX") | G44: =IFERROR(BDP($A44,"FUT_MONTH_YR"),"ERROR PLZ FIX") | H44: =IFERROR(BDP($A44,"FUT_DLV_DT_FIRST"),"ERROR PLZ FIX") | I44: =IFERROR(BDP($A44,"LAST_TRADEABLE_DT"),"ERROR PLZ FIX") | J44: =IFERROR(BDP($A44,"VOLUME"),"ERROR PLZ FIX") | K44: =IFERROR(BDP($A44,"OPEN_INT"),"ERROR PLZ FIX")

Sheet SOFR_OIS_Quotes
A1: SOFR_OIS_Quotes
A2: USD fixed-vs-SOFR OIS strip (USOSFR…, BGN) — 1W to 50Y. Maturity & years are derived live from the tenor.
A3: Spot (T+2): | B3: =WORKDAY(VAL_DATE,2) | C3: Maturity & Tenor(yrs) recompute from the tenor label + spot.
A4: Ticker root | B4: Tenor | C4: Maturity date | D4: Tenor (yrs) | E4: PX_BID | F4: PX_ASK | G4: PX_LAST | H4: Mid = (Bid+Ask)/2 | I4: In bootstrap set
A5: USOSFR1Z | B5: 1W | C5: =IF(RIGHT(B5,1)="W",$B$3+7*VALUE(LEFT(B5,LEN(B5)-1)),IF(RIGHT(B5,1)="M",EDATE($B$3,VALUE(LEFT(B5,LEN(B5)-1))),EDATE($B$3,12*VALUE(LEFT(B5,LEN(B5)-1))))) | D5: =(C5-$B$3)/365 | E5: =IFERROR(BDP(A5&" "&PX_SRC&" Curncy","PX_BID"),"ERROR PLZ FIX") | F5: =IFERROR(BDP(A5&" "&PX_SRC&" Curncy","PX_ASK"),"ERROR PLZ FIX") | G5: =IFERROR(BDP(A5&" "&PX_SRC&" Curncy","PX_LAST"),"ERROR PLZ FIX") | H5: =IFERROR((E5+F5)/2,IFERROR(G5,"ERROR PLZ FIX")) | I5: Y
A6: USOSFR2Z | B6: 2W | C6: =IF(RIGHT(B6,1)="W",$B$3+7*VALUE(LEFT(B6,LEN(B6)-1)),IF(RIGHT(B6,1)="M",EDATE($B$3,VALUE(LEFT(B6,LEN(B6)-1))),EDATE($B$3,12*VALUE(LEFT(B6,LEN(B6)-1))))) | D6: =(C6-$B$3)/365 | E6: =IFERROR(BDP(A6&" "&PX_SRC&" Curncy","PX_BID"),"ERROR PLZ FIX") | F6: =IFERROR(BDP(A6&" "&PX_SRC&" Curncy","PX_ASK"),"ERROR PLZ FIX") | G6: =IFERROR(BDP(A6&" "&PX_SRC&" Curncy","PX_LAST"),"ERROR PLZ FIX") | H6: =IFERROR((E6+F6)/2,IFERROR(G6,"ERROR PLZ FIX"))
A7: USOSFR3Z | B7: 3W | C7: =IF(RIGHT(B7,1)="W",$B$3+7*VALUE(LEFT(B7,LEN(B7)-1)),IF(RIGHT(B7,1)="M",EDATE($B$3,VALUE(LEFT(B7,LEN(B7)-1))),EDATE($B$3,12*VALUE(LEFT(B7,LEN(B7)-1))))) | D7: =(C7-$B$3)/365 | E7: =IFERROR(BDP(A7&" "&PX_SRC&" Curncy","PX_BID"),"ERROR PLZ FIX") | F7: =IFERROR(BDP(A7&" "&PX_SRC&" Curncy","PX_ASK"),"ERROR PLZ FIX") | G7: =IFERROR(BDP(A7&" "&PX_SRC&" Curncy","PX_LAST"),"ERROR PLZ FIX") | H7: =IFERROR((E7+F7)/2,IFERROR(G7,"ERROR PLZ FIX"))
A8: USOSFRA | B8: 1M | C8: =IF(RIGHT(B8,1)="W",$B$3+7*VALUE(LEFT(B8,LEN(B8)-1)),IF(RIGHT(B8,1)="M",EDATE($B$3,VALUE(LEFT(B8,LEN(B8)-1))),EDATE($B$3,12*VALUE(LEFT(B8,LEN(B8)-1))))) | D8: =(C8-$B$3)/365 | E8: =IFERROR(BDP(A8&" "&PX_SRC&" Curncy","PX_BID"),"ERROR PLZ FIX") | F8: =IFERROR(BDP(A8&" "&PX_SRC&" Curncy","PX_ASK"),"ERROR PLZ FIX") | G8: =IFERROR(BDP(A8&" "&PX_SRC&" Curncy","PX_LAST"),"ERROR PLZ FIX") | H8: =IFERROR((E8+F8)/2,IFERROR(G8,"ERROR PLZ FIX")) | I8: Y
A9: USOSFRB | B9: 2M | C9: =IF(RIGHT(B9,1)="W",$B$3+7*VALUE(LEFT(B9,LEN(B9)-1)),IF(RIGHT(B9,1)="M",EDATE($B$3,VALUE(LEFT(B9,LEN(B9)-1))),EDATE($B$3,12*VALUE(LEFT(B9,LEN(B9)-1))))) | D9: =(C9-$B$3)/365 | E9: =IFERROR(BDP(A9&" "&PX_SRC&" Curncy","PX_BID"),"ERROR PLZ FIX") | F9: =IFERROR(BDP(A9&" "&PX_SRC&" Curncy","PX_ASK"),"ERROR PLZ FIX") | G9: =IFERROR(BDP(A9&" "&PX_SRC&" Curncy","PX_LAST"),"ERROR PLZ FIX") | H9: =IFERROR((E9+F9)/2,IFERROR(G9,"ERROR PLZ FIX"))
A10: USOSFRC | B10: 3M | C10: =IF(RIGHT(B10,1)="W",$B$3+7*VALUE(LEFT(B10,LEN(B10)-1)),IF(RIGHT(B10,1)="M",EDATE($B$3,VALUE(LEFT(B10,LEN(B10)-1))),EDATE($B$3,12*VALUE(LEFT(B10,LEN(B10)-1))))) | D10: =(C10-$B$3)/365 | E10: =IFERROR(BDP(A10&" "&PX_SRC&" Curncy","PX_BID"),"ERROR PLZ FIX") | F10: =IFERROR(BDP(A10&" "&PX_SRC&" Curncy","PX_ASK"),"ERROR PLZ FIX") | G10: =IFERROR(BDP(A10&" "&PX_SRC&" Curncy","PX_LAST"),"ERROR PLZ FIX") | H10: =IFERROR((E10+F10)/2,IFERROR(G10,"ERROR PLZ FIX")) | I10: Y
A11: USOSFRD | B11: 4M | C11: =IF(RIGHT(B11,1)="W",$B$3+7*VALUE(LEFT(B11,LEN(B11)-1)),IF(RIGHT(B11,1)="M",EDATE($B$3,VALUE(LEFT(B11,LEN(B11)-1))),EDATE($B$3,12*VALUE(LEFT(B11,LEN(B11)-1))))) | D11: =(C11-$B$3)/365 | E11: =IFERROR(BDP(A11&" "&PX_SRC&" Curncy","PX_BID"),"ERROR PLZ FIX") | F11: =IFERROR(BDP(A11&" "&PX_SRC&" Curncy","PX_ASK"),"ERROR PLZ FIX") | G11: =IFERROR(BDP(A11&" "&PX_SRC&" Curncy","PX_LAST"),"ERROR PLZ FIX") | H11: =IFERROR((E11+F11)/2,IFERROR(G11,"ERROR PLZ FIX"))
A12: USOSFRE | B12: 5M | C12: =IF(RIGHT(B12,1)="W",$B$3+7*VALUE(LEFT(B12,LEN(B12)-1)),IF(RIGHT(B12,1)="M",EDATE($B$3,VALUE(LEFT(B12,LEN(B12)-1))),EDATE($B$3,12*VALUE(LEFT(B12,LEN(B12)-1))))) | D12: =(C12-$B$3)/365 | E12: =IFERROR(BDP(A12&" "&PX_SRC&" Curncy","PX_BID"),"ERROR PLZ FIX") | F12: =IFERROR(BDP(A12&" "&PX_SRC&" Curncy","PX_ASK"),"ERROR PLZ FIX") | G12: =IFERROR(BDP(A12&" "&PX_SRC&" Curncy","PX_LAST"),"ERROR PLZ FIX") | H12: =IFERROR((E12+F12)/2,IFERROR(G12,"ERROR PLZ FIX"))
A13: USOSFRF | B13: 6M | C13: =IF(RIGHT(B13,1)="W",$B$3+7*VALUE(LEFT(B13,LEN(B13)-1)),IF(RIGHT(B13,1)="M",EDATE($B$3,VALUE(LEFT(B13,LEN(B13)-1))),EDATE($B$3,12*VALUE(LEFT(B13,LEN(B13)-1))))) | D13: =(C13-$B$3)/365 | E13: =IFERROR(BDP(A13&" "&PX_SRC&" Curncy","PX_BID"),"ERROR PLZ FIX") | F13: =IFERROR(BDP(A13&" "&PX_SRC&" Curncy","PX_ASK"),"ERROR PLZ FIX") | G13: =IFERROR(BDP(A13&" "&PX_SRC&" Curncy","PX_LAST"),"ERROR PLZ FIX") | H13: =IFERROR((E13+F13)/2,IFERROR(G13,"ERROR PLZ FIX")) | I13: Y
A14: USOSFRG | B14: 7M | C14: =IF(RIGHT(B14,1)="W",$B$3+7*VALUE(LEFT(B14,LEN(B14)-1)),IF(RIGHT(B14,1)="M",EDATE($B$3,VALUE(LEFT(B14,LEN(B14)-1))),EDATE($B$3,12*VALUE(LEFT(B14,LEN(B14)-1))))) | D14: =(C14-$B$3)/365 | E14: =IFERROR(BDP(A14&" "&PX_SRC&" Curncy","PX_BID"),"ERROR PLZ FIX") | F14: =IFERROR(BDP(A14&" "&PX_SRC&" Curncy","PX_ASK"),"ERROR PLZ FIX") | G14: =IFERROR(BDP(A14&" "&PX_SRC&" Curncy","PX_LAST"),"ERROR PLZ FIX") | H14: =IFERROR((E14+F14)/2,IFERROR(G14,"ERROR PLZ FIX"))
A15: USOSFRH | B15: 8M | C15: =IF(RIGHT(B15,1)="W",$B$3+7*VALUE(LEFT(B15,LEN(B15)-1)),IF(RIGHT(B15,1)="M",EDATE($B$3,VALUE(LEFT(B15,LEN(B15)-1))),EDATE($B$3,12*VALUE(LEFT(B15,LEN(B15)-1))))) | D15: =(C15-$B$3)/365 | E15: =IFERROR(BDP(A15&" "&PX_SRC&" Curncy","PX_BID"),"ERROR PLZ FIX") | F15: =IFERROR(BDP(A15&" "&PX_SRC&" Curncy","PX_ASK"),"ERROR PLZ FIX") | G15: =IFERROR(BDP(A15&" "&PX_SRC&" Curncy","PX_LAST"),"ERROR PLZ FIX") | H15: =IFERROR((E15+F15)/2,IFERROR(G15,"ERROR PLZ FIX"))
A16: USOSFRI | B16: 9M | C16: =IF(RIGHT(B16,1)="W",$B$3+7*VALUE(LEFT(B16,LEN(B16)-1)),IF(RIGHT(B16,1)="M",EDATE($B$3,VALUE(LEFT(B16,LEN(B16)-1))),EDATE($B$3,12*VALUE(LEFT(B16,LEN(B16)-1))))) | D16: =(C16-$B$3)/365 | E16: =IFERROR(BDP(A16&" "&PX_SRC&" Curncy","PX_BID"),"ERROR PLZ FIX") | F16: =IFERROR(BDP(A16&" "&PX_SRC&" Curncy","PX_ASK"),"ERROR PLZ FIX") | G16: =IFERROR(BDP(A16&" "&PX_SRC&" Curncy","PX_LAST"),"ERROR PLZ FIX") | H16: =IFERROR((E16+F16)/2,IFERROR(G16,"ERROR PLZ FIX"))
A17: USOSFRJ | B17: 10M | C17: =IF(RIGHT(B17,1)="W",$B$3+7*VALUE(LEFT(B17,LEN(B17)-1)),IF(RIGHT(B17,1)="M",EDATE($B$3,VALUE(LEFT(B17,LEN(B17)-1))),EDATE($B$3,12*VALUE(LEFT(B17,LEN(B17)-1))))) | D17: =(C17-$B$3)/365 | E17: =IFERROR(BDP(A17&" "&PX_SRC&" Curncy","PX_BID"),"ERROR PLZ FIX") | F17: =IFERROR(BDP(A17&" "&PX_SRC&" Curncy","PX_ASK"),"ERROR PLZ FIX") | G17: =IFERROR(BDP(A17&" "&PX_SRC&" Curncy","PX_LAST"),"ERROR PLZ FIX") | H17: =IFERROR((E17+F17)/2,IFERROR(G17,"ERROR PLZ FIX"))
A18: USOSFRK | B18: 11M | C18: =IF(RIGHT(B18,1)="W",$B$3+7*VALUE(LEFT(B18,LEN(B18)-1)),IF(RIGHT(B18,1)="M",EDATE($B$3,VALUE(LEFT(B18,LEN(B18)-1))),EDATE($B$3,12*VALUE(LEFT(B18,LEN(B18)-1))))) | D18: =(C18-$B$3)/365 | E18: =IFERROR(BDP(A18&" "&PX_SRC&" Curncy","PX_BID"),"ERROR PLZ FIX") | F18: =IFERROR(BDP(A18&" "&PX_SRC&" Curncy","PX_ASK"),"ERROR PLZ FIX") | G18: =IFERROR(BDP(A18&" "&PX_SRC&" Curncy","PX_LAST"),"ERROR PLZ FIX") | H18: =IFERROR((E18+F18)/2,IFERROR(G18,"ERROR PLZ FIX"))
A19: USOSFR1 | B19: 1Y | C19: =IF(RIGHT(B19,1)="W",$B$3+7*VALUE(LEFT(B19,LEN(B19)-1)),IF(RIGHT(B19,1)="M",EDATE($B$3,VALUE(LEFT(B19,LEN(B19)-1))),EDATE($B$3,12*VALUE(LEFT(B19,LEN(B19)-1))))) | D19: =(C19-$B$3)/365 | E19: =IFERROR(BDP(A19&" "&PX_SRC&" Curncy","PX_BID"),"ERROR PLZ FIX") | F19: =IFERROR(BDP(A19&" "&PX_SRC&" Curncy","PX_ASK"),"ERROR PLZ FIX") | G19: =IFERROR(BDP(A19&" "&PX_SRC&" Curncy","PX_LAST"),"ERROR PLZ FIX") | H19: =IFERROR((E19+F19)/2,IFERROR(G19,"ERROR PLZ FIX"))
A20: USOSFR1F | B20: 18M | C20: =IF(RIGHT(B20,1)="W",$B$3+7*VALUE(LEFT(B20,LEN(B20)-1)),IF(RIGHT(B20,1)="M",EDATE($B$3,VALUE(LEFT(B20,LEN(B20)-1))),EDATE($B$3,12*VALUE(LEFT(B20,LEN(B20)-1))))) | D20: =(C20-$B$3)/365 | E20: =IFERROR(BDP(A20&" "&PX_SRC&" Curncy","PX_BID"),"ERROR PLZ FIX") | F20: =IFERROR(BDP(A20&" "&PX_SRC&" Curncy","PX_ASK"),"ERROR PLZ FIX") | G20: =IFERROR(BDP(A20&" "&PX_SRC&" Curncy","PX_LAST"),"ERROR PLZ FIX") | H20: =IFERROR((E20+F20)/2,IFERROR(G20,"ERROR PLZ FIX"))
A21: USOSFR2 | B21: 2Y | C21: =IF(RIGHT(B21,1)="W",$B$3+7*VALUE(LEFT(B21,LEN(B21)-1)),IF(RIGHT(B21,1)="M",EDATE($B$3,VALUE(LEFT(B21,LEN(B21)-1))),EDATE($B$3,12*VALUE(LEFT(B21,LEN(B21)-1))))) | D21: =(C21-$B$3)/365 | E21: =IFERROR(BDP(A21&" "&PX_SRC&" Curncy","PX_BID"),"ERROR PLZ FIX") | F21: =IFERROR(BDP(A21&" "&PX_SRC&" Curncy","PX_ASK"),"ERROR PLZ FIX") | G21: =IFERROR(BDP(A21&" "&PX_SRC&" Curncy","PX_LAST"),"ERROR PLZ FIX") | H21: =IFERROR((E21+F21)/2,IFERROR(G21,"ERROR PLZ FIX"))
A22: USOSFR3 | B22: 3Y | C22: =IF(RIGHT(B22,1)="W",$B$3+7*VALUE(LEFT(B22,LEN(B22)-1)),IF(RIGHT(B22,1)="M",EDATE($B$3,VALUE(LEFT(B22,LEN(B22)-1))),EDATE($B$3,12*VALUE(LEFT(B22,LEN(B22)-1))))) | D22: =(C22-$B$3)/365 | E22: =IFERROR(BDP(A22&" "&PX_SRC&" Curncy","PX_BID"),"ERROR PLZ FIX") | F22: =IFERROR(BDP(A22&" "&PX_SRC&" Curncy","PX_ASK"),"ERROR PLZ FIX") | G22: =IFERROR(BDP(A22&" "&PX_SRC&" Curncy","PX_LAST"),"ERROR PLZ FIX") | H22: =IFERROR((E22+F22)/2,IFERROR(G22,"ERROR PLZ FIX"))
A23: USOSFR4 | B23: 4Y | C23: =IF(RIGHT(B23,1)="W",$B$3+7*VALUE(LEFT(B23,LEN(B23)-1)),IF(RIGHT(B23,1)="M",EDATE($B$3,VALUE(LEFT(B23,LEN(B23)-1))),EDATE($B$3,12*VALUE(LEFT(B23,LEN(B23)-1))))) | D23: =(C23-$B$3)/365 | E23: =IFERROR(BDP(A23&" "&PX_SRC&" Curncy","PX_BID"),"ERROR PLZ FIX") | F23: =IFERROR(BDP(A23&" "&PX_SRC&" Curncy","PX_ASK"),"ERROR PLZ FIX") | G23: =IFERROR(BDP(A23&" "&PX_SRC&" Curncy","PX_LAST"),"ERROR PLZ FIX") | H23: =IFERROR((E23+F23)/2,IFERROR(G23,"ERROR PLZ FIX"))
A24: USOSFR5 | B24: 5Y | C24: =IF(RIGHT(B24,1)="W",$B$3+7*VALUE(LEFT(B24,LEN(B24)-1)),IF(RIGHT(B24,1)="M",EDATE($B$3,VALUE(LEFT(B24,LEN(B24)-1))),EDATE($B$3,12*VALUE(LEFT(B24,LEN(B24)-1))))) | D24: =(C24-$B$3)/365 | E24: =IFERROR(BDP(A24&" "&PX_SRC&" Curncy","PX_BID"),"ERROR PLZ FIX") | F24: =IFERROR(BDP(A24&" "&PX_SRC&" Curncy","PX_ASK"),"ERROR PLZ FIX") | G24: =IFERROR(BDP(A24&" "&PX_SRC&" Curncy","PX_LAST"),"ERROR PLZ FIX") | H24: =IFERROR((E24+F24)/2,IFERROR(G24,"ERROR PLZ FIX")) | I24: Y
A25: USOSFR6 | B25: 6Y | C25: =IF(RIGHT(B25,1)="W",$B$3+7*VALUE(LEFT(B25,LEN(B25)-1)),IF(RIGHT(B25,1)="M",EDATE($B$3,VALUE(LEFT(B25,LEN(B25)-1))),EDATE($B$3,12*VALUE(LEFT(B25,LEN(B25)-1))))) | D25: =(C25-$B$3)/365 | E25: =IFERROR(BDP(A25&" "&PX_SRC&" Curncy","PX_BID"),"ERROR PLZ FIX") | F25: =IFERROR(BDP(A25&" "&PX_SRC&" Curncy","PX_ASK"),"ERROR PLZ FIX") | G25: =IFERROR(BDP(A25&" "&PX_SRC&" Curncy","PX_LAST"),"ERROR PLZ FIX") | H25: =IFERROR((E25+F25)/2,IFERROR(G25,"ERROR PLZ FIX")) | I25: Y
A26: USOSFR7 | B26: 7Y | C26: =IF(RIGHT(B26,1)="W",$B$3+7*VALUE(LEFT(B26,LEN(B26)-1)),IF(RIGHT(B26,1)="M",EDATE($B$3,VALUE(LEFT(B26,LEN(B26)-1))),EDATE($B$3,12*VALUE(LEFT(B26,LEN(B26)-1))))) | D26: =(C26-$B$3)/365 | E26: =IFERROR(BDP(A26&" "&PX_SRC&" Curncy","PX_BID"),"ERROR PLZ FIX") | F26: =IFERROR(BDP(A26&" "&PX_SRC&" Curncy","PX_ASK"),"ERROR PLZ FIX") | G26: =IFERROR(BDP(A26&" "&PX_SRC&" Curncy","PX_LAST"),"ERROR PLZ FIX") | H26: =IFERROR((E26+F26)/2,IFERROR(G26,"ERROR PLZ FIX")) | I26: Y
A27: USOSFR8 | B27: 8Y | C27: =IF(RIGHT(B27,1)="W",$B$3+7*VALUE(LEFT(B27,LEN(B27)-1)),IF(RIGHT(B27,1)="M",EDATE($B$3,VALUE(LEFT(B27,LEN(B27)-1))),EDATE($B$3,12*VALUE(LEFT(B27,LEN(B27)-1))))) | D27: =(C27-$B$3)/365 | E27: =IFERROR(BDP(A27&" "&PX_SRC&" Curncy","PX_BID"),"ERROR PLZ FIX") | F27: =IFERROR(BDP(A27&" "&PX_SRC&" Curncy","PX_ASK"),"ERROR PLZ FIX") | G27: =IFERROR(BDP(A27&" "&PX_SRC&" Curncy","PX_LAST"),"ERROR PLZ FIX") | H27: =IFERROR((E27+F27)/2,IFERROR(G27,"ERROR PLZ FIX")) | I27: Y
A28: USOSFR9 | B28: 9Y | C28: =IF(RIGHT(B28,1)="W",$B$3+7*VALUE(LEFT(B28,LEN(B28)-1)),IF(RIGHT(B28,1)="M",EDATE($B$3,VALUE(LEFT(B28,LEN(B28)-1))),EDATE($B$3,12*VALUE(LEFT(B28,LEN(B28)-1))))) | D28: =(C28-$B$3)/365 | E28: =IFERROR(BDP(A28&" "&PX_SRC&" Curncy","PX_BID"),"ERROR PLZ FIX") | F28: =IFERROR(BDP(A28&" "&PX_SRC&" Curncy","PX_ASK"),"ERROR PLZ FIX") | G28: =IFERROR(BDP(A28&" "&PX_SRC&" Curncy","PX_LAST"),"ERROR PLZ FIX") | H28: =IFERROR((E28+F28)/2,IFERROR(G28,"ERROR PLZ FIX")) | I28: Y
A29: USOSFR10 | B29: 10Y | C29: =IF(RIGHT(B29,1)="W",$B$3+7*VALUE(LEFT(B29,LEN(B29)-1)),IF(RIGHT(B29,1)="M",EDATE($B$3,VALUE(LEFT(B29,LEN(B29)-1))),EDATE($B$3,12*VALUE(LEFT(B29,LEN(B29)-1))))) | D29: =(C29-$B$3)/365 | E29: =IFERROR(BDP(A29&" "&PX_SRC&" Curncy","PX_BID"),"ERROR PLZ FIX") | F29: =IFERROR(BDP(A29&" "&PX_SRC&" Curncy","PX_ASK"),"ERROR PLZ FIX") | G29: =IFERROR(BDP(A29&" "&PX_SRC&" Curncy","PX_LAST"),"ERROR PLZ FIX") | H29: =IFERROR((E29+F29)/2,IFERROR(G29,"ERROR PLZ FIX")) | I29: Y
A30: USOSFR12 | B30: 12Y | C30: =IF(RIGHT(B30,1)="W",$B$3+7*VALUE(LEFT(B30,LEN(B30)-1)),IF(RIGHT(B30,1)="M",EDATE($B$3,VALUE(LEFT(B30,LEN(B30)-1))),EDATE($B$3,12*VALUE(LEFT(B30,LEN(B30)-1))))) | D30: =(C30-$B$3)/365 | E30: =IFERROR(BDP(A30&" "&PX_SRC&" Curncy","PX_BID"),"ERROR PLZ FIX") | F30: =IFERROR(BDP(A30&" "&PX_SRC&" Curncy","PX_ASK"),"ERROR PLZ FIX") | G30: =IFERROR(BDP(A30&" "&PX_SRC&" Curncy","PX_LAST"),"ERROR PLZ FIX") | H30: =IFERROR((E30+F30)/2,IFERROR(G30,"ERROR PLZ FIX")) | I30: Y
A31: USOSFR15 | B31: 15Y | C31: =IF(RIGHT(B31,1)="W",$B$3+7*VALUE(LEFT(B31,LEN(B31)-1)),IF(RIGHT(B31,1)="M",EDATE($B$3,VALUE(LEFT(B31,LEN(B31)-1))),EDATE($B$3,12*VALUE(LEFT(B31,LEN(B31)-1))))) | D31: =(C31-$B$3)/365 | E31: =IFERROR(BDP(A31&" "&PX_SRC&" Curncy","PX_BID"),"ERROR PLZ FIX") | F31: =IFERROR(BDP(A31&" "&PX_SRC&" Curncy","PX_ASK"),"ERROR PLZ FIX") | G31: =IFERROR(BDP(A31&" "&PX_SRC&" Curncy","PX_LAST"),"ERROR PLZ FIX") | H31: =IFERROR((E31+F31)/2,IFERROR(G31,"ERROR PLZ FIX")) | I31: Y
A32: USOSFR20 | B32: 20Y | C32: =IF(RIGHT(B32,1)="W",$B$3+7*VALUE(LEFT(B32,LEN(B32)-1)),IF(RIGHT(B32,1)="M",EDATE($B$3,VALUE(LEFT(B32,LEN(B32)-1))),EDATE($B$3,12*VALUE(LEFT(B32,LEN(B32)-1))))) | D32: =(C32-$B$3)/365 | E32: =IFERROR(BDP(A32&" "&PX_SRC&" Curncy","PX_BID"),"ERROR PLZ FIX") | F32: =IFERROR(BDP(A32&" "&PX_SRC&" Curncy","PX_ASK"),"ERROR PLZ FIX") | G32: =IFERROR(BDP(A32&" "&PX_SRC&" Curncy","PX_LAST"),"ERROR PLZ FIX") | H32: =IFERROR((E32+F32)/2,IFERROR(G32,"ERROR PLZ FIX")) | I32: Y
A33: USOSFR25 | B33: 25Y | C33: =IF(RIGHT(B33,1)="W",$B$3+7*VALUE(LEFT(B33,LEN(B33)-1)),IF(RIGHT(B33,1)="M",EDATE($B$3,VALUE(LEFT(B33,LEN(B33)-1))),EDATE($B$3,12*VALUE(LEFT(B33,LEN(B33)-1))))) | D33: =(C33-$B$3)/365 | E33: =IFERROR(BDP(A33&" "&PX_SRC&" Curncy","PX_BID"),"ERROR PLZ FIX") | F33: =IFERROR(BDP(A33&" "&PX_SRC&" Curncy","PX_ASK"),"ERROR PLZ FIX") | G33: =IFERROR(BDP(A33&" "&PX_SRC&" Curncy","PX_LAST"),"ERROR PLZ FIX") | H33: =IFERROR((E33+F33)/2,IFERROR(G33,"ERROR PLZ FIX")) | I33: Y
A34: USOSFR30 | B34: 30Y | C34: =IF(RIGHT(B34,1)="W",$B$3+7*VALUE(LEFT(B34,LEN(B34)-1)),IF(RIGHT(B34,1)="M",EDATE($B$3,VALUE(LEFT(B34,LEN(B34)-1))),EDATE($B$3,12*VALUE(LEFT(B34,LEN(B34)-1))))) | D34: =(C34-$B$3)/365 | E34: =IFERROR(BDP(A34&" "&PX_SRC&" Curncy","PX_BID"),"ERROR PLZ FIX") | F34: =IFERROR(BDP(A34&" "&PX_SRC&" Curncy","PX_ASK"),"ERROR PLZ FIX") | G34: =IFERROR(BDP(A34&" "&PX_SRC&" Curncy","PX_LAST"),"ERROR PLZ FIX") | H34: =IFERROR((E34+F34)/2,IFERROR(G34,"ERROR PLZ FIX")) | I34: Y
A35: USOSFR40 | B35: 40Y | C35: =IF(RIGHT(B35,1)="W",$B$3+7*VALUE(LEFT(B35,LEN(B35)-1)),IF(RIGHT(B35,1)="M",EDATE($B$3,VALUE(LEFT(B35,LEN(B35)-1))),EDATE($B$3,12*VALUE(LEFT(B35,LEN(B35)-1))))) | D35: =(C35-$B$3)/365 | E35: =IFERROR(BDP(A35&" "&PX_SRC&" Curncy","PX_BID"),"ERROR PLZ FIX") | F35: =IFERROR(BDP(A35&" "&PX_SRC&" Curncy","PX_ASK"),"ERROR PLZ FIX") | G35: =IFERROR(BDP(A35&" "&PX_SRC&" Curncy","PX_LAST"),"ERROR PLZ FIX") | H35: =IFERROR((E35+F35)/2,IFERROR(G35,"ERROR PLZ FIX")) | I35: Y
A36: USOSFR50 | B36: 50Y | C36: =IF(RIGHT(B36,1)="W",$B$3+7*VALUE(LEFT(B36,LEN(B36)-1)),IF(RIGHT(B36,1)="M",EDATE($B$3,VALUE(LEFT(B36,LEN(B36)-1))),EDATE($B$3,12*VALUE(LEFT(B36,LEN(B36)-1))))) | D36: =(C36-$B$3)/365 | E36: =IFERROR(BDP(A36&" "&PX_SRC&" Curncy","PX_BID"),"ERROR PLZ FIX") | F36: =IFERROR(BDP(A36&" "&PX_SRC&" Curncy","PX_ASK"),"ERROR PLZ FIX") | G36: =IFERROR(BDP(A36&" "&PX_SRC&" Curncy","PX_LAST"),"ERROR PLZ FIX") | H36: =IFERROR((E36+F36)/2,IFERROR(G36,"ERROR PLZ FIX")) | I36: Y
A38: Maturity date and Tenor (yrs) are live formulas parsed from the tenor label (e.g. "18M" → EDATE(spot,18)) — change the tenor or the valuation date and they update. "In bootstrap set" = Y marks the recommended restricted calibration set (front 1W,1M,3M,6M; long end 5Y–50Y); the 3M–5Y gap is filled by SR3 futures on the SOFR_Futures tab.

Sheet Bootstrap
A1: Bootstrap
A2: Three-segment USD curve (Zhou 2002): short OIS (≤1Y) · SR3 futures (1Y–5Y) · OIS swaps (5Y–50Y)
A4: Spot (T+2): | B4: =WORKDAY(VAL_DATE,2)
A5: SHORT (o/n–1Y): single-payment SOFR OIS, DF = 1/(1+S·tau0). MIDDLE (1Y–5Y): the DF at 18M/2Y/3Y/4Y/5Y is interpolated off the SR3 futures chain (helper block cols O–W), which discounts each contract's forward rate forward from the OIS 1Y DF — so 18M/2Y…5Y here are driven by FUTURES, not the OIS pars (col E is shown only for reference). If the SR3 chain is unavailable the middle DFs FALL BACK to the OIS bootstrap so the curve never breaks — col N shows which is live per pillar. LONG (5Y–50Y): annual SOFR OIS swaps, DF = (1−S·A_prior)/(1+S·taucoupon), annuity (col I) built from the short + middle DFs. Cutovers at 1Y and 5Y mean nothing overlaps. Paste S490 zeros into column L for the Δz check. | O5: sigma (bp/yr): | P5: 100 | Q5: futures convexity CA = 0.5·sigma^2·t1·t2 (col T, bp)
O6: MIDDLE SEGMENT — SR3 futures chain (1Y→5Y) | Y6: Mid interp grid
A7: Tenor | B7: Maturity date | C7: T (yrs) | D7: tau0 spot→mat | E7: Par rate S (%) | F7: tau coupon | G7: Annuity A(prior) | H7: Discount factor | I7: Ann.add tau·DF | J7: Zero rate (%) cont. | K7: Fwd rate (%) | L7: S490 zero (%) [paste] | M7: Δ vs S490 (bp) | N7: DF source | O7: Contract | P7: Fut start | Q7: Fut end | R7: tau eff (post-1Y) | S7: Implied % | T7: Convexity bp | U7: Fwd | V7: DF before | W7: DF after | Y7: Date | Z7: DF
A8: 1W | B8: =$B$4+7 | C8: =(B8-$B$4)/365 | D8: =(B8-$B$4)/360 | E8: ='SOFR_OIS_Quotes'!$H5 | G8: 0 | H8: =1/(1+(E8/100)*D8) | I8: 0 | J8: =-LN(H8)/C8*100 | K8: =(1/H8-1)/D8*100 | M8: =IF(L8="","",(J8-L8)*100) | N8: short OIS | O8: ='SOFR_Futures'!A7 | P8: ='SOFR_Futures'!H7 | Q8: ='SOFR_Futures'!H8 | R8: =MAX(0,(Q8-MAX(P8,$B$22))/360) | S8: ='SOFR_Futures'!F7 | T8: =0.5*$P$5^2*((P8-$B$4)/365)*((Q8-$B$4)/365)/10000 | U8: =(S8-T8/100)/100 | V8: =$H$22 | W8: =V8/(1+U8*R8) | Y8: =$B$22 | Z8: =$H$22
A9: 2W | B9: =$B$4+14 | C9: =(B9-$B$4)/365 | D9: =(B9-$B$4)/360 | E9: ='SOFR_OIS_Quotes'!$H6 | G9: =SUM($I$8:I8) | H9: =1/(1+(E9/100)*D9) | I9: 0 | J9: =-LN(H9)/C9*100 | K9: =(H8/H9-1)/((B9-B8)/360)*100 | M9: =IF(L9="","",(J9-L9)*100) | N9: short OIS | O9: ='SOFR_Futures'!A8 | P9: ='SOFR_Futures'!H8 | Q9: ='SOFR_Futures'!H9 | R9: =MAX(0,(Q9-MAX(P9,$B$22))/360) | S9: ='SOFR_Futures'!F8 | T9: =0.5*$P$5^2*((P9-$B$4)/365)*((Q9-$B$4)/365)/10000 | U9: =(S9-T9/100)/100 | V9: =W8 | W9: =V9/(1+U9*R9) | Y9: =MAX(Q8,$B$22) | Z9: =W8
A10: 3W | B10: =$B$4+21 | C10: =(B10-$B$4)/365 | D10: =(B10-$B$4)/360 | E10: ='SOFR_OIS_Quotes'!$H7 | G10: =SUM($I$8:I9) | H10: =1/(1+(E10/100)*D10) | I10: 0 | J10: =-LN(H10)/C10*100 | K10: =(H9/H10-1)/((B10-B9)/360)*100 | M10: =IF(L10="","",(J10-L10)*100) | N10: short OIS | O10: ='SOFR_Futures'!A9 | P10: ='SOFR_Futures'!H9 | Q10: ='SOFR_Futures'!H10 | R10: =MAX(0,(Q10-MAX(P10,$B$22))/360) | S10: ='SOFR_Futures'!F9 | T10: =0.5*$P$5^2*((P10-$B$4)/365)*((Q10-$B$4)/365)/10000 | U10: =(S10-T10/100)/100 | V10: =W9 | W10: =V10/(1+U10*R10) | Y10: =MAX(Q9,$B$22) | Z10: =W9
A11: 1M | B11: =EDATE($B$4,1) | C11: =(B11-$B$4)/365 | D11: =(B11-$B$4)/360 | E11: ='SOFR_OIS_Quotes'!$H8 | G11: =SUM($I$8:I10) | H11: =1/(1+(E11/100)*D11) | I11: 0 | J11: =-LN(H11)/C11*100 | K11: =(H10/H11-1)/((B11-B10)/360)*100 | M11: =IF(L11="","",(J11-L11)*100) | N11: short OIS | O11: ='SOFR_Futures'!A10 | P11: ='SOFR_Futures'!H10 | Q11: ='SOFR_Futures'!H11 | R11: =MAX(0,(Q11-MAX(P11,$B$22))/360) | S11: ='SOFR_Futures'!F10 | T11: =0.5*$P$5^2*((P11-$B$4)/365)*((Q11-$B$4)/365)/10000 | U11: =(S11-T11/100)/100 | V11: =W10 | W11: =V11/(1+U11*R11) | Y11: =MAX(Q10,$B$22) | Z11: =W10
A12: 2M | B12: =EDATE($B$4,2) | C12: =(B12-$B$4)/365 | D12: =(B12-$B$4)/360 | E12: ='SOFR_OIS_Quotes'!$H9 | G12: =SUM($I$8:I11) | H12: =1/(1+(E12/100)*D12) | I12: 0 | J12: =-LN(H12)/C12*100 | K12: =(H11/H12-1)/((B12-B11)/360)*100 | M12: =IF(L12="","",(J12-L12)*100) | N12: short OIS | O12: ='SOFR_Futures'!A11 | P12: ='SOFR_Futures'!H11 | Q12: ='SOFR_Futures'!H12 | R12: =MAX(0,(Q12-MAX(P12,$B$22))/360) | S12: ='SOFR_Futures'!F11 | T12: =0.5*$P$5^2*((P12-$B$4)/365)*((Q12-$B$4)/365)/10000 | U12: =(S12-T12/100)/100 | V12: =W11 | W12: =V12/(1+U12*R12) | Y12: =MAX(Q11,$B$22) | Z12: =W11
A13: 3M | B13: =EDATE($B$4,3) | C13: =(B13-$B$4)/365 | D13: =(B13-$B$4)/360 | E13: ='SOFR_OIS_Quotes'!$H10 | G13: =SUM($I$8:I12) | H13: =1/(1+(E13/100)*D13) | I13: 0 | J13: =-LN(H13)/C13*100 | K13: =(H12/H13-1)/((B13-B12)/360)*100 | M13: =IF(L13="","",(J13-L13)*100) | N13: short OIS | O13: ='SOFR_Futures'!A12 | P13: ='SOFR_Futures'!H12 | Q13: ='SOFR_Futures'!H13 | R13: =MAX(0,(Q13-MAX(P13,$B$22))/360) | S13: ='SOFR_Futures'!F12 | T13: =0.5*$P$5^2*((P13-$B$4)/365)*((Q13-$B$4)/365)/10000 | U13: =(S13-T13/100)/100 | V13: =W12 | W13: =V13/(1+U13*R13) | Y13: =MAX(Q12,$B$22) | Z13: =W12
A14: 4M | B14: =EDATE($B$4,4) | C14: =(B14-$B$4)/365 | D14: =(B14-$B$4)/360 | E14: ='SOFR_OIS_Quotes'!$H11 | G14: =SUM($I$8:I13) | H14: =1/(1+(E14/100)*D14) | I14: 0 | J14: =-LN(H14)/C14*100 | K14: =(H13/H14-1)/((B14-B13)/360)*100 | M14: =IF(L14="","",(J14-L14)*100) | N14: short OIS | O14: ='SOFR_Futures'!A13 | P14: ='SOFR_Futures'!H13 | Q14: ='SOFR_Futures'!H14 | R14: =MAX(0,(Q14-MAX(P14,$B$22))/360) | S14: ='SOFR_Futures'!F13 | T14: =0.5*$P$5^2*((P14-$B$4)/365)*((Q14-$B$4)/365)/10000 | U14: =(S14-T14/100)/100 | V14: =W13 | W14: =V14/(1+U14*R14) | Y14: =MAX(Q13,$B$22) | Z14: =W13
A15: 5M | B15: =EDATE($B$4,5) | C15: =(B15-$B$4)/365 | D15: =(B15-$B$4)/360 | E15: ='SOFR_OIS_Quotes'!$H12 | G15: =SUM($I$8:I14) | H15: =1/(1+(E15/100)*D15) | I15: 0 | J15: =-LN(H15)/C15*100 | K15: =(H14/H15-1)/((B15-B14)/360)*100 | M15: =IF(L15="","",(J15-L15)*100) | N15: short OIS | O15: ='SOFR_Futures'!A14 | P15: ='SOFR_Futures'!H14 | Q15: ='SOFR_Futures'!H15 | R15: =MAX(0,(Q15-MAX(P15,$B$22))/360) | S15: ='SOFR_Futures'!F14 | T15: =0.5*$P$5^2*((P15-$B$4)/365)*((Q15-$B$4)/365)/10000 | U15: =(S15-T15/100)/100 | V15: =W14 | W15: =V15/(1+U15*R15) | Y15: =MAX(Q14,$B$22) | Z15: =W14
A16: 6M | B16: =EDATE($B$4,6) | C16: =(B16-$B$4)/365 | D16: =(B16-$B$4)/360 | E16: ='SOFR_OIS_Quotes'!$H13 | G16: =SUM($I$8:I15) | H16: =1/(1+(E16/100)*D16) | I16: 0 | J16: =-LN(H16)/C16*100 | K16: =(H15/H16-1)/((B16-B15)/360)*100 | M16: =IF(L16="","",(J16-L16)*100) | N16: short OIS | O16: ='SOFR_Futures'!A15 | P16: ='SOFR_Futures'!H15 | Q16: ='SOFR_Futures'!H16 | R16: =MAX(0,(Q16-MAX(P16,$B$22))/360) | S16: ='SOFR_Futures'!F15 | T16: =0.5*$P$5^2*((P16-$B$4)/365)*((Q16-$B$4)/365)/10000 | U16: =(S16-T16/100)/100 | V16: =W15 | W16: =V16/(1+U16*R16) | Y16: =MAX(Q15,$B$22) | Z16: =W15
A17: 7M | B17: =EDATE($B$4,7) | C17: =(B17-$B$4)/365 | D17: =(B17-$B$4)/360 | E17: ='SOFR_OIS_Quotes'!$H14 | G17: =SUM($I$8:I16) | H17: =1/(1+(E17/100)*D17) | I17: 0 | J17: =-LN(H17)/C17*100 | K17: =(H16/H17-1)/((B17-B16)/360)*100 | M17: =IF(L17="","",(J17-L17)*100) | N17: short OIS | O17: ='SOFR_Futures'!A16 | P17: ='SOFR_Futures'!H16 | Q17: ='SOFR_Futures'!H17 | R17: =MAX(0,(Q17-MAX(P17,$B$22))/360) | S17: ='SOFR_Futures'!F16 | T17: =0.5*$P$5^2*((P17-$B$4)/365)*((Q17-$B$4)/365)/10000 | U17: =(S17-T17/100)/100 | V17: =W16 | W17: =V17/(1+U17*R17) | Y17: =MAX(Q16,$B$22) | Z17: =W16
A18: 8M | B18: =EDATE($B$4,8) | C18: =(B18-$B$4)/365 | D18: =(B18-$B$4)/360 | E18: ='SOFR_OIS_Quotes'!$H15 | G18: =SUM($I$8:I17) | H18: =1/(1+(E18/100)*D18) | I18: 0 | J18: =-LN(H18)/C18*100 | K18: =(H17/H18-1)/((B18-B17)/360)*100 | M18: =IF(L18="","",(J18-L18)*100) | N18: short OIS | O18: ='SOFR_Futures'!A17 | P18: ='SOFR_Futures'!H17 | Q18: ='SOFR_Futures'!H18 | R18: =MAX(0,(Q18-MAX(P18,$B$22))/360) | S18: ='SOFR_Futures'!F17 | T18: =0.5*$P$5^2*((P18-$B$4)/365)*((Q18-$B$4)/365)/10000 | U18: =(S18-T18/100)/100 | V18: =W17 | W18: =V18/(1+U18*R18) | Y18: =MAX(Q17,$B$22) | Z18: =W17
A19: 9M | B19: =EDATE($B$4,9) | C19: =(B19-$B$4)/365 | D19: =(B19-$B$4)/360 | E19: ='SOFR_OIS_Quotes'!$H16 | G19: =SUM($I$8:I18) | H19: =1/(1+(E19/100)*D19) | I19: 0 | J19: =-LN(H19)/C19*100 | K19: =(H18/H19-1)/((B19-B18)/360)*100 | M19: =IF(L19="","",(J19-L19)*100) | N19: short OIS | O19: ='SOFR_Futures'!A18 | P19: ='SOFR_Futures'!H18 | Q19: ='SOFR_Futures'!H19 | R19: =MAX(0,(Q19-MAX(P19,$B$22))/360) | S19: ='SOFR_Futures'!F18 | T19: =0.5*$P$5^2*((P19-$B$4)/365)*((Q19-$B$4)/365)/10000 | U19: =(S19-T19/100)/100 | V19: =W18 | W19: =V19/(1+U19*R19) | Y19: =MAX(Q18,$B$22) | Z19: =W18
A20: 10M | B20: =EDATE($B$4,10) | C20: =(B20-$B$4)/365 | D20: =(B20-$B$4)/360 | E20: ='SOFR_OIS_Quotes'!$H17 | G20: =SUM($I$8:I19) | H20: =1/(1+(E20/100)*D20) | I20: 0 | J20: =-LN(H20)/C20*100 | K20: =(H19/H20-1)/((B20-B19)/360)*100 | M20: =IF(L20="","",(J20-L20)*100) | N20: short OIS | O20: ='SOFR_Futures'!A19 | P20: ='SOFR_Futures'!H19 | Q20: ='SOFR_Futures'!H20 | R20: =MAX(0,(Q20-MAX(P20,$B$22))/360) | S20: ='SOFR_Futures'!F19 | T20: =0.5*$P$5^2*((P20-$B$4)/365)*((Q20-$B$4)/365)/10000 | U20: =(S20-T20/100)/100 | V20: =W19 | W20: =V20/(1+U20*R20) | Y20: =MAX(Q19,$B$22) | Z20: =W19
A21: 11M | B21: =EDATE($B$4,11) | C21: =(B21-$B$4)/365 | D21: =(B21-$B$4)/360 | E21: ='SOFR_OIS_Quotes'!$H18 | G21: =SUM($I$8:I20) | H21: =1/(1+(E21/100)*D21) | I21: 0 | J21: =-LN(H21)/C21*100 | K21: =(H20/H21-1)/((B21-B20)/360)*100 | M21: =IF(L21="","",(J21-L21)*100) | N21: short OIS | O21: ='SOFR_Futures'!A20 | P21: ='SOFR_Futures'!H20 | Q21: ='SOFR_Futures'!H21 | R21: =MAX(0,(Q21-MAX(P21,$B$22))/360) | S21: ='SOFR_Futures'!F20 | T21: =0.5*$P$5^2*((P21-$B$4)/365)*((Q21-$B$4)/365)/10000 | U21: =(S21-T21/100)/100 | V21: =W20 | W21: =V21/(1+U21*R21) | Y21: =MAX(Q20,$B$22) | Z21: =W20
A22: 1Y | B22: =EDATE($B$4,12) | C22: =(B22-$B$4)/365 | D22: =(B22-$B$4)/360 | E22: ='SOFR_OIS_Quotes'!$H19 | F22: =(B22-$B$4)/360 | G22: =SUM($I$8:I21) | H22: =1/(1+(E22/100)*D22) | I22: =F22*H22 | J22: =-LN(H22)/C22*100 | K22: =(H21/H22-1)/((B22-B21)/360)*100 | M22: =IF(L22="","",(J22-L22)*100) | N22: short OIS | O22: ='SOFR_Futures'!A21 | P22: ='SOFR_Futures'!H21 | Q22: ='SOFR_Futures'!H22 | R22: =MAX(0,(Q22-MAX(P22,$B$22))/360) | S22: ='SOFR_Futures'!F21 | T22: =0.5*$P$5^2*((P22-$B$4)/365)*((Q22-$B$4)/365)/10000 | U22: =(S22-T22/100)/100 | V22: =W21 | W22: =V22/(1+U22*R22) | Y22: =MAX(Q21,$B$22) | Z22: =W21
A23: 18M | B23: =EDATE($B$4,18) | C23: =(B23-$B$4)/365 | D23: =(B23-$B$4)/360 | E23: ='SOFR_OIS_Quotes'!$H20 | F23: =(B23-$B$22)/360 | G23: =SUM($I$8:I22) | H23: =IFERROR(IF(ABS((IFERROR(INDEX($Z$8:$Z$28,MATCH(B23,$Y$8:$Y$28,1))*(INDEX($Z$8:$Z$28,MATCH(B23,$Y$8:$Y$28,1)+1)/INDEX($Z$8:$Z$28,MATCH(B23,$Y$8:$Y$28,1)))^((B23-INDEX($Y$8:$Y$28,MATCH(B23,$Y$8:$Y$28,1)))/(INDEX($Y$8:$Y$28,MATCH(B23,$Y$8:$Y$28,1)+1)-INDEX($Y$8:$Y$28,MATCH(B23,$Y$8:$Y$28,1)))),INDEX($Z$8:$Z$28,MATCH(B23,$Y$8:$Y$28,1))))-((1-(E23/100)*G23)/(1+(E23/100)*F23)))<0.03,(IFERROR(INDEX($Z$8:$Z$28,MATCH(B23,$Y$8:$Y$28,1))*(INDEX($Z$8:$Z$28,MATCH(B23,$Y$8:$Y$28,1)+1)/INDEX($Z$8:$Z$28,MATCH(B23,$Y$8:$Y$28,1)))^((B23-INDEX($Y$8:$Y$28,MATCH(B23,$Y$8:$Y$28,1)))/(INDEX($Y$8:$Y$28,MATCH(B23,$Y$8:$Y$28,1)+1)-INDEX($Y$8:$Y$28,MATCH(B23,$Y$8:$Y$28,1)))),INDEX($Z$8:$Z$28,MATCH(B23,$Y$8:$Y$28,1)))),((1-(E23/100)*G23)/(1+(E23/100)*F23))),((1-(E23/100)*G23)/(1+(E23/100)*F23))) | I23: 0 | J23: =-LN(H23)/C23*100 | K23: =(H22/H23-1)/((B23-B22)/360)*100 | M23: =IF(L23="","",(J23-L23)*100) | N23: =IF(AND(ISNUMBER(IFERROR(INDEX($Z$8:$Z$28,MATCH(B23,$Y$8:$Y$28,1))*(INDEX($Z$8:$Z$28,MATCH(B23,$Y$8:$Y$28,1)+1)/INDEX($Z$8:$Z$28,MATCH(B23,$Y$8:$Y$28,1)))^((B23-INDEX($Y$8:$Y$28,MATCH(B23,$Y$8:$Y$28,1)))/(INDEX($Y$8:$Y$28,MATCH(B23,$Y$8:$Y$28,1)+1)-INDEX($Y$8:$Y$28,MATCH(B23,$Y$8:$Y$28,1)))),INDEX($Z$8:$Z$28,MATCH(B23,$Y$8:$Y$28,1)))),ABS((IFERROR(INDEX($Z$8:$Z$28,MATCH(B23,$Y$8:$Y$28,1))*(INDEX($Z$8:$Z$28,MATCH(B23,$Y$8:$Y$28,1)+1)/INDEX($Z$8:$Z$28,MATCH(B23,$Y$8:$Y$28,1)))^((B23-INDEX($Y$8:$Y$28,MATCH(B23,$Y$8:$Y$28,1)))/(INDEX($Y$8:$Y$28,MATCH(B23,$Y$8:$Y$28,1)+1)-INDEX($Y$8:$Y$28,MATCH(B23,$Y$8:$Y$28,1)))),INDEX($Z$8:$Z$28,MATCH(B23,$Y$8:$Y$28,1))))-((1-(E23/100)*G23)/(1+(E23/100)*F23)))<0.03),"SR3 futures","OIS fallback") | O23: ='SOFR_Futures'!A22 | P23: ='SOFR_Futures'!H22 | Q23: ='SOFR_Futures'!H23 | R23: =MAX(0,(Q23-MAX(P23,$B$22))/360) | S23: ='SOFR_Futures'!F22 | T23: =0.5*$P$5^2*((P23-$B$4)/365)*((Q23-$B$4)/365)/10000 | U23: =(S23-T23/100)/100 | V23: =W22 | W23: =V23/(1+U23*R23) | Y23: =MAX(Q22,$B$22) | Z23: =W22
A24: 2Y | B24: =EDATE($B$4,24) | C24: =(B24-$B$4)/365 | D24: =(B24-$B$4)/360 | E24: ='SOFR_OIS_Quotes'!$H21 | F24: =(B24-$B$22)/360 | G24: =SUM($I$8:I23) | H24: =IFERROR(IF(ABS((IFERROR(INDEX($Z$8:$Z$28,MATCH(B24,$Y$8:$Y$28,1))*(INDEX($Z$8:$Z$28,MATCH(B24,$Y$8:$Y$28,1)+1)/INDEX($Z$8:$Z$28,MATCH(B24,$Y$8:$Y$28,1)))^((B24-INDEX($Y$8:$Y$28,MATCH(B24,$Y$8:$Y$28,1)))/(INDEX($Y$8:$Y$28,MATCH(B24,$Y$8:$Y$28,1)+1)-INDEX($Y$8:$Y$28,MATCH(B24,$Y$8:$Y$28,1)))),INDEX($Z$8:$Z$28,MATCH(B24,$Y$8:$Y$28,1))))-((1-(E24/100)*G24)/(1+(E24/100)*F24)))<0.03,(IFERROR(INDEX($Z$8:$Z$28,MATCH(B24,$Y$8:$Y$28,1))*(INDEX($Z$8:$Z$28,MATCH(B24,$Y$8:$Y$28,1)+1)/INDEX($Z$8:$Z$28,MATCH(B24,$Y$8:$Y$28,1)))^((B24-INDEX($Y$8:$Y$28,MATCH(B24,$Y$8:$Y$28,1)))/(INDEX($Y$8:$Y$28,MATCH(B24,$Y$8:$Y$28,1)+1)-INDEX($Y$8:$Y$28,MATCH(B24,$Y$8:$Y$28,1)))),INDEX($Z$8:$Z$28,MATCH(B24,$Y$8:$Y$28,1)))),((1-(E24/100)*G24)/(1+(E24/100)*F24))),((1-(E24/100)*G24)/(1+(E24/100)*F24))) | I24: =F24*H24 | J24: =-LN(H24)/C24*100 | K24: =(H23/H24-1)/((B24-B23)/360)*100 | M24: =IF(L24="","",(J24-L24)*100) | N24: =IF(AND(ISNUMBER(IFERROR(INDEX($Z$8:$Z$28,MATCH(B24,$Y$8:$Y$28,1))*(INDEX($Z$8:$Z$28,MATCH(B24,$Y$8:$Y$28,1)+1)/INDEX($Z$8:$Z$28,MATCH(B24,$Y$8:$Y$28,1)))^((B24-INDEX($Y$8:$Y$28,MATCH(B24,$Y$8:$Y$28,1)))/(INDEX($Y$8:$Y$28,MATCH(B24,$Y$8:$Y$28,1)+1)-INDEX($Y$8:$Y$28,MATCH(B24,$Y$8:$Y$28,1)))),INDEX($Z$8:$Z$28,MATCH(B24,$Y$8:$Y$28,1)))),ABS((IFERROR(INDEX($Z$8:$Z$28,MATCH(B24,$Y$8:$Y$28,1))*(INDEX($Z$8:$Z$28,MATCH(B24,$Y$8:$Y$28,1)+1)/INDEX($Z$8:$Z$28,MATCH(B24,$Y$8:$Y$28,1)))^((B24-INDEX($Y$8:$Y$28,MATCH(B24,$Y$8:$Y$28,1)))/(INDEX($Y$8:$Y$28,MATCH(B24,$Y$8:$Y$28,1)+1)-INDEX($Y$8:$Y$28,MATCH(B24,$Y$8:$Y$28,1)))),INDEX($Z$8:$Z$28,MATCH(B24,$Y$8:$Y$28,1))))-((1-(E24/100)*G24)/(1+(E24/100)*F24)))<0.03),"SR3 futures","OIS fallback") | O24: ='SOFR_Futures'!A23 | P24: ='SOFR_Futures'!H23 | Q24: ='SOFR_Futures'!H24 | R24: =MAX(0,(Q24-MAX(P24,$B$22))/360) | S24: ='SOFR_Futures'!F23 | T24: =0.5*$P$5^2*((P24-$B$4)/365)*((Q24-$B$4)/365)/10000 | U24: =(S24-T24/100)/100 | V24: =W23 | W24: =V24/(1+U24*R24) | Y24: =MAX(Q23,$B$22) | Z24: =W23
A25: 3Y | B25: =EDATE($B$4,36) | C25: =(B25-$B$4)/365 | D25: =(B25-$B$4)/360 | E25: ='SOFR_OIS_Quotes'!$H22 | F25: =(B25-$B$24)/360 | G25: =SUM($I$8:I24) | H25: =IFERROR(IF(ABS((IFERROR(INDEX($Z$8:$Z$28,MATCH(B25,$Y$8:$Y$28,1))*(INDEX($Z$8:$Z$28,MATCH(B25,$Y$8:$Y$28,1)+1)/INDEX($Z$8:$Z$28,MATCH(B25,$Y$8:$Y$28,1)))^((B25-INDEX($Y$8:$Y$28,MATCH(B25,$Y$8:$Y$28,1)))/(INDEX($Y$8:$Y$28,MATCH(B25,$Y$8:$Y$28,1)+1)-INDEX($Y$8:$Y$28,MATCH(B25,$Y$8:$Y$28,1)))),INDEX($Z$8:$Z$28,MATCH(B25,$Y$8:$Y$28,1))))-((1-(E25/100)*G25)/(1+(E25/100)*F25)))<0.03,(IFERROR(INDEX($Z$8:$Z$28,MATCH(B25,$Y$8:$Y$28,1))*(INDEX($Z$8:$Z$28,MATCH(B25,$Y$8:$Y$28,1)+1)/INDEX($Z$8:$Z$28,MATCH(B25,$Y$8:$Y$28,1)))^((B25-INDEX($Y$8:$Y$28,MATCH(B25,$Y$8:$Y$28,1)))/(INDEX($Y$8:$Y$28,MATCH(B25,$Y$8:$Y$28,1)+1)-INDEX($Y$8:$Y$28,MATCH(B25,$Y$8:$Y$28,1)))),INDEX($Z$8:$Z$28,MATCH(B25,$Y$8:$Y$28,1)))),((1-(E25/100)*G25)/(1+(E25/100)*F25))),((1-(E25/100)*G25)/(1+(E25/100)*F25))) | I25: =F25*H25 | J25: =-LN(H25)/C25*100 | K25: =(H24/H25-1)/((B25-B24)/360)*100 | M25: =IF(L25="","",(J25-L25)*100) | N25: =IF(AND(ISNUMBER(IFERROR(INDEX($Z$8:$Z$28,MATCH(B25,$Y$8:$Y$28,1))*(INDEX($Z$8:$Z$28,MATCH(B25,$Y$8:$Y$28,1)+1)/INDEX($Z$8:$Z$28,MATCH(B25,$Y$8:$Y$28,1)))^((B25-INDEX($Y$8:$Y$28,MATCH(B25,$Y$8:$Y$28,1)))/(INDEX($Y$8:$Y$28,MATCH(B25,$Y$8:$Y$28,1)+1)-INDEX($Y$8:$Y$28,MATCH(B25,$Y$8:$Y$28,1)))),INDEX($Z$8:$Z$28,MATCH(B25,$Y$8:$Y$28,1)))),ABS((IFERROR(INDEX($Z$8:$Z$28,MATCH(B25,$Y$8:$Y$28,1))*(INDEX($Z$8:$Z$28,MATCH(B25,$Y$8:$Y$28,1)+1)/INDEX($Z$8:$Z$28,MATCH(B25,$Y$8:$Y$28,1)))^((B25-INDEX($Y$8:$Y$28,MATCH(B25,$Y$8:$Y$28,1)))/(INDEX($Y$8:$Y$28,MATCH(B25,$Y$8:$Y$28,1)+1)-INDEX($Y$8:$Y$28,MATCH(B25,$Y$8:$Y$28,1)))),INDEX($Z$8:$Z$28,MATCH(B25,$Y$8:$Y$28,1))))-((1-(E25/100)*G25)/(1+(E25/100)*F25)))<0.03),"SR3 futures","OIS fallback") | O25: ='SOFR_Futures'!A24 | P25: ='SOFR_Futures'!H24 | Q25: ='SOFR_Futures'!H25 | R25: =MAX(0,(Q25-MAX(P25,$B$22))/360) | S25: ='SOFR_Futures'!F24 | T25: =0.5*$P$5^2*((P25-$B$4)/365)*((Q25-$B$4)/365)/10000 | U25: =(S25-T25/100)/100 | V25: =W24 | W25: =V25/(1+U25*R25) | Y25: =MAX(Q24,$B$22) | Z25: =W24
A26: 4Y | B26: =EDATE($B$4,48) | C26: =(B26-$B$4)/365 | D26: =(B26-$B$4)/360 | E26: ='SOFR_OIS_Quotes'!$H23 | F26: =(B26-$B$25)/360 | G26: =SUM($I$8:I25) | H26: =IFERROR(IF(ABS((IFERROR(INDEX($Z$8:$Z$28,MATCH(B26,$Y$8:$Y$28,1))*(INDEX($Z$8:$Z$28,MATCH(B26,$Y$8:$Y$28,1)+1)/INDEX($Z$8:$Z$28,MATCH(B26,$Y$8:$Y$28,1)))^((B26-INDEX($Y$8:$Y$28,MATCH(B26,$Y$8:$Y$28,1)))/(INDEX($Y$8:$Y$28,MATCH(B26,$Y$8:$Y$28,1)+1)-INDEX($Y$8:$Y$28,MATCH(B26,$Y$8:$Y$28,1)))),INDEX($Z$8:$Z$28,MATCH(B26,$Y$8:$Y$28,1))))-((1-(E26/100)*G26)/(1+(E26/100)*F26)))<0.03,(IFERROR(INDEX($Z$8:$Z$28,MATCH(B26,$Y$8:$Y$28,1))*(INDEX($Z$8:$Z$28,MATCH(B26,$Y$8:$Y$28,1)+1)/INDEX($Z$8:$Z$28,MATCH(B26,$Y$8:$Y$28,1)))^((B26-INDEX($Y$8:$Y$28,MATCH(B26,$Y$8:$Y$28,1)))/(INDEX($Y$8:$Y$28,MATCH(B26,$Y$8:$Y$28,1)+1)-INDEX($Y$8:$Y$28,MATCH(B26,$Y$8:$Y$28,1)))),INDEX($Z$8:$Z$28,MATCH(B26,$Y$8:$Y$28,1)))),((1-(E26/100)*G26)/(1+(E26/100)*F26))),((1-(E26/100)*G26)/(1+(E26/100)*F26))) | I26: =F26*H26 | J26: =-LN(H26)/C26*100 | K26: =(H25/H26-1)/((B26-B25)/360)*100 | M26: =IF(L26="","",(J26-L26)*100) | N26: =IF(AND(ISNUMBER(IFERROR(INDEX($Z$8:$Z$28,MATCH(B26,$Y$8:$Y$28,1))*(INDEX($Z$8:$Z$28,MATCH(B26,$Y$8:$Y$28,1)+1)/INDEX($Z$8:$Z$28,MATCH(B26,$Y$8:$Y$28,1)))^((B26-INDEX($Y$8:$Y$28,MATCH(B26,$Y$8:$Y$28,1)))/(INDEX($Y$8:$Y$28,MATCH(B26,$Y$8:$Y$28,1)+1)-INDEX($Y$8:$Y$28,MATCH(B26,$Y$8:$Y$28,1)))),INDEX($Z$8:$Z$28,MATCH(B26,$Y$8:$Y$28,1)))),ABS((IFERROR(INDEX($Z$8:$Z$28,MATCH(B26,$Y$8:$Y$28,1))*(INDEX($Z$8:$Z$28,MATCH(B26,$Y$8:$Y$28,1)+1)/INDEX($Z$8:$Z$28,MATCH(B26,$Y$8:$Y$28,1)))^((B26-INDEX($Y$8:$Y$28,MATCH(B26,$Y$8:$Y$28,1)))/(INDEX($Y$8:$Y$28,MATCH(B26,$Y$8:$Y$28,1)+1)-INDEX($Y$8:$Y$28,MATCH(B26,$Y$8:$Y$28,1)))),INDEX($Z$8:$Z$28,MATCH(B26,$Y$8:$Y$28,1))))-((1-(E26/100)*G26)/(1+(E26/100)*F26)))<0.03),"SR3 futures","OIS fallback") | O26: ='SOFR_Futures'!A25 | P26: ='SOFR_Futures'!H25 | Q26: ='SOFR_Futures'!H26 | R26: =MAX(0,(Q26-MAX(P26,$B$22))/360) | S26: ='SOFR_Futures'!F25 | T26: =0.5*$P$5^2*((P26-$B$4)/365)*((Q26-$B$4)/365)/10000 | U26: =(S26-T26/100)/100 | V26: =W25 | W26: =V26/(1+U26*R26) | Y26: =MAX(Q25,$B$22) | Z26: =W25
A27: 5Y | B27: =EDATE($B$4,60) | C27: =(B27-$B$4)/365 | D27: =(B27-$B$4)/360 | E27: ='SOFR_OIS_Quotes'!$H24 | F27: =(B27-$B$26)/360 | G27: =SUM($I$8:I26) | H27: =IFERROR(IF(ABS((IFERROR(INDEX($Z$8:$Z$28,MATCH(B27,$Y$8:$Y$28,1))*(INDEX($Z$8:$Z$28,MATCH(B27,$Y$8:$Y$28,1)+1)/INDEX($Z$8:$Z$28,MATCH(B27,$Y$8:$Y$28,1)))^((B27-INDEX($Y$8:$Y$28,MATCH(B27,$Y$8:$Y$28,1)))/(INDEX($Y$8:$Y$28,MATCH(B27,$Y$8:$Y$28,1)+1)-INDEX($Y$8:$Y$28,MATCH(B27,$Y$8:$Y$28,1)))),INDEX($Z$8:$Z$28,MATCH(B27,$Y$8:$Y$28,1))))-((1-(E27/100)*G27)/(1+(E27/100)*F27)))<0.03,(IFERROR(INDEX($Z$8:$Z$28,MATCH(B27,$Y$8:$Y$28,1))*(INDEX($Z$8:$Z$28,MATCH(B27,$Y$8:$Y$28,1)+1)/INDEX($Z$8:$Z$28,MATCH(B27,$Y$8:$Y$28,1)))^((B27-INDEX($Y$8:$Y$28,MATCH(B27,$Y$8:$Y$28,1)))/(INDEX($Y$8:$Y$28,MATCH(B27,$Y$8:$Y$28,1)+1)-INDEX($Y$8:$Y$28,MATCH(B27,$Y$8:$Y$28,1)))),INDEX($Z$8:$Z$28,MATCH(B27,$Y$8:$Y$28,1)))),((1-(E27/100)*G27)/(1+(E27/100)*F27))),((1-(E27/100)*G27)/(1+(E27/100)*F27))) | I27: =F27*H27 | J27: =-LN(H27)/C27*100 | K27: =(H26/H27-1)/((B27-B26)/360)*100 | M27: =IF(L27="","",(J27-L27)*100) | N27: =IF(AND(ISNUMBER(IFERROR(INDEX($Z$8:$Z$28,MATCH(B27,$Y$8:$Y$28,1))*(INDEX($Z$8:$Z$28,MATCH(B27,$Y$8:$Y$28,1)+1)/INDEX($Z$8:$Z$28,MATCH(B27,$Y$8:$Y$28,1)))^((B27-INDEX($Y$8:$Y$28,MATCH(B27,$Y$8:$Y$28,1)))/(INDEX($Y$8:$Y$28,MATCH(B27,$Y$8:$Y$28,1)+1)-INDEX($Y$8:$Y$28,MATCH(B27,$Y$8:$Y$28,1)))),INDEX($Z$8:$Z$28,MATCH(B27,$Y$8:$Y$28,1)))),ABS((IFERROR(INDEX($Z$8:$Z$28,MATCH(B27,$Y$8:$Y$28,1))*(INDEX($Z$8:$Z$28,MATCH(B27,$Y$8:$Y$28,1)+1)/INDEX($Z$8:$Z$28,MATCH(B27,$Y$8:$Y$28,1)))^((B27-INDEX($Y$8:$Y$28,MATCH(B27,$Y$8:$Y$28,1)))/(INDEX($Y$8:$Y$28,MATCH(B27,$Y$8:$Y$28,1)+1)-INDEX($Y$8:$Y$28,MATCH(B27,$Y$8:$Y$28,1)))),INDEX($Z$8:$Z$28,MATCH(B27,$Y$8:$Y$28,1))))-((1-(E27/100)*G27)/(1+(E27/100)*F27)))<0.03),"SR3 futures","OIS fallback") | O27: ='SOFR_Futures'!A26 | P27: ='SOFR_Futures'!H26 | Q27: =EDATE(P27,3) | R27: =MAX(0,(Q27-MAX(P27,$B$22))/360) | S27: ='SOFR_Futures'!F26 | T27: =0.5*$P$5^2*((P27-$B$4)/365)*((Q27-$B$4)/365)/10000 | U27: =(S27-T27/100)/100 | V27: =W26 | W27: =V27/(1+U27*R27) | Y27: =MAX(Q26,$B$22) | Z27: =W26
A28: 6Y | B28: =EDATE($B$4,72) | C28: =(B28-$B$4)/365 | D28: =(B28-$B$4)/360 | E28: ='SOFR_OIS_Quotes'!$H25 | F28: =(B28-$B$27)/360 | G28: =SUM($I$8:I27) | H28: =(1-(E28/100)*G28)/(1+(E28/100)*F28) | I28: =F28*H28 | J28: =-LN(H28)/C28*100 | K28: =(H27/H28-1)/((B28-B27)/360)*100 | M28: =IF(L28="","",(J28-L28)*100) | N28: OIS swap | Y28: =MAX(Q27,$B$22) | Z28: =W27
A29: 7Y | B29: =EDATE($B$4,84) | C29: =(B29-$B$4)/365 | D29: =(B29-$B$4)/360 | E29: ='SOFR_OIS_Quotes'!$H26 | F29: =(B29-$B$28)/360 | G29: =SUM($I$8:I28) | H29: =(1-(E29/100)*G29)/(1+(E29/100)*F29) | I29: =F29*H29 | J29: =-LN(H29)/C29*100 | K29: =(H28/H29-1)/((B29-B28)/360)*100 | M29: =IF(L29="","",(J29-L29)*100) | N29: OIS swap
A30: 8Y | B30: =EDATE($B$4,96) | C30: =(B30-$B$4)/365 | D30: =(B30-$B$4)/360 | E30: ='SOFR_OIS_Quotes'!$H27 | F30: =(B30-$B$29)/360 | G30: =SUM($I$8:I29) | H30: =(1-(E30/100)*G30)/(1+(E30/100)*F30) | I30: =F30*H30 | J30: =-LN(H30)/C30*100 | K30: =(H29/H30-1)/((B30-B29)/360)*100 | M30: =IF(L30="","",(J30-L30)*100) | N30: OIS swap
A31: 9Y | B31: =EDATE($B$4,108) | C31: =(B31-$B$4)/365 | D31: =(B31-$B$4)/360 | E31: ='SOFR_OIS_Quotes'!$H28 | F31: =(B31-$B$30)/360 | G31: =SUM($I$8:I30) | H31: =(1-(E31/100)*G31)/(1+(E31/100)*F31) | I31: =F31*H31 | J31: =-LN(H31)/C31*100 | K31: =(H30/H31-1)/((B31-B30)/360)*100 | M31: =IF(L31="","",(J31-L31)*100) | N31: OIS swap
A32: 10Y | B32: =EDATE($B$4,120) | C32: =(B32-$B$4)/365 | D32: =(B32-$B$4)/360 | E32: ='SOFR_OIS_Quotes'!$H29 | F32: =(B32-$B$31)/360 | G32: =SUM($I$8:I31) | H32: =(1-(E32/100)*G32)/(1+(E32/100)*F32) | I32: =F32*H32 | J32: =-LN(H32)/C32*100 | K32: =(H31/H32-1)/((B32-B31)/360)*100 | M32: =IF(L32="","",(J32-L32)*100) | N32: OIS swap
A33: 12Y | B33: =EDATE($B$4,144) | C33: =(B33-$B$4)/365 | D33: =(B33-$B$4)/360 | E33: ='SOFR_OIS_Quotes'!$H30 | F33: =(B33-$B$32)/360 | G33: =SUM($I$8:I32) | H33: =(1-(E33/100)*G33)/(1+(E33/100)*F33) | I33: =F33*H33 | J33: =-LN(H33)/C33*100 | K33: =(H32/H33-1)/((B33-B32)/360)*100 | M33: =IF(L33="","",(J33-L33)*100) | N33: OIS swap
A34: 15Y | B34: =EDATE($B$4,180) | C34: =(B34-$B$4)/365 | D34: =(B34-$B$4)/360 | E34: ='SOFR_OIS_Quotes'!$H31 | F34: =(B34-$B$33)/360 | G34: =SUM($I$8:I33) | H34: =(1-(E34/100)*G34)/(1+(E34/100)*F34) | I34: =F34*H34 | J34: =-LN(H34)/C34*100 | K34: =(H33/H34-1)/((B34-B33)/360)*100 | M34: =IF(L34="","",(J34-L34)*100) | N34: OIS swap
A35: 20Y | B35: =EDATE($B$4,240) | C35: =(B35-$B$4)/365 | D35: =(B35-$B$4)/360 | E35: ='SOFR_OIS_Quotes'!$H32 | F35: =(B35-$B$34)/360 | G35: =SUM($I$8:I34) | H35: =(1-(E35/100)*G35)/(1+(E35/100)*F35) | I35: =F35*H35 | J35: =-LN(H35)/C35*100 | K35: =(H34/H35-1)/((B35-B34)/360)*100 | M35: =IF(L35="","",(J35-L35)*100) | N35: OIS swap
A36: 25Y | B36: =EDATE($B$4,300) | C36: =(B36-$B$4)/365 | D36: =(B36-$B$4)/360 | E36: ='SOFR_OIS_Quotes'!$H33 | F36: =(B36-$B$35)/360 | G36: =SUM($I$8:I35) | H36: =(1-(E36/100)*G36)/(1+(E36/100)*F36) | I36: =F36*H36 | J36: =-LN(H36)/C36*100 | K36: =(H35/H36-1)/((B36-B35)/360)*100 | M36: =IF(L36="","",(J36-L36)*100) | N36: OIS swap
A37: 30Y | B37: =EDATE($B$4,360) | C37: =(B37-$B$4)/365 | D37: =(B37-$B$4)/360 | E37: ='SOFR_OIS_Quotes'!$H34 | F37: =(B37-$B$36)/360 | G37: =SUM($I$8:I36) | H37: =(1-(E37/100)*G37)/(1+(E37/100)*F37) | I37: =F37*H37 | J37: =-LN(H37)/C37*100 | K37: =(H36/H37-1)/((B37-B36)/360)*100 | M37: =IF(L37="","",(J37-L37)*100) | N37: OIS swap
A38: 40Y | B38: =EDATE($B$4,480) | C38: =(B38-$B$4)/365 | D38: =(B38-$B$4)/360 | E38: ='SOFR_OIS_Quotes'!$H35 | F38: =(B38-$B$37)/360 | G38: =SUM($I$8:I37) | H38: =(1-(E38/100)*G38)/(1+(E38/100)*F38) | I38: =F38*H38 | J38: =-LN(H38)/C38*100 | K38: =(H37/H38-1)/((B38-B37)/360)*100 | M38: =IF(L38="","",(J38-L38)*100) | N38: OIS swap
A39: 50Y | B39: =EDATE($B$4,600) | C39: =(B39-$B$4)/365 | D39: =(B39-$B$4)/360 | E39: ='SOFR_OIS_Quotes'!$H36 | F39: =(B39-$B$38)/360 | G39: =SUM($I$8:I38) | H39: =(1-(E39/100)*G39)/(1+(E39/100)*F39) | I39: =F39*H39 | J39: =-LN(H39)/C39*100 | K39: =(H38/H39-1)/((B39-B38)/360)*100 | M39: =IF(L39="","",(J39-L39)*100) | N39: OIS swap
A41: THREE SEGMENTS (Zhou 2002 structure): SHORT o/n–1Y = single-payment SOFR OIS (DF=1/(1+S·tau0)); MIDDLE 1Y–5Y = SR3 futures chained from the 1Y DF (helper block to the right, cols O–W); LONG 5Y–50Y = annual SOFR OIS swaps built off the futures-derived 5Y point. No overlap — each maturity is covered once. Column H is the curve P(0,T); zero z=−ln(DF)/T; DF source is in col N. Futures→forward convexity (chain col T) = 0.5·sigma^2·t1·t2, driven by the yellow sigma (bp/yr) input above the chain — raise it and the futures pull below the OIS levels. Paste S490 zeros into column L for the Δz check; the Swap_Pricer values any OIS off this curve.

Sheet Curve_Interface
A1: Curve_Interface
A2: Shared discounting D(0,t): interpolates the SOFR Bootstrap curve to ANY date (piecewise-flat forward). One function used by both Swap_Pricer and the CDS module.
A4: Piecewise-flat instantaneous-forward interpolation — the SOFR curve's own baseline method. For t in (T_prev, T_next]: f = −ln(D_next/D_prev)/(T_next−T_prev), then D(0,t) = D_prev·exp(−f·(t−T_prev)). The demo rows are the STANDARD quarterly CDS dates (20 Mar/Jun/Sep/Dec) out to 10Y — proving the curve returns a discount factor on every CDS payment date even though those dates don't coincide with the SOFR pillars. A CDS schedule just references this same formula, so any change to fixings/futures/OIS/interpolation flows straight through. Curve grid (spot + Bootstrap pillars) is in cols K:L.
K6: Curve grid (from Bootstrap)
A7: Valuation: | B7: =VAL_DATE | C7: Spot: | D7: =Bootstrap!$B$4 | E7: 1st CDS date: | F7: =IF(DATE(YEAR(VAL_DATE),CEILING(MONTH(VAL_DATE)/3,1)*3,20)>=VAL_DATE,DATE(YEAR(VAL_DATE),CEILING(MONTH(VAL_DATE)/3,1)*3,20),EDATE(DATE(YEAR(VAL_DATE),CEILING(MONTH(VAL_DATE)/3,1)*3,20),3)) | K7: Date | L7: DF
K8: =Bootstrap!$B$4 | L8: 1
A9: Coupon # | B9: Date | C9: Time from val (yrs) | D9: Prev SOFR pillar | E9: Next SOFR pillar | F9: Segment fwd (%) | G9: Interp DF D(0,t) | H9: Interp zero (%) | K9: =Bootstrap!B8 | L9: =Bootstrap!H8
A10: 1 | B10: =EDATE($F$7,3*0) | C10: =(B10-VAL_DATE)/365 | D10: =INDEX($K$8:$K$40,MATCH(B10,$K$8:$K$40,1)) | E10: =INDEX($K$8:$K$40,MATCH(B10,$K$8:$K$40,1)+1) | F10: =-LN(INDEX($L$8:$L$40,MATCH(B10,$K$8:$K$40,1)+1)/INDEX($L$8:$L$40,MATCH(B10,$K$8:$K$40,1)))/((E10-D10)/365)*100 | G10: =INDEX($L$8:$L$40,MATCH(B10,$K$8:$K$40,1))*EXP(-(F10/100)*(B10-D10)/365) | H10: =-LN(G10)/C10*100 | K10: =Bootstrap!B9 | L10: =Bootstrap!H9
A11: 2 | B11: =EDATE($F$7,3*1) | C11: =(B11-VAL_DATE)/365 | D11: =INDEX($K$8:$K$40,MATCH(B11,$K$8:$K$40,1)) | E11: =INDEX($K$8:$K$40,MATCH(B11,$K$8:$K$40,1)+1) | F11: =-LN(INDEX($L$8:$L$40,MATCH(B11,$K$8:$K$40,1)+1)/INDEX($L$8:$L$40,MATCH(B11,$K$8:$K$40,1)))/((E11-D11)/365)*100 | G11: =INDEX($L$8:$L$40,MATCH(B11,$K$8:$K$40,1))*EXP(-(F11/100)*(B11-D11)/365) | H11: =-LN(G11)/C11*100 | K11: =Bootstrap!B10 | L11: =Bootstrap!H10
A12: 3 | B12: =EDATE($F$7,3*2) | C12: =(B12-VAL_DATE)/365 | D12: =INDEX($K$8:$K$40,MATCH(B12,$K$8:$K$40,1)) | E12: =INDEX($K$8:$K$40,MATCH(B12,$K$8:$K$40,1)+1) | F12: =-LN(INDEX($L$8:$L$40,MATCH(B12,$K$8:$K$40,1)+1)/INDEX($L$8:$L$40,MATCH(B12,$K$8:$K$40,1)))/((E12-D12)/365)*100 | G12: =INDEX($L$8:$L$40,MATCH(B12,$K$8:$K$40,1))*EXP(-(F12/100)*(B12-D12)/365) | H12: =-LN(G12)/C12*100 | K12: =Bootstrap!B11 | L12: =Bootstrap!H11
A13: 4 | B13: =EDATE($F$7,3*3) | C13: =(B13-VAL_DATE)/365 | D13: =INDEX($K$8:$K$40,MATCH(B13,$K$8:$K$40,1)) | E13: =INDEX($K$8:$K$40,MATCH(B13,$K$8:$K$40,1)+1) | F13: =-LN(INDEX($L$8:$L$40,MATCH(B13,$K$8:$K$40,1)+1)/INDEX($L$8:$L$40,MATCH(B13,$K$8:$K$40,1)))/((E13-D13)/365)*100 | G13: =INDEX($L$8:$L$40,MATCH(B13,$K$8:$K$40,1))*EXP(-(F13/100)*(B13-D13)/365) | H13: =-LN(G13)/C13*100 | K13: =Bootstrap!B12 | L13: =Bootstrap!H12
A14: 5 | B14: =EDATE($F$7,3*4) | C14: =(B14-VAL_DATE)/365 | D14: =INDEX($K$8:$K$40,MATCH(B14,$K$8:$K$40,1)) | E14: =INDEX($K$8:$K$40,MATCH(B14,$K$8:$K$40,1)+1) | F14: =-LN(INDEX($L$8:$L$40,MATCH(B14,$K$8:$K$40,1)+1)/INDEX($L$8:$L$40,MATCH(B14,$K$8:$K$40,1)))/((E14-D14)/365)*100 | G14: =INDEX($L$8:$L$40,MATCH(B14,$K$8:$K$40,1))*EXP(-(F14/100)*(B14-D14)/365) | H14: =-LN(G14)/C14*100 | K14: =Bootstrap!B13 | L14: =Bootstrap!H13
A15: 6 | B15: =EDATE($F$7,3*5) | C15: =(B15-VAL_DATE)/365 | D15: =INDEX($K$8:$K$40,MATCH(B15,$K$8:$K$40,1)) | E15: =INDEX($K$8:$K$40,MATCH(B15,$K$8:$K$40,1)+1) | F15: =-LN(INDEX($L$8:$L$40,MATCH(B15,$K$8:$K$40,1)+1)/INDEX($L$8:$L$40,MATCH(B15,$K$8:$K$40,1)))/((E15-D15)/365)*100 | G15: =INDEX($L$8:$L$40,MATCH(B15,$K$8:$K$40,1))*EXP(-(F15/100)*(B15-D15)/365) | H15: =-LN(G15)/C15*100 | K15: =Bootstrap!B14 | L15: =Bootstrap!H14
A16: 7 | B16: =EDATE($F$7,3*6) | C16: =(B16-VAL_DATE)/365 | D16: =INDEX($K$8:$K$40,MATCH(B16,$K$8:$K$40,1)) | E16: =INDEX($K$8:$K$40,MATCH(B16,$K$8:$K$40,1)+1) | F16: =-LN(INDEX($L$8:$L$40,MATCH(B16,$K$8:$K$40,1)+1)/INDEX($L$8:$L$40,MATCH(B16,$K$8:$K$40,1)))/((E16-D16)/365)*100 | G16: =INDEX($L$8:$L$40,MATCH(B16,$K$8:$K$40,1))*EXP(-(F16/100)*(B16-D16)/365) | H16: =-LN(G16)/C16*100 | K16: =Bootstrap!B15 | L16: =Bootstrap!H15
A17: 8 | B17: =EDATE($F$7,3*7) | C17: =(B17-VAL_DATE)/365 | D17: =INDEX($K$8:$K$40,MATCH(B17,$K$8:$K$40,1)) | E17: =INDEX($K$8:$K$40,MATCH(B17,$K$8:$K$40,1)+1) | F17: =-LN(INDEX($L$8:$L$40,MATCH(B17,$K$8:$K$40,1)+1)/INDEX($L$8:$L$40,MATCH(B17,$K$8:$K$40,1)))/((E17-D17)/365)*100 | G17: =INDEX($L$8:$L$40,MATCH(B17,$K$8:$K$40,1))*EXP(-(F17/100)*(B17-D17)/365) | H17: =-LN(G17)/C17*100 | K17: =Bootstrap!B16 | L17: =Bootstrap!H16
A18: 9 | B18: =EDATE($F$7,3*8) | C18: =(B18-VAL_DATE)/365 | D18: =INDEX($K$8:$K$40,MATCH(B18,$K$8:$K$40,1)) | E18: =INDEX($K$8:$K$40,MATCH(B18,$K$8:$K$40,1)+1) | F18: =-LN(INDEX($L$8:$L$40,MATCH(B18,$K$8:$K$40,1)+1)/INDEX($L$8:$L$40,MATCH(B18,$K$8:$K$40,1)))/((E18-D18)/365)*100 | G18: =INDEX($L$8:$L$40,MATCH(B18,$K$8:$K$40,1))*EXP(-(F18/100)*(B18-D18)/365) | H18: =-LN(G18)/C18*100 | K18: =Bootstrap!B17 | L18: =Bootstrap!H17
A19: 10 | B19: =EDATE($F$7,3*9) | C19: =(B19-VAL_DATE)/365 | D19: =INDEX($K$8:$K$40,MATCH(B19,$K$8:$K$40,1)) | E19: =INDEX($K$8:$K$40,MATCH(B19,$K$8:$K$40,1)+1) | F19: =-LN(INDEX($L$8:$L$40,MATCH(B19,$K$8:$K$40,1)+1)/INDEX($L$8:$L$40,MATCH(B19,$K$8:$K$40,1)))/((E19-D19)/365)*100 | G19: =INDEX($L$8:$L$40,MATCH(B19,$K$8:$K$40,1))*EXP(-(F19/100)*(B19-D19)/365) | H19: =-LN(G19)/C19*100 | K19: =Bootstrap!B18 | L19: =Bootstrap!H18
A20: 11 | B20: =EDATE($F$7,3*10) | C20: =(B20-VAL_DATE)/365 | D20: =INDEX($K$8:$K$40,MATCH(B20,$K$8:$K$40,1)) | E20: =INDEX($K$8:$K$40,MATCH(B20,$K$8:$K$40,1)+1) | F20: =-LN(INDEX($L$8:$L$40,MATCH(B20,$K$8:$K$40,1)+1)/INDEX($L$8:$L$40,MATCH(B20,$K$8:$K$40,1)))/((E20-D20)/365)*100 | G20: =INDEX($L$8:$L$40,MATCH(B20,$K$8:$K$40,1))*EXP(-(F20/100)*(B20-D20)/365) | H20: =-LN(G20)/C20*100 | K20: =Bootstrap!B19 | L20: =Bootstrap!H19
A21: 12 | B21: =EDATE($F$7,3*11) | C21: =(B21-VAL_DATE)/365 | D21: =INDEX($K$8:$K$40,MATCH(B21,$K$8:$K$40,1)) | E21: =INDEX($K$8:$K$40,MATCH(B21,$K$8:$K$40,1)+1) | F21: =-LN(INDEX($L$8:$L$40,MATCH(B21,$K$8:$K$40,1)+1)/INDEX($L$8:$L$40,MATCH(B21,$K$8:$K$40,1)))/((E21-D21)/365)*100 | G21: =INDEX($L$8:$L$40,MATCH(B21,$K$8:$K$40,1))*EXP(-(F21/100)*(B21-D21)/365) | H21: =-LN(G21)/C21*100 | K21: =Bootstrap!B20 | L21: =Bootstrap!H20
A22: 13 | B22: =EDATE($F$7,3*12) | C22: =(B22-VAL_DATE)/365 | D22: =INDEX($K$8:$K$40,MATCH(B22,$K$8:$K$40,1)) | E22: =INDEX($K$8:$K$40,MATCH(B22,$K$8:$K$40,1)+1) | F22: =-LN(INDEX($L$8:$L$40,MATCH(B22,$K$8:$K$40,1)+1)/INDEX($L$8:$L$40,MATCH(B22,$K$8:$K$40,1)))/((E22-D22)/365)*100 | G22: =INDEX($L$8:$L$40,MATCH(B22,$K$8:$K$40,1))*EXP(-(F22/100)*(B22-D22)/365) | H22: =-LN(G22)/C22*100 | K22: =Bootstrap!B21 | L22: =Bootstrap!H21
A23: 14 | B23: =EDATE($F$7,3*13) | C23: =(B23-VAL_DATE)/365 | D23: =INDEX($K$8:$K$40,MATCH(B23,$K$8:$K$40,1)) | E23: =INDEX($K$8:$K$40,MATCH(B23,$K$8:$K$40,1)+1) | F23: =-LN(INDEX($L$8:$L$40,MATCH(B23,$K$8:$K$40,1)+1)/INDEX($L$8:$L$40,MATCH(B23,$K$8:$K$40,1)))/((E23-D23)/365)*100 | G23: =INDEX($L$8:$L$40,MATCH(B23,$K$8:$K$40,1))*EXP(-(F23/100)*(B23-D23)/365) | H23: =-LN(G23)/C23*100 | K23: =Bootstrap!B22 | L23: =Bootstrap!H22
A24: 15 | B24: =EDATE($F$7,3*14) | C24: =(B24-VAL_DATE)/365 | D24: =INDEX($K$8:$K$40,MATCH(B24,$K$8:$K$40,1)) | E24: =INDEX($K$8:$K$40,MATCH(B24,$K$8:$K$40,1)+1) | F24: =-LN(INDEX($L$8:$L$40,MATCH(B24,$K$8:$K$40,1)+1)/INDEX($L$8:$L$40,MATCH(B24,$K$8:$K$40,1)))/((E24-D24)/365)*100 | G24: =INDEX($L$8:$L$40,MATCH(B24,$K$8:$K$40,1))*EXP(-(F24/100)*(B24-D24)/365) | H24: =-LN(G24)/C24*100 | K24: =Bootstrap!B23 | L24: =Bootstrap!H23
A25: 16 | B25: =EDATE($F$7,3*15) | C25: =(B25-VAL_DATE)/365 | D25: =INDEX($K$8:$K$40,MATCH(B25,$K$8:$K$40,1)) | E25: =INDEX($K$8:$K$40,MATCH(B25,$K$8:$K$40,1)+1) | F25: =-LN(INDEX($L$8:$L$40,MATCH(B25,$K$8:$K$40,1)+1)/INDEX($L$8:$L$40,MATCH(B25,$K$8:$K$40,1)))/((E25-D25)/365)*100 | G25: =INDEX($L$8:$L$40,MATCH(B25,$K$8:$K$40,1))*EXP(-(F25/100)*(B25-D25)/365) | H25: =-LN(G25)/C25*100 | K25: =Bootstrap!B24 | L25: =Bootstrap!H24
A26: 17 | B26: =EDATE($F$7,3*16) | C26: =(B26-VAL_DATE)/365 | D26: =INDEX($K$8:$K$40,MATCH(B26,$K$8:$K$40,1)) | E26: =INDEX($K$8:$K$40,MATCH(B26,$K$8:$K$40,1)+1) | F26: =-LN(INDEX($L$8:$L$40,MATCH(B26,$K$8:$K$40,1)+1)/INDEX($L$8:$L$40,MATCH(B26,$K$8:$K$40,1)))/((E26-D26)/365)*100 | G26: =INDEX($L$8:$L$40,MATCH(B26,$K$8:$K$40,1))*EXP(-(F26/100)*(B26-D26)/365) | H26: =-LN(G26)/C26*100 | K26: =Bootstrap!B25 | L26: =Bootstrap!H25
A27: 18 | B27: =EDATE($F$7,3*17) | C27: =(B27-VAL_DATE)/365 | D27: =INDEX($K$8:$K$40,MATCH(B27,$K$8:$K$40,1)) | E27: =INDEX($K$8:$K$40,MATCH(B27,$K$8:$K$40,1)+1) | F27: =-LN(INDEX($L$8:$L$40,MATCH(B27,$K$8:$K$40,1)+1)/INDEX($L$8:$L$40,MATCH(B27,$K$8:$K$40,1)))/((E27-D27)/365)*100 | G27: =INDEX($L$8:$L$40,MATCH(B27,$K$8:$K$40,1))*EXP(-(F27/100)*(B27-D27)/365) | H27: =-LN(G27)/C27*100 | K27: =Bootstrap!B26 | L27: =Bootstrap!H26
A28: 19 | B28: =EDATE($F$7,3*18) | C28: =(B28-VAL_DATE)/365 | D28: =INDEX($K$8:$K$40,MATCH(B28,$K$8:$K$40,1)) | E28: =INDEX($K$8:$K$40,MATCH(B28,$K$8:$K$40,1)+1) | F28: =-LN(INDEX($L$8:$L$40,MATCH(B28,$K$8:$K$40,1)+1)/INDEX($L$8:$L$40,MATCH(B28,$K$8:$K$40,1)))/((E28-D28)/365)*100 | G28: =INDEX($L$8:$L$40,MATCH(B28,$K$8:$K$40,1))*EXP(-(F28/100)*(B28-D28)/365) | H28: =-LN(G28)/C28*100 | K28: =Bootstrap!B27 | L28: =Bootstrap!H27
A29: 20 | B29: =EDATE($F$7,3*19) | C29: =(B29-VAL_DATE)/365 | D29: =INDEX($K$8:$K$40,MATCH(B29,$K$8:$K$40,1)) | E29: =INDEX($K$8:$K$40,MATCH(B29,$K$8:$K$40,1)+1) | F29: =-LN(INDEX($L$8:$L$40,MATCH(B29,$K$8:$K$40,1)+1)/INDEX($L$8:$L$40,MATCH(B29,$K$8:$K$40,1)))/((E29-D29)/365)*100 | G29: =INDEX($L$8:$L$40,MATCH(B29,$K$8:$K$40,1))*EXP(-(F29/100)*(B29-D29)/365) | H29: =-LN(G29)/C29*100 | K29: =Bootstrap!B28 | L29: =Bootstrap!H28
A30: 21 | B30: =EDATE($F$7,3*20) | C30: =(B30-VAL_DATE)/365 | D30: =INDEX($K$8:$K$40,MATCH(B30,$K$8:$K$40,1)) | E30: =INDEX($K$8:$K$40,MATCH(B30,$K$8:$K$40,1)+1) | F30: =-LN(INDEX($L$8:$L$40,MATCH(B30,$K$8:$K$40,1)+1)/INDEX($L$8:$L$40,MATCH(B30,$K$8:$K$40,1)))/((E30-D30)/365)*100 | G30: =INDEX($L$8:$L$40,MATCH(B30,$K$8:$K$40,1))*EXP(-(F30/100)*(B30-D30)/365) | H30: =-LN(G30)/C30*100 | K30: =Bootstrap!B29 | L30: =Bootstrap!H29
A31: 22 | B31: =EDATE($F$7,3*21) | C31: =(B31-VAL_DATE)/365 | D31: =INDEX($K$8:$K$40,MATCH(B31,$K$8:$K$40,1)) | E31: =INDEX($K$8:$K$40,MATCH(B31,$K$8:$K$40,1)+1) | F31: =-LN(INDEX($L$8:$L$40,MATCH(B31,$K$8:$K$40,1)+1)/INDEX($L$8:$L$40,MATCH(B31,$K$8:$K$40,1)))/((E31-D31)/365)*100 | G31: =INDEX($L$8:$L$40,MATCH(B31,$K$8:$K$40,1))*EXP(-(F31/100)*(B31-D31)/365) | H31: =-LN(G31)/C31*100 | K31: =Bootstrap!B30 | L31: =Bootstrap!H30
A32: 23 | B32: =EDATE($F$7,3*22) | C32: =(B32-VAL_DATE)/365 | D32: =INDEX($K$8:$K$40,MATCH(B32,$K$8:$K$40,1)) | E32: =INDEX($K$8:$K$40,MATCH(B32,$K$8:$K$40,1)+1) | F32: =-LN(INDEX($L$8:$L$40,MATCH(B32,$K$8:$K$40,1)+1)/INDEX($L$8:$L$40,MATCH(B32,$K$8:$K$40,1)))/((E32-D32)/365)*100 | G32: =INDEX($L$8:$L$40,MATCH(B32,$K$8:$K$40,1))*EXP(-(F32/100)*(B32-D32)/365) | H32: =-LN(G32)/C32*100 | K32: =Bootstrap!B31 | L32: =Bootstrap!H31
A33: 24 | B33: =EDATE($F$7,3*23) | C33: =(B33-VAL_DATE)/365 | D33: =INDEX($K$8:$K$40,MATCH(B33,$K$8:$K$40,1)) | E33: =INDEX($K$8:$K$40,MATCH(B33,$K$8:$K$40,1)+1) | F33: =-LN(INDEX($L$8:$L$40,MATCH(B33,$K$8:$K$40,1)+1)/INDEX($L$8:$L$40,MATCH(B33,$K$8:$K$40,1)))/((E33-D33)/365)*100 | G33: =INDEX($L$8:$L$40,MATCH(B33,$K$8:$K$40,1))*EXP(-(F33/100)*(B33-D33)/365) | H33: =-LN(G33)/C33*100 | K33: =Bootstrap!B32 | L33: =Bootstrap!H32
A34: 25 | B34: =EDATE($F$7,3*24) | C34: =(B34-VAL_DATE)/365 | D34: =INDEX($K$8:$K$40,MATCH(B34,$K$8:$K$40,1)) | E34: =INDEX($K$8:$K$40,MATCH(B34,$K$8:$K$40,1)+1) | F34: =-LN(INDEX($L$8:$L$40,MATCH(B34,$K$8:$K$40,1)+1)/INDEX($L$8:$L$40,MATCH(B34,$K$8:$K$40,1)))/((E34-D34)/365)*100 | G34: =INDEX($L$8:$L$40,MATCH(B34,$K$8:$K$40,1))*EXP(-(F34/100)*(B34-D34)/365) | H34: =-LN(G34)/C34*100 | K34: =Bootstrap!B33 | L34: =Bootstrap!H33
A35: 26 | B35: =EDATE($F$7,3*25) | C35: =(B35-VAL_DATE)/365 | D35: =INDEX($K$8:$K$40,MATCH(B35,$K$8:$K$40,1)) | E35: =INDEX($K$8:$K$40,MATCH(B35,$K$8:$K$40,1)+1) | F35: =-LN(INDEX($L$8:$L$40,MATCH(B35,$K$8:$K$40,1)+1)/INDEX($L$8:$L$40,MATCH(B35,$K$8:$K$40,1)))/((E35-D35)/365)*100 | G35: =INDEX($L$8:$L$40,MATCH(B35,$K$8:$K$40,1))*EXP(-(F35/100)*(B35-D35)/365) | H35: =-LN(G35)/C35*100 | K35: =Bootstrap!B34 | L35: =Bootstrap!H34
A36: 27 | B36: =EDATE($F$7,3*26) | C36: =(B36-VAL_DATE)/365 | D36: =INDEX($K$8:$K$40,MATCH(B36,$K$8:$K$40,1)) | E36: =INDEX($K$8:$K$40,MATCH(B36,$K$8:$K$40,1)+1) | F36: =-LN(INDEX($L$8:$L$40,MATCH(B36,$K$8:$K$40,1)+1)/INDEX($L$8:$L$40,MATCH(B36,$K$8:$K$40,1)))/((E36-D36)/365)*100 | G36: =INDEX($L$8:$L$40,MATCH(B36,$K$8:$K$40,1))*EXP(-(F36/100)*(B36-D36)/365) | H36: =-LN(G36)/C36*100 | K36: =Bootstrap!B35 | L36: =Bootstrap!H35
A37: 28 | B37: =EDATE($F$7,3*27) | C37: =(B37-VAL_DATE)/365 | D37: =INDEX($K$8:$K$40,MATCH(B37,$K$8:$K$40,1)) | E37: =INDEX($K$8:$K$40,MATCH(B37,$K$8:$K$40,1)+1) | F37: =-LN(INDEX($L$8:$L$40,MATCH(B37,$K$8:$K$40,1)+1)/INDEX($L$8:$L$40,MATCH(B37,$K$8:$K$40,1)))/((E37-D37)/365)*100 | G37: =INDEX($L$8:$L$40,MATCH(B37,$K$8:$K$40,1))*EXP(-(F37/100)*(B37-D37)/365) | H37: =-LN(G37)/C37*100 | K37: =Bootstrap!B36 | L37: =Bootstrap!H36
A38: 29 | B38: =EDATE($F$7,3*28) | C38: =(B38-VAL_DATE)/365 | D38: =INDEX($K$8:$K$40,MATCH(B38,$K$8:$K$40,1)) | E38: =INDEX($K$8:$K$40,MATCH(B38,$K$8:$K$40,1)+1) | F38: =-LN(INDEX($L$8:$L$40,MATCH(B38,$K$8:$K$40,1)+1)/INDEX($L$8:$L$40,MATCH(B38,$K$8:$K$40,1)))/((E38-D38)/365)*100 | G38: =INDEX($L$8:$L$40,MATCH(B38,$K$8:$K$40,1))*EXP(-(F38/100)*(B38-D38)/365) | H38: =-LN(G38)/C38*100 | K38: =Bootstrap!B37 | L38: =Bootstrap!H37
A39: 30 | B39: =EDATE($F$7,3*29) | C39: =(B39-VAL_DATE)/365 | D39: =INDEX($K$8:$K$40,MATCH(B39,$K$8:$K$40,1)) | E39: =INDEX($K$8:$K$40,MATCH(B39,$K$8:$K$40,1)+1) | F39: =-LN(INDEX($L$8:$L$40,MATCH(B39,$K$8:$K$40,1)+1)/INDEX($L$8:$L$40,MATCH(B39,$K$8:$K$40,1)))/((E39-D39)/365)*100 | G39: =INDEX($L$8:$L$40,MATCH(B39,$K$8:$K$40,1))*EXP(-(F39/100)*(B39-D39)/365) | H39: =-LN(G39)/C39*100 | K39: =Bootstrap!B38 | L39: =Bootstrap!H38
A40: 31 | B40: =EDATE($F$7,3*30) | C40: =(B40-VAL_DATE)/365 | D40: =INDEX($K$8:$K$40,MATCH(B40,$K$8:$K$40,1)) | E40: =INDEX($K$8:$K$40,MATCH(B40,$K$8:$K$40,1)+1) | F40: =-LN(INDEX($L$8:$L$40,MATCH(B40,$K$8:$K$40,1)+1)/INDEX($L$8:$L$40,MATCH(B40,$K$8:$K$40,1)))/((E40-D40)/365)*100 | G40: =INDEX($L$8:$L$40,MATCH(B40,$K$8:$K$40,1))*EXP(-(F40/100)*(B40-D40)/365) | H40: =-LN(G40)/C40*100 | K40: =Bootstrap!B39 | L40: =Bootstrap!H39
A41: 32 | B41: =EDATE($F$7,3*31) | C41: =(B41-VAL_DATE)/365 | D41: =INDEX($K$8:$K$40,MATCH(B41,$K$8:$K$40,1)) | E41: =INDEX($K$8:$K$40,MATCH(B41,$K$8:$K$40,1)+1) | F41: =-LN(INDEX($L$8:$L$40,MATCH(B41,$K$8:$K$40,1)+1)/INDEX($L$8:$L$40,MATCH(B41,$K$8:$K$40,1)))/((E41-D41)/365)*100 | G41: =INDEX($L$8:$L$40,MATCH(B41,$K$8:$K$40,1))*EXP(-(F41/100)*(B41-D41)/365) | H41: =-LN(G41)/C41*100
A42: 33 | B42: =EDATE($F$7,3*32) | C42: =(B42-VAL_DATE)/365 | D42: =INDEX($K$8:$K$40,MATCH(B42,$K$8:$K$40,1)) | E42: =INDEX($K$8:$K$40,MATCH(B42,$K$8:$K$40,1)+1) | F42: =-LN(INDEX($L$8:$L$40,MATCH(B42,$K$8:$K$40,1)+1)/INDEX($L$8:$L$40,MATCH(B42,$K$8:$K$40,1)))/((E42-D42)/365)*100 | G42: =INDEX($L$8:$L$40,MATCH(B42,$K$8:$K$40,1))*EXP(-(F42/100)*(B42-D42)/365) | H42: =-LN(G42)/C42*100
A43: 34 | B43: =EDATE($F$7,3*33) | C43: =(B43-VAL_DATE)/365 | D43: =INDEX($K$8:$K$40,MATCH(B43,$K$8:$K$40,1)) | E43: =INDEX($K$8:$K$40,MATCH(B43,$K$8:$K$40,1)+1) | F43: =-LN(INDEX($L$8:$L$40,MATCH(B43,$K$8:$K$40,1)+1)/INDEX($L$8:$L$40,MATCH(B43,$K$8:$K$40,1)))/((E43-D43)/365)*100 | G43: =INDEX($L$8:$L$40,MATCH(B43,$K$8:$K$40,1))*EXP(-(F43/100)*(B43-D43)/365) | H43: =-LN(G43)/C43*100
A44: 35 | B44: =EDATE($F$7,3*34) | C44: =(B44-VAL_DATE)/365 | D44: =INDEX($K$8:$K$40,MATCH(B44,$K$8:$K$40,1)) | E44: =INDEX($K$8:$K$40,MATCH(B44,$K$8:$K$40,1)+1) | F44: =-LN(INDEX($L$8:$L$40,MATCH(B44,$K$8:$K$40,1)+1)/INDEX($L$8:$L$40,MATCH(B44,$K$8:$K$40,1)))/((E44-D44)/365)*100 | G44: =INDEX($L$8:$L$40,MATCH(B44,$K$8:$K$40,1))*EXP(-(F44/100)*(B44-D44)/365) | H44: =-LN(G44)/C44*100
A45: 36 | B45: =EDATE($F$7,3*35) | C45: =(B45-VAL_DATE)/365 | D45: =INDEX($K$8:$K$40,MATCH(B45,$K$8:$K$40,1)) | E45: =INDEX($K$8:$K$40,MATCH(B45,$K$8:$K$40,1)+1) | F45: =-LN(INDEX($L$8:$L$40,MATCH(B45,$K$8:$K$40,1)+1)/INDEX($L$8:$L$40,MATCH(B45,$K$8:$K$40,1)))/((E45-D45)/365)*100 | G45: =INDEX($L$8:$L$40,MATCH(B45,$K$8:$K$40,1))*EXP(-(F45/100)*(B45-D45)/365) | H45: =-LN(G45)/C45*100
A46: 37 | B46: =EDATE($F$7,3*36) | C46: =(B46-VAL_DATE)/365 | D46: =INDEX($K$8:$K$40,MATCH(B46,$K$8:$K$40,1)) | E46: =INDEX($K$8:$K$40,MATCH(B46,$K$8:$K$40,1)+1) | F46: =-LN(INDEX($L$8:$L$40,MATCH(B46,$K$8:$K$40,1)+1)/INDEX($L$8:$L$40,MATCH(B46,$K$8:$K$40,1)))/((E46-D46)/365)*100 | G46: =INDEX($L$8:$L$40,MATCH(B46,$K$8:$K$40,1))*EXP(-(F46/100)*(B46-D46)/365) | H46: =-LN(G46)/C46*100
A47: 38 | B47: =EDATE($F$7,3*37) | C47: =(B47-VAL_DATE)/365 | D47: =INDEX($K$8:$K$40,MATCH(B47,$K$8:$K$40,1)) | E47: =INDEX($K$8:$K$40,MATCH(B47,$K$8:$K$40,1)+1) | F47: =-LN(INDEX($L$8:$L$40,MATCH(B47,$K$8:$K$40,1)+1)/INDEX($L$8:$L$40,MATCH(B47,$K$8:$K$40,1)))/((E47-D47)/365)*100 | G47: =INDEX($L$8:$L$40,MATCH(B47,$K$8:$K$40,1))*EXP(-(F47/100)*(B47-D47)/365) | H47: =-LN(G47)/C47*100
A48: 39 | B48: =EDATE($F$7,3*38) | C48: =(B48-VAL_DATE)/365 | D48: =INDEX($K$8:$K$40,MATCH(B48,$K$8:$K$40,1)) | E48: =INDEX($K$8:$K$40,MATCH(B48,$K$8:$K$40,1)+1) | F48: =-LN(INDEX($L$8:$L$40,MATCH(B48,$K$8:$K$40,1)+1)/INDEX($L$8:$L$40,MATCH(B48,$K$8:$K$40,1)))/((E48-D48)/365)*100 | G48: =INDEX($L$8:$L$40,MATCH(B48,$K$8:$K$40,1))*EXP(-(F48/100)*(B48-D48)/365) | H48: =-LN(G48)/C48*100
A49: 40 | B49: =EDATE($F$7,3*39) | C49: =(B49-VAL_DATE)/365 | D49: =INDEX($K$8:$K$40,MATCH(B49,$K$8:$K$40,1)) | E49: =INDEX($K$8:$K$40,MATCH(B49,$K$8:$K$40,1)+1) | F49: =-LN(INDEX($L$8:$L$40,MATCH(B49,$K$8:$K$40,1)+1)/INDEX($L$8:$L$40,MATCH(B49,$K$8:$K$40,1)))/((E49-D49)/365)*100 | G49: =INDEX($L$8:$L$40,MATCH(B49,$K$8:$K$40,1))*EXP(-(F49/100)*(B49-D49)/365) | H49: =-LN(G49)/C49*100

Sheet Swap_Pricer
A1: Swap_Pricer
A2: Dynamic Fixed-vs-SOFR OIS valuation (SWPM-style), priced off the Bootstrap curve — every cell is live
A4: DEAL — Fixed vs SOFR OIS (yellow = inputs; everything else is computed) | K4: Discount curve (from Bootstrap)
A5: Direction (Leg 1 = Fixed) | B5: Receive fixed | C5: Type "Receive fixed" or "Pay fixed". Sets the sign of the net NPV. | K5: Curve date | L5: DF
A6: Notional | B6: 10000000 | C6: Both legs, USD. | K6: =Bootstrap!$B$4 | L6: 1
A7: Currency | B7: USD | K7: =Bootstrap!B8 | L7: =Bootstrap!H8
A8: Effective date | B8: =Bootstrap!$B$4 | C8: Defaults to curve spot (T+2). Overtype for a forward-start swap. | K8: =Bootstrap!B9 | L8: =Bootstrap!H9
A9: Tenor (years) | B9: 1 | C9: Whole years; drives the annual coupon schedule below. | K9: =Bootstrap!B10 | L9: =Bootstrap!H10
A10: Maturity date | B10: =EDATE(B8,12*B9) | C10: Effective + Tenor. | K10: =Bootstrap!B11 | L10: =Bootstrap!H11
A11: Fixed coupon (%) | B11: =B25 | C11: Defaults to the Par coupon (row 25) → NPV ≈ 0. Overtype to value an off-market coupon. | K11: =Bootstrap!B12 | L11: =Bootstrap!H12
A12: Fixed pay frequency | B12: Annual | K12: =Bootstrap!B13 | L12: =Bootstrap!H13
A13: Fixed day count | B13: ACT/360 | K13: =Bootstrap!B14 | L13: =Bootstrap!H14
A14: Float index | B14: SOFR (daily compounded, single-curve) | K14: =Bootstrap!B15 | L14: =Bootstrap!H15
A15: Curve / valuation date | B15: =VAL_DATE | C15: Curve is discounted from spot = Bootstrap!B4. | K15: =Bootstrap!B16 | L15: =Bootstrap!H16
A16: Direction sign (+recv / −pay) | B16: =IF($B$5="Receive fixed",1,-1) | K16: =Bootstrap!B17 | L16: =Bootstrap!H17
K17: =Bootstrap!B18 | L17: =Bootstrap!H18
A18: VALUATION RESULTS — single-curve OIS discounting | K18: =Bootstrap!B19 | L18: =Bootstrap!H19
A19: DF(effective) | B19: =IFERROR(INDEX($L$6:$L$38,MATCH($B$8,$K$6:$K$38,1))*(INDEX($L$6:$L$38,MATCH($B$8,$K$6:$K$38,1)+1)/INDEX($L$6:$L$38,MATCH($B$8,$K$6:$K$38,1)))^(($B$8-INDEX($K$6:$K$38,MATCH($B$8,$K$6:$K$38,1)))/(INDEX($K$6:$K$38,MATCH($B$8,$K$6:$K$38,1)+1)-INDEX($K$6:$K$38,MATCH($B$8,$K$6:$K$38,1)))),INDEX($L$6:$L$38,MATCH($B$8,$K$6:$K$38,1))) | C19: Interpolated from the curve. | K19: =Bootstrap!B20 | L19: =Bootstrap!H20
A20: DF(maturity) | B20: =IFERROR(INDEX($L$6:$L$38,MATCH($B$10,$K$6:$K$38,1))*(INDEX($L$6:$L$38,MATCH($B$10,$K$6:$K$38,1)+1)/INDEX($L$6:$L$38,MATCH($B$10,$K$6:$K$38,1)))^(($B$10-INDEX($K$6:$K$38,MATCH($B$10,$K$6:$K$38,1)))/(INDEX($K$6:$K$38,MATCH($B$10,$K$6:$K$38,1)+1)-INDEX($K$6:$K$38,MATCH($B$10,$K$6:$K$38,1)))),INDEX($L$6:$L$38,MATCH($B$10,$K$6:$K$38,1))) | K20: =Bootstrap!B21 | L20: =Bootstrap!H21
A21: Fixed annuity Sum tau·DF | B21: =SUM(H36:H85) | C21: Sum of tau·DF over the fixed coupon dates. | K21: =Bootstrap!B22 | L21: =Bootstrap!H22
A22: Fixed leg PV (coupons) | B22: =SUM(G36:G85) | K22: =Bootstrap!B23 | L22: =Bootstrap!H23
A23: Float leg PV | B23: =B6*(B19-B20) | C23: Single-curve SOFR float leg telescopes to N·(DF_eff − DF_mat). | K23: =Bootstrap!B24 | L23: =Bootstrap!H24
A24: Notional PV @ maturity | B24: =B6*B20 | C24: For the SWPM-style leg display only. | K24: =Bootstrap!B25 | L24: =Bootstrap!H25
A25: Par coupon (%) | B25: =(B19-B20)/B21*100 | C25: Coupon that sets NPV = 0: (DF_eff − DF_mat) / annuity. | K25: =Bootstrap!B26 | L25: =Bootstrap!H26
A26: Leg 1 NPV (fixed + notional) | B26: =B16*(B22+B24) | C26: SWPM shows each leg incl. a notional redemption. | K26: =Bootstrap!B27 | L26: =Bootstrap!H27
A27: Leg 2 NPV (float + notional) | B27: =-B16*(B23+B24) | K27: =Bootstrap!B28 | L27: =Bootstrap!H28
A28: Net swap NPV | B28: =B26+B27 | C28: Fixed − Float (notionals cancel); ≈ 0 at par coupon. | K28: =Bootstrap!B29 | L28: =Bootstrap!H29
A29: PV01 / DV01 (per 1bp) | B29: =B6*B21*0.0001 | C29: Annuity × notional × 1bp. | K29: =Bootstrap!B30 | L29: =Bootstrap!H30
A30: Accrued (at inception) | B30: 0 | K30: =Bootstrap!B31 | L30: =Bootstrap!H31
K31: =Bootstrap!B32 | L31: =Bootstrap!H32
A32: Cross-check vs the SWPM screen: Par coupon and PV01 match (≈4.02%, ≈974 for a 10mm 1Y). SWPM's leg NPVs read ~9,995,534 rather than 10,000,000 because it discounts from curve date to a valuation date 2 business days after effective; here effective = spot so DF(effective) = 1 exactly. The net NPV, par coupon and DV01 are unaffected. | K32: =Bootstrap!B33 | L32: =Bootstrap!H33
K33: =Bootstrap!B34 | L33: =Bootstrap!H34
K34: =Bootstrap!B35 | L34: =Bootstrap!H35
A35: k | B35: Pay date | C35: Prev date | D35: tau ACT/360 | E35: DF (interp) | F35: Coupon CF | G35: PV | H35: tau·DF | K35: =Bootstrap!B36 | L35: =Bootstrap!H36
A36: =ROW()-35 | B36: =IF(A36<=$B$9,EDATE($B$8,12*A36),"") | C36: =IF(A36<=$B$9,$B$8,"") | D36: =IF(A36<=$B$9,(B36-C36)/360,"") | E36: =IF(A36<=$B$9,IFERROR(INDEX($L$6:$L$38,MATCH(B36,$K$6:$K$38,1))*(INDEX($L$6:$L$38,MATCH(B36,$K$6:$K$38,1)+1)/INDEX($L$6:$L$38,MATCH(B36,$K$6:$K$38,1)))^((B36-INDEX($K$6:$K$38,MATCH(B36,$K$6:$K$38,1)))/(INDEX($K$6:$K$38,MATCH(B36,$K$6:$K$38,1)+1)-INDEX($K$6:$K$38,MATCH(B36,$K$6:$K$38,1)))),INDEX($L$6:$L$38,MATCH(B36,$K$6:$K$38,1))),"") | F36: =IF(A36<=$B$9,$B$6*$B$11/100*D36,"") | G36: =IF(A36<=$B$9,F36*E36,"") | H36: =IF(A36<=$B$9,D36*E36,"") | K36: =Bootstrap!B37 | L36: =Bootstrap!H37
A37: =ROW()-35 | B37: =IF(A37<=$B$9,EDATE($B$8,12*A37),"") | C37: =IF(A37<=$B$9,B36,"") | D37: =IF(A37<=$B$9,(B37-C37)/360,"") | E37: =IF(A37<=$B$9,IFERROR(INDEX($L$6:$L$38,MATCH(B37,$K$6:$K$38,1))*(INDEX($L$6:$L$38,MATCH(B37,$K$6:$K$38,1)+1)/INDEX($L$6:$L$38,MATCH(B37,$K$6:$K$38,1)))^((B37-INDEX($K$6:$K$38,MATCH(B37,$K$6:$K$38,1)))/(INDEX($K$6:$K$38,MATCH(B37,$K$6:$K$38,1)+1)-INDEX($K$6:$K$38,MATCH(B37,$K$6:$K$38,1)))),INDEX($L$6:$L$38,MATCH(B37,$K$6:$K$38,1))),"") | F37: =IF(A37<=$B$9,$B$6*$B$11/100*D37,"") | G37: =IF(A37<=$B$9,F37*E37,"") | H37: =IF(A37<=$B$9,D37*E37,"") | K37: =Bootstrap!B38 | L37: =Bootstrap!H38
A38: =ROW()-35 | B38: =IF(A38<=$B$9,EDATE($B$8,12*A38),"") | C38: =IF(A38<=$B$9,B37,"") | D38: =IF(A38<=$B$9,(B38-C38)/360,"") | E38: =IF(A38<=$B$9,IFERROR(INDEX($L$6:$L$38,MATCH(B38,$K$6:$K$38,1))*(INDEX($L$6:$L$38,MATCH(B38,$K$6:$K$38,1)+1)/INDEX($L$6:$L$38,MATCH(B38,$K$6:$K$38,1)))^((B38-INDEX($K$6:$K$38,MATCH(B38,$K$6:$K$38,1)))/(INDEX($K$6:$K$38,MATCH(B38,$K$6:$K$38,1)+1)-INDEX($K$6:$K$38,MATCH(B38,$K$6:$K$38,1)))),INDEX($L$6:$L$38,MATCH(B38,$K$6:$K$38,1))),"") | F38: =IF(A38<=$B$9,$B$6*$B$11/100*D38,"") | G38: =IF(A38<=$B$9,F38*E38,"") | H38: =IF(A38<=$B$9,D38*E38,"") | K38: =Bootstrap!B39 | L38: =Bootstrap!H39
A39: =ROW()-35 | B39: =IF(A39<=$B$9,EDATE($B$8,12*A39),"") | C39: =IF(A39<=$B$9,B38,"") | D39: =IF(A39<=$B$9,(B39-C39)/360,"") | E39: =IF(A39<=$B$9,IFERROR(INDEX($L$6:$L$38,MATCH(B39,$K$6:$K$38,1))*(INDEX($L$6:$L$38,MATCH(B39,$K$6:$K$38,1)+1)/INDEX($L$6:$L$38,MATCH(B39,$K$6:$K$38,1)))^((B39-INDEX($K$6:$K$38,MATCH(B39,$K$6:$K$38,1)))/(INDEX($K$6:$K$38,MATCH(B39,$K$6:$K$38,1)+1)-INDEX($K$6:$K$38,MATCH(B39,$K$6:$K$38,1)))),INDEX($L$6:$L$38,MATCH(B39,$K$6:$K$38,1))),"") | F39: =IF(A39<=$B$9,$B$6*$B$11/100*D39,"") | G39: =IF(A39<=$B$9,F39*E39,"") | H39: =IF(A39<=$B$9,D39*E39,"") | K39: Log-linear DF interpolation on this grid (dates $K$6:$K$38, DFs $L$6:$L$38).
A40: =ROW()-35 | B40: =IF(A40<=$B$9,EDATE($B$8,12*A40),"") | C40: =IF(A40<=$B$9,B39,"") | D40: =IF(A40<=$B$9,(B40-C40)/360,"") | E40: =IF(A40<=$B$9,IFERROR(INDEX($L$6:$L$38,MATCH(B40,$K$6:$K$38,1))*(INDEX($L$6:$L$38,MATCH(B40,$K$6:$K$38,1)+1)/INDEX($L$6:$L$38,MATCH(B40,$K$6:$K$38,1)))^((B40-INDEX($K$6:$K$38,MATCH(B40,$K$6:$K$38,1)))/(INDEX($K$6:$K$38,MATCH(B40,$K$6:$K$38,1)+1)-INDEX($K$6:$K$38,MATCH(B40,$K$6:$K$38,1)))),INDEX($L$6:$L$38,MATCH(B40,$K$6:$K$38,1))),"") | F40: =IF(A40<=$B$9,$B$6*$B$11/100*D40,"") | G40: =IF(A40<=$B$9,F40*E40,"") | H40: =IF(A40<=$B$9,D40*E40,"")
A41: =ROW()-35 | B41: =IF(A41<=$B$9,EDATE($B$8,12*A41),"") | C41: =IF(A41<=$B$9,B40,"") | D41: =IF(A41<=$B$9,(B41-C41)/360,"") | E41: =IF(A41<=$B$9,IFERROR(INDEX($L$6:$L$38,MATCH(B41,$K$6:$K$38,1))*(INDEX($L$6:$L$38,MATCH(B41,$K$6:$K$38,1)+1)/INDEX($L$6:$L$38,MATCH(B41,$K$6:$K$38,1)))^((B41-INDEX($K$6:$K$38,MATCH(B41,$K$6:$K$38,1)))/(INDEX($K$6:$K$38,MATCH(B41,$K$6:$K$38,1)+1)-INDEX($K$6:$K$38,MATCH(B41,$K$6:$K$38,1)))),INDEX($L$6:$L$38,MATCH(B41,$K$6:$K$38,1))),"") | F41: =IF(A41<=$B$9,$B$6*$B$11/100*D41,"") | G41: =IF(A41<=$B$9,F41*E41,"") | H41: =IF(A41<=$B$9,D41*E41,"")
A42: =ROW()-35 | B42: =IF(A42<=$B$9,EDATE($B$8,12*A42),"") | C42: =IF(A42<=$B$9,B41,"") | D42: =IF(A42<=$B$9,(B42-C42)/360,"") | E42: =IF(A42<=$B$9,IFERROR(INDEX($L$6:$L$38,MATCH(B42,$K$6:$K$38,1))*(INDEX($L$6:$L$38,MATCH(B42,$K$6:$K$38,1)+1)/INDEX($L$6:$L$38,MATCH(B42,$K$6:$K$38,1)))^((B42-INDEX($K$6:$K$38,MATCH(B42,$K$6:$K$38,1)))/(INDEX($K$6:$K$38,MATCH(B42,$K$6:$K$38,1)+1)-INDEX($K$6:$K$38,MATCH(B42,$K$6:$K$38,1)))),INDEX($L$6:$L$38,MATCH(B42,$K$6:$K$38,1))),"") | F42: =IF(A42<=$B$9,$B$6*$B$11/100*D42,"") | G42: =IF(A42<=$B$9,F42*E42,"") | H42: =IF(A42<=$B$9,D42*E42,"")
A43: =ROW()-35 | B43: =IF(A43<=$B$9,EDATE($B$8,12*A43),"") | C43: =IF(A43<=$B$9,B42,"") | D43: =IF(A43<=$B$9,(B43-C43)/360,"") | E43: =IF(A43<=$B$9,IFERROR(INDEX($L$6:$L$38,MATCH(B43,$K$6:$K$38,1))*(INDEX($L$6:$L$38,MATCH(B43,$K$6:$K$38,1)+1)/INDEX($L$6:$L$38,MATCH(B43,$K$6:$K$38,1)))^((B43-INDEX($K$6:$K$38,MATCH(B43,$K$6:$K$38,1)))/(INDEX($K$6:$K$38,MATCH(B43,$K$6:$K$38,1)+1)-INDEX($K$6:$K$38,MATCH(B43,$K$6:$K$38,1)))),INDEX($L$6:$L$38,MATCH(B43,$K$6:$K$38,1))),"") | F43: =IF(A43<=$B$9,$B$6*$B$11/100*D43,"") | G43: =IF(A43<=$B$9,F43*E43,"") | H43: =IF(A43<=$B$9,D43*E43,"")
A44: =ROW()-35 | B44: =IF(A44<=$B$9,EDATE($B$8,12*A44),"") | C44: =IF(A44<=$B$9,B43,"") | D44: =IF(A44<=$B$9,(B44-C44)/360,"") | E44: =IF(A44<=$B$9,IFERROR(INDEX($L$6:$L$38,MATCH(B44,$K$6:$K$38,1))*(INDEX($L$6:$L$38,MATCH(B44,$K$6:$K$38,1)+1)/INDEX($L$6:$L$38,MATCH(B44,$K$6:$K$38,1)))^((B44-INDEX($K$6:$K$38,MATCH(B44,$K$6:$K$38,1)))/(INDEX($K$6:$K$38,MATCH(B44,$K$6:$K$38,1)+1)-INDEX($K$6:$K$38,MATCH(B44,$K$6:$K$38,1)))),INDEX($L$6:$L$38,MATCH(B44,$K$6:$K$38,1))),"") | F44: =IF(A44<=$B$9,$B$6*$B$11/100*D44,"") | G44: =IF(A44<=$B$9,F44*E44,"") | H44: =IF(A44<=$B$9,D44*E44,"")
A45: =ROW()-35 | B45: =IF(A45<=$B$9,EDATE($B$8,12*A45),"") | C45: =IF(A45<=$B$9,B44,"") | D45: =IF(A45<=$B$9,(B45-C45)/360,"") | E45: =IF(A45<=$B$9,IFERROR(INDEX($L$6:$L$38,MATCH(B45,$K$6:$K$38,1))*(INDEX($L$6:$L$38,MATCH(B45,$K$6:$K$38,1)+1)/INDEX($L$6:$L$38,MATCH(B45,$K$6:$K$38,1)))^((B45-INDEX($K$6:$K$38,MATCH(B45,$K$6:$K$38,1)))/(INDEX($K$6:$K$38,MATCH(B45,$K$6:$K$38,1)+1)-INDEX($K$6:$K$38,MATCH(B45,$K$6:$K$38,1)))),INDEX($L$6:$L$38,MATCH(B45,$K$6:$K$38,1))),"") | F45: =IF(A45<=$B$9,$B$6*$B$11/100*D45,"") | G45: =IF(A45<=$B$9,F45*E45,"") | H45: =IF(A45<=$B$9,D45*E45,"")
A46: =ROW()-35 | B46: =IF(A46<=$B$9,EDATE($B$8,12*A46),"") | C46: =IF(A46<=$B$9,B45,"") | D46: =IF(A46<=$B$9,(B46-C46)/360,"") | E46: =IF(A46<=$B$9,IFERROR(INDEX($L$6:$L$38,MATCH(B46,$K$6:$K$38,1))*(INDEX($L$6:$L$38,MATCH(B46,$K$6:$K$38,1)+1)/INDEX($L$6:$L$38,MATCH(B46,$K$6:$K$38,1)))^((B46-INDEX($K$6:$K$38,MATCH(B46,$K$6:$K$38,1)))/(INDEX($K$6:$K$38,MATCH(B46,$K$6:$K$38,1)+1)-INDEX($K$6:$K$38,MATCH(B46,$K$6:$K$38,1)))),INDEX($L$6:$L$38,MATCH(B46,$K$6:$K$38,1))),"") | F46: =IF(A46<=$B$9,$B$6*$B$11/100*D46,"") | G46: =IF(A46<=$B$9,F46*E46,"") | H46: =IF(A46<=$B$9,D46*E46,"")
A47: =ROW()-35 | B47: =IF(A47<=$B$9,EDATE($B$8,12*A47),"") | C47: =IF(A47<=$B$9,B46,"") | D47: =IF(A47<=$B$9,(B47-C47)/360,"") | E47: =IF(A47<=$B$9,IFERROR(INDEX($L$6:$L$38,MATCH(B47,$K$6:$K$38,1))*(INDEX($L$6:$L$38,MATCH(B47,$K$6:$K$38,1)+1)/INDEX($L$6:$L$38,MATCH(B47,$K$6:$K$38,1)))^((B47-INDEX($K$6:$K$38,MATCH(B47,$K$6:$K$38,1)))/(INDEX($K$6:$K$38,MATCH(B47,$K$6:$K$38,1)+1)-INDEX($K$6:$K$38,MATCH(B47,$K$6:$K$38,1)))),INDEX($L$6:$L$38,MATCH(B47,$K$6:$K$38,1))),"") | F47: =IF(A47<=$B$9,$B$6*$B$11/100*D47,"") | G47: =IF(A47<=$B$9,F47*E47,"") | H47: =IF(A47<=$B$9,D47*E47,"")
A48: =ROW()-35 | B48: =IF(A48<=$B$9,EDATE($B$8,12*A48),"") | C48: =IF(A48<=$B$9,B47,"") | D48: =IF(A48<=$B$9,(B48-C48)/360,"") | E48: =IF(A48<=$B$9,IFERROR(INDEX($L$6:$L$38,MATCH(B48,$K$6:$K$38,1))*(INDEX($L$6:$L$38,MATCH(B48,$K$6:$K$38,1)+1)/INDEX($L$6:$L$38,MATCH(B48,$K$6:$K$38,1)))^((B48-INDEX($K$6:$K$38,MATCH(B48,$K$6:$K$38,1)))/(INDEX($K$6:$K$38,MATCH(B48,$K$6:$K$38,1)+1)-INDEX($K$6:$K$38,MATCH(B48,$K$6:$K$38,1)))),INDEX($L$6:$L$38,MATCH(B48,$K$6:$K$38,1))),"") | F48: =IF(A48<=$B$9,$B$6*$B$11/100*D48,"") | G48: =IF(A48<=$B$9,F48*E48,"") | H48: =IF(A48<=$B$9,D48*E48,"")
A49: =ROW()-35 | B49: =IF(A49<=$B$9,EDATE($B$8,12*A49),"") | C49: =IF(A49<=$B$9,B48,"") | D49: =IF(A49<=$B$9,(B49-C49)/360,"") | E49: =IF(A49<=$B$9,IFERROR(INDEX($L$6:$L$38,MATCH(B49,$K$6:$K$38,1))*(INDEX($L$6:$L$38,MATCH(B49,$K$6:$K$38,1)+1)/INDEX($L$6:$L$38,MATCH(B49,$K$6:$K$38,1)))^((B49-INDEX($K$6:$K$38,MATCH(B49,$K$6:$K$38,1)))/(INDEX($K$6:$K$38,MATCH(B49,$K$6:$K$38,1)+1)-INDEX($K$6:$K$38,MATCH(B49,$K$6:$K$38,1)))),INDEX($L$6:$L$38,MATCH(B49,$K$6:$K$38,1))),"") | F49: =IF(A49<=$B$9,$B$6*$B$11/100*D49,"") | G49: =IF(A49<=$B$9,F49*E49,"") | H49: =IF(A49<=$B$9,D49*E49,"")
A50: =ROW()-35 | B50: =IF(A50<=$B$9,EDATE($B$8,12*A50),"") | C50: =IF(A50<=$B$9,B49,"") | D50: =IF(A50<=$B$9,(B50-C50)/360,"") | E50: =IF(A50<=$B$9,IFERROR(INDEX($L$6:$L$38,MATCH(B50,$K$6:$K$38,1))*(INDEX($L$6:$L$38,MATCH(B50,$K$6:$K$38,1)+1)/INDEX($L$6:$L$38,MATCH(B50,$K$6:$K$38,1)))^((B50-INDEX($K$6:$K$38,MATCH(B50,$K$6:$K$38,1)))/(INDEX($K$6:$K$38,MATCH(B50,$K$6:$K$38,1)+1)-INDEX($K$6:$K$38,MATCH(B50,$K$6:$K$38,1)))),INDEX($L$6:$L$38,MATCH(B50,$K$6:$K$38,1))),"") | F50: =IF(A50<=$B$9,$B$6*$B$11/100*D50,"") | G50: =IF(A50<=$B$9,F50*E50,"") | H50: =IF(A50<=$B$9,D50*E50,"")
A51: =ROW()-35 | B51: =IF(A51<=$B$9,EDATE($B$8,12*A51),"") | C51: =IF(A51<=$B$9,B50,"") | D51: =IF(A51<=$B$9,(B51-C51)/360,"") | E51: =IF(A51<=$B$9,IFERROR(INDEX($L$6:$L$38,MATCH(B51,$K$6:$K$38,1))*(INDEX($L$6:$L$38,MATCH(B51,$K$6:$K$38,1)+1)/INDEX($L$6:$L$38,MATCH(B51,$K$6:$K$38,1)))^((B51-INDEX($K$6:$K$38,MATCH(B51,$K$6:$K$38,1)))/(INDEX($K$6:$K$38,MATCH(B51,$K$6:$K$38,1)+1)-INDEX($K$6:$K$38,MATCH(B51,$K$6:$K$38,1)))),INDEX($L$6:$L$38,MATCH(B51,$K$6:$K$38,1))),"") | F51: =IF(A51<=$B$9,$B$6*$B$11/100*D51,"") | G51: =IF(A51<=$B$9,F51*E51,"") | H51: =IF(A51<=$B$9,D51*E51,"")
... A85: =ROW()-35 | B85: =IF(A85<=$B$9,EDATE($B$8,12*A85),"") | C85: =IF(A85<=$B$9,B84,"") | D85: =IF(A85<=$B$9,(B85-C85)/360,"") | E85: =IF(A85<=$B$9,IFERROR(INDEX($L$6:$L$38,MATCH(B85,$K$6:$K$38,1))*(INDEX($L$6:$L$38,MATCH(B85,$K$6:$K$38,1)+1)/INDEX($L$6:$L$38,MATCH(B85,$K$6:$K$38,1)))^((B85-INDEX($K$6:$K$38,MATCH(B85,$K$6:$K$38,1)))/(INDEX($K$6:$K$38,MATCH(B85,$K$6:$K$38,1)+1)-INDEX($K$6:$K$38,MATCH(B85,$K$6:$K$38,1)))),INDEX($L$6:$L$38,MATCH(B85,$K$6:$K$38,1))),"") | F85: =IF(A85<=$B$9,$B$6*$B$11/100*D85,"") | G85: =IF(A85<=$B$9,F85*E85,"") | H85: =IF(A85<=$B$9,D85*E85,"")

Sheet Bloomberg_S490_Validation
A1: Bloomberg_S490_Validation
A2: Bloomberg's own USD SOFR curve (S490 / YCSW0490 Index) — benchmark for your bootstrap, not an input
A4: Curve name: | B4: =IFERROR(BDP(S490_TKR,"NAME"),"ERROR PLZ FIX")
A5: Curve date: | B5: =VAL_DATE
A6: Paste Bloomberg's S490 zero rates (from YCSW0490 <GO> or SWDF) into the yellow column D, tenor for tenor; column E then shows Δz = your bootstrap − Bloomberg in bp (single digits = agreement). The raw BDS(CURVE_TENOR_RATES) dump is off to the right (cols H:I) as an optional live pull — its column order is Bloomberg-defined, so verify before relying on it.
A7: Tenor | B7: Maturity | C7: Your zero (%) | D7: S490 zero (%) [paste] | E7: Δz (bp) | H7: Raw CURVE_TENOR_RATES (verify order)
A8: =Bootstrap!A8 | B8: =Bootstrap!B8 | C8: =Bootstrap!J8 | E8: =IF(D8="","",(C8-D8)*100) | H8: =BDS(S490_TKR,"CURVE_TENOR_RATES")
A9: =Bootstrap!A9 | B9: =Bootstrap!B9 | C9: =Bootstrap!J9 | E9: =IF(D9="","",(C9-D9)*100)
A10: =Bootstrap!A10 | B10: =Bootstrap!B10 | C10: =Bootstrap!J10 | E10: =IF(D10="","",(C10-D10)*100)
A11: =Bootstrap!A11 | B11: =Bootstrap!B11 | C11: =Bootstrap!J11 | E11: =IF(D11="","",(C11-D11)*100)
A12: =Bootstrap!A12 | B12: =Bootstrap!B12 | C12: =Bootstrap!J12 | E12: =IF(D12="","",(C12-D12)*100)
A13: =Bootstrap!A13 | B13: =Bootstrap!B13 | C13: =Bootstrap!J13 | E13: =IF(D13="","",(C13-D13)*100)
A14: =Bootstrap!A14 | B14: =Bootstrap!B14 | C14: =Bootstrap!J14 | E14: =IF(D14="","",(C14-D14)*100)
A15: =Bootstrap!A15 | B15: =Bootstrap!B15 | C15: =Bootstrap!J15 | E15: =IF(D15="","",(C15-D15)*100)
A16: =Bootstrap!A16 | B16: =Bootstrap!B16 | C16: =Bootstrap!J16 | E16: =IF(D16="","",(C16-D16)*100)
A17: =Bootstrap!A17 | B17: =Bootstrap!B17 | C17: =Bootstrap!J17 | E17: =IF(D17="","",(C17-D17)*100)
A18: =Bootstrap!A18 | B18: =Bootstrap!B18 | C18: =Bootstrap!J18 | E18: =IF(D18="","",(C18-D18)*100)
A19: =Bootstrap!A19 | B19: =Bootstrap!B19 | C19: =Bootstrap!J19 | E19: =IF(D19="","",(C19-D19)*100)
A20: =Bootstrap!A20 | B20: =Bootstrap!B20 | C20: =Bootstrap!J20 | E20: =IF(D20="","",(C20-D20)*100)
... A39: =Bootstrap!A39 | B39: =Bootstrap!B39 | C39: =Bootstrap!J39 | E39: =IF(D39="","",(C39-D39)*100)

Sheet Conventions
A1: Conventions
A2: OIS quote conventions (DES/FLDS) for representative tenors — record before you bootstrap
A4: Convention attribute | B4: BDP field (verify via FLDS) | C4: USOSFRC (3M) | D4: USOSFR1 (1Y) | E4: USOSFR5 (5Y) | F4: USOSFR30 (30Y)
A5: Currency | B5: CRNCY | C5: =IFERROR(BDP("USOSFRC BGN Curncy","CRNCY"),"ERROR PLZ FIX") | D5: =IFERROR(BDP("USOSFR1 BGN Curncy","CRNCY"),"ERROR PLZ FIX") | E5: =IFERROR(BDP("USOSFR5 BGN Curncy","CRNCY"),"ERROR PLZ FIX") | F5: =IFERROR(BDP("USOSFR30 BGN Curncy","CRNCY"),"ERROR PLZ FIX")
A6: Reference index | B6: — DES/SWPM manual — | C6: — DES/SWPM — | D6: — DES/SWPM — | E6: — DES/SWPM — | F6: — DES/SWPM —
A7: Spot / settlement lag | B7: — DES/SWPM manual — | C7: — DES/SWPM — | D7: — DES/SWPM — | E7: — DES/SWPM — | F7: — DES/SWPM —
A8: Effective date rule | B8: — DES/SWPM manual — | C8: — DES/SWPM — | D8: — DES/SWPM — | E8: — DES/SWPM — | F8: — DES/SWPM —
A9: Maturity date rule | B9: — DES/SWPM manual — | C9: — DES/SWPM — | D9: — DES/SWPM — | E9: — DES/SWPM — | F9: — DES/SWPM —
A10: Business-day calendar | B10: CALENDAR_CODE | C10: =IFERROR(BDP("USOSFRC BGN Curncy","CALENDAR_CODE"),"ERROR PLZ FIX") | D10: =IFERROR(BDP("USOSFR1 BGN Curncy","CALENDAR_CODE"),"ERROR PLZ FIX") | E10: =IFERROR(BDP("USOSFR5 BGN Curncy","CALENDAR_CODE"),"ERROR PLZ FIX") | F10: =IFERROR(BDP("USOSFR30 BGN Curncy","CALENDAR_CODE"),"ERROR PLZ FIX")
A11: Business-day convention | B11: — DES/SWPM manual — | C11: — DES/SWPM — | D11: — DES/SWPM — | E11: — DES/SWPM — | F11: — DES/SWPM —
A12: Fixed-leg day count | B12: DAY_CNT_DES | C12: =IFERROR(BDP("USOSFRC BGN Curncy","DAY_CNT_DES"),"ERROR PLZ FIX") | D12: =IFERROR(BDP("USOSFR1 BGN Curncy","DAY_CNT_DES"),"ERROR PLZ FIX") | E12: =IFERROR(BDP("USOSFR5 BGN Curncy","DAY_CNT_DES"),"ERROR PLZ FIX") | F12: =IFERROR(BDP("USOSFR30 BGN Curncy","DAY_CNT_DES"),"ERROR PLZ FIX")
A13: Fixed-leg pay frequency | B13: — DES/SWPM manual — | C13: — DES/SWPM — | D13: — DES/SWPM — | E13: — DES/SWPM — | F13: — DES/SWPM —
A14: Floating-leg day count | B14: — DES/SWPM manual — | C14: — DES/SWPM — | D14: — DES/SWPM — | E14: — DES/SWPM — | F14: — DES/SWPM —
A15: Floating-leg pay frequency | B15: — DES/SWPM manual — | C15: — DES/SWPM — | D15: — DES/SWPM — | E15: — DES/SWPM — | F15: — DES/SWPM —
A16: SOFR compounding method | B16: — DES/SWPM manual — | C16: — DES/SWPM — | D16: — DES/SWPM — | E16: — DES/SWPM — | F16: — DES/SWPM —
A17: Payment lag | B17: — DES/SWPM manual — | C17: — DES/SWPM — | D17: — DES/SWPM — | E17: — DES/SWPM — | F17: — DES/SWPM —
A18: Observation shift / lookback | B18: — DES/SWPM manual — | C18: — DES/SWPM — | D18: — DES/SWPM — | E18: — DES/SWPM — | F18: — DES/SWPM —
A19: End-of-month treatment | B19: — DES/SWPM manual — | C19: — DES/SWPM — | D19: — DES/SWPM — | E19: — DES/SWPM — | F19: — DES/SWPM —
A21: USD SOFR OIS — MARKET-STANDARD CONVENTIONS (confirm per-trade in DES)
A22: Reference index | B22: USD-SOFR (compounded in arrears)
A23: Spot / settlement lag | B23: T+2 US business days
A24: Effective date rule | B24: Spot (T+2), modified following
A25: Maturity date rule | B25: Effective + tenor, modified following
A26: Business-day convention | B26: Modified Following
A27: Fixed-leg day count | B27: ACT/360
A28: Fixed-leg pay frequency | B28: Annual (single payment if tenor ≤ 1Y)
A29: Floating-leg day count | B29: ACT/360
A30: Floating-leg pay frequency | B30: Annual (single payment if tenor ≤ 1Y)
A31: SOFR compounding method | B31: Daily compounded, ACT/360
A32: Payment lag | B32: 2 US business days
A33: Observation shift / lookback | B33: None (payment-delay convention, 2 bd)
A34: End-of-month treatment | B34: EOM applies
A36: SWPM <GO>: build a representative SOFR OIS for 1Y, 5Y and 30Y and export the cashflow schedule — that gives an authoritative set of pay/accrual dates to test your own date generation against. Rows marked '— DES/SWPM —' are leg-level conventions that a rate-quote ticker does not carry; read them from DES <GO> on an actual swap (the market-standard defaults above are the expected values). Where a BDP cell shows 'N/A — use FLDS', open FLDS <GO> to find the enabled field.

Sheet Fwd_Interp
A1: Fwd_Interp
A2: Zhou 2002 forward interpolation — V1 piecewise-flat vs V2 piecewise-quadratic instantaneous forwards
A4: Both variants reprice the pillar DFs IDENTICALLY (same segment integral ∫f = −ln(DF_i/DF_(i-1))). V1 (Flat fwd) holds the instantaneous forward CONSTANT over each segment → a step curve; simplest & most stable — Lehman's default. V2 makes the forward piecewise-QUADRATIC f(x)=a+bx+cx², CONTINUOUS across pillars (adjacent segments share the Node fwd) while still repricing exactly. a,b,c are closed-form from (f_left=node at left pillar, f_right=node at right pillar, ∫f) — no solver needed. Node fwd = average of the two adjacent flat forwards. 'reprice check' = ∫quad − ∫f ≈ 0 confirms V2 preserves every DF. The difference is intra-segment: compare Flat fwd (V1) vs V2 fwd @ mid — largest across the wide long-end gaps (10Y→15Y→20Y→30Y), which is exactly what V2 smooths.
A7: Pillar | B7: T (yrs) | C7: DF | D7: Δ (yrs) | E7: ∫f (integral) | F7: Flat fwd (V1) | G7: Node fwd | H7: a | I7: b | J7: c | K7: V2 fwd @ mid | L7: reprice check
A8: Spot | B8: 0 | C8: 1 | G8: =F9
A9: ='Bootstrap'!A8 | B9: ='Bootstrap'!C8 | C9: ='Bootstrap'!H8 | D9: =B9-B8 | E9: =-LN(C9/C8) | F9: =E9/D9 | G9: =(F9+F10)/2 | H9: =G8 | I9: =(G9-G8)/D9-J9*D9 | J9: =3*(G9-G8)/D9^2-6*(E9-G8*D9)/D9^3 | K9: =H9+I9*D9/2+J9*D9^2/4 | L9: =H9*D9+I9*D9^2/2+J9*D9^3/3-E9
A10: ='Bootstrap'!A9 | B10: ='Bootstrap'!C9 | C10: ='Bootstrap'!H9 | D10: =B10-B9 | E10: =-LN(C10/C9) | F10: =E10/D10 | G10: =(F10+F11)/2 | H10: =G9 | I10: =(G10-G9)/D10-J10*D10 | J10: =3*(G10-G9)/D10^2-6*(E10-G9*D10)/D10^3 | K10: =H10+I10*D10/2+J10*D10^2/4 | L10: =H10*D10+I10*D10^2/2+J10*D10^3/3-E10
A11: ='Bootstrap'!A10 | B11: ='Bootstrap'!C10 | C11: ='Bootstrap'!H10 | D11: =B11-B10 | E11: =-LN(C11/C10) | F11: =E11/D11 | G11: =(F11+F12)/2 | H11: =G10 | I11: =(G11-G10)/D11-J11*D11 | J11: =3*(G11-G10)/D11^2-6*(E11-G10*D11)/D11^3 | K11: =H11+I11*D11/2+J11*D11^2/4 | L11: =H11*D11+I11*D11^2/2+J11*D11^3/3-E11
A12: ='Bootstrap'!A11 | B12: ='Bootstrap'!C11 | C12: ='Bootstrap'!H11 | D12: =B12-B11 | E12: =-LN(C12/C11) | F12: =E12/D12 | G12: =(F12+F13)/2 | H12: =G11 | I12: =(G12-G11)/D12-J12*D12 | J12: =3*(G12-G11)/D12^2-6*(E12-G11*D12)/D12^3 | K12: =H12+I12*D12/2+J12*D12^2/4 | L12: =H12*D12+I12*D12^2/2+J12*D12^3/3-E12
A13: ='Bootstrap'!A12 | B13: ='Bootstrap'!C12 | C13: ='Bootstrap'!H12 | D13: =B13-B12 | E13: =-LN(C13/C12) | F13: =E13/D13 | G13: =(F13+F14)/2 | H13: =G12 | I13: =(G13-G12)/D13-J13*D13 | J13: =3*(G13-G12)/D13^2-6*(E13-G12*D13)/D13^3 | K13: =H13+I13*D13/2+J13*D13^2/4 | L13: =H13*D13+I13*D13^2/2+J13*D13^3/3-E13
A14: ='Bootstrap'!A13 | B14: ='Bootstrap'!C13 | C14: ='Bootstrap'!H13 | D14: =B14-B13 | E14: =-LN(C14/C13) | F14: =E14/D14 | G14: =(F14+F15)/2 | H14: =G13 | I14: =(G14-G13)/D14-J14*D14 | J14: =3*(G14-G13)/D14^2-6*(E14-G13*D14)/D14^3 | K14: =H14+I14*D14/2+J14*D14^2/4 | L14: =H14*D14+I14*D14^2/2+J14*D14^3/3-E14
A15: ='Bootstrap'!A14 | B15: ='Bootstrap'!C14 | C15: ='Bootstrap'!H14 | D15: =B15-B14 | E15: =-LN(C15/C14) | F15: =E15/D15 | G15: =(F15+F16)/2 | H15: =G14 | I15: =(G15-G14)/D15-J15*D15 | J15: =3*(G15-G14)/D15^2-6*(E15-G14*D15)/D15^3 | K15: =H15+I15*D15/2+J15*D15^2/4 | L15: =H15*D15+I15*D15^2/2+J15*D15^3/3-E15
A16: ='Bootstrap'!A15 | B16: ='Bootstrap'!C15 | C16: ='Bootstrap'!H15 | D16: =B16-B15 | E16: =-LN(C16/C15) | F16: =E16/D16 | G16: =(F16+F17)/2 | H16: =G15 | I16: =(G16-G15)/D16-J16*D16 | J16: =3*(G16-G15)/D16^2-6*(E16-G15*D16)/D16^3 | K16: =H16+I16*D16/2+J16*D16^2/4 | L16: =H16*D16+I16*D16^2/2+J16*D16^3/3-E16
A17: ='Bootstrap'!A16 | B17: ='Bootstrap'!C16 | C17: ='Bootstrap'!H16 | D17: =B17-B16 | E17: =-LN(C17/C16) | F17: =E17/D17 | G17: =(F17+F18)/2 | H17: =G16 | I17: =(G17-G16)/D17-J17*D17 | J17: =3*(G17-G16)/D17^2-6*(E17-G16*D17)/D17^3 | K17: =H17+I17*D17/2+J17*D17^2/4 | L17: =H17*D17+I17*D17^2/2+J17*D17^3/3-E17
A18: ='Bootstrap'!A17 | B18: ='Bootstrap'!C17 | C18: ='Bootstrap'!H17 | D18: =B18-B17 | E18: =-LN(C18/C17) | F18: =E18/D18 | G18: =(F18+F19)/2 | H18: =G17 | I18: =(G18-G17)/D18-J18*D18 | J18: =3*(G18-G17)/D18^2-6*(E18-G17*D18)/D18^3 | K18: =H18+I18*D18/2+J18*D18^2/4 | L18: =H18*D18+I18*D18^2/2+J18*D18^3/3-E18
A19: ='Bootstrap'!A18 | B19: ='Bootstrap'!C18 | C19: ='Bootstrap'!H18 | D19: =B19-B18 | E19: =-LN(C19/C18) | F19: =E19/D19 | G19: =(F19+F20)/2 | H19: =G18 | I19: =(G19-G18)/D19-J19*D19 | J19: =3*(G19-G18)/D19^2-6*(E19-G18*D19)/D19^3 | K19: =H19+I19*D19/2+J19*D19^2/4 | L19: =H19*D19+I19*D19^2/2+J19*D19^3/3-E19
A20: ='Bootstrap'!A19 | B20: ='Bootstrap'!C19 | C20: ='Bootstrap'!H19 | D20: =B20-B19 | E20: =-LN(C20/C19) | F20: =E20/D20 | G20: =(F20+F21)/2 | H20: =G19 | I20: =(G20-G19)/D20-J20*D20 | J20: =3*(G20-G19)/D20^2-6*(E20-G19*D20)/D20^3 | K20: =H20+I20*D20/2+J20*D20^2/4 | L20: =H20*D20+I20*D20^2/2+J20*D20^3/3-E20
... A39: ='Bootstrap'!A38 | B39: ='Bootstrap'!C38 | C39: ='Bootstrap'!H38 | D39: =B39-B38 | E39: =-LN(C39/C38) | F39: =E39/D39 | G39: =(F39+F40)/2 | H39: =G38 | I39: =(G39-G38)/D39-J39*D39 | J39: =3*(G39-G38)/D39^2-6*(E39-G38*D39)/D39^3 | K39: =H39+I39*D39/2+J39*D39^2/4 | L39: =H39*D39+I39*D39^2/2+J39*D39^3/3-E39
A40: ='Bootstrap'!A39 | B40: ='Bootstrap'!C39 | C40: ='Bootstrap'!H39 | D40: =B40-B39 | E40: =-LN(C40/C39) | F40: =E40/D40 | G40: =F40 | H40: =G39 | I40: =(G40-G39)/D40-J40*D40 | J40: =3*(G40-G39)/D40^2-6*(E40-G39*D40)/D40^3 | K40: =H40+I40*D40/2+J40*D40^2/4 | L40: =H40*D40+I40*D40^2/2+J40*D40^3/3-E40

Sheet CDS_Parameters
A1: CDS_Parameters
A2: Credit-default-swap assumptions (recovery is an INPUT, not bootstrapped)
A4: Valuation date | B4: =VAL_DATE | C4: Linked to the Parameters/Instructions tab.
A5: 1st CDS date (roll) | B5: ='Curve_Interface'!$F$7 | C5: Next 20 Mar/Jun/Sep/Dec.
A6: Currency | B6: USD
A7: Reference entity | B7: EXAMPLE CORP | C7: Type your reference entity.
A8: Recovery rate R | B8: 0.4 | C8: Assumed. Changing R re-fits every hazard.
A9: Notional | B9: 10000000
A10: Standard coupon (bp) | B10: 100 | C10: Fixed running coupon (IG=100, HY=500).
A11: Premium frequency | B11: Quarterly
A12: Premium day count | B12: ACT/360
A13: Hazard interpolation | B13: Piecewise-constant
A14: Discount curve | B14: SOFR OIS (Curve_Interface)
A15: Protection direction | B15: Buy protection | C15: "Buy protection" or "Sell protection".
A16: Accrual-on-default | B16: Included (midpoint approx.)

Sheet CDS_Quotes
A1: CDS_Quotes
A2: Single-name CDS par spreads — one entity, one seniority/clause. Live BDP overrides the manual demo values.
A4: Enter each tenor's Bloomberg CDS ticker in col D (e.g. the entity's par-spread series); Market spread = BDP(ticker,"PX_LAST") when it resolves, else the yellow Manual spread so the module still runs. Do NOT mix seniorities, currencies, or restructuring clauses.
A6: Tenor | B6: Tenor (yrs) | C6: Maturity | D6: CDS ticker | E6: Manual spread (bp) | F6: Market spread (bp) | G6: Approx hazard s/(1-R)
A7: 1Y | B7: 1 | C7: =EDATE('Curve_Interface'!$F$7,3*(4-1)) | E7: 40 | F7: =IF(D7="",E7,IFERROR(BDP(D7,"PX_LAST"),E7)) | G7: =(F7/10000)/(1-CDS_Parameters!$B$8)
A8: 2Y | B8: 2 | C8: =EDATE('Curve_Interface'!$F$7,3*(8-1)) | E8: 55 | F8: =IF(D8="",E8,IFERROR(BDP(D8,"PX_LAST"),E8)) | G8: =(F8/10000)/(1-CDS_Parameters!$B$8)
A9: 3Y | B9: 3 | C9: =EDATE('Curve_Interface'!$F$7,3*(12-1)) | E9: 70 | F9: =IF(D9="",E9,IFERROR(BDP(D9,"PX_LAST"),E9)) | G9: =(F9/10000)/(1-CDS_Parameters!$B$8)
A10: 5Y | B10: 5 | C10: =EDATE('Curve_Interface'!$F$7,3*(20-1)) | E10: 95 | F10: =IF(D10="",E10,IFERROR(BDP(D10,"PX_LAST"),E10)) | G10: =(F10/10000)/(1-CDS_Parameters!$B$8)
A11: 7Y | B11: 7 | C11: =EDATE('Curve_Interface'!$F$7,3*(28-1)) | E11: 115 | F11: =IF(D11="",E11,IFERROR(BDP(D11,"PX_LAST"),E11)) | G11: =(F11/10000)/(1-CDS_Parameters!$B$8)
A12: 10Y | B12: 10 | C12: =EDATE('Curve_Interface'!$F$7,3*(40-1)) | E12: 135 | F12: =IF(D12="",E12,IFERROR(BDP(D12,"PX_LAST"),E12)) | G12: =(F12/10000)/(1-CDS_Parameters!$B$8)

Sheet Hazard_Bootstrap
A1: Hazard_Bootstrap
A2: Piecewise-constant hazard curve. Col D pre-filled with s/(1-R); Goal Seek col J (error)=0 by changing col D for EXACT fit.
A4: Bootstrap maturity by maturity: hold earlier hazards fixed, solve the current segment so model spread = market. Col D defaults to the s/(1-R) approximation (module runs immediately). For an exact fit (|error|<0.01bp), Goal Seek EACH row: Data > What-If > Goal Seek, Set cell = col J, To value 0, By changing = col D — top row first, then down. Survival/PVs come from the CDS_Schedule tab, which discounts on the shared SOFR Curve_Interface.
A6: Tenor | B6: Maturity | C6: Market spread (bp) | D6: Hazard lambda (solve) | E6: Cum. survival Q(T) | F6: Cum. default 1-Q | G6: RPV01 (risky annuity) | H6: Protection PV factor | I6: Model spread (bp) | J6: Repricing error (bp)
A7: 1Y | B7: =CDS_Quotes!C7 | C7: =CDS_Quotes!F7 | D7: =(C7/10000)/(1-CDS_Parameters!$B$8) | E7: =INDEX(CDS_Schedule!$K$7:$K$46,MATCH(B7,CDS_Schedule!$C$7:$C$46,1)) | F7: =1-E7 | G7: =SUMIF(CDS_Schedule!$C$7:$C$46,"<="&B7,CDS_Schedule!$M$7:$M$46)+SUMIF(CDS_Schedule!$C$7:$C$46,"<="&B7,CDS_Schedule!$N$7:$N$46) | H7: =SUMIF(CDS_Schedule!$C$7:$C$46,"<="&B7,CDS_Schedule!$O$7:$O$46) | I7: =(1-CDS_Parameters!$B$8)*H7/G7*10000 | J7: =I7-C7
A8: 2Y | B8: =CDS_Quotes!C8 | C8: =CDS_Quotes!F8 | D8: =((C8/10000)*(B8-VAL_DATE)/365-(C7/10000)*(B7-VAL_DATE)/365)/((1-CDS_Parameters!$B$8)*((B8-VAL_DATE)/365-(B7-VAL_DATE)/365)) | E8: =INDEX(CDS_Schedule!$K$7:$K$46,MATCH(B8,CDS_Schedule!$C$7:$C$46,1)) | F8: =1-E8 | G8: =SUMIF(CDS_Schedule!$C$7:$C$46,"<="&B8,CDS_Schedule!$M$7:$M$46)+SUMIF(CDS_Schedule!$C$7:$C$46,"<="&B8,CDS_Schedule!$N$7:$N$46) | H8: =SUMIF(CDS_Schedule!$C$7:$C$46,"<="&B8,CDS_Schedule!$O$7:$O$46) | I8: =(1-CDS_Parameters!$B$8)*H8/G8*10000 | J8: =I8-C8
A9: 3Y | B9: =CDS_Quotes!C9 | C9: =CDS_Quotes!F9 | D9: =((C9/10000)*(B9-VAL_DATE)/365-(C8/10000)*(B8-VAL_DATE)/365)/((1-CDS_Parameters!$B$8)*((B9-VAL_DATE)/365-(B8-VAL_DATE)/365)) | E9: =INDEX(CDS_Schedule!$K$7:$K$46,MATCH(B9,CDS_Schedule!$C$7:$C$46,1)) | F9: =1-E9 | G9: =SUMIF(CDS_Schedule!$C$7:$C$46,"<="&B9,CDS_Schedule!$M$7:$M$46)+SUMIF(CDS_Schedule!$C$7:$C$46,"<="&B9,CDS_Schedule!$N$7:$N$46) | H9: =SUMIF(CDS_Schedule!$C$7:$C$46,"<="&B9,CDS_Schedule!$O$7:$O$46) | I9: =(1-CDS_Parameters!$B$8)*H9/G9*10000 | J9: =I9-C9
A10: 5Y | B10: =CDS_Quotes!C10 | C10: =CDS_Quotes!F10 | D10: =((C10/10000)*(B10-VAL_DATE)/365-(C9/10000)*(B9-VAL_DATE)/365)/((1-CDS_Parameters!$B$8)*((B10-VAL_DATE)/365-(B9-VAL_DATE)/365)) | E10: =INDEX(CDS_Schedule!$K$7:$K$46,MATCH(B10,CDS_Schedule!$C$7:$C$46,1)) | F10: =1-E10 | G10: =SUMIF(CDS_Schedule!$C$7:$C$46,"<="&B10,CDS_Schedule!$M$7:$M$46)+SUMIF(CDS_Schedule!$C$7:$C$46,"<="&B10,CDS_Schedule!$N$7:$N$46) | H10: =SUMIF(CDS_Schedule!$C$7:$C$46,"<="&B10,CDS_Schedule!$O$7:$O$46) | I10: =(1-CDS_Parameters!$B$8)*H10/G10*10000 | J10: =I10-C10
A11: 7Y | B11: =CDS_Quotes!C11 | C11: =CDS_Quotes!F11 | D11: =((C11/10000)*(B11-VAL_DATE)/365-(C10/10000)*(B10-VAL_DATE)/365)/((1-CDS_Parameters!$B$8)*((B11-VAL_DATE)/365-(B10-VAL_DATE)/365)) | E11: =INDEX(CDS_Schedule!$K$7:$K$46,MATCH(B11,CDS_Schedule!$C$7:$C$46,1)) | F11: =1-E11 | G11: =SUMIF(CDS_Schedule!$C$7:$C$46,"<="&B11,CDS_Schedule!$M$7:$M$46)+SUMIF(CDS_Schedule!$C$7:$C$46,"<="&B11,CDS_Schedule!$N$7:$N$46) | H11: =SUMIF(CDS_Schedule!$C$7:$C$46,"<="&B11,CDS_Schedule!$O$7:$O$46) | I11: =(1-CDS_Parameters!$B$8)*H11/G11*10000 | J11: =I11-C11
A12: 10Y | B12: =CDS_Quotes!C12 | C12: =CDS_Quotes!F12 | D12: =((C12/10000)*(B12-VAL_DATE)/365-(C11/10000)*(B11-VAL_DATE)/365)/((1-CDS_Parameters!$B$8)*((B12-VAL_DATE)/365-(B11-VAL_DATE)/365)) | E12: =INDEX(CDS_Schedule!$K$7:$K$46,MATCH(B12,CDS_Schedule!$C$7:$C$46,1)) | F12: =1-E12 | G12: =SUMIF(CDS_Schedule!$C$7:$C$46,"<="&B12,CDS_Schedule!$M$7:$M$46)+SUMIF(CDS_Schedule!$C$7:$C$46,"<="&B12,CDS_Schedule!$N$7:$N$46) | H12: =SUMIF(CDS_Schedule!$C$7:$C$46,"<="&B12,CDS_Schedule!$O$7:$O$46) | I12: =(1-CDS_Parameters!$B$8)*H12/G12*10000 | J12: =I12-C12

Sheet CDS_Schedule
A1: CDS_Schedule
A2: Quarterly premium & default schedule to 10Y. DF from the shared SOFR curve; survival from the hazard curve.
A4: Each row is one quarterly coupon period. DF(end)/DF(mid) interpolate the SOFR Curve_Interface; hazard is the piecewise-constant Hazard_Bootstrap lambda for the segment (by pay date); Q(end)=Q(prev)*exp(-hazard*dt). Premium factor = alpha*DF*Q ; Accrual factor = (alpha/2)*DF(mid)*deltaPD ; Protection factor = DF(mid)*deltaPD. Front period is a stub from valuation to the first roll.
A6: Period | B6: Accrual start | C6: Pay date | D6: alpha ACT/360 | E6: dt ACT/365 | F6: T (yrs) | G6: DF(end) | H6: DF(mid) | I6: hazard | J6: Q(prev) | K6: Q(end) | L6: delta PD | M6: Premium factor | N6: Accrual factor | O6: Protection factor
A7: 1 | B7: =VAL_DATE | C7: =EDATE('Curve_Interface'!$F$7,3*0) | D7: =(C7-B7)/360 | E7: =(C7-B7)/365 | F7: =(C7-VAL_DATE)/365 | G7: =IFERROR(INDEX('Curve_Interface'!$L$8:$L$40,MATCH(C7,'Curve_Interface'!$K$8:$K$40,1))*(INDEX('Curve_Interface'!$L$8:$L$40,MATCH(C7,'Curve_Interface'!$K$8:$K$40,1)+1)/INDEX('Curve_Interface'!$L$8:$L$40,MATCH(C7,'Curve_Interface'!$K$8:$K$40,1)))^((C7-INDEX('Curve_Interface'!$K$8:$K$40,MATCH(C7,'Curve_Interface'!$K$8:$K$40,1)))/(INDEX('Curve_Interface'!$K$8:$K$40,MATCH(C7,'Curve_Interface'!$K$8:$K$40,1)+1)-INDEX('Curve_Interface'!$K$8:$K$40,MATCH(C7,'Curve_Interface'!$K$8:$K$40,1)))),INDEX('Curve_Interface'!$L$8:$L$40,MATCH(C7,'Curve_Interface'!$K$8:$K$40,1))) | H7: =IFERROR(INDEX('Curve_Interface'!$L$8:$L$40,MATCH((B7+C7)/2,'Curve_Interface'!$K$8:$K$40,1))*(INDEX('Curve_Interface'!$L$8:$L$40,MATCH((B7+C7)/2,'Curve_Interface'!$K$8:$K$40,1)+1)/INDEX('Curve_Interface'!$L$8:$L$40,MATCH((B7+C7)/2,'Curve_Interface'!$K$8:$K$40,1)))^(((B7+C7)/2-INDEX('Curve_Interface'!$K$8:$K$40,MATCH((B7+C7)/2,'Curve_Interface'!$K$8:$K$40,1)))/(INDEX('Curve_Interface'!$K$8:$K$40,MATCH((B7+C7)/2,'Curve_Interface'!$K$8:$K$40,1)+1)-INDEX('Curve_Interface'!$K$8:$K$40,MATCH((B7+C7)/2,'Curve_Interface'!$K$8:$K$40,1)))),INDEX('Curve_Interface'!$L$8:$L$40,MATCH((B7+C7)/2,'Curve_Interface'!$K$8:$K$40,1))) | I7: =INDEX(Hazard_Bootstrap!$D$7:$D$12,MIN(COUNTIF(Hazard_Bootstrap!$B$7:$B$12,"<"&C7)+1,6)) | J7: =1 | K7: =J7*EXP(-I7*E7) | L7: =J7-K7 | M7: =D7*G7*K7 | N7: =(D7/2)*H7*L7 | O7: =H7*L7
A8: 2 | B8: =C7 | C8: =EDATE('Curve_Interface'!$F$7,3*1) | D8: =(C8-B8)/360 | E8: =(C8-B8)/365 | F8: =(C8-VAL_DATE)/365 | G8: =IFERROR(INDEX('Curve_Interface'!$L$8:$L$40,MATCH(C8,'Curve_Interface'!$K$8:$K$40,1))*(INDEX('Curve_Interface'!$L$8:$L$40,MATCH(C8,'Curve_Interface'!$K$8:$K$40,1)+1)/INDEX('Curve_Interface'!$L$8:$L$40,MATCH(C8,'Curve_Interface'!$K$8:$K$40,1)))^((C8-INDEX('Curve_Interface'!$K$8:$K$40,MATCH(C8,'Curve_Interface'!$K$8:$K$40,1)))/(INDEX('Curve_Interface'!$K$8:$K$40,MATCH(C8,'Curve_Interface'!$K$8:$K$40,1)+1)-INDEX('Curve_Interface'!$K$8:$K$40,MATCH(C8,'Curve_Interface'!$K$8:$K$40,1)))),INDEX('Curve_Interface'!$L$8:$L$40,MATCH(C8,'Curve_Interface'!$K$8:$K$40,1))) | H8: =IFERROR(INDEX('Curve_Interface'!$L$8:$L$40,MATCH((B8+C8)/2,'Curve_Interface'!$K$8:$K$40,1))*(INDEX('Curve_Interface'!$L$8:$L$40,MATCH((B8+C8)/2,'Curve_Interface'!$K$8:$K$40,1)+1)/INDEX('Curve_Interface'!$L$8:$L$40,MATCH((B8+C8)/2,'Curve_Interface'!$K$8:$K$40,1)))^(((B8+C8)/2-INDEX('Curve_Interface'!$K$8:$K$40,MATCH((B8+C8)/2,'Curve_Interface'!$K$8:$K$40,1)))/(INDEX('Curve_Interface'!$K$8:$K$40,MATCH((B8+C8)/2,'Curve_Interface'!$K$8:$K$40,1)+1)-INDEX('Curve_Interface'!$K$8:$K$40,MATCH((B8+C8)/2,'Curve_Interface'!$K$8:$K$40,1)))),INDEX('Curve_Interface'!$L$8:$L$40,MATCH((B8+C8)/2,'Curve_Interface'!$K$8:$K$40,1))) | I8: =INDEX(Hazard_Bootstrap!$D$7:$D$12,MIN(COUNTIF(Hazard_Bootstrap!$B$7:$B$12,"<"&C8)+1,6)) | J8: =K7 | K8: =J8*EXP(-I8*E8) | L8: =J8-K8 | M8: =D8*G8*K8 | N8: =(D8/2)*H8*L8 | O8: =H8*L8
A9: 3 | B9: =C8 | C9: =EDATE('Curve_Interface'!$F$7,3*2) | D9: =(C9-B9)/360 | E9: =(C9-B9)/365 | F9: =(C9-VAL_DATE)/365 | G9: =IFERROR(INDEX('Curve_Interface'!$L$8:$L$40,MATCH(C9,'Curve_Interface'!$K$8:$K$40,1))*(INDEX('Curve_Interface'!$L$8:$L$40,MATCH(C9,'Curve_Interface'!$K$8:$K$40,1)+1)/INDEX('Curve_Interface'!$L$8:$L$40,MATCH(C9,'Curve_Interface'!$K$8:$K$40,1)))^((C9-INDEX('Curve_Interface'!$K$8:$K$40,MATCH(C9,'Curve_Interface'!$K$8:$K$40,1)))/(INDEX('Curve_Interface'!$K$8:$K$40,MATCH(C9,'Curve_Interface'!$K$8:$K$40,1)+1)-INDEX('Curve_Interface'!$K$8:$K$40,MATCH(C9,'Curve_Interface'!$K$8:$K$40,1)))),INDEX('Curve_Interface'!$L$8:$L$40,MATCH(C9,'Curve_Interface'!$K$8:$K$40,1))) | H9: =IFERROR(INDEX('Curve_Interface'!$L$8:$L$40,MATCH((B9+C9)/2,'Curve_Interface'!$K$8:$K$40,1))*(INDEX('Curve_Interface'!$L$8:$L$40,MATCH((B9+C9)/2,'Curve_Interface'!$K$8:$K$40,1)+1)/INDEX('Curve_Interface'!$L$8:$L$40,MATCH((B9+C9)/2,'Curve_Interface'!$K$8:$K$40,1)))^(((B9+C9)/2-INDEX('Curve_Interface'!$K$8:$K$40,MATCH((B9+C9)/2,'Curve_Interface'!$K$8:$K$40,1)))/(INDEX('Curve_Interface'!$K$8:$K$40,MATCH((B9+C9)/2,'Curve_Interface'!$K$8:$K$40,1)+1)-INDEX('Curve_Interface'!$K$8:$K$40,MATCH((B9+C9)/2,'Curve_Interface'!$K$8:$K$40,1)))),INDEX('Curve_Interface'!$L$8:$L$40,MATCH((B9+C9)/2,'Curve_Interface'!$K$8:$K$40,1))) | I9: =INDEX(Hazard_Bootstrap!$D$7:$D$12,MIN(COUNTIF(Hazard_Bootstrap!$B$7:$B$12,"<"&C9)+1,6)) | J9: =K8 | K9: =J9*EXP(-I9*E9) | L9: =J9-K9 | M9: =D9*G9*K9 | N9: =(D9/2)*H9*L9 | O9: =H9*L9
A10: 4 | B10: =C9 | C10: =EDATE('Curve_Interface'!$F$7,3*3) | D10: =(C10-B10)/360 | E10: =(C10-B10)/365 | F10: =(C10-VAL_DATE)/365 | G10: =IFERROR(INDEX('Curve_Interface'!$L$8:$L$40,MATCH(C10,'Curve_Interface'!$K$8:$K$40,1))*(INDEX('Curve_Interface'!$L$8:$L$40,MATCH(C10,'Curve_Interface'!$K$8:$K$40,1)+1)/INDEX('Curve_Interface'!$L$8:$L$40,MATCH(C10,'Curve_Interface'!$K$8:$K$40,1)))^((C10-INDEX('Curve_Interface'!$K$8:$K$40,MATCH(C10,'Curve_Interface'!$K$8:$K$40,1)))/(INDEX('Curve_Interface'!$K$8:$K$40,MATCH(C10,'Curve_Interface'!$K$8:$K$40,1)+1)-INDEX('Curve_Interface'!$K$8:$K$40,MATCH(C10,'Curve_Interface'!$K$8:$K$40,1)))),INDEX('Curve_Interface'!$L$8:$L$40,MATCH(C10,'Curve_Interface'!$K$8:$K$40,1))) | H10: =IFERROR(INDEX('Curve_Interface'!$L$8:$L$40,MATCH((B10+C10)/2,'Curve_Interface'!$K$8:$K$40,1))*(INDEX('Curve_Interface'!$L$8:$L$40,MATCH((B10+C10)/2,'Curve_Interface'!$K$8:$K$40,1)+1)/INDEX('Curve_Interface'!$L$8:$L$40,MATCH((B10+C10)/2,'Curve_Interface'!$K$8:$K$40,1)))^(((B10+C10)/2-INDEX('Curve_Interface'!$K$8:$K$40,MATCH((B10+C10)/2,'Curve_Interface'!$K$8:$K$40,1)))/(INDEX('Curve_Interface'!$K$8:$K$40,MATCH((B10+C10)/2,'Curve_Interface'!$K$8:$K$40,1)+1)-INDEX('Curve_Interface'!$K$8:$K$40,MATCH((B10+C10)/2,'Curve_Interface'!$K$8:$K$40,1)))),INDEX('Curve_Interface'!$L$8:$L$40,MATCH((B10+C10)/2,'Curve_Interface'!$K$8:$K$40,1))) | I10: =INDEX(Hazard_Bootstrap!$D$7:$D$12,MIN(COUNTIF(Hazard_Bootstrap!$B$7:$B$12,"<"&C10)+1,6)) | J10: =K9 | K10: =J10*EXP(-I10*E10) | L10: =J10-K10 | M10: =D10*G10*K10 | N10: =(D10/2)*H10*L10 | O10: =H10*L10
A11: 5 | B11: =C10 | C11: =EDATE('Curve_Interface'!$F$7,3*4) | D11: =(C11-B11)/360 | E11: =(C11-B11)/365 | F11: =(C11-VAL_DATE)/365 | G11: =IFERROR(INDEX('Curve_Interface'!$L$8:$L$40,MATCH(C11,'Curve_Interface'!$K$8:$K$40,1))*(INDEX('Curve_Interface'!$L$8:$L$40,MATCH(C11,'Curve_Interface'!$K$8:$K$40,1)+1)/INDEX('Curve_Interface'!$L$8:$L$40,MATCH(C11,'Curve_Interface'!$K$8:$K$40,1)))^((C11-INDEX('Curve_Interface'!$K$8:$K$40,MATCH(C11,'Curve_Interface'!$K$8:$K$40,1)))/(INDEX('Curve_Interface'!$K$8:$K$40,MATCH(C11,'Curve_Interface'!$K$8:$K$40,1)+1)-INDEX('Curve_Interface'!$K$8:$K$40,MATCH(C11,'Curve_Interface'!$K$8:$K$40,1)))),INDEX('Curve_Interface'!$L$8:$L$40,MATCH(C11,'Curve_Interface'!$K$8:$K$40,1))) | H11: =IFERROR(INDEX('Curve_Interface'!$L$8:$L$40,MATCH((B11+C11)/2,'Curve_Interface'!$K$8:$K$40,1))*(INDEX('Curve_Interface'!$L$8:$L$40,MATCH((B11+C11)/2,'Curve_Interface'!$K$8:$K$40,1)+1)/INDEX('Curve_Interface'!$L$8:$L$40,MATCH((B11+C11)/2,'Curve_Interface'!$K$8:$K$40,1)))^(((B11+C11)/2-INDEX('Curve_Interface'!$K$8:$K$40,MATCH((B11+C11)/2,'Curve_Interface'!$K$8:$K$40,1)))/(INDEX('Curve_Interface'!$K$8:$K$40,MATCH((B11+C11)/2,'Curve_Interface'!$K$8:$K$40,1)+1)-INDEX('Curve_Interface'!$K$8:$K$40,MATCH((B11+C11)/2,'Curve_Interface'!$K$8:$K$40,1)))),INDEX('Curve_Interface'!$L$8:$L$40,MATCH((B11+C11)/2,'Curve_Interface'!$K$8:$K$40,1))) | I11: =INDEX(Hazard_Bootstrap!$D$7:$D$12,MIN(COUNTIF(Hazard_Bootstrap!$B$7:$B$12,"<"&C11)+1,6)) | J11: =K10 | K11: =J11*EXP(-I11*E11) | L11: =J11-K11 | M11: =D11*G11*K11 | N11: =(D11/2)*H11*L11 | O11: =H11*L11
A12: 6 | B12: =C11 | C12: =EDATE('Curve_Interface'!$F$7,3*5) | D12: =(C12-B12)/360 | E12: =(C12-B12)/365 | F12: =(C12-VAL_DATE)/365 | G12: =IFERROR(INDEX('Curve_Interface'!$L$8:$L$40,MATCH(C12,'Curve_Interface'!$K$8:$K$40,1))*(INDEX('Curve_Interface'!$L$8:$L$40,MATCH(C12,'Curve_Interface'!$K$8:$K$40,1)+1)/INDEX('Curve_Interface'!$L$8:$L$40,MATCH(C12,'Curve_Interface'!$K$8:$K$40,1)))^((C12-INDEX('Curve_Interface'!$K$8:$K$40,MATCH(C12,'Curve_Interface'!$K$8:$K$40,1)))/(INDEX('Curve_Interface'!$K$8:$K$40,MATCH(C12,'Curve_Interface'!$K$8:$K$40,1)+1)-INDEX('Curve_Interface'!$K$8:$K$40,MATCH(C12,'Curve_Interface'!$K$8:$K$40,1)))),INDEX('Curve_Interface'!$L$8:$L$40,MATCH(C12,'Curve_Interface'!$K$8:$K$40,1))) | H12: =IFERROR(INDEX('Curve_Interface'!$L$8:$L$40,MATCH((B12+C12)/2,'Curve_Interface'!$K$8:$K$40,1))*(INDEX('Curve_Interface'!$L$8:$L$40,MATCH((B12+C12)/2,'Curve_Interface'!$K$8:$K$40,1)+1)/INDEX('Curve_Interface'!$L$8:$L$40,MATCH((B12+C12)/2,'Curve_Interface'!$K$8:$K$40,1)))^(((B12+C12)/2-INDEX('Curve_Interface'!$K$8:$K$40,MATCH((B12+C12)/2,'Curve_Interface'!$K$8:$K$40,1)))/(INDEX('Curve_Interface'!$K$8:$K$40,MATCH((B12+C12)/2,'Curve_Interface'!$K$8:$K$40,1)+1)-INDEX('Curve_Interface'!$K$8:$K$40,MATCH((B12+C12)/2,'Curve_Interface'!$K$8:$K$40,1)))),INDEX('Curve_Interface'!$L$8:$L$40,MATCH((B12+C12)/2,'Curve_Interface'!$K$8:$K$40,1))) | I12: =INDEX(Hazard_Bootstrap!$D$7:$D$12,MIN(COUNTIF(Hazard_Bootstrap!$B$7:$B$12,"<"&C12)+1,6)) | J12: =K11 | K12: =J12*EXP(-I12*E12) | L12: =J12-K12 | M12: =D12*G12*K12 | N12: =(D12/2)*H12*L12 | O12: =H12*L12
A13: 7 | B13: =C12 | C13: =EDATE('Curve_Interface'!$F$7,3*6) | D13: =(C13-B13)/360 | E13: =(C13-B13)/365 | F13: =(C13-VAL_DATE)/365 | G13: =IFERROR(INDEX('Curve_Interface'!$L$8:$L$40,MATCH(C13,'Curve_Interface'!$K$8:$K$40,1))*(INDEX('Curve_Interface'!$L$8:$L$40,MATCH(C13,'Curve_Interface'!$K$8:$K$40,1)+1)/INDEX('Curve_Interface'!$L$8:$L$40,MATCH(C13,'Curve_Interface'!$K$8:$K$40,1)))^((C13-INDEX('Curve_Interface'!$K$8:$K$40,MATCH(C13,'Curve_Interface'!$K$8:$K$40,1)))/(INDEX('Curve_Interface'!$K$8:$K$40,MATCH(C13,'Curve_Interface'!$K$8:$K$40,1)+1)-INDEX('Curve_Interface'!$K$8:$K$40,MATCH(C13,'Curve_Interface'!$K$8:$K$40,1)))),INDEX('Curve_Interface'!$L$8:$L$40,MATCH(C13,'Curve_Interface'!$K$8:$K$40,1))) | H13: =IFERROR(INDEX('Curve_Interface'!$L$8:$L$40,MATCH((B13+C13)/2,'Curve_Interface'!$K$8:$K$40,1))*(INDEX('Curve_Interface'!$L$8:$L$40,MATCH((B13+C13)/2,'Curve_Interface'!$K$8:$K$40,1)+1)/INDEX('Curve_Interface'!$L$8:$L$40,MATCH((B13+C13)/2,'Curve_Interface'!$K$8:$K$40,1)))^(((B13+C13)/2-INDEX('Curve_Interface'!$K$8:$K$40,MATCH((B13+C13)/2,'Curve_Interface'!$K$8:$K$40,1)))/(INDEX('Curve_Interface'!$K$8:$K$40,MATCH((B13+C13)/2,'Curve_Interface'!$K$8:$K$40,1)+1)-INDEX('Curve_Interface'!$K$8:$K$40,MATCH((B13+C13)/2,'Curve_Interface'!$K$8:$K$40,1)))),INDEX('Curve_Interface'!$L$8:$L$40,MATCH((B13+C13)/2,'Curve_Interface'!$K$8:$K$40,1))) | I13: =INDEX(Hazard_Bootstrap!$D$7:$D$12,MIN(COUNTIF(Hazard_Bootstrap!$B$7:$B$12,"<"&C13)+1,6)) | J13: =K12 | K13: =J13*EXP(-I13*E13) | L13: =J13-K13 | M13: =D13*G13*K13 | N13: =(D13/2)*H13*L13 | O13: =H13*L13
A14: 8 | B14: =C13 | C14: =EDATE('Curve_Interface'!$F$7,3*7) | D14: =(C14-B14)/360 | E14: =(C14-B14)/365 | F14: =(C14-VAL_DATE)/365 | G14: =IFERROR(INDEX('Curve_Interface'!$L$8:$L$40,MATCH(C14,'Curve_Interface'!$K$8:$K$40,1))*(INDEX('Curve_Interface'!$L$8:$L$40,MATCH(C14,'Curve_Interface'!$K$8:$K$40,1)+1)/INDEX('Curve_Interface'!$L$8:$L$40,MATCH(C14,'Curve_Interface'!$K$8:$K$40,1)))^((C14-INDEX('Curve_Interface'!$K$8:$K$40,MATCH(C14,'Curve_Interface'!$K$8:$K$40,1)))/(INDEX('Curve_Interface'!$K$8:$K$40,MATCH(C14,'Curve_Interface'!$K$8:$K$40,1)+1)-INDEX('Curve_Interface'!$K$8:$K$40,MATCH(C14,'Curve_Interface'!$K$8:$K$40,1)))),INDEX('Curve_Interface'!$L$8:$L$40,MATCH(C14,'Curve_Interface'!$K$8:$K$40,1))) | H14: =IFERROR(INDEX('Curve_Interface'!$L$8:$L$40,MATCH((B14+C14)/2,'Curve_Interface'!$K$8:$K$40,1))*(INDEX('Curve_Interface'!$L$8:$L$40,MATCH((B14+C14)/2,'Curve_Interface'!$K$8:$K$40,1)+1)/INDEX('Curve_Interface'!$L$8:$L$40,MATCH((B14+C14)/2,'Curve_Interface'!$K$8:$K$40,1)))^(((B14+C14)/2-INDEX('Curve_Interface'!$K$8:$K$40,MATCH((B14+C14)/2,'Curve_Interface'!$K$8:$K$40,1)))/(INDEX('Curve_Interface'!$K$8:$K$40,MATCH((B14+C14)/2,'Curve_Interface'!$K$8:$K$40,1)+1)-INDEX('Curve_Interface'!$K$8:$K$40,MATCH((B14+C14)/2,'Curve_Interface'!$K$8:$K$40,1)))),INDEX('Curve_Interface'!$L$8:$L$40,MATCH((B14+C14)/2,'Curve_Interface'!$K$8:$K$40,1))) | I14: =INDEX(Hazard_Bootstrap!$D$7:$D$12,MIN(COUNTIF(Hazard_Bootstrap!$B$7:$B$12,"<"&C14)+1,6)) | J14: =K13 | K14: =J14*EXP(-I14*E14) | L14: =J14-K14 | M14: =D14*G14*K14 | N14: =(D14/2)*H14*L14 | O14: =H14*L14
A15: 9 | B15: =C14 | C15: =EDATE('Curve_Interface'!$F$7,3*8) | D15: =(C15-B15)/360 | E15: =(C15-B15)/365 | F15: =(C15-VAL_DATE)/365 | G15: =IFERROR(INDEX('Curve_Interface'!$L$8:$L$40,MATCH(C15,'Curve_Interface'!$K$8:$K$40,1))*(INDEX('Curve_Interface'!$L$8:$L$40,MATCH(C15,'Curve_Interface'!$K$8:$K$40,1)+1)/INDEX('Curve_Interface'!$L$8:$L$40,MATCH(C15,'Curve_Interface'!$K$8:$K$40,1)))^((C15-INDEX('Curve_Interface'!$K$8:$K$40,MATCH(C15,'Curve_Interface'!$K$8:$K$40,1)))/(INDEX('Curve_Interface'!$K$8:$K$40,MATCH(C15,'Curve_Interface'!$K$8:$K$40,1)+1)-INDEX('Curve_Interface'!$K$8:$K$40,MATCH(C15,'Curve_Interface'!$K$8:$K$40,1)))),INDEX('Curve_Interface'!$L$8:$L$40,MATCH(C15,'Curve_Interface'!$K$8:$K$40,1))) | H15: =IFERROR(INDEX('Curve_Interface'!$L$8:$L$40,MATCH((B15+C15)/2,'Curve_Interface'!$K$8:$K$40,1))*(INDEX('Curve_Interface'!$L$8:$L$40,MATCH((B15+C15)/2,'Curve_Interface'!$K$8:$K$40,1)+1)/INDEX('Curve_Interface'!$L$8:$L$40,MATCH((B15+C15)/2,'Curve_Interface'!$K$8:$K$40,1)))^(((B15+C15)/2-INDEX('Curve_Interface'!$K$8:$K$40,MATCH((B15+C15)/2,'Curve_Interface'!$K$8:$K$40,1)))/(INDEX('Curve_Interface'!$K$8:$K$40,MATCH((B15+C15)/2,'Curve_Interface'!$K$8:$K$40,1)+1)-INDEX('Curve_Interface'!$K$8:$K$40,MATCH((B15+C15)/2,'Curve_Interface'!$K$8:$K$40,1)))),INDEX('Curve_Interface'!$L$8:$L$40,MATCH((B15+C15)/2,'Curve_Interface'!$K$8:$K$40,1))) | I15: =INDEX(Hazard_Bootstrap!$D$7:$D$12,MIN(COUNTIF(Hazard_Bootstrap!$B$7:$B$12,"<"&C15)+1,6)) | J15: =K14 | K15: =J15*EXP(-I15*E15) | L15: =J15-K15 | M15: =D15*G15*K15 | N15: =(D15/2)*H15*L15 | O15: =H15*L15
A16: 10 | B16: =C15 | C16: =EDATE('Curve_Interface'!$F$7,3*9) | D16: =(C16-B16)/360 | E16: =(C16-B16)/365 | F16: =(C16-VAL_DATE)/365 | G16: =IFERROR(INDEX('Curve_Interface'!$L$8:$L$40,MATCH(C16,'Curve_Interface'!$K$8:$K$40,1))*(INDEX('Curve_Interface'!$L$8:$L$40,MATCH(C16,'Curve_Interface'!$K$8:$K$40,1)+1)/INDEX('Curve_Interface'!$L$8:$L$40,MATCH(C16,'Curve_Interface'!$K$8:$K$40,1)))^((C16-INDEX('Curve_Interface'!$K$8:$K$40,MATCH(C16,'Curve_Interface'!$K$8:$K$40,1)))/(INDEX('Curve_Interface'!$K$8:$K$40,MATCH(C16,'Curve_Interface'!$K$8:$K$40,1)+1)-INDEX('Curve_Interface'!$K$8:$K$40,MATCH(C16,'Curve_Interface'!$K$8:$K$40,1)))),INDEX('Curve_Interface'!$L$8:$L$40,MATCH(C16,'Curve_Interface'!$K$8:$K$40,1))) | H16: =IFERROR(INDEX('Curve_Interface'!$L$8:$L$40,MATCH((B16+C16)/2,'Curve_Interface'!$K$8:$K$40,1))*(INDEX('Curve_Interface'!$L$8:$L$40,MATCH((B16+C16)/2,'Curve_Interface'!$K$8:$K$40,1)+1)/INDEX('Curve_Interface'!$L$8:$L$40,MATCH((B16+C16)/2,'Curve_Interface'!$K$8:$K$40,1)))^(((B16+C16)/2-INDEX('Curve_Interface'!$K$8:$K$40,MATCH((B16+C16)/2,'Curve_Interface'!$K$8:$K$40,1)))/(INDEX('Curve_Interface'!$K$8:$K$40,MATCH((B16+C16)/2,'Curve_Interface'!$K$8:$K$40,1)+1)-INDEX('Curve_Interface'!$K$8:$K$40,MATCH((B16+C16)/2,'Curve_Interface'!$K$8:$K$40,1)))),INDEX('Curve_Interface'!$L$8:$L$40,MATCH((B16+C16)/2,'Curve_Interface'!$K$8:$K$40,1))) | I16: =INDEX(Hazard_Bootstrap!$D$7:$D$12,MIN(COUNTIF(Hazard_Bootstrap!$B$7:$B$12,"<"&C16)+1,6)) | J16: =K15 | K16: =J16*EXP(-I16*E16) | L16: =J16-K16 | M16: =D16*G16*K16 | N16: =(D16/2)*H16*L16 | O16: =H16*L16
A17: 11 | B17: =C16 | C17: =EDATE('Curve_Interface'!$F$7,3*10) | D17: =(C17-B17)/360 | E17: =(C17-B17)/365 | F17: =(C17-VAL_DATE)/365 | G17: =IFERROR(INDEX('Curve_Interface'!$L$8:$L$40,MATCH(C17,'Curve_Interface'!$K$8:$K$40,1))*(INDEX('Curve_Interface'!$L$8:$L$40,MATCH(C17,'Curve_Interface'!$K$8:$K$40,1)+1)/INDEX('Curve_Interface'!$L$8:$L$40,MATCH(C17,'Curve_Interface'!$K$8:$K$40,1)))^((C17-INDEX('Curve_Interface'!$K$8:$K$40,MATCH(C17,'Curve_Interface'!$K$8:$K$40,1)))/(INDEX('Curve_Interface'!$K$8:$K$40,MATCH(C17,'Curve_Interface'!$K$8:$K$40,1)+1)-INDEX('Curve_Interface'!$K$8:$K$40,MATCH(C17,'Curve_Interface'!$K$8:$K$40,1)))),INDEX('Curve_Interface'!$L$8:$L$40,MATCH(C17,'Curve_Interface'!$K$8:$K$40,1))) | H17: =IFERROR(INDEX('Curve_Interface'!$L$8:$L$40,MATCH((B17+C17)/2,'Curve_Interface'!$K$8:$K$40,1))*(INDEX('Curve_Interface'!$L$8:$L$40,MATCH((B17+C17)/2,'Curve_Interface'!$K$8:$K$40,1)+1)/INDEX('Curve_Interface'!$L$8:$L$40,MATCH((B17+C17)/2,'Curve_Interface'!$K$8:$K$40,1)))^(((B17+C17)/2-INDEX('Curve_Interface'!$K$8:$K$40,MATCH((B17+C17)/2,'Curve_Interface'!$K$8:$K$40,1)))/(INDEX('Curve_Interface'!$K$8:$K$40,MATCH((B17+C17)/2,'Curve_Interface'!$K$8:$K$40,1)+1)-INDEX('Curve_Interface'!$K$8:$K$40,MATCH((B17+C17)/2,'Curve_Interface'!$K$8:$K$40,1)))),INDEX('Curve_Interface'!$L$8:$L$40,MATCH((B17+C17)/2,'Curve_Interface'!$K$8:$K$40,1))) | I17: =INDEX(Hazard_Bootstrap!$D$7:$D$12,MIN(COUNTIF(Hazard_Bootstrap!$B$7:$B$12,"<"&C17)+1,6)) | J17: =K16 | K17: =J17*EXP(-I17*E17) | L17: =J17-K17 | M17: =D17*G17*K17 | N17: =(D17/2)*H17*L17 | O17: =H17*L17
A18: 12 | B18: =C17 | C18: =EDATE('Curve_Interface'!$F$7,3*11) | D18: =(C18-B18)/360 | E18: =(C18-B18)/365 | F18: =(C18-VAL_DATE)/365 | G18: =IFERROR(INDEX('Curve_Interface'!$L$8:$L$40,MATCH(C18,'Curve_Interface'!$K$8:$K$40,1))*(INDEX('Curve_Interface'!$L$8:$L$40,MATCH(C18,'Curve_Interface'!$K$8:$K$40,1)+1)/INDEX('Curve_Interface'!$L$8:$L$40,MATCH(C18,'Curve_Interface'!$K$8:$K$40,1)))^((C18-INDEX('Curve_Interface'!$K$8:$K$40,MATCH(C18,'Curve_Interface'!$K$8:$K$40,1)))/(INDEX('Curve_Interface'!$K$8:$K$40,MATCH(C18,'Curve_Interface'!$K$8:$K$40,1)+1)-INDEX('Curve_Interface'!$K$8:$K$40,MATCH(C18,'Curve_Interface'!$K$8:$K$40,1)))),INDEX('Curve_Interface'!$L$8:$L$40,MATCH(C18,'Curve_Interface'!$K$8:$K$40,1))) | H18: =IFERROR(INDEX('Curve_Interface'!$L$8:$L$40,MATCH((B18+C18)/2,'Curve_Interface'!$K$8:$K$40,1))*(INDEX('Curve_Interface'!$L$8:$L$40,MATCH((B18+C18)/2,'Curve_Interface'!$K$8:$K$40,1)+1)/INDEX('Curve_Interface'!$L$8:$L$40,MATCH((B18+C18)/2,'Curve_Interface'!$K$8:$K$40,1)))^(((B18+C18)/2-INDEX('Curve_Interface'!$K$8:$K$40,MATCH((B18+C18)/2,'Curve_Interface'!$K$8:$K$40,1)))/(INDEX('Curve_Interface'!$K$8:$K$40,MATCH((B18+C18)/2,'Curve_Interface'!$K$8:$K$40,1)+1)-INDEX('Curve_Interface'!$K$8:$K$40,MATCH((B18+C18)/2,'Curve_Interface'!$K$8:$K$40,1)))),INDEX('Curve_Interface'!$L$8:$L$40,MATCH((B18+C18)/2,'Curve_Interface'!$K$8:$K$40,1))) | I18: =INDEX(Hazard_Bootstrap!$D$7:$D$12,MIN(COUNTIF(Hazard_Bootstrap!$B$7:$B$12,"<"&C18)+1,6)) | J18: =K17 | K18: =J18*EXP(-I18*E18) | L18: =J18-K18 | M18: =D18*G18*K18 | N18: =(D18/2)*H18*L18 | O18: =H18*L18
A19: 13 | B19: =C18 | C19: =EDATE('Curve_Interface'!$F$7,3*12) | D19: =(C19-B19)/360 | E19: =(C19-B19)/365 | F19: =(C19-VAL_DATE)/365 | G19: =IFERROR(INDEX('Curve_Interface'!$L$8:$L$40,MATCH(C19,'Curve_Interface'!$K$8:$K$40,1))*(INDEX('Curve_Interface'!$L$8:$L$40,MATCH(C19,'Curve_Interface'!$K$8:$K$40,1)+1)/INDEX('Curve_Interface'!$L$8:$L$40,MATCH(C19,'Curve_Interface'!$K$8:$K$40,1)))^((C19-INDEX('Curve_Interface'!$K$8:$K$40,MATCH(C19,'Curve_Interface'!$K$8:$K$40,1)))/(INDEX('Curve_Interface'!$K$8:$K$40,MATCH(C19,'Curve_Interface'!$K$8:$K$40,1)+1)-INDEX('Curve_Interface'!$K$8:$K$40,MATCH(C19,'Curve_Interface'!$K$8:$K$40,1)))),INDEX('Curve_Interface'!$L$8:$L$40,MATCH(C19,'Curve_Interface'!$K$8:$K$40,1))) | H19: =IFERROR(INDEX('Curve_Interface'!$L$8:$L$40,MATCH((B19+C19)/2,'Curve_Interface'!$K$8:$K$40,1))*(INDEX('Curve_Interface'!$L$8:$L$40,MATCH((B19+C19)/2,'Curve_Interface'!$K$8:$K$40,1)+1)/INDEX('Curve_Interface'!$L$8:$L$40,MATCH((B19+C19)/2,'Curve_Interface'!$K$8:$K$40,1)))^(((B19+C19)/2-INDEX('Curve_Interface'!$K$8:$K$40,MATCH((B19+C19)/2,'Curve_Interface'!$K$8:$K$40,1)))/(INDEX('Curve_Interface'!$K$8:$K$40,MATCH((B19+C19)/2,'Curve_Interface'!$K$8:$K$40,1)+1)-INDEX('Curve_Interface'!$K$8:$K$40,MATCH((B19+C19)/2,'Curve_Interface'!$K$8:$K$40,1)))),INDEX('Curve_Interface'!$L$8:$L$40,MATCH((B19+C19)/2,'Curve_Interface'!$K$8:$K$40,1))) | I19: =INDEX(Hazard_Bootstrap!$D$7:$D$12,MIN(COUNTIF(Hazard_Bootstrap!$B$7:$B$12,"<"&C19)+1,6)) | J19: =K18 | K19: =J19*EXP(-I19*E19) | L19: =J19-K19 | M19: =D19*G19*K19 | N19: =(D19/2)*H19*L19 | O19: =H19*L19
A20: 14 | B20: =C19 | C20: =EDATE('Curve_Interface'!$F$7,3*13) | D20: =(C20-B20)/360 | E20: =(C20-B20)/365 | F20: =(C20-VAL_DATE)/365 | G20: =IFERROR(INDEX('Curve_Interface'!$L$8:$L$40,MATCH(C20,'Curve_Interface'!$K$8:$K$40,1))*(INDEX('Curve_Interface'!$L$8:$L$40,MATCH(C20,'Curve_Interface'!$K$8:$K$40,1)+1)/INDEX('Curve_Interface'!$L$8:$L$40,MATCH(C20,'Curve_Interface'!$K$8:$K$40,1)))^((C20-INDEX('Curve_Interface'!$K$8:$K$40,MATCH(C20,'Curve_Interface'!$K$8:$K$40,1)))/(INDEX('Curve_Interface'!$K$8:$K$40,MATCH(C20,'Curve_Interface'!$K$8:$K$40,1)+1)-INDEX('Curve_Interface'!$K$8:$K$40,MATCH(C20,'Curve_Interface'!$K$8:$K$40,1)))),INDEX('Curve_Interface'!$L$8:$L$40,MATCH(C20,'Curve_Interface'!$K$8:$K$40,1))) | H20: =IFERROR(INDEX('Curve_Interface'!$L$8:$L$40,MATCH((B20+C20)/2,'Curve_Interface'!$K$8:$K$40,1))*(INDEX('Curve_Interface'!$L$8:$L$40,MATCH((B20+C20)/2,'Curve_Interface'!$K$8:$K$40,1)+1)/INDEX('Curve_Interface'!$L$8:$L$40,MATCH((B20+C20)/2,'Curve_Interface'!$K$8:$K$40,1)))^(((B20+C20)/2-INDEX('Curve_Interface'!$K$8:$K$40,MATCH((B20+C20)/2,'Curve_Interface'!$K$8:$K$40,1)))/(INDEX('Curve_Interface'!$K$8:$K$40,MATCH((B20+C20)/2,'Curve_Interface'!$K$8:$K$40,1)+1)-INDEX('Curve_Interface'!$K$8:$K$40,MATCH((B20+C20)/2,'Curve_Interface'!$K$8:$K$40,1)))),INDEX('Curve_Interface'!$L$8:$L$40,MATCH((B20+C20)/2,'Curve_Interface'!$K$8:$K$40,1))) | I20: =INDEX(Hazard_Bootstrap!$D$7:$D$12,MIN(COUNTIF(Hazard_Bootstrap!$B$7:$B$12,"<"&C20)+1,6)) | J20: =K19 | K20: =J20*EXP(-I20*E20) | L20: =J20-K20 | M20: =D20*G20*K20 | N20: =(D20/2)*H20*L20 | O20: =H20*L20
A21: 15 | B21: =C20 | C21: =EDATE('Curve_Interface'!$F$7,3*14) | D21: =(C21-B21)/360 | E21: =(C21-B21)/365 | F21: =(C21-VAL_DATE)/365 | G21: =IFERROR(INDEX('Curve_Interface'!$L$8:$L$40,MATCH(C21,'Curve_Interface'!$K$8:$K$40,1))*(INDEX('Curve_Interface'!$L$8:$L$40,MATCH(C21,'Curve_Interface'!$K$8:$K$40,1)+1)/INDEX('Curve_Interface'!$L$8:$L$40,MATCH(C21,'Curve_Interface'!$K$8:$K$40,1)))^((C21-INDEX('Curve_Interface'!$K$8:$K$40,MATCH(C21,'Curve_Interface'!$K$8:$K$40,1)))/(INDEX('Curve_Interface'!$K$8:$K$40,MATCH(C21,'Curve_Interface'!$K$8:$K$40,1)+1)-INDEX('Curve_Interface'!$K$8:$K$40,MATCH(C21,'Curve_Interface'!$K$8:$K$40,1)))),INDEX('Curve_Interface'!$L$8:$L$40,MATCH(C21,'Curve_Interface'!$K$8:$K$40,1))) | H21: =IFERROR(INDEX('Curve_Interface'!$L$8:$L$40,MATCH((B21+C21)/2,'Curve_Interface'!$K$8:$K$40,1))*(INDEX('Curve_Interface'!$L$8:$L$40,MATCH((B21+C21)/2,'Curve_Interface'!$K$8:$K$40,1)+1)/INDEX('Curve_Interface'!$L$8:$L$40,MATCH((B21+C21)/2,'Curve_Interface'!$K$8:$K$40,1)))^(((B21+C21)/2-INDEX('Curve_Interface'!$K$8:$K$40,MATCH((B21+C21)/2,'Curve_Interface'!$K$8:$K$40,1)))/(INDEX('Curve_Interface'!$K$8:$K$40,MATCH((B21+C21)/2,'Curve_Interface'!$K$8:$K$40,1)+1)-INDEX('Curve_Interface'!$K$8:$K$40,MATCH((B21+C21)/2,'Curve_Interface'!$K$8:$K$40,1)))),INDEX('Curve_Interface'!$L$8:$L$40,MATCH((B21+C21)/2,'Curve_Interface'!$K$8:$K$40,1))) | I21: =INDEX(Hazard_Bootstrap!$D$7:$D$12,MIN(COUNTIF(Hazard_Bootstrap!$B$7:$B$12,"<"&C21)+1,6)) | J21: =K20 | K21: =J21*EXP(-I21*E21) | L21: =J21-K21 | M21: =D21*G21*K21 | N21: =(D21/2)*H21*L21 | O21: =H21*L21
A22: 16 | B22: =C21 | C22: =EDATE('Curve_Interface'!$F$7,3*15) | D22: =(C22-B22)/360 | E22: =(C22-B22)/365 | F22: =(C22-VAL_DATE)/365 | G22: =IFERROR(INDEX('Curve_Interface'!$L$8:$L$40,MATCH(C22,'Curve_Interface'!$K$8:$K$40,1))*(INDEX('Curve_Interface'!$L$8:$L$40,MATCH(C22,'Curve_Interface'!$K$8:$K$40,1)+1)/INDEX('Curve_Interface'!$L$8:$L$40,MATCH(C22,'Curve_Interface'!$K$8:$K$40,1)))^((C22-INDEX('Curve_Interface'!$K$8:$K$40,MATCH(C22,'Curve_Interface'!$K$8:$K$40,1)))/(INDEX('Curve_Interface'!$K$8:$K$40,MATCH(C22,'Curve_Interface'!$K$8:$K$40,1)+1)-INDEX('Curve_Interface'!$K$8:$K$40,MATCH(C22,'Curve_Interface'!$K$8:$K$40,1)))),INDEX('Curve_Interface'!$L$8:$L$40,MATCH(C22,'Curve_Interface'!$K$8:$K$40,1))) | H22: =IFERROR(INDEX('Curve_Interface'!$L$8:$L$40,MATCH((B22+C22)/2,'Curve_Interface'!$K$8:$K$40,1))*(INDEX('Curve_Interface'!$L$8:$L$40,MATCH((B22+C22)/2,'Curve_Interface'!$K$8:$K$40,1)+1)/INDEX('Curve_Interface'!$L$8:$L$40,MATCH((B22+C22)/2,'Curve_Interface'!$K$8:$K$40,1)))^(((B22+C22)/2-INDEX('Curve_Interface'!$K$8:$K$40,MATCH((B22+C22)/2,'Curve_Interface'!$K$8:$K$40,1)))/(INDEX('Curve_Interface'!$K$8:$K$40,MATCH((B22+C22)/2,'Curve_Interface'!$K$8:$K$40,1)+1)-INDEX('Curve_Interface'!$K$8:$K$40,MATCH((B22+C22)/2,'Curve_Interface'!$K$8:$K$40,1)))),INDEX('Curve_Interface'!$L$8:$L$40,MATCH((B22+C22)/2,'Curve_Interface'!$K$8:$K$40,1))) | I22: =INDEX(Hazard_Bootstrap!$D$7:$D$12,MIN(COUNTIF(Hazard_Bootstrap!$B$7:$B$12,"<"&C22)+1,6)) | J22: =K21 | K22: =J22*EXP(-I22*E22) | L22: =J22-K22 | M22: =D22*G22*K22 | N22: =(D22/2)*H22*L22 | O22: =H22*L22
A23: 17 | B23: =C22 | C23: =EDATE('Curve_Interface'!$F$7,3*16) | D23: =(C23-B23)/360 | E23: =(C23-B23)/365 | F23: =(C23-VAL_DATE)/365 | G23: =IFERROR(INDEX('Curve_Interface'!$L$8:$L$40,MATCH(C23,'Curve_Interface'!$K$8:$K$40,1))*(INDEX('Curve_Interface'!$L$8:$L$40,MATCH(C23,'Curve_Interface'!$K$8:$K$40,1)+1)/INDEX('Curve_Interface'!$L$8:$L$40,MATCH(C23,'Curve_Interface'!$K$8:$K$40,1)))^((C23-INDEX('Curve_Interface'!$K$8:$K$40,MATCH(C23,'Curve_Interface'!$K$8:$K$40,1)))/(INDEX('Curve_Interface'!$K$8:$K$40,MATCH(C23,'Curve_Interface'!$K$8:$K$40,1)+1)-INDEX('Curve_Interface'!$K$8:$K$40,MATCH(C23,'Curve_Interface'!$K$8:$K$40,1)))),INDEX('Curve_Interface'!$L$8:$L$40,MATCH(C23,'Curve_Interface'!$K$8:$K$40,1))) | H23: =IFERROR(INDEX('Curve_Interface'!$L$8:$L$40,MATCH((B23+C23)/2,'Curve_Interface'!$K$8:$K$40,1))*(INDEX('Curve_Interface'!$L$8:$L$40,MATCH((B23+C23)/2,'Curve_Interface'!$K$8:$K$40,1)+1)/INDEX('Curve_Interface'!$L$8:$L$40,MATCH((B23+C23)/2,'Curve_Interface'!$K$8:$K$40,1)))^(((B23+C23)/2-INDEX('Curve_Interface'!$K$8:$K$40,MATCH((B23+C23)/2,'Curve_Interface'!$K$8:$K$40,1)))/(INDEX('Curve_Interface'!$K$8:$K$40,MATCH((B23+C23)/2,'Curve_Interface'!$K$8:$K$40,1)+1)-INDEX('Curve_Interface'!$K$8:$K$40,MATCH((B23+C23)/2,'Curve_Interface'!$K$8:$K$40,1)))),INDEX('Curve_Interface'!$L$8:$L$40,MATCH((B23+C23)/2,'Curve_Interface'!$K$8:$K$40,1))) | I23: =INDEX(Hazard_Bootstrap!$D$7:$D$12,MIN(COUNTIF(Hazard_Bootstrap!$B$7:$B$12,"<"&C23)+1,6)) | J23: =K22 | K23: =J23*EXP(-I23*E23) | L23: =J23-K23 | M23: =D23*G23*K23 | N23: =(D23/2)*H23*L23 | O23: =H23*L23
A24: 18 | B24: =C23 | C24: =EDATE('Curve_Interface'!$F$7,3*17) | D24: =(C24-B24)/360 | E24: =(C24-B24)/365 | F24: =(C24-VAL_DATE)/365 | G24: =IFERROR(INDEX('Curve_Interface'!$L$8:$L$40,MATCH(C24,'Curve_Interface'!$K$8:$K$40,1))*(INDEX('Curve_Interface'!$L$8:$L$40,MATCH(C24,'Curve_Interface'!$K$8:$K$40,1)+1)/INDEX('Curve_Interface'!$L$8:$L$40,MATCH(C24,'Curve_Interface'!$K$8:$K$40,1)))^((C24-INDEX('Curve_Interface'!$K$8:$K$40,MATCH(C24,'Curve_Interface'!$K$8:$K$40,1)))/(INDEX('Curve_Interface'!$K$8:$K$40,MATCH(C24,'Curve_Interface'!$K$8:$K$40,1)+1)-INDEX('Curve_Interface'!$K$8:$K$40,MATCH(C24,'Curve_Interface'!$K$8:$K$40,1)))),INDEX('Curve_Interface'!$L$8:$L$40,MATCH(C24,'Curve_Interface'!$K$8:$K$40,1))) | H24: =IFERROR(INDEX('Curve_Interface'!$L$8:$L$40,MATCH((B24+C24)/2,'Curve_Interface'!$K$8:$K$40,1))*(INDEX('Curve_Interface'!$L$8:$L$40,MATCH((B24+C24)/2,'Curve_Interface'!$K$8:$K$40,1)+1)/INDEX('Curve_Interface'!$L$8:$L$40,MATCH((B24+C24)/2,'Curve_Interface'!$K$8:$K$40,1)))^(((B24+C24)/2-INDEX('Curve_Interface'!$K$8:$K$40,MATCH((B24+C24)/2,'Curve_Interface'!$K$8:$K$40,1)))/(INDEX('Curve_Interface'!$K$8:$K$40,MATCH((B24+C24)/2,'Curve_Interface'!$K$8:$K$40,1)+1)-INDEX('Curve_Interface'!$K$8:$K$40,MATCH((B24+C24)/2,'Curve_Interface'!$K$8:$K$40,1)))),INDEX('Curve_Interface'!$L$8:$L$40,MATCH((B24+C24)/2,'Curve_Interface'!$K$8:$K$40,1))) | I24: =INDEX(Hazard_Bootstrap!$D$7:$D$12,MIN(COUNTIF(Hazard_Bootstrap!$B$7:$B$12,"<"&C24)+1,6)) | J24: =K23 | K24: =J24*EXP(-I24*E24) | L24: =J24-K24 | M24: =D24*G24*K24 | N24: =(D24/2)*H24*L24 | O24: =H24*L24
A25: 19 | B25: =C24 | C25: =EDATE('Curve_Interface'!$F$7,3*18) | D25: =(C25-B25)/360 | E25: =(C25-B25)/365 | F25: =(C25-VAL_DATE)/365 | G25: =IFERROR(INDEX('Curve_Interface'!$L$8:$L$40,MATCH(C25,'Curve_Interface'!$K$8:$K$40,1))*(INDEX('Curve_Interface'!$L$8:$L$40,MATCH(C25,'Curve_Interface'!$K$8:$K$40,1)+1)/INDEX('Curve_Interface'!$L$8:$L$40,MATCH(C25,'Curve_Interface'!$K$8:$K$40,1)))^((C25-INDEX('Curve_Interface'!$K$8:$K$40,MATCH(C25,'Curve_Interface'!$K$8:$K$40,1)))/(INDEX('Curve_Interface'!$K$8:$K$40,MATCH(C25,'Curve_Interface'!$K$8:$K$40,1)+1)-INDEX('Curve_Interface'!$K$8:$K$40,MATCH(C25,'Curve_Interface'!$K$8:$K$40,1)))),INDEX('Curve_Interface'!$L$8:$L$40,MATCH(C25,'Curve_Interface'!$K$8:$K$40,1))) | H25: =IFERROR(INDEX('Curve_Interface'!$L$8:$L$40,MATCH((B25+C25)/2,'Curve_Interface'!$K$8:$K$40,1))*(INDEX('Curve_Interface'!$L$8:$L$40,MATCH((B25+C25)/2,'Curve_Interface'!$K$8:$K$40,1)+1)/INDEX('Curve_Interface'!$L$8:$L$40,MATCH((B25+C25)/2,'Curve_Interface'!$K$8:$K$40,1)))^(((B25+C25)/2-INDEX('Curve_Interface'!$K$8:$K$40,MATCH((B25+C25)/2,'Curve_Interface'!$K$8:$K$40,1)))/(INDEX('Curve_Interface'!$K$8:$K$40,MATCH((B25+C25)/2,'Curve_Interface'!$K$8:$K$40,1)+1)-INDEX('Curve_Interface'!$K$8:$K$40,MATCH((B25+C25)/2,'Curve_Interface'!$K$8:$K$40,1)))),INDEX('Curve_Interface'!$L$8:$L$40,MATCH((B25+C25)/2,'Curve_Interface'!$K$8:$K$40,1))) | I25: =INDEX(Hazard_Bootstrap!$D$7:$D$12,MIN(COUNTIF(Hazard_Bootstrap!$B$7:$B$12,"<"&C25)+1,6)) | J25: =K24 | K25: =J25*EXP(-I25*E25) | L25: =J25-K25 | M25: =D25*G25*K25 | N25: =(D25/2)*H25*L25 | O25: =H25*L25
A26: 20 | B26: =C25 | C26: =EDATE('Curve_Interface'!$F$7,3*19) | D26: =(C26-B26)/360 | E26: =(C26-B26)/365 | F26: =(C26-VAL_DATE)/365 | G26: =IFERROR(INDEX('Curve_Interface'!$L$8:$L$40,MATCH(C26,'Curve_Interface'!$K$8:$K$40,1))*(INDEX('Curve_Interface'!$L$8:$L$40,MATCH(C26,'Curve_Interface'!$K$8:$K$40,1)+1)/INDEX('Curve_Interface'!$L$8:$L$40,MATCH(C26,'Curve_Interface'!$K$8:$K$40,1)))^((C26-INDEX('Curve_Interface'!$K$8:$K$40,MATCH(C26,'Curve_Interface'!$K$8:$K$40,1)))/(INDEX('Curve_Interface'!$K$8:$K$40,MATCH(C26,'Curve_Interface'!$K$8:$K$40,1)+1)-INDEX('Curve_Interface'!$K$8:$K$40,MATCH(C26,'Curve_Interface'!$K$8:$K$40,1)))),INDEX('Curve_Interface'!$L$8:$L$40,MATCH(C26,'Curve_Interface'!$K$8:$K$40,1))) | H26: =IFERROR(INDEX('Curve_Interface'!$L$8:$L$40,MATCH((B26+C26)/2,'Curve_Interface'!$K$8:$K$40,1))*(INDEX('Curve_Interface'!$L$8:$L$40,MATCH((B26+C26)/2,'Curve_Interface'!$K$8:$K$40,1)+1)/INDEX('Curve_Interface'!$L$8:$L$40,MATCH((B26+C26)/2,'Curve_Interface'!$K$8:$K$40,1)))^(((B26+C26)/2-INDEX('Curve_Interface'!$K$8:$K$40,MATCH((B26+C26)/2,'Curve_Interface'!$K$8:$K$40,1)))/(INDEX('Curve_Interface'!$K$8:$K$40,MATCH((B26+C26)/2,'Curve_Interface'!$K$8:$K$40,1)+1)-INDEX('Curve_Interface'!$K$8:$K$40,MATCH((B26+C26)/2,'Curve_Interface'!$K$8:$K$40,1)))),INDEX('Curve_Interface'!$L$8:$L$40,MATCH((B26+C26)/2,'Curve_Interface'!$K$8:$K$40,1))) | I26: =INDEX(Hazard_Bootstrap!$D$7:$D$12,MIN(COUNTIF(Hazard_Bootstrap!$B$7:$B$12,"<"&C26)+1,6)) | J26: =K25 | K26: =J26*EXP(-I26*E26) | L26: =J26-K26 | M26: =D26*G26*K26 | N26: =(D26/2)*H26*L26 | O26: =H26*L26
A27: 21 | B27: =C26 | C27: =EDATE('Curve_Interface'!$F$7,3*20) | D27: =(C27-B27)/360 | E27: =(C27-B27)/365 | F27: =(C27-VAL_DATE)/365 | G27: =IFERROR(INDEX('Curve_Interface'!$L$8:$L$40,MATCH(C27,'Curve_Interface'!$K$8:$K$40,1))*(INDEX('Curve_Interface'!$L$8:$L$40,MATCH(C27,'Curve_Interface'!$K$8:$K$40,1)+1)/INDEX('Curve_Interface'!$L$8:$L$40,MATCH(C27,'Curve_Interface'!$K$8:$K$40,1)))^((C27-INDEX('Curve_Interface'!$K$8:$K$40,MATCH(C27,'Curve_Interface'!$K$8:$K$40,1)))/(INDEX('Curve_Interface'!$K$8:$K$40,MATCH(C27,'Curve_Interface'!$K$8:$K$40,1)+1)-INDEX('Curve_Interface'!$K$8:$K$40,MATCH(C27,'Curve_Interface'!$K$8:$K$40,1)))),INDEX('Curve_Interface'!$L$8:$L$40,MATCH(C27,'Curve_Interface'!$K$8:$K$40,1))) | H27: =IFERROR(INDEX('Curve_Interface'!$L$8:$L$40,MATCH((B27+C27)/2,'Curve_Interface'!$K$8:$K$40,1))*(INDEX('Curve_Interface'!$L$8:$L$40,MATCH((B27+C27)/2,'Curve_Interface'!$K$8:$K$40,1)+1)/INDEX('Curve_Interface'!$L$8:$L$40,MATCH((B27+C27)/2,'Curve_Interface'!$K$8:$K$40,1)))^(((B27+C27)/2-INDEX('Curve_Interface'!$K$8:$K$40,MATCH((B27+C27)/2,'Curve_Interface'!$K$8:$K$40,1)))/(INDEX('Curve_Interface'!$K$8:$K$40,MATCH((B27+C27)/2,'Curve_Interface'!$K$8:$K$40,1)+1)-INDEX('Curve_Interface'!$K$8:$K$40,MATCH((B27+C27)/2,'Curve_Interface'!$K$8:$K$40,1)))),INDEX('Curve_Interface'!$L$8:$L$40,MATCH((B27+C27)/2,'Curve_Interface'!$K$8:$K$40,1))) | I27: =INDEX(Hazard_Bootstrap!$D$7:$D$12,MIN(COUNTIF(Hazard_Bootstrap!$B$7:$B$12,"<"&C27)+1,6)) | J27: =K26 | K27: =J27*EXP(-I27*E27) | L27: =J27-K27 | M27: =D27*G27*K27 | N27: =(D27/2)*H27*L27 | O27: =H27*L27
A28: 22 | B28: =C27 | C28: =EDATE('Curve_Interface'!$F$7,3*21) | D28: =(C28-B28)/360 | E28: =(C28-B28)/365 | F28: =(C28-VAL_DATE)/365 | G28: =IFERROR(INDEX('Curve_Interface'!$L$8:$L$40,MATCH(C28,'Curve_Interface'!$K$8:$K$40,1))*(INDEX('Curve_Interface'!$L$8:$L$40,MATCH(C28,'Curve_Interface'!$K$8:$K$40,1)+1)/INDEX('Curve_Interface'!$L$8:$L$40,MATCH(C28,'Curve_Interface'!$K$8:$K$40,1)))^((C28-INDEX('Curve_Interface'!$K$8:$K$40,MATCH(C28,'Curve_Interface'!$K$8:$K$40,1)))/(INDEX('Curve_Interface'!$K$8:$K$40,MATCH(C28,'Curve_Interface'!$K$8:$K$40,1)+1)-INDEX('Curve_Interface'!$K$8:$K$40,MATCH(C28,'Curve_Interface'!$K$8:$K$40,1)))),INDEX('Curve_Interface'!$L$8:$L$40,MATCH(C28,'Curve_Interface'!$K$8:$K$40,1))) | H28: =IFERROR(INDEX('Curve_Interface'!$L$8:$L$40,MATCH((B28+C28)/2,'Curve_Interface'!$K$8:$K$40,1))*(INDEX('Curve_Interface'!$L$8:$L$40,MATCH((B28+C28)/2,'Curve_Interface'!$K$8:$K$40,1)+1)/INDEX('Curve_Interface'!$L$8:$L$40,MATCH((B28+C28)/2,'Curve_Interface'!$K$8:$K$40,1)))^(((B28+C28)/2-INDEX('Curve_Interface'!$K$8:$K$40,MATCH((B28+C28)/2,'Curve_Interface'!$K$8:$K$40,1)))/(INDEX('Curve_Interface'!$K$8:$K$40,MATCH((B28+C28)/2,'Curve_Interface'!$K$8:$K$40,1)+1)-INDEX('Curve_Interface'!$K$8:$K$40,MATCH((B28+C28)/2,'Curve_Interface'!$K$8:$K$40,1)))),INDEX('Curve_Interface'!$L$8:$L$40,MATCH((B28+C28)/2,'Curve_Interface'!$K$8:$K$40,1))) | I28: =INDEX(Hazard_Bootstrap!$D$7:$D$12,MIN(COUNTIF(Hazard_Bootstrap!$B$7:$B$12,"<"&C28)+1,6)) | J28: =K27 | K28: =J28*EXP(-I28*E28) | L28: =J28-K28 | M28: =D28*G28*K28 | N28: =(D28/2)*H28*L28 | O28: =H28*L28
A29: 23 | B29: =C28 | C29: =EDATE('Curve_Interface'!$F$7,3*22) | D29: =(C29-B29)/360 | E29: =(C29-B29)/365 | F29: =(C29-VAL_DATE)/365 | G29: =IFERROR(INDEX('Curve_Interface'!$L$8:$L$40,MATCH(C29,'Curve_Interface'!$K$8:$K$40,1))*(INDEX('Curve_Interface'!$L$8:$L$40,MATCH(C29,'Curve_Interface'!$K$8:$K$40,1)+1)/INDEX('Curve_Interface'!$L$8:$L$40,MATCH(C29,'Curve_Interface'!$K$8:$K$40,1)))^((C29-INDEX('Curve_Interface'!$K$8:$K$40,MATCH(C29,'Curve_Interface'!$K$8:$K$40,1)))/(INDEX('Curve_Interface'!$K$8:$K$40,MATCH(C29,'Curve_Interface'!$K$8:$K$40,1)+1)-INDEX('Curve_Interface'!$K$8:$K$40,MATCH(C29,'Curve_Interface'!$K$8:$K$40,1)))),INDEX('Curve_Interface'!$L$8:$L$40,MATCH(C29,'Curve_Interface'!$K$8:$K$40,1))) | H29: =IFERROR(INDEX('Curve_Interface'!$L$8:$L$40,MATCH((B29+C29)/2,'Curve_Interface'!$K$8:$K$40,1))*(INDEX('Curve_Interface'!$L$8:$L$40,MATCH((B29+C29)/2,'Curve_Interface'!$K$8:$K$40,1)+1)/INDEX('Curve_Interface'!$L$8:$L$40,MATCH((B29+C29)/2,'Curve_Interface'!$K$8:$K$40,1)))^(((B29+C29)/2-INDEX('Curve_Interface'!$K$8:$K$40,MATCH((B29+C29)/2,'Curve_Interface'!$K$8:$K$40,1)))/(INDEX('Curve_Interface'!$K$8:$K$40,MATCH((B29+C29)/2,'Curve_Interface'!$K$8:$K$40,1)+1)-INDEX('Curve_Interface'!$K$8:$K$40,MATCH((B29+C29)/2,'Curve_Interface'!$K$8:$K$40,1)))),INDEX('Curve_Interface'!$L$8:$L$40,MATCH((B29+C29)/2,'Curve_Interface'!$K$8:$K$40,1))) | I29: =INDEX(Hazard_Bootstrap!$D$7:$D$12,MIN(COUNTIF(Hazard_Bootstrap!$B$7:$B$12,"<"&C29)+1,6)) | J29: =K28 | K29: =J29*EXP(-I29*E29) | L29: =J29-K29 | M29: =D29*G29*K29 | N29: =(D29/2)*H29*L29 | O29: =H29*L29
A30: 24 | B30: =C29 | C30: =EDATE('Curve_Interface'!$F$7,3*23) | D30: =(C30-B30)/360 | E30: =(C30-B30)/365 | F30: =(C30-VAL_DATE)/365 | G30: =IFERROR(INDEX('Curve_Interface'!$L$8:$L$40,MATCH(C30,'Curve_Interface'!$K$8:$K$40,1))*(INDEX('Curve_Interface'!$L$8:$L$40,MATCH(C30,'Curve_Interface'!$K$8:$K$40,1)+1)/INDEX('Curve_Interface'!$L$8:$L$40,MATCH(C30,'Curve_Interface'!$K$8:$K$40,1)))^((C30-INDEX('Curve_Interface'!$K$8:$K$40,MATCH(C30,'Curve_Interface'!$K$8:$K$40,1)))/(INDEX('Curve_Interface'!$K$8:$K$40,MATCH(C30,'Curve_Interface'!$K$8:$K$40,1)+1)-INDEX('Curve_Interface'!$K$8:$K$40,MATCH(C30,'Curve_Interface'!$K$8:$K$40,1)))),INDEX('Curve_Interface'!$L$8:$L$40,MATCH(C30,'Curve_Interface'!$K$8:$K$40,1))) | H30: =IFERROR(INDEX('Curve_Interface'!$L$8:$L$40,MATCH((B30+C30)/2,'Curve_Interface'!$K$8:$K$40,1))*(INDEX('Curve_Interface'!$L$8:$L$40,MATCH((B30+C30)/2,'Curve_Interface'!$K$8:$K$40,1)+1)/INDEX('Curve_Interface'!$L$8:$L$40,MATCH((B30+C30)/2,'Curve_Interface'!$K$8:$K$40,1)))^(((B30+C30)/2-INDEX('Curve_Interface'!$K$8:$K$40,MATCH((B30+C30)/2,'Curve_Interface'!$K$8:$K$40,1)))/(INDEX('Curve_Interface'!$K$8:$K$40,MATCH((B30+C30)/2,'Curve_Interface'!$K$8:$K$40,1)+1)-INDEX('Curve_Interface'!$K$8:$K$40,MATCH((B30+C30)/2,'Curve_Interface'!$K$8:$K$40,1)))),INDEX('Curve_Interface'!$L$8:$L$40,MATCH((B30+C30)/2,'Curve_Interface'!$K$8:$K$40,1))) | I30: =INDEX(Hazard_Bootstrap!$D$7:$D$12,MIN(COUNTIF(Hazard_Bootstrap!$B$7:$B$12,"<"&C30)+1,6)) | J30: =K29 | K30: =J30*EXP(-I30*E30) | L30: =J30-K30 | M30: =D30*G30*K30 | N30: =(D30/2)*H30*L30 | O30: =H30*L30
A31: 25 | B31: =C30 | C31: =EDATE('Curve_Interface'!$F$7,3*24) | D31: =(C31-B31)/360 | E31: =(C31-B31)/365 | F31: =(C31-VAL_DATE)/365 | G31: =IFERROR(INDEX('Curve_Interface'!$L$8:$L$40,MATCH(C31,'Curve_Interface'!$K$8:$K$40,1))*(INDEX('Curve_Interface'!$L$8:$L$40,MATCH(C31,'Curve_Interface'!$K$8:$K$40,1)+1)/INDEX('Curve_Interface'!$L$8:$L$40,MATCH(C31,'Curve_Interface'!$K$8:$K$40,1)))^((C31-INDEX('Curve_Interface'!$K$8:$K$40,MATCH(C31,'Curve_Interface'!$K$8:$K$40,1)))/(INDEX('Curve_Interface'!$K$8:$K$40,MATCH(C31,'Curve_Interface'!$K$8:$K$40,1)+1)-INDEX('Curve_Interface'!$K$8:$K$40,MATCH(C31,'Curve_Interface'!$K$8:$K$40,1)))),INDEX('Curve_Interface'!$L$8:$L$40,MATCH(C31,'Curve_Interface'!$K$8:$K$40,1))) | H31: =IFERROR(INDEX('Curve_Interface'!$L$8:$L$40,MATCH((B31+C31)/2,'Curve_Interface'!$K$8:$K$40,1))*(INDEX('Curve_Interface'!$L$8:$L$40,MATCH((B31+C31)/2,'Curve_Interface'!$K$8:$K$40,1)+1)/INDEX('Curve_Interface'!$L$8:$L$40,MATCH((B31+C31)/2,'Curve_Interface'!$K$8:$K$40,1)))^(((B31+C31)/2-INDEX('Curve_Interface'!$K$8:$K$40,MATCH((B31+C31)/2,'Curve_Interface'!$K$8:$K$40,1)))/(INDEX('Curve_Interface'!$K$8:$K$40,MATCH((B31+C31)/2,'Curve_Interface'!$K$8:$K$40,1)+1)-INDEX('Curve_Interface'!$K$8:$K$40,MATCH((B31+C31)/2,'Curve_Interface'!$K$8:$K$40,1)))),INDEX('Curve_Interface'!$L$8:$L$40,MATCH((B31+C31)/2,'Curve_Interface'!$K$8:$K$40,1))) | I31: =INDEX(Hazard_Bootstrap!$D$7:$D$12,MIN(COUNTIF(Hazard_Bootstrap!$B$7:$B$12,"<"&C31)+1,6)) | J31: =K30 | K31: =J31*EXP(-I31*E31) | L31: =J31-K31 | M31: =D31*G31*K31 | N31: =(D31/2)*H31*L31 | O31: =H31*L31
A32: 26 | B32: =C31 | C32: =EDATE('Curve_Interface'!$F$7,3*25) | D32: =(C32-B32)/360 | E32: =(C32-B32)/365 | F32: =(C32-VAL_DATE)/365 | G32: =IFERROR(INDEX('Curve_Interface'!$L$8:$L$40,MATCH(C32,'Curve_Interface'!$K$8:$K$40,1))*(INDEX('Curve_Interface'!$L$8:$L$40,MATCH(C32,'Curve_Interface'!$K$8:$K$40,1)+1)/INDEX('Curve_Interface'!$L$8:$L$40,MATCH(C32,'Curve_Interface'!$K$8:$K$40,1)))^((C32-INDEX('Curve_Interface'!$K$8:$K$40,MATCH(C32,'Curve_Interface'!$K$8:$K$40,1)))/(INDEX('Curve_Interface'!$K$8:$K$40,MATCH(C32,'Curve_Interface'!$K$8:$K$40,1)+1)-INDEX('Curve_Interface'!$K$8:$K$40,MATCH(C32,'Curve_Interface'!$K$8:$K$40,1)))),INDEX('Curve_Interface'!$L$8:$L$40,MATCH(C32,'Curve_Interface'!$K$8:$K$40,1))) | H32: =IFERROR(INDEX('Curve_Interface'!$L$8:$L$40,MATCH((B32+C32)/2,'Curve_Interface'!$K$8:$K$40,1))*(INDEX('Curve_Interface'!$L$8:$L$40,MATCH((B32+C32)/2,'Curve_Interface'!$K$8:$K$40,1)+1)/INDEX('Curve_Interface'!$L$8:$L$40,MATCH((B32+C32)/2,'Curve_Interface'!$K$8:$K$40,1)))^(((B32+C32)/2-INDEX('Curve_Interface'!$K$8:$K$40,MATCH((B32+C32)/2,'Curve_Interface'!$K$8:$K$40,1)))/(INDEX('Curve_Interface'!$K$8:$K$40,MATCH((B32+C32)/2,'Curve_Interface'!$K$8:$K$40,1)+1)-INDEX('Curve_Interface'!$K$8:$K$40,MATCH((B32+C32)/2,'Curve_Interface'!$K$8:$K$40,1)))),INDEX('Curve_Interface'!$L$8:$L$40,MATCH((B32+C32)/2,'Curve_Interface'!$K$8:$K$40,1))) | I32: =INDEX(Hazard_Bootstrap!$D$7:$D$12,MIN(COUNTIF(Hazard_Bootstrap!$B$7:$B$12,"<"&C32)+1,6)) | J32: =K31 | K32: =J32*EXP(-I32*E32) | L32: =J32-K32 | M32: =D32*G32*K32 | N32: =(D32/2)*H32*L32 | O32: =H32*L32
A33: 27 | B33: =C32 | C33: =EDATE('Curve_Interface'!$F$7,3*26) | D33: =(C33-B33)/360 | E33: =(C33-B33)/365 | F33: =(C33-VAL_DATE)/365 | G33: =IFERROR(INDEX('Curve_Interface'!$L$8:$L$40,MATCH(C33,'Curve_Interface'!$K$8:$K$40,1))*(INDEX('Curve_Interface'!$L$8:$L$40,MATCH(C33,'Curve_Interface'!$K$8:$K$40,1)+1)/INDEX('Curve_Interface'!$L$8:$L$40,MATCH(C33,'Curve_Interface'!$K$8:$K$40,1)))^((C33-INDEX('Curve_Interface'!$K$8:$K$40,MATCH(C33,'Curve_Interface'!$K$8:$K$40,1)))/(INDEX('Curve_Interface'!$K$8:$K$40,MATCH(C33,'Curve_Interface'!$K$8:$K$40,1)+1)-INDEX('Curve_Interface'!$K$8:$K$40,MATCH(C33,'Curve_Interface'!$K$8:$K$40,1)))),INDEX('Curve_Interface'!$L$8:$L$40,MATCH(C33,'Curve_Interface'!$K$8:$K$40,1))) | H33: =IFERROR(INDEX('Curve_Interface'!$L$8:$L$40,MATCH((B33+C33)/2,'Curve_Interface'!$K$8:$K$40,1))*(INDEX('Curve_Interface'!$L$8:$L$40,MATCH((B33+C33)/2,'Curve_Interface'!$K$8:$K$40,1)+1)/INDEX('Curve_Interface'!$L$8:$L$40,MATCH((B33+C33)/2,'Curve_Interface'!$K$8:$K$40,1)))^(((B33+C33)/2-INDEX('Curve_Interface'!$K$8:$K$40,MATCH((B33+C33)/2,'Curve_Interface'!$K$8:$K$40,1)))/(INDEX('Curve_Interface'!$K$8:$K$40,MATCH((B33+C33)/2,'Curve_Interface'!$K$8:$K$40,1)+1)-INDEX('Curve_Interface'!$K$8:$K$40,MATCH((B33+C33)/2,'Curve_Interface'!$K$8:$K$40,1)))),INDEX('Curve_Interface'!$L$8:$L$40,MATCH((B33+C33)/2,'Curve_Interface'!$K$8:$K$40,1))) | I33: =INDEX(Hazard_Bootstrap!$D$7:$D$12,MIN(COUNTIF(Hazard_Bootstrap!$B$7:$B$12,"<"&C33)+1,6)) | J33: =K32 | K33: =J33*EXP(-I33*E33) | L33: =J33-K33 | M33: =D33*G33*K33 | N33: =(D33/2)*H33*L33 | O33: =H33*L33
A34: 28 | B34: =C33 | C34: =EDATE('Curve_Interface'!$F$7,3*27) | D34: =(C34-B34)/360 | E34: =(C34-B34)/365 | F34: =(C34-VAL_DATE)/365 | G34: =IFERROR(INDEX('Curve_Interface'!$L$8:$L$40,MATCH(C34,'Curve_Interface'!$K$8:$K$40,1))*(INDEX('Curve_Interface'!$L$8:$L$40,MATCH(C34,'Curve_Interface'!$K$8:$K$40,1)+1)/INDEX('Curve_Interface'!$L$8:$L$40,MATCH(C34,'Curve_Interface'!$K$8:$K$40,1)))^((C34-INDEX('Curve_Interface'!$K$8:$K$40,MATCH(C34,'Curve_Interface'!$K$8:$K$40,1)))/(INDEX('Curve_Interface'!$K$8:$K$40,MATCH(C34,'Curve_Interface'!$K$8:$K$40,1)+1)-INDEX('Curve_Interface'!$K$8:$K$40,MATCH(C34,'Curve_Interface'!$K$8:$K$40,1)))),INDEX('Curve_Interface'!$L$8:$L$40,MATCH(C34,'Curve_Interface'!$K$8:$K$40,1))) | H34: =IFERROR(INDEX('Curve_Interface'!$L$8:$L$40,MATCH((B34+C34)/2,'Curve_Interface'!$K$8:$K$40,1))*(INDEX('Curve_Interface'!$L$8:$L$40,MATCH((B34+C34)/2,'Curve_Interface'!$K$8:$K$40,1)+1)/INDEX('Curve_Interface'!$L$8:$L$40,MATCH((B34+C34)/2,'Curve_Interface'!$K$8:$K$40,1)))^(((B34+C34)/2-INDEX('Curve_Interface'!$K$8:$K$40,MATCH((B34+C34)/2,'Curve_Interface'!$K$8:$K$40,1)))/(INDEX('Curve_Interface'!$K$8:$K$40,MATCH((B34+C34)/2,'Curve_Interface'!$K$8:$K$40,1)+1)-INDEX('Curve_Interface'!$K$8:$K$40,MATCH((B34+C34)/2,'Curve_Interface'!$K$8:$K$40,1)))),INDEX('Curve_Interface'!$L$8:$L$40,MATCH((B34+C34)/2,'Curve_Interface'!$K$8:$K$40,1))) | I34: =INDEX(Hazard_Bootstrap!$D$7:$D$12,MIN(COUNTIF(Hazard_Bootstrap!$B$7:$B$12,"<"&C34)+1,6)) | J34: =K33 | K34: =J34*EXP(-I34*E34) | L34: =J34-K34 | M34: =D34*G34*K34 | N34: =(D34/2)*H34*L34 | O34: =H34*L34
A35: 29 | B35: =C34 | C35: =EDATE('Curve_Interface'!$F$7,3*28) | D35: =(C35-B35)/360 | E35: =(C35-B35)/365 | F35: =(C35-VAL_DATE)/365 | G35: =IFERROR(INDEX('Curve_Interface'!$L$8:$L$40,MATCH(C35,'Curve_Interface'!$K$8:$K$40,1))*(INDEX('Curve_Interface'!$L$8:$L$40,MATCH(C35,'Curve_Interface'!$K$8:$K$40,1)+1)/INDEX('Curve_Interface'!$L$8:$L$40,MATCH(C35,'Curve_Interface'!$K$8:$K$40,1)))^((C35-INDEX('Curve_Interface'!$K$8:$K$40,MATCH(C35,'Curve_Interface'!$K$8:$K$40,1)))/(INDEX('Curve_Interface'!$K$8:$K$40,MATCH(C35,'Curve_Interface'!$K$8:$K$40,1)+1)-INDEX('Curve_Interface'!$K$8:$K$40,MATCH(C35,'Curve_Interface'!$K$8:$K$40,1)))),INDEX('Curve_Interface'!$L$8:$L$40,MATCH(C35,'Curve_Interface'!$K$8:$K$40,1))) | H35: =IFERROR(INDEX('Curve_Interface'!$L$8:$L$40,MATCH((B35+C35)/2,'Curve_Interface'!$K$8:$K$40,1))*(INDEX('Curve_Interface'!$L$8:$L$40,MATCH((B35+C35)/2,'Curve_Interface'!$K$8:$K$40,1)+1)/INDEX('Curve_Interface'!$L$8:$L$40,MATCH((B35+C35)/2,'Curve_Interface'!$K$8:$K$40,1)))^(((B35+C35)/2-INDEX('Curve_Interface'!$K$8:$K$40,MATCH((B35+C35)/2,'Curve_Interface'!$K$8:$K$40,1)))/(INDEX('Curve_Interface'!$K$8:$K$40,MATCH((B35+C35)/2,'Curve_Interface'!$K$8:$K$40,1)+1)-INDEX('Curve_Interface'!$K$8:$K$40,MATCH((B35+C35)/2,'Curve_Interface'!$K$8:$K$40,1)))),INDEX('Curve_Interface'!$L$8:$L$40,MATCH((B35+C35)/2,'Curve_Interface'!$K$8:$K$40,1))) | I35: =INDEX(Hazard_Bootstrap!$D$7:$D$12,MIN(COUNTIF(Hazard_Bootstrap!$B$7:$B$12,"<"&C35)+1,6)) | J35: =K34 | K35: =J35*EXP(-I35*E35) | L35: =J35-K35 | M35: =D35*G35*K35 | N35: =(D35/2)*H35*L35 | O35: =H35*L35
A36: 30 | B36: =C35 | C36: =EDATE('Curve_Interface'!$F$7,3*29) | D36: =(C36-B36)/360 | E36: =(C36-B36)/365 | F36: =(C36-VAL_DATE)/365 | G36: =IFERROR(INDEX('Curve_Interface'!$L$8:$L$40,MATCH(C36,'Curve_Interface'!$K$8:$K$40,1))*(INDEX('Curve_Interface'!$L$8:$L$40,MATCH(C36,'Curve_Interface'!$K$8:$K$40,1)+1)/INDEX('Curve_Interface'!$L$8:$L$40,MATCH(C36,'Curve_Interface'!$K$8:$K$40,1)))^((C36-INDEX('Curve_Interface'!$K$8:$K$40,MATCH(C36,'Curve_Interface'!$K$8:$K$40,1)))/(INDEX('Curve_Interface'!$K$8:$K$40,MATCH(C36,'Curve_Interface'!$K$8:$K$40,1)+1)-INDEX('Curve_Interface'!$K$8:$K$40,MATCH(C36,'Curve_Interface'!$K$8:$K$40,1)))),INDEX('Curve_Interface'!$L$8:$L$40,MATCH(C36,'Curve_Interface'!$K$8:$K$40,1))) | H36: =IFERROR(INDEX('Curve_Interface'!$L$8:$L$40,MATCH((B36+C36)/2,'Curve_Interface'!$K$8:$K$40,1))*(INDEX('Curve_Interface'!$L$8:$L$40,MATCH((B36+C36)/2,'Curve_Interface'!$K$8:$K$40,1)+1)/INDEX('Curve_Interface'!$L$8:$L$40,MATCH((B36+C36)/2,'Curve_Interface'!$K$8:$K$40,1)))^(((B36+C36)/2-INDEX('Curve_Interface'!$K$8:$K$40,MATCH((B36+C36)/2,'Curve_Interface'!$K$8:$K$40,1)))/(INDEX('Curve_Interface'!$K$8:$K$40,MATCH((B36+C36)/2,'Curve_Interface'!$K$8:$K$40,1)+1)-INDEX('Curve_Interface'!$K$8:$K$40,MATCH((B36+C36)/2,'Curve_Interface'!$K$8:$K$40,1)))),INDEX('Curve_Interface'!$L$8:$L$40,MATCH((B36+C36)/2,'Curve_Interface'!$K$8:$K$40,1))) | I36: =INDEX(Hazard_Bootstrap!$D$7:$D$12,MIN(COUNTIF(Hazard_Bootstrap!$B$7:$B$12,"<"&C36)+1,6)) | J36: =K35 | K36: =J36*EXP(-I36*E36) | L36: =J36-K36 | M36: =D36*G36*K36 | N36: =(D36/2)*H36*L36 | O36: =H36*L36
A37: 31 | B37: =C36 | C37: =EDATE('Curve_Interface'!$F$7,3*30) | D37: =(C37-B37)/360 | E37: =(C37-B37)/365 | F37: =(C37-VAL_DATE)/365 | G37: =IFERROR(INDEX('Curve_Interface'!$L$8:$L$40,MATCH(C37,'Curve_Interface'!$K$8:$K$40,1))*(INDEX('Curve_Interface'!$L$8:$L$40,MATCH(C37,'Curve_Interface'!$K$8:$K$40,1)+1)/INDEX('Curve_Interface'!$L$8:$L$40,MATCH(C37,'Curve_Interface'!$K$8:$K$40,1)))^((C37-INDEX('Curve_Interface'!$K$8:$K$40,MATCH(C37,'Curve_Interface'!$K$8:$K$40,1)))/(INDEX('Curve_Interface'!$K$8:$K$40,MATCH(C37,'Curve_Interface'!$K$8:$K$40,1)+1)-INDEX('Curve_Interface'!$K$8:$K$40,MATCH(C37,'Curve_Interface'!$K$8:$K$40,1)))),INDEX('Curve_Interface'!$L$8:$L$40,MATCH(C37,'Curve_Interface'!$K$8:$K$40,1))) | H37: =IFERROR(INDEX('Curve_Interface'!$L$8:$L$40,MATCH((B37+C37)/2,'Curve_Interface'!$K$8:$K$40,1))*(INDEX('Curve_Interface'!$L$8:$L$40,MATCH((B37+C37)/2,'Curve_Interface'!$K$8:$K$40,1)+1)/INDEX('Curve_Interface'!$L$8:$L$40,MATCH((B37+C37)/2,'Curve_Interface'!$K$8:$K$40,1)))^(((B37+C37)/2-INDEX('Curve_Interface'!$K$8:$K$40,MATCH((B37+C37)/2,'Curve_Interface'!$K$8:$K$40,1)))/(INDEX('Curve_Interface'!$K$8:$K$40,MATCH((B37+C37)/2,'Curve_Interface'!$K$8:$K$40,1)+1)-INDEX('Curve_Interface'!$K$8:$K$40,MATCH((B37+C37)/2,'Curve_Interface'!$K$8:$K$40,1)))),INDEX('Curve_Interface'!$L$8:$L$40,MATCH((B37+C37)/2,'Curve_Interface'!$K$8:$K$40,1))) | I37: =INDEX(Hazard_Bootstrap!$D$7:$D$12,MIN(COUNTIF(Hazard_Bootstrap!$B$7:$B$12,"<"&C37)+1,6)) | J37: =K36 | K37: =J37*EXP(-I37*E37) | L37: =J37-K37 | M37: =D37*G37*K37 | N37: =(D37/2)*H37*L37 | O37: =H37*L37
A38: 32 | B38: =C37 | C38: =EDATE('Curve_Interface'!$F$7,3*31) | D38: =(C38-B38)/360 | E38: =(C38-B38)/365 | F38: =(C38-VAL_DATE)/365 | G38: =IFERROR(INDEX('Curve_Interface'!$L$8:$L$40,MATCH(C38,'Curve_Interface'!$K$8:$K$40,1))*(INDEX('Curve_Interface'!$L$8:$L$40,MATCH(C38,'Curve_Interface'!$K$8:$K$40,1)+1)/INDEX('Curve_Interface'!$L$8:$L$40,MATCH(C38,'Curve_Interface'!$K$8:$K$40,1)))^((C38-INDEX('Curve_Interface'!$K$8:$K$40,MATCH(C38,'Curve_Interface'!$K$8:$K$40,1)))/(INDEX('Curve_Interface'!$K$8:$K$40,MATCH(C38,'Curve_Interface'!$K$8:$K$40,1)+1)-INDEX('Curve_Interface'!$K$8:$K$40,MATCH(C38,'Curve_Interface'!$K$8:$K$40,1)))),INDEX('Curve_Interface'!$L$8:$L$40,MATCH(C38,'Curve_Interface'!$K$8:$K$40,1))) | H38: =IFERROR(INDEX('Curve_Interface'!$L$8:$L$40,MATCH((B38+C38)/2,'Curve_Interface'!$K$8:$K$40,1))*(INDEX('Curve_Interface'!$L$8:$L$40,MATCH((B38+C38)/2,'Curve_Interface'!$K$8:$K$40,1)+1)/INDEX('Curve_Interface'!$L$8:$L$40,MATCH((B38+C38)/2,'Curve_Interface'!$K$8:$K$40,1)))^(((B38+C38)/2-INDEX('Curve_Interface'!$K$8:$K$40,MATCH((B38+C38)/2,'Curve_Interface'!$K$8:$K$40,1)))/(INDEX('Curve_Interface'!$K$8:$K$40,MATCH((B38+C38)/2,'Curve_Interface'!$K$8:$K$40,1)+1)-INDEX('Curve_Interface'!$K$8:$K$40,MATCH((B38+C38)/2,'Curve_Interface'!$K$8:$K$40,1)))),INDEX('Curve_Interface'!$L$8:$L$40,MATCH((B38+C38)/2,'Curve_Interface'!$K$8:$K$40,1))) | I38: =INDEX(Hazard_Bootstrap!$D$7:$D$12,MIN(COUNTIF(Hazard_Bootstrap!$B$7:$B$12,"<"&C38)+1,6)) | J38: =K37 | K38: =J38*EXP(-I38*E38) | L38: =J38-K38 | M38: =D38*G38*K38 | N38: =(D38/2)*H38*L38 | O38: =H38*L38
A39: 33 | B39: =C38 | C39: =EDATE('Curve_Interface'!$F$7,3*32) | D39: =(C39-B39)/360 | E39: =(C39-B39)/365 | F39: =(C39-VAL_DATE)/365 | G39: =IFERROR(INDEX('Curve_Interface'!$L$8:$L$40,MATCH(C39,'Curve_Interface'!$K$8:$K$40,1))*(INDEX('Curve_Interface'!$L$8:$L$40,MATCH(C39,'Curve_Interface'!$K$8:$K$40,1)+1)/INDEX('Curve_Interface'!$L$8:$L$40,MATCH(C39,'Curve_Interface'!$K$8:$K$40,1)))^((C39-INDEX('Curve_Interface'!$K$8:$K$40,MATCH(C39,'Curve_Interface'!$K$8:$K$40,1)))/(INDEX('Curve_Interface'!$K$8:$K$40,MATCH(C39,'Curve_Interface'!$K$8:$K$40,1)+1)-INDEX('Curve_Interface'!$K$8:$K$40,MATCH(C39,'Curve_Interface'!$K$8:$K$40,1)))),INDEX('Curve_Interface'!$L$8:$L$40,MATCH(C39,'Curve_Interface'!$K$8:$K$40,1))) | H39: =IFERROR(INDEX('Curve_Interface'!$L$8:$L$40,MATCH((B39+C39)/2,'Curve_Interface'!$K$8:$K$40,1))*(INDEX('Curve_Interface'!$L$8:$L$40,MATCH((B39+C39)/2,'Curve_Interface'!$K$8:$K$40,1)+1)/INDEX('Curve_Interface'!$L$8:$L$40,MATCH((B39+C39)/2,'Curve_Interface'!$K$8:$K$40,1)))^(((B39+C39)/2-INDEX('Curve_Interface'!$K$8:$K$40,MATCH((B39+C39)/2,'Curve_Interface'!$K$8:$K$40,1)))/(INDEX('Curve_Interface'!$K$8:$K$40,MATCH((B39+C39)/2,'Curve_Interface'!$K$8:$K$40,1)+1)-INDEX('Curve_Interface'!$K$8:$K$40,MATCH((B39+C39)/2,'Curve_Interface'!$K$8:$K$40,1)))),INDEX('Curve_Interface'!$L$8:$L$40,MATCH((B39+C39)/2,'Curve_Interface'!$K$8:$K$40,1))) | I39: =INDEX(Hazard_Bootstrap!$D$7:$D$12,MIN(COUNTIF(Hazard_Bootstrap!$B$7:$B$12,"<"&C39)+1,6)) | J39: =K38 | K39: =J39*EXP(-I39*E39) | L39: =J39-K39 | M39: =D39*G39*K39 | N39: =(D39/2)*H39*L39 | O39: =H39*L39
A40: 34 | B40: =C39 | C40: =EDATE('Curve_Interface'!$F$7,3*33) | D40: =(C40-B40)/360 | E40: =(C40-B40)/365 | F40: =(C40-VAL_DATE)/365 | G40: =IFERROR(INDEX('Curve_Interface'!$L$8:$L$40,MATCH(C40,'Curve_Interface'!$K$8:$K$40,1))*(INDEX('Curve_Interface'!$L$8:$L$40,MATCH(C40,'Curve_Interface'!$K$8:$K$40,1)+1)/INDEX('Curve_Interface'!$L$8:$L$40,MATCH(C40,'Curve_Interface'!$K$8:$K$40,1)))^((C40-INDEX('Curve_Interface'!$K$8:$K$40,MATCH(C40,'Curve_Interface'!$K$8:$K$40,1)))/(INDEX('Curve_Interface'!$K$8:$K$40,MATCH(C40,'Curve_Interface'!$K$8:$K$40,1)+1)-INDEX('Curve_Interface'!$K$8:$K$40,MATCH(C40,'Curve_Interface'!$K$8:$K$40,1)))),INDEX('Curve_Interface'!$L$8:$L$40,MATCH(C40,'Curve_Interface'!$K$8:$K$40,1))) | H40: =IFERROR(INDEX('Curve_Interface'!$L$8:$L$40,MATCH((B40+C40)/2,'Curve_Interface'!$K$8:$K$40,1))*(INDEX('Curve_Interface'!$L$8:$L$40,MATCH((B40+C40)/2,'Curve_Interface'!$K$8:$K$40,1)+1)/INDEX('Curve_Interface'!$L$8:$L$40,MATCH((B40+C40)/2,'Curve_Interface'!$K$8:$K$40,1)))^(((B40+C40)/2-INDEX('Curve_Interface'!$K$8:$K$40,MATCH((B40+C40)/2,'Curve_Interface'!$K$8:$K$40,1)))/(INDEX('Curve_Interface'!$K$8:$K$40,MATCH((B40+C40)/2,'Curve_Interface'!$K$8:$K$40,1)+1)-INDEX('Curve_Interface'!$K$8:$K$40,MATCH((B40+C40)/2,'Curve_Interface'!$K$8:$K$40,1)))),INDEX('Curve_Interface'!$L$8:$L$40,MATCH((B40+C40)/2,'Curve_Interface'!$K$8:$K$40,1))) | I40: =INDEX(Hazard_Bootstrap!$D$7:$D$12,MIN(COUNTIF(Hazard_Bootstrap!$B$7:$B$12,"<"&C40)+1,6)) | J40: =K39 | K40: =J40*EXP(-I40*E40) | L40: =J40-K40 | M40: =D40*G40*K40 | N40: =(D40/2)*H40*L40 | O40: =H40*L40
A41: 35 | B41: =C40 | C41: =EDATE('Curve_Interface'!$F$7,3*34) | D41: =(C41-B41)/360 | E41: =(C41-B41)/365 | F41: =(C41-VAL_DATE)/365 | G41: =IFERROR(INDEX('Curve_Interface'!$L$8:$L$40,MATCH(C41,'Curve_Interface'!$K$8:$K$40,1))*(INDEX('Curve_Interface'!$L$8:$L$40,MATCH(C41,'Curve_Interface'!$K$8:$K$40,1)+1)/INDEX('Curve_Interface'!$L$8:$L$40,MATCH(C41,'Curve_Interface'!$K$8:$K$40,1)))^((C41-INDEX('Curve_Interface'!$K$8:$K$40,MATCH(C41,'Curve_Interface'!$K$8:$K$40,1)))/(INDEX('Curve_Interface'!$K$8:$K$40,MATCH(C41,'Curve_Interface'!$K$8:$K$40,1)+1)-INDEX('Curve_Interface'!$K$8:$K$40,MATCH(C41,'Curve_Interface'!$K$8:$K$40,1)))),INDEX('Curve_Interface'!$L$8:$L$40,MATCH(C41,'Curve_Interface'!$K$8:$K$40,1))) | H41: =IFERROR(INDEX('Curve_Interface'!$L$8:$L$40,MATCH((B41+C41)/2,'Curve_Interface'!$K$8:$K$40,1))*(INDEX('Curve_Interface'!$L$8:$L$40,MATCH((B41+C41)/2,'Curve_Interface'!$K$8:$K$40,1)+1)/INDEX('Curve_Interface'!$L$8:$L$40,MATCH((B41+C41)/2,'Curve_Interface'!$K$8:$K$40,1)))^(((B41+C41)/2-INDEX('Curve_Interface'!$K$8:$K$40,MATCH((B41+C41)/2,'Curve_Interface'!$K$8:$K$40,1)))/(INDEX('Curve_Interface'!$K$8:$K$40,MATCH((B41+C41)/2,'Curve_Interface'!$K$8:$K$40,1)+1)-INDEX('Curve_Interface'!$K$8:$K$40,MATCH((B41+C41)/2,'Curve_Interface'!$K$8:$K$40,1)))),INDEX('Curve_Interface'!$L$8:$L$40,MATCH((B41+C41)/2,'Curve_Interface'!$K$8:$K$40,1))) | I41: =INDEX(Hazard_Bootstrap!$D$7:$D$12,MIN(COUNTIF(Hazard_Bootstrap!$B$7:$B$12,"<"&C41)+1,6)) | J41: =K40 | K41: =J41*EXP(-I41*E41) | L41: =J41-K41 | M41: =D41*G41*K41 | N41: =(D41/2)*H41*L41 | O41: =H41*L41
A42: 36 | B42: =C41 | C42: =EDATE('Curve_Interface'!$F$7,3*35) | D42: =(C42-B42)/360 | E42: =(C42-B42)/365 | F42: =(C42-VAL_DATE)/365 | G42: =IFERROR(INDEX('Curve_Interface'!$L$8:$L$40,MATCH(C42,'Curve_Interface'!$K$8:$K$40,1))*(INDEX('Curve_Interface'!$L$8:$L$40,MATCH(C42,'Curve_Interface'!$K$8:$K$40,1)+1)/INDEX('Curve_Interface'!$L$8:$L$40,MATCH(C42,'Curve_Interface'!$K$8:$K$40,1)))^((C42-INDEX('Curve_Interface'!$K$8:$K$40,MATCH(C42,'Curve_Interface'!$K$8:$K$40,1)))/(INDEX('Curve_Interface'!$K$8:$K$40,MATCH(C42,'Curve_Interface'!$K$8:$K$40,1)+1)-INDEX('Curve_Interface'!$K$8:$K$40,MATCH(C42,'Curve_Interface'!$K$8:$K$40,1)))),INDEX('Curve_Interface'!$L$8:$L$40,MATCH(C42,'Curve_Interface'!$K$8:$K$40,1))) | H42: =IFERROR(INDEX('Curve_Interface'!$L$8:$L$40,MATCH((B42+C42)/2,'Curve_Interface'!$K$8:$K$40,1))*(INDEX('Curve_Interface'!$L$8:$L$40,MATCH((B42+C42)/2,'Curve_Interface'!$K$8:$K$40,1)+1)/INDEX('Curve_Interface'!$L$8:$L$40,MATCH((B42+C42)/2,'Curve_Interface'!$K$8:$K$40,1)))^(((B42+C42)/2-INDEX('Curve_Interface'!$K$8:$K$40,MATCH((B42+C42)/2,'Curve_Interface'!$K$8:$K$40,1)))/(INDEX('Curve_Interface'!$K$8:$K$40,MATCH((B42+C42)/2,'Curve_Interface'!$K$8:$K$40,1)+1)-INDEX('Curve_Interface'!$K$8:$K$40,MATCH((B42+C42)/2,'Curve_Interface'!$K$8:$K$40,1)))),INDEX('Curve_Interface'!$L$8:$L$40,MATCH((B42+C42)/2,'Curve_Interface'!$K$8:$K$40,1))) | I42: =INDEX(Hazard_Bootstrap!$D$7:$D$12,MIN(COUNTIF(Hazard_Bootstrap!$B$7:$B$12,"<"&C42)+1,6)) | J42: =K41 | K42: =J42*EXP(-I42*E42) | L42: =J42-K42 | M42: =D42*G42*K42 | N42: =(D42/2)*H42*L42 | O42: =H42*L42
A43: 37 | B43: =C42 | C43: =EDATE('Curve_Interface'!$F$7,3*36) | D43: =(C43-B43)/360 | E43: =(C43-B43)/365 | F43: =(C43-VAL_DATE)/365 | G43: =IFERROR(INDEX('Curve_Interface'!$L$8:$L$40,MATCH(C43,'Curve_Interface'!$K$8:$K$40,1))*(INDEX('Curve_Interface'!$L$8:$L$40,MATCH(C43,'Curve_Interface'!$K$8:$K$40,1)+1)/INDEX('Curve_Interface'!$L$8:$L$40,MATCH(C43,'Curve_Interface'!$K$8:$K$40,1)))^((C43-INDEX('Curve_Interface'!$K$8:$K$40,MATCH(C43,'Curve_Interface'!$K$8:$K$40,1)))/(INDEX('Curve_Interface'!$K$8:$K$40,MATCH(C43,'Curve_Interface'!$K$8:$K$40,1)+1)-INDEX('Curve_Interface'!$K$8:$K$40,MATCH(C43,'Curve_Interface'!$K$8:$K$40,1)))),INDEX('Curve_Interface'!$L$8:$L$40,MATCH(C43,'Curve_Interface'!$K$8:$K$40,1))) | H43: =IFERROR(INDEX('Curve_Interface'!$L$8:$L$40,MATCH((B43+C43)/2,'Curve_Interface'!$K$8:$K$40,1))*(INDEX('Curve_Interface'!$L$8:$L$40,MATCH((B43+C43)/2,'Curve_Interface'!$K$8:$K$40,1)+1)/INDEX('Curve_Interface'!$L$8:$L$40,MATCH((B43+C43)/2,'Curve_Interface'!$K$8:$K$40,1)))^(((B43+C43)/2-INDEX('Curve_Interface'!$K$8:$K$40,MATCH((B43+C43)/2,'Curve_Interface'!$K$8:$K$40,1)))/(INDEX('Curve_Interface'!$K$8:$K$40,MATCH((B43+C43)/2,'Curve_Interface'!$K$8:$K$40,1)+1)-INDEX('Curve_Interface'!$K$8:$K$40,MATCH((B43+C43)/2,'Curve_Interface'!$K$8:$K$40,1)))),INDEX('Curve_Interface'!$L$8:$L$40,MATCH((B43+C43)/2,'Curve_Interface'!$K$8:$K$40,1))) | I43: =INDEX(Hazard_Bootstrap!$D$7:$D$12,MIN(COUNTIF(Hazard_Bootstrap!$B$7:$B$12,"<"&C43)+1,6)) | J43: =K42 | K43: =J43*EXP(-I43*E43) | L43: =J43-K43 | M43: =D43*G43*K43 | N43: =(D43/2)*H43*L43 | O43: =H43*L43
A44: 38 | B44: =C43 | C44: =EDATE('Curve_Interface'!$F$7,3*37) | D44: =(C44-B44)/360 | E44: =(C44-B44)/365 | F44: =(C44-VAL_DATE)/365 | G44: =IFERROR(INDEX('Curve_Interface'!$L$8:$L$40,MATCH(C44,'Curve_Interface'!$K$8:$K$40,1))*(INDEX('Curve_Interface'!$L$8:$L$40,MATCH(C44,'Curve_Interface'!$K$8:$K$40,1)+1)/INDEX('Curve_Interface'!$L$8:$L$40,MATCH(C44,'Curve_Interface'!$K$8:$K$40,1)))^((C44-INDEX('Curve_Interface'!$K$8:$K$40,MATCH(C44,'Curve_Interface'!$K$8:$K$40,1)))/(INDEX('Curve_Interface'!$K$8:$K$40,MATCH(C44,'Curve_Interface'!$K$8:$K$40,1)+1)-INDEX('Curve_Interface'!$K$8:$K$40,MATCH(C44,'Curve_Interface'!$K$8:$K$40,1)))),INDEX('Curve_Interface'!$L$8:$L$40,MATCH(C44,'Curve_Interface'!$K$8:$K$40,1))) | H44: =IFERROR(INDEX('Curve_Interface'!$L$8:$L$40,MATCH((B44+C44)/2,'Curve_Interface'!$K$8:$K$40,1))*(INDEX('Curve_Interface'!$L$8:$L$40,MATCH((B44+C44)/2,'Curve_Interface'!$K$8:$K$40,1)+1)/INDEX('Curve_Interface'!$L$8:$L$40,MATCH((B44+C44)/2,'Curve_Interface'!$K$8:$K$40,1)))^(((B44+C44)/2-INDEX('Curve_Interface'!$K$8:$K$40,MATCH((B44+C44)/2,'Curve_Interface'!$K$8:$K$40,1)))/(INDEX('Curve_Interface'!$K$8:$K$40,MATCH((B44+C44)/2,'Curve_Interface'!$K$8:$K$40,1)+1)-INDEX('Curve_Interface'!$K$8:$K$40,MATCH((B44+C44)/2,'Curve_Interface'!$K$8:$K$40,1)))),INDEX('Curve_Interface'!$L$8:$L$40,MATCH((B44+C44)/2,'Curve_Interface'!$K$8:$K$40,1))) | I44: =INDEX(Hazard_Bootstrap!$D$7:$D$12,MIN(COUNTIF(Hazard_Bootstrap!$B$7:$B$12,"<"&C44)+1,6)) | J44: =K43 | K44: =J44*EXP(-I44*E44) | L44: =J44-K44 | M44: =D44*G44*K44 | N44: =(D44/2)*H44*L44 | O44: =H44*L44
A45: 39 | B45: =C44 | C45: =EDATE('Curve_Interface'!$F$7,3*38) | D45: =(C45-B45)/360 | E45: =(C45-B45)/365 | F45: =(C45-VAL_DATE)/365 | G45: =IFERROR(INDEX('Curve_Interface'!$L$8:$L$40,MATCH(C45,'Curve_Interface'!$K$8:$K$40,1))*(INDEX('Curve_Interface'!$L$8:$L$40,MATCH(C45,'Curve_Interface'!$K$8:$K$40,1)+1)/INDEX('Curve_Interface'!$L$8:$L$40,MATCH(C45,'Curve_Interface'!$K$8:$K$40,1)))^((C45-INDEX('Curve_Interface'!$K$8:$K$40,MATCH(C45,'Curve_Interface'!$K$8:$K$40,1)))/(INDEX('Curve_Interface'!$K$8:$K$40,MATCH(C45,'Curve_Interface'!$K$8:$K$40,1)+1)-INDEX('Curve_Interface'!$K$8:$K$40,MATCH(C45,'Curve_Interface'!$K$8:$K$40,1)))),INDEX('Curve_Interface'!$L$8:$L$40,MATCH(C45,'Curve_Interface'!$K$8:$K$40,1))) | H45: =IFERROR(INDEX('Curve_Interface'!$L$8:$L$40,MATCH((B45+C45)/2,'Curve_Interface'!$K$8:$K$40,1))*(INDEX('Curve_Interface'!$L$8:$L$40,MATCH((B45+C45)/2,'Curve_Interface'!$K$8:$K$40,1)+1)/INDEX('Curve_Interface'!$L$8:$L$40,MATCH((B45+C45)/2,'Curve_Interface'!$K$8:$K$40,1)))^(((B45+C45)/2-INDEX('Curve_Interface'!$K$8:$K$40,MATCH((B45+C45)/2,'Curve_Interface'!$K$8:$K$40,1)))/(INDEX('Curve_Interface'!$K$8:$K$40,MATCH((B45+C45)/2,'Curve_Interface'!$K$8:$K$40,1)+1)-INDEX('Curve_Interface'!$K$8:$K$40,MATCH((B45+C45)/2,'Curve_Interface'!$K$8:$K$40,1)))),INDEX('Curve_Interface'!$L$8:$L$40,MATCH((B45+C45)/2,'Curve_Interface'!$K$8:$K$40,1))) | I45: =INDEX(Hazard_Bootstrap!$D$7:$D$12,MIN(COUNTIF(Hazard_Bootstrap!$B$7:$B$12,"<"&C45)+1,6)) | J45: =K44 | K45: =J45*EXP(-I45*E45) | L45: =J45-K45 | M45: =D45*G45*K45 | N45: =(D45/2)*H45*L45 | O45: =H45*L45
A46: 40 | B46: =C45 | C46: =EDATE('Curve_Interface'!$F$7,3*39) | D46: =(C46-B46)/360 | E46: =(C46-B46)/365 | F46: =(C46-VAL_DATE)/365 | G46: =IFERROR(INDEX('Curve_Interface'!$L$8:$L$40,MATCH(C46,'Curve_Interface'!$K$8:$K$40,1))*(INDEX('Curve_Interface'!$L$8:$L$40,MATCH(C46,'Curve_Interface'!$K$8:$K$40,1)+1)/INDEX('Curve_Interface'!$L$8:$L$40,MATCH(C46,'Curve_Interface'!$K$8:$K$40,1)))^((C46-INDEX('Curve_Interface'!$K$8:$K$40,MATCH(C46,'Curve_Interface'!$K$8:$K$40,1)))/(INDEX('Curve_Interface'!$K$8:$K$40,MATCH(C46,'Curve_Interface'!$K$8:$K$40,1)+1)-INDEX('Curve_Interface'!$K$8:$K$40,MATCH(C46,'Curve_Interface'!$K$8:$K$40,1)))),INDEX('Curve_Interface'!$L$8:$L$40,MATCH(C46,'Curve_Interface'!$K$8:$K$40,1))) | H46: =IFERROR(INDEX('Curve_Interface'!$L$8:$L$40,MATCH((B46+C46)/2,'Curve_Interface'!$K$8:$K$40,1))*(INDEX('Curve_Interface'!$L$8:$L$40,MATCH((B46+C46)/2,'Curve_Interface'!$K$8:$K$40,1)+1)/INDEX('Curve_Interface'!$L$8:$L$40,MATCH((B46+C46)/2,'Curve_Interface'!$K$8:$K$40,1)))^(((B46+C46)/2-INDEX('Curve_Interface'!$K$8:$K$40,MATCH((B46+C46)/2,'Curve_Interface'!$K$8:$K$40,1)))/(INDEX('Curve_Interface'!$K$8:$K$40,MATCH((B46+C46)/2,'Curve_Interface'!$K$8:$K$40,1)+1)-INDEX('Curve_Interface'!$K$8:$K$40,MATCH((B46+C46)/2,'Curve_Interface'!$K$8:$K$40,1)))),INDEX('Curve_Interface'!$L$8:$L$40,MATCH((B46+C46)/2,'Curve_Interface'!$K$8:$K$40,1))) | I46: =INDEX(Hazard_Bootstrap!$D$7:$D$12,MIN(COUNTIF(Hazard_Bootstrap!$B$7:$B$12,"<"&C46)+1,6)) | J46: =K45 | K46: =J46*EXP(-I46*E46) | L46: =J46-K46 | M46: =D46*G46*K46 | N46: =(D46/2)*H46*L46 | O46: =H46*L46

Sheet CDS_Pricer
A1: CDS_Pricer
A2: Price a CDS off the SOFR + hazard curves (protection − premium legs)
A4: Notional | B4: =CDS_Parameters!$B$9
A5: Recovery R | B5: =CDS_Parameters!$B$8
A6: Contractual coupon (bp) | B6: =CDS_Parameters!$B$10 | C6: Overtype to price an off-market coupon.
A7: Maturity (tenor yrs) | B7: 5
A8: Maturity date | B8: =EDATE('Curve_Interface'!$F$7,3*(4*B7-1))
A9: Direction | B9: =CDS_Parameters!$B$15
A11: RESULTS
A12: RPV01 (risky annuity) | B12: =SUMIF(CDS_Schedule!$C$7:$C$46,"<="&B8,CDS_Schedule!$M$7:$M$46)+SUMIF(CDS_Schedule!$C$7:$C$46,"<="&B8,CDS_Schedule!$N$7:$N$46) | C12: Scheduled + accrual-on-default.
A13: Protection PV | B13: =B4*(1-B5)*SUMIF(CDS_Schedule!$C$7:$C$46,"<="&B8,CDS_Schedule!$O$7:$O$46)
A14: Premium PV (@ coupon) | B14: =B4*(B6/10000)*B12
A15: Par spread (bp) | B15: =(1-B5)*SUMIF(CDS_Schedule!$C$7:$C$46,"<="&B8,CDS_Schedule!$O$7:$O$46)/B12*10000 | C15: Coupon that makes PV=0.
A16: PV — protection buyer | B16: =B13-B14 | C16: Protection − Premium.
A17: PV to your direction | B17: =IF(B9="Buy protection",B13-B14,B14-B13)
A18: Upfront (% notional) | B18: =B17/B4*100
A21: RISK MEASURES (analytic, first-order)
A22: CS01 (per +1bp spread) | B22: =B4*B12*0.0001 | C22: Spread DV01 = Notional*RPV01*1bp.
A23: IR01 / DV01 (per +1bp SOFR) | B23: =-(B4*(1-B5)*SUMPRODUCT((CDS_Schedule!$C$7:$C$46<=B8)*CDS_Schedule!$O$7:$O$46*CDS_Schedule!$F$7:$F$46)-B4*(B6/10000)*SUMPRODUCT((CDS_Schedule!$C$7:$C$46<=B8)*(CDS_Schedule!$M$7:$M$46+CDS_Schedule!$N$7:$N$46)*CDS_Schedule!$F$7:$F$46))*0.0001 | C23: Net-leg dollar duration x 1bp (small for CDS).
A24: Rec01 (per +1% recovery) | B24: =-B4*SUMIF(CDS_Schedule!$C$7:$C$46,"<="&B8,CDS_Schedule!$O$7:$O$46)*0.01 | C24: Sticky-hazard (hazards held; proper Rec01 re-fits spreads).
A25: Jump-to-default (immediate) | B25: =IF(B9="Buy protection",B4*(1-B5),-B4*(1-B5))-B17 | C25: Default-now P&L to your direction: LGD payout - current PV.

Sheet CDS_Validation
A1: CDS_Validation
A2: Internal checks + the flat-curve approximation s ≈ (1-R)·lambda
A4: Check | B4: Value | C4: Target
A5: Q(0) = 1 | B5: =CDS_Schedule!J7 | C5: 1 (exact)
A6: Survival monotone (min ΔPD ≥ 0) | B6: =MIN(CDS_Schedule!$L$7:$L$46) | C6: ≥ 0 ✓
A7: All hazards ≥ 0 | B7: =MIN(Hazard_Bootstrap!$D$7:$D$12) | C7: ≥ 0 ✓
A8: Q(T) in (0,1] | B8: =AND(MIN(CDS_Schedule!$K$7:$K$46)>0,MAX(CDS_Schedule!$K$7:$K$46)<=1) | C8: TRUE ✓
A9: Max |repricing error| (bp) | B9: =MAX(ABS(Hazard_Bootstrap!$J$7:$J$12)) | C9: →0 after Goal Seek (<0.01)
A11: Approx check: lambda ≈ s/(1-R) (exact only for a flat curve)
A12: Tenor | B12: Bootstrapped lambda | C12: s/(1-R) | D12: diff
A13: 1Y | B13: =Hazard_Bootstrap!D7 | C13: =CDS_Quotes!G7 | D13: =B13-C13
A14: 2Y | B14: =Hazard_Bootstrap!D8 | C14: =CDS_Quotes!G8 | D14: =B14-C14
A15: 3Y | B15: =Hazard_Bootstrap!D9 | C15: =CDS_Quotes!G9 | D15: =B15-C15
A16: 5Y | B16: =Hazard_Bootstrap!D10 | C16: =CDS_Quotes!G10 | D16: =B16-C16
A17: 7Y | B17: =Hazard_Bootstrap!D11 | C17: =CDS_Quotes!G11 | D17: =B17-C17
A18: 10Y | B18: =Hazard_Bootstrap!D12 | C18: =CDS_Quotes!G12 | D18: =B18-C18
