Workbook
Name VAL_DATE: Instructions!$B$9
Name HIST_START: Instructions!$B$10
Name HIST_END: Instructions!$B$11
Name PX_SRC: Instructions!$B$12
Name SOFR_TKR: Instructions!$B$13
Name S490_TKR: Instructions!$B$14
Name BOOT_MODE: Bootstrap!$G$4
Name BOOT_DFSPOT: Bootstrap!$D$4
Name BOOT_DATES: Bootstrap!$B$8:$B$72
Name BOOT_S: Bootstrap!$E$8:$E$72
Name BOOT_TAU0: Bootstrap!$D$8:$D$72
Name BOOT_TAUC: Bootstrap!$F$8:$F$72
Name BOOT_ANN: Bootstrap!$G$8:$G$72
Name BOOT_DF: Bootstrap!$H$8:$H$72
Name BOOT_T: Bootstrap!$C$8:$C$72
Name BOOT_ZERO: Bootstrap!$J$8:$J$72

Sheet Instructions
A1: USD SOFR Curve — Bloomberg Data Template
A2: Modern replication of the Lehman (2002) USD single-curve build: fixing + SR3/SR1 futures + SOFR OIS
A4: This workbook is a live Bloomberg template. Open it in Excel on a machine with the Bloomberg Add-in (BLPAPI) connected; the BDP / BDH / BDS formulas then populate automatically. Off-terminal (or in any non-Bloomberg viewer) the Bloomberg cells show #NAME? or blanks — that is expected, not a defect. Set the parameters below first; every date-driven pull references them.
A7: PARAMETERS (edit the yellow cells)
A8: Parameter | B8: Value | C8: Named ref | D8: Notes
A9: Valuation date | B9: =IF(Bootstrap!$G$4="Test 1",Testing!$D$5,IF(Bootstrap!$G$4="Test 2",Testing!$D$55,IF(Bootstrap!$G$4="Test 3",Testing!$D$105,DATE(2026,7,21)))) | C9: VAL_DATE | D9: Follows the active test case's curve date; otherwise the pinned capture date 07/21/2026. A test case must move the WHOLE workbook to its snapshot, or the bootstrap builds on one date and the targets come from another.
A10: Historical start | B10: 01/01/2018 | C10: HIST_START | D10: Start of BDH history windows.
A11: Historical end | B11: 07/20/2026 | C11: HIST_END | D11: End of BDH history windows.
A12: Price source | B12: BGN | C12: PX_SRC | D12: Bloomberg pricing source suffix used across every OIS ticker (BGN = Bloomberg Generic). Keep one source across all maturities.
A13: Overnight SOFR ticker | B13: SOFRRATE Index | C13: SOFR_TKR | D13: Published overnight SOFR fixing (NY Fed).
A14: Bloomberg SOFR curve | B14: YCSW0490 Index | C14: S490_TKR | D14: Bloomberg curve S490 (USD SOFR) — validation benchmark only.
A16: LEHMAN 2002 → MODERN USD CURVE MAPPING
A17: Lehman 2002 instrument | C17: Modern equivalent | E17: Bloomberg source
A18: LIBOR deposits | C18: SOFR fixing / short OIS | E18: SOFRRATE Index; USOSFR1Z..USOSFRF
A19: Eurodollar futures | C19: 3M SOFR futures (SR3) | E19: SFRA Comdty (CT chain)
A20: (1M money market) | C20: 1M SOFR futures (SR1) | E20: SERA Comdty (CT chain)
A21: LIBOR swaps | C21: SOFR OIS swaps | E21: USOSFR2..USOSFR50 BGN Curncy
A22: Dealer curve | C22: Bloomberg S490 (validation) | E22: YCSW0490 Index
A24: BOOTSTRAP METHODOLOGY — one discount curve, three liquid segments
A25: Short end (o/n – ~1Y) | B25: SOFR fixing + short OIS (1W,1M,3M,6M) anchor P(0,T) at the front — the modern LIBOR-deposit segment.
A26: Mid (~3M – ~5Y) | B26: SR3 3M-SOFR futures; implied rate = 100 − price, each covering one 3M IMM reference quarter — the modern Eurodollar-futures segment.
A27: Long end (~2Y – 50Y) | B27: SOFR OIS par swaps (mid = (bid+ask)/2) where deep liquidity lives — the modern LIBOR-swap segment.
A28: Bootstrap order | B28: Left → right: each instrument solves for the next discount-factor pillar given everything already solved to its left (sequential 1-D root find).
A30: Three differences vs. Lehman 2002 (where 'modern' is not a literal copy):
A31: • Single-curve: the SOFR curve both projects forwards AND discounts. Lehman 2002 was also single-curve (LIBOR did both), so a SOFR OIS build is CLOSER to the paper than a modern LIBOR build would be.
A32: • Compounding: SOFR is an overnight rate compounded daily in arrears over each period; LIBOR was a term rate set once. The OIS/futures legs carry a daily-compounding calc LIBOR did not need.
A33: • Futures convexity: SR3 (like Eurodollar) futures need a small convexity adjustment before the implied rate enters the curve. A first pass can omit it and report the bias against the S490 benchmark.
A35: TABS IN THIS WORKBOOK
A36: Charts | B36: Curve visuals — zero curve, discount factors, and V1-vs-V2 forward comparison.
A37: 1. SOFR_Fixings | B37: Overnight SOFR fixing — current (BDP) + daily history (BDH).
A38: 2. SOFR_Futures | B38: SR3 (3M) and SR1 (1M) SOFR futures chains + fields + implied rate = 100 − price.
A39: 3. SOFR_OIS_Quotes | B39: Full USOSFR OIS strip (1W–50Y): bid / ask / last + mid. Bootstrap-set flagged.
A40: 4. Bootstrap | B40: Purely-OIS bootstrap. The production curve — Swap_Pricer, Curve_Interface, and CDS all use it.
A41: Bootstrap - the single production SOFR curve, purely from OIS quotes. (The former Bootstrap_Lehman futures variant has been removed.) | B41: Lehman methodology: short OIS + SR3 futures (1Y–5Y) + OIS swaps. Compare col H vs the OIS Bootstrap.
A42: Curve_Interface | B42: Shared D(0,t): interpolates the SOFR curve to ANY date (quarterly CDS dates demo). Used by Swap_Pricer + CDS.
A43: CDS_Parameters | B43: Credit assumptions: recovery, notional, coupon, direction (recovery is an INPUT).
A44: CDS_Quotes | B44: Single-name CDS par spreads (BDP ticker, or manual demo). One entity, one seniority.
A45: CDS_Schedule | B45: Quarterly premium/default schedule to 10Y; DF from the SOFR curve, survival from hazards.
A46: Hazard_Bootstrap | B46: Piecewise-constant hazard curve; s/(1-R) default, Goal-Seek the error to 0 for exact fit.
A47: CDS_Pricer | B47: Prices a CDS off both curves: protection − premium, par spread, upfront, CS01.
... A51: 7. Fwd_Interp | B51: Zhou 2002 forward interpolation: V1 piecewise-flat vs V2 piecewise-quadratic forwards.
A53: DO NOT substitute these (wrong instruments):
A54: • TSFR1M/3M/6M/12M Index — Term SOFR benchmarks, NOT overnight-SOFR OIS calibration instruments.
A55: • USISSO02/05/10/30 Index — ICE Swap Rate fixings, NOT the live OIS quote strip needed to bootstrap.
A56: • Use PX midpoint (bid+ask)/2 for construction; use PX_LAST only where bid/ask are unavailable.
A58: Licensing: Bloomberg data is licensed and entitlement-dependent — do NOT redistribute pulled values or commit them to a public repository. This template ships formulas only, no data. Some static convention fields may return N/A under your entitlement; use FLDS <GO> on the security to find the enabled mnemonic.

Sheet Method
A1: USD SOFR curve and CDS module - build method
A2: Order of construction. Each step names the sheet that does the work.
A4: STEP 1 | B4: Pull the OIS strip | C4: SOFR_OIS_Quotes
C5: 32 tickers, USOSFR1Z to USOSFR50, source BGN (Instructions!B12).
C6: E/F = BDP PX_BID / PX_ASK. H = (bid+ask)/2. Curve Side = Mid, matching S490.
C7: H falls back to J (frozen S490 mids) when BDP is unavailable, so the curve always builds.
C8: N:S reconciles the BDP pull against a Bloomberg curve export.
A10: STEP 2 | B10: Dates and settlement | C10: Bootstrap col B
C11: Spot = VAL_DATE + 2 business days. Maturities = spot anniversaries.
C12: Modified following, weekends only, no holiday calendar.
C13: Bloomberg rolls 07/23/2033 to 07/25/2033; plain EDATE does not.
C14: Settle Date = curve date on the S490 screen, so DF(settle) = 1. No spot-lag stub.
A16: STEP 3 | B16: Short end, 1W to 1Y | C16: Bootstrap rows 8-22
C17: Single-payment OIS. DF = 1 / (1 + S * tau)
C18: tau = ACT/360 measured from VAL_DATE, not from spot.
A20: STEP 4 | B20: Long end, 18M to 50Y | C20: Bootstrap rows 23-72
C21: Annual coupons. DF = (1 - S*A) / (1 + S*tau)
C22: A = sum of tau_i * DF_i over prior annual coupon dates (col G).
C23: 18M is off the annual grid: uses the annuity through 1Y and contributes nothing
C24: onward, so I23 = 0 and the 2Y accrual runs from 1Y.
A26: STEP 5 | B26: Gap years | C26: Bootstrap, interpolated rows
C27: 11Y, 13-14Y, 16-19Y, 21-24Y, 26-29Y, 31-39Y, 41-49Y are not quoted.
C28: Log-linear in DF between surrounding pillars = step-function forward.
C29: Confirmed on the S490 screen: Interpolation = Step Forward (Cont).
C30: Tested against the guide's method 1 (piecewise linear simple): 48x worse here.
A32: STEP 6 | B32: Long pillar solver | C32: Curve_Solver (hidden)
C33: Gap DFs feed the annuity of the pillar they interpolate from, which is circular.
C34: Each quoted pillar 12Y+ is bisection-solved so the par identity holds with its
C35: gap points inside the annuity.
C36: Par check: Bootstrap col R, residuals ~1e-13.
A38: STEP 7 | B38: Zero rates | C38: Bootstrap col J
C39: z = -ln(DF) / t, ACT/365 from VAL_DATE, continuously compounded.
A41: STEP 8 | B41: Validate against S490 | C41: Bloomberg_S490_Validation, Bootstrap T:W
C42: Col L = S490 zero curve, hard-coded from the 07/21/26 capture.
C43: Result: 32/32 pillars, max |dz| 0.397bp, max |dDF| 1.88e-05, 0.08bp from 2Y.
C44: Residual is simple interest vs Bloomberg's daily-compounded short OIS.
C45: It is not fitted out: every curve input is a pulled quote.
A47: STEP 9 | B47: Curve interface | C47: Curve_Interface
C48: Exposes D(0,t) for any date. Interpolation selector at J7.
C49: CDS_Schedule and Swap_Pricer each hold their own inline copy of the
C50: interpolation; all three read the J7 selector.
A52: STEP 10 | B52: Swap pricing | C52: Swap_Pricer
C53: Par = (DF_eff - DF_mat) / annuity. PV01 = notional * annuity * 1bp.
C54: B17 maturity override prices sub-annual and off-grid deals.
C55: Reprices its own inputs to <=0.16bp across 1Y-50Y.
C56: SWPM cross-check at A88.
A58: STEP 11 | B58: CDS hazard curve | C58: CDS_Quotes, Hazard_Bootstrap, Hazard_Solver
C59: Two-step pull per Help Desk H#1330731572:
C60: 1. BDP(ticker, "CDS_SPREAD_TICKER_nY") -> CDS ticker
C61: 2. BDP(ticker & " BEST Curncy", "PX_LAST") -> spread
C62: Hazard_Solver bisection-solves each piecewise-constant hazard. No Goal Seek.
C63: CDS_Parameters!B17 switches between bootstrap and a flat hazard.
A65: STEP 12 | B65: CDS pricing | C65: CDS_Schedule, CDS_Pricer
C66: Quarterly IMM grid. DF from Curve_Interface, survival from the hazard curve.
C67: Protection leg (1-R) * sum Z(t)*dQ(t)
C68: Premium leg S * [ sum d_i Z_i Q_i + 1/2 sum d_i Z_i (Q_i-1 - Q_i) ]
C69: CDS_Pricer rows 28+ give the CDSW settlement panel.
C70: No Bloomberg export of hazard rates exists, so the credit side has no external
C71: ground truth. Validate against CDSW output for a known trade.
A73: KNOWN GAPS
C74: CDS spreads on CDS_Quotes are demo values, not market.
C75: Short end prices ~0.15bp rich to Bloomberg (simple vs daily-compounded OIS).
C76: VAL_DATE = TODAY(). The frozen S490 comparison only lines up on 07/21/2026.
C77: SOFR_Futures feeds nothing and its pulls are switched off at B3.

Sheet Conventions
A1: Conventions
A2: OIS quote conventions (DES/FLDS) for representative tenors — record before you bootstrap
A4: Convention attribute | B4: BDP field (verify via FLDS) | C4: USOSFRC (3M) | D4: USOSFR1 (1Y) | E4: USOSFR5 (5Y) | F4: USOSFR30 (30Y)
A5: Currency | B5: CRNCY | C5: =IFERROR(BDP("USOSFRC BGN Curncy","CRNCY"),"ERROR PLZ FIX") | D5: =IFERROR(BDP("USOSFR1 BGN Curncy","CRNCY"),"ERROR PLZ FIX") | E5: =IFERROR(BDP("USOSFR5 BGN Curncy","CRNCY"),"ERROR PLZ FIX") | F5: =IFERROR(BDP("USOSFR30 BGN Curncy","CRNCY"),"ERROR PLZ FIX")
A6: Reference index | B6: — DES/SWPM manual — | C6: — DES/SWPM — | D6: — DES/SWPM — | E6: — DES/SWPM — | F6: — DES/SWPM —
A7: Spot / settlement lag | B7: — DES/SWPM manual — | C7: — DES/SWPM — | D7: — DES/SWPM — | E7: — DES/SWPM — | F7: — DES/SWPM —
A8: Effective date rule | B8: — DES/SWPM manual — | C8: — DES/SWPM — | D8: — DES/SWPM — | E8: — DES/SWPM — | F8: — DES/SWPM —
A9: Maturity date rule | B9: — DES/SWPM manual — | C9: — DES/SWPM — | D9: — DES/SWPM — | E9: — DES/SWPM — | F9: — DES/SWPM —
A10: Business-day calendar | B10: CALENDAR_CODE | C10: =IFERROR(BDP("USOSFRC BGN Curncy","CALENDAR_CODE"),"ERROR PLZ FIX") | D10: =IFERROR(BDP("USOSFR1 BGN Curncy","CALENDAR_CODE"),"ERROR PLZ FIX") | E10: =IFERROR(BDP("USOSFR5 BGN Curncy","CALENDAR_CODE"),"ERROR PLZ FIX") | F10: =IFERROR(BDP("USOSFR30 BGN Curncy","CALENDAR_CODE"),"ERROR PLZ FIX")
A11: Business-day convention | B11: — DES/SWPM manual — | C11: — DES/SWPM — | D11: — DES/SWPM — | E11: — DES/SWPM — | F11: — DES/SWPM —
A12: Fixed-leg day count | B12: DAY_CNT_DES | C12: =IFERROR(BDP("USOSFRC BGN Curncy","DAY_CNT_DES"),"ERROR PLZ FIX") | D12: =IFERROR(BDP("USOSFR1 BGN Curncy","DAY_CNT_DES"),"ERROR PLZ FIX") | E12: =IFERROR(BDP("USOSFR5 BGN Curncy","DAY_CNT_DES"),"ERROR PLZ FIX") | F12: =IFERROR(BDP("USOSFR30 BGN Curncy","DAY_CNT_DES"),"ERROR PLZ FIX")
A13: Fixed-leg pay frequency | B13: — DES/SWPM manual — | C13: — DES/SWPM — | D13: — DES/SWPM — | E13: — DES/SWPM — | F13: — DES/SWPM —
A14: Floating-leg day count | B14: — DES/SWPM manual — | C14: — DES/SWPM — | D14: — DES/SWPM — | E14: — DES/SWPM — | F14: — DES/SWPM —
A15: Floating-leg pay frequency | B15: — DES/SWPM manual — | C15: — DES/SWPM — | D15: — DES/SWPM — | E15: — DES/SWPM — | F15: — DES/SWPM —
A16: SOFR compounding method | B16: — DES/SWPM manual — | C16: — DES/SWPM — | D16: — DES/SWPM — | E16: — DES/SWPM — | F16: — DES/SWPM —
A17: Payment lag | B17: — DES/SWPM manual — | C17: — DES/SWPM — | D17: — DES/SWPM — | E17: — DES/SWPM — | F17: — DES/SWPM —
A18: Observation shift / lookback | B18: — DES/SWPM manual — | C18: — DES/SWPM — | D18: — DES/SWPM — | E18: — DES/SWPM — | F18: — DES/SWPM —
A19: End-of-month treatment | B19: — DES/SWPM manual — | C19: — DES/SWPM — | D19: — DES/SWPM — | E19: — DES/SWPM — | F19: — DES/SWPM —
A21: USD SOFR OIS — MARKET-STANDARD CONVENTIONS (confirm per-trade in DES)
A22: Reference index | B22: USD-SOFR (compounded in arrears)
A23: Spot / settlement lag | B23: T+2 US business days
A24: Effective date rule | B24: Spot (T+2), modified following
A25: Maturity date rule | B25: Effective + tenor, modified following
A26: Business-day convention | B26: Modified Following
A27: Fixed-leg day count | B27: ACT/360
A28: Fixed-leg pay frequency | B28: Annual (single payment if tenor ≤ 1Y)
A29: Floating-leg day count | B29: ACT/360
A30: Floating-leg pay frequency | B30: Annual (single payment if tenor ≤ 1Y)
A31: SOFR compounding method | B31: Daily compounded, ACT/360
A32: Payment lag | B32: 2 US business days
A33: Observation shift / lookback | B33: None (payment-delay convention, 2 bd)
A34: End-of-month treatment | B34: EOM applies
A36: SWPM <GO>: build a representative SOFR OIS for 1Y, 5Y and 30Y and export the cashflow schedule — that gives an authoritative set of pay/accrual dates to test your own date generation against. Rows marked '— DES/SWPM —' are leg-level conventions that a rate-quote ticker does not carry; read them from DES <GO> on an actual swap (the market-standard defaults above are the expected values). Where a BDP cell shows 'N/A — use FLDS', open FLDS <GO> to find the enabled field.

Sheet SOFR_Fixings
A1: SOFR_Fixings
A2: Overnight SOFR fixing (SOFRRATE Index) — the curve's shortest anchor point
A4: CURRENT FIXING
A5: Ticker | B5: Field | C5: Value (%) | D5: As of | E5: O/N stub (%)
A6: =SOFR_TKR | B6: PX_LAST | C6: =IFERROR(BDP(SOFR_TKR,"PX_LAST")+0,E6) | D6: =IFERROR(BDP(SOFR_TKR,"LAST_UPDATE_DT"),"ERROR PLZ FIX") | E6: 3.59 | F6: O/N fixing. Informational only since Step 3 sets DF(settle)=1. Live BDP overrides this cell.
A9: DAILY HISTORY
A10: The BDH array below spills down two columns (Date, PX_LAST) from the anchor cell A12. It uses the HIST_START / HIST_END parameters on the Instructions tab.
A11: Date | B11: SOFR PX_LAST (%)
A12: =IFERROR(BDH(SOFR_TKR,"PX_LAST",TEXT(HIST_START,"mm/dd/yyyy"),TEXT(HIST_END,"mm/dd/yyyy")),"ERROR PLZ FIX")

Sheet SOFR_OIS_Quotes
A1: SOFR_OIS_Quotes | J1: REAL MARKET DATA - S490 USD SOFR, Step Forward (Cont), Settle 07/21/26, Curve Side Mid | N1: RECONCILIATION vs the Bloomberg curve export
A2: USD fixed-vs-SOFR OIS strip (USOSFR…, BGN) — 1W to 50Y. Maturity & years are derived live from the tenor. | J2: S490 screen mids, frozen 07/21/26. Used only when BDP fails. | N2: Paste export bid/ask in N:O. Q/R/S = BDP minus export, bp. Mixed signs of a few tenths = ticked apart. Consistent shift = wrong source/field. | T2: =IF(Bootstrap!$G$4="Fixed (S490 07/21/26)","FIXED - BDP ignored, curve on the 07/21/26 capture","LIVE - BDP mid, falling back to the capture if unavailable")
A3: Spot (T+2): | B3: =WORKDAY(VAL_DATE,2) | C3: Maturity & Tenor(yrs) recompute from the tenor label + spot. | T3: Column H is the mid actually used. T is always the raw BDP mid, so the live-vs-fixed gap stays visible in either mode.
A4: Ticker root | B4: Tenor | C4: Maturity date | D4: Tenor (yrs) | E4: PX_BID | F4: PX_ASK | G4: PX_LAST | H4: Mid = (Bid+Ask)/2 | I4: In bootstrap set | J4: Manual MID (%) <- S490_Snapshot | K4: Source | M4: Dates modified-following, weekends only. Matches S490. | N4: Export Bid (paste) | O4: Export Ask (paste) | P4: Export Mid | Q4: d Bid (bp) | R4: d Ask (bp) | S4: d Mid (bp) | T4: Live mid (BDP only) | U4: d live - fixed (bp)
A5: USOSFR1Z | B5: 1W | C5: =IF(MONTH((IF(RIGHT(B5,1)="W",$B$3+7*VALUE(LEFT(B5,LEN(B5)-1)),IF(RIGHT(B5,1)="M",EDATE($B$3,VALUE(LEFT(B5,LEN(B5)-1))),EDATE($B$3,12*VALUE(LEFT(B5,LEN(B5)-1)))))+IF(WEEKDAY(IF(RIGHT(B5,1)="W",$B$3+7*VALUE(LEFT(B5,LEN(B5)-1)),IF(RIGHT(B5,1)="M",EDATE($B$3,VALUE(LEFT(B5,LEN(B5)-1))),EDATE($B$3,12*VALUE(LEFT(B5,LEN(B5)-1))))),2)=6,2,IF(WEEKDAY(IF(RIGHT(B5,1)="W",$B$3+7*VALUE(LEFT(B5,LEN(B5)-1)),IF(RIGHT(B5,1)="M",EDATE($B$3,VALUE(LEFT(B5,LEN(B5)-1))),EDATE($B$3,12*VALUE(LEFT(B5,LEN(B5)-1))))),2)=7,1,0))))<>MONTH(IF(RIGHT(B5,1)="W",$B$3+7*VALUE(LEFT(B5,LEN(B5)-1)),IF(RIGHT(B5,1)="M",EDATE($B$3,VALUE(LEFT(B5,LEN(B5)-1))),EDATE($B$3,12*VALUE(LEFT(B5,LEN(B5)-1)))))),(IF(RIGHT(B5,1)="W",$B$3+7*VALUE(LEFT(B5,LEN(B5)-1)),IF(RIGHT(B5,1)="M",EDATE($B$3,VALUE(LEFT(B5,LEN(B5)-1))),EDATE($B$3,12*VALUE(LEFT(B5,LEN(B5)-1)))))-IF(WEEKDAY(IF(RIGHT(B5,1)="W",$B$3+7*VALUE(LEFT(B5,LEN(B5)-1)),IF(RIGHT(B5,1)="M",EDATE($B$3,VALUE(LEFT(B5,LEN(B5)-1))),EDATE($B$3,12*VALUE(LEFT(B5,LEN(B5)-1))))),2)=6,1,IF(WEEKDAY(IF(RIGHT(B5,1)="W",$B$3+7*VALUE(LEFT(B5,LEN(B5)-1)),IF(RIGHT(B5,1)="M",EDATE($B$3,VALUE(LEFT(B5,LEN(B5)-1))),EDATE($B$3,12*VALUE(LEFT(B5,LEN(B5)-1))))),2)=7,2,0))),(IF(RIGHT(B5,1)="W",$B$3+7*VALUE(LEFT(B5,LEN(B5)-1)),IF(RIGHT(B5,1)="M",EDATE($B$3,VALUE(LEFT(B5,LEN(B5)-1))),EDATE($B$3,12*VALUE(LEFT(B5,LEN(B5)-1)))))+IF(WEEKDAY(IF(RIGHT(B5,1)="W",$B$3+7*VALUE(LEFT(B5,LEN(B5)-1)),IF(RIGHT(B5,1)="M",EDATE($B$3,VALUE(LEFT(B5,LEN(B5)-1))),EDATE($B$3,12*VALUE(LEFT(B5,LEN(B5)-1))))),2)=6,2,IF(WEEKDAY(IF(RIGHT(B5,1)="W",$B$3+7*VALUE(LEFT(B5,LEN(B5)-1)),IF(RIGHT(B5,1)="M",EDATE($B$3,VALUE(LEFT(B5,LEN(B5)-1))),EDATE($B$3,12*VALUE(LEFT(B5,LEN(B5)-1))))),2)=7,1,0)))) | D5: =(C5-$B$3)/365 | E5: =IFERROR(BDP(A5&" "&PX_SRC&" Curncy","PX_BID"),"ERROR PLZ FIX") | F5: =IFERROR(BDP(A5&" "&PX_SRC&" Curncy","PX_ASK"),"ERROR PLZ FIX") | G5: =IFERROR(BDP(A5&" "&PX_SRC&" Curncy","PX_LAST"),"ERROR PLZ FIX") | H5: =IFERROR(IF(Bootstrap!$G$4="Test 1",INDEX(Testing!$B$8:$B$47,MATCH(C5,Testing!$F$8:$F$47,0)),IF(Bootstrap!$G$4="Test 2",INDEX(Testing!$B$58:$B$97,MATCH(C5,Testing!$F$58:$F$97,0)),IF(Bootstrap!$G$4="Test 3",INDEX(Testing!$B$108:$B$147,MATCH(C5,Testing!$F$108:$F$147,0)),IF(Bootstrap!$G$4="Fixed (S490 07/21/26)",J5,IF(ISNUMBER(T5),T5,J5))))),J5) | I5: Y | J5: =IFERROR(INDEX(S490_Snapshot!$C$7:$C$38,MATCH(B5,S490_Snapshot!$B$7:$B$38,0)),"") | K5: S490_Snapshot | P5: =IF(COUNT(N5:O5)=2,(N5+O5)/2,"") | Q5: =IF(AND(ISNUMBER(N5),ISNUMBER(E5)),(E5-N5)*100,"") | R5: =IF(AND(ISNUMBER(O5),ISNUMBER(F5)),(F5-O5)*100,"") | S5: =IF(AND(ISNUMBER(P5),ISNUMBER(H5)),(H5-P5)*100,"") | T5: =IFERROR((E5+F5)/2,IFERROR(G5+0,"")) | U5: =IF(OR(T5="",NOT(ISNUMBER(J5))),"",(T5-J5)*100)
A6: USOSFR2Z | B6: 2W | C6: =IF(MONTH((IF(RIGHT(B6,1)="W",$B$3+7*VALUE(LEFT(B6,LEN(B6)-1)),IF(RIGHT(B6,1)="M",EDATE($B$3,VALUE(LEFT(B6,LEN(B6)-1))),EDATE($B$3,12*VALUE(LEFT(B6,LEN(B6)-1)))))+IF(WEEKDAY(IF(RIGHT(B6,1)="W",$B$3+7*VALUE(LEFT(B6,LEN(B6)-1)),IF(RIGHT(B6,1)="M",EDATE($B$3,VALUE(LEFT(B6,LEN(B6)-1))),EDATE($B$3,12*VALUE(LEFT(B6,LEN(B6)-1))))),2)=6,2,IF(WEEKDAY(IF(RIGHT(B6,1)="W",$B$3+7*VALUE(LEFT(B6,LEN(B6)-1)),IF(RIGHT(B6,1)="M",EDATE($B$3,VALUE(LEFT(B6,LEN(B6)-1))),EDATE($B$3,12*VALUE(LEFT(B6,LEN(B6)-1))))),2)=7,1,0))))<>MONTH(IF(RIGHT(B6,1)="W",$B$3+7*VALUE(LEFT(B6,LEN(B6)-1)),IF(RIGHT(B6,1)="M",EDATE($B$3,VALUE(LEFT(B6,LEN(B6)-1))),EDATE($B$3,12*VALUE(LEFT(B6,LEN(B6)-1)))))),(IF(RIGHT(B6,1)="W",$B$3+7*VALUE(LEFT(B6,LEN(B6)-1)),IF(RIGHT(B6,1)="M",EDATE($B$3,VALUE(LEFT(B6,LEN(B6)-1))),EDATE($B$3,12*VALUE(LEFT(B6,LEN(B6)-1)))))-IF(WEEKDAY(IF(RIGHT(B6,1)="W",$B$3+7*VALUE(LEFT(B6,LEN(B6)-1)),IF(RIGHT(B6,1)="M",EDATE($B$3,VALUE(LEFT(B6,LEN(B6)-1))),EDATE($B$3,12*VALUE(LEFT(B6,LEN(B6)-1))))),2)=6,1,IF(WEEKDAY(IF(RIGHT(B6,1)="W",$B$3+7*VALUE(LEFT(B6,LEN(B6)-1)),IF(RIGHT(B6,1)="M",EDATE($B$3,VALUE(LEFT(B6,LEN(B6)-1))),EDATE($B$3,12*VALUE(LEFT(B6,LEN(B6)-1))))),2)=7,2,0))),(IF(RIGHT(B6,1)="W",$B$3+7*VALUE(LEFT(B6,LEN(B6)-1)),IF(RIGHT(B6,1)="M",EDATE($B$3,VALUE(LEFT(B6,LEN(B6)-1))),EDATE($B$3,12*VALUE(LEFT(B6,LEN(B6)-1)))))+IF(WEEKDAY(IF(RIGHT(B6,1)="W",$B$3+7*VALUE(LEFT(B6,LEN(B6)-1)),IF(RIGHT(B6,1)="M",EDATE($B$3,VALUE(LEFT(B6,LEN(B6)-1))),EDATE($B$3,12*VALUE(LEFT(B6,LEN(B6)-1))))),2)=6,2,IF(WEEKDAY(IF(RIGHT(B6,1)="W",$B$3+7*VALUE(LEFT(B6,LEN(B6)-1)),IF(RIGHT(B6,1)="M",EDATE($B$3,VALUE(LEFT(B6,LEN(B6)-1))),EDATE($B$3,12*VALUE(LEFT(B6,LEN(B6)-1))))),2)=7,1,0)))) | D6: =(C6-$B$3)/365 | E6: =IFERROR(BDP(A6&" "&PX_SRC&" Curncy","PX_BID"),"ERROR PLZ FIX") | F6: =IFERROR(BDP(A6&" "&PX_SRC&" Curncy","PX_ASK"),"ERROR PLZ FIX") | G6: =IFERROR(BDP(A6&" "&PX_SRC&" Curncy","PX_LAST"),"ERROR PLZ FIX") | H6: =IFERROR(IF(Bootstrap!$G$4="Test 1",INDEX(Testing!$B$8:$B$47,MATCH(C6,Testing!$F$8:$F$47,0)),IF(Bootstrap!$G$4="Test 2",INDEX(Testing!$B$58:$B$97,MATCH(C6,Testing!$F$58:$F$97,0)),IF(Bootstrap!$G$4="Test 3",INDEX(Testing!$B$108:$B$147,MATCH(C6,Testing!$F$108:$F$147,0)),IF(Bootstrap!$G$4="Fixed (S490 07/21/26)",J6,IF(ISNUMBER(T6),T6,J6))))),J6) | J6: =IFERROR(INDEX(S490_Snapshot!$C$7:$C$38,MATCH(B6,S490_Snapshot!$B$7:$B$38,0)),"") | K6: S490_Snapshot | P6: =IF(COUNT(N6:O6)=2,(N6+O6)/2,"") | Q6: =IF(AND(ISNUMBER(N6),ISNUMBER(E6)),(E6-N6)*100,"") | R6: =IF(AND(ISNUMBER(O6),ISNUMBER(F6)),(F6-O6)*100,"") | S6: =IF(AND(ISNUMBER(P6),ISNUMBER(H6)),(H6-P6)*100,"") | T6: =IFERROR((E6+F6)/2,IFERROR(G6+0,"")) | U6: =IF(OR(T6="",NOT(ISNUMBER(J6))),"",(T6-J6)*100)
A7: USOSFR3Z | B7: 3W | C7: =IF(MONTH((IF(RIGHT(B7,1)="W",$B$3+7*VALUE(LEFT(B7,LEN(B7)-1)),IF(RIGHT(B7,1)="M",EDATE($B$3,VALUE(LEFT(B7,LEN(B7)-1))),EDATE($B$3,12*VALUE(LEFT(B7,LEN(B7)-1)))))+IF(WEEKDAY(IF(RIGHT(B7,1)="W",$B$3+7*VALUE(LEFT(B7,LEN(B7)-1)),IF(RIGHT(B7,1)="M",EDATE($B$3,VALUE(LEFT(B7,LEN(B7)-1))),EDATE($B$3,12*VALUE(LEFT(B7,LEN(B7)-1))))),2)=6,2,IF(WEEKDAY(IF(RIGHT(B7,1)="W",$B$3+7*VALUE(LEFT(B7,LEN(B7)-1)),IF(RIGHT(B7,1)="M",EDATE($B$3,VALUE(LEFT(B7,LEN(B7)-1))),EDATE($B$3,12*VALUE(LEFT(B7,LEN(B7)-1))))),2)=7,1,0))))<>MONTH(IF(RIGHT(B7,1)="W",$B$3+7*VALUE(LEFT(B7,LEN(B7)-1)),IF(RIGHT(B7,1)="M",EDATE($B$3,VALUE(LEFT(B7,LEN(B7)-1))),EDATE($B$3,12*VALUE(LEFT(B7,LEN(B7)-1)))))),(IF(RIGHT(B7,1)="W",$B$3+7*VALUE(LEFT(B7,LEN(B7)-1)),IF(RIGHT(B7,1)="M",EDATE($B$3,VALUE(LEFT(B7,LEN(B7)-1))),EDATE($B$3,12*VALUE(LEFT(B7,LEN(B7)-1)))))-IF(WEEKDAY(IF(RIGHT(B7,1)="W",$B$3+7*VALUE(LEFT(B7,LEN(B7)-1)),IF(RIGHT(B7,1)="M",EDATE($B$3,VALUE(LEFT(B7,LEN(B7)-1))),EDATE($B$3,12*VALUE(LEFT(B7,LEN(B7)-1))))),2)=6,1,IF(WEEKDAY(IF(RIGHT(B7,1)="W",$B$3+7*VALUE(LEFT(B7,LEN(B7)-1)),IF(RIGHT(B7,1)="M",EDATE($B$3,VALUE(LEFT(B7,LEN(B7)-1))),EDATE($B$3,12*VALUE(LEFT(B7,LEN(B7)-1))))),2)=7,2,0))),(IF(RIGHT(B7,1)="W",$B$3+7*VALUE(LEFT(B7,LEN(B7)-1)),IF(RIGHT(B7,1)="M",EDATE($B$3,VALUE(LEFT(B7,LEN(B7)-1))),EDATE($B$3,12*VALUE(LEFT(B7,LEN(B7)-1)))))+IF(WEEKDAY(IF(RIGHT(B7,1)="W",$B$3+7*VALUE(LEFT(B7,LEN(B7)-1)),IF(RIGHT(B7,1)="M",EDATE($B$3,VALUE(LEFT(B7,LEN(B7)-1))),EDATE($B$3,12*VALUE(LEFT(B7,LEN(B7)-1))))),2)=6,2,IF(WEEKDAY(IF(RIGHT(B7,1)="W",$B$3+7*VALUE(LEFT(B7,LEN(B7)-1)),IF(RIGHT(B7,1)="M",EDATE($B$3,VALUE(LEFT(B7,LEN(B7)-1))),EDATE($B$3,12*VALUE(LEFT(B7,LEN(B7)-1))))),2)=7,1,0)))) | D7: =(C7-$B$3)/365 | E7: =IFERROR(BDP(A7&" "&PX_SRC&" Curncy","PX_BID"),"ERROR PLZ FIX") | F7: =IFERROR(BDP(A7&" "&PX_SRC&" Curncy","PX_ASK"),"ERROR PLZ FIX") | G7: =IFERROR(BDP(A7&" "&PX_SRC&" Curncy","PX_LAST"),"ERROR PLZ FIX") | H7: =IFERROR(IF(Bootstrap!$G$4="Test 1",INDEX(Testing!$B$8:$B$47,MATCH(C7,Testing!$F$8:$F$47,0)),IF(Bootstrap!$G$4="Test 2",INDEX(Testing!$B$58:$B$97,MATCH(C7,Testing!$F$58:$F$97,0)),IF(Bootstrap!$G$4="Test 3",INDEX(Testing!$B$108:$B$147,MATCH(C7,Testing!$F$108:$F$147,0)),IF(Bootstrap!$G$4="Fixed (S490 07/21/26)",J7,IF(ISNUMBER(T7),T7,J7))))),J7) | J7: =IFERROR(INDEX(S490_Snapshot!$C$7:$C$38,MATCH(B7,S490_Snapshot!$B$7:$B$38,0)),"") | K7: S490_Snapshot | P7: =IF(COUNT(N7:O7)=2,(N7+O7)/2,"") | Q7: =IF(AND(ISNUMBER(N7),ISNUMBER(E7)),(E7-N7)*100,"") | R7: =IF(AND(ISNUMBER(O7),ISNUMBER(F7)),(F7-O7)*100,"") | S7: =IF(AND(ISNUMBER(P7),ISNUMBER(H7)),(H7-P7)*100,"") | T7: =IFERROR((E7+F7)/2,IFERROR(G7+0,"")) | U7: =IF(OR(T7="",NOT(ISNUMBER(J7))),"",(T7-J7)*100)
A8: USOSFRA | B8: 1M | C8: =IF(MONTH((IF(RIGHT(B8,1)="W",$B$3+7*VALUE(LEFT(B8,LEN(B8)-1)),IF(RIGHT(B8,1)="M",EDATE($B$3,VALUE(LEFT(B8,LEN(B8)-1))),EDATE($B$3,12*VALUE(LEFT(B8,LEN(B8)-1)))))+IF(WEEKDAY(IF(RIGHT(B8,1)="W",$B$3+7*VALUE(LEFT(B8,LEN(B8)-1)),IF(RIGHT(B8,1)="M",EDATE($B$3,VALUE(LEFT(B8,LEN(B8)-1))),EDATE($B$3,12*VALUE(LEFT(B8,LEN(B8)-1))))),2)=6,2,IF(WEEKDAY(IF(RIGHT(B8,1)="W",$B$3+7*VALUE(LEFT(B8,LEN(B8)-1)),IF(RIGHT(B8,1)="M",EDATE($B$3,VALUE(LEFT(B8,LEN(B8)-1))),EDATE($B$3,12*VALUE(LEFT(B8,LEN(B8)-1))))),2)=7,1,0))))<>MONTH(IF(RIGHT(B8,1)="W",$B$3+7*VALUE(LEFT(B8,LEN(B8)-1)),IF(RIGHT(B8,1)="M",EDATE($B$3,VALUE(LEFT(B8,LEN(B8)-1))),EDATE($B$3,12*VALUE(LEFT(B8,LEN(B8)-1)))))),(IF(RIGHT(B8,1)="W",$B$3+7*VALUE(LEFT(B8,LEN(B8)-1)),IF(RIGHT(B8,1)="M",EDATE($B$3,VALUE(LEFT(B8,LEN(B8)-1))),EDATE($B$3,12*VALUE(LEFT(B8,LEN(B8)-1)))))-IF(WEEKDAY(IF(RIGHT(B8,1)="W",$B$3+7*VALUE(LEFT(B8,LEN(B8)-1)),IF(RIGHT(B8,1)="M",EDATE($B$3,VALUE(LEFT(B8,LEN(B8)-1))),EDATE($B$3,12*VALUE(LEFT(B8,LEN(B8)-1))))),2)=6,1,IF(WEEKDAY(IF(RIGHT(B8,1)="W",$B$3+7*VALUE(LEFT(B8,LEN(B8)-1)),IF(RIGHT(B8,1)="M",EDATE($B$3,VALUE(LEFT(B8,LEN(B8)-1))),EDATE($B$3,12*VALUE(LEFT(B8,LEN(B8)-1))))),2)=7,2,0))),(IF(RIGHT(B8,1)="W",$B$3+7*VALUE(LEFT(B8,LEN(B8)-1)),IF(RIGHT(B8,1)="M",EDATE($B$3,VALUE(LEFT(B8,LEN(B8)-1))),EDATE($B$3,12*VALUE(LEFT(B8,LEN(B8)-1)))))+IF(WEEKDAY(IF(RIGHT(B8,1)="W",$B$3+7*VALUE(LEFT(B8,LEN(B8)-1)),IF(RIGHT(B8,1)="M",EDATE($B$3,VALUE(LEFT(B8,LEN(B8)-1))),EDATE($B$3,12*VALUE(LEFT(B8,LEN(B8)-1))))),2)=6,2,IF(WEEKDAY(IF(RIGHT(B8,1)="W",$B$3+7*VALUE(LEFT(B8,LEN(B8)-1)),IF(RIGHT(B8,1)="M",EDATE($B$3,VALUE(LEFT(B8,LEN(B8)-1))),EDATE($B$3,12*VALUE(LEFT(B8,LEN(B8)-1))))),2)=7,1,0)))) | D8: =(C8-$B$3)/365 | E8: =IFERROR(BDP(A8&" "&PX_SRC&" Curncy","PX_BID"),"ERROR PLZ FIX") | F8: =IFERROR(BDP(A8&" "&PX_SRC&" Curncy","PX_ASK"),"ERROR PLZ FIX") | G8: =IFERROR(BDP(A8&" "&PX_SRC&" Curncy","PX_LAST"),"ERROR PLZ FIX") | H8: =IFERROR(IF(Bootstrap!$G$4="Test 1",INDEX(Testing!$B$8:$B$47,MATCH(C8,Testing!$F$8:$F$47,0)),IF(Bootstrap!$G$4="Test 2",INDEX(Testing!$B$58:$B$97,MATCH(C8,Testing!$F$58:$F$97,0)),IF(Bootstrap!$G$4="Test 3",INDEX(Testing!$B$108:$B$147,MATCH(C8,Testing!$F$108:$F$147,0)),IF(Bootstrap!$G$4="Fixed (S490 07/21/26)",J8,IF(ISNUMBER(T8),T8,J8))))),J8) | I8: Y | J8: =IFERROR(INDEX(S490_Snapshot!$C$7:$C$38,MATCH(B8,S490_Snapshot!$B$7:$B$38,0)),"") | K8: S490_Snapshot | P8: =IF(COUNT(N8:O8)=2,(N8+O8)/2,"") | Q8: =IF(AND(ISNUMBER(N8),ISNUMBER(E8)),(E8-N8)*100,"") | R8: =IF(AND(ISNUMBER(O8),ISNUMBER(F8)),(F8-O8)*100,"") | S8: =IF(AND(ISNUMBER(P8),ISNUMBER(H8)),(H8-P8)*100,"") | T8: =IFERROR((E8+F8)/2,IFERROR(G8+0,"")) | U8: =IF(OR(T8="",NOT(ISNUMBER(J8))),"",(T8-J8)*100)
A9: USOSFRB | B9: 2M | C9: =IF(MONTH((IF(RIGHT(B9,1)="W",$B$3+7*VALUE(LEFT(B9,LEN(B9)-1)),IF(RIGHT(B9,1)="M",EDATE($B$3,VALUE(LEFT(B9,LEN(B9)-1))),EDATE($B$3,12*VALUE(LEFT(B9,LEN(B9)-1)))))+IF(WEEKDAY(IF(RIGHT(B9,1)="W",$B$3+7*VALUE(LEFT(B9,LEN(B9)-1)),IF(RIGHT(B9,1)="M",EDATE($B$3,VALUE(LEFT(B9,LEN(B9)-1))),EDATE($B$3,12*VALUE(LEFT(B9,LEN(B9)-1))))),2)=6,2,IF(WEEKDAY(IF(RIGHT(B9,1)="W",$B$3+7*VALUE(LEFT(B9,LEN(B9)-1)),IF(RIGHT(B9,1)="M",EDATE($B$3,VALUE(LEFT(B9,LEN(B9)-1))),EDATE($B$3,12*VALUE(LEFT(B9,LEN(B9)-1))))),2)=7,1,0))))<>MONTH(IF(RIGHT(B9,1)="W",$B$3+7*VALUE(LEFT(B9,LEN(B9)-1)),IF(RIGHT(B9,1)="M",EDATE($B$3,VALUE(LEFT(B9,LEN(B9)-1))),EDATE($B$3,12*VALUE(LEFT(B9,LEN(B9)-1)))))),(IF(RIGHT(B9,1)="W",$B$3+7*VALUE(LEFT(B9,LEN(B9)-1)),IF(RIGHT(B9,1)="M",EDATE($B$3,VALUE(LEFT(B9,LEN(B9)-1))),EDATE($B$3,12*VALUE(LEFT(B9,LEN(B9)-1)))))-IF(WEEKDAY(IF(RIGHT(B9,1)="W",$B$3+7*VALUE(LEFT(B9,LEN(B9)-1)),IF(RIGHT(B9,1)="M",EDATE($B$3,VALUE(LEFT(B9,LEN(B9)-1))),EDATE($B$3,12*VALUE(LEFT(B9,LEN(B9)-1))))),2)=6,1,IF(WEEKDAY(IF(RIGHT(B9,1)="W",$B$3+7*VALUE(LEFT(B9,LEN(B9)-1)),IF(RIGHT(B9,1)="M",EDATE($B$3,VALUE(LEFT(B9,LEN(B9)-1))),EDATE($B$3,12*VALUE(LEFT(B9,LEN(B9)-1))))),2)=7,2,0))),(IF(RIGHT(B9,1)="W",$B$3+7*VALUE(LEFT(B9,LEN(B9)-1)),IF(RIGHT(B9,1)="M",EDATE($B$3,VALUE(LEFT(B9,LEN(B9)-1))),EDATE($B$3,12*VALUE(LEFT(B9,LEN(B9)-1)))))+IF(WEEKDAY(IF(RIGHT(B9,1)="W",$B$3+7*VALUE(LEFT(B9,LEN(B9)-1)),IF(RIGHT(B9,1)="M",EDATE($B$3,VALUE(LEFT(B9,LEN(B9)-1))),EDATE($B$3,12*VALUE(LEFT(B9,LEN(B9)-1))))),2)=6,2,IF(WEEKDAY(IF(RIGHT(B9,1)="W",$B$3+7*VALUE(LEFT(B9,LEN(B9)-1)),IF(RIGHT(B9,1)="M",EDATE($B$3,VALUE(LEFT(B9,LEN(B9)-1))),EDATE($B$3,12*VALUE(LEFT(B9,LEN(B9)-1))))),2)=7,1,0)))) | D9: =(C9-$B$3)/365 | E9: =IFERROR(BDP(A9&" "&PX_SRC&" Curncy","PX_BID"),"ERROR PLZ FIX") | F9: =IFERROR(BDP(A9&" "&PX_SRC&" Curncy","PX_ASK"),"ERROR PLZ FIX") | G9: =IFERROR(BDP(A9&" "&PX_SRC&" Curncy","PX_LAST"),"ERROR PLZ FIX") | H9: =IFERROR(IF(Bootstrap!$G$4="Test 1",INDEX(Testing!$B$8:$B$47,MATCH(C9,Testing!$F$8:$F$47,0)),IF(Bootstrap!$G$4="Test 2",INDEX(Testing!$B$58:$B$97,MATCH(C9,Testing!$F$58:$F$97,0)),IF(Bootstrap!$G$4="Test 3",INDEX(Testing!$B$108:$B$147,MATCH(C9,Testing!$F$108:$F$147,0)),IF(Bootstrap!$G$4="Fixed (S490 07/21/26)",J9,IF(ISNUMBER(T9),T9,J9))))),J9) | J9: =IFERROR(INDEX(S490_Snapshot!$C$7:$C$38,MATCH(B9,S490_Snapshot!$B$7:$B$38,0)),"") | K9: S490_Snapshot | P9: =IF(COUNT(N9:O9)=2,(N9+O9)/2,"") | Q9: =IF(AND(ISNUMBER(N9),ISNUMBER(E9)),(E9-N9)*100,"") | R9: =IF(AND(ISNUMBER(O9),ISNUMBER(F9)),(F9-O9)*100,"") | S9: =IF(AND(ISNUMBER(P9),ISNUMBER(H9)),(H9-P9)*100,"") | T9: =IFERROR((E9+F9)/2,IFERROR(G9+0,"")) | U9: =IF(OR(T9="",NOT(ISNUMBER(J9))),"",(T9-J9)*100)
A10: USOSFRC | B10: 3M | C10: =IF(MONTH((IF(RIGHT(B10,1)="W",$B$3+7*VALUE(LEFT(B10,LEN(B10)-1)),IF(RIGHT(B10,1)="M",EDATE($B$3,VALUE(LEFT(B10,LEN(B10)-1))),EDATE($B$3,12*VALUE(LEFT(B10,LEN(B10)-1)))))+IF(WEEKDAY(IF(RIGHT(B10,1)="W",$B$3+7*VALUE(LEFT(B10,LEN(B10)-1)),IF(RIGHT(B10,1)="M",EDATE($B$3,VALUE(LEFT(B10,LEN(B10)-1))),EDATE($B$3,12*VALUE(LEFT(B10,LEN(B10)-1))))),2)=6,2,IF(WEEKDAY(IF(RIGHT(B10,1)="W",$B$3+7*VALUE(LEFT(B10,LEN(B10)-1)),IF(RIGHT(B10,1)="M",EDATE($B$3,VALUE(LEFT(B10,LEN(B10)-1))),EDATE($B$3,12*VALUE(LEFT(B10,LEN(B10)-1))))),2)=7,1,0))))<>MONTH(IF(RIGHT(B10,1)="W",$B$3+7*VALUE(LEFT(B10,LEN(B10)-1)),IF(RIGHT(B10,1)="M",EDATE($B$3,VALUE(LEFT(B10,LEN(B10)-1))),EDATE($B$3,12*VALUE(LEFT(B10,LEN(B10)-1)))))),(IF(RIGHT(B10,1)="W",$B$3+7*VALUE(LEFT(B10,LEN(B10)-1)),IF(RIGHT(B10,1)="M",EDATE($B$3,VALUE(LEFT(B10,LEN(B10)-1))),EDATE($B$3,12*VALUE(LEFT(B10,LEN(B10)-1)))))-IF(WEEKDAY(IF(RIGHT(B10,1)="W",$B$3+7*VALUE(LEFT(B10,LEN(B10)-1)),IF(RIGHT(B10,1)="M",EDATE($B$3,VALUE(LEFT(B10,LEN(B10)-1))),EDATE($B$3,12*VALUE(LEFT(B10,LEN(B10)-1))))),2)=6,1,IF(WEEKDAY(IF(RIGHT(B10,1)="W",$B$3+7*VALUE(LEFT(B10,LEN(B10)-1)),IF(RIGHT(B10,1)="M",EDATE($B$3,VALUE(LEFT(B10,LEN(B10)-1))),EDATE($B$3,12*VALUE(LEFT(B10,LEN(B10)-1))))),2)=7,2,0))),(IF(RIGHT(B10,1)="W",$B$3+7*VALUE(LEFT(B10,LEN(B10)-1)),IF(RIGHT(B10,1)="M",EDATE($B$3,VALUE(LEFT(B10,LEN(B10)-1))),EDATE($B$3,12*VALUE(LEFT(B10,LEN(B10)-1)))))+IF(WEEKDAY(IF(RIGHT(B10,1)="W",$B$3+7*VALUE(LEFT(B10,LEN(B10)-1)),IF(RIGHT(B10,1)="M",EDATE($B$3,VALUE(LEFT(B10,LEN(B10)-1))),EDATE($B$3,12*VALUE(LEFT(B10,LEN(B10)-1))))),2)=6,2,IF(WEEKDAY(IF(RIGHT(B10,1)="W",$B$3+7*VALUE(LEFT(B10,LEN(B10)-1)),IF(RIGHT(B10,1)="M",EDATE($B$3,VALUE(LEFT(B10,LEN(B10)-1))),EDATE($B$3,12*VALUE(LEFT(B10,LEN(B10)-1))))),2)=7,1,0)))) | D10: =(C10-$B$3)/365 | E10: =IFERROR(BDP(A10&" "&PX_SRC&" Curncy","PX_BID"),"ERROR PLZ FIX") | F10: =IFERROR(BDP(A10&" "&PX_SRC&" Curncy","PX_ASK"),"ERROR PLZ FIX") | G10: =IFERROR(BDP(A10&" "&PX_SRC&" Curncy","PX_LAST"),"ERROR PLZ FIX") | H10: =IFERROR(IF(Bootstrap!$G$4="Test 1",INDEX(Testing!$B$8:$B$47,MATCH(C10,Testing!$F$8:$F$47,0)),IF(Bootstrap!$G$4="Test 2",INDEX(Testing!$B$58:$B$97,MATCH(C10,Testing!$F$58:$F$97,0)),IF(Bootstrap!$G$4="Test 3",INDEX(Testing!$B$108:$B$147,MATCH(C10,Testing!$F$108:$F$147,0)),IF(Bootstrap!$G$4="Fixed (S490 07/21/26)",J10,IF(ISNUMBER(T10),T10,J10))))),J10) | I10: Y | J10: =IFERROR(INDEX(S490_Snapshot!$C$7:$C$38,MATCH(B10,S490_Snapshot!$B$7:$B$38,0)),"") | K10: S490_Snapshot | P10: =IF(COUNT(N10:O10)=2,(N10+O10)/2,"") | Q10: =IF(AND(ISNUMBER(N10),ISNUMBER(E10)),(E10-N10)*100,"") | R10: =IF(AND(ISNUMBER(O10),ISNUMBER(F10)),(F10-O10)*100,"") | S10: =IF(AND(ISNUMBER(P10),ISNUMBER(H10)),(H10-P10)*100,"") | T10: =IFERROR((E10+F10)/2,IFERROR(G10+0,"")) | U10: =IF(OR(T10="",NOT(ISNUMBER(J10))),"",(T10-J10)*100)
A11: USOSFRD | B11: 4M | C11: =IF(MONTH((IF(RIGHT(B11,1)="W",$B$3+7*VALUE(LEFT(B11,LEN(B11)-1)),IF(RIGHT(B11,1)="M",EDATE($B$3,VALUE(LEFT(B11,LEN(B11)-1))),EDATE($B$3,12*VALUE(LEFT(B11,LEN(B11)-1)))))+IF(WEEKDAY(IF(RIGHT(B11,1)="W",$B$3+7*VALUE(LEFT(B11,LEN(B11)-1)),IF(RIGHT(B11,1)="M",EDATE($B$3,VALUE(LEFT(B11,LEN(B11)-1))),EDATE($B$3,12*VALUE(LEFT(B11,LEN(B11)-1))))),2)=6,2,IF(WEEKDAY(IF(RIGHT(B11,1)="W",$B$3+7*VALUE(LEFT(B11,LEN(B11)-1)),IF(RIGHT(B11,1)="M",EDATE($B$3,VALUE(LEFT(B11,LEN(B11)-1))),EDATE($B$3,12*VALUE(LEFT(B11,LEN(B11)-1))))),2)=7,1,0))))<>MONTH(IF(RIGHT(B11,1)="W",$B$3+7*VALUE(LEFT(B11,LEN(B11)-1)),IF(RIGHT(B11,1)="M",EDATE($B$3,VALUE(LEFT(B11,LEN(B11)-1))),EDATE($B$3,12*VALUE(LEFT(B11,LEN(B11)-1)))))),(IF(RIGHT(B11,1)="W",$B$3+7*VALUE(LEFT(B11,LEN(B11)-1)),IF(RIGHT(B11,1)="M",EDATE($B$3,VALUE(LEFT(B11,LEN(B11)-1))),EDATE($B$3,12*VALUE(LEFT(B11,LEN(B11)-1)))))-IF(WEEKDAY(IF(RIGHT(B11,1)="W",$B$3+7*VALUE(LEFT(B11,LEN(B11)-1)),IF(RIGHT(B11,1)="M",EDATE($B$3,VALUE(LEFT(B11,LEN(B11)-1))),EDATE($B$3,12*VALUE(LEFT(B11,LEN(B11)-1))))),2)=6,1,IF(WEEKDAY(IF(RIGHT(B11,1)="W",$B$3+7*VALUE(LEFT(B11,LEN(B11)-1)),IF(RIGHT(B11,1)="M",EDATE($B$3,VALUE(LEFT(B11,LEN(B11)-1))),EDATE($B$3,12*VALUE(LEFT(B11,LEN(B11)-1))))),2)=7,2,0))),(IF(RIGHT(B11,1)="W",$B$3+7*VALUE(LEFT(B11,LEN(B11)-1)),IF(RIGHT(B11,1)="M",EDATE($B$3,VALUE(LEFT(B11,LEN(B11)-1))),EDATE($B$3,12*VALUE(LEFT(B11,LEN(B11)-1)))))+IF(WEEKDAY(IF(RIGHT(B11,1)="W",$B$3+7*VALUE(LEFT(B11,LEN(B11)-1)),IF(RIGHT(B11,1)="M",EDATE($B$3,VALUE(LEFT(B11,LEN(B11)-1))),EDATE($B$3,12*VALUE(LEFT(B11,LEN(B11)-1))))),2)=6,2,IF(WEEKDAY(IF(RIGHT(B11,1)="W",$B$3+7*VALUE(LEFT(B11,LEN(B11)-1)),IF(RIGHT(B11,1)="M",EDATE($B$3,VALUE(LEFT(B11,LEN(B11)-1))),EDATE($B$3,12*VALUE(LEFT(B11,LEN(B11)-1))))),2)=7,1,0)))) | D11: =(C11-$B$3)/365 | E11: =IFERROR(BDP(A11&" "&PX_SRC&" Curncy","PX_BID"),"ERROR PLZ FIX") | F11: =IFERROR(BDP(A11&" "&PX_SRC&" Curncy","PX_ASK"),"ERROR PLZ FIX") | G11: =IFERROR(BDP(A11&" "&PX_SRC&" Curncy","PX_LAST"),"ERROR PLZ FIX") | H11: =IFERROR(IF(Bootstrap!$G$4="Test 1",INDEX(Testing!$B$8:$B$47,MATCH(C11,Testing!$F$8:$F$47,0)),IF(Bootstrap!$G$4="Test 2",INDEX(Testing!$B$58:$B$97,MATCH(C11,Testing!$F$58:$F$97,0)),IF(Bootstrap!$G$4="Test 3",INDEX(Testing!$B$108:$B$147,MATCH(C11,Testing!$F$108:$F$147,0)),IF(Bootstrap!$G$4="Fixed (S490 07/21/26)",J11,IF(ISNUMBER(T11),T11,J11))))),J11) | J11: =IFERROR(INDEX(S490_Snapshot!$C$7:$C$38,MATCH(B11,S490_Snapshot!$B$7:$B$38,0)),"") | K11: S490_Snapshot | P11: =IF(COUNT(N11:O11)=2,(N11+O11)/2,"") | Q11: =IF(AND(ISNUMBER(N11),ISNUMBER(E11)),(E11-N11)*100,"") | R11: =IF(AND(ISNUMBER(O11),ISNUMBER(F11)),(F11-O11)*100,"") | S11: =IF(AND(ISNUMBER(P11),ISNUMBER(H11)),(H11-P11)*100,"") | T11: =IFERROR((E11+F11)/2,IFERROR(G11+0,"")) | U11: =IF(OR(T11="",NOT(ISNUMBER(J11))),"",(T11-J11)*100)
A12: USOSFRE | B12: 5M | C12: =IF(MONTH((IF(RIGHT(B12,1)="W",$B$3+7*VALUE(LEFT(B12,LEN(B12)-1)),IF(RIGHT(B12,1)="M",EDATE($B$3,VALUE(LEFT(B12,LEN(B12)-1))),EDATE($B$3,12*VALUE(LEFT(B12,LEN(B12)-1)))))+IF(WEEKDAY(IF(RIGHT(B12,1)="W",$B$3+7*VALUE(LEFT(B12,LEN(B12)-1)),IF(RIGHT(B12,1)="M",EDATE($B$3,VALUE(LEFT(B12,LEN(B12)-1))),EDATE($B$3,12*VALUE(LEFT(B12,LEN(B12)-1))))),2)=6,2,IF(WEEKDAY(IF(RIGHT(B12,1)="W",$B$3+7*VALUE(LEFT(B12,LEN(B12)-1)),IF(RIGHT(B12,1)="M",EDATE($B$3,VALUE(LEFT(B12,LEN(B12)-1))),EDATE($B$3,12*VALUE(LEFT(B12,LEN(B12)-1))))),2)=7,1,0))))<>MONTH(IF(RIGHT(B12,1)="W",$B$3+7*VALUE(LEFT(B12,LEN(B12)-1)),IF(RIGHT(B12,1)="M",EDATE($B$3,VALUE(LEFT(B12,LEN(B12)-1))),EDATE($B$3,12*VALUE(LEFT(B12,LEN(B12)-1)))))),(IF(RIGHT(B12,1)="W",$B$3+7*VALUE(LEFT(B12,LEN(B12)-1)),IF(RIGHT(B12,1)="M",EDATE($B$3,VALUE(LEFT(B12,LEN(B12)-1))),EDATE($B$3,12*VALUE(LEFT(B12,LEN(B12)-1)))))-IF(WEEKDAY(IF(RIGHT(B12,1)="W",$B$3+7*VALUE(LEFT(B12,LEN(B12)-1)),IF(RIGHT(B12,1)="M",EDATE($B$3,VALUE(LEFT(B12,LEN(B12)-1))),EDATE($B$3,12*VALUE(LEFT(B12,LEN(B12)-1))))),2)=6,1,IF(WEEKDAY(IF(RIGHT(B12,1)="W",$B$3+7*VALUE(LEFT(B12,LEN(B12)-1)),IF(RIGHT(B12,1)="M",EDATE($B$3,VALUE(LEFT(B12,LEN(B12)-1))),EDATE($B$3,12*VALUE(LEFT(B12,LEN(B12)-1))))),2)=7,2,0))),(IF(RIGHT(B12,1)="W",$B$3+7*VALUE(LEFT(B12,LEN(B12)-1)),IF(RIGHT(B12,1)="M",EDATE($B$3,VALUE(LEFT(B12,LEN(B12)-1))),EDATE($B$3,12*VALUE(LEFT(B12,LEN(B12)-1)))))+IF(WEEKDAY(IF(RIGHT(B12,1)="W",$B$3+7*VALUE(LEFT(B12,LEN(B12)-1)),IF(RIGHT(B12,1)="M",EDATE($B$3,VALUE(LEFT(B12,LEN(B12)-1))),EDATE($B$3,12*VALUE(LEFT(B12,LEN(B12)-1))))),2)=6,2,IF(WEEKDAY(IF(RIGHT(B12,1)="W",$B$3+7*VALUE(LEFT(B12,LEN(B12)-1)),IF(RIGHT(B12,1)="M",EDATE($B$3,VALUE(LEFT(B12,LEN(B12)-1))),EDATE($B$3,12*VALUE(LEFT(B12,LEN(B12)-1))))),2)=7,1,0)))) | D12: =(C12-$B$3)/365 | E12: =IFERROR(BDP(A12&" "&PX_SRC&" Curncy","PX_BID"),"ERROR PLZ FIX") | F12: =IFERROR(BDP(A12&" "&PX_SRC&" Curncy","PX_ASK"),"ERROR PLZ FIX") | G12: =IFERROR(BDP(A12&" "&PX_SRC&" Curncy","PX_LAST"),"ERROR PLZ FIX") | H12: =IFERROR(IF(Bootstrap!$G$4="Test 1",INDEX(Testing!$B$8:$B$47,MATCH(C12,Testing!$F$8:$F$47,0)),IF(Bootstrap!$G$4="Test 2",INDEX(Testing!$B$58:$B$97,MATCH(C12,Testing!$F$58:$F$97,0)),IF(Bootstrap!$G$4="Test 3",INDEX(Testing!$B$108:$B$147,MATCH(C12,Testing!$F$108:$F$147,0)),IF(Bootstrap!$G$4="Fixed (S490 07/21/26)",J12,IF(ISNUMBER(T12),T12,J12))))),J12) | J12: =IFERROR(INDEX(S490_Snapshot!$C$7:$C$38,MATCH(B12,S490_Snapshot!$B$7:$B$38,0)),"") | K12: S490_Snapshot | P12: =IF(COUNT(N12:O12)=2,(N12+O12)/2,"") | Q12: =IF(AND(ISNUMBER(N12),ISNUMBER(E12)),(E12-N12)*100,"") | R12: =IF(AND(ISNUMBER(O12),ISNUMBER(F12)),(F12-O12)*100,"") | S12: =IF(AND(ISNUMBER(P12),ISNUMBER(H12)),(H12-P12)*100,"") | T12: =IFERROR((E12+F12)/2,IFERROR(G12+0,"")) | U12: =IF(OR(T12="",NOT(ISNUMBER(J12))),"",(T12-J12)*100)
A13: USOSFRF | B13: 6M | C13: =IF(MONTH((IF(RIGHT(B13,1)="W",$B$3+7*VALUE(LEFT(B13,LEN(B13)-1)),IF(RIGHT(B13,1)="M",EDATE($B$3,VALUE(LEFT(B13,LEN(B13)-1))),EDATE($B$3,12*VALUE(LEFT(B13,LEN(B13)-1)))))+IF(WEEKDAY(IF(RIGHT(B13,1)="W",$B$3+7*VALUE(LEFT(B13,LEN(B13)-1)),IF(RIGHT(B13,1)="M",EDATE($B$3,VALUE(LEFT(B13,LEN(B13)-1))),EDATE($B$3,12*VALUE(LEFT(B13,LEN(B13)-1))))),2)=6,2,IF(WEEKDAY(IF(RIGHT(B13,1)="W",$B$3+7*VALUE(LEFT(B13,LEN(B13)-1)),IF(RIGHT(B13,1)="M",EDATE($B$3,VALUE(LEFT(B13,LEN(B13)-1))),EDATE($B$3,12*VALUE(LEFT(B13,LEN(B13)-1))))),2)=7,1,0))))<>MONTH(IF(RIGHT(B13,1)="W",$B$3+7*VALUE(LEFT(B13,LEN(B13)-1)),IF(RIGHT(B13,1)="M",EDATE($B$3,VALUE(LEFT(B13,LEN(B13)-1))),EDATE($B$3,12*VALUE(LEFT(B13,LEN(B13)-1)))))),(IF(RIGHT(B13,1)="W",$B$3+7*VALUE(LEFT(B13,LEN(B13)-1)),IF(RIGHT(B13,1)="M",EDATE($B$3,VALUE(LEFT(B13,LEN(B13)-1))),EDATE($B$3,12*VALUE(LEFT(B13,LEN(B13)-1)))))-IF(WEEKDAY(IF(RIGHT(B13,1)="W",$B$3+7*VALUE(LEFT(B13,LEN(B13)-1)),IF(RIGHT(B13,1)="M",EDATE($B$3,VALUE(LEFT(B13,LEN(B13)-1))),EDATE($B$3,12*VALUE(LEFT(B13,LEN(B13)-1))))),2)=6,1,IF(WEEKDAY(IF(RIGHT(B13,1)="W",$B$3+7*VALUE(LEFT(B13,LEN(B13)-1)),IF(RIGHT(B13,1)="M",EDATE($B$3,VALUE(LEFT(B13,LEN(B13)-1))),EDATE($B$3,12*VALUE(LEFT(B13,LEN(B13)-1))))),2)=7,2,0))),(IF(RIGHT(B13,1)="W",$B$3+7*VALUE(LEFT(B13,LEN(B13)-1)),IF(RIGHT(B13,1)="M",EDATE($B$3,VALUE(LEFT(B13,LEN(B13)-1))),EDATE($B$3,12*VALUE(LEFT(B13,LEN(B13)-1)))))+IF(WEEKDAY(IF(RIGHT(B13,1)="W",$B$3+7*VALUE(LEFT(B13,LEN(B13)-1)),IF(RIGHT(B13,1)="M",EDATE($B$3,VALUE(LEFT(B13,LEN(B13)-1))),EDATE($B$3,12*VALUE(LEFT(B13,LEN(B13)-1))))),2)=6,2,IF(WEEKDAY(IF(RIGHT(B13,1)="W",$B$3+7*VALUE(LEFT(B13,LEN(B13)-1)),IF(RIGHT(B13,1)="M",EDATE($B$3,VALUE(LEFT(B13,LEN(B13)-1))),EDATE($B$3,12*VALUE(LEFT(B13,LEN(B13)-1))))),2)=7,1,0)))) | D13: =(C13-$B$3)/365 | E13: =IFERROR(BDP(A13&" "&PX_SRC&" Curncy","PX_BID"),"ERROR PLZ FIX") | F13: =IFERROR(BDP(A13&" "&PX_SRC&" Curncy","PX_ASK"),"ERROR PLZ FIX") | G13: =IFERROR(BDP(A13&" "&PX_SRC&" Curncy","PX_LAST"),"ERROR PLZ FIX") | H13: =IFERROR(IF(Bootstrap!$G$4="Test 1",INDEX(Testing!$B$8:$B$47,MATCH(C13,Testing!$F$8:$F$47,0)),IF(Bootstrap!$G$4="Test 2",INDEX(Testing!$B$58:$B$97,MATCH(C13,Testing!$F$58:$F$97,0)),IF(Bootstrap!$G$4="Test 3",INDEX(Testing!$B$108:$B$147,MATCH(C13,Testing!$F$108:$F$147,0)),IF(Bootstrap!$G$4="Fixed (S490 07/21/26)",J13,IF(ISNUMBER(T13),T13,J13))))),J13) | I13: Y | J13: =IFERROR(INDEX(S490_Snapshot!$C$7:$C$38,MATCH(B13,S490_Snapshot!$B$7:$B$38,0)),"") | K13: S490_Snapshot | P13: =IF(COUNT(N13:O13)=2,(N13+O13)/2,"") | Q13: =IF(AND(ISNUMBER(N13),ISNUMBER(E13)),(E13-N13)*100,"") | R13: =IF(AND(ISNUMBER(O13),ISNUMBER(F13)),(F13-O13)*100,"") | S13: =IF(AND(ISNUMBER(P13),ISNUMBER(H13)),(H13-P13)*100,"") | T13: =IFERROR((E13+F13)/2,IFERROR(G13+0,"")) | U13: =IF(OR(T13="",NOT(ISNUMBER(J13))),"",(T13-J13)*100)
A14: USOSFRG | B14: 7M | C14: =IF(MONTH((IF(RIGHT(B14,1)="W",$B$3+7*VALUE(LEFT(B14,LEN(B14)-1)),IF(RIGHT(B14,1)="M",EDATE($B$3,VALUE(LEFT(B14,LEN(B14)-1))),EDATE($B$3,12*VALUE(LEFT(B14,LEN(B14)-1)))))+IF(WEEKDAY(IF(RIGHT(B14,1)="W",$B$3+7*VALUE(LEFT(B14,LEN(B14)-1)),IF(RIGHT(B14,1)="M",EDATE($B$3,VALUE(LEFT(B14,LEN(B14)-1))),EDATE($B$3,12*VALUE(LEFT(B14,LEN(B14)-1))))),2)=6,2,IF(WEEKDAY(IF(RIGHT(B14,1)="W",$B$3+7*VALUE(LEFT(B14,LEN(B14)-1)),IF(RIGHT(B14,1)="M",EDATE($B$3,VALUE(LEFT(B14,LEN(B14)-1))),EDATE($B$3,12*VALUE(LEFT(B14,LEN(B14)-1))))),2)=7,1,0))))<>MONTH(IF(RIGHT(B14,1)="W",$B$3+7*VALUE(LEFT(B14,LEN(B14)-1)),IF(RIGHT(B14,1)="M",EDATE($B$3,VALUE(LEFT(B14,LEN(B14)-1))),EDATE($B$3,12*VALUE(LEFT(B14,LEN(B14)-1)))))),(IF(RIGHT(B14,1)="W",$B$3+7*VALUE(LEFT(B14,LEN(B14)-1)),IF(RIGHT(B14,1)="M",EDATE($B$3,VALUE(LEFT(B14,LEN(B14)-1))),EDATE($B$3,12*VALUE(LEFT(B14,LEN(B14)-1)))))-IF(WEEKDAY(IF(RIGHT(B14,1)="W",$B$3+7*VALUE(LEFT(B14,LEN(B14)-1)),IF(RIGHT(B14,1)="M",EDATE($B$3,VALUE(LEFT(B14,LEN(B14)-1))),EDATE($B$3,12*VALUE(LEFT(B14,LEN(B14)-1))))),2)=6,1,IF(WEEKDAY(IF(RIGHT(B14,1)="W",$B$3+7*VALUE(LEFT(B14,LEN(B14)-1)),IF(RIGHT(B14,1)="M",EDATE($B$3,VALUE(LEFT(B14,LEN(B14)-1))),EDATE($B$3,12*VALUE(LEFT(B14,LEN(B14)-1))))),2)=7,2,0))),(IF(RIGHT(B14,1)="W",$B$3+7*VALUE(LEFT(B14,LEN(B14)-1)),IF(RIGHT(B14,1)="M",EDATE($B$3,VALUE(LEFT(B14,LEN(B14)-1))),EDATE($B$3,12*VALUE(LEFT(B14,LEN(B14)-1)))))+IF(WEEKDAY(IF(RIGHT(B14,1)="W",$B$3+7*VALUE(LEFT(B14,LEN(B14)-1)),IF(RIGHT(B14,1)="M",EDATE($B$3,VALUE(LEFT(B14,LEN(B14)-1))),EDATE($B$3,12*VALUE(LEFT(B14,LEN(B14)-1))))),2)=6,2,IF(WEEKDAY(IF(RIGHT(B14,1)="W",$B$3+7*VALUE(LEFT(B14,LEN(B14)-1)),IF(RIGHT(B14,1)="M",EDATE($B$3,VALUE(LEFT(B14,LEN(B14)-1))),EDATE($B$3,12*VALUE(LEFT(B14,LEN(B14)-1))))),2)=7,1,0)))) | D14: =(C14-$B$3)/365 | E14: =IFERROR(BDP(A14&" "&PX_SRC&" Curncy","PX_BID"),"ERROR PLZ FIX") | F14: =IFERROR(BDP(A14&" "&PX_SRC&" Curncy","PX_ASK"),"ERROR PLZ FIX") | G14: =IFERROR(BDP(A14&" "&PX_SRC&" Curncy","PX_LAST"),"ERROR PLZ FIX") | H14: =IFERROR(IF(Bootstrap!$G$4="Test 1",INDEX(Testing!$B$8:$B$47,MATCH(C14,Testing!$F$8:$F$47,0)),IF(Bootstrap!$G$4="Test 2",INDEX(Testing!$B$58:$B$97,MATCH(C14,Testing!$F$58:$F$97,0)),IF(Bootstrap!$G$4="Test 3",INDEX(Testing!$B$108:$B$147,MATCH(C14,Testing!$F$108:$F$147,0)),IF(Bootstrap!$G$4="Fixed (S490 07/21/26)",J14,IF(ISNUMBER(T14),T14,J14))))),J14) | J14: =IFERROR(INDEX(S490_Snapshot!$C$7:$C$38,MATCH(B14,S490_Snapshot!$B$7:$B$38,0)),"") | K14: S490_Snapshot | P14: =IF(COUNT(N14:O14)=2,(N14+O14)/2,"") | Q14: =IF(AND(ISNUMBER(N14),ISNUMBER(E14)),(E14-N14)*100,"") | R14: =IF(AND(ISNUMBER(O14),ISNUMBER(F14)),(F14-O14)*100,"") | S14: =IF(AND(ISNUMBER(P14),ISNUMBER(H14)),(H14-P14)*100,"") | T14: =IFERROR((E14+F14)/2,IFERROR(G14+0,"")) | U14: =IF(OR(T14="",NOT(ISNUMBER(J14))),"",(T14-J14)*100)
A15: USOSFRH | B15: 8M | C15: =IF(MONTH((IF(RIGHT(B15,1)="W",$B$3+7*VALUE(LEFT(B15,LEN(B15)-1)),IF(RIGHT(B15,1)="M",EDATE($B$3,VALUE(LEFT(B15,LEN(B15)-1))),EDATE($B$3,12*VALUE(LEFT(B15,LEN(B15)-1)))))+IF(WEEKDAY(IF(RIGHT(B15,1)="W",$B$3+7*VALUE(LEFT(B15,LEN(B15)-1)),IF(RIGHT(B15,1)="M",EDATE($B$3,VALUE(LEFT(B15,LEN(B15)-1))),EDATE($B$3,12*VALUE(LEFT(B15,LEN(B15)-1))))),2)=6,2,IF(WEEKDAY(IF(RIGHT(B15,1)="W",$B$3+7*VALUE(LEFT(B15,LEN(B15)-1)),IF(RIGHT(B15,1)="M",EDATE($B$3,VALUE(LEFT(B15,LEN(B15)-1))),EDATE($B$3,12*VALUE(LEFT(B15,LEN(B15)-1))))),2)=7,1,0))))<>MONTH(IF(RIGHT(B15,1)="W",$B$3+7*VALUE(LEFT(B15,LEN(B15)-1)),IF(RIGHT(B15,1)="M",EDATE($B$3,VALUE(LEFT(B15,LEN(B15)-1))),EDATE($B$3,12*VALUE(LEFT(B15,LEN(B15)-1)))))),(IF(RIGHT(B15,1)="W",$B$3+7*VALUE(LEFT(B15,LEN(B15)-1)),IF(RIGHT(B15,1)="M",EDATE($B$3,VALUE(LEFT(B15,LEN(B15)-1))),EDATE($B$3,12*VALUE(LEFT(B15,LEN(B15)-1)))))-IF(WEEKDAY(IF(RIGHT(B15,1)="W",$B$3+7*VALUE(LEFT(B15,LEN(B15)-1)),IF(RIGHT(B15,1)="M",EDATE($B$3,VALUE(LEFT(B15,LEN(B15)-1))),EDATE($B$3,12*VALUE(LEFT(B15,LEN(B15)-1))))),2)=6,1,IF(WEEKDAY(IF(RIGHT(B15,1)="W",$B$3+7*VALUE(LEFT(B15,LEN(B15)-1)),IF(RIGHT(B15,1)="M",EDATE($B$3,VALUE(LEFT(B15,LEN(B15)-1))),EDATE($B$3,12*VALUE(LEFT(B15,LEN(B15)-1))))),2)=7,2,0))),(IF(RIGHT(B15,1)="W",$B$3+7*VALUE(LEFT(B15,LEN(B15)-1)),IF(RIGHT(B15,1)="M",EDATE($B$3,VALUE(LEFT(B15,LEN(B15)-1))),EDATE($B$3,12*VALUE(LEFT(B15,LEN(B15)-1)))))+IF(WEEKDAY(IF(RIGHT(B15,1)="W",$B$3+7*VALUE(LEFT(B15,LEN(B15)-1)),IF(RIGHT(B15,1)="M",EDATE($B$3,VALUE(LEFT(B15,LEN(B15)-1))),EDATE($B$3,12*VALUE(LEFT(B15,LEN(B15)-1))))),2)=6,2,IF(WEEKDAY(IF(RIGHT(B15,1)="W",$B$3+7*VALUE(LEFT(B15,LEN(B15)-1)),IF(RIGHT(B15,1)="M",EDATE($B$3,VALUE(LEFT(B15,LEN(B15)-1))),EDATE($B$3,12*VALUE(LEFT(B15,LEN(B15)-1))))),2)=7,1,0)))) | D15: =(C15-$B$3)/365 | E15: =IFERROR(BDP(A15&" "&PX_SRC&" Curncy","PX_BID"),"ERROR PLZ FIX") | F15: =IFERROR(BDP(A15&" "&PX_SRC&" Curncy","PX_ASK"),"ERROR PLZ FIX") | G15: =IFERROR(BDP(A15&" "&PX_SRC&" Curncy","PX_LAST"),"ERROR PLZ FIX") | H15: =IFERROR(IF(Bootstrap!$G$4="Test 1",INDEX(Testing!$B$8:$B$47,MATCH(C15,Testing!$F$8:$F$47,0)),IF(Bootstrap!$G$4="Test 2",INDEX(Testing!$B$58:$B$97,MATCH(C15,Testing!$F$58:$F$97,0)),IF(Bootstrap!$G$4="Test 3",INDEX(Testing!$B$108:$B$147,MATCH(C15,Testing!$F$108:$F$147,0)),IF(Bootstrap!$G$4="Fixed (S490 07/21/26)",J15,IF(ISNUMBER(T15),T15,J15))))),J15) | J15: =IFERROR(INDEX(S490_Snapshot!$C$7:$C$38,MATCH(B15,S490_Snapshot!$B$7:$B$38,0)),"") | K15: S490_Snapshot | P15: =IF(COUNT(N15:O15)=2,(N15+O15)/2,"") | Q15: =IF(AND(ISNUMBER(N15),ISNUMBER(E15)),(E15-N15)*100,"") | R15: =IF(AND(ISNUMBER(O15),ISNUMBER(F15)),(F15-O15)*100,"") | S15: =IF(AND(ISNUMBER(P15),ISNUMBER(H15)),(H15-P15)*100,"") | T15: =IFERROR((E15+F15)/2,IFERROR(G15+0,"")) | U15: =IF(OR(T15="",NOT(ISNUMBER(J15))),"",(T15-J15)*100)
A16: USOSFRI | B16: 9M | C16: =IF(MONTH((IF(RIGHT(B16,1)="W",$B$3+7*VALUE(LEFT(B16,LEN(B16)-1)),IF(RIGHT(B16,1)="M",EDATE($B$3,VALUE(LEFT(B16,LEN(B16)-1))),EDATE($B$3,12*VALUE(LEFT(B16,LEN(B16)-1)))))+IF(WEEKDAY(IF(RIGHT(B16,1)="W",$B$3+7*VALUE(LEFT(B16,LEN(B16)-1)),IF(RIGHT(B16,1)="M",EDATE($B$3,VALUE(LEFT(B16,LEN(B16)-1))),EDATE($B$3,12*VALUE(LEFT(B16,LEN(B16)-1))))),2)=6,2,IF(WEEKDAY(IF(RIGHT(B16,1)="W",$B$3+7*VALUE(LEFT(B16,LEN(B16)-1)),IF(RIGHT(B16,1)="M",EDATE($B$3,VALUE(LEFT(B16,LEN(B16)-1))),EDATE($B$3,12*VALUE(LEFT(B16,LEN(B16)-1))))),2)=7,1,0))))<>MONTH(IF(RIGHT(B16,1)="W",$B$3+7*VALUE(LEFT(B16,LEN(B16)-1)),IF(RIGHT(B16,1)="M",EDATE($B$3,VALUE(LEFT(B16,LEN(B16)-1))),EDATE($B$3,12*VALUE(LEFT(B16,LEN(B16)-1)))))),(IF(RIGHT(B16,1)="W",$B$3+7*VALUE(LEFT(B16,LEN(B16)-1)),IF(RIGHT(B16,1)="M",EDATE($B$3,VALUE(LEFT(B16,LEN(B16)-1))),EDATE($B$3,12*VALUE(LEFT(B16,LEN(B16)-1)))))-IF(WEEKDAY(IF(RIGHT(B16,1)="W",$B$3+7*VALUE(LEFT(B16,LEN(B16)-1)),IF(RIGHT(B16,1)="M",EDATE($B$3,VALUE(LEFT(B16,LEN(B16)-1))),EDATE($B$3,12*VALUE(LEFT(B16,LEN(B16)-1))))),2)=6,1,IF(WEEKDAY(IF(RIGHT(B16,1)="W",$B$3+7*VALUE(LEFT(B16,LEN(B16)-1)),IF(RIGHT(B16,1)="M",EDATE($B$3,VALUE(LEFT(B16,LEN(B16)-1))),EDATE($B$3,12*VALUE(LEFT(B16,LEN(B16)-1))))),2)=7,2,0))),(IF(RIGHT(B16,1)="W",$B$3+7*VALUE(LEFT(B16,LEN(B16)-1)),IF(RIGHT(B16,1)="M",EDATE($B$3,VALUE(LEFT(B16,LEN(B16)-1))),EDATE($B$3,12*VALUE(LEFT(B16,LEN(B16)-1)))))+IF(WEEKDAY(IF(RIGHT(B16,1)="W",$B$3+7*VALUE(LEFT(B16,LEN(B16)-1)),IF(RIGHT(B16,1)="M",EDATE($B$3,VALUE(LEFT(B16,LEN(B16)-1))),EDATE($B$3,12*VALUE(LEFT(B16,LEN(B16)-1))))),2)=6,2,IF(WEEKDAY(IF(RIGHT(B16,1)="W",$B$3+7*VALUE(LEFT(B16,LEN(B16)-1)),IF(RIGHT(B16,1)="M",EDATE($B$3,VALUE(LEFT(B16,LEN(B16)-1))),EDATE($B$3,12*VALUE(LEFT(B16,LEN(B16)-1))))),2)=7,1,0)))) | D16: =(C16-$B$3)/365 | E16: =IFERROR(BDP(A16&" "&PX_SRC&" Curncy","PX_BID"),"ERROR PLZ FIX") | F16: =IFERROR(BDP(A16&" "&PX_SRC&" Curncy","PX_ASK"),"ERROR PLZ FIX") | G16: =IFERROR(BDP(A16&" "&PX_SRC&" Curncy","PX_LAST"),"ERROR PLZ FIX") | H16: =IFERROR(IF(Bootstrap!$G$4="Test 1",INDEX(Testing!$B$8:$B$47,MATCH(C16,Testing!$F$8:$F$47,0)),IF(Bootstrap!$G$4="Test 2",INDEX(Testing!$B$58:$B$97,MATCH(C16,Testing!$F$58:$F$97,0)),IF(Bootstrap!$G$4="Test 3",INDEX(Testing!$B$108:$B$147,MATCH(C16,Testing!$F$108:$F$147,0)),IF(Bootstrap!$G$4="Fixed (S490 07/21/26)",J16,IF(ISNUMBER(T16),T16,J16))))),J16) | J16: =IFERROR(INDEX(S490_Snapshot!$C$7:$C$38,MATCH(B16,S490_Snapshot!$B$7:$B$38,0)),"") | K16: S490_Snapshot | P16: =IF(COUNT(N16:O16)=2,(N16+O16)/2,"") | Q16: =IF(AND(ISNUMBER(N16),ISNUMBER(E16)),(E16-N16)*100,"") | R16: =IF(AND(ISNUMBER(O16),ISNUMBER(F16)),(F16-O16)*100,"") | S16: =IF(AND(ISNUMBER(P16),ISNUMBER(H16)),(H16-P16)*100,"") | T16: =IFERROR((E16+F16)/2,IFERROR(G16+0,"")) | U16: =IF(OR(T16="",NOT(ISNUMBER(J16))),"",(T16-J16)*100)
A17: USOSFRJ | B17: 10M | C17: =IF(MONTH((IF(RIGHT(B17,1)="W",$B$3+7*VALUE(LEFT(B17,LEN(B17)-1)),IF(RIGHT(B17,1)="M",EDATE($B$3,VALUE(LEFT(B17,LEN(B17)-1))),EDATE($B$3,12*VALUE(LEFT(B17,LEN(B17)-1)))))+IF(WEEKDAY(IF(RIGHT(B17,1)="W",$B$3+7*VALUE(LEFT(B17,LEN(B17)-1)),IF(RIGHT(B17,1)="M",EDATE($B$3,VALUE(LEFT(B17,LEN(B17)-1))),EDATE($B$3,12*VALUE(LEFT(B17,LEN(B17)-1))))),2)=6,2,IF(WEEKDAY(IF(RIGHT(B17,1)="W",$B$3+7*VALUE(LEFT(B17,LEN(B17)-1)),IF(RIGHT(B17,1)="M",EDATE($B$3,VALUE(LEFT(B17,LEN(B17)-1))),EDATE($B$3,12*VALUE(LEFT(B17,LEN(B17)-1))))),2)=7,1,0))))<>MONTH(IF(RIGHT(B17,1)="W",$B$3+7*VALUE(LEFT(B17,LEN(B17)-1)),IF(RIGHT(B17,1)="M",EDATE($B$3,VALUE(LEFT(B17,LEN(B17)-1))),EDATE($B$3,12*VALUE(LEFT(B17,LEN(B17)-1)))))),(IF(RIGHT(B17,1)="W",$B$3+7*VALUE(LEFT(B17,LEN(B17)-1)),IF(RIGHT(B17,1)="M",EDATE($B$3,VALUE(LEFT(B17,LEN(B17)-1))),EDATE($B$3,12*VALUE(LEFT(B17,LEN(B17)-1)))))-IF(WEEKDAY(IF(RIGHT(B17,1)="W",$B$3+7*VALUE(LEFT(B17,LEN(B17)-1)),IF(RIGHT(B17,1)="M",EDATE($B$3,VALUE(LEFT(B17,LEN(B17)-1))),EDATE($B$3,12*VALUE(LEFT(B17,LEN(B17)-1))))),2)=6,1,IF(WEEKDAY(IF(RIGHT(B17,1)="W",$B$3+7*VALUE(LEFT(B17,LEN(B17)-1)),IF(RIGHT(B17,1)="M",EDATE($B$3,VALUE(LEFT(B17,LEN(B17)-1))),EDATE($B$3,12*VALUE(LEFT(B17,LEN(B17)-1))))),2)=7,2,0))),(IF(RIGHT(B17,1)="W",$B$3+7*VALUE(LEFT(B17,LEN(B17)-1)),IF(RIGHT(B17,1)="M",EDATE($B$3,VALUE(LEFT(B17,LEN(B17)-1))),EDATE($B$3,12*VALUE(LEFT(B17,LEN(B17)-1)))))+IF(WEEKDAY(IF(RIGHT(B17,1)="W",$B$3+7*VALUE(LEFT(B17,LEN(B17)-1)),IF(RIGHT(B17,1)="M",EDATE($B$3,VALUE(LEFT(B17,LEN(B17)-1))),EDATE($B$3,12*VALUE(LEFT(B17,LEN(B17)-1))))),2)=6,2,IF(WEEKDAY(IF(RIGHT(B17,1)="W",$B$3+7*VALUE(LEFT(B17,LEN(B17)-1)),IF(RIGHT(B17,1)="M",EDATE($B$3,VALUE(LEFT(B17,LEN(B17)-1))),EDATE($B$3,12*VALUE(LEFT(B17,LEN(B17)-1))))),2)=7,1,0)))) | D17: =(C17-$B$3)/365 | E17: =IFERROR(BDP(A17&" "&PX_SRC&" Curncy","PX_BID"),"ERROR PLZ FIX") | F17: =IFERROR(BDP(A17&" "&PX_SRC&" Curncy","PX_ASK"),"ERROR PLZ FIX") | G17: =IFERROR(BDP(A17&" "&PX_SRC&" Curncy","PX_LAST"),"ERROR PLZ FIX") | H17: =IFERROR(IF(Bootstrap!$G$4="Test 1",INDEX(Testing!$B$8:$B$47,MATCH(C17,Testing!$F$8:$F$47,0)),IF(Bootstrap!$G$4="Test 2",INDEX(Testing!$B$58:$B$97,MATCH(C17,Testing!$F$58:$F$97,0)),IF(Bootstrap!$G$4="Test 3",INDEX(Testing!$B$108:$B$147,MATCH(C17,Testing!$F$108:$F$147,0)),IF(Bootstrap!$G$4="Fixed (S490 07/21/26)",J17,IF(ISNUMBER(T17),T17,J17))))),J17) | J17: =IFERROR(INDEX(S490_Snapshot!$C$7:$C$38,MATCH(B17,S490_Snapshot!$B$7:$B$38,0)),"") | K17: S490_Snapshot | P17: =IF(COUNT(N17:O17)=2,(N17+O17)/2,"") | Q17: =IF(AND(ISNUMBER(N17),ISNUMBER(E17)),(E17-N17)*100,"") | R17: =IF(AND(ISNUMBER(O17),ISNUMBER(F17)),(F17-O17)*100,"") | S17: =IF(AND(ISNUMBER(P17),ISNUMBER(H17)),(H17-P17)*100,"") | T17: =IFERROR((E17+F17)/2,IFERROR(G17+0,"")) | U17: =IF(OR(T17="",NOT(ISNUMBER(J17))),"",(T17-J17)*100)
A18: USOSFRK | B18: 11M | C18: =IF(MONTH((IF(RIGHT(B18,1)="W",$B$3+7*VALUE(LEFT(B18,LEN(B18)-1)),IF(RIGHT(B18,1)="M",EDATE($B$3,VALUE(LEFT(B18,LEN(B18)-1))),EDATE($B$3,12*VALUE(LEFT(B18,LEN(B18)-1)))))+IF(WEEKDAY(IF(RIGHT(B18,1)="W",$B$3+7*VALUE(LEFT(B18,LEN(B18)-1)),IF(RIGHT(B18,1)="M",EDATE($B$3,VALUE(LEFT(B18,LEN(B18)-1))),EDATE($B$3,12*VALUE(LEFT(B18,LEN(B18)-1))))),2)=6,2,IF(WEEKDAY(IF(RIGHT(B18,1)="W",$B$3+7*VALUE(LEFT(B18,LEN(B18)-1)),IF(RIGHT(B18,1)="M",EDATE($B$3,VALUE(LEFT(B18,LEN(B18)-1))),EDATE($B$3,12*VALUE(LEFT(B18,LEN(B18)-1))))),2)=7,1,0))))<>MONTH(IF(RIGHT(B18,1)="W",$B$3+7*VALUE(LEFT(B18,LEN(B18)-1)),IF(RIGHT(B18,1)="M",EDATE($B$3,VALUE(LEFT(B18,LEN(B18)-1))),EDATE($B$3,12*VALUE(LEFT(B18,LEN(B18)-1)))))),(IF(RIGHT(B18,1)="W",$B$3+7*VALUE(LEFT(B18,LEN(B18)-1)),IF(RIGHT(B18,1)="M",EDATE($B$3,VALUE(LEFT(B18,LEN(B18)-1))),EDATE($B$3,12*VALUE(LEFT(B18,LEN(B18)-1)))))-IF(WEEKDAY(IF(RIGHT(B18,1)="W",$B$3+7*VALUE(LEFT(B18,LEN(B18)-1)),IF(RIGHT(B18,1)="M",EDATE($B$3,VALUE(LEFT(B18,LEN(B18)-1))),EDATE($B$3,12*VALUE(LEFT(B18,LEN(B18)-1))))),2)=6,1,IF(WEEKDAY(IF(RIGHT(B18,1)="W",$B$3+7*VALUE(LEFT(B18,LEN(B18)-1)),IF(RIGHT(B18,1)="M",EDATE($B$3,VALUE(LEFT(B18,LEN(B18)-1))),EDATE($B$3,12*VALUE(LEFT(B18,LEN(B18)-1))))),2)=7,2,0))),(IF(RIGHT(B18,1)="W",$B$3+7*VALUE(LEFT(B18,LEN(B18)-1)),IF(RIGHT(B18,1)="M",EDATE($B$3,VALUE(LEFT(B18,LEN(B18)-1))),EDATE($B$3,12*VALUE(LEFT(B18,LEN(B18)-1)))))+IF(WEEKDAY(IF(RIGHT(B18,1)="W",$B$3+7*VALUE(LEFT(B18,LEN(B18)-1)),IF(RIGHT(B18,1)="M",EDATE($B$3,VALUE(LEFT(B18,LEN(B18)-1))),EDATE($B$3,12*VALUE(LEFT(B18,LEN(B18)-1))))),2)=6,2,IF(WEEKDAY(IF(RIGHT(B18,1)="W",$B$3+7*VALUE(LEFT(B18,LEN(B18)-1)),IF(RIGHT(B18,1)="M",EDATE($B$3,VALUE(LEFT(B18,LEN(B18)-1))),EDATE($B$3,12*VALUE(LEFT(B18,LEN(B18)-1))))),2)=7,1,0)))) | D18: =(C18-$B$3)/365 | E18: =IFERROR(BDP(A18&" "&PX_SRC&" Curncy","PX_BID"),"ERROR PLZ FIX") | F18: =IFERROR(BDP(A18&" "&PX_SRC&" Curncy","PX_ASK"),"ERROR PLZ FIX") | G18: =IFERROR(BDP(A18&" "&PX_SRC&" Curncy","PX_LAST"),"ERROR PLZ FIX") | H18: =IFERROR(IF(Bootstrap!$G$4="Test 1",INDEX(Testing!$B$8:$B$47,MATCH(C18,Testing!$F$8:$F$47,0)),IF(Bootstrap!$G$4="Test 2",INDEX(Testing!$B$58:$B$97,MATCH(C18,Testing!$F$58:$F$97,0)),IF(Bootstrap!$G$4="Test 3",INDEX(Testing!$B$108:$B$147,MATCH(C18,Testing!$F$108:$F$147,0)),IF(Bootstrap!$G$4="Fixed (S490 07/21/26)",J18,IF(ISNUMBER(T18),T18,J18))))),J18) | J18: =IFERROR(INDEX(S490_Snapshot!$C$7:$C$38,MATCH(B18,S490_Snapshot!$B$7:$B$38,0)),"") | K18: S490_Snapshot | P18: =IF(COUNT(N18:O18)=2,(N18+O18)/2,"") | Q18: =IF(AND(ISNUMBER(N18),ISNUMBER(E18)),(E18-N18)*100,"") | R18: =IF(AND(ISNUMBER(O18),ISNUMBER(F18)),(F18-O18)*100,"") | S18: =IF(AND(ISNUMBER(P18),ISNUMBER(H18)),(H18-P18)*100,"") | T18: =IFERROR((E18+F18)/2,IFERROR(G18+0,"")) | U18: =IF(OR(T18="",NOT(ISNUMBER(J18))),"",(T18-J18)*100)
A19: USOSFR1 | B19: 1Y | C19: =IF(MONTH((IF(RIGHT(B19,1)="W",$B$3+7*VALUE(LEFT(B19,LEN(B19)-1)),IF(RIGHT(B19,1)="M",EDATE($B$3,VALUE(LEFT(B19,LEN(B19)-1))),EDATE($B$3,12*VALUE(LEFT(B19,LEN(B19)-1)))))+IF(WEEKDAY(IF(RIGHT(B19,1)="W",$B$3+7*VALUE(LEFT(B19,LEN(B19)-1)),IF(RIGHT(B19,1)="M",EDATE($B$3,VALUE(LEFT(B19,LEN(B19)-1))),EDATE($B$3,12*VALUE(LEFT(B19,LEN(B19)-1))))),2)=6,2,IF(WEEKDAY(IF(RIGHT(B19,1)="W",$B$3+7*VALUE(LEFT(B19,LEN(B19)-1)),IF(RIGHT(B19,1)="M",EDATE($B$3,VALUE(LEFT(B19,LEN(B19)-1))),EDATE($B$3,12*VALUE(LEFT(B19,LEN(B19)-1))))),2)=7,1,0))))<>MONTH(IF(RIGHT(B19,1)="W",$B$3+7*VALUE(LEFT(B19,LEN(B19)-1)),IF(RIGHT(B19,1)="M",EDATE($B$3,VALUE(LEFT(B19,LEN(B19)-1))),EDATE($B$3,12*VALUE(LEFT(B19,LEN(B19)-1)))))),(IF(RIGHT(B19,1)="W",$B$3+7*VALUE(LEFT(B19,LEN(B19)-1)),IF(RIGHT(B19,1)="M",EDATE($B$3,VALUE(LEFT(B19,LEN(B19)-1))),EDATE($B$3,12*VALUE(LEFT(B19,LEN(B19)-1)))))-IF(WEEKDAY(IF(RIGHT(B19,1)="W",$B$3+7*VALUE(LEFT(B19,LEN(B19)-1)),IF(RIGHT(B19,1)="M",EDATE($B$3,VALUE(LEFT(B19,LEN(B19)-1))),EDATE($B$3,12*VALUE(LEFT(B19,LEN(B19)-1))))),2)=6,1,IF(WEEKDAY(IF(RIGHT(B19,1)="W",$B$3+7*VALUE(LEFT(B19,LEN(B19)-1)),IF(RIGHT(B19,1)="M",EDATE($B$3,VALUE(LEFT(B19,LEN(B19)-1))),EDATE($B$3,12*VALUE(LEFT(B19,LEN(B19)-1))))),2)=7,2,0))),(IF(RIGHT(B19,1)="W",$B$3+7*VALUE(LEFT(B19,LEN(B19)-1)),IF(RIGHT(B19,1)="M",EDATE($B$3,VALUE(LEFT(B19,LEN(B19)-1))),EDATE($B$3,12*VALUE(LEFT(B19,LEN(B19)-1)))))+IF(WEEKDAY(IF(RIGHT(B19,1)="W",$B$3+7*VALUE(LEFT(B19,LEN(B19)-1)),IF(RIGHT(B19,1)="M",EDATE($B$3,VALUE(LEFT(B19,LEN(B19)-1))),EDATE($B$3,12*VALUE(LEFT(B19,LEN(B19)-1))))),2)=6,2,IF(WEEKDAY(IF(RIGHT(B19,1)="W",$B$3+7*VALUE(LEFT(B19,LEN(B19)-1)),IF(RIGHT(B19,1)="M",EDATE($B$3,VALUE(LEFT(B19,LEN(B19)-1))),EDATE($B$3,12*VALUE(LEFT(B19,LEN(B19)-1))))),2)=7,1,0)))) | D19: =(C19-$B$3)/365 | E19: =IFERROR(BDP(A19&" "&PX_SRC&" Curncy","PX_BID"),"ERROR PLZ FIX") | F19: =IFERROR(BDP(A19&" "&PX_SRC&" Curncy","PX_ASK"),"ERROR PLZ FIX") | G19: =IFERROR(BDP(A19&" "&PX_SRC&" Curncy","PX_LAST"),"ERROR PLZ FIX") | H19: =IFERROR(IF(Bootstrap!$G$4="Test 1",INDEX(Testing!$B$8:$B$47,MATCH(C19,Testing!$F$8:$F$47,0)),IF(Bootstrap!$G$4="Test 2",INDEX(Testing!$B$58:$B$97,MATCH(C19,Testing!$F$58:$F$97,0)),IF(Bootstrap!$G$4="Test 3",INDEX(Testing!$B$108:$B$147,MATCH(C19,Testing!$F$108:$F$147,0)),IF(Bootstrap!$G$4="Fixed (S490 07/21/26)",J19,IF(ISNUMBER(T19),T19,J19))))),J19) | J19: =IFERROR(INDEX(S490_Snapshot!$C$7:$C$38,MATCH(B19,S490_Snapshot!$B$7:$B$38,0)),"") | K19: S490_Snapshot | P19: =IF(COUNT(N19:O19)=2,(N19+O19)/2,"") | Q19: =IF(AND(ISNUMBER(N19),ISNUMBER(E19)),(E19-N19)*100,"") | R19: =IF(AND(ISNUMBER(O19),ISNUMBER(F19)),(F19-O19)*100,"") | S19: =IF(AND(ISNUMBER(P19),ISNUMBER(H19)),(H19-P19)*100,"") | T19: =IFERROR((E19+F19)/2,IFERROR(G19+0,"")) | U19: =IF(OR(T19="",NOT(ISNUMBER(J19))),"",(T19-J19)*100)
A20: Col H is the mid in use. Test cases match on the derived MATURITY DATE, not the tenor label - a capture writing 12M where this sheet writes 1Y still lines up. | B20: 18M | C20: =IF(MONTH((IF(RIGHT(B20,1)="W",$B$3+7*VALUE(LEFT(B20,LEN(B20)-1)),IF(RIGHT(B20,1)="M",EDATE($B$3,VALUE(LEFT(B20,LEN(B20)-1))),EDATE($B$3,12*VALUE(LEFT(B20,LEN(B20)-1)))))+IF(WEEKDAY(IF(RIGHT(B20,1)="W",$B$3+7*VALUE(LEFT(B20,LEN(B20)-1)),IF(RIGHT(B20,1)="M",EDATE($B$3,VALUE(LEFT(B20,LEN(B20)-1))),EDATE($B$3,12*VALUE(LEFT(B20,LEN(B20)-1))))),2)=6,2,IF(WEEKDAY(IF(RIGHT(B20,1)="W",$B$3+7*VALUE(LEFT(B20,LEN(B20)-1)),IF(RIGHT(B20,1)="M",EDATE($B$3,VALUE(LEFT(B20,LEN(B20)-1))),EDATE($B$3,12*VALUE(LEFT(B20,LEN(B20)-1))))),2)=7,1,0))))<>MONTH(IF(RIGHT(B20,1)="W",$B$3+7*VALUE(LEFT(B20,LEN(B20)-1)),IF(RIGHT(B20,1)="M",EDATE($B$3,VALUE(LEFT(B20,LEN(B20)-1))),EDATE($B$3,12*VALUE(LEFT(B20,LEN(B20)-1)))))),(IF(RIGHT(B20,1)="W",$B$3+7*VALUE(LEFT(B20,LEN(B20)-1)),IF(RIGHT(B20,1)="M",EDATE($B$3,VALUE(LEFT(B20,LEN(B20)-1))),EDATE($B$3,12*VALUE(LEFT(B20,LEN(B20)-1)))))-IF(WEEKDAY(IF(RIGHT(B20,1)="W",$B$3+7*VALUE(LEFT(B20,LEN(B20)-1)),IF(RIGHT(B20,1)="M",EDATE($B$3,VALUE(LEFT(B20,LEN(B20)-1))),EDATE($B$3,12*VALUE(LEFT(B20,LEN(B20)-1))))),2)=6,1,IF(WEEKDAY(IF(RIGHT(B20,1)="W",$B$3+7*VALUE(LEFT(B20,LEN(B20)-1)),IF(RIGHT(B20,1)="M",EDATE($B$3,VALUE(LEFT(B20,LEN(B20)-1))),EDATE($B$3,12*VALUE(LEFT(B20,LEN(B20)-1))))),2)=7,2,0))),(IF(RIGHT(B20,1)="W",$B$3+7*VALUE(LEFT(B20,LEN(B20)-1)),IF(RIGHT(B20,1)="M",EDATE($B$3,VALUE(LEFT(B20,LEN(B20)-1))),EDATE($B$3,12*VALUE(LEFT(B20,LEN(B20)-1)))))+IF(WEEKDAY(IF(RIGHT(B20,1)="W",$B$3+7*VALUE(LEFT(B20,LEN(B20)-1)),IF(RIGHT(B20,1)="M",EDATE($B$3,VALUE(LEFT(B20,LEN(B20)-1))),EDATE($B$3,12*VALUE(LEFT(B20,LEN(B20)-1))))),2)=6,2,IF(WEEKDAY(IF(RIGHT(B20,1)="W",$B$3+7*VALUE(LEFT(B20,LEN(B20)-1)),IF(RIGHT(B20,1)="M",EDATE($B$3,VALUE(LEFT(B20,LEN(B20)-1))),EDATE($B$3,12*VALUE(LEFT(B20,LEN(B20)-1))))),2)=7,1,0)))) | D20: =(C20-$B$3)/365 | E20: =IFERROR(BDP(A20&" "&PX_SRC&" Curncy","PX_BID"),"ERROR PLZ FIX") | F20: =IFERROR(BDP(A20&" "&PX_SRC&" Curncy","PX_ASK"),"ERROR PLZ FIX") | G20: =IFERROR(BDP(A20&" "&PX_SRC&" Curncy","PX_LAST"),"ERROR PLZ FIX") | H20: =IFERROR(IF(Bootstrap!$G$4="Test 1",INDEX(Testing!$B$8:$B$47,MATCH(C20,Testing!$F$8:$F$47,0)),IF(Bootstrap!$G$4="Test 2",INDEX(Testing!$B$58:$B$97,MATCH(C20,Testing!$F$58:$F$97,0)),IF(Bootstrap!$G$4="Test 3",INDEX(Testing!$B$108:$B$147,MATCH(C20,Testing!$F$108:$F$147,0)),IF(Bootstrap!$G$4="Fixed (S490 07/21/26)",J20,IF(ISNUMBER(T20),T20,J20))))),J20) | J20: =IFERROR(INDEX(S490_Snapshot!$C$7:$C$38,MATCH(B20,S490_Snapshot!$B$7:$B$38,0)),"") | K20: S490_Snapshot | P20: =IF(COUNT(N20:O20)=2,(N20+O20)/2,"") | Q20: =IF(AND(ISNUMBER(N20),ISNUMBER(E20)),(E20-N20)*100,"") | R20: =IF(AND(ISNUMBER(O20),ISNUMBER(F20)),(F20-O20)*100,"") | S20: =IF(AND(ISNUMBER(P20),ISNUMBER(H20)),(H20-P20)*100,"") | T20: =IFERROR((E20+F20)/2,IFERROR(G20+0,"")) | U20: =IF(OR(T20="",NOT(ISNUMBER(J20))),"",(T20-J20)*100)
A21: USOSFR2 | B21: 2Y | C21: =IF(MONTH((IF(RIGHT(B21,1)="W",$B$3+7*VALUE(LEFT(B21,LEN(B21)-1)),IF(RIGHT(B21,1)="M",EDATE($B$3,VALUE(LEFT(B21,LEN(B21)-1))),EDATE($B$3,12*VALUE(LEFT(B21,LEN(B21)-1)))))+IF(WEEKDAY(IF(RIGHT(B21,1)="W",$B$3+7*VALUE(LEFT(B21,LEN(B21)-1)),IF(RIGHT(B21,1)="M",EDATE($B$3,VALUE(LEFT(B21,LEN(B21)-1))),EDATE($B$3,12*VALUE(LEFT(B21,LEN(B21)-1))))),2)=6,2,IF(WEEKDAY(IF(RIGHT(B21,1)="W",$B$3+7*VALUE(LEFT(B21,LEN(B21)-1)),IF(RIGHT(B21,1)="M",EDATE($B$3,VALUE(LEFT(B21,LEN(B21)-1))),EDATE($B$3,12*VALUE(LEFT(B21,LEN(B21)-1))))),2)=7,1,0))))<>MONTH(IF(RIGHT(B21,1)="W",$B$3+7*VALUE(LEFT(B21,LEN(B21)-1)),IF(RIGHT(B21,1)="M",EDATE($B$3,VALUE(LEFT(B21,LEN(B21)-1))),EDATE($B$3,12*VALUE(LEFT(B21,LEN(B21)-1)))))),(IF(RIGHT(B21,1)="W",$B$3+7*VALUE(LEFT(B21,LEN(B21)-1)),IF(RIGHT(B21,1)="M",EDATE($B$3,VALUE(LEFT(B21,LEN(B21)-1))),EDATE($B$3,12*VALUE(LEFT(B21,LEN(B21)-1)))))-IF(WEEKDAY(IF(RIGHT(B21,1)="W",$B$3+7*VALUE(LEFT(B21,LEN(B21)-1)),IF(RIGHT(B21,1)="M",EDATE($B$3,VALUE(LEFT(B21,LEN(B21)-1))),EDATE($B$3,12*VALUE(LEFT(B21,LEN(B21)-1))))),2)=6,1,IF(WEEKDAY(IF(RIGHT(B21,1)="W",$B$3+7*VALUE(LEFT(B21,LEN(B21)-1)),IF(RIGHT(B21,1)="M",EDATE($B$3,VALUE(LEFT(B21,LEN(B21)-1))),EDATE($B$3,12*VALUE(LEFT(B21,LEN(B21)-1))))),2)=7,2,0))),(IF(RIGHT(B21,1)="W",$B$3+7*VALUE(LEFT(B21,LEN(B21)-1)),IF(RIGHT(B21,1)="M",EDATE($B$3,VALUE(LEFT(B21,LEN(B21)-1))),EDATE($B$3,12*VALUE(LEFT(B21,LEN(B21)-1)))))+IF(WEEKDAY(IF(RIGHT(B21,1)="W",$B$3+7*VALUE(LEFT(B21,LEN(B21)-1)),IF(RIGHT(B21,1)="M",EDATE($B$3,VALUE(LEFT(B21,LEN(B21)-1))),EDATE($B$3,12*VALUE(LEFT(B21,LEN(B21)-1))))),2)=6,2,IF(WEEKDAY(IF(RIGHT(B21,1)="W",$B$3+7*VALUE(LEFT(B21,LEN(B21)-1)),IF(RIGHT(B21,1)="M",EDATE($B$3,VALUE(LEFT(B21,LEN(B21)-1))),EDATE($B$3,12*VALUE(LEFT(B21,LEN(B21)-1))))),2)=7,1,0)))) | D21: =(C21-$B$3)/365 | E21: =IFERROR(BDP(A21&" "&PX_SRC&" Curncy","PX_BID"),"ERROR PLZ FIX") | F21: =IFERROR(BDP(A21&" "&PX_SRC&" Curncy","PX_ASK"),"ERROR PLZ FIX") | G21: =IFERROR(BDP(A21&" "&PX_SRC&" Curncy","PX_LAST"),"ERROR PLZ FIX") | H21: =IFERROR(IF(Bootstrap!$G$4="Test 1",INDEX(Testing!$B$8:$B$47,MATCH(C21,Testing!$F$8:$F$47,0)),IF(Bootstrap!$G$4="Test 2",INDEX(Testing!$B$58:$B$97,MATCH(C21,Testing!$F$58:$F$97,0)),IF(Bootstrap!$G$4="Test 3",INDEX(Testing!$B$108:$B$147,MATCH(C21,Testing!$F$108:$F$147,0)),IF(Bootstrap!$G$4="Fixed (S490 07/21/26)",J21,IF(ISNUMBER(T21),T21,J21))))),J21) | J21: =IFERROR(INDEX(S490_Snapshot!$C$7:$C$38,MATCH(B21,S490_Snapshot!$B$7:$B$38,0)),"") | K21: S490_Snapshot | P21: =IF(COUNT(N21:O21)=2,(N21+O21)/2,"") | Q21: =IF(AND(ISNUMBER(N21),ISNUMBER(E21)),(E21-N21)*100,"") | R21: =IF(AND(ISNUMBER(O21),ISNUMBER(F21)),(F21-O21)*100,"") | S21: =IF(AND(ISNUMBER(P21),ISNUMBER(H21)),(H21-P21)*100,"") | T21: =IFERROR((E21+F21)/2,IFERROR(G21+0,"")) | U21: =IF(OR(T21="",NOT(ISNUMBER(J21))),"",(T21-J21)*100)
A22: USOSFR3 | B22: 3Y | C22: =IF(MONTH((IF(RIGHT(B22,1)="W",$B$3+7*VALUE(LEFT(B22,LEN(B22)-1)),IF(RIGHT(B22,1)="M",EDATE($B$3,VALUE(LEFT(B22,LEN(B22)-1))),EDATE($B$3,12*VALUE(LEFT(B22,LEN(B22)-1)))))+IF(WEEKDAY(IF(RIGHT(B22,1)="W",$B$3+7*VALUE(LEFT(B22,LEN(B22)-1)),IF(RIGHT(B22,1)="M",EDATE($B$3,VALUE(LEFT(B22,LEN(B22)-1))),EDATE($B$3,12*VALUE(LEFT(B22,LEN(B22)-1))))),2)=6,2,IF(WEEKDAY(IF(RIGHT(B22,1)="W",$B$3+7*VALUE(LEFT(B22,LEN(B22)-1)),IF(RIGHT(B22,1)="M",EDATE($B$3,VALUE(LEFT(B22,LEN(B22)-1))),EDATE($B$3,12*VALUE(LEFT(B22,LEN(B22)-1))))),2)=7,1,0))))<>MONTH(IF(RIGHT(B22,1)="W",$B$3+7*VALUE(LEFT(B22,LEN(B22)-1)),IF(RIGHT(B22,1)="M",EDATE($B$3,VALUE(LEFT(B22,LEN(B22)-1))),EDATE($B$3,12*VALUE(LEFT(B22,LEN(B22)-1)))))),(IF(RIGHT(B22,1)="W",$B$3+7*VALUE(LEFT(B22,LEN(B22)-1)),IF(RIGHT(B22,1)="M",EDATE($B$3,VALUE(LEFT(B22,LEN(B22)-1))),EDATE($B$3,12*VALUE(LEFT(B22,LEN(B22)-1)))))-IF(WEEKDAY(IF(RIGHT(B22,1)="W",$B$3+7*VALUE(LEFT(B22,LEN(B22)-1)),IF(RIGHT(B22,1)="M",EDATE($B$3,VALUE(LEFT(B22,LEN(B22)-1))),EDATE($B$3,12*VALUE(LEFT(B22,LEN(B22)-1))))),2)=6,1,IF(WEEKDAY(IF(RIGHT(B22,1)="W",$B$3+7*VALUE(LEFT(B22,LEN(B22)-1)),IF(RIGHT(B22,1)="M",EDATE($B$3,VALUE(LEFT(B22,LEN(B22)-1))),EDATE($B$3,12*VALUE(LEFT(B22,LEN(B22)-1))))),2)=7,2,0))),(IF(RIGHT(B22,1)="W",$B$3+7*VALUE(LEFT(B22,LEN(B22)-1)),IF(RIGHT(B22,1)="M",EDATE($B$3,VALUE(LEFT(B22,LEN(B22)-1))),EDATE($B$3,12*VALUE(LEFT(B22,LEN(B22)-1)))))+IF(WEEKDAY(IF(RIGHT(B22,1)="W",$B$3+7*VALUE(LEFT(B22,LEN(B22)-1)),IF(RIGHT(B22,1)="M",EDATE($B$3,VALUE(LEFT(B22,LEN(B22)-1))),EDATE($B$3,12*VALUE(LEFT(B22,LEN(B22)-1))))),2)=6,2,IF(WEEKDAY(IF(RIGHT(B22,1)="W",$B$3+7*VALUE(LEFT(B22,LEN(B22)-1)),IF(RIGHT(B22,1)="M",EDATE($B$3,VALUE(LEFT(B22,LEN(B22)-1))),EDATE($B$3,12*VALUE(LEFT(B22,LEN(B22)-1))))),2)=7,1,0)))) | D22: =(C22-$B$3)/365 | E22: =IFERROR(BDP(A22&" "&PX_SRC&" Curncy","PX_BID"),"ERROR PLZ FIX") | F22: =IFERROR(BDP(A22&" "&PX_SRC&" Curncy","PX_ASK"),"ERROR PLZ FIX") | G22: =IFERROR(BDP(A22&" "&PX_SRC&" Curncy","PX_LAST"),"ERROR PLZ FIX") | H22: =IFERROR(IF(Bootstrap!$G$4="Test 1",INDEX(Testing!$B$8:$B$47,MATCH(C22,Testing!$F$8:$F$47,0)),IF(Bootstrap!$G$4="Test 2",INDEX(Testing!$B$58:$B$97,MATCH(C22,Testing!$F$58:$F$97,0)),IF(Bootstrap!$G$4="Test 3",INDEX(Testing!$B$108:$B$147,MATCH(C22,Testing!$F$108:$F$147,0)),IF(Bootstrap!$G$4="Fixed (S490 07/21/26)",J22,IF(ISNUMBER(T22),T22,J22))))),J22) | J22: =IFERROR(INDEX(S490_Snapshot!$C$7:$C$38,MATCH(B22,S490_Snapshot!$B$7:$B$38,0)),"") | K22: S490_Snapshot | P22: =IF(COUNT(N22:O22)=2,(N22+O22)/2,"") | Q22: =IF(AND(ISNUMBER(N22),ISNUMBER(E22)),(E22-N22)*100,"") | R22: =IF(AND(ISNUMBER(O22),ISNUMBER(F22)),(F22-O22)*100,"") | S22: =IF(AND(ISNUMBER(P22),ISNUMBER(H22)),(H22-P22)*100,"") | T22: =IFERROR((E22+F22)/2,IFERROR(G22+0,"")) | U22: =IF(OR(T22="",NOT(ISNUMBER(J22))),"",(T22-J22)*100)
A23: USOSFR4 | B23: 4Y | C23: =IF(MONTH((IF(RIGHT(B23,1)="W",$B$3+7*VALUE(LEFT(B23,LEN(B23)-1)),IF(RIGHT(B23,1)="M",EDATE($B$3,VALUE(LEFT(B23,LEN(B23)-1))),EDATE($B$3,12*VALUE(LEFT(B23,LEN(B23)-1)))))+IF(WEEKDAY(IF(RIGHT(B23,1)="W",$B$3+7*VALUE(LEFT(B23,LEN(B23)-1)),IF(RIGHT(B23,1)="M",EDATE($B$3,VALUE(LEFT(B23,LEN(B23)-1))),EDATE($B$3,12*VALUE(LEFT(B23,LEN(B23)-1))))),2)=6,2,IF(WEEKDAY(IF(RIGHT(B23,1)="W",$B$3+7*VALUE(LEFT(B23,LEN(B23)-1)),IF(RIGHT(B23,1)="M",EDATE($B$3,VALUE(LEFT(B23,LEN(B23)-1))),EDATE($B$3,12*VALUE(LEFT(B23,LEN(B23)-1))))),2)=7,1,0))))<>MONTH(IF(RIGHT(B23,1)="W",$B$3+7*VALUE(LEFT(B23,LEN(B23)-1)),IF(RIGHT(B23,1)="M",EDATE($B$3,VALUE(LEFT(B23,LEN(B23)-1))),EDATE($B$3,12*VALUE(LEFT(B23,LEN(B23)-1)))))),(IF(RIGHT(B23,1)="W",$B$3+7*VALUE(LEFT(B23,LEN(B23)-1)),IF(RIGHT(B23,1)="M",EDATE($B$3,VALUE(LEFT(B23,LEN(B23)-1))),EDATE($B$3,12*VALUE(LEFT(B23,LEN(B23)-1)))))-IF(WEEKDAY(IF(RIGHT(B23,1)="W",$B$3+7*VALUE(LEFT(B23,LEN(B23)-1)),IF(RIGHT(B23,1)="M",EDATE($B$3,VALUE(LEFT(B23,LEN(B23)-1))),EDATE($B$3,12*VALUE(LEFT(B23,LEN(B23)-1))))),2)=6,1,IF(WEEKDAY(IF(RIGHT(B23,1)="W",$B$3+7*VALUE(LEFT(B23,LEN(B23)-1)),IF(RIGHT(B23,1)="M",EDATE($B$3,VALUE(LEFT(B23,LEN(B23)-1))),EDATE($B$3,12*VALUE(LEFT(B23,LEN(B23)-1))))),2)=7,2,0))),(IF(RIGHT(B23,1)="W",$B$3+7*VALUE(LEFT(B23,LEN(B23)-1)),IF(RIGHT(B23,1)="M",EDATE($B$3,VALUE(LEFT(B23,LEN(B23)-1))),EDATE($B$3,12*VALUE(LEFT(B23,LEN(B23)-1)))))+IF(WEEKDAY(IF(RIGHT(B23,1)="W",$B$3+7*VALUE(LEFT(B23,LEN(B23)-1)),IF(RIGHT(B23,1)="M",EDATE($B$3,VALUE(LEFT(B23,LEN(B23)-1))),EDATE($B$3,12*VALUE(LEFT(B23,LEN(B23)-1))))),2)=6,2,IF(WEEKDAY(IF(RIGHT(B23,1)="W",$B$3+7*VALUE(LEFT(B23,LEN(B23)-1)),IF(RIGHT(B23,1)="M",EDATE($B$3,VALUE(LEFT(B23,LEN(B23)-1))),EDATE($B$3,12*VALUE(LEFT(B23,LEN(B23)-1))))),2)=7,1,0)))) | D23: =(C23-$B$3)/365 | E23: =IFERROR(BDP(A23&" "&PX_SRC&" Curncy","PX_BID"),"ERROR PLZ FIX") | F23: =IFERROR(BDP(A23&" "&PX_SRC&" Curncy","PX_ASK"),"ERROR PLZ FIX") | G23: =IFERROR(BDP(A23&" "&PX_SRC&" Curncy","PX_LAST"),"ERROR PLZ FIX") | H23: =IFERROR(IF(Bootstrap!$G$4="Test 1",INDEX(Testing!$B$8:$B$47,MATCH(C23,Testing!$F$8:$F$47,0)),IF(Bootstrap!$G$4="Test 2",INDEX(Testing!$B$58:$B$97,MATCH(C23,Testing!$F$58:$F$97,0)),IF(Bootstrap!$G$4="Test 3",INDEX(Testing!$B$108:$B$147,MATCH(C23,Testing!$F$108:$F$147,0)),IF(Bootstrap!$G$4="Fixed (S490 07/21/26)",J23,IF(ISNUMBER(T23),T23,J23))))),J23) | J23: =IFERROR(INDEX(S490_Snapshot!$C$7:$C$38,MATCH(B23,S490_Snapshot!$B$7:$B$38,0)),"") | K23: S490_Snapshot | P23: =IF(COUNT(N23:O23)=2,(N23+O23)/2,"") | Q23: =IF(AND(ISNUMBER(N23),ISNUMBER(E23)),(E23-N23)*100,"") | R23: =IF(AND(ISNUMBER(O23),ISNUMBER(F23)),(F23-O23)*100,"") | S23: =IF(AND(ISNUMBER(P23),ISNUMBER(H23)),(H23-P23)*100,"") | T23: =IFERROR((E23+F23)/2,IFERROR(G23+0,"")) | U23: =IF(OR(T23="",NOT(ISNUMBER(J23))),"",(T23-J23)*100)
A24: USOSFR5 | B24: 5Y | C24: =IF(MONTH((IF(RIGHT(B24,1)="W",$B$3+7*VALUE(LEFT(B24,LEN(B24)-1)),IF(RIGHT(B24,1)="M",EDATE($B$3,VALUE(LEFT(B24,LEN(B24)-1))),EDATE($B$3,12*VALUE(LEFT(B24,LEN(B24)-1)))))+IF(WEEKDAY(IF(RIGHT(B24,1)="W",$B$3+7*VALUE(LEFT(B24,LEN(B24)-1)),IF(RIGHT(B24,1)="M",EDATE($B$3,VALUE(LEFT(B24,LEN(B24)-1))),EDATE($B$3,12*VALUE(LEFT(B24,LEN(B24)-1))))),2)=6,2,IF(WEEKDAY(IF(RIGHT(B24,1)="W",$B$3+7*VALUE(LEFT(B24,LEN(B24)-1)),IF(RIGHT(B24,1)="M",EDATE($B$3,VALUE(LEFT(B24,LEN(B24)-1))),EDATE($B$3,12*VALUE(LEFT(B24,LEN(B24)-1))))),2)=7,1,0))))<>MONTH(IF(RIGHT(B24,1)="W",$B$3+7*VALUE(LEFT(B24,LEN(B24)-1)),IF(RIGHT(B24,1)="M",EDATE($B$3,VALUE(LEFT(B24,LEN(B24)-1))),EDATE($B$3,12*VALUE(LEFT(B24,LEN(B24)-1)))))),(IF(RIGHT(B24,1)="W",$B$3+7*VALUE(LEFT(B24,LEN(B24)-1)),IF(RIGHT(B24,1)="M",EDATE($B$3,VALUE(LEFT(B24,LEN(B24)-1))),EDATE($B$3,12*VALUE(LEFT(B24,LEN(B24)-1)))))-IF(WEEKDAY(IF(RIGHT(B24,1)="W",$B$3+7*VALUE(LEFT(B24,LEN(B24)-1)),IF(RIGHT(B24,1)="M",EDATE($B$3,VALUE(LEFT(B24,LEN(B24)-1))),EDATE($B$3,12*VALUE(LEFT(B24,LEN(B24)-1))))),2)=6,1,IF(WEEKDAY(IF(RIGHT(B24,1)="W",$B$3+7*VALUE(LEFT(B24,LEN(B24)-1)),IF(RIGHT(B24,1)="M",EDATE($B$3,VALUE(LEFT(B24,LEN(B24)-1))),EDATE($B$3,12*VALUE(LEFT(B24,LEN(B24)-1))))),2)=7,2,0))),(IF(RIGHT(B24,1)="W",$B$3+7*VALUE(LEFT(B24,LEN(B24)-1)),IF(RIGHT(B24,1)="M",EDATE($B$3,VALUE(LEFT(B24,LEN(B24)-1))),EDATE($B$3,12*VALUE(LEFT(B24,LEN(B24)-1)))))+IF(WEEKDAY(IF(RIGHT(B24,1)="W",$B$3+7*VALUE(LEFT(B24,LEN(B24)-1)),IF(RIGHT(B24,1)="M",EDATE($B$3,VALUE(LEFT(B24,LEN(B24)-1))),EDATE($B$3,12*VALUE(LEFT(B24,LEN(B24)-1))))),2)=6,2,IF(WEEKDAY(IF(RIGHT(B24,1)="W",$B$3+7*VALUE(LEFT(B24,LEN(B24)-1)),IF(RIGHT(B24,1)="M",EDATE($B$3,VALUE(LEFT(B24,LEN(B24)-1))),EDATE($B$3,12*VALUE(LEFT(B24,LEN(B24)-1))))),2)=7,1,0)))) | D24: =(C24-$B$3)/365 | E24: =IFERROR(BDP(A24&" "&PX_SRC&" Curncy","PX_BID"),"ERROR PLZ FIX") | F24: =IFERROR(BDP(A24&" "&PX_SRC&" Curncy","PX_ASK"),"ERROR PLZ FIX") | G24: =IFERROR(BDP(A24&" "&PX_SRC&" Curncy","PX_LAST"),"ERROR PLZ FIX") | H24: =IFERROR(IF(Bootstrap!$G$4="Test 1",INDEX(Testing!$B$8:$B$47,MATCH(C24,Testing!$F$8:$F$47,0)),IF(Bootstrap!$G$4="Test 2",INDEX(Testing!$B$58:$B$97,MATCH(C24,Testing!$F$58:$F$97,0)),IF(Bootstrap!$G$4="Test 3",INDEX(Testing!$B$108:$B$147,MATCH(C24,Testing!$F$108:$F$147,0)),IF(Bootstrap!$G$4="Fixed (S490 07/21/26)",J24,IF(ISNUMBER(T24),T24,J24))))),J24) | I24: Y | J24: =IFERROR(INDEX(S490_Snapshot!$C$7:$C$38,MATCH(B24,S490_Snapshot!$B$7:$B$38,0)),"") | K24: S490_Snapshot | P24: =IF(COUNT(N24:O24)=2,(N24+O24)/2,"") | Q24: =IF(AND(ISNUMBER(N24),ISNUMBER(E24)),(E24-N24)*100,"") | R24: =IF(AND(ISNUMBER(O24),ISNUMBER(F24)),(F24-O24)*100,"") | S24: =IF(AND(ISNUMBER(P24),ISNUMBER(H24)),(H24-P24)*100,"") | T24: =IFERROR((E24+F24)/2,IFERROR(G24+0,"")) | U24: =IF(OR(T24="",NOT(ISNUMBER(J24))),"",(T24-J24)*100)
A25: USOSFR6 | B25: 6Y | C25: =IF(MONTH((IF(RIGHT(B25,1)="W",$B$3+7*VALUE(LEFT(B25,LEN(B25)-1)),IF(RIGHT(B25,1)="M",EDATE($B$3,VALUE(LEFT(B25,LEN(B25)-1))),EDATE($B$3,12*VALUE(LEFT(B25,LEN(B25)-1)))))+IF(WEEKDAY(IF(RIGHT(B25,1)="W",$B$3+7*VALUE(LEFT(B25,LEN(B25)-1)),IF(RIGHT(B25,1)="M",EDATE($B$3,VALUE(LEFT(B25,LEN(B25)-1))),EDATE($B$3,12*VALUE(LEFT(B25,LEN(B25)-1))))),2)=6,2,IF(WEEKDAY(IF(RIGHT(B25,1)="W",$B$3+7*VALUE(LEFT(B25,LEN(B25)-1)),IF(RIGHT(B25,1)="M",EDATE($B$3,VALUE(LEFT(B25,LEN(B25)-1))),EDATE($B$3,12*VALUE(LEFT(B25,LEN(B25)-1))))),2)=7,1,0))))<>MONTH(IF(RIGHT(B25,1)="W",$B$3+7*VALUE(LEFT(B25,LEN(B25)-1)),IF(RIGHT(B25,1)="M",EDATE($B$3,VALUE(LEFT(B25,LEN(B25)-1))),EDATE($B$3,12*VALUE(LEFT(B25,LEN(B25)-1)))))),(IF(RIGHT(B25,1)="W",$B$3+7*VALUE(LEFT(B25,LEN(B25)-1)),IF(RIGHT(B25,1)="M",EDATE($B$3,VALUE(LEFT(B25,LEN(B25)-1))),EDATE($B$3,12*VALUE(LEFT(B25,LEN(B25)-1)))))-IF(WEEKDAY(IF(RIGHT(B25,1)="W",$B$3+7*VALUE(LEFT(B25,LEN(B25)-1)),IF(RIGHT(B25,1)="M",EDATE($B$3,VALUE(LEFT(B25,LEN(B25)-1))),EDATE($B$3,12*VALUE(LEFT(B25,LEN(B25)-1))))),2)=6,1,IF(WEEKDAY(IF(RIGHT(B25,1)="W",$B$3+7*VALUE(LEFT(B25,LEN(B25)-1)),IF(RIGHT(B25,1)="M",EDATE($B$3,VALUE(LEFT(B25,LEN(B25)-1))),EDATE($B$3,12*VALUE(LEFT(B25,LEN(B25)-1))))),2)=7,2,0))),(IF(RIGHT(B25,1)="W",$B$3+7*VALUE(LEFT(B25,LEN(B25)-1)),IF(RIGHT(B25,1)="M",EDATE($B$3,VALUE(LEFT(B25,LEN(B25)-1))),EDATE($B$3,12*VALUE(LEFT(B25,LEN(B25)-1)))))+IF(WEEKDAY(IF(RIGHT(B25,1)="W",$B$3+7*VALUE(LEFT(B25,LEN(B25)-1)),IF(RIGHT(B25,1)="M",EDATE($B$3,VALUE(LEFT(B25,LEN(B25)-1))),EDATE($B$3,12*VALUE(LEFT(B25,LEN(B25)-1))))),2)=6,2,IF(WEEKDAY(IF(RIGHT(B25,1)="W",$B$3+7*VALUE(LEFT(B25,LEN(B25)-1)),IF(RIGHT(B25,1)="M",EDATE($B$3,VALUE(LEFT(B25,LEN(B25)-1))),EDATE($B$3,12*VALUE(LEFT(B25,LEN(B25)-1))))),2)=7,1,0)))) | D25: =(C25-$B$3)/365 | E25: =IFERROR(BDP(A25&" "&PX_SRC&" Curncy","PX_BID"),"ERROR PLZ FIX") | F25: =IFERROR(BDP(A25&" "&PX_SRC&" Curncy","PX_ASK"),"ERROR PLZ FIX") | G25: =IFERROR(BDP(A25&" "&PX_SRC&" Curncy","PX_LAST"),"ERROR PLZ FIX") | H25: =IFERROR(IF(Bootstrap!$G$4="Test 1",INDEX(Testing!$B$8:$B$47,MATCH(C25,Testing!$F$8:$F$47,0)),IF(Bootstrap!$G$4="Test 2",INDEX(Testing!$B$58:$B$97,MATCH(C25,Testing!$F$58:$F$97,0)),IF(Bootstrap!$G$4="Test 3",INDEX(Testing!$B$108:$B$147,MATCH(C25,Testing!$F$108:$F$147,0)),IF(Bootstrap!$G$4="Fixed (S490 07/21/26)",J25,IF(ISNUMBER(T25),T25,J25))))),J25) | I25: Y | J25: =IFERROR(INDEX(S490_Snapshot!$C$7:$C$38,MATCH(B25,S490_Snapshot!$B$7:$B$38,0)),"") | K25: S490_Snapshot | P25: =IF(COUNT(N25:O25)=2,(N25+O25)/2,"") | Q25: =IF(AND(ISNUMBER(N25),ISNUMBER(E25)),(E25-N25)*100,"") | R25: =IF(AND(ISNUMBER(O25),ISNUMBER(F25)),(F25-O25)*100,"") | S25: =IF(AND(ISNUMBER(P25),ISNUMBER(H25)),(H25-P25)*100,"") | T25: =IFERROR((E25+F25)/2,IFERROR(G25+0,"")) | U25: =IF(OR(T25="",NOT(ISNUMBER(J25))),"",(T25-J25)*100)
A26: USOSFR7 | B26: 7Y | C26: =IF(MONTH((IF(RIGHT(B26,1)="W",$B$3+7*VALUE(LEFT(B26,LEN(B26)-1)),IF(RIGHT(B26,1)="M",EDATE($B$3,VALUE(LEFT(B26,LEN(B26)-1))),EDATE($B$3,12*VALUE(LEFT(B26,LEN(B26)-1)))))+IF(WEEKDAY(IF(RIGHT(B26,1)="W",$B$3+7*VALUE(LEFT(B26,LEN(B26)-1)),IF(RIGHT(B26,1)="M",EDATE($B$3,VALUE(LEFT(B26,LEN(B26)-1))),EDATE($B$3,12*VALUE(LEFT(B26,LEN(B26)-1))))),2)=6,2,IF(WEEKDAY(IF(RIGHT(B26,1)="W",$B$3+7*VALUE(LEFT(B26,LEN(B26)-1)),IF(RIGHT(B26,1)="M",EDATE($B$3,VALUE(LEFT(B26,LEN(B26)-1))),EDATE($B$3,12*VALUE(LEFT(B26,LEN(B26)-1))))),2)=7,1,0))))<>MONTH(IF(RIGHT(B26,1)="W",$B$3+7*VALUE(LEFT(B26,LEN(B26)-1)),IF(RIGHT(B26,1)="M",EDATE($B$3,VALUE(LEFT(B26,LEN(B26)-1))),EDATE($B$3,12*VALUE(LEFT(B26,LEN(B26)-1)))))),(IF(RIGHT(B26,1)="W",$B$3+7*VALUE(LEFT(B26,LEN(B26)-1)),IF(RIGHT(B26,1)="M",EDATE($B$3,VALUE(LEFT(B26,LEN(B26)-1))),EDATE($B$3,12*VALUE(LEFT(B26,LEN(B26)-1)))))-IF(WEEKDAY(IF(RIGHT(B26,1)="W",$B$3+7*VALUE(LEFT(B26,LEN(B26)-1)),IF(RIGHT(B26,1)="M",EDATE($B$3,VALUE(LEFT(B26,LEN(B26)-1))),EDATE($B$3,12*VALUE(LEFT(B26,LEN(B26)-1))))),2)=6,1,IF(WEEKDAY(IF(RIGHT(B26,1)="W",$B$3+7*VALUE(LEFT(B26,LEN(B26)-1)),IF(RIGHT(B26,1)="M",EDATE($B$3,VALUE(LEFT(B26,LEN(B26)-1))),EDATE($B$3,12*VALUE(LEFT(B26,LEN(B26)-1))))),2)=7,2,0))),(IF(RIGHT(B26,1)="W",$B$3+7*VALUE(LEFT(B26,LEN(B26)-1)),IF(RIGHT(B26,1)="M",EDATE($B$3,VALUE(LEFT(B26,LEN(B26)-1))),EDATE($B$3,12*VALUE(LEFT(B26,LEN(B26)-1)))))+IF(WEEKDAY(IF(RIGHT(B26,1)="W",$B$3+7*VALUE(LEFT(B26,LEN(B26)-1)),IF(RIGHT(B26,1)="M",EDATE($B$3,VALUE(LEFT(B26,LEN(B26)-1))),EDATE($B$3,12*VALUE(LEFT(B26,LEN(B26)-1))))),2)=6,2,IF(WEEKDAY(IF(RIGHT(B26,1)="W",$B$3+7*VALUE(LEFT(B26,LEN(B26)-1)),IF(RIGHT(B26,1)="M",EDATE($B$3,VALUE(LEFT(B26,LEN(B26)-1))),EDATE($B$3,12*VALUE(LEFT(B26,LEN(B26)-1))))),2)=7,1,0)))) | D26: =(C26-$B$3)/365 | E26: =IFERROR(BDP(A26&" "&PX_SRC&" Curncy","PX_BID"),"ERROR PLZ FIX") | F26: =IFERROR(BDP(A26&" "&PX_SRC&" Curncy","PX_ASK"),"ERROR PLZ FIX") | G26: =IFERROR(BDP(A26&" "&PX_SRC&" Curncy","PX_LAST"),"ERROR PLZ FIX") | H26: =IFERROR(IF(Bootstrap!$G$4="Test 1",INDEX(Testing!$B$8:$B$47,MATCH(C26,Testing!$F$8:$F$47,0)),IF(Bootstrap!$G$4="Test 2",INDEX(Testing!$B$58:$B$97,MATCH(C26,Testing!$F$58:$F$97,0)),IF(Bootstrap!$G$4="Test 3",INDEX(Testing!$B$108:$B$147,MATCH(C26,Testing!$F$108:$F$147,0)),IF(Bootstrap!$G$4="Fixed (S490 07/21/26)",J26,IF(ISNUMBER(T26),T26,J26))))),J26) | I26: Y | J26: =IFERROR(INDEX(S490_Snapshot!$C$7:$C$38,MATCH(B26,S490_Snapshot!$B$7:$B$38,0)),"") | K26: S490_Snapshot | P26: =IF(COUNT(N26:O26)=2,(N26+O26)/2,"") | Q26: =IF(AND(ISNUMBER(N26),ISNUMBER(E26)),(E26-N26)*100,"") | R26: =IF(AND(ISNUMBER(O26),ISNUMBER(F26)),(F26-O26)*100,"") | S26: =IF(AND(ISNUMBER(P26),ISNUMBER(H26)),(H26-P26)*100,"") | T26: =IFERROR((E26+F26)/2,IFERROR(G26+0,"")) | U26: =IF(OR(T26="",NOT(ISNUMBER(J26))),"",(T26-J26)*100)
A27: USOSFR8 | B27: 8Y | C27: =IF(MONTH((IF(RIGHT(B27,1)="W",$B$3+7*VALUE(LEFT(B27,LEN(B27)-1)),IF(RIGHT(B27,1)="M",EDATE($B$3,VALUE(LEFT(B27,LEN(B27)-1))),EDATE($B$3,12*VALUE(LEFT(B27,LEN(B27)-1)))))+IF(WEEKDAY(IF(RIGHT(B27,1)="W",$B$3+7*VALUE(LEFT(B27,LEN(B27)-1)),IF(RIGHT(B27,1)="M",EDATE($B$3,VALUE(LEFT(B27,LEN(B27)-1))),EDATE($B$3,12*VALUE(LEFT(B27,LEN(B27)-1))))),2)=6,2,IF(WEEKDAY(IF(RIGHT(B27,1)="W",$B$3+7*VALUE(LEFT(B27,LEN(B27)-1)),IF(RIGHT(B27,1)="M",EDATE($B$3,VALUE(LEFT(B27,LEN(B27)-1))),EDATE($B$3,12*VALUE(LEFT(B27,LEN(B27)-1))))),2)=7,1,0))))<>MONTH(IF(RIGHT(B27,1)="W",$B$3+7*VALUE(LEFT(B27,LEN(B27)-1)),IF(RIGHT(B27,1)="M",EDATE($B$3,VALUE(LEFT(B27,LEN(B27)-1))),EDATE($B$3,12*VALUE(LEFT(B27,LEN(B27)-1)))))),(IF(RIGHT(B27,1)="W",$B$3+7*VALUE(LEFT(B27,LEN(B27)-1)),IF(RIGHT(B27,1)="M",EDATE($B$3,VALUE(LEFT(B27,LEN(B27)-1))),EDATE($B$3,12*VALUE(LEFT(B27,LEN(B27)-1)))))-IF(WEEKDAY(IF(RIGHT(B27,1)="W",$B$3+7*VALUE(LEFT(B27,LEN(B27)-1)),IF(RIGHT(B27,1)="M",EDATE($B$3,VALUE(LEFT(B27,LEN(B27)-1))),EDATE($B$3,12*VALUE(LEFT(B27,LEN(B27)-1))))),2)=6,1,IF(WEEKDAY(IF(RIGHT(B27,1)="W",$B$3+7*VALUE(LEFT(B27,LEN(B27)-1)),IF(RIGHT(B27,1)="M",EDATE($B$3,VALUE(LEFT(B27,LEN(B27)-1))),EDATE($B$3,12*VALUE(LEFT(B27,LEN(B27)-1))))),2)=7,2,0))),(IF(RIGHT(B27,1)="W",$B$3+7*VALUE(LEFT(B27,LEN(B27)-1)),IF(RIGHT(B27,1)="M",EDATE($B$3,VALUE(LEFT(B27,LEN(B27)-1))),EDATE($B$3,12*VALUE(LEFT(B27,LEN(B27)-1)))))+IF(WEEKDAY(IF(RIGHT(B27,1)="W",$B$3+7*VALUE(LEFT(B27,LEN(B27)-1)),IF(RIGHT(B27,1)="M",EDATE($B$3,VALUE(LEFT(B27,LEN(B27)-1))),EDATE($B$3,12*VALUE(LEFT(B27,LEN(B27)-1))))),2)=6,2,IF(WEEKDAY(IF(RIGHT(B27,1)="W",$B$3+7*VALUE(LEFT(B27,LEN(B27)-1)),IF(RIGHT(B27,1)="M",EDATE($B$3,VALUE(LEFT(B27,LEN(B27)-1))),EDATE($B$3,12*VALUE(LEFT(B27,LEN(B27)-1))))),2)=7,1,0)))) | D27: =(C27-$B$3)/365 | E27: =IFERROR(BDP(A27&" "&PX_SRC&" Curncy","PX_BID"),"ERROR PLZ FIX") | F27: =IFERROR(BDP(A27&" "&PX_SRC&" Curncy","PX_ASK"),"ERROR PLZ FIX") | G27: =IFERROR(BDP(A27&" "&PX_SRC&" Curncy","PX_LAST"),"ERROR PLZ FIX") | H27: =IFERROR(IF(Bootstrap!$G$4="Test 1",INDEX(Testing!$B$8:$B$47,MATCH(C27,Testing!$F$8:$F$47,0)),IF(Bootstrap!$G$4="Test 2",INDEX(Testing!$B$58:$B$97,MATCH(C27,Testing!$F$58:$F$97,0)),IF(Bootstrap!$G$4="Test 3",INDEX(Testing!$B$108:$B$147,MATCH(C27,Testing!$F$108:$F$147,0)),IF(Bootstrap!$G$4="Fixed (S490 07/21/26)",J27,IF(ISNUMBER(T27),T27,J27))))),J27) | I27: Y | J27: =IFERROR(INDEX(S490_Snapshot!$C$7:$C$38,MATCH(B27,S490_Snapshot!$B$7:$B$38,0)),"") | K27: S490_Snapshot | P27: =IF(COUNT(N27:O27)=2,(N27+O27)/2,"") | Q27: =IF(AND(ISNUMBER(N27),ISNUMBER(E27)),(E27-N27)*100,"") | R27: =IF(AND(ISNUMBER(O27),ISNUMBER(F27)),(F27-O27)*100,"") | S27: =IF(AND(ISNUMBER(P27),ISNUMBER(H27)),(H27-P27)*100,"") | T27: =IFERROR((E27+F27)/2,IFERROR(G27+0,"")) | U27: =IF(OR(T27="",NOT(ISNUMBER(J27))),"",(T27-J27)*100)
A28: USOSFR9 | B28: 9Y | C28: =IF(MONTH((IF(RIGHT(B28,1)="W",$B$3+7*VALUE(LEFT(B28,LEN(B28)-1)),IF(RIGHT(B28,1)="M",EDATE($B$3,VALUE(LEFT(B28,LEN(B28)-1))),EDATE($B$3,12*VALUE(LEFT(B28,LEN(B28)-1)))))+IF(WEEKDAY(IF(RIGHT(B28,1)="W",$B$3+7*VALUE(LEFT(B28,LEN(B28)-1)),IF(RIGHT(B28,1)="M",EDATE($B$3,VALUE(LEFT(B28,LEN(B28)-1))),EDATE($B$3,12*VALUE(LEFT(B28,LEN(B28)-1))))),2)=6,2,IF(WEEKDAY(IF(RIGHT(B28,1)="W",$B$3+7*VALUE(LEFT(B28,LEN(B28)-1)),IF(RIGHT(B28,1)="M",EDATE($B$3,VALUE(LEFT(B28,LEN(B28)-1))),EDATE($B$3,12*VALUE(LEFT(B28,LEN(B28)-1))))),2)=7,1,0))))<>MONTH(IF(RIGHT(B28,1)="W",$B$3+7*VALUE(LEFT(B28,LEN(B28)-1)),IF(RIGHT(B28,1)="M",EDATE($B$3,VALUE(LEFT(B28,LEN(B28)-1))),EDATE($B$3,12*VALUE(LEFT(B28,LEN(B28)-1)))))),(IF(RIGHT(B28,1)="W",$B$3+7*VALUE(LEFT(B28,LEN(B28)-1)),IF(RIGHT(B28,1)="M",EDATE($B$3,VALUE(LEFT(B28,LEN(B28)-1))),EDATE($B$3,12*VALUE(LEFT(B28,LEN(B28)-1)))))-IF(WEEKDAY(IF(RIGHT(B28,1)="W",$B$3+7*VALUE(LEFT(B28,LEN(B28)-1)),IF(RIGHT(B28,1)="M",EDATE($B$3,VALUE(LEFT(B28,LEN(B28)-1))),EDATE($B$3,12*VALUE(LEFT(B28,LEN(B28)-1))))),2)=6,1,IF(WEEKDAY(IF(RIGHT(B28,1)="W",$B$3+7*VALUE(LEFT(B28,LEN(B28)-1)),IF(RIGHT(B28,1)="M",EDATE($B$3,VALUE(LEFT(B28,LEN(B28)-1))),EDATE($B$3,12*VALUE(LEFT(B28,LEN(B28)-1))))),2)=7,2,0))),(IF(RIGHT(B28,1)="W",$B$3+7*VALUE(LEFT(B28,LEN(B28)-1)),IF(RIGHT(B28,1)="M",EDATE($B$3,VALUE(LEFT(B28,LEN(B28)-1))),EDATE($B$3,12*VALUE(LEFT(B28,LEN(B28)-1)))))+IF(WEEKDAY(IF(RIGHT(B28,1)="W",$B$3+7*VALUE(LEFT(B28,LEN(B28)-1)),IF(RIGHT(B28,1)="M",EDATE($B$3,VALUE(LEFT(B28,LEN(B28)-1))),EDATE($B$3,12*VALUE(LEFT(B28,LEN(B28)-1))))),2)=6,2,IF(WEEKDAY(IF(RIGHT(B28,1)="W",$B$3+7*VALUE(LEFT(B28,LEN(B28)-1)),IF(RIGHT(B28,1)="M",EDATE($B$3,VALUE(LEFT(B28,LEN(B28)-1))),EDATE($B$3,12*VALUE(LEFT(B28,LEN(B28)-1))))),2)=7,1,0)))) | D28: =(C28-$B$3)/365 | E28: =IFERROR(BDP(A28&" "&PX_SRC&" Curncy","PX_BID"),"ERROR PLZ FIX") | F28: =IFERROR(BDP(A28&" "&PX_SRC&" Curncy","PX_ASK"),"ERROR PLZ FIX") | G28: =IFERROR(BDP(A28&" "&PX_SRC&" Curncy","PX_LAST"),"ERROR PLZ FIX") | H28: =IFERROR(IF(Bootstrap!$G$4="Test 1",INDEX(Testing!$B$8:$B$47,MATCH(C28,Testing!$F$8:$F$47,0)),IF(Bootstrap!$G$4="Test 2",INDEX(Testing!$B$58:$B$97,MATCH(C28,Testing!$F$58:$F$97,0)),IF(Bootstrap!$G$4="Test 3",INDEX(Testing!$B$108:$B$147,MATCH(C28,Testing!$F$108:$F$147,0)),IF(Bootstrap!$G$4="Fixed (S490 07/21/26)",J28,IF(ISNUMBER(T28),T28,J28))))),J28) | I28: Y | J28: =IFERROR(INDEX(S490_Snapshot!$C$7:$C$38,MATCH(B28,S490_Snapshot!$B$7:$B$38,0)),"") | K28: S490_Snapshot | P28: =IF(COUNT(N28:O28)=2,(N28+O28)/2,"") | Q28: =IF(AND(ISNUMBER(N28),ISNUMBER(E28)),(E28-N28)*100,"") | R28: =IF(AND(ISNUMBER(O28),ISNUMBER(F28)),(F28-O28)*100,"") | S28: =IF(AND(ISNUMBER(P28),ISNUMBER(H28)),(H28-P28)*100,"") | T28: =IFERROR((E28+F28)/2,IFERROR(G28+0,"")) | U28: =IF(OR(T28="",NOT(ISNUMBER(J28))),"",(T28-J28)*100)
A29: USOSFR10 | B29: 10Y | C29: =IF(MONTH((IF(RIGHT(B29,1)="W",$B$3+7*VALUE(LEFT(B29,LEN(B29)-1)),IF(RIGHT(B29,1)="M",EDATE($B$3,VALUE(LEFT(B29,LEN(B29)-1))),EDATE($B$3,12*VALUE(LEFT(B29,LEN(B29)-1)))))+IF(WEEKDAY(IF(RIGHT(B29,1)="W",$B$3+7*VALUE(LEFT(B29,LEN(B29)-1)),IF(RIGHT(B29,1)="M",EDATE($B$3,VALUE(LEFT(B29,LEN(B29)-1))),EDATE($B$3,12*VALUE(LEFT(B29,LEN(B29)-1))))),2)=6,2,IF(WEEKDAY(IF(RIGHT(B29,1)="W",$B$3+7*VALUE(LEFT(B29,LEN(B29)-1)),IF(RIGHT(B29,1)="M",EDATE($B$3,VALUE(LEFT(B29,LEN(B29)-1))),EDATE($B$3,12*VALUE(LEFT(B29,LEN(B29)-1))))),2)=7,1,0))))<>MONTH(IF(RIGHT(B29,1)="W",$B$3+7*VALUE(LEFT(B29,LEN(B29)-1)),IF(RIGHT(B29,1)="M",EDATE($B$3,VALUE(LEFT(B29,LEN(B29)-1))),EDATE($B$3,12*VALUE(LEFT(B29,LEN(B29)-1)))))),(IF(RIGHT(B29,1)="W",$B$3+7*VALUE(LEFT(B29,LEN(B29)-1)),IF(RIGHT(B29,1)="M",EDATE($B$3,VALUE(LEFT(B29,LEN(B29)-1))),EDATE($B$3,12*VALUE(LEFT(B29,LEN(B29)-1)))))-IF(WEEKDAY(IF(RIGHT(B29,1)="W",$B$3+7*VALUE(LEFT(B29,LEN(B29)-1)),IF(RIGHT(B29,1)="M",EDATE($B$3,VALUE(LEFT(B29,LEN(B29)-1))),EDATE($B$3,12*VALUE(LEFT(B29,LEN(B29)-1))))),2)=6,1,IF(WEEKDAY(IF(RIGHT(B29,1)="W",$B$3+7*VALUE(LEFT(B29,LEN(B29)-1)),IF(RIGHT(B29,1)="M",EDATE($B$3,VALUE(LEFT(B29,LEN(B29)-1))),EDATE($B$3,12*VALUE(LEFT(B29,LEN(B29)-1))))),2)=7,2,0))),(IF(RIGHT(B29,1)="W",$B$3+7*VALUE(LEFT(B29,LEN(B29)-1)),IF(RIGHT(B29,1)="M",EDATE($B$3,VALUE(LEFT(B29,LEN(B29)-1))),EDATE($B$3,12*VALUE(LEFT(B29,LEN(B29)-1)))))+IF(WEEKDAY(IF(RIGHT(B29,1)="W",$B$3+7*VALUE(LEFT(B29,LEN(B29)-1)),IF(RIGHT(B29,1)="M",EDATE($B$3,VALUE(LEFT(B29,LEN(B29)-1))),EDATE($B$3,12*VALUE(LEFT(B29,LEN(B29)-1))))),2)=6,2,IF(WEEKDAY(IF(RIGHT(B29,1)="W",$B$3+7*VALUE(LEFT(B29,LEN(B29)-1)),IF(RIGHT(B29,1)="M",EDATE($B$3,VALUE(LEFT(B29,LEN(B29)-1))),EDATE($B$3,12*VALUE(LEFT(B29,LEN(B29)-1))))),2)=7,1,0)))) | D29: =(C29-$B$3)/365 | E29: =IFERROR(BDP(A29&" "&PX_SRC&" Curncy","PX_BID"),"ERROR PLZ FIX") | F29: =IFERROR(BDP(A29&" "&PX_SRC&" Curncy","PX_ASK"),"ERROR PLZ FIX") | G29: =IFERROR(BDP(A29&" "&PX_SRC&" Curncy","PX_LAST"),"ERROR PLZ FIX") | H29: =IFERROR(IF(Bootstrap!$G$4="Test 1",INDEX(Testing!$B$8:$B$47,MATCH(C29,Testing!$F$8:$F$47,0)),IF(Bootstrap!$G$4="Test 2",INDEX(Testing!$B$58:$B$97,MATCH(C29,Testing!$F$58:$F$97,0)),IF(Bootstrap!$G$4="Test 3",INDEX(Testing!$B$108:$B$147,MATCH(C29,Testing!$F$108:$F$147,0)),IF(Bootstrap!$G$4="Fixed (S490 07/21/26)",J29,IF(ISNUMBER(T29),T29,J29))))),J29) | I29: Y | J29: =IFERROR(INDEX(S490_Snapshot!$C$7:$C$38,MATCH(B29,S490_Snapshot!$B$7:$B$38,0)),"") | K29: S490_Snapshot | P29: =IF(COUNT(N29:O29)=2,(N29+O29)/2,"") | Q29: =IF(AND(ISNUMBER(N29),ISNUMBER(E29)),(E29-N29)*100,"") | R29: =IF(AND(ISNUMBER(O29),ISNUMBER(F29)),(F29-O29)*100,"") | S29: =IF(AND(ISNUMBER(P29),ISNUMBER(H29)),(H29-P29)*100,"") | T29: =IFERROR((E29+F29)/2,IFERROR(G29+0,"")) | U29: =IF(OR(T29="",NOT(ISNUMBER(J29))),"",(T29-J29)*100)
A30: USOSFR12 | B30: 12Y | C30: =IF(MONTH((IF(RIGHT(B30,1)="W",$B$3+7*VALUE(LEFT(B30,LEN(B30)-1)),IF(RIGHT(B30,1)="M",EDATE($B$3,VALUE(LEFT(B30,LEN(B30)-1))),EDATE($B$3,12*VALUE(LEFT(B30,LEN(B30)-1)))))+IF(WEEKDAY(IF(RIGHT(B30,1)="W",$B$3+7*VALUE(LEFT(B30,LEN(B30)-1)),IF(RIGHT(B30,1)="M",EDATE($B$3,VALUE(LEFT(B30,LEN(B30)-1))),EDATE($B$3,12*VALUE(LEFT(B30,LEN(B30)-1))))),2)=6,2,IF(WEEKDAY(IF(RIGHT(B30,1)="W",$B$3+7*VALUE(LEFT(B30,LEN(B30)-1)),IF(RIGHT(B30,1)="M",EDATE($B$3,VALUE(LEFT(B30,LEN(B30)-1))),EDATE($B$3,12*VALUE(LEFT(B30,LEN(B30)-1))))),2)=7,1,0))))<>MONTH(IF(RIGHT(B30,1)="W",$B$3+7*VALUE(LEFT(B30,LEN(B30)-1)),IF(RIGHT(B30,1)="M",EDATE($B$3,VALUE(LEFT(B30,LEN(B30)-1))),EDATE($B$3,12*VALUE(LEFT(B30,LEN(B30)-1)))))),(IF(RIGHT(B30,1)="W",$B$3+7*VALUE(LEFT(B30,LEN(B30)-1)),IF(RIGHT(B30,1)="M",EDATE($B$3,VALUE(LEFT(B30,LEN(B30)-1))),EDATE($B$3,12*VALUE(LEFT(B30,LEN(B30)-1)))))-IF(WEEKDAY(IF(RIGHT(B30,1)="W",$B$3+7*VALUE(LEFT(B30,LEN(B30)-1)),IF(RIGHT(B30,1)="M",EDATE($B$3,VALUE(LEFT(B30,LEN(B30)-1))),EDATE($B$3,12*VALUE(LEFT(B30,LEN(B30)-1))))),2)=6,1,IF(WEEKDAY(IF(RIGHT(B30,1)="W",$B$3+7*VALUE(LEFT(B30,LEN(B30)-1)),IF(RIGHT(B30,1)="M",EDATE($B$3,VALUE(LEFT(B30,LEN(B30)-1))),EDATE($B$3,12*VALUE(LEFT(B30,LEN(B30)-1))))),2)=7,2,0))),(IF(RIGHT(B30,1)="W",$B$3+7*VALUE(LEFT(B30,LEN(B30)-1)),IF(RIGHT(B30,1)="M",EDATE($B$3,VALUE(LEFT(B30,LEN(B30)-1))),EDATE($B$3,12*VALUE(LEFT(B30,LEN(B30)-1)))))+IF(WEEKDAY(IF(RIGHT(B30,1)="W",$B$3+7*VALUE(LEFT(B30,LEN(B30)-1)),IF(RIGHT(B30,1)="M",EDATE($B$3,VALUE(LEFT(B30,LEN(B30)-1))),EDATE($B$3,12*VALUE(LEFT(B30,LEN(B30)-1))))),2)=6,2,IF(WEEKDAY(IF(RIGHT(B30,1)="W",$B$3+7*VALUE(LEFT(B30,LEN(B30)-1)),IF(RIGHT(B30,1)="M",EDATE($B$3,VALUE(LEFT(B30,LEN(B30)-1))),EDATE($B$3,12*VALUE(LEFT(B30,LEN(B30)-1))))),2)=7,1,0)))) | D30: =(C30-$B$3)/365 | E30: =IFERROR(BDP(A30&" "&PX_SRC&" Curncy","PX_BID"),"ERROR PLZ FIX") | F30: =IFERROR(BDP(A30&" "&PX_SRC&" Curncy","PX_ASK"),"ERROR PLZ FIX") | G30: =IFERROR(BDP(A30&" "&PX_SRC&" Curncy","PX_LAST"),"ERROR PLZ FIX") | H30: =IFERROR(IF(Bootstrap!$G$4="Test 1",INDEX(Testing!$B$8:$B$47,MATCH(C30,Testing!$F$8:$F$47,0)),IF(Bootstrap!$G$4="Test 2",INDEX(Testing!$B$58:$B$97,MATCH(C30,Testing!$F$58:$F$97,0)),IF(Bootstrap!$G$4="Test 3",INDEX(Testing!$B$108:$B$147,MATCH(C30,Testing!$F$108:$F$147,0)),IF(Bootstrap!$G$4="Fixed (S490 07/21/26)",J30,IF(ISNUMBER(T30),T30,J30))))),J30) | I30: Y | J30: =IFERROR(INDEX(S490_Snapshot!$C$7:$C$38,MATCH(B30,S490_Snapshot!$B$7:$B$38,0)),"") | K30: S490_Snapshot | P30: =IF(COUNT(N30:O30)=2,(N30+O30)/2,"") | Q30: =IF(AND(ISNUMBER(N30),ISNUMBER(E30)),(E30-N30)*100,"") | R30: =IF(AND(ISNUMBER(O30),ISNUMBER(F30)),(F30-O30)*100,"") | S30: =IF(AND(ISNUMBER(P30),ISNUMBER(H30)),(H30-P30)*100,"") | T30: =IFERROR((E30+F30)/2,IFERROR(G30+0,"")) | U30: =IF(OR(T30="",NOT(ISNUMBER(J30))),"",(T30-J30)*100)
A31: USOSFR15 | B31: 15Y | C31: =IF(MONTH((IF(RIGHT(B31,1)="W",$B$3+7*VALUE(LEFT(B31,LEN(B31)-1)),IF(RIGHT(B31,1)="M",EDATE($B$3,VALUE(LEFT(B31,LEN(B31)-1))),EDATE($B$3,12*VALUE(LEFT(B31,LEN(B31)-1)))))+IF(WEEKDAY(IF(RIGHT(B31,1)="W",$B$3+7*VALUE(LEFT(B31,LEN(B31)-1)),IF(RIGHT(B31,1)="M",EDATE($B$3,VALUE(LEFT(B31,LEN(B31)-1))),EDATE($B$3,12*VALUE(LEFT(B31,LEN(B31)-1))))),2)=6,2,IF(WEEKDAY(IF(RIGHT(B31,1)="W",$B$3+7*VALUE(LEFT(B31,LEN(B31)-1)),IF(RIGHT(B31,1)="M",EDATE($B$3,VALUE(LEFT(B31,LEN(B31)-1))),EDATE($B$3,12*VALUE(LEFT(B31,LEN(B31)-1))))),2)=7,1,0))))<>MONTH(IF(RIGHT(B31,1)="W",$B$3+7*VALUE(LEFT(B31,LEN(B31)-1)),IF(RIGHT(B31,1)="M",EDATE($B$3,VALUE(LEFT(B31,LEN(B31)-1))),EDATE($B$3,12*VALUE(LEFT(B31,LEN(B31)-1)))))),(IF(RIGHT(B31,1)="W",$B$3+7*VALUE(LEFT(B31,LEN(B31)-1)),IF(RIGHT(B31,1)="M",EDATE($B$3,VALUE(LEFT(B31,LEN(B31)-1))),EDATE($B$3,12*VALUE(LEFT(B31,LEN(B31)-1)))))-IF(WEEKDAY(IF(RIGHT(B31,1)="W",$B$3+7*VALUE(LEFT(B31,LEN(B31)-1)),IF(RIGHT(B31,1)="M",EDATE($B$3,VALUE(LEFT(B31,LEN(B31)-1))),EDATE($B$3,12*VALUE(LEFT(B31,LEN(B31)-1))))),2)=6,1,IF(WEEKDAY(IF(RIGHT(B31,1)="W",$B$3+7*VALUE(LEFT(B31,LEN(B31)-1)),IF(RIGHT(B31,1)="M",EDATE($B$3,VALUE(LEFT(B31,LEN(B31)-1))),EDATE($B$3,12*VALUE(LEFT(B31,LEN(B31)-1))))),2)=7,2,0))),(IF(RIGHT(B31,1)="W",$B$3+7*VALUE(LEFT(B31,LEN(B31)-1)),IF(RIGHT(B31,1)="M",EDATE($B$3,VALUE(LEFT(B31,LEN(B31)-1))),EDATE($B$3,12*VALUE(LEFT(B31,LEN(B31)-1)))))+IF(WEEKDAY(IF(RIGHT(B31,1)="W",$B$3+7*VALUE(LEFT(B31,LEN(B31)-1)),IF(RIGHT(B31,1)="M",EDATE($B$3,VALUE(LEFT(B31,LEN(B31)-1))),EDATE($B$3,12*VALUE(LEFT(B31,LEN(B31)-1))))),2)=6,2,IF(WEEKDAY(IF(RIGHT(B31,1)="W",$B$3+7*VALUE(LEFT(B31,LEN(B31)-1)),IF(RIGHT(B31,1)="M",EDATE($B$3,VALUE(LEFT(B31,LEN(B31)-1))),EDATE($B$3,12*VALUE(LEFT(B31,LEN(B31)-1))))),2)=7,1,0)))) | D31: =(C31-$B$3)/365 | E31: =IFERROR(BDP(A31&" "&PX_SRC&" Curncy","PX_BID"),"ERROR PLZ FIX") | F31: =IFERROR(BDP(A31&" "&PX_SRC&" Curncy","PX_ASK"),"ERROR PLZ FIX") | G31: =IFERROR(BDP(A31&" "&PX_SRC&" Curncy","PX_LAST"),"ERROR PLZ FIX") | H31: =IFERROR(IF(Bootstrap!$G$4="Test 1",INDEX(Testing!$B$8:$B$47,MATCH(C31,Testing!$F$8:$F$47,0)),IF(Bootstrap!$G$4="Test 2",INDEX(Testing!$B$58:$B$97,MATCH(C31,Testing!$F$58:$F$97,0)),IF(Bootstrap!$G$4="Test 3",INDEX(Testing!$B$108:$B$147,MATCH(C31,Testing!$F$108:$F$147,0)),IF(Bootstrap!$G$4="Fixed (S490 07/21/26)",J31,IF(ISNUMBER(T31),T31,J31))))),J31) | I31: Y | J31: =IFERROR(INDEX(S490_Snapshot!$C$7:$C$38,MATCH(B31,S490_Snapshot!$B$7:$B$38,0)),"") | K31: S490_Snapshot | P31: =IF(COUNT(N31:O31)=2,(N31+O31)/2,"") | Q31: =IF(AND(ISNUMBER(N31),ISNUMBER(E31)),(E31-N31)*100,"") | R31: =IF(AND(ISNUMBER(O31),ISNUMBER(F31)),(F31-O31)*100,"") | S31: =IF(AND(ISNUMBER(P31),ISNUMBER(H31)),(H31-P31)*100,"") | T31: =IFERROR((E31+F31)/2,IFERROR(G31+0,"")) | U31: =IF(OR(T31="",NOT(ISNUMBER(J31))),"",(T31-J31)*100)
A32: USOSFR20 | B32: 20Y | C32: =IF(MONTH((IF(RIGHT(B32,1)="W",$B$3+7*VALUE(LEFT(B32,LEN(B32)-1)),IF(RIGHT(B32,1)="M",EDATE($B$3,VALUE(LEFT(B32,LEN(B32)-1))),EDATE($B$3,12*VALUE(LEFT(B32,LEN(B32)-1)))))+IF(WEEKDAY(IF(RIGHT(B32,1)="W",$B$3+7*VALUE(LEFT(B32,LEN(B32)-1)),IF(RIGHT(B32,1)="M",EDATE($B$3,VALUE(LEFT(B32,LEN(B32)-1))),EDATE($B$3,12*VALUE(LEFT(B32,LEN(B32)-1))))),2)=6,2,IF(WEEKDAY(IF(RIGHT(B32,1)="W",$B$3+7*VALUE(LEFT(B32,LEN(B32)-1)),IF(RIGHT(B32,1)="M",EDATE($B$3,VALUE(LEFT(B32,LEN(B32)-1))),EDATE($B$3,12*VALUE(LEFT(B32,LEN(B32)-1))))),2)=7,1,0))))<>MONTH(IF(RIGHT(B32,1)="W",$B$3+7*VALUE(LEFT(B32,LEN(B32)-1)),IF(RIGHT(B32,1)="M",EDATE($B$3,VALUE(LEFT(B32,LEN(B32)-1))),EDATE($B$3,12*VALUE(LEFT(B32,LEN(B32)-1)))))),(IF(RIGHT(B32,1)="W",$B$3+7*VALUE(LEFT(B32,LEN(B32)-1)),IF(RIGHT(B32,1)="M",EDATE($B$3,VALUE(LEFT(B32,LEN(B32)-1))),EDATE($B$3,12*VALUE(LEFT(B32,LEN(B32)-1)))))-IF(WEEKDAY(IF(RIGHT(B32,1)="W",$B$3+7*VALUE(LEFT(B32,LEN(B32)-1)),IF(RIGHT(B32,1)="M",EDATE($B$3,VALUE(LEFT(B32,LEN(B32)-1))),EDATE($B$3,12*VALUE(LEFT(B32,LEN(B32)-1))))),2)=6,1,IF(WEEKDAY(IF(RIGHT(B32,1)="W",$B$3+7*VALUE(LEFT(B32,LEN(B32)-1)),IF(RIGHT(B32,1)="M",EDATE($B$3,VALUE(LEFT(B32,LEN(B32)-1))),EDATE($B$3,12*VALUE(LEFT(B32,LEN(B32)-1))))),2)=7,2,0))),(IF(RIGHT(B32,1)="W",$B$3+7*VALUE(LEFT(B32,LEN(B32)-1)),IF(RIGHT(B32,1)="M",EDATE($B$3,VALUE(LEFT(B32,LEN(B32)-1))),EDATE($B$3,12*VALUE(LEFT(B32,LEN(B32)-1)))))+IF(WEEKDAY(IF(RIGHT(B32,1)="W",$B$3+7*VALUE(LEFT(B32,LEN(B32)-1)),IF(RIGHT(B32,1)="M",EDATE($B$3,VALUE(LEFT(B32,LEN(B32)-1))),EDATE($B$3,12*VALUE(LEFT(B32,LEN(B32)-1))))),2)=6,2,IF(WEEKDAY(IF(RIGHT(B32,1)="W",$B$3+7*VALUE(LEFT(B32,LEN(B32)-1)),IF(RIGHT(B32,1)="M",EDATE($B$3,VALUE(LEFT(B32,LEN(B32)-1))),EDATE($B$3,12*VALUE(LEFT(B32,LEN(B32)-1))))),2)=7,1,0)))) | D32: =(C32-$B$3)/365 | E32: =IFERROR(BDP(A32&" "&PX_SRC&" Curncy","PX_BID"),"ERROR PLZ FIX") | F32: =IFERROR(BDP(A32&" "&PX_SRC&" Curncy","PX_ASK"),"ERROR PLZ FIX") | G32: =IFERROR(BDP(A32&" "&PX_SRC&" Curncy","PX_LAST"),"ERROR PLZ FIX") | H32: =IFERROR(IF(Bootstrap!$G$4="Test 1",INDEX(Testing!$B$8:$B$47,MATCH(C32,Testing!$F$8:$F$47,0)),IF(Bootstrap!$G$4="Test 2",INDEX(Testing!$B$58:$B$97,MATCH(C32,Testing!$F$58:$F$97,0)),IF(Bootstrap!$G$4="Test 3",INDEX(Testing!$B$108:$B$147,MATCH(C32,Testing!$F$108:$F$147,0)),IF(Bootstrap!$G$4="Fixed (S490 07/21/26)",J32,IF(ISNUMBER(T32),T32,J32))))),J32) | I32: Y | J32: =IFERROR(INDEX(S490_Snapshot!$C$7:$C$38,MATCH(B32,S490_Snapshot!$B$7:$B$38,0)),"") | K32: S490_Snapshot | P32: =IF(COUNT(N32:O32)=2,(N32+O32)/2,"") | Q32: =IF(AND(ISNUMBER(N32),ISNUMBER(E32)),(E32-N32)*100,"") | R32: =IF(AND(ISNUMBER(O32),ISNUMBER(F32)),(F32-O32)*100,"") | S32: =IF(AND(ISNUMBER(P32),ISNUMBER(H32)),(H32-P32)*100,"") | T32: =IFERROR((E32+F32)/2,IFERROR(G32+0,"")) | U32: =IF(OR(T32="",NOT(ISNUMBER(J32))),"",(T32-J32)*100)
A33: USOSFR25 | B33: 25Y | C33: =IF(MONTH((IF(RIGHT(B33,1)="W",$B$3+7*VALUE(LEFT(B33,LEN(B33)-1)),IF(RIGHT(B33,1)="M",EDATE($B$3,VALUE(LEFT(B33,LEN(B33)-1))),EDATE($B$3,12*VALUE(LEFT(B33,LEN(B33)-1)))))+IF(WEEKDAY(IF(RIGHT(B33,1)="W",$B$3+7*VALUE(LEFT(B33,LEN(B33)-1)),IF(RIGHT(B33,1)="M",EDATE($B$3,VALUE(LEFT(B33,LEN(B33)-1))),EDATE($B$3,12*VALUE(LEFT(B33,LEN(B33)-1))))),2)=6,2,IF(WEEKDAY(IF(RIGHT(B33,1)="W",$B$3+7*VALUE(LEFT(B33,LEN(B33)-1)),IF(RIGHT(B33,1)="M",EDATE($B$3,VALUE(LEFT(B33,LEN(B33)-1))),EDATE($B$3,12*VALUE(LEFT(B33,LEN(B33)-1))))),2)=7,1,0))))<>MONTH(IF(RIGHT(B33,1)="W",$B$3+7*VALUE(LEFT(B33,LEN(B33)-1)),IF(RIGHT(B33,1)="M",EDATE($B$3,VALUE(LEFT(B33,LEN(B33)-1))),EDATE($B$3,12*VALUE(LEFT(B33,LEN(B33)-1)))))),(IF(RIGHT(B33,1)="W",$B$3+7*VALUE(LEFT(B33,LEN(B33)-1)),IF(RIGHT(B33,1)="M",EDATE($B$3,VALUE(LEFT(B33,LEN(B33)-1))),EDATE($B$3,12*VALUE(LEFT(B33,LEN(B33)-1)))))-IF(WEEKDAY(IF(RIGHT(B33,1)="W",$B$3+7*VALUE(LEFT(B33,LEN(B33)-1)),IF(RIGHT(B33,1)="M",EDATE($B$3,VALUE(LEFT(B33,LEN(B33)-1))),EDATE($B$3,12*VALUE(LEFT(B33,LEN(B33)-1))))),2)=6,1,IF(WEEKDAY(IF(RIGHT(B33,1)="W",$B$3+7*VALUE(LEFT(B33,LEN(B33)-1)),IF(RIGHT(B33,1)="M",EDATE($B$3,VALUE(LEFT(B33,LEN(B33)-1))),EDATE($B$3,12*VALUE(LEFT(B33,LEN(B33)-1))))),2)=7,2,0))),(IF(RIGHT(B33,1)="W",$B$3+7*VALUE(LEFT(B33,LEN(B33)-1)),IF(RIGHT(B33,1)="M",EDATE($B$3,VALUE(LEFT(B33,LEN(B33)-1))),EDATE($B$3,12*VALUE(LEFT(B33,LEN(B33)-1)))))+IF(WEEKDAY(IF(RIGHT(B33,1)="W",$B$3+7*VALUE(LEFT(B33,LEN(B33)-1)),IF(RIGHT(B33,1)="M",EDATE($B$3,VALUE(LEFT(B33,LEN(B33)-1))),EDATE($B$3,12*VALUE(LEFT(B33,LEN(B33)-1))))),2)=6,2,IF(WEEKDAY(IF(RIGHT(B33,1)="W",$B$3+7*VALUE(LEFT(B33,LEN(B33)-1)),IF(RIGHT(B33,1)="M",EDATE($B$3,VALUE(LEFT(B33,LEN(B33)-1))),EDATE($B$3,12*VALUE(LEFT(B33,LEN(B33)-1))))),2)=7,1,0)))) | D33: =(C33-$B$3)/365 | E33: =IFERROR(BDP(A33&" "&PX_SRC&" Curncy","PX_BID"),"ERROR PLZ FIX") | F33: =IFERROR(BDP(A33&" "&PX_SRC&" Curncy","PX_ASK"),"ERROR PLZ FIX") | G33: =IFERROR(BDP(A33&" "&PX_SRC&" Curncy","PX_LAST"),"ERROR PLZ FIX") | H33: =IFERROR(IF(Bootstrap!$G$4="Test 1",INDEX(Testing!$B$8:$B$47,MATCH(C33,Testing!$F$8:$F$47,0)),IF(Bootstrap!$G$4="Test 2",INDEX(Testing!$B$58:$B$97,MATCH(C33,Testing!$F$58:$F$97,0)),IF(Bootstrap!$G$4="Test 3",INDEX(Testing!$B$108:$B$147,MATCH(C33,Testing!$F$108:$F$147,0)),IF(Bootstrap!$G$4="Fixed (S490 07/21/26)",J33,IF(ISNUMBER(T33),T33,J33))))),J33) | I33: Y | J33: =IFERROR(INDEX(S490_Snapshot!$C$7:$C$38,MATCH(B33,S490_Snapshot!$B$7:$B$38,0)),"") | K33: S490_Snapshot | P33: =IF(COUNT(N33:O33)=2,(N33+O33)/2,"") | Q33: =IF(AND(ISNUMBER(N33),ISNUMBER(E33)),(E33-N33)*100,"") | R33: =IF(AND(ISNUMBER(O33),ISNUMBER(F33)),(F33-O33)*100,"") | S33: =IF(AND(ISNUMBER(P33),ISNUMBER(H33)),(H33-P33)*100,"") | T33: =IFERROR((E33+F33)/2,IFERROR(G33+0,"")) | U33: =IF(OR(T33="",NOT(ISNUMBER(J33))),"",(T33-J33)*100)
A34: USOSFR30 | B34: 30Y | C34: =IF(MONTH((IF(RIGHT(B34,1)="W",$B$3+7*VALUE(LEFT(B34,LEN(B34)-1)),IF(RIGHT(B34,1)="M",EDATE($B$3,VALUE(LEFT(B34,LEN(B34)-1))),EDATE($B$3,12*VALUE(LEFT(B34,LEN(B34)-1)))))+IF(WEEKDAY(IF(RIGHT(B34,1)="W",$B$3+7*VALUE(LEFT(B34,LEN(B34)-1)),IF(RIGHT(B34,1)="M",EDATE($B$3,VALUE(LEFT(B34,LEN(B34)-1))),EDATE($B$3,12*VALUE(LEFT(B34,LEN(B34)-1))))),2)=6,2,IF(WEEKDAY(IF(RIGHT(B34,1)="W",$B$3+7*VALUE(LEFT(B34,LEN(B34)-1)),IF(RIGHT(B34,1)="M",EDATE($B$3,VALUE(LEFT(B34,LEN(B34)-1))),EDATE($B$3,12*VALUE(LEFT(B34,LEN(B34)-1))))),2)=7,1,0))))<>MONTH(IF(RIGHT(B34,1)="W",$B$3+7*VALUE(LEFT(B34,LEN(B34)-1)),IF(RIGHT(B34,1)="M",EDATE($B$3,VALUE(LEFT(B34,LEN(B34)-1))),EDATE($B$3,12*VALUE(LEFT(B34,LEN(B34)-1)))))),(IF(RIGHT(B34,1)="W",$B$3+7*VALUE(LEFT(B34,LEN(B34)-1)),IF(RIGHT(B34,1)="M",EDATE($B$3,VALUE(LEFT(B34,LEN(B34)-1))),EDATE($B$3,12*VALUE(LEFT(B34,LEN(B34)-1)))))-IF(WEEKDAY(IF(RIGHT(B34,1)="W",$B$3+7*VALUE(LEFT(B34,LEN(B34)-1)),IF(RIGHT(B34,1)="M",EDATE($B$3,VALUE(LEFT(B34,LEN(B34)-1))),EDATE($B$3,12*VALUE(LEFT(B34,LEN(B34)-1))))),2)=6,1,IF(WEEKDAY(IF(RIGHT(B34,1)="W",$B$3+7*VALUE(LEFT(B34,LEN(B34)-1)),IF(RIGHT(B34,1)="M",EDATE($B$3,VALUE(LEFT(B34,LEN(B34)-1))),EDATE($B$3,12*VALUE(LEFT(B34,LEN(B34)-1))))),2)=7,2,0))),(IF(RIGHT(B34,1)="W",$B$3+7*VALUE(LEFT(B34,LEN(B34)-1)),IF(RIGHT(B34,1)="M",EDATE($B$3,VALUE(LEFT(B34,LEN(B34)-1))),EDATE($B$3,12*VALUE(LEFT(B34,LEN(B34)-1)))))+IF(WEEKDAY(IF(RIGHT(B34,1)="W",$B$3+7*VALUE(LEFT(B34,LEN(B34)-1)),IF(RIGHT(B34,1)="M",EDATE($B$3,VALUE(LEFT(B34,LEN(B34)-1))),EDATE($B$3,12*VALUE(LEFT(B34,LEN(B34)-1))))),2)=6,2,IF(WEEKDAY(IF(RIGHT(B34,1)="W",$B$3+7*VALUE(LEFT(B34,LEN(B34)-1)),IF(RIGHT(B34,1)="M",EDATE($B$3,VALUE(LEFT(B34,LEN(B34)-1))),EDATE($B$3,12*VALUE(LEFT(B34,LEN(B34)-1))))),2)=7,1,0)))) | D34: =(C34-$B$3)/365 | E34: =IFERROR(BDP(A34&" "&PX_SRC&" Curncy","PX_BID"),"ERROR PLZ FIX") | F34: =IFERROR(BDP(A34&" "&PX_SRC&" Curncy","PX_ASK"),"ERROR PLZ FIX") | G34: =IFERROR(BDP(A34&" "&PX_SRC&" Curncy","PX_LAST"),"ERROR PLZ FIX") | H34: =IFERROR(IF(Bootstrap!$G$4="Test 1",INDEX(Testing!$B$8:$B$47,MATCH(C34,Testing!$F$8:$F$47,0)),IF(Bootstrap!$G$4="Test 2",INDEX(Testing!$B$58:$B$97,MATCH(C34,Testing!$F$58:$F$97,0)),IF(Bootstrap!$G$4="Test 3",INDEX(Testing!$B$108:$B$147,MATCH(C34,Testing!$F$108:$F$147,0)),IF(Bootstrap!$G$4="Fixed (S490 07/21/26)",J34,IF(ISNUMBER(T34),T34,J34))))),J34) | I34: Y | J34: =IFERROR(INDEX(S490_Snapshot!$C$7:$C$38,MATCH(B34,S490_Snapshot!$B$7:$B$38,0)),"") | K34: S490_Snapshot | P34: =IF(COUNT(N34:O34)=2,(N34+O34)/2,"") | Q34: =IF(AND(ISNUMBER(N34),ISNUMBER(E34)),(E34-N34)*100,"") | R34: =IF(AND(ISNUMBER(O34),ISNUMBER(F34)),(F34-O34)*100,"") | S34: =IF(AND(ISNUMBER(P34),ISNUMBER(H34)),(H34-P34)*100,"") | T34: =IFERROR((E34+F34)/2,IFERROR(G34+0,"")) | U34: =IF(OR(T34="",NOT(ISNUMBER(J34))),"",(T34-J34)*100)
A35: USOSFR40 | B35: 40Y | C35: =IF(MONTH((IF(RIGHT(B35,1)="W",$B$3+7*VALUE(LEFT(B35,LEN(B35)-1)),IF(RIGHT(B35,1)="M",EDATE($B$3,VALUE(LEFT(B35,LEN(B35)-1))),EDATE($B$3,12*VALUE(LEFT(B35,LEN(B35)-1)))))+IF(WEEKDAY(IF(RIGHT(B35,1)="W",$B$3+7*VALUE(LEFT(B35,LEN(B35)-1)),IF(RIGHT(B35,1)="M",EDATE($B$3,VALUE(LEFT(B35,LEN(B35)-1))),EDATE($B$3,12*VALUE(LEFT(B35,LEN(B35)-1))))),2)=6,2,IF(WEEKDAY(IF(RIGHT(B35,1)="W",$B$3+7*VALUE(LEFT(B35,LEN(B35)-1)),IF(RIGHT(B35,1)="M",EDATE($B$3,VALUE(LEFT(B35,LEN(B35)-1))),EDATE($B$3,12*VALUE(LEFT(B35,LEN(B35)-1))))),2)=7,1,0))))<>MONTH(IF(RIGHT(B35,1)="W",$B$3+7*VALUE(LEFT(B35,LEN(B35)-1)),IF(RIGHT(B35,1)="M",EDATE($B$3,VALUE(LEFT(B35,LEN(B35)-1))),EDATE($B$3,12*VALUE(LEFT(B35,LEN(B35)-1)))))),(IF(RIGHT(B35,1)="W",$B$3+7*VALUE(LEFT(B35,LEN(B35)-1)),IF(RIGHT(B35,1)="M",EDATE($B$3,VALUE(LEFT(B35,LEN(B35)-1))),EDATE($B$3,12*VALUE(LEFT(B35,LEN(B35)-1)))))-IF(WEEKDAY(IF(RIGHT(B35,1)="W",$B$3+7*VALUE(LEFT(B35,LEN(B35)-1)),IF(RIGHT(B35,1)="M",EDATE($B$3,VALUE(LEFT(B35,LEN(B35)-1))),EDATE($B$3,12*VALUE(LEFT(B35,LEN(B35)-1))))),2)=6,1,IF(WEEKDAY(IF(RIGHT(B35,1)="W",$B$3+7*VALUE(LEFT(B35,LEN(B35)-1)),IF(RIGHT(B35,1)="M",EDATE($B$3,VALUE(LEFT(B35,LEN(B35)-1))),EDATE($B$3,12*VALUE(LEFT(B35,LEN(B35)-1))))),2)=7,2,0))),(IF(RIGHT(B35,1)="W",$B$3+7*VALUE(LEFT(B35,LEN(B35)-1)),IF(RIGHT(B35,1)="M",EDATE($B$3,VALUE(LEFT(B35,LEN(B35)-1))),EDATE($B$3,12*VALUE(LEFT(B35,LEN(B35)-1)))))+IF(WEEKDAY(IF(RIGHT(B35,1)="W",$B$3+7*VALUE(LEFT(B35,LEN(B35)-1)),IF(RIGHT(B35,1)="M",EDATE($B$3,VALUE(LEFT(B35,LEN(B35)-1))),EDATE($B$3,12*VALUE(LEFT(B35,LEN(B35)-1))))),2)=6,2,IF(WEEKDAY(IF(RIGHT(B35,1)="W",$B$3+7*VALUE(LEFT(B35,LEN(B35)-1)),IF(RIGHT(B35,1)="M",EDATE($B$3,VALUE(LEFT(B35,LEN(B35)-1))),EDATE($B$3,12*VALUE(LEFT(B35,LEN(B35)-1))))),2)=7,1,0)))) | D35: =(C35-$B$3)/365 | E35: =IFERROR(BDP(A35&" "&PX_SRC&" Curncy","PX_BID"),"ERROR PLZ FIX") | F35: =IFERROR(BDP(A35&" "&PX_SRC&" Curncy","PX_ASK"),"ERROR PLZ FIX") | G35: =IFERROR(BDP(A35&" "&PX_SRC&" Curncy","PX_LAST"),"ERROR PLZ FIX") | H35: =IFERROR(IF(Bootstrap!$G$4="Test 1",INDEX(Testing!$B$8:$B$47,MATCH(C35,Testing!$F$8:$F$47,0)),IF(Bootstrap!$G$4="Test 2",INDEX(Testing!$B$58:$B$97,MATCH(C35,Testing!$F$58:$F$97,0)),IF(Bootstrap!$G$4="Test 3",INDEX(Testing!$B$108:$B$147,MATCH(C35,Testing!$F$108:$F$147,0)),IF(Bootstrap!$G$4="Fixed (S490 07/21/26)",J35,IF(ISNUMBER(T35),T35,J35))))),J35) | I35: Y | J35: =IFERROR(INDEX(S490_Snapshot!$C$7:$C$38,MATCH(B35,S490_Snapshot!$B$7:$B$38,0)),"") | K35: S490_Snapshot | P35: =IF(COUNT(N35:O35)=2,(N35+O35)/2,"") | Q35: =IF(AND(ISNUMBER(N35),ISNUMBER(E35)),(E35-N35)*100,"") | R35: =IF(AND(ISNUMBER(O35),ISNUMBER(F35)),(F35-O35)*100,"") | S35: =IF(AND(ISNUMBER(P35),ISNUMBER(H35)),(H35-P35)*100,"") | T35: =IFERROR((E35+F35)/2,IFERROR(G35+0,"")) | U35: =IF(OR(T35="",NOT(ISNUMBER(J35))),"",(T35-J35)*100)
A36: USOSFR50 | B36: 50Y | C36: =IF(MONTH((IF(RIGHT(B36,1)="W",$B$3+7*VALUE(LEFT(B36,LEN(B36)-1)),IF(RIGHT(B36,1)="M",EDATE($B$3,VALUE(LEFT(B36,LEN(B36)-1))),EDATE($B$3,12*VALUE(LEFT(B36,LEN(B36)-1)))))+IF(WEEKDAY(IF(RIGHT(B36,1)="W",$B$3+7*VALUE(LEFT(B36,LEN(B36)-1)),IF(RIGHT(B36,1)="M",EDATE($B$3,VALUE(LEFT(B36,LEN(B36)-1))),EDATE($B$3,12*VALUE(LEFT(B36,LEN(B36)-1))))),2)=6,2,IF(WEEKDAY(IF(RIGHT(B36,1)="W",$B$3+7*VALUE(LEFT(B36,LEN(B36)-1)),IF(RIGHT(B36,1)="M",EDATE($B$3,VALUE(LEFT(B36,LEN(B36)-1))),EDATE($B$3,12*VALUE(LEFT(B36,LEN(B36)-1))))),2)=7,1,0))))<>MONTH(IF(RIGHT(B36,1)="W",$B$3+7*VALUE(LEFT(B36,LEN(B36)-1)),IF(RIGHT(B36,1)="M",EDATE($B$3,VALUE(LEFT(B36,LEN(B36)-1))),EDATE($B$3,12*VALUE(LEFT(B36,LEN(B36)-1)))))),(IF(RIGHT(B36,1)="W",$B$3+7*VALUE(LEFT(B36,LEN(B36)-1)),IF(RIGHT(B36,1)="M",EDATE($B$3,VALUE(LEFT(B36,LEN(B36)-1))),EDATE($B$3,12*VALUE(LEFT(B36,LEN(B36)-1)))))-IF(WEEKDAY(IF(RIGHT(B36,1)="W",$B$3+7*VALUE(LEFT(B36,LEN(B36)-1)),IF(RIGHT(B36,1)="M",EDATE($B$3,VALUE(LEFT(B36,LEN(B36)-1))),EDATE($B$3,12*VALUE(LEFT(B36,LEN(B36)-1))))),2)=6,1,IF(WEEKDAY(IF(RIGHT(B36,1)="W",$B$3+7*VALUE(LEFT(B36,LEN(B36)-1)),IF(RIGHT(B36,1)="M",EDATE($B$3,VALUE(LEFT(B36,LEN(B36)-1))),EDATE($B$3,12*VALUE(LEFT(B36,LEN(B36)-1))))),2)=7,2,0))),(IF(RIGHT(B36,1)="W",$B$3+7*VALUE(LEFT(B36,LEN(B36)-1)),IF(RIGHT(B36,1)="M",EDATE($B$3,VALUE(LEFT(B36,LEN(B36)-1))),EDATE($B$3,12*VALUE(LEFT(B36,LEN(B36)-1)))))+IF(WEEKDAY(IF(RIGHT(B36,1)="W",$B$3+7*VALUE(LEFT(B36,LEN(B36)-1)),IF(RIGHT(B36,1)="M",EDATE($B$3,VALUE(LEFT(B36,LEN(B36)-1))),EDATE($B$3,12*VALUE(LEFT(B36,LEN(B36)-1))))),2)=6,2,IF(WEEKDAY(IF(RIGHT(B36,1)="W",$B$3+7*VALUE(LEFT(B36,LEN(B36)-1)),IF(RIGHT(B36,1)="M",EDATE($B$3,VALUE(LEFT(B36,LEN(B36)-1))),EDATE($B$3,12*VALUE(LEFT(B36,LEN(B36)-1))))),2)=7,1,0)))) | D36: =(C36-$B$3)/365 | E36: =IFERROR(BDP(A36&" "&PX_SRC&" Curncy","PX_BID"),"ERROR PLZ FIX") | F36: =IFERROR(BDP(A36&" "&PX_SRC&" Curncy","PX_ASK"),"ERROR PLZ FIX") | G36: =IFERROR(BDP(A36&" "&PX_SRC&" Curncy","PX_LAST"),"ERROR PLZ FIX") | H36: =IFERROR(IF(Bootstrap!$G$4="Test 1",INDEX(Testing!$B$8:$B$47,MATCH(C36,Testing!$F$8:$F$47,0)),IF(Bootstrap!$G$4="Test 2",INDEX(Testing!$B$58:$B$97,MATCH(C36,Testing!$F$58:$F$97,0)),IF(Bootstrap!$G$4="Test 3",INDEX(Testing!$B$108:$B$147,MATCH(C36,Testing!$F$108:$F$147,0)),IF(Bootstrap!$G$4="Fixed (S490 07/21/26)",J36,IF(ISNUMBER(T36),T36,J36))))),J36) | I36: Y | J36: =IFERROR(INDEX(S490_Snapshot!$C$7:$C$38,MATCH(B36,S490_Snapshot!$B$7:$B$38,0)),"") | K36: S490_Snapshot | P36: =IF(COUNT(N36:O36)=2,(N36+O36)/2,"") | Q36: =IF(AND(ISNUMBER(N36),ISNUMBER(E36)),(E36-N36)*100,"") | R36: =IF(AND(ISNUMBER(O36),ISNUMBER(F36)),(F36-O36)*100,"") | S36: =IF(AND(ISNUMBER(P36),ISNUMBER(H36)),(H36-P36)*100,"") | T36: =IFERROR((E36+F36)/2,IFERROR(G36+0,"")) | U36: =IF(OR(T36="",NOT(ISNUMBER(J36))),"",(T36-J36)*100)
A38: Maturity and Tenor(yrs) are parsed from the tenor label, business-day rolled. Display only; the curve reads col H.
N40: Max |d Mid| (bp) | P40: =IF(COUNT(S5:S36)=0,"paste the export first",MAX(MAX(S5:S36),-MIN(S5:S36)))
N41: Mean d Mid (bp) - a non-zero mean is the tell for a systematic offset | P41: =IF(COUNT(S5:S36)=0,"",AVERAGE(S5:S36)) | T41: Max |d live-fixed| (bp) | U41: =IF(COUNT(U5:U36)=0,"BDP unavailable",MAX(MAX(U5:U36),-MIN(U5:U36)))

Sheet SOFR_Futures
A1: SOFR_Futures
A2: UNUSED: no formula on any sheet reads this tab since the futures-based bootstrap was removed. Kept as reference data only - the production curve is purely OIS.
A3: Enable Bloomberg pulls on this sheet | B3: No | C3: 301 BDP/BDS calls live here and nothing reads them. Left on they fill the sheet with errors for no benefit. Yes re-enables; formulas unchanged.
A4: SR3 — THREE-MONTH SOFR FUTURES (SFRA Comdty · CME SR3) — first 20 quarterly contracts
A5: Column A cell below holds =BDS("SFRA Comdty","FUT_CHAIN") and SPILLS the active contract tickers down. Field columns reference each row's contract in column A. Adjust the row count to the liquid strip (check VOLUME / OPEN_INT).
A6: Contract (from CT chain) | B6: SECURITY_DES | C6: PX_LAST | D6: PX_BID | E6: PX_ASK | F6: Implied rate % (100−Last) | G6: FUT_MONTH_YR | H6: Ref. start (FUT_DLV_DT_FIRST) | I6: LAST_TRADEABLE_DT | J6: VOLUME | K6: OPEN_INT
A7: =IF($B$3<>"Yes","",BDS("SFRA Comdty","FUT_CHAIN")) | B7: =IF($B$3<>"Yes","",IFERROR(BDP($A7,"SECURITY_DES"),"ERROR PLZ FIX")) | C7: =IF($B$3<>"Yes","",IFERROR(BDP($A7,"PX_LAST"),"ERROR PLZ FIX")) | D7: =IF($B$3<>"Yes","",IFERROR(BDP($A7,"PX_BID"),"ERROR PLZ FIX")) | E7: =IF($B$3<>"Yes","",IFERROR(BDP($A7,"PX_ASK"),"ERROR PLZ FIX")) | F7: =IFERROR(100-C7,"ERROR PLZ FIX") | G7: =IF($B$3<>"Yes","",IFERROR(BDP($A7,"FUT_MONTH_YR"),"ERROR PLZ FIX")) | H7: =IF($B$3<>"Yes","",IFERROR(BDP($A7,"FUT_DLV_DT_FIRST"),"ERROR PLZ FIX")) | I7: =IF($B$3<>"Yes","",IFERROR(BDP($A7,"LAST_TRADEABLE_DT"),"ERROR PLZ FIX")) | J7: =IF($B$3<>"Yes","",IFERROR(BDP($A7,"VOLUME"),"ERROR PLZ FIX")) | K7: =IF($B$3<>"Yes","",IFERROR(BDP($A7,"OPEN_INT"),"ERROR PLZ FIX"))
B8: =IF($B$3<>"Yes","",IFERROR(BDP($A8,"SECURITY_DES"),"ERROR PLZ FIX")) | C8: =IF($B$3<>"Yes","",IFERROR(BDP($A8,"PX_LAST"),"ERROR PLZ FIX")) | D8: =IF($B$3<>"Yes","",IFERROR(BDP($A8,"PX_BID"),"ERROR PLZ FIX")) | E8: =IF($B$3<>"Yes","",IFERROR(BDP($A8,"PX_ASK"),"ERROR PLZ FIX")) | F8: =IFERROR(100-C8,"ERROR PLZ FIX") | G8: =IF($B$3<>"Yes","",IFERROR(BDP($A8,"FUT_MONTH_YR"),"ERROR PLZ FIX")) | H8: =IF($B$3<>"Yes","",IFERROR(BDP($A8,"FUT_DLV_DT_FIRST"),"ERROR PLZ FIX")) | I8: =IF($B$3<>"Yes","",IFERROR(BDP($A8,"LAST_TRADEABLE_DT"),"ERROR PLZ FIX")) | J8: =IF($B$3<>"Yes","",IFERROR(BDP($A8,"VOLUME"),"ERROR PLZ FIX")) | K8: =IF($B$3<>"Yes","",IFERROR(BDP($A8,"OPEN_INT"),"ERROR PLZ FIX"))
B9: =IF($B$3<>"Yes","",IFERROR(BDP($A9,"SECURITY_DES"),"ERROR PLZ FIX")) | C9: =IF($B$3<>"Yes","",IFERROR(BDP($A9,"PX_LAST"),"ERROR PLZ FIX")) | D9: =IF($B$3<>"Yes","",IFERROR(BDP($A9,"PX_BID"),"ERROR PLZ FIX")) | E9: =IF($B$3<>"Yes","",IFERROR(BDP($A9,"PX_ASK"),"ERROR PLZ FIX")) | F9: =IFERROR(100-C9,"ERROR PLZ FIX") | G9: =IF($B$3<>"Yes","",IFERROR(BDP($A9,"FUT_MONTH_YR"),"ERROR PLZ FIX")) | H9: =IF($B$3<>"Yes","",IFERROR(BDP($A9,"FUT_DLV_DT_FIRST"),"ERROR PLZ FIX")) | I9: =IF($B$3<>"Yes","",IFERROR(BDP($A9,"LAST_TRADEABLE_DT"),"ERROR PLZ FIX")) | J9: =IF($B$3<>"Yes","",IFERROR(BDP($A9,"VOLUME"),"ERROR PLZ FIX")) | K9: =IF($B$3<>"Yes","",IFERROR(BDP($A9,"OPEN_INT"),"ERROR PLZ FIX"))
B10: =IF($B$3<>"Yes","",IFERROR(BDP($A10,"SECURITY_DES"),"ERROR PLZ FIX")) | C10: =IF($B$3<>"Yes","",IFERROR(BDP($A10,"PX_LAST"),"ERROR PLZ FIX")) | D10: =IF($B$3<>"Yes","",IFERROR(BDP($A10,"PX_BID"),"ERROR PLZ FIX")) | E10: =IF($B$3<>"Yes","",IFERROR(BDP($A10,"PX_ASK"),"ERROR PLZ FIX")) | F10: =IFERROR(100-C10,"ERROR PLZ FIX") | G10: =IF($B$3<>"Yes","",IFERROR(BDP($A10,"FUT_MONTH_YR"),"ERROR PLZ FIX")) | H10: =IF($B$3<>"Yes","",IFERROR(BDP($A10,"FUT_DLV_DT_FIRST"),"ERROR PLZ FIX")) | I10: =IF($B$3<>"Yes","",IFERROR(BDP($A10,"LAST_TRADEABLE_DT"),"ERROR PLZ FIX")) | J10: =IF($B$3<>"Yes","",IFERROR(BDP($A10,"VOLUME"),"ERROR PLZ FIX")) | K10: =IF($B$3<>"Yes","",IFERROR(BDP($A10,"OPEN_INT"),"ERROR PLZ FIX"))
B11: =IF($B$3<>"Yes","",IFERROR(BDP($A11,"SECURITY_DES"),"ERROR PLZ FIX")) | C11: =IF($B$3<>"Yes","",IFERROR(BDP($A11,"PX_LAST"),"ERROR PLZ FIX")) | D11: =IF($B$3<>"Yes","",IFERROR(BDP($A11,"PX_BID"),"ERROR PLZ FIX")) | E11: =IF($B$3<>"Yes","",IFERROR(BDP($A11,"PX_ASK"),"ERROR PLZ FIX")) | F11: =IFERROR(100-C11,"ERROR PLZ FIX") | G11: =IF($B$3<>"Yes","",IFERROR(BDP($A11,"FUT_MONTH_YR"),"ERROR PLZ FIX")) | H11: =IF($B$3<>"Yes","",IFERROR(BDP($A11,"FUT_DLV_DT_FIRST"),"ERROR PLZ FIX")) | I11: =IF($B$3<>"Yes","",IFERROR(BDP($A11,"LAST_TRADEABLE_DT"),"ERROR PLZ FIX")) | J11: =IF($B$3<>"Yes","",IFERROR(BDP($A11,"VOLUME"),"ERROR PLZ FIX")) | K11: =IF($B$3<>"Yes","",IFERROR(BDP($A11,"OPEN_INT"),"ERROR PLZ FIX"))
B12: =IF($B$3<>"Yes","",IFERROR(BDP($A12,"SECURITY_DES"),"ERROR PLZ FIX")) | C12: =IF($B$3<>"Yes","",IFERROR(BDP($A12,"PX_LAST"),"ERROR PLZ FIX")) | D12: =IF($B$3<>"Yes","",IFERROR(BDP($A12,"PX_BID"),"ERROR PLZ FIX")) | E12: =IF($B$3<>"Yes","",IFERROR(BDP($A12,"PX_ASK"),"ERROR PLZ FIX")) | F12: =IFERROR(100-C12,"ERROR PLZ FIX") | G12: =IF($B$3<>"Yes","",IFERROR(BDP($A12,"FUT_MONTH_YR"),"ERROR PLZ FIX")) | H12: =IF($B$3<>"Yes","",IFERROR(BDP($A12,"FUT_DLV_DT_FIRST"),"ERROR PLZ FIX")) | I12: =IF($B$3<>"Yes","",IFERROR(BDP($A12,"LAST_TRADEABLE_DT"),"ERROR PLZ FIX")) | J12: =IF($B$3<>"Yes","",IFERROR(BDP($A12,"VOLUME"),"ERROR PLZ FIX")) | K12: =IF($B$3<>"Yes","",IFERROR(BDP($A12,"OPEN_INT"),"ERROR PLZ FIX"))
B13: =IF($B$3<>"Yes","",IFERROR(BDP($A13,"SECURITY_DES"),"ERROR PLZ FIX")) | C13: =IF($B$3<>"Yes","",IFERROR(BDP($A13,"PX_LAST"),"ERROR PLZ FIX")) | D13: =IF($B$3<>"Yes","",IFERROR(BDP($A13,"PX_BID"),"ERROR PLZ FIX")) | E13: =IF($B$3<>"Yes","",IFERROR(BDP($A13,"PX_ASK"),"ERROR PLZ FIX")) | F13: =IFERROR(100-C13,"ERROR PLZ FIX") | G13: =IF($B$3<>"Yes","",IFERROR(BDP($A13,"FUT_MONTH_YR"),"ERROR PLZ FIX")) | H13: =IF($B$3<>"Yes","",IFERROR(BDP($A13,"FUT_DLV_DT_FIRST"),"ERROR PLZ FIX")) | I13: =IF($B$3<>"Yes","",IFERROR(BDP($A13,"LAST_TRADEABLE_DT"),"ERROR PLZ FIX")) | J13: =IF($B$3<>"Yes","",IFERROR(BDP($A13,"VOLUME"),"ERROR PLZ FIX")) | K13: =IF($B$3<>"Yes","",IFERROR(BDP($A13,"OPEN_INT"),"ERROR PLZ FIX"))
B14: =IF($B$3<>"Yes","",IFERROR(BDP($A14,"SECURITY_DES"),"ERROR PLZ FIX")) | C14: =IF($B$3<>"Yes","",IFERROR(BDP($A14,"PX_LAST"),"ERROR PLZ FIX")) | D14: =IF($B$3<>"Yes","",IFERROR(BDP($A14,"PX_BID"),"ERROR PLZ FIX")) | E14: =IF($B$3<>"Yes","",IFERROR(BDP($A14,"PX_ASK"),"ERROR PLZ FIX")) | F14: =IFERROR(100-C14,"ERROR PLZ FIX") | G14: =IF($B$3<>"Yes","",IFERROR(BDP($A14,"FUT_MONTH_YR"),"ERROR PLZ FIX")) | H14: =IF($B$3<>"Yes","",IFERROR(BDP($A14,"FUT_DLV_DT_FIRST"),"ERROR PLZ FIX")) | I14: =IF($B$3<>"Yes","",IFERROR(BDP($A14,"LAST_TRADEABLE_DT"),"ERROR PLZ FIX")) | J14: =IF($B$3<>"Yes","",IFERROR(BDP($A14,"VOLUME"),"ERROR PLZ FIX")) | K14: =IF($B$3<>"Yes","",IFERROR(BDP($A14,"OPEN_INT"),"ERROR PLZ FIX"))
B15: =IF($B$3<>"Yes","",IFERROR(BDP($A15,"SECURITY_DES"),"ERROR PLZ FIX")) | C15: =IF($B$3<>"Yes","",IFERROR(BDP($A15,"PX_LAST"),"ERROR PLZ FIX")) | D15: =IF($B$3<>"Yes","",IFERROR(BDP($A15,"PX_BID"),"ERROR PLZ FIX")) | E15: =IF($B$3<>"Yes","",IFERROR(BDP($A15,"PX_ASK"),"ERROR PLZ FIX")) | F15: =IFERROR(100-C15,"ERROR PLZ FIX") | G15: =IF($B$3<>"Yes","",IFERROR(BDP($A15,"FUT_MONTH_YR"),"ERROR PLZ FIX")) | H15: =IF($B$3<>"Yes","",IFERROR(BDP($A15,"FUT_DLV_DT_FIRST"),"ERROR PLZ FIX")) | I15: =IF($B$3<>"Yes","",IFERROR(BDP($A15,"LAST_TRADEABLE_DT"),"ERROR PLZ FIX")) | J15: =IF($B$3<>"Yes","",IFERROR(BDP($A15,"VOLUME"),"ERROR PLZ FIX")) | K15: =IF($B$3<>"Yes","",IFERROR(BDP($A15,"OPEN_INT"),"ERROR PLZ FIX"))
B16: =IF($B$3<>"Yes","",IFERROR(BDP($A16,"SECURITY_DES"),"ERROR PLZ FIX")) | C16: =IF($B$3<>"Yes","",IFERROR(BDP($A16,"PX_LAST"),"ERROR PLZ FIX")) | D16: =IF($B$3<>"Yes","",IFERROR(BDP($A16,"PX_BID"),"ERROR PLZ FIX")) | E16: =IF($B$3<>"Yes","",IFERROR(BDP($A16,"PX_ASK"),"ERROR PLZ FIX")) | F16: =IFERROR(100-C16,"ERROR PLZ FIX") | G16: =IF($B$3<>"Yes","",IFERROR(BDP($A16,"FUT_MONTH_YR"),"ERROR PLZ FIX")) | H16: =IF($B$3<>"Yes","",IFERROR(BDP($A16,"FUT_DLV_DT_FIRST"),"ERROR PLZ FIX")) | I16: =IF($B$3<>"Yes","",IFERROR(BDP($A16,"LAST_TRADEABLE_DT"),"ERROR PLZ FIX")) | J16: =IF($B$3<>"Yes","",IFERROR(BDP($A16,"VOLUME"),"ERROR PLZ FIX")) | K16: =IF($B$3<>"Yes","",IFERROR(BDP($A16,"OPEN_INT"),"ERROR PLZ FIX"))
B17: =IF($B$3<>"Yes","",IFERROR(BDP($A17,"SECURITY_DES"),"ERROR PLZ FIX")) | C17: =IF($B$3<>"Yes","",IFERROR(BDP($A17,"PX_LAST"),"ERROR PLZ FIX")) | D17: =IF($B$3<>"Yes","",IFERROR(BDP($A17,"PX_BID"),"ERROR PLZ FIX")) | E17: =IF($B$3<>"Yes","",IFERROR(BDP($A17,"PX_ASK"),"ERROR PLZ FIX")) | F17: =IFERROR(100-C17,"ERROR PLZ FIX") | G17: =IF($B$3<>"Yes","",IFERROR(BDP($A17,"FUT_MONTH_YR"),"ERROR PLZ FIX")) | H17: =IF($B$3<>"Yes","",IFERROR(BDP($A17,"FUT_DLV_DT_FIRST"),"ERROR PLZ FIX")) | I17: =IF($B$3<>"Yes","",IFERROR(BDP($A17,"LAST_TRADEABLE_DT"),"ERROR PLZ FIX")) | J17: =IF($B$3<>"Yes","",IFERROR(BDP($A17,"VOLUME"),"ERROR PLZ FIX")) | K17: =IF($B$3<>"Yes","",IFERROR(BDP($A17,"OPEN_INT"),"ERROR PLZ FIX"))
B18: =IF($B$3<>"Yes","",IFERROR(BDP($A18,"SECURITY_DES"),"ERROR PLZ FIX")) | C18: =IF($B$3<>"Yes","",IFERROR(BDP($A18,"PX_LAST"),"ERROR PLZ FIX")) | D18: =IF($B$3<>"Yes","",IFERROR(BDP($A18,"PX_BID"),"ERROR PLZ FIX")) | E18: =IF($B$3<>"Yes","",IFERROR(BDP($A18,"PX_ASK"),"ERROR PLZ FIX")) | F18: =IFERROR(100-C18,"ERROR PLZ FIX") | G18: =IF($B$3<>"Yes","",IFERROR(BDP($A18,"FUT_MONTH_YR"),"ERROR PLZ FIX")) | H18: =IF($B$3<>"Yes","",IFERROR(BDP($A18,"FUT_DLV_DT_FIRST"),"ERROR PLZ FIX")) | I18: =IF($B$3<>"Yes","",IFERROR(BDP($A18,"LAST_TRADEABLE_DT"),"ERROR PLZ FIX")) | J18: =IF($B$3<>"Yes","",IFERROR(BDP($A18,"VOLUME"),"ERROR PLZ FIX")) | K18: =IF($B$3<>"Yes","",IFERROR(BDP($A18,"OPEN_INT"),"ERROR PLZ FIX"))
B19: =IF($B$3<>"Yes","",IFERROR(BDP($A19,"SECURITY_DES"),"ERROR PLZ FIX")) | C19: =IF($B$3<>"Yes","",IFERROR(BDP($A19,"PX_LAST"),"ERROR PLZ FIX")) | D19: =IF($B$3<>"Yes","",IFERROR(BDP($A19,"PX_BID"),"ERROR PLZ FIX")) | E19: =IF($B$3<>"Yes","",IFERROR(BDP($A19,"PX_ASK"),"ERROR PLZ FIX")) | F19: =IFERROR(100-C19,"ERROR PLZ FIX") | G19: =IF($B$3<>"Yes","",IFERROR(BDP($A19,"FUT_MONTH_YR"),"ERROR PLZ FIX")) | H19: =IF($B$3<>"Yes","",IFERROR(BDP($A19,"FUT_DLV_DT_FIRST"),"ERROR PLZ FIX")) | I19: =IF($B$3<>"Yes","",IFERROR(BDP($A19,"LAST_TRADEABLE_DT"),"ERROR PLZ FIX")) | J19: =IF($B$3<>"Yes","",IFERROR(BDP($A19,"VOLUME"),"ERROR PLZ FIX")) | K19: =IF($B$3<>"Yes","",IFERROR(BDP($A19,"OPEN_INT"),"ERROR PLZ FIX"))
... B26: =IF($B$3<>"Yes","",IFERROR(BDP($A26,"SECURITY_DES"),"ERROR PLZ FIX")) | C26: =IF($B$3<>"Yes","",IFERROR(BDP($A26,"PX_LAST"),"ERROR PLZ FIX")) | D26: =IF($B$3<>"Yes","",IFERROR(BDP($A26,"PX_BID"),"ERROR PLZ FIX")) | E26: =IF($B$3<>"Yes","",IFERROR(BDP($A26,"PX_ASK"),"ERROR PLZ FIX")) | F26: =IFERROR(100-C26,"ERROR PLZ FIX") | G26: =IF($B$3<>"Yes","",IFERROR(BDP($A26,"FUT_MONTH_YR"),"ERROR PLZ FIX")) | H26: =IF($B$3<>"Yes","",IFERROR(BDP($A26,"FUT_DLV_DT_FIRST"),"ERROR PLZ FIX")) | I26: =IF($B$3<>"Yes","",IFERROR(BDP($A26,"LAST_TRADEABLE_DT"),"ERROR PLZ FIX")) | J26: =IF($B$3<>"Yes","",IFERROR(BDP($A26,"VOLUME"),"ERROR PLZ FIX")) | K26: =IF($B$3<>"Yes","",IFERROR(BDP($A26,"OPEN_INT"),"ERROR PLZ FIX"))
A29: SR1 — ONE-MONTH SOFR FUTURES (SERA Comdty · CME SR1) — first 13 monthly contracts
A30: Column A cell below holds =BDS("SERA Comdty","FUT_CHAIN") and SPILLS the active contract tickers down. Field columns reference each row's contract in column A. Adjust the row count to the liquid strip (check VOLUME / OPEN_INT).
A31: Contract (from CT chain) | B31: SECURITY_DES | C31: PX_LAST | D31: PX_BID | E31: PX_ASK | F31: Implied rate % (100−Last) | G31: FUT_MONTH_YR | H31: Ref. start (FUT_DLV_DT_FIRST) | I31: LAST_TRADEABLE_DT | J31: VOLUME | K31: OPEN_INT
A32: =IF($B$3<>"Yes","",BDS("SERA Comdty","FUT_CHAIN")) | B32: =IF($B$3<>"Yes","",IFERROR(BDP($A32,"SECURITY_DES"),"ERROR PLZ FIX")) | C32: =IF($B$3<>"Yes","",IFERROR(BDP($A32,"PX_LAST"),"ERROR PLZ FIX")) | D32: =IF($B$3<>"Yes","",IFERROR(BDP($A32,"PX_BID"),"ERROR PLZ FIX")) | E32: =IF($B$3<>"Yes","",IFERROR(BDP($A32,"PX_ASK"),"ERROR PLZ FIX")) | F32: =IFERROR(100-C32,"ERROR PLZ FIX") | G32: =IF($B$3<>"Yes","",IFERROR(BDP($A32,"FUT_MONTH_YR"),"ERROR PLZ FIX")) | H32: =IF($B$3<>"Yes","",IFERROR(BDP($A32,"FUT_DLV_DT_FIRST"),"ERROR PLZ FIX")) | I32: =IF($B$3<>"Yes","",IFERROR(BDP($A32,"LAST_TRADEABLE_DT"),"ERROR PLZ FIX")) | J32: =IF($B$3<>"Yes","",IFERROR(BDP($A32,"VOLUME"),"ERROR PLZ FIX")) | K32: =IF($B$3<>"Yes","",IFERROR(BDP($A32,"OPEN_INT"),"ERROR PLZ FIX"))
B33: =IF($B$3<>"Yes","",IFERROR(BDP($A33,"SECURITY_DES"),"ERROR PLZ FIX")) | C33: =IF($B$3<>"Yes","",IFERROR(BDP($A33,"PX_LAST"),"ERROR PLZ FIX")) | D33: =IF($B$3<>"Yes","",IFERROR(BDP($A33,"PX_BID"),"ERROR PLZ FIX")) | E33: =IF($B$3<>"Yes","",IFERROR(BDP($A33,"PX_ASK"),"ERROR PLZ FIX")) | F33: =IFERROR(100-C33,"ERROR PLZ FIX") | G33: =IF($B$3<>"Yes","",IFERROR(BDP($A33,"FUT_MONTH_YR"),"ERROR PLZ FIX")) | H33: =IF($B$3<>"Yes","",IFERROR(BDP($A33,"FUT_DLV_DT_FIRST"),"ERROR PLZ FIX")) | I33: =IF($B$3<>"Yes","",IFERROR(BDP($A33,"LAST_TRADEABLE_DT"),"ERROR PLZ FIX")) | J33: =IF($B$3<>"Yes","",IFERROR(BDP($A33,"VOLUME"),"ERROR PLZ FIX")) | K33: =IF($B$3<>"Yes","",IFERROR(BDP($A33,"OPEN_INT"),"ERROR PLZ FIX"))
B34: =IF($B$3<>"Yes","",IFERROR(BDP($A34,"SECURITY_DES"),"ERROR PLZ FIX")) | C34: =IF($B$3<>"Yes","",IFERROR(BDP($A34,"PX_LAST"),"ERROR PLZ FIX")) | D34: =IF($B$3<>"Yes","",IFERROR(BDP($A34,"PX_BID"),"ERROR PLZ FIX")) | E34: =IF($B$3<>"Yes","",IFERROR(BDP($A34,"PX_ASK"),"ERROR PLZ FIX")) | F34: =IFERROR(100-C34,"ERROR PLZ FIX") | G34: =IF($B$3<>"Yes","",IFERROR(BDP($A34,"FUT_MONTH_YR"),"ERROR PLZ FIX")) | H34: =IF($B$3<>"Yes","",IFERROR(BDP($A34,"FUT_DLV_DT_FIRST"),"ERROR PLZ FIX")) | I34: =IF($B$3<>"Yes","",IFERROR(BDP($A34,"LAST_TRADEABLE_DT"),"ERROR PLZ FIX")) | J34: =IF($B$3<>"Yes","",IFERROR(BDP($A34,"VOLUME"),"ERROR PLZ FIX")) | K34: =IF($B$3<>"Yes","",IFERROR(BDP($A34,"OPEN_INT"),"ERROR PLZ FIX"))
B35: =IF($B$3<>"Yes","",IFERROR(BDP($A35,"SECURITY_DES"),"ERROR PLZ FIX")) | C35: =IF($B$3<>"Yes","",IFERROR(BDP($A35,"PX_LAST"),"ERROR PLZ FIX")) | D35: =IF($B$3<>"Yes","",IFERROR(BDP($A35,"PX_BID"),"ERROR PLZ FIX")) | E35: =IF($B$3<>"Yes","",IFERROR(BDP($A35,"PX_ASK"),"ERROR PLZ FIX")) | F35: =IFERROR(100-C35,"ERROR PLZ FIX") | G35: =IF($B$3<>"Yes","",IFERROR(BDP($A35,"FUT_MONTH_YR"),"ERROR PLZ FIX")) | H35: =IF($B$3<>"Yes","",IFERROR(BDP($A35,"FUT_DLV_DT_FIRST"),"ERROR PLZ FIX")) | I35: =IF($B$3<>"Yes","",IFERROR(BDP($A35,"LAST_TRADEABLE_DT"),"ERROR PLZ FIX")) | J35: =IF($B$3<>"Yes","",IFERROR(BDP($A35,"VOLUME"),"ERROR PLZ FIX")) | K35: =IF($B$3<>"Yes","",IFERROR(BDP($A35,"OPEN_INT"),"ERROR PLZ FIX"))
B36: =IF($B$3<>"Yes","",IFERROR(BDP($A36,"SECURITY_DES"),"ERROR PLZ FIX")) | C36: =IF($B$3<>"Yes","",IFERROR(BDP($A36,"PX_LAST"),"ERROR PLZ FIX")) | D36: =IF($B$3<>"Yes","",IFERROR(BDP($A36,"PX_BID"),"ERROR PLZ FIX")) | E36: =IF($B$3<>"Yes","",IFERROR(BDP($A36,"PX_ASK"),"ERROR PLZ FIX")) | F36: =IFERROR(100-C36,"ERROR PLZ FIX") | G36: =IF($B$3<>"Yes","",IFERROR(BDP($A36,"FUT_MONTH_YR"),"ERROR PLZ FIX")) | H36: =IF($B$3<>"Yes","",IFERROR(BDP($A36,"FUT_DLV_DT_FIRST"),"ERROR PLZ FIX")) | I36: =IF($B$3<>"Yes","",IFERROR(BDP($A36,"LAST_TRADEABLE_DT"),"ERROR PLZ FIX")) | J36: =IF($B$3<>"Yes","",IFERROR(BDP($A36,"VOLUME"),"ERROR PLZ FIX")) | K36: =IF($B$3<>"Yes","",IFERROR(BDP($A36,"OPEN_INT"),"ERROR PLZ FIX"))
B37: =IF($B$3<>"Yes","",IFERROR(BDP($A37,"SECURITY_DES"),"ERROR PLZ FIX")) | C37: =IF($B$3<>"Yes","",IFERROR(BDP($A37,"PX_LAST"),"ERROR PLZ FIX")) | D37: =IF($B$3<>"Yes","",IFERROR(BDP($A37,"PX_BID"),"ERROR PLZ FIX")) | E37: =IF($B$3<>"Yes","",IFERROR(BDP($A37,"PX_ASK"),"ERROR PLZ FIX")) | F37: =IFERROR(100-C37,"ERROR PLZ FIX") | G37: =IF($B$3<>"Yes","",IFERROR(BDP($A37,"FUT_MONTH_YR"),"ERROR PLZ FIX")) | H37: =IF($B$3<>"Yes","",IFERROR(BDP($A37,"FUT_DLV_DT_FIRST"),"ERROR PLZ FIX")) | I37: =IF($B$3<>"Yes","",IFERROR(BDP($A37,"LAST_TRADEABLE_DT"),"ERROR PLZ FIX")) | J37: =IF($B$3<>"Yes","",IFERROR(BDP($A37,"VOLUME"),"ERROR PLZ FIX")) | K37: =IF($B$3<>"Yes","",IFERROR(BDP($A37,"OPEN_INT"),"ERROR PLZ FIX"))
B38: =IF($B$3<>"Yes","",IFERROR(BDP($A38,"SECURITY_DES"),"ERROR PLZ FIX")) | C38: =IF($B$3<>"Yes","",IFERROR(BDP($A38,"PX_LAST"),"ERROR PLZ FIX")) | D38: =IF($B$3<>"Yes","",IFERROR(BDP($A38,"PX_BID"),"ERROR PLZ FIX")) | E38: =IF($B$3<>"Yes","",IFERROR(BDP($A38,"PX_ASK"),"ERROR PLZ FIX")) | F38: =IFERROR(100-C38,"ERROR PLZ FIX") | G38: =IF($B$3<>"Yes","",IFERROR(BDP($A38,"FUT_MONTH_YR"),"ERROR PLZ FIX")) | H38: =IF($B$3<>"Yes","",IFERROR(BDP($A38,"FUT_DLV_DT_FIRST"),"ERROR PLZ FIX")) | I38: =IF($B$3<>"Yes","",IFERROR(BDP($A38,"LAST_TRADEABLE_DT"),"ERROR PLZ FIX")) | J38: =IF($B$3<>"Yes","",IFERROR(BDP($A38,"VOLUME"),"ERROR PLZ FIX")) | K38: =IF($B$3<>"Yes","",IFERROR(BDP($A38,"OPEN_INT"),"ERROR PLZ FIX"))
B39: =IF($B$3<>"Yes","",IFERROR(BDP($A39,"SECURITY_DES"),"ERROR PLZ FIX")) | C39: =IF($B$3<>"Yes","",IFERROR(BDP($A39,"PX_LAST"),"ERROR PLZ FIX")) | D39: =IF($B$3<>"Yes","",IFERROR(BDP($A39,"PX_BID"),"ERROR PLZ FIX")) | E39: =IF($B$3<>"Yes","",IFERROR(BDP($A39,"PX_ASK"),"ERROR PLZ FIX")) | F39: =IFERROR(100-C39,"ERROR PLZ FIX") | G39: =IF($B$3<>"Yes","",IFERROR(BDP($A39,"FUT_MONTH_YR"),"ERROR PLZ FIX")) | H39: =IF($B$3<>"Yes","",IFERROR(BDP($A39,"FUT_DLV_DT_FIRST"),"ERROR PLZ FIX")) | I39: =IF($B$3<>"Yes","",IFERROR(BDP($A39,"LAST_TRADEABLE_DT"),"ERROR PLZ FIX")) | J39: =IF($B$3<>"Yes","",IFERROR(BDP($A39,"VOLUME"),"ERROR PLZ FIX")) | K39: =IF($B$3<>"Yes","",IFERROR(BDP($A39,"OPEN_INT"),"ERROR PLZ FIX"))
B40: =IF($B$3<>"Yes","",IFERROR(BDP($A40,"SECURITY_DES"),"ERROR PLZ FIX")) | C40: =IF($B$3<>"Yes","",IFERROR(BDP($A40,"PX_LAST"),"ERROR PLZ FIX")) | D40: =IF($B$3<>"Yes","",IFERROR(BDP($A40,"PX_BID"),"ERROR PLZ FIX")) | E40: =IF($B$3<>"Yes","",IFERROR(BDP($A40,"PX_ASK"),"ERROR PLZ FIX")) | F40: =IFERROR(100-C40,"ERROR PLZ FIX") | G40: =IF($B$3<>"Yes","",IFERROR(BDP($A40,"FUT_MONTH_YR"),"ERROR PLZ FIX")) | H40: =IF($B$3<>"Yes","",IFERROR(BDP($A40,"FUT_DLV_DT_FIRST"),"ERROR PLZ FIX")) | I40: =IF($B$3<>"Yes","",IFERROR(BDP($A40,"LAST_TRADEABLE_DT"),"ERROR PLZ FIX")) | J40: =IF($B$3<>"Yes","",IFERROR(BDP($A40,"VOLUME"),"ERROR PLZ FIX")) | K40: =IF($B$3<>"Yes","",IFERROR(BDP($A40,"OPEN_INT"),"ERROR PLZ FIX"))
B41: =IF($B$3<>"Yes","",IFERROR(BDP($A41,"SECURITY_DES"),"ERROR PLZ FIX")) | C41: =IF($B$3<>"Yes","",IFERROR(BDP($A41,"PX_LAST"),"ERROR PLZ FIX")) | D41: =IF($B$3<>"Yes","",IFERROR(BDP($A41,"PX_BID"),"ERROR PLZ FIX")) | E41: =IF($B$3<>"Yes","",IFERROR(BDP($A41,"PX_ASK"),"ERROR PLZ FIX")) | F41: =IFERROR(100-C41,"ERROR PLZ FIX") | G41: =IF($B$3<>"Yes","",IFERROR(BDP($A41,"FUT_MONTH_YR"),"ERROR PLZ FIX")) | H41: =IF($B$3<>"Yes","",IFERROR(BDP($A41,"FUT_DLV_DT_FIRST"),"ERROR PLZ FIX")) | I41: =IF($B$3<>"Yes","",IFERROR(BDP($A41,"LAST_TRADEABLE_DT"),"ERROR PLZ FIX")) | J41: =IF($B$3<>"Yes","",IFERROR(BDP($A41,"VOLUME"),"ERROR PLZ FIX")) | K41: =IF($B$3<>"Yes","",IFERROR(BDP($A41,"OPEN_INT"),"ERROR PLZ FIX"))
B42: =IF($B$3<>"Yes","",IFERROR(BDP($A42,"SECURITY_DES"),"ERROR PLZ FIX")) | C42: =IF($B$3<>"Yes","",IFERROR(BDP($A42,"PX_LAST"),"ERROR PLZ FIX")) | D42: =IF($B$3<>"Yes","",IFERROR(BDP($A42,"PX_BID"),"ERROR PLZ FIX")) | E42: =IF($B$3<>"Yes","",IFERROR(BDP($A42,"PX_ASK"),"ERROR PLZ FIX")) | F42: =IFERROR(100-C42,"ERROR PLZ FIX") | G42: =IF($B$3<>"Yes","",IFERROR(BDP($A42,"FUT_MONTH_YR"),"ERROR PLZ FIX")) | H42: =IF($B$3<>"Yes","",IFERROR(BDP($A42,"FUT_DLV_DT_FIRST"),"ERROR PLZ FIX")) | I42: =IF($B$3<>"Yes","",IFERROR(BDP($A42,"LAST_TRADEABLE_DT"),"ERROR PLZ FIX")) | J42: =IF($B$3<>"Yes","",IFERROR(BDP($A42,"VOLUME"),"ERROR PLZ FIX")) | K42: =IF($B$3<>"Yes","",IFERROR(BDP($A42,"OPEN_INT"),"ERROR PLZ FIX"))
B43: =IF($B$3<>"Yes","",IFERROR(BDP($A43,"SECURITY_DES"),"ERROR PLZ FIX")) | C43: =IF($B$3<>"Yes","",IFERROR(BDP($A43,"PX_LAST"),"ERROR PLZ FIX")) | D43: =IF($B$3<>"Yes","",IFERROR(BDP($A43,"PX_BID"),"ERROR PLZ FIX")) | E43: =IF($B$3<>"Yes","",IFERROR(BDP($A43,"PX_ASK"),"ERROR PLZ FIX")) | F43: =IFERROR(100-C43,"ERROR PLZ FIX") | G43: =IF($B$3<>"Yes","",IFERROR(BDP($A43,"FUT_MONTH_YR"),"ERROR PLZ FIX")) | H43: =IF($B$3<>"Yes","",IFERROR(BDP($A43,"FUT_DLV_DT_FIRST"),"ERROR PLZ FIX")) | I43: =IF($B$3<>"Yes","",IFERROR(BDP($A43,"LAST_TRADEABLE_DT"),"ERROR PLZ FIX")) | J43: =IF($B$3<>"Yes","",IFERROR(BDP($A43,"VOLUME"),"ERROR PLZ FIX")) | K43: =IF($B$3<>"Yes","",IFERROR(BDP($A43,"OPEN_INT"),"ERROR PLZ FIX"))
B44: =IF($B$3<>"Yes","",IFERROR(BDP($A44,"SECURITY_DES"),"ERROR PLZ FIX")) | C44: =IF($B$3<>"Yes","",IFERROR(BDP($A44,"PX_LAST"),"ERROR PLZ FIX")) | D44: =IF($B$3<>"Yes","",IFERROR(BDP($A44,"PX_BID"),"ERROR PLZ FIX")) | E44: =IF($B$3<>"Yes","",IFERROR(BDP($A44,"PX_ASK"),"ERROR PLZ FIX")) | F44: =IFERROR(100-C44,"ERROR PLZ FIX") | G44: =IF($B$3<>"Yes","",IFERROR(BDP($A44,"FUT_MONTH_YR"),"ERROR PLZ FIX")) | H44: =IF($B$3<>"Yes","",IFERROR(BDP($A44,"FUT_DLV_DT_FIRST"),"ERROR PLZ FIX")) | I44: =IF($B$3<>"Yes","",IFERROR(BDP($A44,"LAST_TRADEABLE_DT"),"ERROR PLZ FIX")) | J44: =IF($B$3<>"Yes","",IFERROR(BDP($A44,"VOLUME"),"ERROR PLZ FIX")) | K44: =IF($B$3<>"Yes","",IFERROR(BDP($A44,"OPEN_INT"),"ERROR PLZ FIX"))

Sheet S490_Snapshot
A1: S490_Snapshot
A2: Bloomberg S490 Curve Analysis capture - FROZEN. USD SOFR (vs FIXED), Step Forward (Cont), Settle 07/21/26, Curve Side Mid, Shift +0.00bp.
A3: Single place to update the comparison. Market Rate feeds SOFR_OIS_Quotes!J (input); Zero/Discount feed Bootstrap T:U and Bloomberg_S490_Validation (target).
A4: Matched pair: Market Rate is the mid of the export's bid/ask. Valid while VAL_DATE = 07/21/2026.
A6: Date | B6: Tenor | C6: Market rate (%) | D6: Zero rate (%) | E6: Discount
A7: 46233 | B7: 1W | C7: 3.6376 | D7: 3.68682 | E7: 0.999091
A8: 46240 | B8: 2W | C8: 3.6733 | D8: 3.71731 | E8: 0.998372
A9: 46247 | B9: 3W | C9: 3.68739 | D9: 3.73043 | E9: 0.997652
A10: 46258 | B10: 1M | C10: 3.69655 | D10: 3.73852 | E10: 0.996524
A11: 46288 | B11: 2M | C11: 3.72255 | D11: 3.75985 | E11: 0.993429
A12: 46318 | B12: 3M | C12: 3.77525 | D12: 3.80673 | E12: 0.990244
A13: 46349 | B13: 4M | C13: 3.82085 | D13: 3.84626 | E13: 0.986914
A14: 46379 | B14: 5M | C14: 3.8622 | D14: 3.88151 | E14: 0.983652
A15: 46412 | B15: 6M | C15: 3.908 | D15: 3.9203 | E15: 0.98001
A16: 46441 | B16: 7M | C16: 3.9415 | D16: 3.94751 | E16: 0.976805
A17: 46469 | B17: 8M | C17: 3.96975 | D17: 3.96958 | E17: 0.973707
A18: 46500 | B18: 9M | C18: 4.0007 | D18: 3.9935 | E18: 0.970254
... A38: 64489 | B38: 50Y | C38: 4.12427 | D38: 3.81556 | E38: 0.148177
A40: 32 pillars

Sheet Bootstrap
A1: Bootstrap | R1: Pillar dates are modified-following business-day adjusted (weekends only, no holiday calendar). Bloomberg rolls 07/23/2033->07/25/2033 and 07/23/2028->07/24/2028; plain EDATE did not, which shifted the curve.
A2: Purely-OIS USD SOFR curve: short single-payment OIS (≤1Y) + annual OIS swaps (18M–50Y). The production curve — used by Swap_Pricer, Curve_Interface and the CDS module.
R3: 12Y+ solved on Curve_Solver to break the gap-row annuity circularity.
A4: Spot (T+2): | B4: =WORKDAY(VAL_DATE,2) | C4: DFspot: | D4: 1 | E4: DF(settle)=1: the S490 Settle Date is the curve date, so there is no spot-lag stub. SOFR_Fixings o/n is informational only. | F4: Curve source | G4: Fixed (S490 07/21/26) | I4: Live / Fixed / Test 1-3. Test cases come from the Testing sheet and route through SOFR_OIS_Quotes!H, so the whole curve and the charts follow.
A5: Purely-OIS USD SOFR curve. Short single-payment OIS to 1Y, annual OIS swaps 18M-50Y. The production curve: Swap_Pricer, Curve_Interface and the CDS module all read it. See Method. | R5: Rebuilds each solved pillar from its own annuity and differences it against the solver. ~0 confirms the par identity.
S6: Working — fixed-leg PV = float-leg PV (par swap) | X6: from S490_Snapshot, never BDP | AA6: Targets live on S490_Snapshot.
A7: Tenor | B7: Maturity date | C7: T (yrs) | D7: tau0 spot→mat | E7: Par rate S (%) dynamic | F7: tau coupon | G7: Annuity A(prior) | H7: Discount factor | I7: Ann.add tau·DF | J7: Zero rate (%) cont. | K7: Fwd rate (%) | L7: S490 zero (%) [paste] | M7: Δ vs S490 (bp) | N7: DF source | P7: yr | Q7: quoted % | R7: Par check (~0) | S7: Annuity Σα·DF | T7: Zero (S490) | U7: DF (S490) | V7: d zero (bp) | W7: d DF | X7: Par rate S hard-coded (%) | Y7: d in-use vs fixed (bp)
A8: 1W | B8: =IF(MONTH((($B$4+7)+IF(WEEKDAY(($B$4+7),2)=6,2,IF(WEEKDAY(($B$4+7),2)=7,1,0))))<>MONTH(($B$4+7)),(($B$4+7)-IF(WEEKDAY(($B$4+7),2)=6,1,IF(WEEKDAY(($B$4+7),2)=7,2,0))),(($B$4+7)+IF(WEEKDAY(($B$4+7),2)=6,2,IF(WEEKDAY(($B$4+7),2)=7,1,0)))) | C8: =(B8-VAL_DATE)/365 | D8: =(B8-VAL_DATE)/360 | E8: ='SOFR_OIS_Quotes'!$H5 | G8: 0 | H8: =$D$4/(1+(E8/100)*D8) | I8: 0 | J8: =-LN(H8)/C8*100 | K8: =(1/H8-1)/D8*100 | M8: =IF(L8="","",(J8-L8)*100) | N8: market | P8: 1 | Q8: ='SOFR_OIS_Quotes'!$H19 | S8: =(D8*H8) | T8: =IFERROR(INDEX(S490_Snapshot!$D$7:$D$38,MATCH(B8,S490_Snapshot!$A$7:$A$38,0)),"") | U8: =IFERROR(INDEX(S490_Snapshot!$E$7:$E$38,MATCH(B8,S490_Snapshot!$A$7:$A$38,0)),"") | V8: =IF(T8="","",(J8-T8)*100) | W8: =IF(U8="","",H8-U8) | X8: =IFERROR(INDEX(S490_Snapshot!$C$7:$C$38,MATCH(B8,S490_Snapshot!$A$7:$A$38,0)),"") | Y8: =IF(OR(X8="",NOT(ISNUMBER(E8))),"",(E8-X8)*100)
A9: 2W | B9: =IF(MONTH((($B$4+14)+IF(WEEKDAY(($B$4+14),2)=6,2,IF(WEEKDAY(($B$4+14),2)=7,1,0))))<>MONTH(($B$4+14)),(($B$4+14)-IF(WEEKDAY(($B$4+14),2)=6,1,IF(WEEKDAY(($B$4+14),2)=7,2,0))),(($B$4+14)+IF(WEEKDAY(($B$4+14),2)=6,2,IF(WEEKDAY(($B$4+14),2)=7,1,0)))) | C9: =(B9-VAL_DATE)/365 | D9: =(B9-VAL_DATE)/360 | E9: ='SOFR_OIS_Quotes'!$H6 | G9: =SUM($I$8:I8) | H9: =$D$4/(1+(E9/100)*D9) | I9: 0 | J9: =-LN(H9)/C9*100 | K9: =(H8/H9-1)/((B9-B8)/360)*100 | M9: =IF(L9="","",(J9-L9)*100) | N9: market | P9: 2 | Q9: ='SOFR_OIS_Quotes'!$H21 | S9: =(D9*H9) | T9: =IFERROR(INDEX(S490_Snapshot!$D$7:$D$38,MATCH(B9,S490_Snapshot!$A$7:$A$38,0)),"") | U9: =IFERROR(INDEX(S490_Snapshot!$E$7:$E$38,MATCH(B9,S490_Snapshot!$A$7:$A$38,0)),"") | V9: =IF(T9="","",(J9-T9)*100) | W9: =IF(U9="","",H9-U9) | X9: =IFERROR(INDEX(S490_Snapshot!$C$7:$C$38,MATCH(B9,S490_Snapshot!$A$7:$A$38,0)),"") | Y9: =IF(OR(X9="",NOT(ISNUMBER(E9))),"",(E9-X9)*100)
A10: 3W | B10: =IF(MONTH((($B$4+21)+IF(WEEKDAY(($B$4+21),2)=6,2,IF(WEEKDAY(($B$4+21),2)=7,1,0))))<>MONTH(($B$4+21)),(($B$4+21)-IF(WEEKDAY(($B$4+21),2)=6,1,IF(WEEKDAY(($B$4+21),2)=7,2,0))),(($B$4+21)+IF(WEEKDAY(($B$4+21),2)=6,2,IF(WEEKDAY(($B$4+21),2)=7,1,0)))) | C10: =(B10-VAL_DATE)/365 | D10: =(B10-VAL_DATE)/360 | E10: ='SOFR_OIS_Quotes'!$H7 | G10: =SUM($I$8:I9) | H10: =$D$4/(1+(E10/100)*D10) | I10: 0 | J10: =-LN(H10)/C10*100 | K10: =(H9/H10-1)/((B10-B9)/360)*100 | M10: =IF(L10="","",(J10-L10)*100) | N10: market | P10: 3 | Q10: ='SOFR_OIS_Quotes'!$H22 | S10: =(D10*H10) | T10: =IFERROR(INDEX(S490_Snapshot!$D$7:$D$38,MATCH(B10,S490_Snapshot!$A$7:$A$38,0)),"") | U10: =IFERROR(INDEX(S490_Snapshot!$E$7:$E$38,MATCH(B10,S490_Snapshot!$A$7:$A$38,0)),"") | V10: =IF(T10="","",(J10-T10)*100) | W10: =IF(U10="","",H10-U10) | X10: =IFERROR(INDEX(S490_Snapshot!$C$7:$C$38,MATCH(B10,S490_Snapshot!$A$7:$A$38,0)),"") | Y10: =IF(OR(X10="",NOT(ISNUMBER(E10))),"",(E10-X10)*100)
A11: 1M | B11: =IF(MONTH(((EDATE($B$4,1))+IF(WEEKDAY((EDATE($B$4,1)),2)=6,2,IF(WEEKDAY((EDATE($B$4,1)),2)=7,1,0))))<>MONTH((EDATE($B$4,1))),((EDATE($B$4,1))-IF(WEEKDAY((EDATE($B$4,1)),2)=6,1,IF(WEEKDAY((EDATE($B$4,1)),2)=7,2,0))),((EDATE($B$4,1))+IF(WEEKDAY((EDATE($B$4,1)),2)=6,2,IF(WEEKDAY((EDATE($B$4,1)),2)=7,1,0)))) | C11: =(B11-VAL_DATE)/365 | D11: =(B11-VAL_DATE)/360 | E11: ='SOFR_OIS_Quotes'!$H8 | G11: =SUM($I$8:I10) | H11: =$D$4/(1+(E11/100)*D11) | I11: 0 | J11: =-LN(H11)/C11*100 | K11: =(H10/H11-1)/((B11-B10)/360)*100 | M11: =IF(L11="","",(J11-L11)*100) | N11: market | P11: 4 | Q11: ='SOFR_OIS_Quotes'!$H23 | S11: =(D11*H11) | T11: =IFERROR(INDEX(S490_Snapshot!$D$7:$D$38,MATCH(B11,S490_Snapshot!$A$7:$A$38,0)),"") | U11: =IFERROR(INDEX(S490_Snapshot!$E$7:$E$38,MATCH(B11,S490_Snapshot!$A$7:$A$38,0)),"") | V11: =IF(T11="","",(J11-T11)*100) | W11: =IF(U11="","",H11-U11) | X11: =IFERROR(INDEX(S490_Snapshot!$C$7:$C$38,MATCH(B11,S490_Snapshot!$A$7:$A$38,0)),"") | Y11: =IF(OR(X11="",NOT(ISNUMBER(E11))),"",(E11-X11)*100)
A12: 2M | B12: =IF(MONTH(((EDATE($B$4,2))+IF(WEEKDAY((EDATE($B$4,2)),2)=6,2,IF(WEEKDAY((EDATE($B$4,2)),2)=7,1,0))))<>MONTH((EDATE($B$4,2))),((EDATE($B$4,2))-IF(WEEKDAY((EDATE($B$4,2)),2)=6,1,IF(WEEKDAY((EDATE($B$4,2)),2)=7,2,0))),((EDATE($B$4,2))+IF(WEEKDAY((EDATE($B$4,2)),2)=6,2,IF(WEEKDAY((EDATE($B$4,2)),2)=7,1,0)))) | C12: =(B12-VAL_DATE)/365 | D12: =(B12-VAL_DATE)/360 | E12: ='SOFR_OIS_Quotes'!$H9 | G12: =SUM($I$8:I11) | H12: =$D$4/(1+(E12/100)*D12) | I12: 0 | J12: =-LN(H12)/C12*100 | K12: =(H11/H12-1)/((B12-B11)/360)*100 | M12: =IF(L12="","",(J12-L12)*100) | N12: market | P12: 5 | Q12: ='SOFR_OIS_Quotes'!$H24 | S12: =(D12*H12) | T12: =IFERROR(INDEX(S490_Snapshot!$D$7:$D$38,MATCH(B12,S490_Snapshot!$A$7:$A$38,0)),"") | U12: =IFERROR(INDEX(S490_Snapshot!$E$7:$E$38,MATCH(B12,S490_Snapshot!$A$7:$A$38,0)),"") | V12: =IF(T12="","",(J12-T12)*100) | W12: =IF(U12="","",H12-U12) | X12: =IFERROR(INDEX(S490_Snapshot!$C$7:$C$38,MATCH(B12,S490_Snapshot!$A$7:$A$38,0)),"") | Y12: =IF(OR(X12="",NOT(ISNUMBER(E12))),"",(E12-X12)*100)
A13: 3M | B13: =IF(MONTH(((EDATE($B$4,3))+IF(WEEKDAY((EDATE($B$4,3)),2)=6,2,IF(WEEKDAY((EDATE($B$4,3)),2)=7,1,0))))<>MONTH((EDATE($B$4,3))),((EDATE($B$4,3))-IF(WEEKDAY((EDATE($B$4,3)),2)=6,1,IF(WEEKDAY((EDATE($B$4,3)),2)=7,2,0))),((EDATE($B$4,3))+IF(WEEKDAY((EDATE($B$4,3)),2)=6,2,IF(WEEKDAY((EDATE($B$4,3)),2)=7,1,0)))) | C13: =(B13-VAL_DATE)/365 | D13: =(B13-VAL_DATE)/360 | E13: ='SOFR_OIS_Quotes'!$H10 | G13: =SUM($I$8:I12) | H13: =$D$4/(1+(E13/100)*D13) | I13: 0 | J13: =-LN(H13)/C13*100 | K13: =(H12/H13-1)/((B13-B12)/360)*100 | M13: =IF(L13="","",(J13-L13)*100) | N13: market | P13: 6 | Q13: ='SOFR_OIS_Quotes'!$H25 | S13: =(D13*H13) | T13: =IFERROR(INDEX(S490_Snapshot!$D$7:$D$38,MATCH(B13,S490_Snapshot!$A$7:$A$38,0)),"") | U13: =IFERROR(INDEX(S490_Snapshot!$E$7:$E$38,MATCH(B13,S490_Snapshot!$A$7:$A$38,0)),"") | V13: =IF(T13="","",(J13-T13)*100) | W13: =IF(U13="","",H13-U13) | X13: =IFERROR(INDEX(S490_Snapshot!$C$7:$C$38,MATCH(B13,S490_Snapshot!$A$7:$A$38,0)),"") | Y13: =IF(OR(X13="",NOT(ISNUMBER(E13))),"",(E13-X13)*100)
A14: 4M | B14: =IF(MONTH(((EDATE($B$4,4))+IF(WEEKDAY((EDATE($B$4,4)),2)=6,2,IF(WEEKDAY((EDATE($B$4,4)),2)=7,1,0))))<>MONTH((EDATE($B$4,4))),((EDATE($B$4,4))-IF(WEEKDAY((EDATE($B$4,4)),2)=6,1,IF(WEEKDAY((EDATE($B$4,4)),2)=7,2,0))),((EDATE($B$4,4))+IF(WEEKDAY((EDATE($B$4,4)),2)=6,2,IF(WEEKDAY((EDATE($B$4,4)),2)=7,1,0)))) | C14: =(B14-VAL_DATE)/365 | D14: =(B14-VAL_DATE)/360 | E14: ='SOFR_OIS_Quotes'!$H11 | G14: =SUM($I$8:I13) | H14: =$D$4/(1+(E14/100)*D14) | I14: 0 | J14: =-LN(H14)/C14*100 | K14: =(H13/H14-1)/((B14-B13)/360)*100 | M14: =IF(L14="","",(J14-L14)*100) | N14: market | P14: 7 | Q14: ='SOFR_OIS_Quotes'!$H26 | S14: =(D14*H14) | T14: =IFERROR(INDEX(S490_Snapshot!$D$7:$D$38,MATCH(B14,S490_Snapshot!$A$7:$A$38,0)),"") | U14: =IFERROR(INDEX(S490_Snapshot!$E$7:$E$38,MATCH(B14,S490_Snapshot!$A$7:$A$38,0)),"") | V14: =IF(T14="","",(J14-T14)*100) | W14: =IF(U14="","",H14-U14) | X14: =IFERROR(INDEX(S490_Snapshot!$C$7:$C$38,MATCH(B14,S490_Snapshot!$A$7:$A$38,0)),"") | Y14: =IF(OR(X14="",NOT(ISNUMBER(E14))),"",(E14-X14)*100)
A15: 5M | B15: =IF(MONTH(((EDATE($B$4,5))+IF(WEEKDAY((EDATE($B$4,5)),2)=6,2,IF(WEEKDAY((EDATE($B$4,5)),2)=7,1,0))))<>MONTH((EDATE($B$4,5))),((EDATE($B$4,5))-IF(WEEKDAY((EDATE($B$4,5)),2)=6,1,IF(WEEKDAY((EDATE($B$4,5)),2)=7,2,0))),((EDATE($B$4,5))+IF(WEEKDAY((EDATE($B$4,5)),2)=6,2,IF(WEEKDAY((EDATE($B$4,5)),2)=7,1,0)))) | C15: =(B15-VAL_DATE)/365 | D15: =(B15-VAL_DATE)/360 | E15: ='SOFR_OIS_Quotes'!$H12 | G15: =SUM($I$8:I14) | H15: =$D$4/(1+(E15/100)*D15) | I15: 0 | J15: =-LN(H15)/C15*100 | K15: =(H14/H15-1)/((B15-B14)/360)*100 | M15: =IF(L15="","",(J15-L15)*100) | N15: market | P15: 8 | Q15: ='SOFR_OIS_Quotes'!$H27 | S15: =(D15*H15) | T15: =IFERROR(INDEX(S490_Snapshot!$D$7:$D$38,MATCH(B15,S490_Snapshot!$A$7:$A$38,0)),"") | U15: =IFERROR(INDEX(S490_Snapshot!$E$7:$E$38,MATCH(B15,S490_Snapshot!$A$7:$A$38,0)),"") | V15: =IF(T15="","",(J15-T15)*100) | W15: =IF(U15="","",H15-U15) | X15: =IFERROR(INDEX(S490_Snapshot!$C$7:$C$38,MATCH(B15,S490_Snapshot!$A$7:$A$38,0)),"") | Y15: =IF(OR(X15="",NOT(ISNUMBER(E15))),"",(E15-X15)*100)
A16: 6M | B16: =IF(MONTH(((EDATE($B$4,6))+IF(WEEKDAY((EDATE($B$4,6)),2)=6,2,IF(WEEKDAY((EDATE($B$4,6)),2)=7,1,0))))<>MONTH((EDATE($B$4,6))),((EDATE($B$4,6))-IF(WEEKDAY((EDATE($B$4,6)),2)=6,1,IF(WEEKDAY((EDATE($B$4,6)),2)=7,2,0))),((EDATE($B$4,6))+IF(WEEKDAY((EDATE($B$4,6)),2)=6,2,IF(WEEKDAY((EDATE($B$4,6)),2)=7,1,0)))) | C16: =(B16-VAL_DATE)/365 | D16: =(B16-VAL_DATE)/360 | E16: ='SOFR_OIS_Quotes'!$H13 | G16: =SUM($I$8:I15) | H16: =$D$4/(1+(E16/100)*D16) | I16: 0 | J16: =-LN(H16)/C16*100 | K16: =(H15/H16-1)/((B16-B15)/360)*100 | M16: =IF(L16="","",(J16-L16)*100) | N16: market | P16: 9 | Q16: ='SOFR_OIS_Quotes'!$H28 | S16: =(D16*H16) | T16: =IFERROR(INDEX(S490_Snapshot!$D$7:$D$38,MATCH(B16,S490_Snapshot!$A$7:$A$38,0)),"") | U16: =IFERROR(INDEX(S490_Snapshot!$E$7:$E$38,MATCH(B16,S490_Snapshot!$A$7:$A$38,0)),"") | V16: =IF(T16="","",(J16-T16)*100) | W16: =IF(U16="","",H16-U16) | X16: =IFERROR(INDEX(S490_Snapshot!$C$7:$C$38,MATCH(B16,S490_Snapshot!$A$7:$A$38,0)),"") | Y16: =IF(OR(X16="",NOT(ISNUMBER(E16))),"",(E16-X16)*100)
A17: 7M | B17: =IF(MONTH(((EDATE($B$4,7))+IF(WEEKDAY((EDATE($B$4,7)),2)=6,2,IF(WEEKDAY((EDATE($B$4,7)),2)=7,1,0))))<>MONTH((EDATE($B$4,7))),((EDATE($B$4,7))-IF(WEEKDAY((EDATE($B$4,7)),2)=6,1,IF(WEEKDAY((EDATE($B$4,7)),2)=7,2,0))),((EDATE($B$4,7))+IF(WEEKDAY((EDATE($B$4,7)),2)=6,2,IF(WEEKDAY((EDATE($B$4,7)),2)=7,1,0)))) | C17: =(B17-VAL_DATE)/365 | D17: =(B17-VAL_DATE)/360 | E17: ='SOFR_OIS_Quotes'!$H14 | G17: =SUM($I$8:I16) | H17: =$D$4/(1+(E17/100)*D17) | I17: 0 | J17: =-LN(H17)/C17*100 | K17: =(H16/H17-1)/((B17-B16)/360)*100 | M17: =IF(L17="","",(J17-L17)*100) | N17: market | P17: 10 | Q17: ='SOFR_OIS_Quotes'!$H29 | S17: =(D17*H17) | T17: =IFERROR(INDEX(S490_Snapshot!$D$7:$D$38,MATCH(B17,S490_Snapshot!$A$7:$A$38,0)),"") | U17: =IFERROR(INDEX(S490_Snapshot!$E$7:$E$38,MATCH(B17,S490_Snapshot!$A$7:$A$38,0)),"") | V17: =IF(T17="","",(J17-T17)*100) | W17: =IF(U17="","",H17-U17) | X17: =IFERROR(INDEX(S490_Snapshot!$C$7:$C$38,MATCH(B17,S490_Snapshot!$A$7:$A$38,0)),"") | Y17: =IF(OR(X17="",NOT(ISNUMBER(E17))),"",(E17-X17)*100)
A18: 8M | B18: =IF(MONTH(((EDATE($B$4,8))+IF(WEEKDAY((EDATE($B$4,8)),2)=6,2,IF(WEEKDAY((EDATE($B$4,8)),2)=7,1,0))))<>MONTH((EDATE($B$4,8))),((EDATE($B$4,8))-IF(WEEKDAY((EDATE($B$4,8)),2)=6,1,IF(WEEKDAY((EDATE($B$4,8)),2)=7,2,0))),((EDATE($B$4,8))+IF(WEEKDAY((EDATE($B$4,8)),2)=6,2,IF(WEEKDAY((EDATE($B$4,8)),2)=7,1,0)))) | C18: =(B18-VAL_DATE)/365 | D18: =(B18-VAL_DATE)/360 | E18: ='SOFR_OIS_Quotes'!$H15 | G18: =SUM($I$8:I17) | H18: =$D$4/(1+(E18/100)*D18) | I18: 0 | J18: =-LN(H18)/C18*100 | K18: =(H17/H18-1)/((B18-B17)/360)*100 | M18: =IF(L18="","",(J18-L18)*100) | N18: market | P18: 12 | Q18: ='SOFR_OIS_Quotes'!$H30 | S18: =(D18*H18) | T18: =IFERROR(INDEX(S490_Snapshot!$D$7:$D$38,MATCH(B18,S490_Snapshot!$A$7:$A$38,0)),"") | U18: =IFERROR(INDEX(S490_Snapshot!$E$7:$E$38,MATCH(B18,S490_Snapshot!$A$7:$A$38,0)),"") | V18: =IF(T18="","",(J18-T18)*100) | W18: =IF(U18="","",H18-U18) | X18: =IFERROR(INDEX(S490_Snapshot!$C$7:$C$38,MATCH(B18,S490_Snapshot!$A$7:$A$38,0)),"") | Y18: =IF(OR(X18="",NOT(ISNUMBER(E18))),"",(E18-X18)*100)
A19: 9M | B19: =IF(MONTH(((EDATE($B$4,9))+IF(WEEKDAY((EDATE($B$4,9)),2)=6,2,IF(WEEKDAY((EDATE($B$4,9)),2)=7,1,0))))<>MONTH((EDATE($B$4,9))),((EDATE($B$4,9))-IF(WEEKDAY((EDATE($B$4,9)),2)=6,1,IF(WEEKDAY((EDATE($B$4,9)),2)=7,2,0))),((EDATE($B$4,9))+IF(WEEKDAY((EDATE($B$4,9)),2)=6,2,IF(WEEKDAY((EDATE($B$4,9)),2)=7,1,0)))) | C19: =(B19-VAL_DATE)/365 | D19: =(B19-VAL_DATE)/360 | E19: ='SOFR_OIS_Quotes'!$H16 | G19: =SUM($I$8:I18) | H19: =$D$4/(1+(E19/100)*D19) | I19: 0 | J19: =-LN(H19)/C19*100 | K19: =(H18/H19-1)/((B19-B18)/360)*100 | M19: =IF(L19="","",(J19-L19)*100) | N19: market | P19: 15 | Q19: ='SOFR_OIS_Quotes'!$H31 | S19: =(D19*H19) | T19: =IFERROR(INDEX(S490_Snapshot!$D$7:$D$38,MATCH(B19,S490_Snapshot!$A$7:$A$38,0)),"") | U19: =IFERROR(INDEX(S490_Snapshot!$E$7:$E$38,MATCH(B19,S490_Snapshot!$A$7:$A$38,0)),"") | V19: =IF(T19="","",(J19-T19)*100) | W19: =IF(U19="","",H19-U19) | X19: =IFERROR(INDEX(S490_Snapshot!$C$7:$C$38,MATCH(B19,S490_Snapshot!$A$7:$A$38,0)),"") | Y19: =IF(OR(X19="",NOT(ISNUMBER(E19))),"",(E19-X19)*100)
A20: 10M | B20: =IF(MONTH(((EDATE($B$4,10))+IF(WEEKDAY((EDATE($B$4,10)),2)=6,2,IF(WEEKDAY((EDATE($B$4,10)),2)=7,1,0))))<>MONTH((EDATE($B$4,10))),((EDATE($B$4,10))-IF(WEEKDAY((EDATE($B$4,10)),2)=6,1,IF(WEEKDAY((EDATE($B$4,10)),2)=7,2,0))),((EDATE($B$4,10))+IF(WEEKDAY((EDATE($B$4,10)),2)=6,2,IF(WEEKDAY((EDATE($B$4,10)),2)=7,1,0)))) | C20: =(B20-VAL_DATE)/365 | D20: =(B20-VAL_DATE)/360 | E20: ='SOFR_OIS_Quotes'!$H17 | G20: =SUM($I$8:I19) | H20: =$D$4/(1+(E20/100)*D20) | I20: 0 | J20: =-LN(H20)/C20*100 | K20: =(H19/H20-1)/((B20-B19)/360)*100 | M20: =IF(L20="","",(J20-L20)*100) | N20: market | P20: 20 | Q20: ='SOFR_OIS_Quotes'!$H32 | S20: =(D20*H20) | T20: =IFERROR(INDEX(S490_Snapshot!$D$7:$D$38,MATCH(B20,S490_Snapshot!$A$7:$A$38,0)),"") | U20: =IFERROR(INDEX(S490_Snapshot!$E$7:$E$38,MATCH(B20,S490_Snapshot!$A$7:$A$38,0)),"") | V20: =IF(T20="","",(J20-T20)*100) | W20: =IF(U20="","",H20-U20) | X20: =IFERROR(INDEX(S490_Snapshot!$C$7:$C$38,MATCH(B20,S490_Snapshot!$A$7:$A$38,0)),"") | Y20: =IF(OR(X20="",NOT(ISNUMBER(E20))),"",(E20-X20)*100)
A21: 11M | B21: =IF(MONTH(((EDATE($B$4,11))+IF(WEEKDAY((EDATE($B$4,11)),2)=6,2,IF(WEEKDAY((EDATE($B$4,11)),2)=7,1,0))))<>MONTH((EDATE($B$4,11))),((EDATE($B$4,11))-IF(WEEKDAY((EDATE($B$4,11)),2)=6,1,IF(WEEKDAY((EDATE($B$4,11)),2)=7,2,0))),((EDATE($B$4,11))+IF(WEEKDAY((EDATE($B$4,11)),2)=6,2,IF(WEEKDAY((EDATE($B$4,11)),2)=7,1,0)))) | C21: =(B21-VAL_DATE)/365 | D21: =(B21-VAL_DATE)/360 | E21: ='SOFR_OIS_Quotes'!$H18 | G21: =SUM($I$8:I20) | H21: =$D$4/(1+(E21/100)*D21) | I21: 0 | J21: =-LN(H21)/C21*100 | K21: =(H20/H21-1)/((B21-B20)/360)*100 | M21: =IF(L21="","",(J21-L21)*100) | N21: market | P21: 25 | Q21: ='SOFR_OIS_Quotes'!$H33 | S21: =(D21*H21) | T21: =IFERROR(INDEX(S490_Snapshot!$D$7:$D$38,MATCH(B21,S490_Snapshot!$A$7:$A$38,0)),"") | U21: =IFERROR(INDEX(S490_Snapshot!$E$7:$E$38,MATCH(B21,S490_Snapshot!$A$7:$A$38,0)),"") | V21: =IF(T21="","",(J21-T21)*100) | W21: =IF(U21="","",H21-U21) | X21: =IFERROR(INDEX(S490_Snapshot!$C$7:$C$38,MATCH(B21,S490_Snapshot!$A$7:$A$38,0)),"") | Y21: =IF(OR(X21="",NOT(ISNUMBER(E21))),"",(E21-X21)*100)
A22: 1Y | B22: =IF(MONTH(((EDATE($B$4,12))+IF(WEEKDAY((EDATE($B$4,12)),2)=6,2,IF(WEEKDAY((EDATE($B$4,12)),2)=7,1,0))))<>MONTH((EDATE($B$4,12))),((EDATE($B$4,12))-IF(WEEKDAY((EDATE($B$4,12)),2)=6,1,IF(WEEKDAY((EDATE($B$4,12)),2)=7,2,0))),((EDATE($B$4,12))+IF(WEEKDAY((EDATE($B$4,12)),2)=6,2,IF(WEEKDAY((EDATE($B$4,12)),2)=7,1,0)))) | C22: =(B22-VAL_DATE)/365 | D22: =(B22-VAL_DATE)/360 | E22: ='SOFR_OIS_Quotes'!$H19 | F22: =(B22-VAL_DATE)/360 | G22: =SUM($I$8:I21) | H22: =$D$4/(1+(E22/100)*D22) | I22: =F22*H22 | J22: =-LN(H22)/C22*100 | K22: =(H21/H22-1)/((B22-B21)/360)*100 | M22: =IF(L22="","",(J22-L22)*100) | N22: market | P22: 30 | Q22: ='SOFR_OIS_Quotes'!$H34 | S22: =(D22*H22) | T22: =IFERROR(INDEX(S490_Snapshot!$D$7:$D$38,MATCH(B22,S490_Snapshot!$A$7:$A$38,0)),"") | U22: =IFERROR(INDEX(S490_Snapshot!$E$7:$E$38,MATCH(B22,S490_Snapshot!$A$7:$A$38,0)),"") | V22: =IF(T22="","",(J22-T22)*100) | W22: =IF(U22="","",H22-U22) | X22: =IFERROR(INDEX(S490_Snapshot!$C$7:$C$38,MATCH(B22,S490_Snapshot!$A$7:$A$38,0)),"") | Y22: =IF(OR(X22="",NOT(ISNUMBER(E22))),"",(E22-X22)*100)
A23: 18M | B23: =IF(MONTH(((EDATE($B$4,18))+IF(WEEKDAY((EDATE($B$4,18)),2)=6,2,IF(WEEKDAY((EDATE($B$4,18)),2)=7,1,0))))<>MONTH((EDATE($B$4,18))),((EDATE($B$4,18))-IF(WEEKDAY((EDATE($B$4,18)),2)=6,1,IF(WEEKDAY((EDATE($B$4,18)),2)=7,2,0))),((EDATE($B$4,18))+IF(WEEKDAY((EDATE($B$4,18)),2)=6,2,IF(WEEKDAY((EDATE($B$4,18)),2)=7,1,0)))) | C23: =(B23-VAL_DATE)/365 | D23: =(B23-$B$4)/360 | E23: ='SOFR_OIS_Quotes'!$H20 | F23: =(B23-$B$22)/360 | G23: =SUM($I$8:I22) | H23: =($D$4-(E23/100)*G23)/(1+(E23/100)*F23) | I23: 0 | J23: =-LN(H23)/C23*100 | K23: =(H22/H23-1)/((B23-B22)/360)*100 | M23: =IF(L23="","",(J23-L23)*100) | N23: market | P23: 40 | Q23: ='SOFR_OIS_Quotes'!$H35 | S23: =(G23+F23*H23) | T23: =IFERROR(INDEX(S490_Snapshot!$D$7:$D$38,MATCH(B23,S490_Snapshot!$A$7:$A$38,0)),"") | U23: =IFERROR(INDEX(S490_Snapshot!$E$7:$E$38,MATCH(B23,S490_Snapshot!$A$7:$A$38,0)),"") | V23: =IF(T23="","",(J23-T23)*100) | W23: =IF(U23="","",H23-U23) | X23: =IFERROR(INDEX(S490_Snapshot!$C$7:$C$38,MATCH(B23,S490_Snapshot!$A$7:$A$38,0)),"") | Y23: =IF(OR(X23="",NOT(ISNUMBER(E23))),"",(E23-X23)*100)
A24: 2Y | B24: =IF(MONTH(((EDATE($B$4,24))+IF(WEEKDAY((EDATE($B$4,24)),2)=6,2,IF(WEEKDAY((EDATE($B$4,24)),2)=7,1,0))))<>MONTH((EDATE($B$4,24))),((EDATE($B$4,24))-IF(WEEKDAY((EDATE($B$4,24)),2)=6,1,IF(WEEKDAY((EDATE($B$4,24)),2)=7,2,0))),((EDATE($B$4,24))+IF(WEEKDAY((EDATE($B$4,24)),2)=6,2,IF(WEEKDAY((EDATE($B$4,24)),2)=7,1,0)))) | C24: =(B24-VAL_DATE)/365 | D24: =(B24-$B$4)/360 | E24: ='SOFR_OIS_Quotes'!$H21 | F24: =(B24-$B$22)/360 | G24: =SUM($I$8:I23) | H24: =($D$4-(E24/100)*G24)/(1+(E24/100)*F24) | I24: =F24*H24 | J24: =-LN(H24)/C24*100 | K24: =(H23/H24-1)/((B24-B23)/360)*100 | M24: =IF(L24="","",(J24-L24)*100) | N24: market | P24: 50 | Q24: ='SOFR_OIS_Quotes'!$H36 | S24: =(G24+F24*H24) | T24: =IFERROR(INDEX(S490_Snapshot!$D$7:$D$38,MATCH(B24,S490_Snapshot!$A$7:$A$38,0)),"") | U24: =IFERROR(INDEX(S490_Snapshot!$E$7:$E$38,MATCH(B24,S490_Snapshot!$A$7:$A$38,0)),"") | V24: =IF(T24="","",(J24-T24)*100) | W24: =IF(U24="","",H24-U24) | X24: =IFERROR(INDEX(S490_Snapshot!$C$7:$C$38,MATCH(B24,S490_Snapshot!$A$7:$A$38,0)),"") | Y24: =IF(OR(X24="",NOT(ISNUMBER(E24))),"",(E24-X24)*100)
A25: 3Y | B25: =IF(MONTH(((EDATE($B$4,36))+IF(WEEKDAY((EDATE($B$4,36)),2)=6,2,IF(WEEKDAY((EDATE($B$4,36)),2)=7,1,0))))<>MONTH((EDATE($B$4,36))),((EDATE($B$4,36))-IF(WEEKDAY((EDATE($B$4,36)),2)=6,1,IF(WEEKDAY((EDATE($B$4,36)),2)=7,2,0))),((EDATE($B$4,36))+IF(WEEKDAY((EDATE($B$4,36)),2)=6,2,IF(WEEKDAY((EDATE($B$4,36)),2)=7,1,0)))) | C25: =(B25-VAL_DATE)/365 | D25: =(B25-$B$4)/360 | E25: ='SOFR_OIS_Quotes'!$H22 | F25: =(B25-$B$24)/360 | G25: =SUM($I$8:I24) | H25: =($D$4-(E25/100)*G25)/(1+(E25/100)*F25) | I25: =F25*H25 | J25: =-LN(H25)/C25*100 | K25: =(H24/H25-1)/((B25-B24)/360)*100 | M25: =IF(L25="","",(J25-L25)*100) | N25: market | S25: =(G25+F25*H25) | T25: =IFERROR(INDEX(S490_Snapshot!$D$7:$D$38,MATCH(B25,S490_Snapshot!$A$7:$A$38,0)),"") | U25: =IFERROR(INDEX(S490_Snapshot!$E$7:$E$38,MATCH(B25,S490_Snapshot!$A$7:$A$38,0)),"") | V25: =IF(T25="","",(J25-T25)*100) | W25: =IF(U25="","",H25-U25) | X25: =IFERROR(INDEX(S490_Snapshot!$C$7:$C$38,MATCH(B25,S490_Snapshot!$A$7:$A$38,0)),"") | Y25: =IF(OR(X25="",NOT(ISNUMBER(E25))),"",(E25-X25)*100)
A26: 4Y | B26: =IF(MONTH(((EDATE($B$4,48))+IF(WEEKDAY((EDATE($B$4,48)),2)=6,2,IF(WEEKDAY((EDATE($B$4,48)),2)=7,1,0))))<>MONTH((EDATE($B$4,48))),((EDATE($B$4,48))-IF(WEEKDAY((EDATE($B$4,48)),2)=6,1,IF(WEEKDAY((EDATE($B$4,48)),2)=7,2,0))),((EDATE($B$4,48))+IF(WEEKDAY((EDATE($B$4,48)),2)=6,2,IF(WEEKDAY((EDATE($B$4,48)),2)=7,1,0)))) | C26: =(B26-VAL_DATE)/365 | D26: =(B26-$B$4)/360 | E26: ='SOFR_OIS_Quotes'!$H23 | F26: =(B26-$B$25)/360 | G26: =SUM($I$8:I25) | H26: =($D$4-(E26/100)*G26)/(1+(E26/100)*F26) | I26: =F26*H26 | J26: =-LN(H26)/C26*100 | K26: =(H25/H26-1)/((B26-B25)/360)*100 | M26: =IF(L26="","",(J26-L26)*100) | N26: market | S26: =(G26+F26*H26) | T26: =IFERROR(INDEX(S490_Snapshot!$D$7:$D$38,MATCH(B26,S490_Snapshot!$A$7:$A$38,0)),"") | U26: =IFERROR(INDEX(S490_Snapshot!$E$7:$E$38,MATCH(B26,S490_Snapshot!$A$7:$A$38,0)),"") | V26: =IF(T26="","",(J26-T26)*100) | W26: =IF(U26="","",H26-U26) | X26: =IFERROR(INDEX(S490_Snapshot!$C$7:$C$38,MATCH(B26,S490_Snapshot!$A$7:$A$38,0)),"") | Y26: =IF(OR(X26="",NOT(ISNUMBER(E26))),"",(E26-X26)*100)
A27: 5Y | B27: =IF(MONTH(((EDATE($B$4,60))+IF(WEEKDAY((EDATE($B$4,60)),2)=6,2,IF(WEEKDAY((EDATE($B$4,60)),2)=7,1,0))))<>MONTH((EDATE($B$4,60))),((EDATE($B$4,60))-IF(WEEKDAY((EDATE($B$4,60)),2)=6,1,IF(WEEKDAY((EDATE($B$4,60)),2)=7,2,0))),((EDATE($B$4,60))+IF(WEEKDAY((EDATE($B$4,60)),2)=6,2,IF(WEEKDAY((EDATE($B$4,60)),2)=7,1,0)))) | C27: =(B27-VAL_DATE)/365 | D27: =(B27-$B$4)/360 | E27: ='SOFR_OIS_Quotes'!$H24 | F27: =(B27-$B$26)/360 | G27: =SUM($I$8:I26) | H27: =($D$4-(E27/100)*G27)/(1+(E27/100)*F27) | I27: =F27*H27 | J27: =-LN(H27)/C27*100 | K27: =(H26/H27-1)/((B27-B26)/360)*100 | M27: =IF(L27="","",(J27-L27)*100) | N27: market | S27: =(G27+F27*H27) | T27: =IFERROR(INDEX(S490_Snapshot!$D$7:$D$38,MATCH(B27,S490_Snapshot!$A$7:$A$38,0)),"") | U27: =IFERROR(INDEX(S490_Snapshot!$E$7:$E$38,MATCH(B27,S490_Snapshot!$A$7:$A$38,0)),"") | V27: =IF(T27="","",(J27-T27)*100) | W27: =IF(U27="","",H27-U27) | X27: =IFERROR(INDEX(S490_Snapshot!$C$7:$C$38,MATCH(B27,S490_Snapshot!$A$7:$A$38,0)),"") | Y27: =IF(OR(X27="",NOT(ISNUMBER(E27))),"",(E27-X27)*100)
A28: 6Y | B28: =IF(MONTH(((EDATE($B$4,72))+IF(WEEKDAY((EDATE($B$4,72)),2)=6,2,IF(WEEKDAY((EDATE($B$4,72)),2)=7,1,0))))<>MONTH((EDATE($B$4,72))),((EDATE($B$4,72))-IF(WEEKDAY((EDATE($B$4,72)),2)=6,1,IF(WEEKDAY((EDATE($B$4,72)),2)=7,2,0))),((EDATE($B$4,72))+IF(WEEKDAY((EDATE($B$4,72)),2)=6,2,IF(WEEKDAY((EDATE($B$4,72)),2)=7,1,0)))) | C28: =(B28-VAL_DATE)/365 | D28: =(B28-$B$4)/360 | E28: ='SOFR_OIS_Quotes'!$H25 | F28: =(B28-$B$27)/360 | G28: =SUM($I$8:I27) | H28: =($D$4-(E28/100)*G28)/(1+(E28/100)*F28) | I28: =F28*H28 | J28: =-LN(H28)/C28*100 | K28: =(H27/H28-1)/((B28-B27)/360)*100 | M28: =IF(L28="","",(J28-L28)*100) | N28: market | S28: =(G28+F28*H28) | T28: =IFERROR(INDEX(S490_Snapshot!$D$7:$D$38,MATCH(B28,S490_Snapshot!$A$7:$A$38,0)),"") | U28: =IFERROR(INDEX(S490_Snapshot!$E$7:$E$38,MATCH(B28,S490_Snapshot!$A$7:$A$38,0)),"") | V28: =IF(T28="","",(J28-T28)*100) | W28: =IF(U28="","",H28-U28) | X28: =IFERROR(INDEX(S490_Snapshot!$C$7:$C$38,MATCH(B28,S490_Snapshot!$A$7:$A$38,0)),"") | Y28: =IF(OR(X28="",NOT(ISNUMBER(E28))),"",(E28-X28)*100)
A29: 7Y | B29: =IF(MONTH(((EDATE($B$4,84))+IF(WEEKDAY((EDATE($B$4,84)),2)=6,2,IF(WEEKDAY((EDATE($B$4,84)),2)=7,1,0))))<>MONTH((EDATE($B$4,84))),((EDATE($B$4,84))-IF(WEEKDAY((EDATE($B$4,84)),2)=6,1,IF(WEEKDAY((EDATE($B$4,84)),2)=7,2,0))),((EDATE($B$4,84))+IF(WEEKDAY((EDATE($B$4,84)),2)=6,2,IF(WEEKDAY((EDATE($B$4,84)),2)=7,1,0)))) | C29: =(B29-VAL_DATE)/365 | D29: =(B29-$B$4)/360 | E29: ='SOFR_OIS_Quotes'!$H26 | F29: =(B29-$B$28)/360 | G29: =SUM($I$8:I28) | H29: =($D$4-(E29/100)*G29)/(1+(E29/100)*F29) | I29: =F29*H29 | J29: =-LN(H29)/C29*100 | K29: =(H28/H29-1)/((B29-B28)/360)*100 | M29: =IF(L29="","",(J29-L29)*100) | N29: market | S29: =(G29+F29*H29) | T29: =IFERROR(INDEX(S490_Snapshot!$D$7:$D$38,MATCH(B29,S490_Snapshot!$A$7:$A$38,0)),"") | U29: =IFERROR(INDEX(S490_Snapshot!$E$7:$E$38,MATCH(B29,S490_Snapshot!$A$7:$A$38,0)),"") | V29: =IF(T29="","",(J29-T29)*100) | W29: =IF(U29="","",H29-U29) | X29: =IFERROR(INDEX(S490_Snapshot!$C$7:$C$38,MATCH(B29,S490_Snapshot!$A$7:$A$38,0)),"") | Y29: =IF(OR(X29="",NOT(ISNUMBER(E29))),"",(E29-X29)*100)
A30: 8Y | B30: =IF(MONTH(((EDATE($B$4,96))+IF(WEEKDAY((EDATE($B$4,96)),2)=6,2,IF(WEEKDAY((EDATE($B$4,96)),2)=7,1,0))))<>MONTH((EDATE($B$4,96))),((EDATE($B$4,96))-IF(WEEKDAY((EDATE($B$4,96)),2)=6,1,IF(WEEKDAY((EDATE($B$4,96)),2)=7,2,0))),((EDATE($B$4,96))+IF(WEEKDAY((EDATE($B$4,96)),2)=6,2,IF(WEEKDAY((EDATE($B$4,96)),2)=7,1,0)))) | C30: =(B30-VAL_DATE)/365 | D30: =(B30-$B$4)/360 | E30: ='SOFR_OIS_Quotes'!$H27 | F30: =(B30-$B$29)/360 | G30: =SUM($I$8:I29) | H30: =($D$4-(E30/100)*G30)/(1+(E30/100)*F30) | I30: =F30*H30 | J30: =-LN(H30)/C30*100 | K30: =(H29/H30-1)/((B30-B29)/360)*100 | M30: =IF(L30="","",(J30-L30)*100) | N30: market | S30: =(G30+F30*H30) | T30: =IFERROR(INDEX(S490_Snapshot!$D$7:$D$38,MATCH(B30,S490_Snapshot!$A$7:$A$38,0)),"") | U30: =IFERROR(INDEX(S490_Snapshot!$E$7:$E$38,MATCH(B30,S490_Snapshot!$A$7:$A$38,0)),"") | V30: =IF(T30="","",(J30-T30)*100) | W30: =IF(U30="","",H30-U30) | X30: =IFERROR(INDEX(S490_Snapshot!$C$7:$C$38,MATCH(B30,S490_Snapshot!$A$7:$A$38,0)),"") | Y30: =IF(OR(X30="",NOT(ISNUMBER(E30))),"",(E30-X30)*100)
A31: 9Y | B31: =IF(MONTH(((EDATE($B$4,108))+IF(WEEKDAY((EDATE($B$4,108)),2)=6,2,IF(WEEKDAY((EDATE($B$4,108)),2)=7,1,0))))<>MONTH((EDATE($B$4,108))),((EDATE($B$4,108))-IF(WEEKDAY((EDATE($B$4,108)),2)=6,1,IF(WEEKDAY((EDATE($B$4,108)),2)=7,2,0))),((EDATE($B$4,108))+IF(WEEKDAY((EDATE($B$4,108)),2)=6,2,IF(WEEKDAY((EDATE($B$4,108)),2)=7,1,0)))) | C31: =(B31-VAL_DATE)/365 | D31: =(B31-$B$4)/360 | E31: ='SOFR_OIS_Quotes'!$H28 | F31: =(B31-$B$30)/360 | G31: =SUM($I$8:I30) | H31: =($D$4-(E31/100)*G31)/(1+(E31/100)*F31) | I31: =F31*H31 | J31: =-LN(H31)/C31*100 | K31: =(H30/H31-1)/((B31-B30)/360)*100 | M31: =IF(L31="","",(J31-L31)*100) | N31: market | S31: =(G31+F31*H31) | T31: =IFERROR(INDEX(S490_Snapshot!$D$7:$D$38,MATCH(B31,S490_Snapshot!$A$7:$A$38,0)),"") | U31: =IFERROR(INDEX(S490_Snapshot!$E$7:$E$38,MATCH(B31,S490_Snapshot!$A$7:$A$38,0)),"") | V31: =IF(T31="","",(J31-T31)*100) | W31: =IF(U31="","",H31-U31) | X31: =IFERROR(INDEX(S490_Snapshot!$C$7:$C$38,MATCH(B31,S490_Snapshot!$A$7:$A$38,0)),"") | Y31: =IF(OR(X31="",NOT(ISNUMBER(E31))),"",(E31-X31)*100)
A32: 10Y | B32: =IF(MONTH(((EDATE($B$4,120))+IF(WEEKDAY((EDATE($B$4,120)),2)=6,2,IF(WEEKDAY((EDATE($B$4,120)),2)=7,1,0))))<>MONTH((EDATE($B$4,120))),((EDATE($B$4,120))-IF(WEEKDAY((EDATE($B$4,120)),2)=6,1,IF(WEEKDAY((EDATE($B$4,120)),2)=7,2,0))),((EDATE($B$4,120))+IF(WEEKDAY((EDATE($B$4,120)),2)=6,2,IF(WEEKDAY((EDATE($B$4,120)),2)=7,1,0)))) | C32: =(B32-VAL_DATE)/365 | D32: =(B32-$B$4)/360 | E32: ='SOFR_OIS_Quotes'!$H29 | F32: =(B32-$B$31)/360 | G32: =SUM($I$8:I31) | H32: =($D$4-(E32/100)*G32)/(1+(E32/100)*F32) | I32: =F32*H32 | J32: =-LN(H32)/C32*100 | K32: =(H31/H32-1)/((B32-B31)/360)*100 | M32: =IF(L32="","",(J32-L32)*100) | N32: market | S32: =(G32+F32*H32) | T32: =IFERROR(INDEX(S490_Snapshot!$D$7:$D$38,MATCH(B32,S490_Snapshot!$A$7:$A$38,0)),"") | U32: =IFERROR(INDEX(S490_Snapshot!$E$7:$E$38,MATCH(B32,S490_Snapshot!$A$7:$A$38,0)),"") | V32: =IF(T32="","",(J32-T32)*100) | W32: =IF(U32="","",H32-U32) | X32: =IFERROR(INDEX(S490_Snapshot!$C$7:$C$38,MATCH(B32,S490_Snapshot!$A$7:$A$38,0)),"") | Y32: =IF(OR(X32="",NOT(ISNUMBER(E32))),"",(E32-X32)*100)
A33: 11Y | B33: =IF(MONTH(((EDATE($B$4,132))+IF(WEEKDAY((EDATE($B$4,132)),2)=6,2,IF(WEEKDAY((EDATE($B$4,132)),2)=7,1,0))))<>MONTH((EDATE($B$4,132))),((EDATE($B$4,132))-IF(WEEKDAY((EDATE($B$4,132)),2)=6,1,IF(WEEKDAY((EDATE($B$4,132)),2)=7,2,0))),((EDATE($B$4,132))+IF(WEEKDAY((EDATE($B$4,132)),2)=6,2,IF(WEEKDAY((EDATE($B$4,132)),2)=7,1,0)))) | C33: =(B33-VAL_DATE)/365 | D33: =(B33-$B$4)/360 | E33: =INDEX($Q$8:$Q$24,MATCH(11,$P$8:$P$24,1))+(INDEX($Q$8:$Q$24,MATCH(11,$P$8:$P$24,1)+1)-INDEX($Q$8:$Q$24,MATCH(11,$P$8:$P$24,1)))*(11-INDEX($P$8:$P$24,MATCH(11,$P$8:$P$24,1)))/(INDEX($P$8:$P$24,MATCH(11,$P$8:$P$24,1)+1)-INDEX($P$8:$P$24,MATCH(11,$P$8:$P$24,1))) | F33: =(B33-$B$32)/360 | G33: =SUM($I$8:I32) | H33: =H32*(H34/H32)^((C33-C32)/(C34-C32)) | I33: =F33*H33 | J33: =-LN(H33)/C33*100 | K33: =(H32/H33-1)/((B33-B32)/360)*100 | M33: =IF(L33="","",(J33-L33)*100) | N33: interp | S33: =(G33+F33*H33) | T33: =IFERROR(INDEX(S490_Snapshot!$D$7:$D$38,MATCH(B33,S490_Snapshot!$A$7:$A$38,0)),"") | U33: =IFERROR(INDEX(S490_Snapshot!$E$7:$E$38,MATCH(B33,S490_Snapshot!$A$7:$A$38,0)),"") | V33: =IF(T33="","",(J33-T33)*100) | W33: =IF(U33="","",H33-U33) | X33: =IFERROR(INDEX(S490_Snapshot!$C$7:$C$38,MATCH(B33,S490_Snapshot!$A$7:$A$38,0)),"") | Y33: =IF(OR(X33="",NOT(ISNUMBER(E33))),"",(E33-X33)*100)
A34: 12Y | B34: =IF(MONTH(((EDATE($B$4,144))+IF(WEEKDAY((EDATE($B$4,144)),2)=6,2,IF(WEEKDAY((EDATE($B$4,144)),2)=7,1,0))))<>MONTH((EDATE($B$4,144))),((EDATE($B$4,144))-IF(WEEKDAY((EDATE($B$4,144)),2)=6,1,IF(WEEKDAY((EDATE($B$4,144)),2)=7,2,0))),((EDATE($B$4,144))+IF(WEEKDAY((EDATE($B$4,144)),2)=6,2,IF(WEEKDAY((EDATE($B$4,144)),2)=7,1,0)))) | C34: =(B34-VAL_DATE)/365 | D34: =(B34-$B$4)/360 | E34: ='SOFR_OIS_Quotes'!$H30 | F34: =(B34-$B$33)/360 | G34: =SUM($I$8:I33) | H34: =Curve_Solver!$B$53 | I34: =F34*H34 | J34: =-LN(H34)/C34*100 | K34: =(H33/H34-1)/((B34-B33)/360)*100 | M34: =IF(L34="","",(J34-L34)*100) | N34: market | R34: =($D$4-(E34/100)*G34)/(1+(E34/100)*F34)-H34 | S34: =(G34+F34*H34) | T34: =IFERROR(INDEX(S490_Snapshot!$D$7:$D$38,MATCH(B34,S490_Snapshot!$A$7:$A$38,0)),"") | U34: =IFERROR(INDEX(S490_Snapshot!$E$7:$E$38,MATCH(B34,S490_Snapshot!$A$7:$A$38,0)),"") | V34: =IF(T34="","",(J34-T34)*100) | W34: =IF(U34="","",H34-U34) | X34: =IFERROR(INDEX(S490_Snapshot!$C$7:$C$38,MATCH(B34,S490_Snapshot!$A$7:$A$38,0)),"") | Y34: =IF(OR(X34="",NOT(ISNUMBER(E34))),"",(E34-X34)*100)
A35: 13Y | B35: =IF(MONTH(((EDATE($B$4,156))+IF(WEEKDAY((EDATE($B$4,156)),2)=6,2,IF(WEEKDAY((EDATE($B$4,156)),2)=7,1,0))))<>MONTH((EDATE($B$4,156))),((EDATE($B$4,156))-IF(WEEKDAY((EDATE($B$4,156)),2)=6,1,IF(WEEKDAY((EDATE($B$4,156)),2)=7,2,0))),((EDATE($B$4,156))+IF(WEEKDAY((EDATE($B$4,156)),2)=6,2,IF(WEEKDAY((EDATE($B$4,156)),2)=7,1,0)))) | C35: =(B35-VAL_DATE)/365 | D35: =(B35-$B$4)/360 | E35: =INDEX($Q$8:$Q$24,MATCH(13,$P$8:$P$24,1))+(INDEX($Q$8:$Q$24,MATCH(13,$P$8:$P$24,1)+1)-INDEX($Q$8:$Q$24,MATCH(13,$P$8:$P$24,1)))*(13-INDEX($P$8:$P$24,MATCH(13,$P$8:$P$24,1)))/(INDEX($P$8:$P$24,MATCH(13,$P$8:$P$24,1)+1)-INDEX($P$8:$P$24,MATCH(13,$P$8:$P$24,1))) | F35: =(B35-$B$34)/360 | G35: =SUM($I$8:I34) | H35: =H34*(H37/H34)^((C35-C34)/(C37-C34)) | I35: =F35*H35 | J35: =-LN(H35)/C35*100 | K35: =(H34/H35-1)/((B35-B34)/360)*100 | M35: =IF(L35="","",(J35-L35)*100) | N35: interp | S35: =(G35+F35*H35) | T35: =IFERROR(INDEX(S490_Snapshot!$D$7:$D$38,MATCH(B35,S490_Snapshot!$A$7:$A$38,0)),"") | U35: =IFERROR(INDEX(S490_Snapshot!$E$7:$E$38,MATCH(B35,S490_Snapshot!$A$7:$A$38,0)),"") | V35: =IF(T35="","",(J35-T35)*100) | W35: =IF(U35="","",H35-U35) | X35: =IFERROR(INDEX(S490_Snapshot!$C$7:$C$38,MATCH(B35,S490_Snapshot!$A$7:$A$38,0)),"") | Y35: =IF(OR(X35="",NOT(ISNUMBER(E35))),"",(E35-X35)*100)
A36: 14Y | B36: =IF(MONTH(((EDATE($B$4,168))+IF(WEEKDAY((EDATE($B$4,168)),2)=6,2,IF(WEEKDAY((EDATE($B$4,168)),2)=7,1,0))))<>MONTH((EDATE($B$4,168))),((EDATE($B$4,168))-IF(WEEKDAY((EDATE($B$4,168)),2)=6,1,IF(WEEKDAY((EDATE($B$4,168)),2)=7,2,0))),((EDATE($B$4,168))+IF(WEEKDAY((EDATE($B$4,168)),2)=6,2,IF(WEEKDAY((EDATE($B$4,168)),2)=7,1,0)))) | C36: =(B36-VAL_DATE)/365 | D36: =(B36-$B$4)/360 | E36: =INDEX($Q$8:$Q$24,MATCH(14,$P$8:$P$24,1))+(INDEX($Q$8:$Q$24,MATCH(14,$P$8:$P$24,1)+1)-INDEX($Q$8:$Q$24,MATCH(14,$P$8:$P$24,1)))*(14-INDEX($P$8:$P$24,MATCH(14,$P$8:$P$24,1)))/(INDEX($P$8:$P$24,MATCH(14,$P$8:$P$24,1)+1)-INDEX($P$8:$P$24,MATCH(14,$P$8:$P$24,1))) | F36: =(B36-$B$35)/360 | G36: =SUM($I$8:I35) | H36: =H34*(H37/H34)^((C36-C34)/(C37-C34)) | I36: =F36*H36 | J36: =-LN(H36)/C36*100 | K36: =(H35/H36-1)/((B36-B35)/360)*100 | M36: =IF(L36="","",(J36-L36)*100) | N36: interp | S36: =(G36+F36*H36) | T36: =IFERROR(INDEX(S490_Snapshot!$D$7:$D$38,MATCH(B36,S490_Snapshot!$A$7:$A$38,0)),"") | U36: =IFERROR(INDEX(S490_Snapshot!$E$7:$E$38,MATCH(B36,S490_Snapshot!$A$7:$A$38,0)),"") | V36: =IF(T36="","",(J36-T36)*100) | W36: =IF(U36="","",H36-U36) | X36: =IFERROR(INDEX(S490_Snapshot!$C$7:$C$38,MATCH(B36,S490_Snapshot!$A$7:$A$38,0)),"") | Y36: =IF(OR(X36="",NOT(ISNUMBER(E36))),"",(E36-X36)*100)
A37: 15Y | B37: =IF(MONTH(((EDATE($B$4,180))+IF(WEEKDAY((EDATE($B$4,180)),2)=6,2,IF(WEEKDAY((EDATE($B$4,180)),2)=7,1,0))))<>MONTH((EDATE($B$4,180))),((EDATE($B$4,180))-IF(WEEKDAY((EDATE($B$4,180)),2)=6,1,IF(WEEKDAY((EDATE($B$4,180)),2)=7,2,0))),((EDATE($B$4,180))+IF(WEEKDAY((EDATE($B$4,180)),2)=6,2,IF(WEEKDAY((EDATE($B$4,180)),2)=7,1,0)))) | C37: =(B37-VAL_DATE)/365 | D37: =(B37-$B$4)/360 | E37: ='SOFR_OIS_Quotes'!$H31 | F37: =(B37-$B$36)/360 | G37: =SUM($I$8:I36) | H37: =Curve_Solver!$B$103 | I37: =F37*H37 | J37: =-LN(H37)/C37*100 | K37: =(H36/H37-1)/((B37-B36)/360)*100 | M37: =IF(L37="","",(J37-L37)*100) | N37: market | R37: =($D$4-(E37/100)*G37)/(1+(E37/100)*F37)-H37 | S37: =(G37+F37*H37) | T37: =IFERROR(INDEX(S490_Snapshot!$D$7:$D$38,MATCH(B37,S490_Snapshot!$A$7:$A$38,0)),"") | U37: =IFERROR(INDEX(S490_Snapshot!$E$7:$E$38,MATCH(B37,S490_Snapshot!$A$7:$A$38,0)),"") | V37: =IF(T37="","",(J37-T37)*100) | W37: =IF(U37="","",H37-U37) | X37: =IFERROR(INDEX(S490_Snapshot!$C$7:$C$38,MATCH(B37,S490_Snapshot!$A$7:$A$38,0)),"") | Y37: =IF(OR(X37="",NOT(ISNUMBER(E37))),"",(E37-X37)*100)
A38: 16Y | B38: =IF(MONTH(((EDATE($B$4,192))+IF(WEEKDAY((EDATE($B$4,192)),2)=6,2,IF(WEEKDAY((EDATE($B$4,192)),2)=7,1,0))))<>MONTH((EDATE($B$4,192))),((EDATE($B$4,192))-IF(WEEKDAY((EDATE($B$4,192)),2)=6,1,IF(WEEKDAY((EDATE($B$4,192)),2)=7,2,0))),((EDATE($B$4,192))+IF(WEEKDAY((EDATE($B$4,192)),2)=6,2,IF(WEEKDAY((EDATE($B$4,192)),2)=7,1,0)))) | C38: =(B38-VAL_DATE)/365 | D38: =(B38-$B$4)/360 | E38: =INDEX($Q$8:$Q$24,MATCH(16,$P$8:$P$24,1))+(INDEX($Q$8:$Q$24,MATCH(16,$P$8:$P$24,1)+1)-INDEX($Q$8:$Q$24,MATCH(16,$P$8:$P$24,1)))*(16-INDEX($P$8:$P$24,MATCH(16,$P$8:$P$24,1)))/(INDEX($P$8:$P$24,MATCH(16,$P$8:$P$24,1)+1)-INDEX($P$8:$P$24,MATCH(16,$P$8:$P$24,1))) | F38: =(B38-$B$37)/360 | G38: =SUM($I$8:I37) | H38: =H37*(H42/H37)^((C38-C37)/(C42-C37)) | I38: =F38*H38 | J38: =-LN(H38)/C38*100 | K38: =(H37/H38-1)/((B38-B37)/360)*100 | M38: =IF(L38="","",(J38-L38)*100) | N38: interp | S38: =(G38+F38*H38) | T38: =IFERROR(INDEX(S490_Snapshot!$D$7:$D$38,MATCH(B38,S490_Snapshot!$A$7:$A$38,0)),"") | U38: =IFERROR(INDEX(S490_Snapshot!$E$7:$E$38,MATCH(B38,S490_Snapshot!$A$7:$A$38,0)),"") | V38: =IF(T38="","",(J38-T38)*100) | W38: =IF(U38="","",H38-U38) | X38: =IFERROR(INDEX(S490_Snapshot!$C$7:$C$38,MATCH(B38,S490_Snapshot!$A$7:$A$38,0)),"") | Y38: =IF(OR(X38="",NOT(ISNUMBER(E38))),"",(E38-X38)*100)
A39: 17Y | B39: =IF(MONTH(((EDATE($B$4,204))+IF(WEEKDAY((EDATE($B$4,204)),2)=6,2,IF(WEEKDAY((EDATE($B$4,204)),2)=7,1,0))))<>MONTH((EDATE($B$4,204))),((EDATE($B$4,204))-IF(WEEKDAY((EDATE($B$4,204)),2)=6,1,IF(WEEKDAY((EDATE($B$4,204)),2)=7,2,0))),((EDATE($B$4,204))+IF(WEEKDAY((EDATE($B$4,204)),2)=6,2,IF(WEEKDAY((EDATE($B$4,204)),2)=7,1,0)))) | C39: =(B39-VAL_DATE)/365 | D39: =(B39-$B$4)/360 | E39: =INDEX($Q$8:$Q$24,MATCH(17,$P$8:$P$24,1))+(INDEX($Q$8:$Q$24,MATCH(17,$P$8:$P$24,1)+1)-INDEX($Q$8:$Q$24,MATCH(17,$P$8:$P$24,1)))*(17-INDEX($P$8:$P$24,MATCH(17,$P$8:$P$24,1)))/(INDEX($P$8:$P$24,MATCH(17,$P$8:$P$24,1)+1)-INDEX($P$8:$P$24,MATCH(17,$P$8:$P$24,1))) | F39: =(B39-$B$38)/360 | G39: =SUM($I$8:I38) | H39: =H37*(H42/H37)^((C39-C37)/(C42-C37)) | I39: =F39*H39 | J39: =-LN(H39)/C39*100 | K39: =(H38/H39-1)/((B39-B38)/360)*100 | M39: =IF(L39="","",(J39-L39)*100) | N39: interp | S39: =(G39+F39*H39) | T39: =IFERROR(INDEX(S490_Snapshot!$D$7:$D$38,MATCH(B39,S490_Snapshot!$A$7:$A$38,0)),"") | U39: =IFERROR(INDEX(S490_Snapshot!$E$7:$E$38,MATCH(B39,S490_Snapshot!$A$7:$A$38,0)),"") | V39: =IF(T39="","",(J39-T39)*100) | W39: =IF(U39="","",H39-U39) | X39: =IFERROR(INDEX(S490_Snapshot!$C$7:$C$38,MATCH(B39,S490_Snapshot!$A$7:$A$38,0)),"") | Y39: =IF(OR(X39="",NOT(ISNUMBER(E39))),"",(E39-X39)*100)
A40: 18Y | B40: =IF(MONTH(((EDATE($B$4,216))+IF(WEEKDAY((EDATE($B$4,216)),2)=6,2,IF(WEEKDAY((EDATE($B$4,216)),2)=7,1,0))))<>MONTH((EDATE($B$4,216))),((EDATE($B$4,216))-IF(WEEKDAY((EDATE($B$4,216)),2)=6,1,IF(WEEKDAY((EDATE($B$4,216)),2)=7,2,0))),((EDATE($B$4,216))+IF(WEEKDAY((EDATE($B$4,216)),2)=6,2,IF(WEEKDAY((EDATE($B$4,216)),2)=7,1,0)))) | C40: =(B40-VAL_DATE)/365 | D40: =(B40-$B$4)/360 | E40: =INDEX($Q$8:$Q$24,MATCH(18,$P$8:$P$24,1))+(INDEX($Q$8:$Q$24,MATCH(18,$P$8:$P$24,1)+1)-INDEX($Q$8:$Q$24,MATCH(18,$P$8:$P$24,1)))*(18-INDEX($P$8:$P$24,MATCH(18,$P$8:$P$24,1)))/(INDEX($P$8:$P$24,MATCH(18,$P$8:$P$24,1)+1)-INDEX($P$8:$P$24,MATCH(18,$P$8:$P$24,1))) | F40: =(B40-$B$39)/360 | G40: =SUM($I$8:I39) | H40: =H37*(H42/H37)^((C40-C37)/(C42-C37)) | I40: =F40*H40 | J40: =-LN(H40)/C40*100 | K40: =(H39/H40-1)/((B40-B39)/360)*100 | M40: =IF(L40="","",(J40-L40)*100) | N40: interp | S40: =(G40+F40*H40) | T40: =IFERROR(INDEX(S490_Snapshot!$D$7:$D$38,MATCH(B40,S490_Snapshot!$A$7:$A$38,0)),"") | U40: =IFERROR(INDEX(S490_Snapshot!$E$7:$E$38,MATCH(B40,S490_Snapshot!$A$7:$A$38,0)),"") | V40: =IF(T40="","",(J40-T40)*100) | W40: =IF(U40="","",H40-U40) | X40: =IFERROR(INDEX(S490_Snapshot!$C$7:$C$38,MATCH(B40,S490_Snapshot!$A$7:$A$38,0)),"") | Y40: =IF(OR(X40="",NOT(ISNUMBER(E40))),"",(E40-X40)*100)
A41: 19Y | B41: =IF(MONTH(((EDATE($B$4,228))+IF(WEEKDAY((EDATE($B$4,228)),2)=6,2,IF(WEEKDAY((EDATE($B$4,228)),2)=7,1,0))))<>MONTH((EDATE($B$4,228))),((EDATE($B$4,228))-IF(WEEKDAY((EDATE($B$4,228)),2)=6,1,IF(WEEKDAY((EDATE($B$4,228)),2)=7,2,0))),((EDATE($B$4,228))+IF(WEEKDAY((EDATE($B$4,228)),2)=6,2,IF(WEEKDAY((EDATE($B$4,228)),2)=7,1,0)))) | C41: =(B41-VAL_DATE)/365 | D41: =(B41-$B$4)/360 | E41: =INDEX($Q$8:$Q$24,MATCH(19,$P$8:$P$24,1))+(INDEX($Q$8:$Q$24,MATCH(19,$P$8:$P$24,1)+1)-INDEX($Q$8:$Q$24,MATCH(19,$P$8:$P$24,1)))*(19-INDEX($P$8:$P$24,MATCH(19,$P$8:$P$24,1)))/(INDEX($P$8:$P$24,MATCH(19,$P$8:$P$24,1)+1)-INDEX($P$8:$P$24,MATCH(19,$P$8:$P$24,1))) | F41: =(B41-$B$40)/360 | G41: =SUM($I$8:I40) | H41: =H37*(H42/H37)^((C41-C37)/(C42-C37)) | I41: =F41*H41 | J41: =-LN(H41)/C41*100 | K41: =(H40/H41-1)/((B41-B40)/360)*100 | M41: =IF(L41="","",(J41-L41)*100) | N41: interp | S41: =(G41+F41*H41) | T41: =IFERROR(INDEX(S490_Snapshot!$D$7:$D$38,MATCH(B41,S490_Snapshot!$A$7:$A$38,0)),"") | U41: =IFERROR(INDEX(S490_Snapshot!$E$7:$E$38,MATCH(B41,S490_Snapshot!$A$7:$A$38,0)),"") | V41: =IF(T41="","",(J41-T41)*100) | W41: =IF(U41="","",H41-U41) | X41: =IFERROR(INDEX(S490_Snapshot!$C$7:$C$38,MATCH(B41,S490_Snapshot!$A$7:$A$38,0)),"") | Y41: =IF(OR(X41="",NOT(ISNUMBER(E41))),"",(E41-X41)*100)
A42: 20Y | B42: =IF(MONTH(((EDATE($B$4,240))+IF(WEEKDAY((EDATE($B$4,240)),2)=6,2,IF(WEEKDAY((EDATE($B$4,240)),2)=7,1,0))))<>MONTH((EDATE($B$4,240))),((EDATE($B$4,240))-IF(WEEKDAY((EDATE($B$4,240)),2)=6,1,IF(WEEKDAY((EDATE($B$4,240)),2)=7,2,0))),((EDATE($B$4,240))+IF(WEEKDAY((EDATE($B$4,240)),2)=6,2,IF(WEEKDAY((EDATE($B$4,240)),2)=7,1,0)))) | C42: =(B42-VAL_DATE)/365 | D42: =(B42-$B$4)/360 | E42: ='SOFR_OIS_Quotes'!$H32 | F42: =(B42-$B$41)/360 | G42: =SUM($I$8:I41) | H42: =Curve_Solver!$B$153 | I42: =F42*H42 | J42: =-LN(H42)/C42*100 | K42: =(H41/H42-1)/((B42-B41)/360)*100 | M42: =IF(L42="","",(J42-L42)*100) | N42: market | R42: =($D$4-(E42/100)*G42)/(1+(E42/100)*F42)-H42 | S42: =(G42+F42*H42) | T42: =IFERROR(INDEX(S490_Snapshot!$D$7:$D$38,MATCH(B42,S490_Snapshot!$A$7:$A$38,0)),"") | U42: =IFERROR(INDEX(S490_Snapshot!$E$7:$E$38,MATCH(B42,S490_Snapshot!$A$7:$A$38,0)),"") | V42: =IF(T42="","",(J42-T42)*100) | W42: =IF(U42="","",H42-U42) | X42: =IFERROR(INDEX(S490_Snapshot!$C$7:$C$38,MATCH(B42,S490_Snapshot!$A$7:$A$38,0)),"") | Y42: =IF(OR(X42="",NOT(ISNUMBER(E42))),"",(E42-X42)*100)
A43: 21Y | B43: =IF(MONTH(((EDATE($B$4,252))+IF(WEEKDAY((EDATE($B$4,252)),2)=6,2,IF(WEEKDAY((EDATE($B$4,252)),2)=7,1,0))))<>MONTH((EDATE($B$4,252))),((EDATE($B$4,252))-IF(WEEKDAY((EDATE($B$4,252)),2)=6,1,IF(WEEKDAY((EDATE($B$4,252)),2)=7,2,0))),((EDATE($B$4,252))+IF(WEEKDAY((EDATE($B$4,252)),2)=6,2,IF(WEEKDAY((EDATE($B$4,252)),2)=7,1,0)))) | C43: =(B43-VAL_DATE)/365 | D43: =(B43-$B$4)/360 | E43: =INDEX($Q$8:$Q$24,MATCH(21,$P$8:$P$24,1))+(INDEX($Q$8:$Q$24,MATCH(21,$P$8:$P$24,1)+1)-INDEX($Q$8:$Q$24,MATCH(21,$P$8:$P$24,1)))*(21-INDEX($P$8:$P$24,MATCH(21,$P$8:$P$24,1)))/(INDEX($P$8:$P$24,MATCH(21,$P$8:$P$24,1)+1)-INDEX($P$8:$P$24,MATCH(21,$P$8:$P$24,1))) | F43: =(B43-$B$42)/360 | G43: =SUM($I$8:I42) | H43: =H42*(H47/H42)^((C43-C42)/(C47-C42)) | I43: =F43*H43 | J43: =-LN(H43)/C43*100 | K43: =(H42/H43-1)/((B43-B42)/360)*100 | M43: =IF(L43="","",(J43-L43)*100) | N43: interp | S43: =(G43+F43*H43) | T43: =IFERROR(INDEX(S490_Snapshot!$D$7:$D$38,MATCH(B43,S490_Snapshot!$A$7:$A$38,0)),"") | U43: =IFERROR(INDEX(S490_Snapshot!$E$7:$E$38,MATCH(B43,S490_Snapshot!$A$7:$A$38,0)),"") | V43: =IF(T43="","",(J43-T43)*100) | W43: =IF(U43="","",H43-U43) | X43: =IFERROR(INDEX(S490_Snapshot!$C$7:$C$38,MATCH(B43,S490_Snapshot!$A$7:$A$38,0)),"") | Y43: =IF(OR(X43="",NOT(ISNUMBER(E43))),"",(E43-X43)*100)
A44: 22Y | B44: =IF(MONTH(((EDATE($B$4,264))+IF(WEEKDAY((EDATE($B$4,264)),2)=6,2,IF(WEEKDAY((EDATE($B$4,264)),2)=7,1,0))))<>MONTH((EDATE($B$4,264))),((EDATE($B$4,264))-IF(WEEKDAY((EDATE($B$4,264)),2)=6,1,IF(WEEKDAY((EDATE($B$4,264)),2)=7,2,0))),((EDATE($B$4,264))+IF(WEEKDAY((EDATE($B$4,264)),2)=6,2,IF(WEEKDAY((EDATE($B$4,264)),2)=7,1,0)))) | C44: =(B44-VAL_DATE)/365 | D44: =(B44-$B$4)/360 | E44: =INDEX($Q$8:$Q$24,MATCH(22,$P$8:$P$24,1))+(INDEX($Q$8:$Q$24,MATCH(22,$P$8:$P$24,1)+1)-INDEX($Q$8:$Q$24,MATCH(22,$P$8:$P$24,1)))*(22-INDEX($P$8:$P$24,MATCH(22,$P$8:$P$24,1)))/(INDEX($P$8:$P$24,MATCH(22,$P$8:$P$24,1)+1)-INDEX($P$8:$P$24,MATCH(22,$P$8:$P$24,1))) | F44: =(B44-$B$43)/360 | G44: =SUM($I$8:I43) | H44: =H42*(H47/H42)^((C44-C42)/(C47-C42)) | I44: =F44*H44 | J44: =-LN(H44)/C44*100 | K44: =(H43/H44-1)/((B44-B43)/360)*100 | M44: =IF(L44="","",(J44-L44)*100) | N44: interp | S44: =(G44+F44*H44) | T44: =IFERROR(INDEX(S490_Snapshot!$D$7:$D$38,MATCH(B44,S490_Snapshot!$A$7:$A$38,0)),"") | U44: =IFERROR(INDEX(S490_Snapshot!$E$7:$E$38,MATCH(B44,S490_Snapshot!$A$7:$A$38,0)),"") | V44: =IF(T44="","",(J44-T44)*100) | W44: =IF(U44="","",H44-U44) | X44: =IFERROR(INDEX(S490_Snapshot!$C$7:$C$38,MATCH(B44,S490_Snapshot!$A$7:$A$38,0)),"") | Y44: =IF(OR(X44="",NOT(ISNUMBER(E44))),"",(E44-X44)*100)
A45: 23Y | B45: =IF(MONTH(((EDATE($B$4,276))+IF(WEEKDAY((EDATE($B$4,276)),2)=6,2,IF(WEEKDAY((EDATE($B$4,276)),2)=7,1,0))))<>MONTH((EDATE($B$4,276))),((EDATE($B$4,276))-IF(WEEKDAY((EDATE($B$4,276)),2)=6,1,IF(WEEKDAY((EDATE($B$4,276)),2)=7,2,0))),((EDATE($B$4,276))+IF(WEEKDAY((EDATE($B$4,276)),2)=6,2,IF(WEEKDAY((EDATE($B$4,276)),2)=7,1,0)))) | C45: =(B45-VAL_DATE)/365 | D45: =(B45-$B$4)/360 | E45: =INDEX($Q$8:$Q$24,MATCH(23,$P$8:$P$24,1))+(INDEX($Q$8:$Q$24,MATCH(23,$P$8:$P$24,1)+1)-INDEX($Q$8:$Q$24,MATCH(23,$P$8:$P$24,1)))*(23-INDEX($P$8:$P$24,MATCH(23,$P$8:$P$24,1)))/(INDEX($P$8:$P$24,MATCH(23,$P$8:$P$24,1)+1)-INDEX($P$8:$P$24,MATCH(23,$P$8:$P$24,1))) | F45: =(B45-$B$44)/360 | G45: =SUM($I$8:I44) | H45: =H42*(H47/H42)^((C45-C42)/(C47-C42)) | I45: =F45*H45 | J45: =-LN(H45)/C45*100 | K45: =(H44/H45-1)/((B45-B44)/360)*100 | M45: =IF(L45="","",(J45-L45)*100) | N45: interp | S45: =(G45+F45*H45) | T45: =IFERROR(INDEX(S490_Snapshot!$D$7:$D$38,MATCH(B45,S490_Snapshot!$A$7:$A$38,0)),"") | U45: =IFERROR(INDEX(S490_Snapshot!$E$7:$E$38,MATCH(B45,S490_Snapshot!$A$7:$A$38,0)),"") | V45: =IF(T45="","",(J45-T45)*100) | W45: =IF(U45="","",H45-U45) | X45: =IFERROR(INDEX(S490_Snapshot!$C$7:$C$38,MATCH(B45,S490_Snapshot!$A$7:$A$38,0)),"") | Y45: =IF(OR(X45="",NOT(ISNUMBER(E45))),"",(E45-X45)*100)
A46: 24Y | B46: =IF(MONTH(((EDATE($B$4,288))+IF(WEEKDAY((EDATE($B$4,288)),2)=6,2,IF(WEEKDAY((EDATE($B$4,288)),2)=7,1,0))))<>MONTH((EDATE($B$4,288))),((EDATE($B$4,288))-IF(WEEKDAY((EDATE($B$4,288)),2)=6,1,IF(WEEKDAY((EDATE($B$4,288)),2)=7,2,0))),((EDATE($B$4,288))+IF(WEEKDAY((EDATE($B$4,288)),2)=6,2,IF(WEEKDAY((EDATE($B$4,288)),2)=7,1,0)))) | C46: =(B46-VAL_DATE)/365 | D46: =(B46-$B$4)/360 | E46: =INDEX($Q$8:$Q$24,MATCH(24,$P$8:$P$24,1))+(INDEX($Q$8:$Q$24,MATCH(24,$P$8:$P$24,1)+1)-INDEX($Q$8:$Q$24,MATCH(24,$P$8:$P$24,1)))*(24-INDEX($P$8:$P$24,MATCH(24,$P$8:$P$24,1)))/(INDEX($P$8:$P$24,MATCH(24,$P$8:$P$24,1)+1)-INDEX($P$8:$P$24,MATCH(24,$P$8:$P$24,1))) | F46: =(B46-$B$45)/360 | G46: =SUM($I$8:I45) | H46: =H42*(H47/H42)^((C46-C42)/(C47-C42)) | I46: =F46*H46 | J46: =-LN(H46)/C46*100 | K46: =(H45/H46-1)/((B46-B45)/360)*100 | M46: =IF(L46="","",(J46-L46)*100) | N46: interp | S46: =(G46+F46*H46) | T46: =IFERROR(INDEX(S490_Snapshot!$D$7:$D$38,MATCH(B46,S490_Snapshot!$A$7:$A$38,0)),"") | U46: =IFERROR(INDEX(S490_Snapshot!$E$7:$E$38,MATCH(B46,S490_Snapshot!$A$7:$A$38,0)),"") | V46: =IF(T46="","",(J46-T46)*100) | W46: =IF(U46="","",H46-U46) | X46: =IFERROR(INDEX(S490_Snapshot!$C$7:$C$38,MATCH(B46,S490_Snapshot!$A$7:$A$38,0)),"") | Y46: =IF(OR(X46="",NOT(ISNUMBER(E46))),"",(E46-X46)*100)
A47: 25Y | B47: =IF(MONTH(((EDATE($B$4,300))+IF(WEEKDAY((EDATE($B$4,300)),2)=6,2,IF(WEEKDAY((EDATE($B$4,300)),2)=7,1,0))))<>MONTH((EDATE($B$4,300))),((EDATE($B$4,300))-IF(WEEKDAY((EDATE($B$4,300)),2)=6,1,IF(WEEKDAY((EDATE($B$4,300)),2)=7,2,0))),((EDATE($B$4,300))+IF(WEEKDAY((EDATE($B$4,300)),2)=6,2,IF(WEEKDAY((EDATE($B$4,300)),2)=7,1,0)))) | C47: =(B47-VAL_DATE)/365 | D47: =(B47-$B$4)/360 | E47: ='SOFR_OIS_Quotes'!$H33 | F47: =(B47-$B$46)/360 | G47: =SUM($I$8:I46) | H47: =Curve_Solver!$B$203 | I47: =F47*H47 | J47: =-LN(H47)/C47*100 | K47: =(H46/H47-1)/((B47-B46)/360)*100 | M47: =IF(L47="","",(J47-L47)*100) | N47: market | R47: =($D$4-(E47/100)*G47)/(1+(E47/100)*F47)-H47 | S47: =(G47+F47*H47) | T47: =IFERROR(INDEX(S490_Snapshot!$D$7:$D$38,MATCH(B47,S490_Snapshot!$A$7:$A$38,0)),"") | U47: =IFERROR(INDEX(S490_Snapshot!$E$7:$E$38,MATCH(B47,S490_Snapshot!$A$7:$A$38,0)),"") | V47: =IF(T47="","",(J47-T47)*100) | W47: =IF(U47="","",H47-U47) | X47: =IFERROR(INDEX(S490_Snapshot!$C$7:$C$38,MATCH(B47,S490_Snapshot!$A$7:$A$38,0)),"") | Y47: =IF(OR(X47="",NOT(ISNUMBER(E47))),"",(E47-X47)*100)
A48: 26Y | B48: =IF(MONTH(((EDATE($B$4,312))+IF(WEEKDAY((EDATE($B$4,312)),2)=6,2,IF(WEEKDAY((EDATE($B$4,312)),2)=7,1,0))))<>MONTH((EDATE($B$4,312))),((EDATE($B$4,312))-IF(WEEKDAY((EDATE($B$4,312)),2)=6,1,IF(WEEKDAY((EDATE($B$4,312)),2)=7,2,0))),((EDATE($B$4,312))+IF(WEEKDAY((EDATE($B$4,312)),2)=6,2,IF(WEEKDAY((EDATE($B$4,312)),2)=7,1,0)))) | C48: =(B48-VAL_DATE)/365 | D48: =(B48-$B$4)/360 | E48: =INDEX($Q$8:$Q$24,MATCH(26,$P$8:$P$24,1))+(INDEX($Q$8:$Q$24,MATCH(26,$P$8:$P$24,1)+1)-INDEX($Q$8:$Q$24,MATCH(26,$P$8:$P$24,1)))*(26-INDEX($P$8:$P$24,MATCH(26,$P$8:$P$24,1)))/(INDEX($P$8:$P$24,MATCH(26,$P$8:$P$24,1)+1)-INDEX($P$8:$P$24,MATCH(26,$P$8:$P$24,1))) | F48: =(B48-$B$47)/360 | G48: =SUM($I$8:I47) | H48: =H47*(H52/H47)^((C48-C47)/(C52-C47)) | I48: =F48*H48 | J48: =-LN(H48)/C48*100 | K48: =(H47/H48-1)/((B48-B47)/360)*100 | M48: =IF(L48="","",(J48-L48)*100) | N48: interp | S48: =(G48+F48*H48) | T48: =IFERROR(INDEX(S490_Snapshot!$D$7:$D$38,MATCH(B48,S490_Snapshot!$A$7:$A$38,0)),"") | U48: =IFERROR(INDEX(S490_Snapshot!$E$7:$E$38,MATCH(B48,S490_Snapshot!$A$7:$A$38,0)),"") | V48: =IF(T48="","",(J48-T48)*100) | W48: =IF(U48="","",H48-U48) | X48: =IFERROR(INDEX(S490_Snapshot!$C$7:$C$38,MATCH(B48,S490_Snapshot!$A$7:$A$38,0)),"") | Y48: =IF(OR(X48="",NOT(ISNUMBER(E48))),"",(E48-X48)*100)
A49: 27Y | B49: =IF(MONTH(((EDATE($B$4,324))+IF(WEEKDAY((EDATE($B$4,324)),2)=6,2,IF(WEEKDAY((EDATE($B$4,324)),2)=7,1,0))))<>MONTH((EDATE($B$4,324))),((EDATE($B$4,324))-IF(WEEKDAY((EDATE($B$4,324)),2)=6,1,IF(WEEKDAY((EDATE($B$4,324)),2)=7,2,0))),((EDATE($B$4,324))+IF(WEEKDAY((EDATE($B$4,324)),2)=6,2,IF(WEEKDAY((EDATE($B$4,324)),2)=7,1,0)))) | C49: =(B49-VAL_DATE)/365 | D49: =(B49-$B$4)/360 | E49: =INDEX($Q$8:$Q$24,MATCH(27,$P$8:$P$24,1))+(INDEX($Q$8:$Q$24,MATCH(27,$P$8:$P$24,1)+1)-INDEX($Q$8:$Q$24,MATCH(27,$P$8:$P$24,1)))*(27-INDEX($P$8:$P$24,MATCH(27,$P$8:$P$24,1)))/(INDEX($P$8:$P$24,MATCH(27,$P$8:$P$24,1)+1)-INDEX($P$8:$P$24,MATCH(27,$P$8:$P$24,1))) | F49: =(B49-$B$48)/360 | G49: =SUM($I$8:I48) | H49: =H47*(H52/H47)^((C49-C47)/(C52-C47)) | I49: =F49*H49 | J49: =-LN(H49)/C49*100 | K49: =(H48/H49-1)/((B49-B48)/360)*100 | M49: =IF(L49="","",(J49-L49)*100) | N49: interp | S49: =(G49+F49*H49) | T49: =IFERROR(INDEX(S490_Snapshot!$D$7:$D$38,MATCH(B49,S490_Snapshot!$A$7:$A$38,0)),"") | U49: =IFERROR(INDEX(S490_Snapshot!$E$7:$E$38,MATCH(B49,S490_Snapshot!$A$7:$A$38,0)),"") | V49: =IF(T49="","",(J49-T49)*100) | W49: =IF(U49="","",H49-U49) | X49: =IFERROR(INDEX(S490_Snapshot!$C$7:$C$38,MATCH(B49,S490_Snapshot!$A$7:$A$38,0)),"") | Y49: =IF(OR(X49="",NOT(ISNUMBER(E49))),"",(E49-X49)*100)
A50: 28Y | B50: =IF(MONTH(((EDATE($B$4,336))+IF(WEEKDAY((EDATE($B$4,336)),2)=6,2,IF(WEEKDAY((EDATE($B$4,336)),2)=7,1,0))))<>MONTH((EDATE($B$4,336))),((EDATE($B$4,336))-IF(WEEKDAY((EDATE($B$4,336)),2)=6,1,IF(WEEKDAY((EDATE($B$4,336)),2)=7,2,0))),((EDATE($B$4,336))+IF(WEEKDAY((EDATE($B$4,336)),2)=6,2,IF(WEEKDAY((EDATE($B$4,336)),2)=7,1,0)))) | C50: =(B50-VAL_DATE)/365 | D50: =(B50-$B$4)/360 | E50: =INDEX($Q$8:$Q$24,MATCH(28,$P$8:$P$24,1))+(INDEX($Q$8:$Q$24,MATCH(28,$P$8:$P$24,1)+1)-INDEX($Q$8:$Q$24,MATCH(28,$P$8:$P$24,1)))*(28-INDEX($P$8:$P$24,MATCH(28,$P$8:$P$24,1)))/(INDEX($P$8:$P$24,MATCH(28,$P$8:$P$24,1)+1)-INDEX($P$8:$P$24,MATCH(28,$P$8:$P$24,1))) | F50: =(B50-$B$49)/360 | G50: =SUM($I$8:I49) | H50: =H47*(H52/H47)^((C50-C47)/(C52-C47)) | I50: =F50*H50 | J50: =-LN(H50)/C50*100 | K50: =(H49/H50-1)/((B50-B49)/360)*100 | M50: =IF(L50="","",(J50-L50)*100) | N50: interp | S50: =(G50+F50*H50) | T50: =IFERROR(INDEX(S490_Snapshot!$D$7:$D$38,MATCH(B50,S490_Snapshot!$A$7:$A$38,0)),"") | U50: =IFERROR(INDEX(S490_Snapshot!$E$7:$E$38,MATCH(B50,S490_Snapshot!$A$7:$A$38,0)),"") | V50: =IF(T50="","",(J50-T50)*100) | W50: =IF(U50="","",H50-U50) | X50: =IFERROR(INDEX(S490_Snapshot!$C$7:$C$38,MATCH(B50,S490_Snapshot!$A$7:$A$38,0)),"") | Y50: =IF(OR(X50="",NOT(ISNUMBER(E50))),"",(E50-X50)*100)
A51: 29Y | B51: =IF(MONTH(((EDATE($B$4,348))+IF(WEEKDAY((EDATE($B$4,348)),2)=6,2,IF(WEEKDAY((EDATE($B$4,348)),2)=7,1,0))))<>MONTH((EDATE($B$4,348))),((EDATE($B$4,348))-IF(WEEKDAY((EDATE($B$4,348)),2)=6,1,IF(WEEKDAY((EDATE($B$4,348)),2)=7,2,0))),((EDATE($B$4,348))+IF(WEEKDAY((EDATE($B$4,348)),2)=6,2,IF(WEEKDAY((EDATE($B$4,348)),2)=7,1,0)))) | C51: =(B51-VAL_DATE)/365 | D51: =(B51-$B$4)/360 | E51: =INDEX($Q$8:$Q$24,MATCH(29,$P$8:$P$24,1))+(INDEX($Q$8:$Q$24,MATCH(29,$P$8:$P$24,1)+1)-INDEX($Q$8:$Q$24,MATCH(29,$P$8:$P$24,1)))*(29-INDEX($P$8:$P$24,MATCH(29,$P$8:$P$24,1)))/(INDEX($P$8:$P$24,MATCH(29,$P$8:$P$24,1)+1)-INDEX($P$8:$P$24,MATCH(29,$P$8:$P$24,1))) | F51: =(B51-$B$50)/360 | G51: =SUM($I$8:I50) | H51: =H47*(H52/H47)^((C51-C47)/(C52-C47)) | I51: =F51*H51 | J51: =-LN(H51)/C51*100 | K51: =(H50/H51-1)/((B51-B50)/360)*100 | M51: =IF(L51="","",(J51-L51)*100) | N51: interp | S51: =(G51+F51*H51) | T51: =IFERROR(INDEX(S490_Snapshot!$D$7:$D$38,MATCH(B51,S490_Snapshot!$A$7:$A$38,0)),"") | U51: =IFERROR(INDEX(S490_Snapshot!$E$7:$E$38,MATCH(B51,S490_Snapshot!$A$7:$A$38,0)),"") | V51: =IF(T51="","",(J51-T51)*100) | W51: =IF(U51="","",H51-U51) | X51: =IFERROR(INDEX(S490_Snapshot!$C$7:$C$38,MATCH(B51,S490_Snapshot!$A$7:$A$38,0)),"") | Y51: =IF(OR(X51="",NOT(ISNUMBER(E51))),"",(E51-X51)*100)
A52: 30Y | B52: =IF(MONTH(((EDATE($B$4,360))+IF(WEEKDAY((EDATE($B$4,360)),2)=6,2,IF(WEEKDAY((EDATE($B$4,360)),2)=7,1,0))))<>MONTH((EDATE($B$4,360))),((EDATE($B$4,360))-IF(WEEKDAY((EDATE($B$4,360)),2)=6,1,IF(WEEKDAY((EDATE($B$4,360)),2)=7,2,0))),((EDATE($B$4,360))+IF(WEEKDAY((EDATE($B$4,360)),2)=6,2,IF(WEEKDAY((EDATE($B$4,360)),2)=7,1,0)))) | C52: =(B52-VAL_DATE)/365 | D52: =(B52-$B$4)/360 | E52: ='SOFR_OIS_Quotes'!$H34 | F52: =(B52-$B$51)/360 | G52: =SUM($I$8:I51) | H52: =Curve_Solver!$B$253 | I52: =F52*H52 | J52: =-LN(H52)/C52*100 | K52: =(H51/H52-1)/((B52-B51)/360)*100 | M52: =IF(L52="","",(J52-L52)*100) | N52: market | R52: =($D$4-(E52/100)*G52)/(1+(E52/100)*F52)-H52 | S52: =(G52+F52*H52) | T52: =IFERROR(INDEX(S490_Snapshot!$D$7:$D$38,MATCH(B52,S490_Snapshot!$A$7:$A$38,0)),"") | U52: =IFERROR(INDEX(S490_Snapshot!$E$7:$E$38,MATCH(B52,S490_Snapshot!$A$7:$A$38,0)),"") | V52: =IF(T52="","",(J52-T52)*100) | W52: =IF(U52="","",H52-U52) | X52: =IFERROR(INDEX(S490_Snapshot!$C$7:$C$38,MATCH(B52,S490_Snapshot!$A$7:$A$38,0)),"") | Y52: =IF(OR(X52="",NOT(ISNUMBER(E52))),"",(E52-X52)*100)
A53: 31Y | B53: =IF(MONTH(((EDATE($B$4,372))+IF(WEEKDAY((EDATE($B$4,372)),2)=6,2,IF(WEEKDAY((EDATE($B$4,372)),2)=7,1,0))))<>MONTH((EDATE($B$4,372))),((EDATE($B$4,372))-IF(WEEKDAY((EDATE($B$4,372)),2)=6,1,IF(WEEKDAY((EDATE($B$4,372)),2)=7,2,0))),((EDATE($B$4,372))+IF(WEEKDAY((EDATE($B$4,372)),2)=6,2,IF(WEEKDAY((EDATE($B$4,372)),2)=7,1,0)))) | C53: =(B53-VAL_DATE)/365 | D53: =(B53-$B$4)/360 | E53: =INDEX($Q$8:$Q$24,MATCH(31,$P$8:$P$24,1))+(INDEX($Q$8:$Q$24,MATCH(31,$P$8:$P$24,1)+1)-INDEX($Q$8:$Q$24,MATCH(31,$P$8:$P$24,1)))*(31-INDEX($P$8:$P$24,MATCH(31,$P$8:$P$24,1)))/(INDEX($P$8:$P$24,MATCH(31,$P$8:$P$24,1)+1)-INDEX($P$8:$P$24,MATCH(31,$P$8:$P$24,1))) | F53: =(B53-$B$52)/360 | G53: =SUM($I$8:I52) | H53: =H52*(H62/H52)^((C53-C52)/(C62-C52)) | I53: =F53*H53 | J53: =-LN(H53)/C53*100 | K53: =(H52/H53-1)/((B53-B52)/360)*100 | M53: =IF(L53="","",(J53-L53)*100) | N53: interp | S53: =(G53+F53*H53) | T53: =IFERROR(INDEX(S490_Snapshot!$D$7:$D$38,MATCH(B53,S490_Snapshot!$A$7:$A$38,0)),"") | U53: =IFERROR(INDEX(S490_Snapshot!$E$7:$E$38,MATCH(B53,S490_Snapshot!$A$7:$A$38,0)),"") | V53: =IF(T53="","",(J53-T53)*100) | W53: =IF(U53="","",H53-U53) | X53: =IFERROR(INDEX(S490_Snapshot!$C$7:$C$38,MATCH(B53,S490_Snapshot!$A$7:$A$38,0)),"") | Y53: =IF(OR(X53="",NOT(ISNUMBER(E53))),"",(E53-X53)*100)
A54: 32Y | B54: =IF(MONTH(((EDATE($B$4,384))+IF(WEEKDAY((EDATE($B$4,384)),2)=6,2,IF(WEEKDAY((EDATE($B$4,384)),2)=7,1,0))))<>MONTH((EDATE($B$4,384))),((EDATE($B$4,384))-IF(WEEKDAY((EDATE($B$4,384)),2)=6,1,IF(WEEKDAY((EDATE($B$4,384)),2)=7,2,0))),((EDATE($B$4,384))+IF(WEEKDAY((EDATE($B$4,384)),2)=6,2,IF(WEEKDAY((EDATE($B$4,384)),2)=7,1,0)))) | C54: =(B54-VAL_DATE)/365 | D54: =(B54-$B$4)/360 | E54: =INDEX($Q$8:$Q$24,MATCH(32,$P$8:$P$24,1))+(INDEX($Q$8:$Q$24,MATCH(32,$P$8:$P$24,1)+1)-INDEX($Q$8:$Q$24,MATCH(32,$P$8:$P$24,1)))*(32-INDEX($P$8:$P$24,MATCH(32,$P$8:$P$24,1)))/(INDEX($P$8:$P$24,MATCH(32,$P$8:$P$24,1)+1)-INDEX($P$8:$P$24,MATCH(32,$P$8:$P$24,1))) | F54: =(B54-$B$53)/360 | G54: =SUM($I$8:I53) | H54: =H52*(H62/H52)^((C54-C52)/(C62-C52)) | I54: =F54*H54 | J54: =-LN(H54)/C54*100 | K54: =(H53/H54-1)/((B54-B53)/360)*100 | M54: =IF(L54="","",(J54-L54)*100) | N54: interp | S54: =(G54+F54*H54) | T54: =IFERROR(INDEX(S490_Snapshot!$D$7:$D$38,MATCH(B54,S490_Snapshot!$A$7:$A$38,0)),"") | U54: =IFERROR(INDEX(S490_Snapshot!$E$7:$E$38,MATCH(B54,S490_Snapshot!$A$7:$A$38,0)),"") | V54: =IF(T54="","",(J54-T54)*100) | W54: =IF(U54="","",H54-U54) | X54: =IFERROR(INDEX(S490_Snapshot!$C$7:$C$38,MATCH(B54,S490_Snapshot!$A$7:$A$38,0)),"") | Y54: =IF(OR(X54="",NOT(ISNUMBER(E54))),"",(E54-X54)*100)
A55: 33Y | B55: =IF(MONTH(((EDATE($B$4,396))+IF(WEEKDAY((EDATE($B$4,396)),2)=6,2,IF(WEEKDAY((EDATE($B$4,396)),2)=7,1,0))))<>MONTH((EDATE($B$4,396))),((EDATE($B$4,396))-IF(WEEKDAY((EDATE($B$4,396)),2)=6,1,IF(WEEKDAY((EDATE($B$4,396)),2)=7,2,0))),((EDATE($B$4,396))+IF(WEEKDAY((EDATE($B$4,396)),2)=6,2,IF(WEEKDAY((EDATE($B$4,396)),2)=7,1,0)))) | C55: =(B55-VAL_DATE)/365 | D55: =(B55-$B$4)/360 | E55: =INDEX($Q$8:$Q$24,MATCH(33,$P$8:$P$24,1))+(INDEX($Q$8:$Q$24,MATCH(33,$P$8:$P$24,1)+1)-INDEX($Q$8:$Q$24,MATCH(33,$P$8:$P$24,1)))*(33-INDEX($P$8:$P$24,MATCH(33,$P$8:$P$24,1)))/(INDEX($P$8:$P$24,MATCH(33,$P$8:$P$24,1)+1)-INDEX($P$8:$P$24,MATCH(33,$P$8:$P$24,1))) | F55: =(B55-$B$54)/360 | G55: =SUM($I$8:I54) | H55: =H52*(H62/H52)^((C55-C52)/(C62-C52)) | I55: =F55*H55 | J55: =-LN(H55)/C55*100 | K55: =(H54/H55-1)/((B55-B54)/360)*100 | M55: =IF(L55="","",(J55-L55)*100) | N55: interp | S55: =(G55+F55*H55) | T55: =IFERROR(INDEX(S490_Snapshot!$D$7:$D$38,MATCH(B55,S490_Snapshot!$A$7:$A$38,0)),"") | U55: =IFERROR(INDEX(S490_Snapshot!$E$7:$E$38,MATCH(B55,S490_Snapshot!$A$7:$A$38,0)),"") | V55: =IF(T55="","",(J55-T55)*100) | W55: =IF(U55="","",H55-U55) | X55: =IFERROR(INDEX(S490_Snapshot!$C$7:$C$38,MATCH(B55,S490_Snapshot!$A$7:$A$38,0)),"") | Y55: =IF(OR(X55="",NOT(ISNUMBER(E55))),"",(E55-X55)*100)
A56: 34Y | B56: =IF(MONTH(((EDATE($B$4,408))+IF(WEEKDAY((EDATE($B$4,408)),2)=6,2,IF(WEEKDAY((EDATE($B$4,408)),2)=7,1,0))))<>MONTH((EDATE($B$4,408))),((EDATE($B$4,408))-IF(WEEKDAY((EDATE($B$4,408)),2)=6,1,IF(WEEKDAY((EDATE($B$4,408)),2)=7,2,0))),((EDATE($B$4,408))+IF(WEEKDAY((EDATE($B$4,408)),2)=6,2,IF(WEEKDAY((EDATE($B$4,408)),2)=7,1,0)))) | C56: =(B56-VAL_DATE)/365 | D56: =(B56-$B$4)/360 | E56: =INDEX($Q$8:$Q$24,MATCH(34,$P$8:$P$24,1))+(INDEX($Q$8:$Q$24,MATCH(34,$P$8:$P$24,1)+1)-INDEX($Q$8:$Q$24,MATCH(34,$P$8:$P$24,1)))*(34-INDEX($P$8:$P$24,MATCH(34,$P$8:$P$24,1)))/(INDEX($P$8:$P$24,MATCH(34,$P$8:$P$24,1)+1)-INDEX($P$8:$P$24,MATCH(34,$P$8:$P$24,1))) | F56: =(B56-$B$55)/360 | G56: =SUM($I$8:I55) | H56: =H52*(H62/H52)^((C56-C52)/(C62-C52)) | I56: =F56*H56 | J56: =-LN(H56)/C56*100 | K56: =(H55/H56-1)/((B56-B55)/360)*100 | M56: =IF(L56="","",(J56-L56)*100) | N56: interp | S56: =(G56+F56*H56) | T56: =IFERROR(INDEX(S490_Snapshot!$D$7:$D$38,MATCH(B56,S490_Snapshot!$A$7:$A$38,0)),"") | U56: =IFERROR(INDEX(S490_Snapshot!$E$7:$E$38,MATCH(B56,S490_Snapshot!$A$7:$A$38,0)),"") | V56: =IF(T56="","",(J56-T56)*100) | W56: =IF(U56="","",H56-U56) | X56: =IFERROR(INDEX(S490_Snapshot!$C$7:$C$38,MATCH(B56,S490_Snapshot!$A$7:$A$38,0)),"") | Y56: =IF(OR(X56="",NOT(ISNUMBER(E56))),"",(E56-X56)*100)
A57: 35Y | B57: =IF(MONTH(((EDATE($B$4,420))+IF(WEEKDAY((EDATE($B$4,420)),2)=6,2,IF(WEEKDAY((EDATE($B$4,420)),2)=7,1,0))))<>MONTH((EDATE($B$4,420))),((EDATE($B$4,420))-IF(WEEKDAY((EDATE($B$4,420)),2)=6,1,IF(WEEKDAY((EDATE($B$4,420)),2)=7,2,0))),((EDATE($B$4,420))+IF(WEEKDAY((EDATE($B$4,420)),2)=6,2,IF(WEEKDAY((EDATE($B$4,420)),2)=7,1,0)))) | C57: =(B57-VAL_DATE)/365 | D57: =(B57-$B$4)/360 | E57: =INDEX($Q$8:$Q$24,MATCH(35,$P$8:$P$24,1))+(INDEX($Q$8:$Q$24,MATCH(35,$P$8:$P$24,1)+1)-INDEX($Q$8:$Q$24,MATCH(35,$P$8:$P$24,1)))*(35-INDEX($P$8:$P$24,MATCH(35,$P$8:$P$24,1)))/(INDEX($P$8:$P$24,MATCH(35,$P$8:$P$24,1)+1)-INDEX($P$8:$P$24,MATCH(35,$P$8:$P$24,1))) | F57: =(B57-$B$56)/360 | G57: =SUM($I$8:I56) | H57: =H52*(H62/H52)^((C57-C52)/(C62-C52)) | I57: =F57*H57 | J57: =-LN(H57)/C57*100 | K57: =(H56/H57-1)/((B57-B56)/360)*100 | M57: =IF(L57="","",(J57-L57)*100) | N57: interp | S57: =(G57+F57*H57) | T57: =IFERROR(INDEX(S490_Snapshot!$D$7:$D$38,MATCH(B57,S490_Snapshot!$A$7:$A$38,0)),"") | U57: =IFERROR(INDEX(S490_Snapshot!$E$7:$E$38,MATCH(B57,S490_Snapshot!$A$7:$A$38,0)),"") | V57: =IF(T57="","",(J57-T57)*100) | W57: =IF(U57="","",H57-U57) | X57: =IFERROR(INDEX(S490_Snapshot!$C$7:$C$38,MATCH(B57,S490_Snapshot!$A$7:$A$38,0)),"") | Y57: =IF(OR(X57="",NOT(ISNUMBER(E57))),"",(E57-X57)*100)
A58: 36Y | B58: =IF(MONTH(((EDATE($B$4,432))+IF(WEEKDAY((EDATE($B$4,432)),2)=6,2,IF(WEEKDAY((EDATE($B$4,432)),2)=7,1,0))))<>MONTH((EDATE($B$4,432))),((EDATE($B$4,432))-IF(WEEKDAY((EDATE($B$4,432)),2)=6,1,IF(WEEKDAY((EDATE($B$4,432)),2)=7,2,0))),((EDATE($B$4,432))+IF(WEEKDAY((EDATE($B$4,432)),2)=6,2,IF(WEEKDAY((EDATE($B$4,432)),2)=7,1,0)))) | C58: =(B58-VAL_DATE)/365 | D58: =(B58-$B$4)/360 | E58: =INDEX($Q$8:$Q$24,MATCH(36,$P$8:$P$24,1))+(INDEX($Q$8:$Q$24,MATCH(36,$P$8:$P$24,1)+1)-INDEX($Q$8:$Q$24,MATCH(36,$P$8:$P$24,1)))*(36-INDEX($P$8:$P$24,MATCH(36,$P$8:$P$24,1)))/(INDEX($P$8:$P$24,MATCH(36,$P$8:$P$24,1)+1)-INDEX($P$8:$P$24,MATCH(36,$P$8:$P$24,1))) | F58: =(B58-$B$57)/360 | G58: =SUM($I$8:I57) | H58: =H52*(H62/H52)^((C58-C52)/(C62-C52)) | I58: =F58*H58 | J58: =-LN(H58)/C58*100 | K58: =(H57/H58-1)/((B58-B57)/360)*100 | M58: =IF(L58="","",(J58-L58)*100) | N58: interp | S58: =(G58+F58*H58) | T58: =IFERROR(INDEX(S490_Snapshot!$D$7:$D$38,MATCH(B58,S490_Snapshot!$A$7:$A$38,0)),"") | U58: =IFERROR(INDEX(S490_Snapshot!$E$7:$E$38,MATCH(B58,S490_Snapshot!$A$7:$A$38,0)),"") | V58: =IF(T58="","",(J58-T58)*100) | W58: =IF(U58="","",H58-U58) | X58: =IFERROR(INDEX(S490_Snapshot!$C$7:$C$38,MATCH(B58,S490_Snapshot!$A$7:$A$38,0)),"") | Y58: =IF(OR(X58="",NOT(ISNUMBER(E58))),"",(E58-X58)*100)
A59: 37Y | B59: =IF(MONTH(((EDATE($B$4,444))+IF(WEEKDAY((EDATE($B$4,444)),2)=6,2,IF(WEEKDAY((EDATE($B$4,444)),2)=7,1,0))))<>MONTH((EDATE($B$4,444))),((EDATE($B$4,444))-IF(WEEKDAY((EDATE($B$4,444)),2)=6,1,IF(WEEKDAY((EDATE($B$4,444)),2)=7,2,0))),((EDATE($B$4,444))+IF(WEEKDAY((EDATE($B$4,444)),2)=6,2,IF(WEEKDAY((EDATE($B$4,444)),2)=7,1,0)))) | C59: =(B59-VAL_DATE)/365 | D59: =(B59-$B$4)/360 | E59: =INDEX($Q$8:$Q$24,MATCH(37,$P$8:$P$24,1))+(INDEX($Q$8:$Q$24,MATCH(37,$P$8:$P$24,1)+1)-INDEX($Q$8:$Q$24,MATCH(37,$P$8:$P$24,1)))*(37-INDEX($P$8:$P$24,MATCH(37,$P$8:$P$24,1)))/(INDEX($P$8:$P$24,MATCH(37,$P$8:$P$24,1)+1)-INDEX($P$8:$P$24,MATCH(37,$P$8:$P$24,1))) | F59: =(B59-$B$58)/360 | G59: =SUM($I$8:I58) | H59: =H52*(H62/H52)^((C59-C52)/(C62-C52)) | I59: =F59*H59 | J59: =-LN(H59)/C59*100 | K59: =(H58/H59-1)/((B59-B58)/360)*100 | M59: =IF(L59="","",(J59-L59)*100) | N59: interp | S59: =(G59+F59*H59) | T59: =IFERROR(INDEX(S490_Snapshot!$D$7:$D$38,MATCH(B59,S490_Snapshot!$A$7:$A$38,0)),"") | U59: =IFERROR(INDEX(S490_Snapshot!$E$7:$E$38,MATCH(B59,S490_Snapshot!$A$7:$A$38,0)),"") | V59: =IF(T59="","",(J59-T59)*100) | W59: =IF(U59="","",H59-U59) | X59: =IFERROR(INDEX(S490_Snapshot!$C$7:$C$38,MATCH(B59,S490_Snapshot!$A$7:$A$38,0)),"") | Y59: =IF(OR(X59="",NOT(ISNUMBER(E59))),"",(E59-X59)*100)
A60: 38Y | B60: =IF(MONTH(((EDATE($B$4,456))+IF(WEEKDAY((EDATE($B$4,456)),2)=6,2,IF(WEEKDAY((EDATE($B$4,456)),2)=7,1,0))))<>MONTH((EDATE($B$4,456))),((EDATE($B$4,456))-IF(WEEKDAY((EDATE($B$4,456)),2)=6,1,IF(WEEKDAY((EDATE($B$4,456)),2)=7,2,0))),((EDATE($B$4,456))+IF(WEEKDAY((EDATE($B$4,456)),2)=6,2,IF(WEEKDAY((EDATE($B$4,456)),2)=7,1,0)))) | C60: =(B60-VAL_DATE)/365 | D60: =(B60-$B$4)/360 | E60: =INDEX($Q$8:$Q$24,MATCH(38,$P$8:$P$24,1))+(INDEX($Q$8:$Q$24,MATCH(38,$P$8:$P$24,1)+1)-INDEX($Q$8:$Q$24,MATCH(38,$P$8:$P$24,1)))*(38-INDEX($P$8:$P$24,MATCH(38,$P$8:$P$24,1)))/(INDEX($P$8:$P$24,MATCH(38,$P$8:$P$24,1)+1)-INDEX($P$8:$P$24,MATCH(38,$P$8:$P$24,1))) | F60: =(B60-$B$59)/360 | G60: =SUM($I$8:I59) | H60: =H52*(H62/H52)^((C60-C52)/(C62-C52)) | I60: =F60*H60 | J60: =-LN(H60)/C60*100 | K60: =(H59/H60-1)/((B60-B59)/360)*100 | M60: =IF(L60="","",(J60-L60)*100) | N60: interp | S60: =(G60+F60*H60) | T60: =IFERROR(INDEX(S490_Snapshot!$D$7:$D$38,MATCH(B60,S490_Snapshot!$A$7:$A$38,0)),"") | U60: =IFERROR(INDEX(S490_Snapshot!$E$7:$E$38,MATCH(B60,S490_Snapshot!$A$7:$A$38,0)),"") | V60: =IF(T60="","",(J60-T60)*100) | W60: =IF(U60="","",H60-U60) | X60: =IFERROR(INDEX(S490_Snapshot!$C$7:$C$38,MATCH(B60,S490_Snapshot!$A$7:$A$38,0)),"") | Y60: =IF(OR(X60="",NOT(ISNUMBER(E60))),"",(E60-X60)*100)
A61: 39Y | B61: =IF(MONTH(((EDATE($B$4,468))+IF(WEEKDAY((EDATE($B$4,468)),2)=6,2,IF(WEEKDAY((EDATE($B$4,468)),2)=7,1,0))))<>MONTH((EDATE($B$4,468))),((EDATE($B$4,468))-IF(WEEKDAY((EDATE($B$4,468)),2)=6,1,IF(WEEKDAY((EDATE($B$4,468)),2)=7,2,0))),((EDATE($B$4,468))+IF(WEEKDAY((EDATE($B$4,468)),2)=6,2,IF(WEEKDAY((EDATE($B$4,468)),2)=7,1,0)))) | C61: =(B61-VAL_DATE)/365 | D61: =(B61-$B$4)/360 | E61: =INDEX($Q$8:$Q$24,MATCH(39,$P$8:$P$24,1))+(INDEX($Q$8:$Q$24,MATCH(39,$P$8:$P$24,1)+1)-INDEX($Q$8:$Q$24,MATCH(39,$P$8:$P$24,1)))*(39-INDEX($P$8:$P$24,MATCH(39,$P$8:$P$24,1)))/(INDEX($P$8:$P$24,MATCH(39,$P$8:$P$24,1)+1)-INDEX($P$8:$P$24,MATCH(39,$P$8:$P$24,1))) | F61: =(B61-$B$60)/360 | G61: =SUM($I$8:I60) | H61: =H52*(H62/H52)^((C61-C52)/(C62-C52)) | I61: =F61*H61 | J61: =-LN(H61)/C61*100 | K61: =(H60/H61-1)/((B61-B60)/360)*100 | M61: =IF(L61="","",(J61-L61)*100) | N61: interp | S61: =(G61+F61*H61) | T61: =IFERROR(INDEX(S490_Snapshot!$D$7:$D$38,MATCH(B61,S490_Snapshot!$A$7:$A$38,0)),"") | U61: =IFERROR(INDEX(S490_Snapshot!$E$7:$E$38,MATCH(B61,S490_Snapshot!$A$7:$A$38,0)),"") | V61: =IF(T61="","",(J61-T61)*100) | W61: =IF(U61="","",H61-U61) | X61: =IFERROR(INDEX(S490_Snapshot!$C$7:$C$38,MATCH(B61,S490_Snapshot!$A$7:$A$38,0)),"") | Y61: =IF(OR(X61="",NOT(ISNUMBER(E61))),"",(E61-X61)*100)
A62: 40Y | B62: =IF(MONTH(((EDATE($B$4,480))+IF(WEEKDAY((EDATE($B$4,480)),2)=6,2,IF(WEEKDAY((EDATE($B$4,480)),2)=7,1,0))))<>MONTH((EDATE($B$4,480))),((EDATE($B$4,480))-IF(WEEKDAY((EDATE($B$4,480)),2)=6,1,IF(WEEKDAY((EDATE($B$4,480)),2)=7,2,0))),((EDATE($B$4,480))+IF(WEEKDAY((EDATE($B$4,480)),2)=6,2,IF(WEEKDAY((EDATE($B$4,480)),2)=7,1,0)))) | C62: =(B62-VAL_DATE)/365 | D62: =(B62-$B$4)/360 | E62: ='SOFR_OIS_Quotes'!$H35 | F62: =(B62-$B$61)/360 | G62: =SUM($I$8:I61) | H62: =Curve_Solver!$B$303 | I62: =F62*H62 | J62: =-LN(H62)/C62*100 | K62: =(H61/H62-1)/((B62-B61)/360)*100 | M62: =IF(L62="","",(J62-L62)*100) | N62: market | R62: =($D$4-(E62/100)*G62)/(1+(E62/100)*F62)-H62 | S62: =(G62+F62*H62) | T62: =IFERROR(INDEX(S490_Snapshot!$D$7:$D$38,MATCH(B62,S490_Snapshot!$A$7:$A$38,0)),"") | U62: =IFERROR(INDEX(S490_Snapshot!$E$7:$E$38,MATCH(B62,S490_Snapshot!$A$7:$A$38,0)),"") | V62: =IF(T62="","",(J62-T62)*100) | W62: =IF(U62="","",H62-U62) | X62: =IFERROR(INDEX(S490_Snapshot!$C$7:$C$38,MATCH(B62,S490_Snapshot!$A$7:$A$38,0)),"") | Y62: =IF(OR(X62="",NOT(ISNUMBER(E62))),"",(E62-X62)*100)
A63: 41Y | B63: =IF(MONTH(((EDATE($B$4,492))+IF(WEEKDAY((EDATE($B$4,492)),2)=6,2,IF(WEEKDAY((EDATE($B$4,492)),2)=7,1,0))))<>MONTH((EDATE($B$4,492))),((EDATE($B$4,492))-IF(WEEKDAY((EDATE($B$4,492)),2)=6,1,IF(WEEKDAY((EDATE($B$4,492)),2)=7,2,0))),((EDATE($B$4,492))+IF(WEEKDAY((EDATE($B$4,492)),2)=6,2,IF(WEEKDAY((EDATE($B$4,492)),2)=7,1,0)))) | C63: =(B63-VAL_DATE)/365 | D63: =(B63-$B$4)/360 | E63: =INDEX($Q$8:$Q$24,MATCH(41,$P$8:$P$24,1))+(INDEX($Q$8:$Q$24,MATCH(41,$P$8:$P$24,1)+1)-INDEX($Q$8:$Q$24,MATCH(41,$P$8:$P$24,1)))*(41-INDEX($P$8:$P$24,MATCH(41,$P$8:$P$24,1)))/(INDEX($P$8:$P$24,MATCH(41,$P$8:$P$24,1)+1)-INDEX($P$8:$P$24,MATCH(41,$P$8:$P$24,1))) | F63: =(B63-$B$62)/360 | G63: =SUM($I$8:I62) | H63: =H62*(H72/H62)^((C63-C62)/(C72-C62)) | I63: =F63*H63 | J63: =-LN(H63)/C63*100 | K63: =(H62/H63-1)/((B63-B62)/360)*100 | M63: =IF(L63="","",(J63-L63)*100) | N63: interp | S63: =(G63+F63*H63) | T63: =IFERROR(INDEX(S490_Snapshot!$D$7:$D$38,MATCH(B63,S490_Snapshot!$A$7:$A$38,0)),"") | U63: =IFERROR(INDEX(S490_Snapshot!$E$7:$E$38,MATCH(B63,S490_Snapshot!$A$7:$A$38,0)),"") | V63: =IF(T63="","",(J63-T63)*100) | W63: =IF(U63="","",H63-U63) | X63: =IFERROR(INDEX(S490_Snapshot!$C$7:$C$38,MATCH(B63,S490_Snapshot!$A$7:$A$38,0)),"") | Y63: =IF(OR(X63="",NOT(ISNUMBER(E63))),"",(E63-X63)*100)
A64: 42Y | B64: =IF(MONTH(((EDATE($B$4,504))+IF(WEEKDAY((EDATE($B$4,504)),2)=6,2,IF(WEEKDAY((EDATE($B$4,504)),2)=7,1,0))))<>MONTH((EDATE($B$4,504))),((EDATE($B$4,504))-IF(WEEKDAY((EDATE($B$4,504)),2)=6,1,IF(WEEKDAY((EDATE($B$4,504)),2)=7,2,0))),((EDATE($B$4,504))+IF(WEEKDAY((EDATE($B$4,504)),2)=6,2,IF(WEEKDAY((EDATE($B$4,504)),2)=7,1,0)))) | C64: =(B64-VAL_DATE)/365 | D64: =(B64-$B$4)/360 | E64: =INDEX($Q$8:$Q$24,MATCH(42,$P$8:$P$24,1))+(INDEX($Q$8:$Q$24,MATCH(42,$P$8:$P$24,1)+1)-INDEX($Q$8:$Q$24,MATCH(42,$P$8:$P$24,1)))*(42-INDEX($P$8:$P$24,MATCH(42,$P$8:$P$24,1)))/(INDEX($P$8:$P$24,MATCH(42,$P$8:$P$24,1)+1)-INDEX($P$8:$P$24,MATCH(42,$P$8:$P$24,1))) | F64: =(B64-$B$63)/360 | G64: =SUM($I$8:I63) | H64: =H62*(H72/H62)^((C64-C62)/(C72-C62)) | I64: =F64*H64 | J64: =-LN(H64)/C64*100 | K64: =(H63/H64-1)/((B64-B63)/360)*100 | M64: =IF(L64="","",(J64-L64)*100) | N64: interp | S64: =(G64+F64*H64) | T64: =IFERROR(INDEX(S490_Snapshot!$D$7:$D$38,MATCH(B64,S490_Snapshot!$A$7:$A$38,0)),"") | U64: =IFERROR(INDEX(S490_Snapshot!$E$7:$E$38,MATCH(B64,S490_Snapshot!$A$7:$A$38,0)),"") | V64: =IF(T64="","",(J64-T64)*100) | W64: =IF(U64="","",H64-U64) | X64: =IFERROR(INDEX(S490_Snapshot!$C$7:$C$38,MATCH(B64,S490_Snapshot!$A$7:$A$38,0)),"") | Y64: =IF(OR(X64="",NOT(ISNUMBER(E64))),"",(E64-X64)*100)
A65: 43Y | B65: =IF(MONTH(((EDATE($B$4,516))+IF(WEEKDAY((EDATE($B$4,516)),2)=6,2,IF(WEEKDAY((EDATE($B$4,516)),2)=7,1,0))))<>MONTH((EDATE($B$4,516))),((EDATE($B$4,516))-IF(WEEKDAY((EDATE($B$4,516)),2)=6,1,IF(WEEKDAY((EDATE($B$4,516)),2)=7,2,0))),((EDATE($B$4,516))+IF(WEEKDAY((EDATE($B$4,516)),2)=6,2,IF(WEEKDAY((EDATE($B$4,516)),2)=7,1,0)))) | C65: =(B65-VAL_DATE)/365 | D65: =(B65-$B$4)/360 | E65: =INDEX($Q$8:$Q$24,MATCH(43,$P$8:$P$24,1))+(INDEX($Q$8:$Q$24,MATCH(43,$P$8:$P$24,1)+1)-INDEX($Q$8:$Q$24,MATCH(43,$P$8:$P$24,1)))*(43-INDEX($P$8:$P$24,MATCH(43,$P$8:$P$24,1)))/(INDEX($P$8:$P$24,MATCH(43,$P$8:$P$24,1)+1)-INDEX($P$8:$P$24,MATCH(43,$P$8:$P$24,1))) | F65: =(B65-$B$64)/360 | G65: =SUM($I$8:I64) | H65: =H62*(H72/H62)^((C65-C62)/(C72-C62)) | I65: =F65*H65 | J65: =-LN(H65)/C65*100 | K65: =(H64/H65-1)/((B65-B64)/360)*100 | M65: =IF(L65="","",(J65-L65)*100) | N65: interp | S65: =(G65+F65*H65) | T65: =IFERROR(INDEX(S490_Snapshot!$D$7:$D$38,MATCH(B65,S490_Snapshot!$A$7:$A$38,0)),"") | U65: =IFERROR(INDEX(S490_Snapshot!$E$7:$E$38,MATCH(B65,S490_Snapshot!$A$7:$A$38,0)),"") | V65: =IF(T65="","",(J65-T65)*100) | W65: =IF(U65="","",H65-U65) | X65: =IFERROR(INDEX(S490_Snapshot!$C$7:$C$38,MATCH(B65,S490_Snapshot!$A$7:$A$38,0)),"") | Y65: =IF(OR(X65="",NOT(ISNUMBER(E65))),"",(E65-X65)*100)
